{
  "type": "Feature",
  "properties": {
    "gn:admin1_code":"36.0",
    "gn:asciiname":"Pahala Lunugama",
    "gn:country_code":"LK",
    "gn:dem":52,
    "gn:feature_class":"P",
    "gn:feature_code":"PPL",
    "gn:name":"Pahala Lunugama",
    "gn:population":0,
    "gn:timezone":"Asia/Colombo",
    "iso:country":"LK",
    "name:und_x_variant":[
        "Lunugama"
    ],
    "wof:name":"Pahala Lunugama",
    "wof:placetype":"locality"
},
  "geometry": {"coordinates":[80.0933,6.9714],"type":"Point"}
}