{
  "type": "Feature",
  "properties": {
    "gn:admin1_code":"33.0",
    "gn:asciiname":"Gonnana",
    "gn:country_code":"LK",
    "gn:dem":221,
    "gn:feature_class":"P",
    "gn:feature_code":"PPL",
    "gn:name":"Gonnana",
    "gn:population":0,
    "gn:timezone":"Asia/Colombo",
    "iso:country":"LK",
    "wof:name":"Gonnana",
    "wof:placetype":"locality"
},
  "geometry": {"coordinates":[80.39530000000001,7.0174],"type":"Point"}
}