{
  "type": "Feature",
  "properties": {
    "gn:admin1_code":"30.0",
    "gn:asciiname":"Negampaha",
    "gn:country_code":"LK",
    "gn:dem":136,
    "gn:feature_class":"P",
    "gn:feature_code":"PPL",
    "gn:name":"Negampaha",
    "gn:population":0,
    "gn:timezone":"Asia/Colombo",
    "iso:country":"LK",
    "wof:name":"Negampaha",
    "wof:placetype":"locality"
},
  "geometry": {"coordinates":[80.45950000000001,7.998],"type":"Point"}
}