{
  "type": "Feature",
  "properties": {
    "gn:admin1_code":"32.0",
    "gn:asciiname":"Puswella",
    "gn:country_code":"LK",
    "gn:dem":162,
    "gn:feature_class":"P",
    "gn:feature_code":"PPL",
    "gn:name":"Puswella",
    "gn:population":0,
    "gn:timezone":"Asia/Colombo",
    "iso:country":"LK",
    "wof:name":"Puswella",
    "wof:placetype":"locality"
},
  "geometry": {"coordinates":[80.479,7.4408],"type":"Point"}
}