{
  "type": "Feature",
  "properties": {
    "gn:admin1_code":"30.0",
    "gn:asciiname":"Maha Puliyankulama",
    "gn:country_code":"LK",
    "gn:dem":90,
    "gn:feature_class":"P",
    "gn:feature_code":"PPL",
    "gn:name":"Maha Puliyankulama",
    "gn:population":0,
    "gn:timezone":"Asia/Colombo",
    "iso:country":"LK",
    "wof:name":"Maha Puliyankulama",
    "wof:placetype":"locality"
},
  "geometry": {"coordinates":[80.45820000000001,8.6501],"type":"Point"}
}