{
  "type": "Feature",
  "properties": {
    "gn:admin1_code":"32.0",
    "gn:asciiname":"Getilawa",
    "gn:cc2":"LK",
    "gn:country_code":"LK",
    "gn:dem":65,
    "gn:feature_class":"P",
    "gn:feature_code":"PPL",
    "gn:name":"Getilawa",
    "gn:population":0,
    "gn:timezone":"Asia/Colombo",
    "iso:country":"LK",
    "name:und_x_variant":[
        "Getilewa",
        "Getilawa"
    ],
    "wof:name":"Getilawa",
    "wof:placetype":"locality"
},
  "geometry": {"coordinates":[80.25,7.75],"type":"Point"}
}