{
  "type": "Feature",
  "properties": {
    "gn:admin1_code":"33.0",
    "gn:asciiname":"Welange",
    "gn:country_code":"LK",
    "gn:dem":665,
    "gn:feature_class":"P",
    "gn:feature_code":"PPL",
    "gn:name":"Welange",
    "gn:population":0,
    "gn:timezone":"Asia/Colombo",
    "iso:country":"LK",
    "wof:name":"Welange",
    "wof:placetype":"locality"
},
  "geometry": {"coordinates":[80.6949,6.6222],"type":"Point"}
}