{
  "type": "Feature",
  "properties": {
    "gn:admin1_code":"32.0",
    "gn:asciiname":"Werapola",
    "gn:country_code":"LK",
    "gn:dem":79,
    "gn:feature_class":"P",
    "gn:feature_code":"PPL",
    "gn:name":"Werapola",
    "gn:population":0,
    "gn:timezone":"Asia/Colombo",
    "iso:country":"LK",
    "wof:name":"Werapola",
    "wof:placetype":"locality"
},
  "geometry": {"coordinates":[80.2505,7.5938],"type":"Point"}
}