{
  "type": "Feature",
  "properties": {
    "gn:admin1_code":"32.0",
    "gn:asciiname":"Ginidammana",
    "gn:country_code":"LK",
    "gn:dem":35,
    "gn:feature_class":"P",
    "gn:feature_code":"PPL",
    "gn:name":"Ginidammana",
    "gn:population":0,
    "gn:timezone":"Asia/Colombo",
    "iso:country":"LK",
    "wof:name":"Ginidammana",
    "wof:placetype":"locality"
},
  "geometry": {"coordinates":[79.91759999999999,7.5894],"type":"Point"}
}