{
  "type": "Feature",
  "properties": {
    "gn:admin1_code":"29.0",
    "gn:asciiname":"Rannantalawa",
    "gn:country_code":"LK",
    "gn:dem":783,
    "gn:feature_class":"P",
    "gn:feature_code":"PPL",
    "gn:name":"Rannantalawa",
    "gn:population":0,
    "gn:timezone":"Asia/Colombo",
    "iso:country":"LK",
    "name:und_x_variant":[
        "Ranwantalawa",
        "Ranatalawa",
        "Rannantalawa"
    ],
    "wof:name":"Rannantalawa",
    "wof:placetype":"locality"
},
  "geometry": {"coordinates":[80.6016,7.0639],"type":"Point"}
}