{
  "type": "Feature",
  "properties": {
    "gn:admin1_code":"29.0",
    "gn:asciiname":"Kollanwelapitiya",
    "gn:country_code":"LK",
    "gn:dem":563,
    "gn:feature_class":"P",
    "gn:feature_code":"PPL",
    "gn:name":"Kollanwelapitiya",
    "gn:population":0,
    "gn:timezone":"Asia/Colombo",
    "iso:country":"LK",
    "wof:name":"Kollanwelapitiya",
    "wof:placetype":"locality"
},
  "geometry": {"coordinates":[80.6998,7.2425],"type":"Point"}
}