{
  "type": "Feature",
  "properties": {
    "gn:admin1_code":"34.0",
    "gn:asciiname":"Paniyanduwa",
    "gn:country_code":"LK",
    "gn:dem":-9999,
    "gn:feature_class":"P",
    "gn:feature_code":"PPL",
    "gn:name":"Paniyanduwa",
    "gn:population":0,
    "gn:timezone":"Asia/Colombo",
    "iso:country":"LK",
    "wof:name":"Paniyanduwa",
    "wof:placetype":"locality"
},
  "geometry": {"coordinates":[80.05,6.23333],"type":"Point"}
}