{
  "type": "Feature",
  "properties": {
    "gn:admin1_code":"34.0",
    "gn:asciiname":"Vavilihengoda",
    "gn:country_code":"LK",
    "gn:dem":14,
    "gn:feature_class":"P",
    "gn:feature_code":"PPL",
    "gn:name":"Vavilihengoda",
    "gn:population":0,
    "gn:timezone":"Asia/Colombo",
    "iso:country":"LK",
    "name:und_x_variant":[
        "Wewilihengoda"
    ],
    "wof:name":"Vavilihengoda",
    "wof:placetype":"locality"
},
  "geometry": {"coordinates":[80.35550000000001,5.9913],"type":"Point"}
}