{
  "type": "Feature",
  "properties": {
    "gn:admin1_code":"29.0",
    "gn:asciiname":"Suwandelpotha",
    "gn:country_code":"LK",
    "gn:dem":1205,
    "gn:feature_class":"P",
    "gn:feature_code":"PPL",
    "gn:name":"Suwandelpotha",
    "gn:population":0,
    "gn:timezone":"Asia/Colombo",
    "iso:country":"LK",
    "wof:name":"Suwandelpotha",
    "wof:placetype":"locality"
},
  "geometry": {"coordinates":[80.7805,7.0527],"type":"Point"}
}