{
  "type": "Feature",
  "properties": {
    "gn:admin1_code":"33.0",
    "gn:asciiname":"Ritidolawatta",
    "gn:country_code":"LK",
    "gn:dem":236,
    "gn:feature_class":"P",
    "gn:feature_code":"PPL",
    "gn:name":"Ritidolawatta",
    "gn:population":0,
    "gn:timezone":"Asia/Colombo",
    "iso:country":"LK",
    "wof:name":"Ritidolawatta",
    "wof:placetype":"locality"
},
  "geometry": {"coordinates":[80.53319999999999,6.6138],"type":"Point"}
}