{
  "type": "Feature",
  "properties": {
    "gn:admin1_code":"29.0",
    "gn:asciiname":"Balawatgoda",
    "gn:country_code":"LK",
    "gn:dem":555,
    "gn:feature_class":"P",
    "gn:feature_code":"PPL",
    "gn:name":"Balawatgoda",
    "gn:population":0,
    "gn:timezone":"Asia/Colombo",
    "iso:country":"LK",
    "wof:name":"Balawatgoda",
    "wof:placetype":"locality"
},
  "geometry": {"coordinates":[80.57550000000001,7.3393],"type":"Point"}
}