{
  "type": "Feature",
  "properties": {
    "gn:admin1_code":"32.0",
    "gn:asciiname":"Chenaikudiruppu",
    "gn:country_code":"LK",
    "gn:dem":24,
    "gn:feature_class":"P",
    "gn:feature_code":"PPL",
    "gn:name":"Chenaikudiruppu",
    "gn:population":0,
    "gn:timezone":"Asia/Colombo",
    "iso:country":"LK",
    "name:und_x_variant":[
        "Chenakudirippu",
        "Chenakudiruppu"
    ],
    "wof:name":"Chenaikudiruppu",
    "wof:placetype":"locality"
},
  "geometry": {"coordinates":[79.85469999999999,8.0237],"type":"Point"}
}