{
  "type": "Feature",
  "properties": {
    "gn:admin1_code":"37.0",
    "gn:asciiname":"Foul Point",
    "gn:country_code":"LK",
    "gn:dem":9,
    "gn:feature_class":"P",
    "gn:feature_code":"PPL",
    "gn:name":"Foul Point",
    "gn:population":0,
    "gn:timezone":"Asia/Colombo",
    "iso:country":"LK",
    "name:ceb_x_preferred":[
        "Peligrosa"
    ],
    "name:deu_x_preferred":[
        "Foul Point"
    ],
    "name:nno_x_preferred":[
        "Foul Point"
    ],
    "name:swe_x_preferred":[
        "Peligrosa"
    ],
    "name:und_x_variant":[
        "Kevuliya"
    ],
    "name:zho_x_preferred":[
        "\u798f\u723e\u89d2"
    ],
    "wof:name":"Foul Point",
    "wof:placetype":"locality"
},
  "geometry": {"coordinates":[81.31667,8.51667],"type":"Point"}
}