{
  "type": "Feature",
  "properties": {
    "gn:admin1_code":"29.0",
    "gn:asciiname":"Udakumbura",
    "gn:country_code":"LK",
    "gn:dem":736,
    "gn:feature_class":"P",
    "gn:feature_code":"PPL",
    "gn:name":"Udakumbura",
    "gn:population":0,
    "gn:timezone":"Asia/Colombo",
    "iso:country":"LK",
    "wof:name":"Udakumbura",
    "wof:placetype":"locality"
},
  "geometry": {"coordinates":[80.7076,7.3624],"type":"Point"}
}