{
  "type": "Feature",
  "properties": {
    "gn:admin1_code":"29.0",
    "gn:asciiname":"Udakumbura",
    "gn:country_code":"LK",
    "gn:dem":736,
    "gn:feature_class":"P",
    "gn:feature_code":"PPL",
    "gn:name":"Udakumbura",
    "gn:population":0,
    "gn:timezone":"Asia/Colombo",
    "iso:country":"LK",
    "name:fas_x_preferred":[
        "\u06cc\u0648\u062f\u0627\u06a9\u0648\u0645\u0628\u0648\u0631\u0627"
    ],
    "name:urd_x_preferred":[
        "\u0627\u062f\u06a9\u0645\u0628\u0631\u0627"
    ],
    "wof:name":"Udakumbura",
    "wof:placetype":"locality"
},
  "geometry": {"coordinates":[80.7076,7.3624],"type":"Point"}
}