{
  "type": "Feature",
  "properties": {
    "gn:admin1_code":"29.0",
    "gn:asciiname":"Giraambegammedda",
    "gn:country_code":"LK",
    "gn:dem":540,
    "gn:feature_class":"P",
    "gn:feature_code":"PPL",
    "gn:name":"Giraambegammedda",
    "gn:population":0,
    "gn:timezone":"Asia/Colombo",
    "iso:country":"LK",
    "wof:name":"Giraambegammedda",
    "wof:placetype":"locality"
},
  "geometry": {"coordinates":[80.6854,7.3338],"type":"Point"}
}