{
  "type": "Feature",
  "properties": {
    "gn:admin1_code":"30.0",
    "gn:asciiname":"Hirigollegama",
    "gn:country_code":"LK",
    "gn:dem":97,
    "gn:feature_class":"P",
    "gn:feature_code":"PPL",
    "gn:name":"Hirigollegama",
    "gn:population":0,
    "gn:timezone":"Asia/Colombo",
    "iso:country":"LK",
    "wof:name":"Hirigollegama",
    "wof:placetype":"locality"
},
  "geometry": {"coordinates":[80.29300000000001,8.2229],"type":"Point"}
}