{
  "type": "Feature",
  "properties": {
    "gn:admin1_code":"32.0",
    "gn:asciiname":"Galagama",
    "gn:country_code":"LK",
    "gn:dem":215,
    "gn:feature_class":"P",
    "gn:feature_code":"PPL",
    "gn:name":"Galagama",
    "gn:population":0,
    "gn:timezone":"Asia/Colombo",
    "iso:country":"LK",
    "name:ceb_x_preferred":[
        "Galagama"
    ],
    "name:swe_x_preferred":[
        "Galagama"
    ],
    "name:und_x_variant":[
        "Galagama Niyangama"
    ],
    "wof:name":"Galagama",
    "wof:placetype":"locality"
},
  "geometry": {"coordinates":[80.5416,7.4289],"type":"Point"}
}