{
  "type": "Feature",
  "properties": {
    "gn:admin1_code":"29.0",
    "gn:asciiname":"Halpola",
    "gn:country_code":"LK",
    "gn:dem":798,
    "gn:feature_class":"P",
    "gn:feature_code":"PPL",
    "gn:name":"Halpola",
    "gn:population":0,
    "gn:timezone":"Asia/Colombo",
    "iso:country":"LK",
    "wof:name":"Halpola",
    "wof:placetype":"locality"
},
  "geometry": {"coordinates":[80.63849999999999,7.0183],"type":"Point"}
}