{
  "type": "Feature",
  "properties": {
    "gn:admin1_code":"33.0",
    "gn:asciiname":"Wahakula",
    "gn:country_code":"LK",
    "gn:dem":213,
    "gn:feature_class":"P",
    "gn:feature_code":"PPL",
    "gn:name":"Wahakula",
    "gn:population":0,
    "gn:timezone":"Asia/Colombo",
    "iso:country":"LK",
    "wof:name":"Wahakula",
    "wof:placetype":"locality"
},
  "geometry": {"coordinates":[80.2084,7.0593],"type":"Point"}
}