{
  "type": "Feature",
  "properties": {
    "gn:admin1_code":"33.0",
    "gn:asciiname":"Jasinkanda",
    "gn:country_code":"LK",
    "gn:dem":551,
    "gn:feature_class":"P",
    "gn:feature_code":"PPL",
    "gn:name":"Jasinkanda",
    "gn:population":0,
    "gn:timezone":"Asia/Colombo",
    "iso:country":"LK",
    "wof:name":"Jasinkanda",
    "wof:placetype":"locality"
},
  "geometry": {"coordinates":[80.6754,6.6587],"type":"Point"}
}