{
  "type": "Feature",
  "properties": {
    "gn:admin1_code":"29.0",
    "gn:asciiname":"Kattota",
    "gn:country_code":"LK",
    "gn:dem":523,
    "gn:feature_class":"P",
    "gn:feature_code":"PPL",
    "gn:name":"Kattota",
    "gn:population":0,
    "gn:timezone":"Asia/Colombo",
    "iso:country":"LK",
    "wof:name":"Kattota",
    "wof:placetype":"locality"
},
  "geometry": {"coordinates":[80.5314,7.2774],"type":"Point"}
}