{
  "type": "Feature",
  "properties": {
    "gn:admin1_code":"33.0",
    "gn:asciiname":"Panapitiya",
    "gn:country_code":"LK",
    "gn:dem":309,
    "gn:feature_class":"P",
    "gn:feature_code":"PPL",
    "gn:name":"Panapitiya",
    "gn:population":0,
    "gn:timezone":"Asia/Colombo",
    "iso:country":"LK",
    "wof:name":"Panapitiya",
    "wof:placetype":"locality"
},
  "geometry": {"coordinates":[80.5581,6.526],"type":"Point"}
}