{
  "type": "Feature",
  "properties": {
    "gn:admin1_code":"29.0",
    "gn:asciiname":"Rajawellawatta",
    "gn:country_code":"LK",
    "gn:dem":555,
    "gn:feature_class":"P",
    "gn:feature_code":"PPL",
    "gn:name":"Rajawellawatta",
    "gn:population":0,
    "gn:timezone":"Asia/Colombo",
    "iso:country":"LK",
    "wof:name":"Rajawellawatta",
    "wof:placetype":"locality"
},
  "geometry": {"coordinates":[80.7354,7.2821],"type":"Point"}
}