{
  "type": "Feature",
  "properties": {
    "gn:admin1_code":"30.0",
    "gn:asciiname":"Waragodayagama",
    "gn:country_code":"LK",
    "gn:dem":122,
    "gn:feature_class":"P",
    "gn:feature_code":"PPL",
    "gn:name":"Waragodayagama",
    "gn:population":0,
    "gn:timezone":"Asia/Colombo",
    "iso:country":"LK",
    "name:und_x_variant":[
        "Waragodavagama",
        "Waragodayagama"
    ],
    "wof:name":"Waragodayagama",
    "wof:placetype":"locality"
},
  "geometry": {"coordinates":[80.3563,8.2214],"type":"Point"}
}