{
  "type": "Feature",
  "properties": {
    "gn:admin1_code":"37.0",
    "gn:asciiname":"Sinnakinniya",
    "gn:country_code":"LK",
    "gn:dem":10,
    "gn:feature_class":"P",
    "gn:feature_code":"PPL",
    "gn:name":"Sinnakinniya",
    "gn:population":0,
    "gn:timezone":"Asia/Colombo",
    "iso:country":"LK",
    "name:und_x_variant":[
        "Kinniyai",
        "Sinnakinniya",
        "Chinnakinniyai",
        "Chinna Kiniyai",
        "Sinnakinniyai"
    ],
    "wof:name":"Sinnakinniya",
    "wof:placetype":"locality"
},
  "geometry": {"coordinates":[81.1853,8.4909],"type":"Point"}
}