{
  "type": "Feature",
  "properties": {
    "gn:admin1_code":"34.0",
    "gn:asciiname":"Pitadeniya",
    "gn:country_code":"LK",
    "gn:dem":272,
    "gn:feature_class":"P",
    "gn:feature_code":"PPL",
    "gn:name":"Pitadeniya",
    "gn:population":0,
    "gn:timezone":"Asia/Colombo",
    "iso:country":"LK",
    "wof:name":"Pitadeniya",
    "wof:placetype":"locality"
},
  "geometry": {"coordinates":[80.4658,6.3653],"type":"Point"}
}