{
  "type": "Feature",
  "properties": {
    "gn:admin1_code":"33.0",
    "gn:asciiname":"Neluwankanda",
    "gn:country_code":"LK",
    "gn:dem":474,
    "gn:feature_class":"P",
    "gn:feature_code":"PPL",
    "gn:name":"Neluwankanda",
    "gn:population":0,
    "gn:timezone":"Asia/Colombo",
    "iso:country":"LK",
    "wof:name":"Neluwankanda",
    "wof:placetype":"locality"
},
  "geometry": {"coordinates":[80.4425,6.5421],"type":"Point"}
}