{
  "type": "Feature",
  "properties": {
    "gn:admin1_code":"36.0",
    "gn:asciiname":"Madakadakanda Deeganwela",
    "gn:country_code":"LK",
    "gn:dem":22,
    "gn:feature_class":"P",
    "gn:feature_code":"PPL",
    "gn:name":"Madakadakanda Deeganwela",
    "gn:population":0,
    "gn:timezone":"Asia/Colombo",
    "iso:country":"LK",
    "wof:name":"Madakadakanda Deeganwela",
    "wof:placetype":"locality"
},
  "geometry": {"coordinates":[80.0789,6.7275],"type":"Point"}
}