{
  "type": "Feature",
  "properties": {
    "gn:admin1_code":"29.0",
    "gn:asciiname":"Paragahamada",
    "gn:country_code":"LK",
    "gn:dem":413,
    "gn:feature_class":"P",
    "gn:feature_code":"PPL",
    "gn:name":"Paragahamada",
    "gn:population":0,
    "gn:timezone":"Asia/Colombo",
    "iso:country":"LK",
    "wof:name":"Paragahamada",
    "wof:placetype":"locality"
},
  "geometry": {"coordinates":[80.6755,7.5289],"type":"Point"}
}