{
  "type": "Feature",
  "properties": {
    "gn:admin1_code":"37.0",
    "gn:asciiname":"Manthottama",
    "gn:country_code":"LK",
    "gn:dem":47,
    "gn:feature_class":"P",
    "gn:feature_code":"PPL",
    "gn:name":"Manthottama",
    "gn:population":0,
    "gn:timezone":"Asia/Colombo",
    "iso:country":"LK",
    "wof:name":"Manthottama",
    "wof:placetype":"locality"
},
  "geometry": {"coordinates":[81.70610000000001,7.1423],"type":"Point"}
}