{
  "type": "Feature",
  "properties": {
    "gn:admin1_code":"30.0",
    "gn:asciiname":"Talattewa",
    "gn:country_code":"LK",
    "gn:dem":103,
    "gn:feature_class":"P",
    "gn:feature_code":"PPL",
    "gn:name":"Talattewa",
    "gn:population":0,
    "gn:timezone":"Asia/Colombo",
    "iso:country":"LK",
    "wof:name":"Talattewa",
    "wof:placetype":"locality"
},
  "geometry": {"coordinates":[80.7393,8.4206],"type":"Point"}
}