{
  "type": "Feature",
  "properties": {
    "gn:admin1_code":"34.0",
    "gn:asciiname":"Dimbulgoda",
    "gn:country_code":"LK",
    "gn:dem":35,
    "gn:feature_class":"P",
    "gn:feature_code":"PPL",
    "gn:name":"Dimbulgoda",
    "gn:population":0,
    "gn:timezone":"Asia/Colombo",
    "iso:country":"LK",
    "name:ceb_x_preferred":[
        "Dimbulgoda"
    ],
    "name:swe_x_preferred":[
        "Dimbulgoda"
    ],
    "wof:name":"Dimbulgoda",
    "wof:placetype":"locality"
},
  "geometry": {"coordinates":[80.7983,6.1685],"type":"Point"}
}