{
  "type": "Feature",
  "properties": {
    "gn:admin1_code":"35.0",
    "gn:asciiname":"Bodagama",
    "gn:country_code":"LK",
    "gn:dem":97,
    "gn:feature_class":"P",
    "gn:feature_code":"PPL",
    "gn:name":"Bodagama",
    "gn:population":0,
    "gn:timezone":"Asia/Colombo",
    "iso:country":"LK",
    "wof:name":"Bodagama",
    "wof:placetype":"locality"
},
  "geometry": {"coordinates":[81.1033,6.4274],"type":"Point"}
}