{
  "type": "Feature",
  "properties": {
    "gn:admin1_code":"36.0",
    "gn:asciiname":"Pingomuwa",
    "gn:country_code":"LK",
    "gn:dem":40,
    "gn:feature_class":"P",
    "gn:feature_code":"PPL",
    "gn:name":"Pingomuwa",
    "gn:population":0,
    "gn:timezone":"Asia/Colombo",
    "iso:country":"LK",
    "wof:name":"Pingomuwa",
    "wof:placetype":"locality"
},
  "geometry": {"coordinates":[80.15430000000001,7.0518],"type":"Point"}
}