{
  "type": "Feature",
  "properties": {
    "gn:admin1_code":"29.0",
    "gn:asciiname":"Akuramboda",
    "gn:country_code":"LK",
    "gn:dem":388,
    "gn:feature_class":"P",
    "gn:feature_code":"PPL",
    "gn:name":"Akuramboda",
    "gn:population":0,
    "gn:timezone":"Asia/Colombo",
    "iso:country":"LK",
    "name:ceb_x_preferred":[
        "Akuramboda"
    ],
    "name:fas_x_preferred":[
        "\u0627\u06a9\u0648\u0631\u0627\u0645\u0628\u0648\u062f\u0627"
    ],
    "name:swe_x_preferred":[
        "Akuramboda"
    ],
    "wof:name":"Akuramboda",
    "wof:placetype":"locality"
},
  "geometry": {"coordinates":[80.6014,7.6467],"type":"Point"}
}