{
  "type": "Feature",
  "properties": {
    "gn:admin1_code":"29.0",
    "gn:asciiname":"Akuramboda",
    "gn:country_code":"LK",
    "gn:dem":388,
    "gn:feature_class":"P",
    "gn:feature_code":"PPL",
    "gn:name":"Akuramboda",
    "gn:population":0,
    "gn:timezone":"Asia/Colombo",
    "iso:country":"LK",
    "wof:name":"Akuramboda",
    "wof:placetype":"locality"
},
  "geometry": {"coordinates":[80.6014,7.6467],"type":"Point"}
}