{
  "type": "Feature",
  "properties": {
    "gn:asciiname":"Kadawatha",
    "gn:country_code":"LK",
    "gn:dem":27,
    "gn:feature_class":"P",
    "gn:feature_code":"PPL",
    "gn:name":"Kadawatha",
    "gn:population":0,
    "gn:timezone":"Asia/Colombo",
    "iso:country":"LK",
    "name:ceb_x_preferred":[
        "Kadawatha"
    ],
    "name:fra_x_preferred":[
        "Kadawatha"
    ],
    "name:nld_x_preferred":[
        "Kadawatha"
    ],
    "name:sin_x_preferred":[
        "\u0d9a\u0da9\u0dc0\u0dad"
    ],
    "name:swe_x_preferred":[
        "Kadawatha"
    ],
    "wof:name":"Kadawatha",
    "wof:placetype":"locality"
},
  "geometry": {"coordinates":[79.95012,7.0009],"type":"Point"}
}