{
  "type": "Feature",
  "properties": {
    "gn:admin1_code":"32.0",
    "gn:asciiname":"Taranagolla",
    "gn:country_code":"LK",
    "gn:dem":84,
    "gn:feature_class":"P",
    "gn:feature_code":"PPL",
    "gn:name":"Taranagolla",
    "gn:population":0,
    "gn:timezone":"Asia/Colombo",
    "iso:country":"LK",
    "wof:name":"Taranagolla",
    "wof:placetype":"locality"
},
  "geometry": {"coordinates":[80.298,7.6287],"type":"Point"}
}