{
  "type": "Feature",
  "properties": {
    "gn:admin1_code":"35.0",
    "gn:asciiname":"Bandara Wadiya",
    "gn:country_code":"LK",
    "gn:dem":175,
    "gn:feature_class":"P",
    "gn:feature_code":"PPL",
    "gn:name":"Bandara Wadiya",
    "gn:population":0,
    "gn:timezone":"Asia/Colombo",
    "iso:country":"LK",
    "wof:name":"Bandara Wadiya",
    "wof:placetype":"locality"
},
  "geometry": {"coordinates":[81.3292,6.8752],"type":"Point"}
}