{
  "type": "Feature",
  "properties": {
    "gn:admin1_code":"33.0",
    "gn:asciiname":"Thalagahawatta",
    "gn:country_code":"LK",
    "gn:dem":291,
    "gn:feature_class":"P",
    "gn:feature_code":"PPL",
    "gn:name":"Thalagahawatta",
    "gn:population":0,
    "gn:timezone":"Asia/Colombo",
    "iso:country":"LK",
    "wof:name":"Thalagahawatta",
    "wof:placetype":"locality"
},
  "geometry": {"coordinates":[80.5981,6.6367],"type":"Point"}
}