{
  "type": "Feature",
  "properties": {
    "gn:admin1_code":"32.0",
    "gn:asciiname":"Aluthherathgama",
    "gn:country_code":"LK",
    "gn:dem":83,
    "gn:feature_class":"P",
    "gn:feature_code":"PPL",
    "gn:name":"Aluthherathgama",
    "gn:population":0,
    "gn:timezone":"Asia/Colombo",
    "iso:country":"LK",
    "wof:name":"Aluthherathgama",
    "wof:placetype":"locality"
},
  "geometry": {"coordinates":[80.2577,7.9911],"type":"Point"}
}