{
  "type": "Feature",
  "properties": {
    "gn:admin1_code":"38.0",
    "gn:asciiname":"Konnayankudiyiruppu",
    "gn:country_code":"LK",
    "gn:dem":-9999,
    "gn:feature_class":"P",
    "gn:feature_code":"PPL",
    "gn:name":"Konnayankudiyiruppu",
    "gn:population":0,
    "gn:timezone":"Asia/Colombo",
    "iso:country":"LK",
    "name:und_x_variant":[
        "Konnayankudiyirppu",
        "Konnayankudiyiruppu"
    ],
    "wof:name":"Konnayankudiyiruppu",
    "wof:placetype":"locality"
},
  "geometry": {"coordinates":[79.83333,9.01667],"type":"Point"}
}