{
  "type": "Feature",
  "properties": {
    "gn:admin1_code":"33.0",
    "gn:asciiname":"Minnana",
    "gn:country_code":"LK",
    "gn:dem":54,
    "gn:feature_class":"P",
    "gn:feature_code":"PPL",
    "gn:name":"Minnana",
    "gn:population":0,
    "gn:timezone":"Asia/Colombo",
    "iso:country":"LK",
    "wof:name":"Minnana",
    "wof:placetype":"locality"
},
  "geometry": {"coordinates":[80.23609999999999,6.8888],"type":"Point"}
}