{
  "type": "Feature",
  "properties": {
    "gn:admin1_code":"33.0",
    "gn:asciiname":"Waharaka",
    "gn:country_code":"LK",
    "gn:dem":74,
    "gn:feature_class":"P",
    "gn:feature_code":"PPL",
    "gn:name":"Waharaka",
    "gn:population":0,
    "gn:timezone":"Asia/Colombo",
    "iso:country":"LK",
    "name:und_x_variant":[
        "Wahareka",
        "Waharaka"
    ],
    "wof:name":"Waharaka",
    "wof:placetype":"locality"
},
  "geometry": {"coordinates":[80.1878,7.096],"type":"Point"}
}