{
  "type": "Feature",
  "properties": {
    "gn:admin1_code":"33.0",
    "gn:asciiname":"Uturala",
    "gn:country_code":"LK",
    "gn:dem":222,
    "gn:feature_class":"P",
    "gn:feature_code":"PPL",
    "gn:name":"Uturala",
    "gn:population":0,
    "gn:timezone":"Asia/Colombo",
    "iso:country":"LK",
    "wof:name":"Uturala",
    "wof:placetype":"locality"
},
  "geometry": {"coordinates":[80.4487,7.2218],"type":"Point"}
}