{
  "type": "Feature",
  "properties": {
    "gn:admin1_code":"32.0",
    "gn:asciiname":"Badalgama",
    "gn:country_code":"LK",
    "gn:dem":113,
    "gn:feature_class":"P",
    "gn:feature_code":"PPL",
    "gn:name":"Badalgama",
    "gn:population":0,
    "gn:timezone":"Asia/Colombo",
    "iso:country":"LK",
    "wof:name":"Badalgama",
    "wof:placetype":"locality"
},
  "geometry": {"coordinates":[80.31480000000001,7.9466],"type":"Point"}
}