{
  "type": "Feature",
  "properties": {
    "gn:admin1_code":"33.0",
    "gn:asciiname":"Panawanna",
    "gn:country_code":"LK",
    "gn:dem":195,
    "gn:feature_class":"P",
    "gn:feature_code":"PPL",
    "gn:name":"Panawanna",
    "gn:population":0,
    "gn:timezone":"Asia/Colombo",
    "iso:country":"LK",
    "name:und_x_variant":[
        "Panawenna"
    ],
    "wof:name":"Panawanna",
    "wof:placetype":"locality"
},
  "geometry": {"coordinates":[80.5692,6.5966],"type":"Point"}
}