{
  "type": "Feature",
  "properties": {
    "gn:admin1_code":"30.0",
    "gn:asciiname":"Perakumpura",
    "gn:country_code":"LK",
    "gn:dem":98,
    "gn:feature_class":"P",
    "gn:feature_code":"PPL",
    "gn:name":"Perakumpura",
    "gn:population":0,
    "gn:timezone":"Asia/Colombo",
    "iso:country":"LK",
    "wof:name":"Perakumpura",
    "wof:placetype":"locality"
},
  "geometry": {"coordinates":[80.2877,8.2969],"type":"Point"}
}