{
  "type": "Feature",
  "properties": {
    "gn:admin1_code":"33.0",
    "gn:asciiname":"Meegastenna",
    "gn:country_code":"LK",
    "gn:dem":212,
    "gn:feature_class":"P",
    "gn:feature_code":"PPL",
    "gn:name":"Meegastenna",
    "gn:population":0,
    "gn:timezone":"Asia/Colombo",
    "iso:country":"LK",
    "name:und_x_variant":[
        "Misgastenna"
    ],
    "wof:name":"Meegastenna",
    "wof:placetype":"locality"
},
  "geometry": {"coordinates":[80.2901,6.993],"type":"Point"}
}