{
  "type": "Feature",
  "properties": {
    "gn:admin1_code":"29.0",
    "gn:asciiname":"Henegama",
    "gn:country_code":"LK",
    "gn:dem":530,
    "gn:feature_class":"P",
    "gn:feature_code":"PPL",
    "gn:name":"Henegama",
    "gn:population":0,
    "gn:timezone":"Asia/Colombo",
    "iso:country":"LK",
    "wof:name":"Henegama",
    "wof:placetype":"locality"
},
  "geometry": {"coordinates":[80.54049999999999,7.3819],"type":"Point"}
}