{
  "type": "Feature",
  "properties": {
    "gn:admin1_code":"29.0",
    "gn:asciiname":"Gallange",
    "gn:country_code":"LK",
    "gn:dem":587,
    "gn:feature_class":"P",
    "gn:feature_code":"PPL",
    "gn:name":"Gallange",
    "gn:population":0,
    "gn:timezone":"Asia/Colombo",
    "iso:country":"LK",
    "wof:name":"Gallange",
    "wof:placetype":"locality"
},
  "geometry": {"coordinates":[80.49460000000001,7.283],"type":"Point"}
}