{
  "type": "Feature",
  "properties": {
    "gn:admin1_code":"33.0",
    "gn:asciiname":"Kuda-Pallegama",
    "gn:country_code":"LK",
    "gn:dem":195,
    "gn:feature_class":"P",
    "gn:feature_code":"PPL",
    "gn:name":"Kuda-Pallegama",
    "gn:population":0,
    "gn:timezone":"Asia/Colombo",
    "iso:country":"LK",
    "name:und_x_variant":[
        "Pallegama Kuda",
        "Kuda-Pallegama"
    ],
    "wof:name":"Kuda-Pallegama",
    "wof:placetype":"locality"
},
  "geometry": {"coordinates":[80.25960000000001,7.1589],"type":"Point"}
}