{
  "type": "Feature",
  "properties": {
    "gn:admin1_code":"32.0",
    "gn:asciiname":"Bamunugama",
    "gn:country_code":"LK",
    "gn:dem":129,
    "gn:feature_class":"P",
    "gn:feature_code":"PPL",
    "gn:name":"Bamunugama",
    "gn:population":0,
    "gn:timezone":"Asia/Colombo",
    "iso:country":"LK",
    "wof:name":"Bamunugama",
    "wof:placetype":"locality"
},
  "geometry": {"coordinates":[80.38333,7.85],"type":"Point"}
}