{
  "type": "Feature",
  "properties": {
    "gn:admin1_code":"32.0",
    "gn:asciiname":"Diyawa",
    "gn:country_code":"LK",
    "gn:dem":144,
    "gn:feature_class":"P",
    "gn:feature_code":"PPL",
    "gn:name":"Diyawa",
    "gn:population":0,
    "gn:timezone":"Asia/Colombo",
    "iso:country":"LK",
    "wof:name":"Diyawa",
    "wof:placetype":"locality"
},
  "geometry": {"coordinates":[80.42829999999999,7.6033],"type":"Point"}
}