{
  "type": "Feature",
  "properties": {
    "gn:admin1_code":"33.0",
    "gn:asciiname":"Gallela",
    "gn:country_code":"LK",
    "gn:dem":249,
    "gn:feature_class":"P",
    "gn:feature_code":"PPL",
    "gn:name":"Gallela",
    "gn:population":0,
    "gn:timezone":"Asia/Colombo",
    "iso:country":"LK",
    "name:und_x_variant":[
        "Gallella",
        "Gallela"
    ],
    "wof:name":"Gallela",
    "wof:placetype":"locality"
},
  "geometry": {"coordinates":[80.3554,6.855],"type":"Point"}
}