{
  "type": "Feature",
  "properties": {
    "gn:admin1_code":"34.0",
    "gn:asciiname":"Kehelwala",
    "gn:country_code":"LK",
    "gn:dem":135,
    "gn:feature_class":"P",
    "gn:feature_code":"PPL",
    "gn:name":"Kehelwala",
    "gn:population":0,
    "gn:timezone":"Asia/Colombo",
    "iso:country":"LK",
    "wof:name":"Kehelwala",
    "wof:placetype":"locality"
},
  "geometry": {"coordinates":[80.5097,6.1642],"type":"Point"}
}