{
  "type": "Feature",
  "properties": {
    "gn:admin1_code":"36.0",
    "gn:asciiname":"Halpe",
    "gn:country_code":"LK",
    "gn:dem":64,
    "gn:feature_class":"P",
    "gn:feature_code":"PPL",
    "gn:name":"Halpe",
    "gn:population":0,
    "gn:timezone":"Asia/Colombo",
    "iso:country":"LK",
    "name:ceb_x_preferred":[
        "Halpe"
    ],
    "name:nor_x_preferred":[
        "Halpe"
    ],
    "name:swe_x_preferred":[
        "Halpe"
    ],
    "name:vie_x_preferred":[
        "Halpe"
    ],
    "name:war_x_preferred":[
        "Halpe"
    ],
    "name:zho_x_preferred":[
        "\u9163\u5f04\u8776\u5c6c"
    ],
    "wof:name":"Halpe",
    "wof:placetype":"locality"
},
  "geometry": {"coordinates":[80.1063,7.2582],"type":"Point"}
}