{
  "type": "Feature",
  "properties": {
    "gn:admin1_code":"34.0",
    "gn:asciiname":"Peddapitiya North",
    "gn:country_code":"LK",
    "gn:dem":69,
    "gn:feature_class":"P",
    "gn:feature_code":"PPL",
    "gn:name":"Peddapitiya North",
    "gn:population":0,
    "gn:timezone":"Asia/Colombo",
    "iso:country":"LK",
    "wof:name":"Peddapitiya North",
    "wof:placetype":"locality"
},
  "geometry": {"coordinates":[80.47499999999999,6.1579],"type":"Point"}
}