{
  "type": "Feature",
  "properties": {
    "gn:admin1_code":"35.0",
    "gn:asciiname":"Kirindegama",
    "gn:country_code":"LK",
    "gn:dem":770,
    "gn:feature_class":"P",
    "gn:feature_code":"PPL",
    "gn:name":"Kirindegama",
    "gn:population":0,
    "gn:timezone":"Asia/Colombo",
    "iso:country":"LK",
    "wof:name":"Kirindegama",
    "wof:placetype":"locality"
},
  "geometry": {"coordinates":[81.0424,7.0345],"type":"Point"}
}