{
  "type": "Feature",
  "properties": {
    "gn:admin1_code":"33.0",
    "gn:asciiname":"Taniantenna",
    "gn:country_code":"LK",
    "gn:dem":410,
    "gn:feature_class":"P",
    "gn:feature_code":"PPL",
    "gn:name":"Taniantenna",
    "gn:population":0,
    "gn:timezone":"Asia/Colombo",
    "iso:country":"LK",
    "name:und_x_variant":[
        "Tanlantenna",
        "Tanjantenna",
        "Taniantenna"
    ],
    "wof:name":"Taniantenna",
    "wof:placetype":"locality"
},
  "geometry": {"coordinates":[80.8548,6.6328],"type":"Point"}
}