{
  "type": "Feature",
  "properties": {
    "gn:admin1_code":"33.0",
    "gn:asciiname":"Hangawela",
    "gn:country_code":"LK",
    "gn:dem":128,
    "gn:feature_class":"P",
    "gn:feature_code":"PPL",
    "gn:name":"Hangawela",
    "gn:population":0,
    "gn:timezone":"Asia/Colombo",
    "iso:country":"LK",
    "name:und_x_variant":[
        "Hangawda",
        "Hangawela"
    ],
    "wof:name":"Hangawela",
    "wof:placetype":"locality"
},
  "geometry": {"coordinates":[80.38160000000001,7.3473],"type":"Point"}
}