{
  "type": "Feature",
  "properties": {
    "gn:admin1_code":"32.0",
    "gn:asciiname":"Madurankuliya",
    "gn:country_code":"LK",
    "gn:dem":5,
    "gn:feature_class":"P",
    "gn:feature_code":"PPL",
    "gn:name":"Madurankuliya",
    "gn:population":0,
    "gn:timezone":"Asia/Colombo",
    "iso:country":"LK",
    "wof:name":"Madurankuliya",
    "wof:placetype":"locality"
},
  "geometry": {"coordinates":[79.8203,7.9102],"type":"Point"}
}