{
  "type": "Feature",
  "properties": {
    "gn:admin1_code":"29.0",
    "gn:asciiname":"Kumaragama",
    "gn:country_code":"LK",
    "gn:dem":529,
    "gn:feature_class":"P",
    "gn:feature_code":"PPL",
    "gn:name":"Kumaragama",
    "gn:population":0,
    "gn:timezone":"Asia/Colombo",
    "iso:country":"LK",
    "wof:name":"Kumaragama",
    "wof:placetype":"locality"
},
  "geometry": {"coordinates":[80.5151,7.2761],"type":"Point"}
}