{
  "type": "Feature",
  "properties": {
    "gn:admin1_code":"29.0",
    "gn:asciiname":"Yatiwehera",
    "gn:country_code":"LK",
    "gn:dem":426,
    "gn:feature_class":"P",
    "gn:feature_code":"PPL",
    "gn:name":"Yatiwehera",
    "gn:population":0,
    "gn:timezone":"Asia/Colombo",
    "iso:country":"LK",
    "name:urd_x_preferred":[
        "\u06cc\u062a\u06cc\u0648\u06be\u06cc\u0631\u0627"
    ],
    "wof:name":"Yatiwehera",
    "wof:placetype":"locality"
},
  "geometry": {"coordinates":[80.58333,7.71667],"type":"Point"}
}