{
  "type": "Feature",
  "properties": {
    "gn:admin1_code":"36.0",
    "gn:asciiname":"Dagonna",
    "gn:country_code":"LK",
    "gn:dem":21,
    "gn:feature_class":"P",
    "gn:feature_code":"PPL",
    "gn:name":"Dagonna",
    "gn:population":0,
    "gn:timezone":"Asia/Colombo",
    "iso:country":"LK",
    "name:und_x_variant":[
        "Dagona",
        "Dagonna"
    ],
    "wof:name":"Dagonna",
    "wof:placetype":"locality"
},
  "geometry": {"coordinates":[79.92789999999999,7.2219],"type":"Point"}
}