{
  "type": "Feature",
  "properties": {
    "gn:admin1_code":"33.0",
    "gn:asciiname":"Korakahinna",
    "gn:country_code":"LK",
    "gn:dem":256,
    "gn:feature_class":"P",
    "gn:feature_code":"PPL",
    "gn:name":"Korakahinna",
    "gn:population":0,
    "gn:timezone":"Asia/Colombo",
    "iso:country":"LK",
    "wof:name":"Korakahinna",
    "wof:placetype":"locality"
},
  "geometry": {"coordinates":[80.39699999999998,6.9523],"type":"Point"}
}