{
  "type": "Feature",
  "properties": {
    "gn:admin1_code":"38.0",
    "gn:asciiname":"Piramanankulam",
    "gn:country_code":"LK",
    "gn:dem":110,
    "gn:feature_class":"P",
    "gn:feature_code":"PPL",
    "gn:name":"Piramanankulam",
    "gn:population":0,
    "gn:timezone":"Asia/Colombo",
    "iso:country":"LK",
    "wof:name":"Piramanankulam",
    "wof:placetype":"locality"
},
  "geometry": {"coordinates":[80.5351,8.7399],"type":"Point"}
}