{
  "type": "Feature",
  "properties": {
    "gn:admin1_code":"29.0",
    "gn:asciiname":"Paldeniya",
    "gn:country_code":"LK",
    "gn:dem":417,
    "gn:feature_class":"P",
    "gn:feature_code":"PPL",
    "gn:name":"Paldeniya",
    "gn:population":0,
    "gn:timezone":"Asia/Colombo",
    "iso:country":"LK",
    "wof:name":"Paldeniya",
    "wof:placetype":"locality"
},
  "geometry": {"coordinates":[80.607,7.608],"type":"Point"}
}