{
  "type": "Feature",
  "properties": {
    "gn:admin1_code":"29.0",
    "gn:asciiname":"Watagollagama",
    "gn:country_code":"LK",
    "gn:dem":1144,
    "gn:feature_class":"P",
    "gn:feature_code":"PPL",
    "gn:name":"Watagollagama",
    "gn:population":0,
    "gn:timezone":"Asia/Colombo",
    "iso:country":"LK",
    "wof:name":"Watagollagama",
    "wof:placetype":"locality"
},
  "geometry": {"coordinates":[80.87569999999999,7.0743],"type":"Point"}
}