{
  "type": "Feature",
  "properties": {
    "gn:admin1_code":"32.0",
    "gn:asciiname":"Divullewa",
    "gn:country_code":"LK",
    "gn:dem":44,
    "gn:feature_class":"P",
    "gn:feature_code":"PPL",
    "gn:name":"Divullewa",
    "gn:population":0,
    "gn:timezone":"Asia/Colombo",
    "iso:country":"LK",
    "name:und_x_variant":[
        "Divulwewa",
        "Divullewa"
    ],
    "wof:name":"Divullewa",
    "wof:placetype":"locality"
},
  "geometry": {"coordinates":[79.9683,7.8487],"type":"Point"}
}