{
  "type": "Feature",
  "properties": {
    "gn:admin1_code":"33.0",
    "gn:asciiname":"Kathlana",
    "gn:country_code":"LK",
    "gn:dem":420,
    "gn:feature_class":"P",
    "gn:feature_code":"PPL",
    "gn:name":"Kathlana",
    "gn:population":0,
    "gn:timezone":"Asia/Colombo",
    "iso:country":"LK",
    "name:und_x_variant":[
        "Kathlama",
        "Kahlana",
        "Kathlana"
    ],
    "wof:name":"Kathlana",
    "wof:placetype":"locality"
},
  "geometry": {"coordinates":[80.5115,6.4399],"type":"Point"}
}