{
  "type": "Feature",
  "properties": {
    "gn:admin1_code":"35.0",
    "gn:asciiname":"Katuwethenna",
    "gn:country_code":"LK",
    "gn:dem":726,
    "gn:feature_class":"P",
    "gn:feature_code":"PPL",
    "gn:name":"Katuwethenna",
    "gn:population":0,
    "gn:timezone":"Asia/Colombo",
    "iso:country":"LK",
    "wof:name":"Katuwethenna",
    "wof:placetype":"locality"
},
  "geometry": {"coordinates":[81.07899999999999,7.0657],"type":"Point"}
}