{
  "type": "Feature",
  "properties": {
    "gn:admin1_code":"36.0",
    "gn:asciiname":"Polhena",
    "gn:country_code":"LK",
    "gn:dem":7,
    "gn:feature_class":"P",
    "gn:feature_code":"PPL",
    "gn:name":"Polhena",
    "gn:population":0,
    "gn:timezone":"Asia/Colombo",
    "iso:country":"LK",
    "wof:name":"Polhena",
    "wof:placetype":"locality"
},
  "geometry": {"coordinates":[79.9345,6.7679],"type":"Point"}
}