{
  "type": "Feature",
  "properties": {
    "gn:admin1_code":"38.0",
    "gn:asciiname":"Pudubulankulama",
    "gn:country_code":"LK",
    "gn:dem":92,
    "gn:feature_class":"P",
    "gn:feature_code":"PPL",
    "gn:name":"Pudubulankulama",
    "gn:population":0,
    "gn:timezone":"Asia/Colombo",
    "iso:country":"LK",
    "name:und_x_variant":[
        "Putubulankulama",
        "Putubulankulam"
    ],
    "wof:name":"Pudubulankulama",
    "wof:placetype":"locality"
},
  "geometry": {"coordinates":[80.5247,8.7842],"type":"Point"}
}