{
  "type": "Feature",
  "properties": {
    "gn:admin1_code":"35.0",
    "gn:asciiname":"Tangamale",
    "gn:country_code":"LK",
    "gn:dem":1017,
    "gn:feature_class":"P",
    "gn:feature_code":"PPL",
    "gn:name":"Tangamale",
    "gn:population":0,
    "gn:timezone":"Asia/Colombo",
    "iso:country":"LK",
    "wof:name":"Tangamale",
    "wof:placetype":"locality"
},
  "geometry": {"coordinates":[80.9361,7.0329],"type":"Point"}
}