{
  "type": "Feature",
  "properties": {
    "gn:admin1_code":"30.0",
    "gn:asciiname":"Kuda Nelumbewa",
    "gn:country_code":"LK",
    "gn:dem":103,
    "gn:feature_class":"P",
    "gn:feature_code":"PPL",
    "gn:name":"Kuda Nelumbewa",
    "gn:population":0,
    "gn:timezone":"Asia/Colombo",
    "iso:country":"LK",
    "name:und_x_variant":[
        "Kuda Nelubewa"
    ],
    "wof:name":"Kuda Nelumbewa",
    "wof:placetype":"locality"
},
  "geometry": {"coordinates":[80.3798,8.2757],"type":"Point"}
}