{
  "type": "Feature",
  "properties": {
    "gn:admin1_code":"29.0",
    "gn:asciiname":"Badatalwatta",
    "gn:country_code":"LK",
    "gn:dem":278,
    "gn:feature_class":"P",
    "gn:feature_code":"PPL",
    "gn:name":"Badatalwatta",
    "gn:population":0,
    "gn:timezone":"Asia/Colombo",
    "iso:country":"LK",
    "wof:name":"Badatalwatta",
    "wof:placetype":"locality"
},
  "geometry": {"coordinates":[80.43170000000001,7.336],"type":"Point"}
}