{
  "type": "Feature",
  "properties": {
    "gn:admin1_code":"33.0",
    "gn:asciiname":"Madeiyawa",
    "gn:country_code":"LK",
    "gn:dem":208,
    "gn:feature_class":"P",
    "gn:feature_code":"PPL",
    "gn:name":"Madeiyawa",
    "gn:population":0,
    "gn:timezone":"Asia/Colombo",
    "iso:country":"LK",
    "wof:name":"Madeiyawa",
    "wof:placetype":"locality"
},
  "geometry": {"coordinates":[80.34999999999999,7.25],"type":"Point"}
}