{
  "type": "Feature",
  "properties": {
    "gn:admin1_code":"32.0",
    "gn:asciiname":"Tract Five",
    "gn:country_code":"LK",
    "gn:dem":64,
    "gn:feature_class":"P",
    "gn:feature_code":"PPL",
    "gn:name":"Tract Five",
    "gn:population":0,
    "gn:timezone":"Asia/Colombo",
    "iso:country":"LK",
    "name:und_x_variant":[
        "Tract 5"
    ],
    "wof:name":"Tract Five",
    "wof:placetype":"locality"
},
  "geometry": {"coordinates":[80.1345,8.1406],"type":"Point"}
}