{
  "type": "Feature",
  "properties": {
    "gn:admin1_code":"35.0",
    "gn:asciiname":"Muthukeliyawa",
    "gn:country_code":"LK",
    "gn:dem":196,
    "gn:feature_class":"P",
    "gn:feature_code":"PPL",
    "gn:name":"Muthukeliyawa",
    "gn:population":0,
    "gn:timezone":"Asia/Colombo",
    "iso:country":"LK",
    "name:und_x_variant":[
        "Mutukeiyawa",
        "Mutuketiyawa",
        "Muthukeliyawa"
    ],
    "wof:name":"Muthukeliyawa",
    "wof:placetype":"locality"
},
  "geometry": {"coordinates":[81.24509999999999,6.8244],"type":"Point"}
}