{
  "type": "Feature",
  "properties": {
    "gn:admin1_code":"37.0",
    "gn:asciiname":"Mahaella",
    "gn:country_code":"LK",
    "gn:dem":108,
    "gn:feature_class":"P",
    "gn:feature_code":"PPL",
    "gn:name":"Mahaella",
    "gn:population":0,
    "gn:timezone":"Asia/Colombo",
    "iso:country":"LK",
    "wof:name":"Mahaella",
    "wof:placetype":"locality"
},
  "geometry": {"coordinates":[81.08333,7.61667],"type":"Point"}
}