{
  "type": "Feature",
  "properties": {
    "gn:admin1_code":"38.0",
    "gn:asciiname":"Alankulam",
    "gn:country_code":"LK",
    "gn:dem":41,
    "gn:feature_class":"P",
    "gn:feature_code":"PPL",
    "gn:name":"Alankulam",
    "gn:population":0,
    "gn:timezone":"Asia/Colombo",
    "iso:country":"LK",
    "wof:name":"Alankulam",
    "wof:placetype":"locality"
},
  "geometry": {"coordinates":[80.28333000000001,9.16667],"type":"Point"}
}