{
  "type": "Feature",
  "properties": {
    "gn:admin1_code":"37.0",
    "gn:asciiname":"Cheddipalayam",
    "gn:country_code":"LK",
    "gn:dem":10,
    "gn:feature_class":"P",
    "gn:feature_code":"PPL",
    "gn:name":"Cheddipalayam",
    "gn:population":0,
    "gn:timezone":"Asia/Colombo",
    "iso:country":"LK",
    "name:und_x_variant":[
        "Cheddipalavam",
        "Cheddipalayam"
    ],
    "wof:name":"Cheddipalayam",
    "wof:placetype":"locality"
},
  "geometry": {"coordinates":[81.78333000000001,7.58333],"type":"Point"}
}