{
  "type": "Feature",
  "properties": {
    "gn:admin1_code":"32.0",
    "gn:asciiname":"Walpalagedara",
    "gn:country_code":"LK",
    "gn:dem":111,
    "gn:feature_class":"P",
    "gn:feature_code":"PPL",
    "gn:name":"Walpalagedara",
    "gn:population":0,
    "gn:timezone":"Asia/Colombo",
    "iso:country":"LK",
    "name:und_x_variant":[
        "Walpolagedara"
    ],
    "wof:name":"Walpalagedara",
    "wof:placetype":"locality"
},
  "geometry": {"coordinates":[80.28749999999999,7.467],"type":"Point"}
}