{
  "type": "Feature",
  "properties": {
    "gn:admin1_code":"34.0",
    "gn:asciiname":"Gurukanda",
    "gn:country_code":"LK",
    "gn:dem":13,
    "gn:feature_class":"P",
    "gn:feature_code":"PPL",
    "gn:name":"Gurukanda",
    "gn:population":0,
    "gn:timezone":"Asia/Colombo",
    "iso:country":"LK",
    "wof:name":"Gurukanda",
    "wof:placetype":"locality"
},
  "geometry": {"coordinates":[80.2561,6.0087],"type":"Point"}
}