{
  "type": "Feature",
  "properties": {
    "gn:admin1_code":"38.0",
    "gn:asciiname":"Tudarikkulam",
    "gn:country_code":"LK",
    "gn:dem":75,
    "gn:feature_class":"P",
    "gn:feature_code":"PPL",
    "gn:name":"Tudarikkulam",
    "gn:population":0,
    "gn:timezone":"Asia/Colombo",
    "iso:country":"LK",
    "wof:name":"Tudarikkulam",
    "wof:placetype":"locality"
},
  "geometry": {"coordinates":[80.3925,8.6593],"type":"Point"}
}