{
  "type": "Feature",
  "properties": {
    "gn:admin1_code":"35.0",
    "gn:asciiname":"Magandanamulla",
    "gn:country_code":"LK",
    "gn:dem":163,
    "gn:feature_class":"P",
    "gn:feature_code":"PPL",
    "gn:name":"Magandanamulla",
    "gn:population":0,
    "gn:timezone":"Asia/Colombo",
    "iso:country":"LK",
    "name:und_x_variant":[
        "Magandenamulla",
        "Magandanamulla"
    ],
    "wof:name":"Magandanamulla",
    "wof:placetype":"locality"
},
  "geometry": {"coordinates":[81.3306,6.8844],"type":"Point"}
}