{
  "type": "Feature",
  "properties": {
    "gn:admin1_code":"29.0",
    "gn:asciiname":"Panawelulla",
    "gn:country_code":"LK",
    "gn:dem":851,
    "gn:feature_class":"P",
    "gn:feature_code":"PPL",
    "gn:name":"Panawelulla",
    "gn:population":0,
    "gn:timezone":"Asia/Colombo",
    "iso:country":"LK",
    "wof:name":"Panawelulla",
    "wof:placetype":"locality"
},
  "geometry": {"coordinates":[80.90000000000001,7.33333],"type":"Point"}
}