{
  "type": "Feature",
  "properties": {
    "gn:admin1_code":"36.0",
    "gn:asciiname":"Delthara",
    "gn:country_code":"LK",
    "gn:dem":23,
    "gn:feature_class":"P",
    "gn:feature_code":"PPL",
    "gn:name":"Delthara",
    "gn:population":0,
    "gn:timezone":"Asia/Colombo",
    "iso:country":"LK",
    "name:und_x_variant":[
        "Deltara"
    ],
    "wof:name":"Delthara",
    "wof:placetype":"locality"
},
  "geometry": {"coordinates":[79.9117,6.7841],"type":"Point"}
}