{
  "type": "Feature",
  "properties": {
    "gn:admin1_code":"30.0",
    "gn:asciiname":"Ihala Nochchikulama",
    "gn:country_code":"LK",
    "gn:dem":148,
    "gn:feature_class":"P",
    "gn:feature_code":"PPL",
    "gn:name":"Ihala Nochchikulama",
    "gn:population":0,
    "gn:timezone":"Asia/Colombo",
    "iso:country":"LK",
    "wof:name":"Ihala Nochchikulama",
    "wof:placetype":"locality"
},
  "geometry": {"coordinates":[80.5942,8.0972],"type":"Point"}
}