{
  "type": "Feature",
  "properties": {
    "gn:admin1_code":"32.0",
    "gn:asciiname":"Dewategedara",
    "gn:country_code":"LK",
    "gn:dem":100,
    "gn:feature_class":"P",
    "gn:feature_code":"PPL",
    "gn:name":"Dewategedara",
    "gn:population":0,
    "gn:timezone":"Asia/Colombo",
    "iso:country":"LK",
    "wof:name":"Dewategedara",
    "wof:placetype":"locality"
},
  "geometry": {"coordinates":[80.28333000000001,7.41667],"type":"Point"}
}