{
  "type": "Feature",
  "properties": {
    "gn:admin1_code":"29.0",
    "gn:asciiname":"Florence Rondura",
    "gn:country_code":"LK",
    "gn:dem":367,
    "gn:feature_class":"P",
    "gn:feature_code":"PPL",
    "gn:name":"Florence Rondura",
    "gn:population":0,
    "gn:timezone":"Asia/Colombo",
    "iso:country":"LK",
    "wof:name":"Florence Rondura",
    "wof:placetype":"locality"
},
  "geometry": {"coordinates":[80.4532,6.995],"type":"Point"}
}