{
  "type": "Feature",
  "properties": {
    "gn:admin1_code":"32.0",
    "gn:asciiname":"Sankadayagama",
    "gn:country_code":"LK",
    "gn:dem":53,
    "gn:feature_class":"P",
    "gn:feature_code":"PPL",
    "gn:name":"Sankadayagama",
    "gn:population":0,
    "gn:timezone":"Asia/Colombo",
    "iso:country":"LK",
    "wof:name":"Sankadayagama",
    "wof:placetype":"locality"
},
  "geometry": {"coordinates":[80.03333000000001,7.91667],"type":"Point"}
}