{
  "type": "Feature",
  "properties": {
    "gn:admin1_code":"32.0",
    "gn:asciiname":"Nelungama",
    "gn:country_code":"LK",
    "gn:dem":88,
    "gn:feature_class":"P",
    "gn:feature_code":"PPL",
    "gn:name":"Nelungama",
    "gn:population":0,
    "gn:timezone":"Asia/Colombo",
    "iso:country":"LK",
    "wof:name":"Nelungama",
    "wof:placetype":"locality"
},
  "geometry": {"coordinates":[80.28279999999999,8.0856],"type":"Point"}
}