{
  "type": "Feature",
  "properties": {
    "gn:admin1_code":"33.0",
    "gn:asciiname":"Assella",
    "gn:country_code":"LK",
    "gn:dem":208,
    "gn:feature_class":"P",
    "gn:feature_code":"PPL",
    "gn:name":"Assella",
    "gn:population":0,
    "gn:timezone":"Asia/Colombo",
    "iso:country":"LK",
    "wof:name":"Assella",
    "wof:placetype":"locality"
},
  "geometry": {"coordinates":[80.25790000000001,7.2169],"type":"Point"}
}