{
  "type": "Feature",
  "properties": {
    "gn:admin1_code":"32.0",
    "gn:asciiname":"Bogahawatta",
    "gn:country_code":"LK",
    "gn:dem":70,
    "gn:feature_class":"P",
    "gn:feature_code":"PPL",
    "gn:name":"Bogahawatta",
    "gn:population":0,
    "gn:timezone":"Asia/Colombo",
    "iso:country":"LK",
    "wof:name":"Bogahawatta",
    "wof:placetype":"locality"
},
  "geometry": {"coordinates":[80.1645,7.2966],"type":"Point"}
}