{
  "type": "Feature",
  "properties": {
    "gn:admin1_code":"32.0",
    "gn:asciiname":"Hittaragama",
    "gn:country_code":"LK",
    "gn:dem":164,
    "gn:feature_class":"P",
    "gn:feature_code":"PPL",
    "gn:name":"Hittaragama",
    "gn:population":0,
    "gn:timezone":"Asia/Colombo",
    "iso:country":"LK",
    "wof:name":"Hittaragama",
    "wof:placetype":"locality"
},
  "geometry": {"coordinates":[80.4667,7.6156],"type":"Point"}
}