{
  "type": "Feature",
  "properties": {
    "gn:admin1_code":"33.0",
    "gn:asciiname":"Palarambegama",
    "gn:country_code":"LK",
    "gn:dem":132,
    "gn:feature_class":"P",
    "gn:feature_code":"PPL",
    "gn:name":"Palarambegama",
    "gn:population":0,
    "gn:timezone":"Asia/Colombo",
    "iso:country":"LK",
    "wof:name":"Palarambegama",
    "wof:placetype":"locality"
},
  "geometry": {"coordinates":[80.407,7.2585],"type":"Point"}
}