{
  "type": "Feature",
  "properties": {
    "gn:admin1_code":"34.0",
    "gn:asciiname":"Yagala",
    "gn:country_code":"LK",
    "gn:dem":38,
    "gn:feature_class":"P",
    "gn:feature_code":"PPL",
    "gn:name":"Yagala",
    "gn:population":0,
    "gn:timezone":"Asia/Colombo",
    "iso:country":"LK",
    "wof:name":"Yagala",
    "wof:placetype":"locality"
},
  "geometry": {"coordinates":[80.37100000000002,5.9972],"type":"Point"}
}