{
  "type": "Feature",
  "properties": {
    "gn:admin1_code":"35.0",
    "gn:asciiname":"Kanupelella",
    "gn:country_code":"LK",
    "gn:dem":750,
    "gn:feature_class":"P",
    "gn:feature_code":"PPL",
    "gn:name":"Kanupelella",
    "gn:population":0,
    "gn:timezone":"Asia/Colombo",
    "iso:country":"LK",
    "name:und_x_variant":[
        "Kanupalaella"
    ],
    "wof:name":"Kanupelella",
    "wof:placetype":"locality"
},
  "geometry": {"coordinates":[81.0573,6.9762],"type":"Point"}
}