{
  "type": "Feature",
  "properties": {
    "gn:admin1_code":"32.0",
    "gn:asciiname":"Tarapota",
    "gn:country_code":"LK",
    "gn:dem":184,
    "gn:feature_class":"P",
    "gn:feature_code":"PPL",
    "gn:name":"Tarapota",
    "gn:population":0,
    "gn:timezone":"Asia/Colombo",
    "iso:country":"LK",
    "name:und_x_variant":[
        "Madawa Tarapota",
        "Tarapota"
    ],
    "wof:name":"Tarapota",
    "wof:placetype":"locality"
},
  "geometry": {"coordinates":[80.4229,7.4787],"type":"Point"}
}