{
  "type": "Feature",
  "properties": {
    "gn:admin1_code":"36.0",
    "gn:asciiname":"Nungomuwa",
    "gn:country_code":"LK",
    "gn:dem":43,
    "gn:feature_class":"P",
    "gn:feature_code":"PPL",
    "gn:name":"Nungomuwa",
    "gn:population":0,
    "gn:timezone":"Asia/Colombo",
    "iso:country":"LK",
    "name:und_x_variant":[
        "Nungamuwa",
        "Nungomuwa"
    ],
    "wof:name":"Nungomuwa",
    "wof:placetype":"locality"
},
  "geometry": {"coordinates":[80.07510000000001,7.1972],"type":"Point"}
}