{
  "type": "Feature",
  "properties": {
    "gn:admin1_code":"30.0",
    "gn:asciiname":"Kunchikulama",
    "gn:country_code":"LK",
    "gn:dem":135,
    "gn:feature_class":"P",
    "gn:feature_code":"PPL",
    "gn:name":"Kunchikulama",
    "gn:population":0,
    "gn:timezone":"Asia/Colombo",
    "iso:country":"LK",
    "name:und_x_variant":[
        "Kunchikulam",
        "Kunchikulama"
    ],
    "wof:name":"Kunchikulama",
    "wof:placetype":"locality"
},
  "geometry": {"coordinates":[80.5211,8.0928],"type":"Point"}
}