{
  "type": "Feature",
  "properties": {
    "gn:admin1_code":"35.0",
    "gn:asciiname":"Bambaragalapathana",
    "gn:country_code":"LK",
    "gn:dem":1329,
    "gn:feature_class":"P",
    "gn:feature_code":"PPL",
    "gn:name":"Bambaragalapathana",
    "gn:population":0,
    "gn:timezone":"Asia/Colombo",
    "iso:country":"LK",
    "wof:name":"Bambaragalapathana",
    "wof:placetype":"locality"
},
  "geometry": {"coordinates":[81.1302,6.8816],"type":"Point"}
}