{
  "type": "Feature",
  "properties": {
    "gn:admin1_code":"35.0",
    "gn:asciiname":"Samagipura",
    "gn:country_code":"LK",
    "gn:dem":80,
    "gn:feature_class":"P",
    "gn:feature_code":"PPL",
    "gn:name":"Samagipura",
    "gn:population":0,
    "gn:timezone":"Asia/Colombo",
    "iso:country":"LK",
    "wof:name":"Samagipura",
    "wof:placetype":"locality"
},
  "geometry": {"coordinates":[80.9736,6.3961],"type":"Point"}
}