{
  "type": "Feature",
  "properties": {
    "gn:admin1_code":"35.0",
    "gn:asciiname":"Pallewela",
    "gn:country_code":"LK",
    "gn:dem":233,
    "gn:feature_class":"P",
    "gn:feature_code":"PPL",
    "gn:name":"Pallewela",
    "gn:population":0,
    "gn:timezone":"Asia/Colombo",
    "iso:country":"LK",
    "wof:name":"Pallewela",
    "wof:placetype":"locality"
},
  "geometry": {"coordinates":[80.9914,7.1334],"type":"Point"}
}