{
  "type": "Feature",
  "properties": {
    "gn:admin1_code":"32.0",
    "gn:asciiname":"Mankulama",
    "gn:country_code":"LK",
    "gn:dem":38,
    "gn:feature_class":"P",
    "gn:feature_code":"PPL",
    "gn:name":"Mankulama",
    "gn:population":0,
    "gn:timezone":"Asia/Colombo",
    "iso:country":"LK",
    "wof:name":"Mankulama",
    "wof:placetype":"locality"
},
  "geometry": {"coordinates":[79.9136,7.7852],"type":"Point"}
}