{
  "type": "Feature",
  "properties": {
    "gn:admin1_code":"35.0",
    "gn:asciiname":"Potuliyadda",
    "gn:country_code":"LK",
    "gn:dem":96,
    "gn:feature_class":"P",
    "gn:feature_code":"PPL",
    "gn:name":"Potuliyadda",
    "gn:population":0,
    "gn:timezone":"Asia/Colombo",
    "iso:country":"LK",
    "wof:name":"Potuliyadda",
    "wof:placetype":"locality"
},
  "geometry": {"coordinates":[81.45,7.26667],"type":"Point"}
}