{
  "type": "Feature",
  "properties": {
    "gn:admin1_code":"36.0",
    "gn:asciiname":"Dumunegedara",
    "gn:country_code":"LK",
    "gn:dem":35,
    "gn:feature_class":"P",
    "gn:feature_code":"PPL",
    "gn:name":"Dumunegedara",
    "gn:population":0,
    "gn:timezone":"Asia/Colombo",
    "iso:country":"LK",
    "name:und_x_variant":[
        "Dummunegedara",
        "Dumunegedara"
    ],
    "wof:name":"Dumunegedara",
    "wof:placetype":"locality"
},
  "geometry": {"coordinates":[80.0951,7.1714],"type":"Point"}
}