{
  "type": "Feature",
  "properties": {
    "gn:admin1_code":"35.0",
    "gn:asciiname":"Kachcheri",
    "gn:country_code":"LK",
    "gn:dem":159,
    "gn:feature_class":"P",
    "gn:feature_code":"PPL",
    "gn:name":"Kachcheri",
    "gn:population":0,
    "gn:timezone":"Asia/Colombo",
    "iso:country":"LK",
    "wof:name":"Kachcheri",
    "wof:placetype":"locality"
},
  "geometry": {"coordinates":[81.3365,6.8632],"type":"Point"}
}