{
  "type": "Feature",
  "properties": {
    "gn:admin1_code":"36.0",
    "gn:asciiname":"Depanama",
    "gn:country_code":"LK",
    "gn:dem":15,
    "gn:feature_class":"P",
    "gn:feature_code":"PPL",
    "gn:name":"Depanama",
    "gn:population":0,
    "gn:timezone":"Asia/Colombo",
    "iso:country":"LK",
    "wof:name":"Depanama",
    "wof:placetype":"locality"
},
  "geometry": {"coordinates":[79.9415,6.8491],"type":"Point"}
}