{
  "type": "Feature",
  "properties": {
    "gn:admin1_code":"32.0",
    "gn:asciiname":"Surukkulama",
    "gn:country_code":"LK",
    "gn:dem":45,
    "gn:feature_class":"P",
    "gn:feature_code":"PPL",
    "gn:name":"Surukkulama",
    "gn:population":0,
    "gn:timezone":"Asia/Colombo",
    "iso:country":"LK",
    "name:und_x_variant":[
        "Soorakkulama",
        "Soorukkulama",
        "Surukkulama"
    ],
    "wof:name":"Surukkulama",
    "wof:placetype":"locality"
},
  "geometry": {"coordinates":[79.95359999999999,7.8024],"type":"Point"}
}