{
  "type": "Feature",
  "properties": {
    "gn:admin1_code":"35.0",
    "gn:asciiname":"Baladangolla",
    "gn:country_code":"LK",
    "gn:dem":181,
    "gn:feature_class":"P",
    "gn:feature_code":"PPL",
    "gn:name":"Baladangolla",
    "gn:population":0,
    "gn:timezone":"Asia/Colombo",
    "iso:country":"LK",
    "wof:name":"Baladangolla",
    "wof:placetype":"locality"
},
  "geometry": {"coordinates":[81.06667,7.23333],"type":"Point"}
}