{
  "type": "Feature",
  "properties": {
    "gn:admin1_code":"34.0",
    "gn:asciiname":"Siyambalagaswila",
    "gn:country_code":"LK",
    "gn:dem":21,
    "gn:feature_class":"P",
    "gn:feature_code":"PPL",
    "gn:name":"Siyambalagaswila",
    "gn:population":0,
    "gn:timezone":"Asia/Colombo",
    "iso:country":"LK",
    "name:und_x_variant":[
        "Siyambalagaswela"
    ],
    "wof:name":"Siyambalagaswila",
    "wof:placetype":"locality"
},
  "geometry": {"coordinates":[81.02930000000001,6.1682],"type":"Point"}
}