{
  "type": "Feature",
  "properties": {
    "gn:admin1_code":"32.0",
    "gn:asciiname":"Palukadawela",
    "gn:country_code":"LK",
    "gn:dem":93,
    "gn:feature_class":"P",
    "gn:feature_code":"PPL",
    "gn:name":"Palukadawela",
    "gn:population":0,
    "gn:timezone":"Asia/Colombo",
    "iso:country":"LK",
    "name:und_x_variant":[
        "Palukadawala"
    ],
    "wof:name":"Palukadawela",
    "wof:placetype":"locality"
},
  "geometry": {"coordinates":[80.2811,7.947],"type":"Point"}
}