{
  "type": "Feature",
  "properties": {
    "gn:admin1_code":"35.0",
    "gn:asciiname":"Kandekumbura",
    "gn:country_code":"LK",
    "gn:dem":723,
    "gn:feature_class":"P",
    "gn:feature_code":"PPL",
    "gn:name":"Kandekumbura",
    "gn:population":0,
    "gn:timezone":"Asia/Colombo",
    "iso:country":"LK",
    "wof:name":"Kandekumbura",
    "wof:placetype":"locality"
},
  "geometry": {"coordinates":[81.08333,6.98333],"type":"Point"}
}