{
  "type": "Feature",
  "properties": {
    "gn:admin1_code":"32.0",
    "gn:asciiname":"Kivula Youth Scheme",
    "gn:country_code":"LK",
    "gn:dem":47,
    "gn:feature_class":"P",
    "gn:feature_code":"PPL",
    "gn:name":"Kivula Youth Scheme",
    "gn:population":0,
    "gn:timezone":"Asia/Colombo",
    "iso:country":"LK",
    "wof:name":"Kivula Youth Scheme",
    "wof:placetype":"locality"
},
  "geometry": {"coordinates":[79.90389999999999,7.8927],"type":"Point"}
}