{
  "type": "Feature",
  "properties": {
    "gn:admin1_code":"36.0",
    "gn:asciiname":"Lewwanduwa",
    "gn:country_code":"LK",
    "gn:dem":6,
    "gn:feature_class":"P",
    "gn:feature_code":"PPL",
    "gn:name":"Lewwanduwa",
    "gn:population":0,
    "gn:timezone":"Asia/Colombo",
    "iso:country":"LK",
    "name:und_x_variant":[
        "Leuwanduwa"
    ],
    "wof:name":"Lewwanduwa",
    "wof:placetype":"locality"
},
  "geometry": {"coordinates":[80.0989,6.4515],"type":"Point"}
}