{
  "type": "Feature",
  "properties": {
    "gn:admin1_code":"30.0",
    "gn:asciiname":"Tract Nine",
    "gn:country_code":"LK",
    "gn:dem":56,
    "gn:feature_class":"P",
    "gn:feature_code":"PPL",
    "gn:name":"Tract Nine",
    "gn:population":0,
    "gn:timezone":"Asia/Colombo",
    "iso:country":"LK",
    "name:und_x_variant":[
        "Tract 9"
    ],
    "wof:name":"Tract Nine",
    "wof:placetype":"locality"
},
  "geometry": {"coordinates":[80.1494,8.1897],"type":"Point"}
}