{
  "type": "Feature",
  "properties": {
    "gn:admin1_code":"32.0",
    "gn:asciiname":"Siyambalewa",
    "gn:country_code":"LK",
    "gn:dem":41,
    "gn:feature_class":"P",
    "gn:feature_code":"PPL",
    "gn:name":"Siyambalewa",
    "gn:population":0,
    "gn:timezone":"Asia/Colombo",
    "iso:country":"LK",
    "name:und_x_variant":[
        "Siyambalawela"
    ],
    "wof:name":"Siyambalewa",
    "wof:placetype":"locality"
},
  "geometry": {"coordinates":[80.0535,7.6472],"type":"Point"}
}