{
  "type": "Feature",
  "properties": {
    "gn:admin1_code":"35.0",
    "gn:asciiname":"Kachthari",
    "gn:country_code":"LK",
    "gn:dem":699,
    "gn:feature_class":"P",
    "gn:feature_code":"PPL",
    "gn:name":"Kachthari",
    "gn:population":0,
    "gn:timezone":"Asia/Colombo",
    "iso:country":"LK",
    "wof:name":"Kachthari",
    "wof:placetype":"locality"
},
  "geometry": {"coordinates":[81.04949999999999,6.9918],"type":"Point"}
}