{
  "type": "Feature",
  "properties": {
    "gn:admin1_code":"29.0",
    "gn:asciiname":"Petiyagoda",
    "gn:country_code":"LK",
    "gn:dem":502,
    "gn:feature_class":"P",
    "gn:feature_code":"PPL",
    "gn:name":"Petiyagoda",
    "gn:population":0,
    "gn:timezone":"Asia/Colombo",
    "iso:country":"LK",
    "wof:name":"Petiyagoda",
    "wof:placetype":"locality"
},
  "geometry": {"coordinates":[80.5836,7.2137],"type":"Point"}
}