{
  "type": "Feature",
  "properties": {
    "gn:admin1_code":"34.0",
    "gn:asciiname":"Kirinda Magin Pahala",
    "gn:country_code":"LK",
    "gn:dem":28,
    "gn:feature_class":"P",
    "gn:feature_code":"PPL",
    "gn:name":"Kirinda Magin Pahala",
    "gn:population":0,
    "gn:timezone":"Asia/Colombo",
    "iso:country":"LK",
    "wof:name":"Kirinda Magin Pahala",
    "wof:placetype":"locality"
},
  "geometry": {"coordinates":[80.61667,6.05],"type":"Point"}
}