{
  "type": "Feature",
  "properties": {
    "gn:admin1_code":"29.0",
    "gn:asciiname":"Katupathwela",
    "gn:country_code":"LK",
    "gn:dem":275,
    "gn:feature_class":"P",
    "gn:feature_code":"PPL",
    "gn:name":"Katupathwela",
    "gn:population":0,
    "gn:timezone":"Asia/Colombo",
    "iso:country":"LK",
    "name:und_x_variant":[
        "Kalapathwela",
        "Katupathwela"
    ],
    "wof:name":"Katupathwela",
    "wof:placetype":"locality"
},
  "geometry": {"coordinates":[80.833,7.1892],"type":"Point"}
}