{
  "type": "Feature",
  "properties": {
    "gn:admin1_code":"30.0",
    "gn:asciiname":"Mawatagama",
    "gn:country_code":"LK",
    "gn:dem":104,
    "gn:feature_class":"P",
    "gn:feature_code":"PPL",
    "gn:name":"Mawatagama",
    "gn:population":0,
    "gn:timezone":"Asia/Colombo",
    "iso:country":"LK",
    "name:ceb_x_preferred":[
        "Mawatagama"
    ],
    "name:swe_x_preferred":[
        "Mawatagama"
    ],
    "wof:name":"Mawatagama",
    "wof:placetype":"locality"
},
  "geometry": {"coordinates":[80.376,8.172],"type":"Point"}
}