{
  "type": "Feature",
  "properties": {
    "gn:admin1_code":"38.0",
    "gn:asciiname":"Periyapuliyankulam",
    "gn:country_code":"LK",
    "gn:dem":56,
    "gn:feature_class":"P",
    "gn:feature_code":"PPL",
    "gn:name":"Periyapuliyankulam",
    "gn:population":0,
    "gn:timezone":"Asia/Colombo",
    "iso:country":"LK",
    "wof:name":"Periyapuliyankulam",
    "wof:placetype":"locality"
},
  "geometry": {"coordinates":[80.50360000000001,9.1396],"type":"Point"}
}