{
  "type": "Feature",
  "properties": {
    "gn:admin1_code":"32.0",
    "gn:asciiname":"Tambarombuwa",
    "gn:cc2":"LK",
    "gn:country_code":"LK",
    "gn:dem":84,
    "gn:feature_class":"P",
    "gn:feature_code":"PPL",
    "gn:name":"Tambarombuwa",
    "gn:population":0,
    "gn:timezone":"Asia/Colombo",
    "iso:country":"LK",
    "name:und_x_variant":[
        "Thamba Rombuwa",
        "Tambarombuwa"
    ],
    "wof:name":"Tambarombuwa",
    "wof:placetype":"locality"
},
  "geometry": {"coordinates":[80.09999999999999,7.85],"type":"Point"}
}