{
  "type": "Feature",
  "properties": {
    "gn:admin1_code":"33.0",
    "gn:asciiname":"Wanniyawatta",
    "gn:country_code":"LK",
    "gn:dem":68,
    "gn:feature_class":"P",
    "gn:feature_code":"PPL",
    "gn:name":"Wanniyawatta",
    "gn:population":0,
    "gn:timezone":"Asia/Colombo",
    "iso:country":"LK",
    "wof:name":"Wanniyawatta",
    "wof:placetype":"locality"
},
  "geometry": {"coordinates":[80.5029,6.5929],"type":"Point"}
}