{
  "type": "Feature",
  "properties": {
    "gn:admin1_code":"33.0",
    "gn:asciiname":"Basnagala",
    "gn:country_code":"LK",
    "gn:dem":324,
    "gn:feature_class":"P",
    "gn:feature_code":"PPL",
    "gn:name":"Basnagala",
    "gn:population":0,
    "gn:timezone":"Asia/Colombo",
    "iso:country":"LK",
    "wof:name":"Basnagala",
    "wof:placetype":"locality"
},
  "geometry": {"coordinates":[80.4029,6.9446],"type":"Point"}
}