{
  "type": "Feature",
  "properties": {
    "gn:admin1_code":"30.0",
    "gn:asciiname":"Ihala Anduketiyawa",
    "gn:country_code":"LK",
    "gn:dem":98,
    "gn:feature_class":"P",
    "gn:feature_code":"PPL",
    "gn:name":"Ihala Anduketiyawa",
    "gn:population":0,
    "gn:timezone":"Asia/Colombo",
    "iso:country":"LK",
    "wof:name":"Ihala Anduketiyawa",
    "wof:placetype":"locality"
},
  "geometry": {"coordinates":[80.3652,8.3936],"type":"Point"}
}