{
  "type": "Feature",
  "properties": {
    "gn:admin1_code":"29.0",
    "gn:asciiname":"Bokalawala",
    "gn:country_code":"LK",
    "gn:dem":493,
    "gn:feature_class":"P",
    "gn:feature_code":"PPL",
    "gn:name":"Bokalawala",
    "gn:population":0,
    "gn:timezone":"Asia/Colombo",
    "iso:country":"LK",
    "name:ron_x_preferred":[
        "Bokalawela"
    ],
    "name:und_x_variant":[
        "Bokalawela"
    ],
    "wof:name":"Bokalawala",
    "wof:placetype":"locality"
},
  "geometry": {"coordinates":[80.6024,7.3455],"type":"Point"}
}