{
  "type": "Feature",
  "properties": {
    "gn:admin1_code":"29.0",
    "gn:asciiname":"Raitalawa",
    "gn:country_code":"LK",
    "gn:dem":303,
    "gn:feature_class":"P",
    "gn:feature_code":"PPL",
    "gn:name":"Raitalawa",
    "gn:population":0,
    "gn:timezone":"Asia/Colombo",
    "iso:country":"LK",
    "wof:name":"Raitalawa",
    "wof:placetype":"locality"
},
  "geometry": {"coordinates":[80.6601,7.5495],"type":"Point"}
}