{
  "type": "Feature",
  "properties": {
    "gn:admin1_code":"34.0",
    "gn:asciiname":"Muttetuhengoda",
    "gn:country_code":"LK",
    "gn:dem":90,
    "gn:feature_class":"P",
    "gn:feature_code":"PPL",
    "gn:name":"Muttetuhengoda",
    "gn:population":0,
    "gn:timezone":"Asia/Colombo",
    "iso:country":"LK",
    "wof:name":"Muttetuhengoda",
    "wof:placetype":"locality"
},
  "geometry": {"coordinates":[80.7221,6.1415],"type":"Point"}
}