{
  "type": "Feature",
  "properties": {
    "gn:admin1_code":"36.0",
    "gn:asciiname":"Embaraluwa North",
    "gn:country_code":"LK",
    "gn:dem":40,
    "gn:feature_class":"P",
    "gn:feature_code":"PPL",
    "gn:name":"Embaraluwa North",
    "gn:population":0,
    "gn:timezone":"Asia/Colombo",
    "iso:country":"LK",
    "wof:name":"Embaraluwa North",
    "wof:placetype":"locality"
},
  "geometry": {"coordinates":[80.0043,7.0238],"type":"Point"}
}