{
  "type": "Feature",
  "properties": {
    "gn:admin1_code":"32.0",
    "gn:asciiname":"Ambagahalanda",
    "gn:country_code":"LK",
    "gn:dem":147,
    "gn:feature_class":"P",
    "gn:feature_code":"PPL",
    "gn:name":"Ambagahalanda",
    "gn:population":0,
    "gn:timezone":"Asia/Colombo",
    "iso:country":"LK",
    "wof:name":"Ambagahalanda",
    "wof:placetype":"locality"
},
  "geometry": {"coordinates":[80.4863,7.6469],"type":"Point"}
}