{
  "type": "Feature",
  "properties": {
    "gn:admin1_code":"34.0",
    "gn:asciiname":"Aggarahere",
    "gn:country_code":"LK",
    "gn:dem":61,
    "gn:feature_class":"P",
    "gn:feature_code":"PPL",
    "gn:name":"Aggarahere",
    "gn:population":0,
    "gn:timezone":"Asia/Colombo",
    "iso:country":"LK",
    "name:fas_x_preferred":[
        "\u0627\u062c\u0631\u0627\u0647\u0631"
    ],
    "name:urd_x_preferred":[
        "\u0627\u062c\u0631\u0627\u06c1\u0631"
    ],
    "wof:name":"Aggarahere",
    "wof:placetype":"locality"
},
  "geometry": {"coordinates":[80.78333000000001,6.13333],"type":"Point"}
}