{
  "type": "Feature",
  "properties": {
    "gn:admin1_code":"32.0",
    "gn:asciiname":"Medamulla",
    "gn:country_code":"LK",
    "gn:dem":143,
    "gn:feature_class":"P",
    "gn:feature_code":"PPL",
    "gn:name":"Medamulla",
    "gn:population":0,
    "gn:timezone":"Asia/Colombo",
    "iso:country":"LK",
    "wof:name":"Medamulla",
    "wof:placetype":"locality"
},
  "geometry": {"coordinates":[80.49890000000001,7.6442],"type":"Point"}
}