{
  "type": "Feature",
  "properties": {
    "gn:admin1_code":"35.0",
    "gn:asciiname":"Medawelagama",
    "gn:country_code":"LK",
    "gn:dem":987,
    "gn:feature_class":"P",
    "gn:feature_code":"PPL",
    "gn:name":"Medawelagama",
    "gn:population":0,
    "gn:timezone":"Asia/Colombo",
    "iso:country":"LK",
    "name:und_x_variant":[
        "Medawela"
    ],
    "wof:name":"Medawelagama",
    "wof:placetype":"locality"
},
  "geometry": {"coordinates":[81.1712,6.976],"type":"Point"}
}