{
  "type": "Feature",
  "properties": {
    "gn:admin1_code":"37.0",
    "gn:asciiname":"Malaimuntal",
    "gn:country_code":"LK",
    "gn:dem":8,
    "gn:feature_class":"P",
    "gn:feature_code":"PPL",
    "gn:name":"Malaimuntal",
    "gn:population":0,
    "gn:timezone":"Asia/Colombo",
    "iso:country":"LK",
    "name:und_x_variant":[
        "Malaimunthal",
        "Malaimuntal"
    ],
    "wof:name":"Malaimuntal",
    "wof:placetype":"locality"
},
  "geometry": {"coordinates":[81.36667,8.43333],"type":"Point"}
}