{
  "type": "Feature",
  "properties": {
    "gn:admin1_code":"32.0",
    "gn:asciiname":"Tambagalla",
    "gn:country_code":"LK",
    "gn:dem":93,
    "gn:feature_class":"P",
    "gn:feature_code":"PPL",
    "gn:name":"Tambagalla",
    "gn:population":0,
    "gn:timezone":"Asia/Colombo",
    "iso:country":"LK",
    "wof:name":"Tambagalla",
    "wof:placetype":"locality"
},
  "geometry": {"coordinates":[80.3291,7.6656],"type":"Point"}
}