{
  "type": "Feature",
  "properties": {
    "gn:admin1_code":"29.0",
    "gn:asciiname":"Kirindiketiya",
    "gn:country_code":"LK",
    "gn:dem":396,
    "gn:feature_class":"P",
    "gn:feature_code":"PPL",
    "gn:name":"Kirindiketiya",
    "gn:population":0,
    "gn:timezone":"Asia/Colombo",
    "iso:country":"LK",
    "wof:name":"Kirindiketiya",
    "wof:placetype":"locality"
},
  "geometry": {"coordinates":[80.83333,7.51667],"type":"Point"}
}