{
  "type": "Feature",
  "properties": {
    "gn:admin1_code":"33.0",
    "gn:asciiname":"Katugaha",
    "gn:country_code":"LK",
    "gn:dem":230,
    "gn:feature_class":"P",
    "gn:feature_code":"PPL",
    "gn:name":"Katugaha",
    "gn:population":0,
    "gn:timezone":"Asia/Colombo",
    "iso:country":"LK",
    "wof:name":"Katugaha",
    "wof:placetype":"locality"
},
  "geometry": {"coordinates":[80.45,7.21667],"type":"Point"}
}