{
  "type": "Feature",
  "properties": {
    "gn:admin1_code":"38.0",
    "gn:asciiname":"Pokkarvanni",
    "gn:country_code":"LK",
    "gn:dem":73,
    "gn:feature_class":"P",
    "gn:feature_code":"PPL",
    "gn:name":"Pokkarvanni",
    "gn:population":0,
    "gn:timezone":"Asia/Colombo",
    "iso:country":"LK",
    "name:und_x_variant":[
        "Pokkarranni",
        "Pokkarvanni"
    ],
    "wof:name":"Pokkarvanni",
    "wof:placetype":"locality"
},
  "geometry": {"coordinates":[80.31667,8.86667],"type":"Point"}
}