{
  "type": "Feature",
  "properties": {
    "gn:admin1_code":"29.0",
    "gn:asciiname":"Ambagamuwa",
    "gn:country_code":"LK",
    "gn:dem":632,
    "gn:feature_class":"P",
    "gn:feature_code":"PPL",
    "gn:name":"Ambagamuwa",
    "gn:population":0,
    "gn:timezone":"Asia/Colombo",
    "iso:country":"LK",
    "wof:name":"Ambagamuwa",
    "wof:placetype":"locality"
},
  "geometry": {"coordinates":[80.4875,7.0132],"type":"Point"}
}