{
  "type": "Feature",
  "properties": {
    "gn:admin1_code":"33.0",
    "gn:asciiname":"Sitakele",
    "gn:country_code":"LK",
    "gn:dem":546,
    "gn:feature_class":"P",
    "gn:feature_code":"PPL",
    "gn:name":"Sitakele",
    "gn:population":0,
    "gn:timezone":"Asia/Colombo",
    "iso:country":"LK",
    "wof:name":"Sitakele",
    "wof:placetype":"locality"
},
  "geometry": {"coordinates":[80.6705,6.6098],"type":"Point"}
}