{
  "type": "Feature",
  "properties": {
    "gn:admin1_code":"33.0",
    "gn:asciiname":"Epalawa",
    "gn:country_code":"LK",
    "gn:dem":314,
    "gn:feature_class":"P",
    "gn:feature_code":"PPL",
    "gn:name":"Epalawa",
    "gn:population":0,
    "gn:timezone":"Asia/Colombo",
    "iso:country":"LK",
    "wof:name":"Epalawa",
    "wof:placetype":"locality"
},
  "geometry": {"coordinates":[80.41930000000001,7.2071],"type":"Point"}
}