{
  "type": "Feature",
  "properties": {
    "gn:admin1_code":"37.0",
    "gn:asciiname":"Bandaraduwa",
    "gn:country_code":"LK",
    "gn:dem":41,
    "gn:feature_class":"P",
    "gn:feature_code":"PPL",
    "gn:name":"Bandaraduwa",
    "gn:population":0,
    "gn:timezone":"Asia/Colombo",
    "iso:country":"LK",
    "wof:name":"Bandaraduwa",
    "wof:placetype":"locality"
},
  "geometry": {"coordinates":[81.56667,7.43333],"type":"Point"}
}