{
  "type": "Feature",
  "properties": {
    "gn:admin1_code":"38.0",
    "gn:asciiname":"Putukkulam",
    "gn:country_code":"LK",
    "gn:dem":10,
    "gn:feature_class":"P",
    "gn:feature_code":"PPL",
    "gn:name":"Putukkulam",
    "gn:population":0,
    "gn:timezone":"Asia/Colombo",
    "iso:country":"LK",
    "name:und_x_variant":[
        "Puthukulam",
        "Puthukkulam",
        "Putukkulam"
    ],
    "wof:name":"Putukkulam",
    "wof:placetype":"locality"
},
  "geometry": {"coordinates":[80.09999999999999,9.03333],"type":"Point"}
}