{
  "type": "Feature",
  "properties": {
    "gn:admin1_code":"32.0",
    "gn:asciiname":"Ipalogama",
    "gn:country_code":"LK",
    "gn:dem":61,
    "gn:feature_class":"P",
    "gn:feature_code":"PPL",
    "gn:name":"Ipalogama",
    "gn:population":0,
    "gn:timezone":"Asia/Colombo",
    "iso:country":"LK",
    "name:und_x_variant":[
        "Ipologama"
    ],
    "wof:name":"Ipalogama",
    "wof:placetype":"locality"
},
  "geometry": {"coordinates":[80.0986,8.1193],"type":"Point"}
}