{
  "type": "Feature",
  "properties": {
    "gn:admin1_code":"38.0",
    "gn:asciiname":"Chavakachcheri",
    "gn:country_code":"LK",
    "gn:dem":8,
    "gn:feature_class":"P",
    "gn:feature_code":"PPL",
    "gn:name":"Chavakachcheri",
    "gn:population":0,
    "gn:timezone":"Asia/Colombo",
    "iso:country":"LK",
    "name:und_x_variant":[
        "Chavakacheri",
        "Chavakachcheri"
    ],
    "wof:name":"Chavakachcheri",
    "wof:placetype":"locality"
},
  "geometry": {"coordinates":[80.15100000000002,9.66],"type":"Point"}
}