{
  "type": "Feature",
  "properties": {
    "gn:admin1_code":"38.0",
    "gn:asciiname":"Chavakachcheri",
    "gn:country_code":"LK",
    "gn:dem":8,
    "gn:feature_class":"P",
    "gn:feature_code":"PPL",
    "gn:name":"Chavakachcheri",
    "gn:population":0,
    "gn:timezone":"Asia/Colombo",
    "iso:country":"LK",
    "name:ceb_x_preferred":[
        "Chavakachcheri"
    ],
    "name:deu_x_preferred":[
        "Chavakacheri"
    ],
    "name:epo_x_preferred":[
        "\u0108avaka\u0109eri"
    ],
    "name:fas_x_preferred":[
        "\u0686\u0627\u0648\u0627\u06a9\u0627\u0686\u0631\u06cc"
    ],
    "name:fra_x_preferred":[
        "Chavakacheri"
    ],
    "name:lit_x_preferred":[
        "\u010cavaka\u010deris"
    ],
    "name:mal_x_preferred":[
        "\u0d1a\u0d3e\u0d35\u0d15\u0d4d\u0d15\u0d1a\u0d4d\u0d1a\u0d47\u0d30\u0d3f"
    ],
    "name:pol_x_preferred":[
        "Chavakacheri"
    ],
    "name:sin_x_preferred":[
        "\u0da0\u0dcf\u0dc0\u0d9a\u0da0\u0dca\u0da0\u0dda\u0dbb\u0dd2"
    ],
    "name:spa_x_preferred":[
        "Chavakacheri"
    ],
    "name:swe_x_preferred":[
        "Chavakachcheri"
    ],
    "name:tam_x_preferred":[
        "\u0b9a\u0bbe\u0bb5\u0b95\u0b9a\u0bcd\u0b9a\u0bc7\u0bb0\u0bbf"
    ],
    "name:und_x_variant":[
        "Chavakacheri",
        "Chavakachcheri"
    ],
    "name:urd_x_preferred":[
        "\u0686\u0627\u0648\u0627\u06a9\u0627\u0686\u0686\u06cc\u0631\u06cc"
    ],
    "wof:name":"Chavakachcheri",
    "wof:placetype":"locality"
},
  "geometry": {"coordinates":[80.15100000000002,9.66],"type":"Point"}
}