{
  "type": "Feature",
  "properties": {
    "gn:admin1_code":"34.0",
    "gn:asciiname":"Maragaswathugoda",
    "gn:country_code":"LK",
    "gn:dem":53,
    "gn:feature_class":"P",
    "gn:feature_code":"PPL",
    "gn:name":"Maragaswathugoda",
    "gn:population":0,
    "gn:timezone":"Asia/Colombo",
    "iso:country":"LK",
    "wof:name":"Maragaswathugoda",
    "wof:placetype":"locality"
},
  "geometry": {"coordinates":[80.6966,6.1063],"type":"Point"}
}