{
  "type": "Feature",
  "properties": {
    "gn:admin1_code":"29.0",
    "gn:asciiname":"Samarakonehena",
    "gn:country_code":"LK",
    "gn:dem":714,
    "gn:feature_class":"P",
    "gn:feature_code":"PPL",
    "gn:name":"Samarakonehena",
    "gn:population":0,
    "gn:timezone":"Asia/Colombo",
    "iso:country":"LK",
    "wof:name":"Samarakonehena",
    "wof:placetype":"locality"
},
  "geometry": {"coordinates":[80.6198,7.1759],"type":"Point"}
}