{
  "type": "Feature",
  "properties": {
    "gn:admin1_code":"29.0",
    "gn:asciiname":"Merigwatta",
    "gn:country_code":"LK",
    "gn:dem":912,
    "gn:feature_class":"P",
    "gn:feature_code":"PPL",
    "gn:name":"Merigwatta",
    "gn:population":0,
    "gn:timezone":"Asia/Colombo",
    "iso:country":"LK",
    "wof:name":"Merigwatta",
    "wof:placetype":"locality"
},
  "geometry": {"coordinates":[80.6897,7.4104],"type":"Point"}
}