{
  "type": "Feature",
  "properties": {
    "gn:admin1_code":"30.0",
    "gn:asciiname":"Elapatwewa",
    "gn:country_code":"LK",
    "gn:dem":71,
    "gn:feature_class":"P",
    "gn:feature_code":"PPL",
    "gn:name":"Elapatwewa",
    "gn:population":0,
    "gn:timezone":"Asia/Colombo",
    "iso:country":"LK",
    "wof:name":"Elapatwewa",
    "wof:placetype":"locality"
},
  "geometry": {"coordinates":[80.4033,8.5405],"type":"Point"}
}