{
  "type": "Feature",
  "properties": {
    "gn:admin1_code":"36.0",
    "gn:asciiname":"Yakupitiya",
    "gn:country_code":"LK",
    "gn:dem":77,
    "gn:feature_class":"P",
    "gn:feature_code":"PPL",
    "gn:name":"Yakupitiya",
    "gn:population":0,
    "gn:timezone":"Asia/Colombo",
    "iso:country":"LK",
    "wof:name":"Yakupitiya",
    "wof:placetype":"locality"
},
  "geometry": {"coordinates":[80.1957,6.5177],"type":"Point"}
}