{
  "type": "Feature",
  "properties": {
    "gn:admin1_code":"35.0",
    "gn:asciiname":"Weliarawa",
    "gn:country_code":"LK",
    "gn:dem":924,
    "gn:feature_class":"P",
    "gn:feature_code":"PPL",
    "gn:name":"Weliarawa",
    "gn:population":0,
    "gn:timezone":"Asia/Colombo",
    "iso:country":"LK",
    "wof:name":"Weliarawa",
    "wof:placetype":"locality"
},
  "geometry": {"coordinates":[80.952,6.9548],"type":"Point"}
}