{
  "type": "Feature",
  "properties": {
    "gn:admin1_code":"29.0",
    "gn:asciiname":"Kahawatugoda",
    "gn:country_code":"LK",
    "gn:dem":532,
    "gn:feature_class":"P",
    "gn:feature_code":"PPL",
    "gn:name":"Kahawatugoda",
    "gn:population":0,
    "gn:timezone":"Asia/Colombo",
    "iso:country":"LK",
    "wof:name":"Kahawatugoda",
    "wof:placetype":"locality"
},
  "geometry": {"coordinates":[80.55,7.28333],"type":"Point"}
}