{
  "type": "Feature",
  "properties": {
    "gn:admin1_code":"30.0",
    "gn:asciiname":"Mudunnegama",
    "gn:country_code":"LK",
    "gn:dem":104,
    "gn:feature_class":"P",
    "gn:feature_code":"PPL",
    "gn:name":"Mudunnegama",
    "gn:population":0,
    "gn:timezone":"Asia/Colombo",
    "iso:country":"LK",
    "wof:name":"Mudunnegama",
    "wof:placetype":"locality"
},
  "geometry": {"coordinates":[80.3103,8.2284],"type":"Point"}
}