{
  "type": "Feature",
  "properties": {
    "gn:admin1_code":"36.0",
    "gn:asciiname":"Thimbirigama",
    "gn:country_code":"LK",
    "gn:dem":49,
    "gn:feature_class":"P",
    "gn:feature_code":"PPL",
    "gn:name":"Thimbirigama",
    "gn:population":0,
    "gn:timezone":"Asia/Colombo",
    "iso:country":"LK",
    "name:und_x_variant":[
        "Timbirigama"
    ],
    "wof:name":"Thimbirigama",
    "wof:placetype":"locality"
},
  "geometry": {"coordinates":[80.1343,7.0649],"type":"Point"}
}