{
  "type": "Feature",
  "properties": {
    "gn:admin1_code":"38.0",
    "gn:asciiname":"Putukulam",
    "gn:country_code":"LK",
    "gn:dem":62,
    "gn:feature_class":"P",
    "gn:feature_code":"PPL",
    "gn:name":"Putukulam",
    "gn:population":0,
    "gn:timezone":"Asia/Colombo",
    "iso:country":"LK",
    "name:und_x_variant":[
        "Puthukulam",
        "Putukkulam"
    ],
    "wof:name":"Putukulam",
    "wof:placetype":"locality"
},
  "geometry": {"coordinates":[80.49250000000001,9.0955],"type":"Point"}
}