{
  "type": "Feature",
  "properties": {
    "gn:admin1_code":"32.0",
    "gn:asciiname":"Awaragodawatta",
    "gn:country_code":"LK",
    "gn:dem":72,
    "gn:feature_class":"P",
    "gn:feature_code":"PPL",
    "gn:name":"Awaragodawatta",
    "gn:population":0,
    "gn:timezone":"Asia/Colombo",
    "iso:country":"LK",
    "wof:name":"Awaragodawatta",
    "wof:placetype":"locality"
},
  "geometry": {"coordinates":[80.1327,7.395],"type":"Point"}
}