{
  "type": "Feature",
  "properties": {
    "gn:admin1_code":"34.0",
    "gn:asciiname":"Banwelgodella",
    "gn:country_code":"LK",
    "gn:dem":23,
    "gn:feature_class":"P",
    "gn:feature_code":"PPL",
    "gn:name":"Banwelgodella",
    "gn:population":0,
    "gn:timezone":"Asia/Colombo",
    "iso:country":"LK",
    "wof:name":"Banwelgodella",
    "wof:placetype":"locality"
},
  "geometry": {"coordinates":[80.1353,6.1845],"type":"Point"}
}