{
  "type": "Feature",
  "properties": {
    "gn:admin1_code":"35.0",
    "gn:asciiname":"Maragalawatta",
    "gn:country_code":"LK",
    "gn:dem":418,
    "gn:feature_class":"P",
    "gn:feature_code":"PPL",
    "gn:name":"Maragalawatta",
    "gn:population":0,
    "gn:timezone":"Asia/Colombo",
    "iso:country":"LK",
    "wof:name":"Maragalawatta",
    "wof:placetype":"locality"
},
  "geometry": {"coordinates":[81.3676,6.8785],"type":"Point"}
}