{
  "type": "Feature",
  "properties": {
    "gn:admin1_code":"33.0",
    "gn:asciiname":"Wewawatta",
    "gn:country_code":"LK",
    "gn:dem":530,
    "gn:feature_class":"P",
    "gn:feature_code":"PPL",
    "gn:name":"Wewawatta",
    "gn:population":0,
    "gn:timezone":"Asia/Colombo",
    "iso:country":"LK",
    "wof:name":"Wewawatta",
    "wof:placetype":"locality"
},
  "geometry": {"coordinates":[80.69110000000001,6.6705],"type":"Point"}
}