{
  "type": "Feature",
  "properties": {
    "gn:admin1_code":"35.0",
    "gn:asciiname":"Kadadoragama",
    "gn:country_code":"LK",
    "gn:dem":1151,
    "gn:feature_class":"P",
    "gn:feature_code":"PPL",
    "gn:name":"Kadadoragama",
    "gn:population":0,
    "gn:timezone":"Asia/Colombo",
    "iso:country":"LK",
    "wof:name":"Kadadoragama",
    "wof:placetype":"locality"
},
  "geometry": {"coordinates":[80.8882,6.9429],"type":"Point"}
}