{
  "type": "Feature",
  "properties": {
    "gn:admin1_code":"34.0",
    "gn:asciiname":"Bandaramulla",
    "gn:cc2":"LK",
    "gn:country_code":"LK",
    "gn:dem":8,
    "gn:feature_class":"P",
    "gn:feature_code":"PPL",
    "gn:name":"Bandaramulla",
    "gn:population":0,
    "gn:timezone":"Asia/Colombo",
    "iso:country":"LK",
    "name:und_x_variant":[
        "Banduramulla",
        "Bandaramulla"
    ],
    "wof:name":"Bandaramulla",
    "wof:placetype":"locality"
},
  "geometry": {"coordinates":[80.46666999999999,5.95],"type":"Point"}
}