{
  "type": "Feature",
  "properties": {
    "gn:admin1_code":"33.0",
    "gn:asciiname":"Endiriyanwala",
    "gn:country_code":"LK",
    "gn:dem":200,
    "gn:feature_class":"P",
    "gn:feature_code":"PPL",
    "gn:name":"Endiriyanwala",
    "gn:population":0,
    "gn:timezone":"Asia/Colombo",
    "iso:country":"LK",
    "wof:name":"Endiriyanwala",
    "wof:placetype":"locality"
},
  "geometry": {"coordinates":[80.36539999999999,6.8311],"type":"Point"}
}