{
  "type": "Feature",
  "properties": {
    "gn:admin1_code":"32.0",
    "gn:asciiname":"Muttetupattuwa",
    "gn:country_code":"LK",
    "gn:dem":27,
    "gn:feature_class":"P",
    "gn:feature_code":"PPL",
    "gn:name":"Muttetupattuwa",
    "gn:population":0,
    "gn:timezone":"Asia/Colombo",
    "iso:country":"LK",
    "name:und_x_variant":[
        "Muttettupatuwa",
        "Muttetupattuwa"
    ],
    "wof:name":"Muttetupattuwa",
    "wof:placetype":"locality"
},
  "geometry": {"coordinates":[79.99639999999999,7.5492],"type":"Point"}
}