{
  "type": "Feature",
  "properties": {
    "gn:admin1_code":"33.0",
    "gn:asciiname":"Madam",
    "gn:country_code":"LK",
    "gn:dem":821,
    "gn:feature_class":"P",
    "gn:feature_code":"PPL",
    "gn:name":"Madam",
    "gn:population":0,
    "gn:timezone":"Asia/Colombo",
    "iso:country":"LK",
    "wof:name":"Madam",
    "wof:placetype":"locality"
},
  "geometry": {"coordinates":[80.444,6.8258],"type":"Point"}
}