{
  "type": "Feature",
  "properties": {
    "gn:admin1_code":"35.0",
    "gn:asciiname":"Galanda",
    "gn:country_code":"LK",
    "gn:dem":829,
    "gn:feature_class":"P",
    "gn:feature_code":"PPL",
    "gn:name":"Galanda",
    "gn:population":0,
    "gn:timezone":"Asia/Colombo",
    "iso:country":"LK",
    "name:por_x_preferred":[
        "Galanda"
    ],
    "name:und_x_variant":[
        "Galauda",
        "Galanda",
        "Galaudagama"
    ],
    "name:vie_x_preferred":[
        "Galanda"
    ],
    "wof:name":"Galanda",
    "wof:placetype":"locality"
},
  "geometry": {"coordinates":[80.98609999999999,7.034],"type":"Point"}
}