{
  "type": "Feature",
  "properties": {
    "gn:admin1_code":"37.0",
    "gn:asciiname":"Veranativu",
    "gn:country_code":"LK",
    "gn:dem":6,
    "gn:feature_class":"P",
    "gn:feature_code":"PPL",
    "gn:name":"Veranativu",
    "gn:population":0,
    "gn:timezone":"Asia/Colombo",
    "iso:country":"LK",
    "name:und_x_variant":[
        "Verantivu",
        "Veranativa",
        "Veranativu"
    ],
    "wof:name":"Veranativu",
    "wof:placetype":"locality"
},
  "geometry": {"coordinates":[81.43333,8.08333],"type":"Point"}
}