{
  "type": "Feature",
  "properties": {
    "gn:admin1_code":"33.0",
    "gn:asciiname":"Pahala Thambawita",
    "gn:country_code":"LK",
    "gn:dem":443,
    "gn:feature_class":"P",
    "gn:feature_code":"PPL",
    "gn:name":"Pahala Thambawita",
    "gn:population":0,
    "gn:timezone":"Asia/Colombo",
    "iso:country":"LK",
    "name:und_x_variant":[
        "Tambawita"
    ],
    "wof:name":"Pahala Thambawita",
    "wof:placetype":"locality"
},
  "geometry": {"coordinates":[80.51479999999999,7.1821],"type":"Point"}
}