{
  "type": "Feature",
  "properties": {
    "gn:admin1_code":"32.0",
    "gn:asciiname":"Bimpokuna Wehera",
    "gn:country_code":"LK",
    "gn:dem":129,
    "gn:feature_class":"P",
    "gn:feature_code":"PPL",
    "gn:name":"Bimpokuna Wehera",
    "gn:population":0,
    "gn:timezone":"Asia/Colombo",
    "iso:country":"LK",
    "name:und_x_variant":[
        "Binpokuna Vihare",
        "Bimpokuna Wehera",
        "Binpokunu Vihare"
    ],
    "wof:name":"Bimpokuna Wehera",
    "wof:placetype":"locality"
},
  "geometry": {"coordinates":[80.3313,7.9851],"type":"Point"}
}