{
  "type": "Feature",
  "properties": {
    "gn:admin1_code":"29.0",
    "gn:asciiname":"Koholdeniya",
    "gn:country_code":"LK",
    "gn:dem":755,
    "gn:feature_class":"P",
    "gn:feature_code":"PPL",
    "gn:name":"Koholdeniya",
    "gn:population":0,
    "gn:timezone":"Asia/Colombo",
    "iso:country":"LK",
    "name:und_x_variant":[
        "Kohodeniya",
        "Koholdeniya"
    ],
    "wof:name":"Koholdeniya",
    "wof:placetype":"locality"
},
  "geometry": {"coordinates":[80.6597,7.0483],"type":"Point"}
}