{
  "type": "Feature",
  "properties": {
    "gn:admin1_code":"32.0",
    "gn:asciiname":"Pahala Potanegama",
    "gn:country_code":"LK",
    "gn:dem":71,
    "gn:feature_class":"P",
    "gn:feature_code":"PPL",
    "gn:name":"Pahala Potanegama",
    "gn:population":0,
    "gn:timezone":"Asia/Colombo",
    "iso:country":"LK",
    "wof:name":"Pahala Potanegama",
    "wof:placetype":"locality"
},
  "geometry": {"coordinates":[80.15000000000001,8.13333],"type":"Point"}
}