{
  "type": "Feature",
  "properties": {
    "gn:admin1_code":"32.0",
    "gn:asciiname":"Medagodayagama",
    "gn:country_code":"LK",
    "gn:dem":129,
    "gn:feature_class":"P",
    "gn:feature_code":"PPL",
    "gn:name":"Medagodayagama",
    "gn:population":0,
    "gn:timezone":"Asia/Colombo",
    "iso:country":"LK",
    "wof:name":"Medagodayagama",
    "wof:placetype":"locality"
},
  "geometry": {"coordinates":[80.34999999999999,7.86667],"type":"Point"}
}