{
  "type": "Feature",
  "properties": {
    "gn:admin1_code":"29.0",
    "gn:asciiname":"Kurakolayaya",
    "gn:country_code":"LK",
    "gn:dem":463,
    "gn:feature_class":"P",
    "gn:feature_code":"PPL",
    "gn:name":"Kurakolayaya",
    "gn:population":0,
    "gn:timezone":"Asia/Colombo",
    "iso:country":"LK",
    "wof:name":"Kurakolayaya",
    "wof:placetype":"locality"
},
  "geometry": {"coordinates":[80.58669999999999,7.5435],"type":"Point"}
}