{
  "type": "Feature",
  "properties": {
    "gn:admin1_code":"32.0",
    "gn:asciiname":"Hettigama",
    "gn:country_code":"LK",
    "gn:dem":116,
    "gn:feature_class":"P",
    "gn:feature_code":"PPL",
    "gn:name":"Hettigama",
    "gn:population":0,
    "gn:timezone":"Asia/Colombo",
    "iso:country":"LK",
    "wof:name":"Hettigama",
    "wof:placetype":"locality"
},
  "geometry": {"coordinates":[80.3323,7.9903],"type":"Point"}
}