{
  "type": "Feature",
  "properties": {
    "gn:admin1_code":"35.0",
    "gn:asciiname":"Kandauda Panguwa",
    "gn:country_code":"LK",
    "gn:dem":107,
    "gn:feature_class":"P",
    "gn:feature_code":"PPL",
    "gn:name":"Kandauda Panguwa",
    "gn:population":0,
    "gn:timezone":"Asia/Colombo",
    "iso:country":"LK",
    "wof:name":"Kandauda Panguwa",
    "wof:placetype":"locality"
},
  "geometry": {"coordinates":[81.5341,6.9841],"type":"Point"}
}