{
  "type": "Feature",
  "properties": {
    "gn:admin1_code":"32.0",
    "gn:asciiname":"Budumuttawa",
    "gn:country_code":"LK",
    "gn:dem":43,
    "gn:feature_class":"P",
    "gn:feature_code":"PPL",
    "gn:name":"Budumuttawa",
    "gn:population":0,
    "gn:timezone":"Asia/Colombo",
    "iso:country":"LK",
    "wof:name":"Budumuttawa",
    "wof:placetype":"locality"
},
  "geometry": {"coordinates":[80.09999999999999,7.75],"type":"Point"}
}