{
  "type": "Feature",
  "properties": {
    "gn:admin1_code":"33.0",
    "gn:asciiname":"Bogahakumburugoda",
    "gn:country_code":"LK",
    "gn:dem":280,
    "gn:feature_class":"P",
    "gn:feature_code":"PPL",
    "gn:name":"Bogahakumburugoda",
    "gn:population":0,
    "gn:timezone":"Asia/Colombo",
    "iso:country":"LK",
    "wof:name":"Bogahakumburugoda",
    "wof:placetype":"locality"
},
  "geometry": {"coordinates":[80.6515,6.5852],"type":"Point"}
}