{
  "type": "Feature",
  "properties": {
    "gn:admin1_code":"30.0",
    "gn:asciiname":"Kuratiyawa",
    "gn:country_code":"LK",
    "gn:dem":121,
    "gn:feature_class":"P",
    "gn:feature_code":"PPL",
    "gn:name":"Kuratiyawa",
    "gn:population":0,
    "gn:timezone":"Asia/Colombo",
    "iso:country":"LK",
    "wof:name":"Kuratiyawa",
    "wof:placetype":"locality"
},
  "geometry": {"coordinates":[80.56570000000001,8.6121],"type":"Point"}
}