{
  "type": "Feature",
  "properties": {
    "gn:admin1_code":"30.0",
    "gn:asciiname":"Diyabeduma",
    "gn:country_code":"LK",
    "gn:dem":95,
    "gn:feature_class":"P",
    "gn:feature_code":"PPL",
    "gn:name":"Diyabeduma",
    "gn:population":0,
    "gn:timezone":"Asia/Colombo",
    "iso:country":"LK",
    "wof:name":"Diyabeduma",
    "wof:placetype":"locality"
},
  "geometry": {"coordinates":[80.88333,7.88333],"type":"Point"}
}