{
  "type": "Feature",
  "properties": {
    "gn:admin1_code":"33.0",
    "gn:asciiname":"Kottapola",
    "gn:country_code":"LK",
    "gn:dem":182,
    "gn:feature_class":"P",
    "gn:feature_code":"PPL",
    "gn:name":"Kottapola",
    "gn:population":0,
    "gn:timezone":"Asia/Colombo",
    "iso:country":"LK",
    "wof:name":"Kottapola",
    "wof:placetype":"locality"
},
  "geometry": {"coordinates":[80.30029999999999,7.2079],"type":"Point"}
}