{
  "type": "Feature",
  "properties": {
    "gn:admin1_code":"36.0",
    "gn:asciiname":"Dambore",
    "gn:country_code":"LK",
    "gn:dem":104,
    "gn:feature_class":"P",
    "gn:feature_code":"PPL",
    "gn:name":"Dambore",
    "gn:population":0,
    "gn:timezone":"Asia/Colombo",
    "iso:country":"LK",
    "wof:name":"Dambore",
    "wof:placetype":"locality"
},
  "geometry": {"coordinates":[80.1658,6.8442],"type":"Point"}
}