{
  "type": "Feature",
  "properties": {
    "gn:admin1_code":"33.0",
    "gn:asciiname":"Walgama",
    "gn:country_code":"LK",
    "gn:dem":174,
    "gn:feature_class":"P",
    "gn:feature_code":"PPL",
    "gn:name":"Walgama",
    "gn:population":0,
    "gn:timezone":"Asia/Colombo",
    "iso:country":"LK",
    "wof:name":"Walgama",
    "wof:placetype":"locality"
},
  "geometry": {"coordinates":[80.3477,7.3477],"type":"Point"}
}