{
  "type": "Feature",
  "properties": {
    "gn:admin1_code":"32.0",
    "gn:asciiname":"Kitaramulla",
    "gn:country_code":"LK",
    "gn:dem":32,
    "gn:feature_class":"P",
    "gn:feature_code":"PPL",
    "gn:name":"Kitaramulla",
    "gn:population":0,
    "gn:timezone":"Asia/Colombo",
    "iso:country":"LK",
    "name:und_x_variant":[
        "Kitarammulla",
        "Kitaramulla"
    ],
    "wof:name":"Kitaramulla",
    "wof:placetype":"locality"
},
  "geometry": {"coordinates":[80.0343,7.5693],"type":"Point"}
}