{
  "type": "Feature",
  "properties": {
    "gn:admin1_code":"36.0",
    "gn:asciiname":"Welikada",
    "gn:country_code":"LK",
    "gn:dem":18,
    "gn:feature_class":"P",
    "gn:feature_code":"PPL",
    "gn:name":"Welikada",
    "gn:population":0,
    "gn:timezone":"Asia/Colombo",
    "iso:country":"LK",
    "name:sin_x_preferred":[
        "\u0dc0\u0dd0\u0dbd\u0dd2\u0d9a\u0da9"
    ],
    "wof:name":"Welikada",
    "wof:placetype":"locality"
},
  "geometry": {"coordinates":[79.9466,7.0925],"type":"Point"}
}