{
  "type": "Feature",
  "properties": {
    "gn:admin1_code":"35.0",
    "gn:asciiname":"Godahena",
    "gn:country_code":"LK",
    "gn:dem":543,
    "gn:feature_class":"P",
    "gn:feature_code":"PPL",
    "gn:name":"Godahena",
    "gn:population":0,
    "gn:timezone":"Asia/Colombo",
    "iso:country":"LK",
    "wof:name":"Godahena",
    "wof:placetype":"locality"
},
  "geometry": {"coordinates":[81.0638,7.0907],"type":"Point"}
}