{
  "type": "Feature",
  "properties": {
    "gn:admin1_code":"29.0",
    "gn:asciiname":"Rathmeltiya Colony",
    "gn:country_code":"LK",
    "gn:dem":902,
    "gn:feature_class":"P",
    "gn:feature_code":"PPL",
    "gn:name":"Rathmeltiya Colony",
    "gn:population":0,
    "gn:timezone":"Asia/Colombo",
    "iso:country":"LK",
    "wof:name":"Rathmeltiya Colony",
    "wof:placetype":"locality"
},
  "geometry": {"coordinates":[80.76139999999999,7.1541],"type":"Point"}
}