{
  "type": "Feature",
  "properties": {
    "gn:admin1_code":"29.0",
    "gn:asciiname":"New Nellumale Watta",
    "gn:country_code":"LK",
    "gn:dem":1133,
    "gn:feature_class":"P",
    "gn:feature_code":"PPL",
    "gn:name":"New Nellumale Watta",
    "gn:population":0,
    "gn:timezone":"Asia/Colombo",
    "iso:country":"LK",
    "wof:name":"New Nellumale Watta",
    "wof:placetype":"locality"
},
  "geometry": {"coordinates":[80.7303,7.4411],"type":"Point"}
}