{
  "type": "Feature",
  "properties": {
    "gn:admin1_code":"36.0",
    "gn:asciiname":"Petiyagoda",
    "gn:country_code":"LK",
    "gn:dem":43,
    "gn:feature_class":"P",
    "gn:feature_code":"PPL",
    "gn:name":"Petiyagoda",
    "gn:population":0,
    "gn:timezone":"Asia/Colombo",
    "iso:country":"LK",
    "name:ceb_x_preferred":[
        "Petiyagoda"
    ],
    "name:swe_x_preferred":[
        "Petiyagoda"
    ],
    "wof:name":"Petiyagoda",
    "wof:placetype":"locality"
},
  "geometry": {"coordinates":[79.99590000000001,7.1378],"type":"Point"}
}