{
  "type": "Feature",
  "properties": {
    "gn:admin1_code":"34.0",
    "gn:asciiname":"Kitulampitiya",
    "gn:country_code":"LK",
    "gn:dem":27,
    "gn:feature_class":"P",
    "gn:feature_code":"PPL",
    "gn:name":"Kitulampitiya",
    "gn:population":0,
    "gn:timezone":"Asia/Colombo",
    "iso:country":"LK",
    "wof:name":"Kitulampitiya",
    "wof:placetype":"locality"
},
  "geometry": {"coordinates":[80.2093,6.0644],"type":"Point"}
}