{
  "type": "Feature",
  "properties": {
    "gn:admin1_code":"35.0",
    "gn:asciiname":"Komarikagama",
    "gn:country_code":"LK",
    "gn:dem":171,
    "gn:feature_class":"P",
    "gn:feature_code":"PPL",
    "gn:name":"Komarikagama",
    "gn:population":0,
    "gn:timezone":"Asia/Colombo",
    "iso:country":"LK",
    "wof:name":"Komarikagama",
    "wof:placetype":"locality"
},
  "geometry": {"coordinates":[81.08450000000001,7.1273],"type":"Point"}
}