{
  "type": "Feature",
  "properties": {
    "gn:admin1_code":"35.0",
    "gn:asciiname":"Unanpitiya",
    "gn:cc2":"LK",
    "gn:country_code":"LK",
    "gn:dem":163,
    "gn:feature_class":"P",
    "gn:feature_code":"PPL",
    "gn:name":"Unanpitiya",
    "gn:population":0,
    "gn:timezone":"Asia/Colombo",
    "iso:country":"LK",
    "name:und_x_variant":[
        "Unampitiya",
        "Unanpitiya"
    ],
    "wof:name":"Unanpitiya",
    "wof:placetype":"locality"
},
  "geometry": {"coordinates":[81.16667,7.26667],"type":"Point"}
}