{
  "type": "Feature",
  "properties": {
    "gn:admin1_code":"36.0",
    "gn:asciiname":"Himbutana",
    "gn:country_code":"LK",
    "gn:dem":10,
    "gn:feature_class":"P",
    "gn:feature_code":"PPL",
    "gn:name":"Himbutana",
    "gn:population":0,
    "gn:timezone":"Asia/Colombo",
    "iso:country":"LK",
    "wof:name":"Himbutana",
    "wof:placetype":"locality"
},
  "geometry": {"coordinates":[79.9312,6.9258],"type":"Point"}
}