{
  "type": "Feature",
  "properties": {
    "gn:admin1_code":"33.0",
    "gn:asciiname":"Samanalawatta",
    "gn:country_code":"LK",
    "gn:dem":922,
    "gn:feature_class":"P",
    "gn:feature_code":"PPL",
    "gn:name":"Samanalawatta",
    "gn:population":0,
    "gn:timezone":"Asia/Colombo",
    "iso:country":"LK",
    "wof:name":"Samanalawatta",
    "wof:placetype":"locality"
},
  "geometry": {"coordinates":[80.61709999999999,6.6746],"type":"Point"}
}