{
  "type": "Feature",
  "properties": {
    "gn:admin1_code":"30.0",
    "gn:asciiname":"Habawewa",
    "gn:country_code":"LK",
    "gn:dem":77,
    "gn:feature_class":"P",
    "gn:feature_code":"PPL",
    "gn:name":"Habawewa",
    "gn:population":0,
    "gn:timezone":"Asia/Colombo",
    "iso:country":"LK",
    "wof:name":"Habawewa",
    "wof:placetype":"locality"
},
  "geometry": {"coordinates":[80.1463,8.3054],"type":"Point"}
}