{
  "type": "Feature",
  "properties": {
    "gn:admin1_code":"32.0",
    "gn:asciiname":"Dalupotayagama",
    "gn:cc2":"LK",
    "gn:country_code":"LK",
    "gn:dem":85,
    "gn:feature_class":"P",
    "gn:feature_code":"PPL",
    "gn:name":"Dalupotayagama",
    "gn:population":0,
    "gn:timezone":"Asia/Colombo",
    "iso:country":"LK",
    "name:und_x_variant":[
        "Dalupoteyagama",
        "Dalupothayagama",
        "Dalupotayagama"
    ],
    "wof:name":"Dalupotayagama",
    "wof:placetype":"locality"
},
  "geometry": {"coordinates":[80.26666999999998,7.81667],"type":"Point"}
}