{
  "type": "Feature",
  "properties": {
    "gn:admin1_code":"34.0",
    "gn:asciiname":"Handugala",
    "gn:country_code":"LK",
    "gn:dem":150,
    "gn:feature_class":"P",
    "gn:feature_code":"PPL",
    "gn:name":"Handugala",
    "gn:population":0,
    "gn:timezone":"Asia/Colombo",
    "iso:country":"LK",
    "wof:name":"Handugala",
    "wof:placetype":"locality"
},
  "geometry": {"coordinates":[80.6193,6.1895],"type":"Point"}
}