{
  "type": "Feature",
  "properties": {
    "gn:admin1_code":"33.0",
    "gn:asciiname":"Selvakanda",
    "gn:country_code":"LK",
    "gn:dem":485,
    "gn:feature_class":"P",
    "gn:feature_code":"PPL",
    "gn:name":"Selvakanda",
    "gn:population":0,
    "gn:timezone":"Asia/Colombo",
    "iso:country":"LK",
    "wof:name":"Selvakanda",
    "wof:placetype":"locality"
},
  "geometry": {"coordinates":[80.67659999999999,6.6258],"type":"Point"}
}