{
  "type": "Feature",
  "properties": {
    "gn:admin1_code":"32.0",
    "gn:asciiname":"Pitadeniya",
    "gn:country_code":"LK",
    "gn:dem":45,
    "gn:feature_class":"P",
    "gn:feature_code":"PPL",
    "gn:name":"Pitadeniya",
    "gn:population":0,
    "gn:timezone":"Asia/Colombo",
    "iso:country":"LK",
    "wof:name":"Pitadeniya",
    "wof:placetype":"locality"
},
  "geometry": {"coordinates":[80.054,7.4299],"type":"Point"}
}