{
  "type": "Feature",
  "properties": {
    "gn:admin1_code":"29.0",
    "gn:asciiname":"Talgahagoda",
    "gn:country_code":"LK",
    "gn:dem":503,
    "gn:feature_class":"P",
    "gn:feature_code":"PPL",
    "gn:name":"Talgahagoda",
    "gn:population":0,
    "gn:timezone":"Asia/Colombo",
    "iso:country":"LK",
    "wof:name":"Talgahagoda",
    "wof:placetype":"locality"
},
  "geometry": {"coordinates":[80.59480000000001,7.4999],"type":"Point"}
}