{
  "type": "Feature",
  "properties": {
    "gn:admin1_code":"37.0",
    "gn:asciiname":"Red Bluff",
    "gn:country_code":"LK",
    "gn:dem":9,
    "gn:feature_class":"P",
    "gn:feature_code":"PPL",
    "gn:name":"Red Bluff",
    "gn:population":0,
    "gn:timezone":"Asia/Colombo",
    "iso:country":"LK",
    "name:ceb_x_preferred":[
        "Red Bluff"
    ],
    "name:deu_x_preferred":[
        "Red Bluff"
    ],
    "name:ita_x_preferred":[
        "Red Bluff"
    ],
    "name:swe_x_preferred":[
        "Red Bluff"
    ],
    "wof:name":"Red Bluff",
    "wof:placetype":"locality"
},
  "geometry": {"coordinates":[81.21666999999999,8.61667],"type":"Point"}
}