{
  "type": "Feature",
  "properties": {
    "gn:admin1_code":"30.0",
    "gn:asciiname":"Ratmalawetiya",
    "gn:country_code":"LK",
    "gn:dem":99,
    "gn:feature_class":"P",
    "gn:feature_code":"PPL",
    "gn:name":"Ratmalawetiya",
    "gn:population":0,
    "gn:timezone":"Asia/Colombo",
    "iso:country":"LK",
    "wof:name":"Ratmalawetiya",
    "wof:placetype":"locality"
},
  "geometry": {"coordinates":[80.688,8.618],"type":"Point"}
}