{
  "type": "Feature",
  "properties": {
    "gn:admin1_code":"33.0",
    "gn:asciiname":"Hakbellawa",
    "gn:country_code":"LK",
    "gn:dem":44,
    "gn:feature_class":"P",
    "gn:feature_code":"PPL",
    "gn:name":"Hakbellawa",
    "gn:population":0,
    "gn:timezone":"Asia/Colombo",
    "iso:country":"LK",
    "wof:name":"Hakbellawa",
    "wof:placetype":"locality"
},
  "geometry": {"coordinates":[80.3219,6.9946],"type":"Point"}
}