{
  "type": "Feature",
  "properties": {
    "gn:admin1_code":"32.0",
    "gn:asciiname":"Thattewa",
    "gn:country_code":"LK",
    "gn:dem":59,
    "gn:feature_class":"P",
    "gn:feature_code":"PPL",
    "gn:name":"Thattewa",
    "gn:population":0,
    "gn:timezone":"Asia/Colombo",
    "iso:country":"LK",
    "name:und_x_variant":[
        "Tattewa",
        "Thattewa"
    ],
    "wof:name":"Thattewa",
    "wof:placetype":"locality"
},
  "geometry": {"coordinates":[79.9854,7.88],"type":"Point"}
}