{
  "type": "Feature",
  "properties": {
    "gn:admin1_code":"34.0",
    "gn:asciiname":"Kambussawala",
    "gn:cc2":"LK",
    "gn:country_code":"LK",
    "gn:dem":59,
    "gn:feature_class":"P",
    "gn:feature_code":"PPL",
    "gn:name":"Kambussawala",
    "gn:population":0,
    "gn:timezone":"Asia/Colombo",
    "iso:country":"LK",
    "name:und_x_variant":[
        "Kambussawela",
        "Kambussawala"
    ],
    "wof:name":"Kambussawala",
    "wof:placetype":"locality"
},
  "geometry": {"coordinates":[80.71666999999999,6.05],"type":"Point"}
}