{
  "type": "Feature",
  "properties": {
    "gn:admin1_code":"32.0",
    "gn:asciiname":"Galissapitiya",
    "gn:cc2":"LK",
    "gn:country_code":"LK",
    "gn:dem":42,
    "gn:feature_class":"P",
    "gn:feature_code":"PPL",
    "gn:name":"Galissapitiya",
    "gn:population":0,
    "gn:timezone":"Asia/Colombo",
    "iso:country":"LK",
    "name:und_x_variant":[
        "Galisapitiya",
        "Galissapitiya"
    ],
    "wof:name":"Galissapitiya",
    "wof:placetype":"locality"
},
  "geometry": {"coordinates":[79.93333,7.55],"type":"Point"}
}