{
  "type": "Feature",
  "properties": {
    "gn:admin1_code":"29.0",
    "gn:asciiname":"Kandegama",
    "gn:country_code":"LK",
    "gn:dem":901,
    "gn:feature_class":"P",
    "gn:feature_code":"PPL",
    "gn:name":"Kandegama",
    "gn:population":0,
    "gn:timezone":"Asia/Colombo",
    "iso:country":"LK",
    "name:ceb_x_preferred":[
        "Kandegama"
    ],
    "name:rus_x_preferred":[
        "\u041a\u0430\u043d\u0434\u0435\u0433\u0430\u043c\u0430"
    ],
    "name:swe_x_preferred":[
        "Kandegama"
    ],
    "wof:name":"Kandegama",
    "wof:placetype":"locality"
},
  "geometry": {"coordinates":[80.84999999999999,7.35],"type":"Point"}
}