{
  "type": "Feature",
  "properties": {
    "gn:admin1_code":"32.0",
    "gn:asciiname":"Mudalpolla",
    "gn:country_code":"LK",
    "gn:dem":90,
    "gn:feature_class":"P",
    "gn:feature_code":"PPL",
    "gn:name":"Mudalpolla",
    "gn:population":0,
    "gn:timezone":"Asia/Colombo",
    "iso:country":"LK",
    "name:und_x_variant":[
        "Mudalpola"
    ],
    "wof:name":"Mudalpolla",
    "wof:placetype":"locality"
},
  "geometry": {"coordinates":[80.3047,7.556],"type":"Point"}
}