{
  "type": "Feature",
  "properties": {
    "gn:admin1_code":"33.0",
    "gn:asciiname":"Hapugoda",
    "gn:country_code":"LK",
    "gn:dem":186,
    "gn:feature_class":"P",
    "gn:feature_code":"PPL",
    "gn:name":"Hapugoda",
    "gn:population":0,
    "gn:timezone":"Asia/Colombo",
    "iso:country":"LK",
    "name:ceb_x_preferred":[
        "Hapugoda"
    ],
    "name:swe_x_preferred":[
        "Hapugoda"
    ],
    "wof:name":"Hapugoda",
    "wof:placetype":"locality"
},
  "geometry": {"coordinates":[80.37,7.3087],"type":"Point"}
}