{
  "type": "Feature",
  "properties": {
    "gn:admin1_code":"29.0",
    "gn:asciiname":"Alawatugama",
    "gn:country_code":"LK",
    "gn:dem":732,
    "gn:feature_class":"P",
    "gn:feature_code":"PPL",
    "gn:name":"Alawatugama",
    "gn:population":0,
    "gn:timezone":"Asia/Colombo",
    "iso:country":"LK",
    "wof:name":"Alawatugama",
    "wof:placetype":"locality"
},
  "geometry": {"coordinates":[80.76649999999999,7.17],"type":"Point"}
}