{
  "type": "Feature",
  "properties": {
    "gn:admin1_code":"30.0",
    "gn:asciiname":"Hiriyalegama",
    "gn:country_code":"LK",
    "gn:dem":98,
    "gn:feature_class":"P",
    "gn:feature_code":"PPL",
    "gn:name":"Hiriyalegama",
    "gn:population":0,
    "gn:timezone":"Asia/Colombo",
    "iso:country":"LK",
    "wof:name":"Hiriyalegama",
    "wof:placetype":"locality"
},
  "geometry": {"coordinates":[80.22239999999999,8.2719],"type":"Point"}
}