{
  "type": "Feature",
  "properties": {
    "gn:admin1_code":"37.0",
    "gn:asciiname":"Vettilaipoddamadu",
    "gn:country_code":"LK",
    "gn:dem":11,
    "gn:feature_class":"P",
    "gn:feature_code":"PPL",
    "gn:name":"Vettilaipoddamadu",
    "gn:population":0,
    "gn:timezone":"Asia/Colombo",
    "iso:country":"LK",
    "name:und_x_variant":[
        "Vettilaipoddanamadu",
        "Vaddipoddamadu",
        "Vettilaipoddamadu"
    ],
    "wof:name":"Vettilaipoddamadu",
    "wof:placetype":"locality"
},
  "geometry": {"coordinates":[81.43333,7.86667],"type":"Point"}
}