{
  "type": "Feature",
  "properties": {
    "gn:admin1_code":"32.0",
    "gn:asciiname":"Ihala Malagane",
    "gn:country_code":"LK",
    "gn:dem":86,
    "gn:feature_class":"P",
    "gn:feature_code":"PPL",
    "gn:name":"Ihala Malagane",
    "gn:population":0,
    "gn:timezone":"Asia/Colombo",
    "iso:country":"LK",
    "name:und_x_variant":[
        "Malagane",
        "Ihala Malagane"
    ],
    "wof:name":"Ihala Malagane",
    "wof:placetype":"locality"
},
  "geometry": {"coordinates":[80.2839,7.6608],"type":"Point"}
}