{
  "type": "Feature",
  "properties": {
    "gn:admin1_code":"35.0",
    "gn:asciiname":"Kavudawa",
    "gn:country_code":"LK",
    "gn:dem":156,
    "gn:feature_class":"P",
    "gn:feature_code":"PPL",
    "gn:name":"Kavudawa",
    "gn:population":0,
    "gn:timezone":"Asia/Colombo",
    "iso:country":"LK",
    "wof:name":"Kavudawa",
    "wof:placetype":"locality"
},
  "geometry": {"coordinates":[81.3738,6.8398],"type":"Point"}
}