{
  "type": "Feature",
  "properties": {
    "gn:admin1_code":"29.0",
    "gn:asciiname":"Gangodapitiya",
    "gn:country_code":"LK",
    "gn:dem":202,
    "gn:feature_class":"P",
    "gn:feature_code":"PPL",
    "gn:name":"Gangodapitiya",
    "gn:population":0,
    "gn:timezone":"Asia/Colombo",
    "iso:country":"LK",
    "wof:name":"Gangodapitiya",
    "wof:placetype":"locality"
},
  "geometry": {"coordinates":[80.47669999999999,7.3905],"type":"Point"}
}