{
  "type": "Feature",
  "properties": {
    "gn:admin1_code":"32.0",
    "gn:asciiname":"Bakmeegolla",
    "gn:country_code":"LK",
    "gn:dem":117,
    "gn:feature_class":"P",
    "gn:feature_code":"PPL",
    "gn:name":"Bakmeegolla",
    "gn:population":0,
    "gn:timezone":"Asia/Colombo",
    "iso:country":"LK",
    "name:und_x_variant":[
        "Bakmigolla"
    ],
    "wof:name":"Bakmeegolla",
    "wof:placetype":"locality"
},
  "geometry": {"coordinates":[80.42789999999999,7.5313],"type":"Point"}
}