{
  "type": "Feature",
  "properties": {
    "gn:admin1_code":"29.0",
    "gn:asciiname":"Tawapitiya",
    "gn:country_code":"LK",
    "gn:dem":522,
    "gn:feature_class":"P",
    "gn:feature_code":"PPL",
    "gn:name":"Tawapitiya",
    "gn:population":0,
    "gn:timezone":"Asia/Colombo",
    "iso:country":"LK",
    "wof:name":"Tawapitiya",
    "wof:placetype":"locality"
},
  "geometry": {"coordinates":[80.51220000000001,7.2834],"type":"Point"}
}