{
  "type": "Feature",
  "properties": {
    "gn:admin1_code":"32.0",
    "gn:asciiname":"Polgahayaya",
    "gn:country_code":"LK",
    "gn:dem":82,
    "gn:feature_class":"P",
    "gn:feature_code":"PPL",
    "gn:name":"Polgahayaya",
    "gn:population":0,
    "gn:timezone":"Asia/Colombo",
    "iso:country":"LK",
    "wof:name":"Polgahayaya",
    "wof:placetype":"locality"
},
  "geometry": {"coordinates":[80.21250000000001,7.4463],"type":"Point"}
}