{
  "type": "Feature",
  "properties": {
    "gn:admin1_code":"30.0",
    "gn:asciiname":"Tract One",
    "gn:country_code":"LK",
    "gn:dem":66,
    "gn:feature_class":"P",
    "gn:feature_code":"PPL",
    "gn:name":"Tract One",
    "gn:population":0,
    "gn:timezone":"Asia/Colombo",
    "iso:country":"LK",
    "name:und_x_variant":[
        "Tract 1"
    ],
    "wof:name":"Tract One",
    "wof:placetype":"locality"
},
  "geometry": {"coordinates":[80.2184,8.1531],"type":"Point"}
}