{
  "type": "Feature",
  "properties": {
    "gn:admin1_code":"35.0",
    "gn:asciiname":"Pussallakanda",
    "gn:country_code":"LK",
    "gn:dem":964,
    "gn:feature_class":"P",
    "gn:feature_code":"PPL",
    "gn:name":"Pussallakanda",
    "gn:population":0,
    "gn:timezone":"Asia/Colombo",
    "iso:country":"LK",
    "name:und_x_variant":[
        "Pussella Kanda"
    ],
    "wof:name":"Pussallakanda",
    "wof:placetype":"locality"
},
  "geometry": {"coordinates":[81.0398,7.0419],"type":"Point"}
}