{
  "type": "Feature",
  "properties": {
    "gn:admin1_code":"29.0",
    "gn:asciiname":"Pottatawela",
    "gn:country_code":"LK",
    "gn:dem":338,
    "gn:feature_class":"P",
    "gn:feature_code":"PPL",
    "gn:name":"Pottatawela",
    "gn:population":0,
    "gn:timezone":"Asia/Colombo",
    "iso:country":"LK",
    "name:tur_x_preferred":[
        "Pottatawela"
    ],
    "wof:name":"Pottatawela",
    "wof:placetype":"locality"
},
  "geometry": {"coordinates":[80.76390000000001,7.5984],"type":"Point"}
}