{
  "type": "Feature",
  "properties": {
    "gn:admin1_code":"36.0",
    "gn:asciiname":"Moraenda",
    "gn:country_code":"LK",
    "gn:dem":5,
    "gn:feature_class":"P",
    "gn:feature_code":"PPL",
    "gn:name":"Moraenda",
    "gn:population":0,
    "gn:timezone":"Asia/Colombo",
    "iso:country":"LK",
    "wof:name":"Moraenda",
    "wof:placetype":"locality"
},
  "geometry": {"coordinates":[79.95100000000002,6.7718],"type":"Point"}
}