{
  "type": "Feature",
  "properties": {
    "gn:admin1_code":"32.0",
    "gn:asciiname":"Karavitaagare West",
    "gn:country_code":"LK",
    "gn:dem":17,
    "gn:feature_class":"P",
    "gn:feature_code":"PPL",
    "gn:name":"Karavitaagare West",
    "gn:population":0,
    "gn:timezone":"Asia/Colombo",
    "iso:country":"LK",
    "wof:name":"Karavitaagare West",
    "wof:placetype":"locality"
},
  "geometry": {"coordinates":[79.8519,7.5629],"type":"Point"}
}