{
  "type": "Feature",
  "properties": {
    "gn:admin1_code":"34.0",
    "gn:asciiname":"Hinatihatamuna",
    "gn:country_code":"LK",
    "gn:dem":40,
    "gn:feature_class":"P",
    "gn:feature_code":"PPL",
    "gn:name":"Hinatihatamuna",
    "gn:population":0,
    "gn:timezone":"Asia/Colombo",
    "iso:country":"LK",
    "wof:name":"Hinatihatamuna",
    "wof:placetype":"locality"
},
  "geometry": {"coordinates":[80.7079,6.1053],"type":"Point"}
}