{
  "type": "Feature",
  "properties": {
    "gn:admin1_code":"34.0",
    "gn:asciiname":"Mandiyagoda",
    "gn:country_code":"LK",
    "gn:dem":67,
    "gn:feature_class":"P",
    "gn:feature_code":"PPL",
    "gn:name":"Mandiyagoda",
    "gn:population":0,
    "gn:timezone":"Asia/Colombo",
    "iso:country":"LK",
    "wof:name":"Mandiyagoda",
    "wof:placetype":"locality"
},
  "geometry": {"coordinates":[80.727,6.1054],"type":"Point"}
}