{
  "type": "Feature",
  "properties": {
    "gn:admin1_code":"36.0",
    "gn:asciiname":"Pahala Mapitigama",
    "gn:country_code":"LK",
    "gn:dem":25,
    "gn:feature_class":"P",
    "gn:feature_code":"PPL",
    "gn:name":"Pahala Mapitigama",
    "gn:population":0,
    "gn:timezone":"Asia/Colombo",
    "iso:country":"LK",
    "name:und_x_variant":[
        "Mapitagama Pahala",
        "Pahala Mapitigama"
    ],
    "wof:name":"Pahala Mapitigama",
    "wof:placetype":"locality"
},
  "geometry": {"coordinates":[80.0311,6.9322],"type":"Point"}
}