{
  "type": "Feature",
  "properties": {
    "gn:admin1_code":"32.0",
    "gn:asciiname":"Gomugomuwa Ihala",
    "gn:country_code":"LK",
    "gn:dem":63,
    "gn:feature_class":"P",
    "gn:feature_code":"PPL",
    "gn:name":"Gomugomuwa Ihala",
    "gn:population":0,
    "gn:timezone":"Asia/Colombo",
    "iso:country":"LK",
    "wof:name":"Gomugomuwa Ihala",
    "wof:placetype":"locality"
},
  "geometry": {"coordinates":[80.0754,7.5135],"type":"Point"}
}