{
  "type": "Feature",
  "properties": {
    "gn:admin1_code":"35.0",
    "gn:asciiname":"Ulpothagama",
    "gn:country_code":"LK",
    "gn:dem":942,
    "gn:feature_class":"P",
    "gn:feature_code":"PPL",
    "gn:name":"Ulpothagama",
    "gn:population":0,
    "gn:timezone":"Asia/Colombo",
    "iso:country":"LK",
    "wof:name":"Ulpothagama",
    "wof:placetype":"locality"
},
  "geometry": {"coordinates":[81.02600000000002,7.0108],"type":"Point"}
}