{
  "type": "Feature",
  "properties": {
    "gn:admin1_code":"33.0",
    "gn:asciiname":"Badulupitiya",
    "gn:country_code":"LK",
    "gn:dem":227,
    "gn:feature_class":"P",
    "gn:feature_code":"PPL",
    "gn:name":"Badulupitiya",
    "gn:population":0,
    "gn:timezone":"Asia/Colombo",
    "iso:country":"LK",
    "wof:name":"Badulupitiya",
    "wof:placetype":"locality"
},
  "geometry": {"coordinates":[80.4558,7.2749],"type":"Point"}
}