{
  "type": "Feature",
  "properties": {
    "gn:admin1_code":"29.0",
    "gn:asciiname":"Yatigammana",
    "gn:country_code":"LK",
    "gn:dem":558,
    "gn:feature_class":"P",
    "gn:feature_code":"PPL",
    "gn:name":"Yatigammana",
    "gn:population":0,
    "gn:timezone":"Asia/Colombo",
    "iso:country":"LK",
    "name:ceb_x_preferred":[
        "Yatigammana"
    ],
    "name:swe_x_preferred":[
        "Yatigammana"
    ],
    "name:urd_x_preferred":[
        "\u06cc\u062a\u06cc\u06af\u0645\u0645\u0646\u0627"
    ],
    "wof:name":"Yatigammana",
    "wof:placetype":"locality"
},
  "geometry": {"coordinates":[80.4995,7.2937],"type":"Point"}
}