{
  "type": "Feature",
  "properties": {
    "gn:admin1_code":"30.0",
    "gn:asciiname":"Nikawewa",
    "gn:country_code":"LK",
    "gn:dem":146,
    "gn:feature_class":"P",
    "gn:feature_code":"PPL",
    "gn:name":"Nikawewa",
    "gn:population":0,
    "gn:timezone":"Asia/Colombo",
    "iso:country":"LK",
    "wof:name":"Nikawewa",
    "wof:placetype":"locality"
},
  "geometry": {"coordinates":[80.73650000000001,8.1292],"type":"Point"}
}