{
  "type": "Feature",
  "properties": {
    "gn:admin1_code":"32.0",
    "gn:asciiname":"Paragammana",
    "gn:country_code":"LK",
    "gn:dem":54,
    "gn:feature_class":"P",
    "gn:feature_code":"PPL",
    "gn:name":"Paragammana",
    "gn:population":0,
    "gn:timezone":"Asia/Colombo",
    "iso:country":"LK",
    "wof:name":"Paragammana",
    "wof:placetype":"locality"
},
  "geometry": {"coordinates":[80.0369,7.4018],"type":"Point"}
}