{
  "type": "Feature",
  "properties": {
    "gn:admin1_code":"33.0",
    "gn:asciiname":"Uda Haupe",
    "gn:country_code":"LK",
    "gn:dem":274,
    "gn:feature_class":"P",
    "gn:feature_code":"PPL",
    "gn:name":"Uda Haupe",
    "gn:population":0,
    "gn:timezone":"Asia/Colombo",
    "iso:country":"LK",
    "wof:name":"Uda Haupe",
    "wof:placetype":"locality"
},
  "geometry": {"coordinates":[80.5401,6.5526],"type":"Point"}
}