{
  "type": "Feature",
  "properties": {
    "gn:admin1_code":"33.0",
    "gn:asciiname":"Moraketiya",
    "gn:country_code":"LK",
    "gn:dem":56,
    "gn:feature_class":"P",
    "gn:feature_code":"PPL",
    "gn:name":"Moraketiya",
    "gn:population":0,
    "gn:timezone":"Asia/Colombo",
    "iso:country":"LK",
    "wof:name":"Moraketiya",
    "wof:placetype":"locality"
},
  "geometry": {"coordinates":[80.86667,6.33333],"type":"Point"}
}