{
  "type": "Feature",
  "properties": {
    "gn:admin1_code":"38.0",
    "gn:asciiname":"Kurukkalputukkulam",
    "gn:country_code":"LK",
    "gn:dem":74,
    "gn:feature_class":"P",
    "gn:feature_code":"PPL",
    "gn:name":"Kurukkalputukkulam",
    "gn:population":0,
    "gn:timezone":"Asia/Colombo",
    "iso:country":"LK",
    "name:und_x_variant":[
        "Kurukkalur",
        "Kurukkalputukkulam",
        "Kurukalputukkulam"
    ],
    "wof:name":"Kurukkalputukkulam",
    "wof:placetype":"locality"
},
  "geometry": {"coordinates":[80.3437,8.7559],"type":"Point"}
}