{
  "type": "Feature",
  "properties": {
    "gn:admin1_code":"35.0",
    "gn:asciiname":"Dunhinda",
    "gn:country_code":"LK",
    "gn:dem":675,
    "gn:feature_class":"P",
    "gn:feature_code":"PPL",
    "gn:name":"Dunhinda",
    "gn:population":0,
    "gn:timezone":"Asia/Colombo",
    "iso:country":"LK",
    "wof:name":"Dunhinda",
    "wof:placetype":"locality"
},
  "geometry": {"coordinates":[81.06229999999999,7.0156],"type":"Point"}
}