{
  "type": "Feature",
  "properties": {
    "gn:admin1_code":"32.0",
    "gn:asciiname":"Pahala Malagane",
    "gn:country_code":"LK",
    "gn:dem":43,
    "gn:feature_class":"P",
    "gn:feature_code":"PPL",
    "gn:name":"Pahala Malagane",
    "gn:population":0,
    "gn:timezone":"Asia/Colombo",
    "iso:country":"LK",
    "name:und_x_variant":[
        "Malagane Pahala",
        "Pahala Malagane"
    ],
    "wof:name":"Pahala Malagane",
    "wof:placetype":"locality"
},
  "geometry": {"coordinates":[80.0656,7.5917],"type":"Point"}
}