{
  "type": "Feature",
  "properties": {
    "gn:admin1_code":"32.0",
    "gn:asciiname":"Modarawella",
    "gn:country_code":"LK",
    "gn:dem":20,
    "gn:feature_class":"P",
    "gn:feature_code":"PPL",
    "gn:name":"Modarawella",
    "gn:population":0,
    "gn:timezone":"Asia/Colombo",
    "iso:country":"LK",
    "wof:name":"Modarawella",
    "wof:placetype":"locality"
},
  "geometry": {"coordinates":[79.82559999999999,7.4085],"type":"Point"}
}