{
  "type": "Feature",
  "properties": {
    "gn:admin1_code":"32.0",
    "gn:asciiname":"Molewa",
    "gn:country_code":"LK",
    "gn:dem":106,
    "gn:feature_class":"P",
    "gn:feature_code":"PPL",
    "gn:name":"Molewa",
    "gn:population":0,
    "gn:timezone":"Asia/Colombo",
    "iso:country":"LK",
    "wof:name":"Molewa",
    "wof:placetype":"locality"
},
  "geometry": {"coordinates":[80.24509999999999,8.0335],"type":"Point"}
}