{
  "type": "Feature",
  "properties": {
    "gn:admin1_code":"32.0",
    "gn:asciiname":"Nagawila",
    "gn:country_code":"LK",
    "gn:dem":48,
    "gn:feature_class":"P",
    "gn:feature_code":"PPL",
    "gn:name":"Nagawila",
    "gn:population":0,
    "gn:timezone":"Asia/Colombo",
    "iso:country":"LK",
    "wof:name":"Nagawila",
    "wof:placetype":"locality"
},
  "geometry": {"coordinates":[79.94670000000001,7.7574],"type":"Point"}
}