{
  "type": "Feature",
  "properties": {
    "gn:admin1_code":"32.0",
    "gn:asciiname":"Kivulegama",
    "gn:cc2":"LK",
    "gn:country_code":"LK",
    "gn:dem":59,
    "gn:feature_class":"P",
    "gn:feature_code":"PPL",
    "gn:name":"Kivulegama",
    "gn:population":0,
    "gn:timezone":"Asia/Colombo",
    "iso:country":"LK",
    "name:und_x_variant":[
        "Kiwulegama",
        "Kivulegama"
    ],
    "wof:name":"Kivulegama",
    "wof:placetype":"locality"
},
  "geometry": {"coordinates":[80.11667,7.78333],"type":"Point"}
}