{
  "type": "Feature",
  "properties": {
    "gn:admin1_code":"29.0",
    "gn:asciiname":"Pussellawa",
    "gn:country_code":"LK",
    "gn:dem":924,
    "gn:feature_class":"P",
    "gn:feature_code":"PPL",
    "gn:name":"Pussellawa",
    "gn:population":0,
    "gn:timezone":"Asia/Colombo",
    "iso:country":"LK",
    "name:ceb_x_preferred":[
        "Pussellawa"
    ],
    "name:sin_x_preferred":[
        "\u0db4\u0dd4\u0dc3\u0dca\u0dc3\u0dd0\u0dbd\u0dca\u0dbd\u0dcf\u0dc0"
    ],
    "name:swe_x_preferred":[
        "Pussellawa"
    ],
    "wof:name":"Pussellawa",
    "wof:placetype":"locality"
},
  "geometry": {"coordinates":[80.6322,7.1073],"type":"Point"}
}