{
  "type": "Feature",
  "properties": {
    "gn:admin1_code":"33.0",
    "gn:asciiname":"Balawane",
    "gn:country_code":"LK",
    "gn:dem":494,
    "gn:feature_class":"P",
    "gn:feature_code":"PPL",
    "gn:name":"Balawane",
    "gn:population":0,
    "gn:timezone":"Asia/Colombo",
    "iso:country":"LK",
    "wof:name":"Balawane",
    "wof:placetype":"locality"
},
  "geometry": {"coordinates":[80.44889999999999,6.7973],"type":"Point"}
}