{
  "type": "Feature",
  "properties": {
    "gn:admin1_code":"36.0",
    "gn:asciiname":"Warahantuduwa",
    "gn:country_code":"LK",
    "gn:dem":5,
    "gn:feature_class":"P",
    "gn:feature_code":"PPL",
    "gn:name":"Warahantuduwa",
    "gn:population":0,
    "gn:timezone":"Asia/Colombo",
    "iso:country":"LK",
    "wof:name":"Warahantuduwa",
    "wof:placetype":"locality"
},
  "geometry": {"coordinates":[79.93519999999999,6.9841],"type":"Point"}
}