{
  "type": "Feature",
  "properties": {
    "gn:admin1_code":"35.0",
    "gn:asciiname":"Metikumbura",
    "gn:country_code":"LK",
    "gn:dem":1262,
    "gn:feature_class":"P",
    "gn:feature_code":"PPL",
    "gn:name":"Metikumbura",
    "gn:population":0,
    "gn:timezone":"Asia/Colombo",
    "iso:country":"LK",
    "wof:name":"Metikumbura",
    "wof:placetype":"locality"
},
  "geometry": {"coordinates":[80.9003,6.8627],"type":"Point"}
}