{
  "type": "Feature",
  "properties": {
    "gn:admin1_code":"38.0",
    "gn:asciiname":"Chenkarattimoddai",
    "gn:country_code":"LK",
    "gn:dem":92,
    "gn:feature_class":"P",
    "gn:feature_code":"PPL",
    "gn:name":"Chenkarattimoddai",
    "gn:population":0,
    "gn:timezone":"Asia/Colombo",
    "iso:country":"LK",
    "name:und_x_variant":[
        "Senkara-attimoddai",
        "Chenkarattimoddai"
    ],
    "wof:name":"Chenkarattimoddai",
    "wof:placetype":"locality"
},
  "geometry": {"coordinates":[80.5575,8.9081],"type":"Point"}
}