{
  "type": "Feature",
  "properties": {
    "gn:admin1_code":"32.0",
    "gn:asciiname":"Amunuwela",
    "gn:country_code":"LK",
    "gn:dem":20,
    "gn:feature_class":"P",
    "gn:feature_code":"PPL",
    "gn:name":"Amunuwela",
    "gn:population":0,
    "gn:timezone":"Asia/Colombo",
    "iso:country":"LK",
    "wof:name":"Amunuwela",
    "wof:placetype":"locality"
},
  "geometry": {"coordinates":[79.9862,7.5007],"type":"Point"}
}