{
  "type": "Feature",
  "properties": {
    "gn:admin1_code":"33.0",
    "gn:asciiname":"Ihalagalagama",
    "gn:country_code":"LK",
    "gn:dem":1063,
    "gn:feature_class":"P",
    "gn:feature_code":"PPL",
    "gn:name":"Ihalagalagama",
    "gn:population":0,
    "gn:timezone":"Asia/Colombo",
    "iso:country":"LK",
    "wof:name":"Ihalagalagama",
    "wof:placetype":"locality"
},
  "geometry": {"coordinates":[80.7325,6.7409],"type":"Point"}
}