{
  "type": "Feature",
  "properties": {
    "gn:admin1_code":"35.0",
    "gn:asciiname":"Kimbullewa",
    "gn:country_code":"LK",
    "gn:dem":809,
    "gn:feature_class":"P",
    "gn:feature_code":"PPL",
    "gn:name":"Kimbullewa",
    "gn:population":0,
    "gn:timezone":"Asia/Colombo",
    "iso:country":"LK",
    "name:und_x_variant":[
        "Kimbullawa",
        "Kimbullewa"
    ],
    "wof:name":"Kimbullewa",
    "wof:placetype":"locality"
},
  "geometry": {"coordinates":[81.0305,7.0652],"type":"Point"}
}