{
  "type": "Feature",
  "properties": {
    "gn:admin1_code":"30.0",
    "gn:asciiname":"Dennewa",
    "gn:country_code":"LK",
    "gn:dem":138,
    "gn:feature_class":"P",
    "gn:feature_code":"PPL",
    "gn:name":"Dennewa",
    "gn:population":0,
    "gn:timezone":"Asia/Colombo",
    "iso:country":"LK",
    "wof:name":"Dennewa",
    "wof:placetype":"locality"
},
  "geometry": {"coordinates":[80.5665,7.9578],"type":"Point"}
}