{
  "type": "Feature",
  "properties": {
    "gn:admin1_code":"32.0",
    "gn:asciiname":"Bogahawewa",
    "gn:country_code":"LK",
    "gn:dem":76,
    "gn:feature_class":"P",
    "gn:feature_code":"PPL",
    "gn:name":"Bogahawewa",
    "gn:population":0,
    "gn:timezone":"Asia/Colombo",
    "iso:country":"LK",
    "wof:name":"Bogahawewa",
    "wof:placetype":"locality"
},
  "geometry": {"coordinates":[80.09699999999999,7.9956],"type":"Point"}
}