{
  "type": "Feature",
  "properties": {
    "gn:admin1_code":"37.0",
    "gn:asciiname":"Palaiyadimadu",
    "gn:country_code":"LK",
    "gn:dem":3,
    "gn:feature_class":"P",
    "gn:feature_code":"PPL",
    "gn:name":"Palaiyadimadu",
    "gn:population":0,
    "gn:timezone":"Asia/Colombo",
    "iso:country":"LK",
    "wof:name":"Palaiyadimadu",
    "wof:placetype":"locality"
},
  "geometry": {"coordinates":[81.41667,8.11667],"type":"Point"}
}