{
  "type": "Feature",
  "properties": {
    "gn:admin1_code":"33.0",
    "gn:asciiname":"Welideniya",
    "gn:country_code":"LK",
    "gn:dem":226,
    "gn:feature_class":"P",
    "gn:feature_code":"PPL",
    "gn:name":"Welideniya",
    "gn:population":0,
    "gn:timezone":"Asia/Colombo",
    "iso:country":"LK",
    "wof:name":"Welideniya",
    "wof:placetype":"locality"
},
  "geometry": {"coordinates":[80.44110000000001,7.2241],"type":"Point"}
}