{
  "type": "Feature",
  "properties": {
    "gn:admin1_code":"29.0",
    "gn:asciiname":"Toradeniya",
    "gn:country_code":"LK",
    "gn:dem":515,
    "gn:feature_class":"P",
    "gn:feature_code":"PPL",
    "gn:name":"Toradeniya",
    "gn:population":0,
    "gn:timezone":"Asia/Colombo",
    "iso:country":"LK",
    "wof:name":"Toradeniya",
    "wof:placetype":"locality"
},
  "geometry": {"coordinates":[80.55549999999999,7.362],"type":"Point"}
}