{
  "type": "Feature",
  "properties": {
    "gn:admin1_code":"38.0",
    "gn:asciiname":"Vakkappaddankandal-Metpuliyankulam",
    "gn:country_code":"LK",
    "gn:dem":9,
    "gn:feature_class":"P",
    "gn:feature_code":"PPL",
    "gn:name":"Vakkappaddankandal-Metpuliyankulam",
    "gn:population":0,
    "gn:timezone":"Asia/Colombo",
    "iso:country":"LK",
    "wof:name":"Vakkappaddankandal-Metpuliyankulam",
    "wof:placetype":"locality"
},
  "geometry": {"coordinates":[79.98333000000002,8.81667],"type":"Point"}
}