{
  "type": "Feature",
  "properties": {
    "gn:admin1_code":"33.0",
    "gn:asciiname":"Mullegama",
    "gn:country_code":"LK",
    "gn:dem":301,
    "gn:feature_class":"P",
    "gn:feature_code":"PPL",
    "gn:name":"Mullegama",
    "gn:population":0,
    "gn:timezone":"Asia/Colombo",
    "iso:country":"LK",
    "wof:name":"Mullegama",
    "wof:placetype":"locality"
},
  "geometry": {"coordinates":[80.73390000000001,6.5814],"type":"Point"}
}