{
  "type": "Feature",
  "properties": {
    "gn:admin1_code":"34.0",
    "gn:asciiname":"Urumutta",
    "gn:country_code":"LK",
    "gn:dem":152,
    "gn:feature_class":"P",
    "gn:feature_code":"PPL",
    "gn:name":"Urumutta",
    "gn:population":0,
    "gn:timezone":"Asia/Colombo",
    "iso:country":"LK",
    "wof:name":"Urumutta",
    "wof:placetype":"locality"
},
  "geometry": {"coordinates":[80.5151,6.1563],"type":"Point"}
}