{
  "type": "Feature",
  "properties": {
    "gn:admin1_code":"34.0",
    "gn:asciiname":"Welipitiya",
    "gn:country_code":"LK",
    "gn:dem":143,
    "gn:feature_class":"P",
    "gn:feature_code":"PPL",
    "gn:name":"Welipitiya",
    "gn:population":0,
    "gn:timezone":"Asia/Colombo",
    "iso:country":"LK",
    "wof:name":"Welipitiya",
    "wof:placetype":"locality"
},
  "geometry": {"coordinates":[80.7411,6.267],"type":"Point"}
}