{
  "type": "Feature",
  "properties": {
    "gn:admin1_code":"32.0",
    "gn:asciiname":"Kabalewa",
    "gn:country_code":"LK",
    "gn:dem":48,
    "gn:feature_class":"P",
    "gn:feature_code":"PPL",
    "gn:name":"Kabalewa",
    "gn:population":0,
    "gn:timezone":"Asia/Colombo",
    "iso:country":"LK",
    "wof:name":"Kabalewa",
    "wof:placetype":"locality"
},
  "geometry": {"coordinates":[80.0231,7.5925],"type":"Point"}
}