{
  "type": "Feature",
  "properties": {
    "iso:country":"LK",
    "name:jpn_x_preferred":[
        "\u30b7\u30ca\u30e2\u30f3\u30fb\u30ac\u30fc\u30c7\u30f3\u30ba"
    ],
    "name:sin_x_preferred":[
        "\u0d9a\u0dd4\u0dbb\u0dd4\u0db3\u0dd4 \u0dc0\u0dad\u0dca\u0dad"
    ],
    "name:tam_x_preferred":[
        "\u0b95\u0bb1\u0bc1\u0bb5\u0bbe\u0ba4\u0bcd \u0ba4\u0bcb\u0b9f\u0bcd\u0b9f\u0bae\u0bcd"
    ],
    "qs:gn_country":"LK",
    "qs:gn_fcode":"PPLX",
    "qs:gn_pop":0,
    "qs:name":"Cinnamon Gardens",
    "qs:name_adm0":"Sri Lanka",
    "qs:name_adm1":"Western",
    "qs:photos":1,
    "qs:photos_1k":1,
    "qs:photos_9k":1,
    "qs:photos_9r":1,
    "qs:photos_all":1,
    "qs:photos_sr":1,
    "qs:placetype":"Suburb",
    "qs:pop_sr":"0",
    "qs:woe_adm0":23424778,
    "wd:wordcount":377,
    "wof:name":"Cinnamon Gardens",
    "wof:placetype":"neighbourhood"
},
  "geometry": {"coordinates":[79.8691,6.9098],"type":"Point"}
}