{
  "type": "Feature",
  "properties": {
    "gn:admin1_code":"35.0",
    "gn:asciiname":"Pallebedda",
    "gn:country_code":"LK",
    "gn:dem":122,
    "gn:feature_class":"P",
    "gn:feature_code":"PPL",
    "gn:name":"Pallebedda",
    "gn:population":0,
    "gn:timezone":"Asia/Colombo",
    "iso:country":"LK",
    "wof:name":"Pallebedda",
    "wof:placetype":"locality"
},
  "geometry": {"coordinates":[81.42959999999999,6.92],"type":"Point"}
}