{
  "type": "Feature",
  "properties": {
    "gn:admin1_code":"33.0",
    "gn:asciiname":"Katukumbura",
    "gn:country_code":"LK",
    "gn:dem":163,
    "gn:feature_class":"P",
    "gn:feature_code":"PPL",
    "gn:name":"Katukumbura",
    "gn:population":0,
    "gn:timezone":"Asia/Colombo",
    "iso:country":"LK",
    "wof:name":"Katukumbura",
    "wof:placetype":"locality"
},
  "geometry": {"coordinates":[80.7343,6.4094],"type":"Point"}
}