{
  "type": "Feature",
  "properties": {
    "gn:admin1_code":"35.0",
    "gn:asciiname":"Mahathenna",
    "gn:country_code":"LK",
    "gn:dem":927,
    "gn:feature_class":"P",
    "gn:feature_code":"PPL",
    "gn:name":"Mahathenna",
    "gn:population":0,
    "gn:timezone":"Asia/Colombo",
    "iso:country":"LK",
    "wof:name":"Mahathenna",
    "wof:placetype":"locality"
},
  "geometry": {"coordinates":[81.0367,7.0046],"type":"Point"}
}