{
  "type": "Feature",
  "properties": {
    "gn:admin1_code":"30.0",
    "gn:asciiname":"Musnewa",
    "gn:country_code":"LK",
    "gn:dem":133,
    "gn:feature_class":"P",
    "gn:feature_code":"PPL",
    "gn:name":"Musnewa",
    "gn:population":0,
    "gn:timezone":"Asia/Colombo",
    "iso:country":"LK",
    "name:und_x_variant":[
        "Musnawa"
    ],
    "wof:name":"Musnewa",
    "wof:placetype":"locality"
},
  "geometry": {"coordinates":[80.46559999999999,8.0001],"type":"Point"}
}