{
  "type": "Feature",
  "properties": {
    "gn:admin1_code":"34.0",
    "gn:asciiname":"Weraniyagodakanda",
    "gn:country_code":"LK",
    "gn:dem":12,
    "gn:feature_class":"P",
    "gn:feature_code":"PPL",
    "gn:name":"Weraniyagodakanda",
    "gn:population":0,
    "gn:timezone":"Asia/Colombo",
    "iso:country":"LK",
    "wof:name":"Weraniyagodakanda",
    "wof:placetype":"locality"
},
  "geometry": {"coordinates":[80.3389,6.0258],"type":"Point"}
}