{
  "type": "Feature",
  "properties": {
    "gn:admin1_code":"33.0",
    "gn:asciiname":"Dehimaduwa",
    "gn:country_code":"LK",
    "gn:dem":317,
    "gn:feature_class":"P",
    "gn:feature_code":"PPL",
    "gn:name":"Dehimaduwa",
    "gn:population":0,
    "gn:timezone":"Asia/Colombo",
    "iso:country":"LK",
    "wof:name":"Dehimaduwa",
    "wof:placetype":"locality"
},
  "geometry": {"coordinates":[80.4302,7.2425],"type":"Point"}
}