{
  "type": "Feature",
  "properties": {
    "gn:admin1_code":"34.0",
    "gn:asciiname":"Hangaranwala",
    "gn:country_code":"LK",
    "gn:dem":32,
    "gn:feature_class":"P",
    "gn:feature_code":"PPL",
    "gn:name":"Hangaranwala",
    "gn:population":0,
    "gn:timezone":"Asia/Colombo",
    "iso:country":"LK",
    "wof:name":"Hangaranwala",
    "wof:placetype":"locality"
},
  "geometry": {"coordinates":[80.30419999999999,6.1831],"type":"Point"}
}