{
  "type": "Feature",
  "properties": {
    "gn:admin1_code":"29.0",
    "gn:asciiname":"Paladoraella",
    "gn:country_code":"LK",
    "gn:dem":686,
    "gn:feature_class":"P",
    "gn:feature_code":"PPL",
    "gn:name":"Paladoraella",
    "gn:population":0,
    "gn:timezone":"Asia/Colombo",
    "iso:country":"LK",
    "wof:name":"Paladoraella",
    "wof:placetype":"locality"
},
  "geometry": {"coordinates":[80.65000000000001,7.06667],"type":"Point"}
}