{
  "type": "Feature",
  "properties": {
    "gn:admin1_code":"30.0",
    "gn:asciiname":"Lokunaidegama",
    "gn:country_code":"LK",
    "gn:dem":144,
    "gn:feature_class":"P",
    "gn:feature_code":"PPL",
    "gn:name":"Lokunaidegama",
    "gn:population":0,
    "gn:timezone":"Asia/Colombo",
    "iso:country":"LK",
    "name:und_x_variant":[
        "Lokunaidagama"
    ],
    "wof:name":"Lokunaidegama",
    "wof:placetype":"locality"
},
  "geometry": {"coordinates":[80.5877,7.9573],"type":"Point"}
}