{
  "type": "Feature",
  "properties": {
    "gn:admin1_code":"32.0",
    "gn:asciiname":"Ihala Alawwagama",
    "gn:cc2":"LK",
    "gn:country_code":"LK",
    "gn:dem":129,
    "gn:feature_class":"P",
    "gn:feature_code":"PPL",
    "gn:name":"Ihala Alawwagama",
    "gn:population":0,
    "gn:timezone":"Asia/Colombo",
    "iso:country":"LK",
    "name:und_x_variant":[
        "Ihala Alauwagama",
        "Ihala Alawwagama"
    ],
    "wof:name":"Ihala Alawwagama",
    "wof:placetype":"locality"
},
  "geometry": {"coordinates":[80.34999999999999,7.86667],"type":"Point"}
}