{
  "type": "Feature",
  "properties": {
    "gn:admin1_code":"32.0",
    "gn:asciiname":"Karadipuval",
    "gn:country_code":"LK",
    "gn:dem":30,
    "gn:feature_class":"P",
    "gn:feature_code":"PPL",
    "gn:name":"Karadipuval",
    "gn:population":0,
    "gn:timezone":"Asia/Colombo",
    "iso:country":"LK",
    "name:und_x_variant":[
        "Karadipuvel",
        "Karadipuval"
    ],
    "wof:name":"Karadipuval",
    "wof:placetype":"locality"
},
  "geometry": {"coordinates":[79.85769999999999,8.135],"type":"Point"}
}