{
  "type": "Feature",
  "properties": {
    "gn:admin1_code":"35.0",
    "gn:asciiname":"Pahekanuwa",
    "gn:country_code":"LK",
    "gn:dem":248,
    "gn:feature_class":"P",
    "gn:feature_code":"PPL",
    "gn:name":"Pahekanuwa",
    "gn:population":0,
    "gn:timezone":"Asia/Colombo",
    "iso:country":"LK",
    "wof:name":"Pahekanuwa",
    "wof:placetype":"locality"
},
  "geometry": {"coordinates":[81.24209999999999,6.8463],"type":"Point"}
}