{
  "type": "Feature",
  "properties": {
    "gn:admin1_code":"32.0",
    "gn:asciiname":"Katagomuwa",
    "gn:country_code":"LK",
    "gn:dem":51,
    "gn:feature_class":"P",
    "gn:feature_code":"PPL",
    "gn:name":"Katagomuwa",
    "gn:population":0,
    "gn:timezone":"Asia/Colombo",
    "iso:country":"LK",
    "wof:name":"Katagomuwa",
    "wof:placetype":"locality"
},
  "geometry": {"coordinates":[80.16667,7.71667],"type":"Point"}
}