{
  "type": "Feature",
  "properties": {
    "gn:admin1_code":"33.0",
    "gn:asciiname":"Bagature",
    "gn:country_code":"LK",
    "gn:dem":566,
    "gn:feature_class":"P",
    "gn:feature_code":"PPL",
    "gn:name":"Bagature",
    "gn:population":0,
    "gn:timezone":"Asia/Colombo",
    "iso:country":"LK",
    "wof:name":"Bagature",
    "wof:placetype":"locality"
},
  "geometry": {"coordinates":[80.81667,6.61667],"type":"Point"}
}