{
  "type": "Feature",
  "properties": {
    "gn:admin1_code":"36.0",
    "gn:asciiname":"Beruwala Town",
    "gn:country_code":"LK",
    "gn:dem":9,
    "gn:feature_class":"P",
    "gn:feature_code":"PPL",
    "gn:name":"Beruwala Town",
    "gn:population":0,
    "gn:timezone":"Asia/Colombo",
    "iso:country":"LK",
    "name:und_x_variant":[
        "Beruwela",
        "Beruwala Town"
    ],
    "wof:name":"Beruwala Town",
    "wof:placetype":"locality"
},
  "geometry": {"coordinates":[79.9855,6.4665],"type":"Point"}
}