{
  "type": "Feature",
  "properties": {
    "gn:admin1_code":"32.0",
    "gn:asciiname":"Gepallawa",
    "gn:country_code":"LK",
    "gn:dem":98,
    "gn:feature_class":"P",
    "gn:feature_code":"PPL",
    "gn:name":"Gepallawa",
    "gn:population":0,
    "gn:timezone":"Asia/Colombo",
    "iso:country":"LK",
    "wof:name":"Gepallawa",
    "wof:placetype":"locality"
},
  "geometry": {"coordinates":[80.37479999999999,7.5814],"type":"Point"}
}