{
  "type": "Feature",
  "properties": {
    "gn:admin1_code":"33.0",
    "gn:asciiname":"Atawakwala",
    "gn:country_code":"LK",
    "gn:dem":586,
    "gn:feature_class":"P",
    "gn:feature_code":"PPL",
    "gn:name":"Atawakwala",
    "gn:population":0,
    "gn:timezone":"Asia/Colombo",
    "iso:country":"LK",
    "name:und_x_variant":[
        "Etawakwala"
    ],
    "wof:name":"Atawakwala",
    "wof:placetype":"locality"
},
  "geometry": {"coordinates":[80.70659999999999,6.707],"type":"Point"}
}