{
  "type": "Feature",
  "properties": {
    "gn:admin1_code":"33.0",
    "gn:asciiname":"Mipagama",
    "gn:country_code":"LK",
    "gn:dem":225,
    "gn:feature_class":"P",
    "gn:feature_code":"PPL",
    "gn:name":"Mipagama",
    "gn:population":0,
    "gn:timezone":"Asia/Colombo",
    "iso:country":"LK",
    "wof:name":"Mipagama",
    "wof:placetype":"locality"
},
  "geometry": {"coordinates":[80.36333,6.53528],"type":"Point"}
}