{
  "type": "Feature",
  "properties": {
    "gn:admin1_code":"35.0",
    "gn:asciiname":"Sripana",
    "gn:country_code":"LK",
    "gn:dem":496,
    "gn:feature_class":"P",
    "gn:feature_code":"PPL",
    "gn:name":"Sripana",
    "gn:population":0,
    "gn:timezone":"Asia/Colombo",
    "iso:country":"LK",
    "wof:name":"Sripana",
    "wof:placetype":"locality"
},
  "geometry": {"coordinates":[81.38379999999999,6.9102],"type":"Point"}
}