{
  "type": "Feature",
  "properties": {
    "gn:admin1_code":"33.0",
    "gn:asciiname":"Kahantenna",
    "gn:country_code":"LK",
    "gn:dem":344,
    "gn:feature_class":"P",
    "gn:feature_code":"PPL",
    "gn:name":"Kahantenna",
    "gn:population":0,
    "gn:timezone":"Asia/Colombo",
    "iso:country":"LK",
    "wof:name":"Kahantenna",
    "wof:placetype":"locality"
},
  "geometry": {"coordinates":[80.4498,6.4498],"type":"Point"}
}