{
  "type": "Feature",
  "properties": {
    "gn:admin1_code":"30.0",
    "gn:asciiname":"Maha Wannanmaduwa",
    "gn:country_code":"LK",
    "gn:dem":112,
    "gn:feature_class":"P",
    "gn:feature_code":"PPL",
    "gn:name":"Maha Wannanmaduwa",
    "gn:population":0,
    "gn:timezone":"Asia/Colombo",
    "iso:country":"LK",
    "wof:name":"Maha Wannanmaduwa",
    "wof:placetype":"locality"
},
  "geometry": {"coordinates":[80.48333000000002,8.28333],"type":"Point"}
}