{
  "type": "Feature",
  "properties": {
    "gn:admin1_code":"29.0",
    "gn:asciiname":"Urawala",
    "gn:country_code":"LK",
    "gn:dem":493,
    "gn:feature_class":"P",
    "gn:feature_code":"PPL",
    "gn:name":"Urawala",
    "gn:population":0,
    "gn:timezone":"Asia/Colombo",
    "iso:country":"LK",
    "wof:name":"Urawala",
    "wof:placetype":"locality"
},
  "geometry": {"coordinates":[80.6095,7.2681],"type":"Point"}
}