{
  "type": "Feature",
  "properties": {
    "gn:admin1_code":"30.0",
    "gn:asciiname":"Tittellewa",
    "gn:country_code":"LK",
    "gn:dem":131,
    "gn:feature_class":"P",
    "gn:feature_code":"PPL",
    "gn:name":"Tittellewa",
    "gn:population":0,
    "gn:timezone":"Asia/Colombo",
    "iso:country":"LK",
    "wof:name":"Tittellewa",
    "wof:placetype":"locality"
},
  "geometry": {"coordinates":[80.77719999999999,8.309],"type":"Point"}
}