{
  "type": "Feature",
  "properties": {
    "gn:admin1_code":"30.0",
    "gn:asciiname":"Kalahagala",
    "gn:country_code":"LK",
    "gn:dem":73,
    "gn:feature_class":"P",
    "gn:feature_code":"PPL",
    "gn:name":"Kalahagala",
    "gn:population":0,
    "gn:timezone":"Asia/Colombo",
    "iso:country":"LK",
    "wof:name":"Kalahagala",
    "wof:placetype":"locality"
},
  "geometry": {"coordinates":[80.93333,7.86667],"type":"Point"}
}