{
  "type": "Feature",
  "properties": {
    "gn:admin1_code":"35.0",
    "gn:asciiname":"Ambekandura",
    "gn:country_code":"LK",
    "gn:dem":119,
    "gn:feature_class":"P",
    "gn:feature_code":"PPL",
    "gn:name":"Ambekandura",
    "gn:population":0,
    "gn:timezone":"Asia/Colombo",
    "iso:country":"LK",
    "wof:name":"Ambekandura",
    "wof:placetype":"locality"
},
  "geometry": {"coordinates":[81.03579999999999,7.2204],"type":"Point"}
}