{
  "type": "Feature",
  "properties": {
    "gn:admin1_code":"38.0",
    "gn:asciiname":"Chittankeni",
    "gn:country_code":"LK",
    "gn:dem":12,
    "gn:feature_class":"P",
    "gn:feature_code":"PPL",
    "gn:name":"Chittankeni",
    "gn:population":0,
    "gn:timezone":"Asia/Colombo",
    "iso:country":"LK",
    "name:und_x_variant":[
        "Chittankeny",
        "Chittankeni"
    ],
    "wof:name":"Chittankeni",
    "wof:placetype":"locality"
},
  "geometry": {"coordinates":[79.96666999999999,9.75],"type":"Point"}
}