{
  "type": "Feature",
  "properties": {
    "gn:admin1_code":"33.0",
    "gn:asciiname":"Illupotta",
    "gn:country_code":"LK",
    "gn:dem":427,
    "gn:feature_class":"P",
    "gn:feature_code":"PPL",
    "gn:name":"Illupotta",
    "gn:population":0,
    "gn:timezone":"Asia/Colombo",
    "iso:country":"LK",
    "wof:name":"Illupotta",
    "wof:placetype":"locality"
},
  "geometry": {"coordinates":[80.48899999999998,6.4256],"type":"Point"}
}