{
  "type": "Feature",
  "properties": {
    "gn:admin1_code":"36.0",
    "gn:asciiname":"Tunmanhandiya",
    "gn:country_code":"LK",
    "gn:dem":-1,
    "gn:feature_class":"P",
    "gn:feature_code":"PPL",
    "gn:name":"Tunmanhandiya",
    "gn:population":0,
    "gn:timezone":"Asia/Colombo",
    "iso:country":"LK",
    "wof:name":"Tunmanhandiya",
    "wof:placetype":"locality"
},
  "geometry": {"coordinates":[79.9811,6.4748],"type":"Point"}
}