{
  "type": "Feature",
  "properties": {
    "gn:admin1_code":"35.0",
    "gn:asciiname":"Kohana",
    "gn:country_code":"LK",
    "gn:dem":867,
    "gn:feature_class":"P",
    "gn:feature_code":"PPL",
    "gn:name":"Kohana",
    "gn:population":0,
    "gn:timezone":"Asia/Colombo",
    "iso:country":"LK",
    "name:fra_x_preferred":[
        "Kohana"
    ],
    "wof:name":"Kohana",
    "wof:placetype":"locality"
},
  "geometry": {"coordinates":[81.0441,7.0465],"type":"Point"}
}