{
  "type": "Feature",
  "properties": {
    "gn:admin1_code":"33.0",
    "gn:asciiname":"Mukalanhena",
    "gn:country_code":"LK",
    "gn:dem":723,
    "gn:feature_class":"P",
    "gn:feature_code":"PPL",
    "gn:name":"Mukalanhena",
    "gn:population":0,
    "gn:timezone":"Asia/Colombo",
    "iso:country":"LK",
    "wof:name":"Mukalanhena",
    "wof:placetype":"locality"
},
  "geometry": {"coordinates":[80.65278000000001,6.36139],"type":"Point"}
}