{
  "type": "Feature",
  "properties": {
    "gn:admin1_code":"32.0",
    "gn:asciiname":"Ulpota",
    "gn:cc2":"LK",
    "gn:country_code":"LK",
    "gn:dem":151,
    "gn:feature_class":"P",
    "gn:feature_code":"PPL",
    "gn:name":"Ulpota",
    "gn:population":0,
    "gn:timezone":"Asia/Colombo",
    "iso:country":"LK",
    "name:und_x_variant":[
        "Ulpotha",
        "Ulpota"
    ],
    "wof:name":"Ulpota",
    "wof:placetype":"locality"
},
  "geometry": {"coordinates":[80.43333,7.85],"type":"Point"}
}