{
  "type": "Feature",
  "properties": {
    "gn:admin1_code":"35.0",
    "gn:asciiname":"Dibbedda",
    "gn:country_code":"LK",
    "gn:dem":1273,
    "gn:feature_class":"P",
    "gn:feature_code":"PPL",
    "gn:name":"Dibbedda",
    "gn:population":0,
    "gn:timezone":"Asia/Colombo",
    "iso:country":"LK",
    "wof:name":"Dibbedda",
    "wof:placetype":"locality"
},
  "geometry": {"coordinates":[80.9188,6.8523],"type":"Point"}
}