{
  "type": "Feature",
  "properties": {
    "gn:admin1_code":"36.0",
    "gn:asciiname":"Matalana",
    "gn:country_code":"LK",
    "gn:dem":44,
    "gn:feature_class":"P",
    "gn:feature_code":"PPL",
    "gn:name":"Matalana",
    "gn:population":0,
    "gn:timezone":"Asia/Colombo",
    "iso:country":"LK",
    "wof:name":"Matalana",
    "wof:placetype":"locality"
},
  "geometry": {"coordinates":[80.0975,7.1152],"type":"Point"}
}