{
  "type": "Feature",
  "properties": {
    "gn:admin1_code":"30.0",
    "gn:asciiname":"Kelegama",
    "gn:country_code":"LK",
    "gn:dem":91,
    "gn:feature_class":"P",
    "gn:feature_code":"PPL",
    "gn:name":"Kelegama",
    "gn:population":0,
    "gn:timezone":"Asia/Colombo",
    "iso:country":"LK",
    "wof:name":"Kelegama",
    "wof:placetype":"locality"
},
  "geometry": {"coordinates":[80.30159999999999,8.1991],"type":"Point"}
}