{
  "type": "Feature",
  "properties": {
    "gn:admin1_code":"32.0",
    "gn:asciiname":"Akalagamuwa",
    "gn:country_code":"LK",
    "gn:dem":235,
    "gn:feature_class":"P",
    "gn:feature_code":"PPL",
    "gn:name":"Akalagamuwa",
    "gn:population":0,
    "gn:timezone":"Asia/Colombo",
    "iso:country":"LK",
    "name:und_x_variant":[
        "Akalagomuwa"
    ],
    "wof:name":"Akalagamuwa",
    "wof:placetype":"locality"
},
  "geometry": {"coordinates":[80.529,7.469],"type":"Point"}
}