{
  "type": "Feature",
  "properties": {
    "gn:admin1_code":"33.0",
    "gn:asciiname":"Anduwawala",
    "gn:country_code":"LK",
    "gn:dem":209,
    "gn:feature_class":"P",
    "gn:feature_code":"PPL",
    "gn:name":"Anduwawala",
    "gn:population":0,
    "gn:timezone":"Asia/Colombo",
    "iso:country":"LK",
    "wof:name":"Anduwawala",
    "wof:placetype":"locality"
},
  "geometry": {"coordinates":[80.45,7.25],"type":"Point"}
}