{
  "type": "Feature",
  "properties": {
    "gn:admin1_code":"29.0",
    "gn:asciiname":"Ittamaliyagoda",
    "gn:country_code":"LK",
    "gn:dem":483,
    "gn:feature_class":"P",
    "gn:feature_code":"PPL",
    "gn:name":"Ittamaliyagoda",
    "gn:population":0,
    "gn:timezone":"Asia/Colombo",
    "iso:country":"LK",
    "name:und_x_variant":[
        "Ittamalliyagoda"
    ],
    "wof:name":"Ittamaliyagoda",
    "wof:placetype":"locality"
},
  "geometry": {"coordinates":[80.68989999999999,7.3071],"type":"Point"}
}