{
  "type": "Feature",
  "properties": {
    "gn:admin1_code":"29.0",
    "gn:asciiname":"Muruthatenna",
    "gn:country_code":"LK",
    "gn:dem":757,
    "gn:feature_class":"P",
    "gn:feature_code":"PPL",
    "gn:name":"Muruthatenna",
    "gn:population":0,
    "gn:timezone":"Asia/Colombo",
    "iso:country":"LK",
    "wof:name":"Muruthatenna",
    "wof:placetype":"locality"
},
  "geometry": {"coordinates":[80.4949,6.9004],"type":"Point"}
}