{
  "type": "Feature",
  "properties": {
    "gn:admin1_code":"36.0",
    "gn:asciiname":"Kahawela",
    "gn:country_code":"LK",
    "gn:dem":19,
    "gn:feature_class":"P",
    "gn:feature_code":"PPL",
    "gn:name":"Kahawela",
    "gn:population":0,
    "gn:timezone":"Asia/Colombo",
    "iso:country":"LK",
    "name:und_x_variant":[
        "Kahawala"
    ],
    "wof:name":"Kahawela",
    "wof:placetype":"locality"
},
  "geometry": {"coordinates":[80.1057,6.7772],"type":"Point"}
}