{
  "type": "Feature",
  "properties": {
    "gn:admin1_code":"36.0",
    "gn:asciiname":"Balapokuna",
    "gn:country_code":"LK",
    "gn:dem":24,
    "gn:feature_class":"P",
    "gn:feature_code":"PPL",
    "gn:name":"Balapokuna",
    "gn:population":0,
    "gn:timezone":"Asia/Colombo",
    "iso:country":"LK",
    "wof:name":"Balapokuna",
    "wof:placetype":"locality"
},
  "geometry": {"coordinates":[79.88420000000001,6.8667],"type":"Point"}
}