{
  "type": "Feature",
  "properties": {
    "gn:admin1_code":"33.0",
    "gn:asciiname":"Koskulana",
    "gn:country_code":"LK",
    "gn:dem":377,
    "gn:feature_class":"P",
    "gn:feature_code":"PPL",
    "gn:name":"Koskulana",
    "gn:population":0,
    "gn:timezone":"Asia/Colombo",
    "iso:country":"LK",
    "wof:name":"Koskulana",
    "wof:placetype":"locality"
},
  "geometry": {"coordinates":[80.4532,6.4208],"type":"Point"}
}