{
  "type": "Feature",
  "properties": {
    "gn:admin1_code":"32.0",
    "gn:asciiname":"Kivula",
    "gn:cc2":"LK",
    "gn:country_code":"LK",
    "gn:dem":178,
    "gn:feature_class":"P",
    "gn:feature_code":"PPL",
    "gn:name":"Kivula",
    "gn:population":0,
    "gn:timezone":"Asia/Colombo",
    "iso:country":"LK",
    "name:und_x_variant":[
        "Kiula",
        "Kivula"
    ],
    "wof:name":"Kivula",
    "wof:placetype":"locality"
},
  "geometry": {"coordinates":[80.43333,7.43333],"type":"Point"}
}