{
  "type": "Feature",
  "properties": {
    "gn:admin1_code":"37.0",
    "gn:asciiname":"Panchenai",
    "gn:country_code":"LK",
    "gn:dem":32,
    "gn:feature_class":"P",
    "gn:feature_code":"PPL",
    "gn:name":"Panchenai",
    "gn:population":0,
    "gn:timezone":"Asia/Colombo",
    "iso:country":"LK",
    "wof:name":"Panchenai",
    "wof:placetype":"locality"
},
  "geometry": {"coordinates":[81.59999999999999,7.58333],"type":"Point"}
}