{
  "type": "Feature",
  "properties": {
    "gn:admin1_code":"30.0",
    "gn:asciiname":"Amane",
    "gn:country_code":"LK",
    "gn:dem":102,
    "gn:feature_class":"P",
    "gn:feature_code":"PPL",
    "gn:name":"Amane",
    "gn:population":0,
    "gn:timezone":"Asia/Colombo",
    "iso:country":"LK",
    "wof:name":"Amane",
    "wof:placetype":"locality"
},
  "geometry": {"coordinates":[80.3867,8.2825],"type":"Point"}
}