{
  "type": "Feature",
  "properties": {
    "gn:admin1_code":"32.0",
    "gn:asciiname":"Levugolla",
    "gn:country_code":"LK",
    "gn:dem":128,
    "gn:feature_class":"P",
    "gn:feature_code":"PPL",
    "gn:name":"Levugolla",
    "gn:population":0,
    "gn:timezone":"Asia/Colombo",
    "iso:country":"LK",
    "name:und_x_variant":[
        "Levugalla"
    ],
    "wof:name":"Levugolla",
    "wof:placetype":"locality"
},
  "geometry": {"coordinates":[80.4508,7.6525],"type":"Point"}
}