{
  "type": "Feature",
  "properties": {
    "gn:admin1_code":"33.0",
    "gn:asciiname":"Malwala",
    "gn:country_code":"LK",
    "gn:dem":41,
    "gn:feature_class":"P",
    "gn:feature_code":"PPL",
    "gn:name":"Malwala",
    "gn:population":0,
    "gn:timezone":"Asia/Colombo",
    "iso:country":"LK",
    "name:und_x_variant":[
        "Malwala Junction",
        "Malwala"
    ],
    "wof:name":"Malwala",
    "wof:placetype":"locality"
},
  "geometry": {"coordinates":[80.4336,6.707],"type":"Point"}
}