{
  "type": "Feature",
  "properties": {
    "gn:admin1_code":"30.0",
    "gn:asciiname":"Janaladagama",
    "gn:country_code":"LK",
    "gn:dem":78,
    "gn:feature_class":"P",
    "gn:feature_code":"PPL",
    "gn:name":"Janaladagama",
    "gn:population":0,
    "gn:timezone":"Asia/Colombo",
    "iso:country":"LK",
    "wof:name":"Janaladagama",
    "wof:placetype":"locality"
},
  "geometry": {"coordinates":[80.286,8.1405],"type":"Point"}
}