{
  "type": "Feature",
  "properties": {
    "gn:admin1_code":"34.0",
    "gn:asciiname":"Kumbukwewa",
    "gn:country_code":"LK",
    "gn:dem":83,
    "gn:feature_class":"P",
    "gn:feature_code":"PPL",
    "gn:name":"Kumbukwewa",
    "gn:population":0,
    "gn:timezone":"Asia/Colombo",
    "iso:country":"LK",
    "wof:name":"Kumbukwewa",
    "wof:placetype":"locality"
},
  "geometry": {"coordinates":[81.01666999999998,6.38333],"type":"Point"}
}