{
  "type": "Feature",
  "properties": {
    "gn:admin1_code":"29.0",
    "gn:asciiname":"Bokarabevila",
    "gn:country_code":"LK",
    "gn:dem":304,
    "gn:feature_class":"P",
    "gn:feature_code":"PPL",
    "gn:name":"Bokarabevila",
    "gn:population":0,
    "gn:timezone":"Asia/Colombo",
    "iso:country":"LK",
    "wof:name":"Bokarabevila",
    "wof:placetype":"locality"
},
  "geometry": {"coordinates":[80.456,6.9577],"type":"Point"}
}