{
  "type": "Feature",
  "properties": {
    "gn:admin1_code":"29.0",
    "gn:asciiname":"Pawulpawa",
    "gn:country_code":"LK",
    "gn:dem":270,
    "gn:feature_class":"P",
    "gn:feature_code":"PPL",
    "gn:name":"Pawulpawa",
    "gn:population":0,
    "gn:timezone":"Asia/Colombo",
    "iso:country":"LK",
    "wof:name":"Pawulpawa",
    "wof:placetype":"locality"
},
  "geometry": {"coordinates":[80.5111,7.3624],"type":"Point"}
}