{
  "type": "Feature",
  "properties": {
    "gn:admin1_code":"29.0",
    "gn:asciiname":"Venture",
    "gn:country_code":"LK",
    "gn:dem":1305,
    "gn:feature_class":"P",
    "gn:feature_code":"PPL",
    "gn:name":"Venture",
    "gn:population":0,
    "gn:timezone":"Asia/Colombo",
    "iso:country":"LK",
    "name:deu_x_preferred":[
        "Venture"
    ],
    "name:rus_x_preferred":[
        "\u0412\u0435\u043d\u0447\u0443\u0440"
    ],
    "name:ukr_x_preferred":[
        "\u0412\u0435\u043d\u0447\u0443\u0440"
    ],
    "wof:name":"Venture",
    "wof:placetype":"locality"
},
  "geometry": {"coordinates":[80.6084,6.8273],"type":"Point"}
}