{
  "type": "Feature",
  "properties": {
    "gn:admin1_code":"29.0",
    "gn:asciiname":"Potawa",
    "gn:country_code":"LK",
    "gn:dem":248,
    "gn:feature_class":"P",
    "gn:feature_code":"PPL",
    "gn:name":"Potawa",
    "gn:population":0,
    "gn:timezone":"Asia/Colombo",
    "iso:country":"LK",
    "wof:name":"Potawa",
    "wof:placetype":"locality"
},
  "geometry": {"coordinates":[80.61667,7.73333],"type":"Point"}
}