{
  "type": "Feature",
  "properties": {
    "gn:admin1_code":"30.0",
    "gn:asciiname":"Dahalyagama Handiya",
    "gn:country_code":"LK",
    "gn:dem":89,
    "gn:feature_class":"P",
    "gn:feature_code":"PPL",
    "gn:name":"Dahalyagama Handiya",
    "gn:population":0,
    "gn:timezone":"Asia/Colombo",
    "iso:country":"LK",
    "wof:name":"Dahalyagama Handiya",
    "wof:placetype":"locality"
},
  "geometry": {"coordinates":[80.3956,8.3187],"type":"Point"}
}