{
  "type": "Feature",
  "properties": {
    "gn:admin1_code":"34.0",
    "gn:asciiname":"Anguluwelamedagama",
    "gn:country_code":"LK",
    "gn:dem":58,
    "gn:feature_class":"P",
    "gn:feature_code":"PPL",
    "gn:name":"Anguluwelamedagama",
    "gn:population":0,
    "gn:timezone":"Asia/Colombo",
    "iso:country":"LK",
    "wof:name":"Anguluwelamedagama",
    "wof:placetype":"locality"
},
  "geometry": {"coordinates":[80.7548,6.1432],"type":"Point"}
}