{
  "type": "Feature",
  "properties": {
    "gn:admin1_code":"32.0",
    "gn:asciiname":"Kebellegama",
    "gn:country_code":"LK",
    "gn:dem":81,
    "gn:feature_class":"P",
    "gn:feature_code":"PPL",
    "gn:name":"Kebellegama",
    "gn:population":0,
    "gn:timezone":"Asia/Colombo",
    "iso:country":"LK",
    "wof:name":"Kebellegama",
    "wof:placetype":"locality"
},
  "geometry": {"coordinates":[80.18333,7.98333],"type":"Point"}
}