{
  "type": "Feature",
  "properties": {
    "gn:admin1_code":"36.0",
    "gn:asciiname":"Kirimetiagara",
    "gn:country_code":"LK",
    "gn:dem":24,
    "gn:feature_class":"P",
    "gn:feature_code":"PPL",
    "gn:name":"Kirimetiagara",
    "gn:population":0,
    "gn:timezone":"Asia/Colombo",
    "iso:country":"LK",
    "wof:name":"Kirimetiagara",
    "wof:placetype":"locality"
},
  "geometry": {"coordinates":[79.9361,7.0024],"type":"Point"}
}