{
  "type": "Feature",
  "properties": {
    "gn:admin1_code":"34.0",
    "gn:asciiname":"Berawagoda",
    "gn:country_code":"LK",
    "gn:dem":28,
    "gn:feature_class":"P",
    "gn:feature_code":"PPL",
    "gn:name":"Berawagoda",
    "gn:population":0,
    "gn:timezone":"Asia/Colombo",
    "iso:country":"LK",
    "wof:name":"Berawagoda",
    "wof:placetype":"locality"
},
  "geometry": {"coordinates":[80.1812,6.3368],"type":"Point"}
}