{
  "type": "Feature",
  "properties": {
    "gn:admin1_code":"34.0",
    "gn:asciiname":"Telwatta",
    "gn:country_code":"LK",
    "gn:dem":11,
    "gn:feature_class":"P",
    "gn:feature_code":"PPL",
    "gn:name":"Telwatta",
    "gn:population":0,
    "gn:timezone":"Asia/Colombo",
    "iso:country":"LK",
    "name:und_x_variant":[
        "Kahawa Telwatta",
        "Telwatta"
    ],
    "wof:name":"Telwatta",
    "wof:placetype":"locality"
},
  "geometry": {"coordinates":[80.0886,6.1672],"type":"Point"}
}