{
  "type": "Feature",
  "properties": {
    "gn:admin1_code":"35.0",
    "gn:asciiname":"Malaboda",
    "gn:country_code":"LK",
    "gn:dem":443,
    "gn:feature_class":"P",
    "gn:feature_code":"PPL",
    "gn:name":"Malaboda",
    "gn:population":0,
    "gn:timezone":"Asia/Colombo",
    "iso:country":"LK",
    "name:und_x_variant":[
        "Malabodagolla",
        "Malaboda",
        "Malabodagalla"
    ],
    "wof:name":"Malaboda",
    "wof:placetype":"locality"
},
  "geometry": {"coordinates":[81.09220000000001,7.0856],"type":"Point"}
}