{
  "type": "Feature",
  "properties": {
    "gn:admin1_code":"30.0",
    "gn:asciiname":"Pelawattegama",
    "gn:country_code":"LK",
    "gn:dem":87,
    "gn:feature_class":"P",
    "gn:feature_code":"PPL",
    "gn:name":"Pelawattegama",
    "gn:population":0,
    "gn:timezone":"Asia/Colombo",
    "iso:country":"LK",
    "wof:name":"Pelawattegama",
    "wof:placetype":"locality"
},
  "geometry": {"coordinates":[80.2919,8.1639],"type":"Point"}
}