{
  "type": "Feature",
  "properties": {
    "gn:admin1_code":"29.0",
    "gn:asciiname":"Galkanda",
    "gn:country_code":"LK",
    "gn:dem":519,
    "gn:feature_class":"P",
    "gn:feature_code":"PPL",
    "gn:name":"Galkanda",
    "gn:population":0,
    "gn:timezone":"Asia/Colombo",
    "iso:country":"LK",
    "wof:name":"Galkanda",
    "wof:placetype":"locality"
},
  "geometry": {"coordinates":[80.6289,7.2912],"type":"Point"}
}