{
  "type": "Feature",
  "properties": {
    "gn:admin1_code":"35.0",
    "gn:asciiname":"Neludanda",
    "gn:country_code":"LK",
    "gn:dem":1038,
    "gn:feature_class":"P",
    "gn:feature_code":"PPL",
    "gn:name":"Neludanda",
    "gn:population":0,
    "gn:timezone":"Asia/Colombo",
    "iso:country":"LK",
    "wof:name":"Neludanda",
    "wof:placetype":"locality"
},
  "geometry": {"coordinates":[81.0102,6.9453],"type":"Point"}
}