{
  "type": "Feature",
  "properties": {
    "gn:admin1_code":"34.0",
    "gn:asciiname":"Daramitiara",
    "gn:country_code":"LK",
    "gn:dem":131,
    "gn:feature_class":"P",
    "gn:feature_code":"PPL",
    "gn:name":"Daramitiara",
    "gn:population":0,
    "gn:timezone":"Asia/Colombo",
    "iso:country":"LK",
    "wof:name":"Daramitiara",
    "wof:placetype":"locality"
},
  "geometry": {"coordinates":[80.70440000000001,6.2827],"type":"Point"}
}