{
  "type": "Feature",
  "properties": {
    "gn:admin1_code":"30.0",
    "gn:asciiname":"Palugaswewa",
    "gn:country_code":"LK",
    "gn:dem":116,
    "gn:feature_class":"P",
    "gn:feature_code":"PPL",
    "gn:name":"Palugaswewa",
    "gn:population":0,
    "gn:timezone":"Asia/Colombo",
    "iso:country":"LK",
    "wof:name":"Palugaswewa",
    "wof:placetype":"locality"
},
  "geometry": {"coordinates":[80.48333000000002,8.08333],"type":"Point"}
}