{
  "type": "Feature",
  "properties": {
    "gn:admin1_code":"34.0",
    "gn:asciiname":"Bengamukanda",
    "gn:country_code":"LK",
    "gn:dem":418,
    "gn:feature_class":"P",
    "gn:feature_code":"PPL",
    "gn:name":"Bengamukanda",
    "gn:population":0,
    "gn:timezone":"Asia/Colombo",
    "iso:country":"LK",
    "wof:name":"Bengamukanda",
    "wof:placetype":"locality"
},
  "geometry": {"coordinates":[80.6686,6.2821],"type":"Point"}
}