{
  "type": "Feature",
  "properties": {
    "gn:admin1_code":"29.0",
    "gn:asciiname":"Yatihalgala Pallegama",
    "gn:country_code":"LK",
    "gn:dem":485,
    "gn:feature_class":"P",
    "gn:feature_code":"PPL",
    "gn:name":"Yatihalgala Pallegama",
    "gn:population":0,
    "gn:timezone":"Asia/Colombo",
    "iso:country":"LK",
    "name:und_x_variant":[
        "Yatihalagala",
        "Yatihalgala Pallegama",
        "Yatihalagala Pallegama"
    ],
    "wof:name":"Yatihalgala Pallegama",
    "wof:placetype":"locality"
},
  "geometry": {"coordinates":[80.59820000000001,7.2932],"type":"Point"}
}