{
  "type": "Feature",
  "properties": {
    "gn:admin1_code":"33.0",
    "gn:asciiname":"Mugunuwala",
    "gn:country_code":"LK",
    "gn:dem":223,
    "gn:feature_class":"P",
    "gn:feature_code":"PPL",
    "gn:name":"Mugunuwala",
    "gn:population":0,
    "gn:timezone":"Asia/Colombo",
    "iso:country":"LK",
    "wof:name":"Mugunuwala",
    "wof:placetype":"locality"
},
  "geometry": {"coordinates":[80.3274,7.0394],"type":"Point"}
}