{
  "type": "Feature",
  "properties": {
    "gn:admin1_code":"37.0",
    "gn:asciiname":"Charalakadai",
    "gn:country_code":"LK",
    "gn:dem":6,
    "gn:feature_class":"P",
    "gn:feature_code":"PPL",
    "gn:name":"Charalakadai",
    "gn:population":0,
    "gn:timezone":"Asia/Colombo",
    "iso:country":"LK",
    "name:und_x_variant":[
        "Chavalakadai",
        "Chavalakkadai",
        "Chavalkadai",
        "Charalakadai"
    ],
    "wof:name":"Charalakadai",
    "wof:placetype":"locality"
},
  "geometry": {"coordinates":[81.78333000000001,7.41667],"type":"Point"}
}