{
  "type": "Feature",
  "properties": {
    "gn:admin1_code":"35.0",
    "gn:asciiname":"Idamegama",
    "gn:country_code":"LK",
    "gn:dem":1035,
    "gn:feature_class":"P",
    "gn:feature_code":"PPL",
    "gn:name":"Idamegama",
    "gn:population":0,
    "gn:timezone":"Asia/Colombo",
    "iso:country":"LK",
    "wof:name":"Idamegama",
    "wof:placetype":"locality"
},
  "geometry": {"coordinates":[81.03333000000001,6.86667],"type":"Point"}
}