{
  "type": "Feature",
  "properties": {
    "gn:admin1_code":"37.0",
    "gn:asciiname":"Ambagahawela",
    "gn:country_code":"LK",
    "gn:dem":78,
    "gn:feature_class":"P",
    "gn:feature_code":"PPL",
    "gn:name":"Ambagahawela",
    "gn:population":0,
    "gn:timezone":"Asia/Colombo",
    "iso:country":"LK",
    "name:und_x_variant":[
        "Ambagahawella",
        "Ambagahawela"
    ],
    "wof:name":"Ambagahawela",
    "wof:placetype":"locality"
},
  "geometry": {"coordinates":[81.56667,7.26667],"type":"Point"}
}