{
  "type": "Feature",
  "properties": {
    "gn:admin1_code":"35.0",
    "gn:asciiname":"Karunagama",
    "gn:country_code":"LK",
    "gn:dem":719,
    "gn:feature_class":"P",
    "gn:feature_code":"PPL",
    "gn:name":"Karunagama",
    "gn:population":0,
    "gn:timezone":"Asia/Colombo",
    "iso:country":"LK",
    "wof:name":"Karunagama",
    "wof:placetype":"locality"
},
  "geometry": {"coordinates":[81.0581,7.006],"type":"Point"}
}