{
  "type": "Feature",
  "properties": {
    "gn:admin1_code":"36.0",
    "gn:asciiname":"Kandapitiya",
    "gn:country_code":"LK",
    "gn:dem":52,
    "gn:feature_class":"P",
    "gn:feature_code":"PPL",
    "gn:name":"Kandapitiya",
    "gn:population":0,
    "gn:timezone":"Asia/Colombo",
    "iso:country":"LK",
    "wof:name":"Kandapitiya",
    "wof:placetype":"locality"
},
  "geometry": {"coordinates":[80.1452,6.823],"type":"Point"}
}