{
  "type": "Feature",
  "properties": {
    "gn:admin1_code":"33.0",
    "gn:asciiname":"Panapura",
    "gn:country_code":"LK",
    "gn:dem":310,
    "gn:feature_class":"P",
    "gn:feature_code":"PPL",
    "gn:name":"Panapura",
    "gn:population":0,
    "gn:timezone":"Asia/Colombo",
    "iso:country":"LK",
    "wof:name":"Panapura",
    "wof:placetype":"locality"
},
  "geometry": {"coordinates":[80.4873,7.1699],"type":"Point"}
}