{
  "type": "Feature",
  "properties": {
    "gn:admin1_code":"38.0",
    "gn:asciiname":"Siruvilan",
    "gn:country_code":"LK",
    "gn:dem":11,
    "gn:feature_class":"P",
    "gn:feature_code":"PPL",
    "gn:name":"Siruvilan",
    "gn:population":0,
    "gn:timezone":"Asia/Colombo",
    "iso:country":"LK",
    "name:und_x_variant":[
        "Chiruvilan",
        "Siruvilan"
    ],
    "wof:name":"Siruvilan",
    "wof:placetype":"locality"
},
  "geometry": {"coordinates":[79.9995,9.7851],"type":"Point"}
}