{
  "type": "Feature",
  "properties": {
    "gn:admin1_code":"29.0",
    "gn:asciiname":"Bodikotuwa",
    "gn:country_code":"LK",
    "gn:dem":699,
    "gn:feature_class":"P",
    "gn:feature_code":"PPL",
    "gn:name":"Bodikotuwa",
    "gn:population":0,
    "gn:timezone":"Asia/Colombo",
    "iso:country":"LK",
    "wof:name":"Bodikotuwa",
    "wof:placetype":"locality"
},
  "geometry": {"coordinates":[80.711,7.5067],"type":"Point"}
}