{
  "type": "Feature",
  "properties": {
    "gn:admin1_code":"36.0",
    "gn:asciiname":"Beragama",
    "gn:country_code":"LK",
    "gn:dem":19,
    "gn:feature_class":"P",
    "gn:feature_code":"PPL",
    "gn:name":"Beragama",
    "gn:population":0,
    "gn:timezone":"Asia/Colombo",
    "iso:country":"LK",
    "wof:name":"Beragama",
    "wof:placetype":"locality"
},
  "geometry": {"coordinates":[80.1412,6.5431],"type":"Point"}
}