{
  "type": "Feature",
  "properties": {
    "gn:admin1_code":"34.0",
    "gn:asciiname":"Massalapitiya",
    "gn:country_code":"LK",
    "gn:dem":2,
    "gn:feature_class":"P",
    "gn:feature_code":"PPL",
    "gn:name":"Massalapitiya",
    "gn:population":0,
    "gn:timezone":"Asia/Colombo",
    "iso:country":"LK",
    "wof:name":"Massalapitiya",
    "wof:placetype":"locality"
},
  "geometry": {"coordinates":[80.4008,5.9731],"type":"Point"}
}