{
  "type": "Feature",
  "properties": {
    "gn:admin1_code":"34.0",
    "gn:asciiname":"Gammedapitiya",
    "gn:cc2":"LK",
    "gn:country_code":"LK",
    "gn:dem":48,
    "gn:feature_class":"P",
    "gn:feature_code":"PPL",
    "gn:name":"Gammedapitiya",
    "gn:population":0,
    "gn:timezone":"Asia/Colombo",
    "iso:country":"LK",
    "name:und_x_variant":[
        "Gammedipitiya",
        "Gammedapitiya"
    ],
    "wof:name":"Gammedapitiya",
    "wof:placetype":"locality"
},
  "geometry": {"coordinates":[80.65000000000001,6.08333],"type":"Point"}
}