{
  "type": "Feature",
  "properties": {
    "gn:admin1_code":"30.0",
    "gn:asciiname":"Ratmalgama",
    "gn:country_code":"LK",
    "gn:dem":90,
    "gn:feature_class":"P",
    "gn:feature_code":"PPL",
    "gn:name":"Ratmalgama",
    "gn:population":0,
    "gn:timezone":"Asia/Colombo",
    "iso:country":"LK",
    "wof:name":"Ratmalgama",
    "wof:placetype":"locality"
},
  "geometry": {"coordinates":[80.2513,8.2295],"type":"Point"}
}