{
  "type": "Feature",
  "properties": {
    "gn:admin1_code":"35.0",
    "gn:asciiname":"Galgodeyaya",
    "gn:country_code":"LK",
    "gn:dem":141,
    "gn:feature_class":"P",
    "gn:feature_code":"PPL",
    "gn:name":"Galgodeyaya",
    "gn:population":0,
    "gn:timezone":"Asia/Colombo",
    "iso:country":"LK",
    "wof:name":"Galgodeyaya",
    "wof:placetype":"locality"
},
  "geometry": {"coordinates":[81.0633,7.1891],"type":"Point"}
}