{
  "type": "Feature",
  "properties": {
    "gn:admin1_code":"32.0",
    "gn:asciiname":"Diwulkumbura",
    "gn:country_code":"LK",
    "gn:dem":80,
    "gn:feature_class":"P",
    "gn:feature_code":"PPL",
    "gn:name":"Diwulkumbura",
    "gn:population":0,
    "gn:timezone":"Asia/Colombo",
    "iso:country":"LK",
    "name:und_x_variant":[
        "Divulkumbura"
    ],
    "wof:name":"Diwulkumbura",
    "wof:placetype":"locality"
},
  "geometry": {"coordinates":[80.30459999999999,7.3602],"type":"Point"}
}