{
  "type": "Feature",
  "properties": {
    "gn:admin1_code":"29.0",
    "gn:asciiname":"Waturakumbura",
    "gn:country_code":"LK",
    "gn:dem":561,
    "gn:feature_class":"P",
    "gn:feature_code":"PPL",
    "gn:name":"Waturakumbura",
    "gn:population":0,
    "gn:timezone":"Asia/Colombo",
    "iso:country":"LK",
    "name:ceb_x_preferred":[
        "Waturakumbura"
    ],
    "name:swe_x_preferred":[
        "Waturakumbura"
    ],
    "name:und_x_variant":[
        "Waturukumbura"
    ],
    "wof:name":"Waturakumbura",
    "wof:placetype":"locality"
},
  "geometry": {"coordinates":[80.5467,7.2978],"type":"Point"}
}