{
  "type": "Feature",
  "properties": {
    "gn:admin1_code":"36.0",
    "gn:asciiname":"Himbutuwegoda",
    "gn:country_code":"LK",
    "gn:dem":9,
    "gn:feature_class":"P",
    "gn:feature_code":"PPL",
    "gn:name":"Himbutuwegoda",
    "gn:population":0,
    "gn:timezone":"Asia/Colombo",
    "iso:country":"LK",
    "name:und_x_variant":[
        "Himbutuwelgoda"
    ],
    "wof:name":"Himbutuwegoda",
    "wof:placetype":"locality"
},
  "geometry": {"coordinates":[79.9122,6.9658],"type":"Point"}
}