{
  "type": "Feature",
  "properties": {
    "gn:admin1_code":"32.0",
    "gn:asciiname":"Olagama",
    "gn:country_code":"LK",
    "gn:dem":167,
    "gn:feature_class":"P",
    "gn:feature_code":"PPL",
    "gn:name":"Olagama",
    "gn:population":0,
    "gn:timezone":"Asia/Colombo",
    "iso:country":"LK",
    "name:ceb_x_preferred":[
        "Olagama"
    ],
    "name:swe_x_preferred":[
        "Olagama"
    ],
    "wof:name":"Olagama",
    "wof:placetype":"locality"
},
  "geometry": {"coordinates":[80.51139999999999,7.5093],"type":"Point"}
}