{
  "type": "Feature",
  "properties": {
    "gn:admin1_code":"30.0",
    "gn:asciiname":"Niyangama",
    "gn:country_code":"LK",
    "gn:dem":89,
    "gn:feature_class":"P",
    "gn:feature_code":"PPL",
    "gn:name":"Niyangama",
    "gn:population":0,
    "gn:timezone":"Asia/Colombo",
    "iso:country":"LK",
    "name:und_x_variant":[
        "Niangama",
        "Niyangama"
    ],
    "wof:name":"Niyangama",
    "wof:placetype":"locality"
},
  "geometry": {"coordinates":[80.33410000000001,8.4222],"type":"Point"}
}