{
  "type": "Feature",
  "properties": {
    "gn:admin1_code":"29.0",
    "gn:asciiname":"Marguerita",
    "gn:country_code":"LK",
    "gn:dem":1681,
    "gn:feature_class":"P",
    "gn:feature_code":"PPL",
    "gn:name":"Marguerita",
    "gn:population":0,
    "gn:timezone":"Asia/Colombo",
    "iso:country":"LK",
    "wof:name":"Marguerita",
    "wof:placetype":"locality"
},
  "geometry": {"coordinates":[80.79340000000001,7.0466],"type":"Point"}
}