{
  "type": "Feature",
  "properties": {
    "gn:admin1_code":"32.0",
    "gn:asciiname":"Panadaragama",
    "gn:cc2":"LK",
    "gn:country_code":"LK",
    "gn:dem":106,
    "gn:feature_class":"P",
    "gn:feature_code":"PPL",
    "gn:name":"Panadaragama",
    "gn:population":0,
    "gn:timezone":"Asia/Colombo",
    "iso:country":"LK",
    "name:und_x_variant":[
        "Panaduragama",
        "Panadaragama"
    ],
    "wof:name":"Panadaragama",
    "wof:placetype":"locality"
},
  "geometry": {"coordinates":[80.21666999999999,7.86667],"type":"Point"}
}