{
  "type": "Feature",
  "properties": {
    "gn:admin1_code":"32.0",
    "gn:asciiname":"Ambokkagma",
    "gn:country_code":"LK",
    "gn:dem":96,
    "gn:feature_class":"P",
    "gn:feature_code":"PPL",
    "gn:name":"Ambokkagma",
    "gn:population":0,
    "gn:timezone":"Asia/Colombo",
    "iso:country":"LK",
    "wof:name":"Ambokkagma",
    "wof:placetype":"locality"
},
  "geometry": {"coordinates":[80.3646,7.6479],"type":"Point"}
}