{
  "type": "Feature",
  "properties": {
    "gn:admin1_code":"37.0",
    "gn:asciiname":"Malwatta",
    "gn:country_code":"LK",
    "gn:dem":16,
    "gn:feature_class":"P",
    "gn:feature_code":"PPL",
    "gn:name":"Malwatta",
    "gn:population":0,
    "gn:timezone":"Asia/Colombo",
    "iso:country":"LK",
    "name:und_x_variant":[
        "Malvattai",
        "Malwattai",
        "Malwatta"
    ],
    "wof:name":"Malwatta",
    "wof:placetype":"locality"
},
  "geometry": {"coordinates":[81.73333000000002,7.33333],"type":"Point"}
}