{
  "type": "Feature",
  "properties": {
    "gn:admin1_code":"29.0",
    "gn:asciiname":"Dambalagala Colony",
    "gn:country_code":"LK",
    "gn:dem":597,
    "gn:feature_class":"P",
    "gn:feature_code":"PPL",
    "gn:name":"Dambalagala Colony",
    "gn:population":0,
    "gn:timezone":"Asia/Colombo",
    "iso:country":"LK",
    "wof:name":"Dambalagala Colony",
    "wof:placetype":"locality"
},
  "geometry": {"coordinates":[80.6878,7.5707],"type":"Point"}
}