{
  "type": "Feature",
  "properties": {
    "gn:admin1_code":"34.0",
    "gn:asciiname":"Kadawara",
    "gn:country_code":"LK",
    "gn:dem":69,
    "gn:feature_class":"P",
    "gn:feature_code":"PPL",
    "gn:name":"Kadawara",
    "gn:population":0,
    "gn:timezone":"Asia/Colombo",
    "iso:country":"LK",
    "wof:name":"Kadawara",
    "wof:placetype":"locality"
},
  "geometry": {"coordinates":[81.164,6.3309],"type":"Point"}
}