{
  "type": "Feature",
  "properties": {
    "gn:admin1_code":"29.0",
    "gn:asciiname":"Rozellagama",
    "gn:country_code":"LK",
    "gn:dem":1262,
    "gn:feature_class":"P",
    "gn:feature_code":"PPL",
    "gn:name":"Rozellagama",
    "gn:population":0,
    "gn:timezone":"Asia/Colombo",
    "iso:country":"LK",
    "wof:name":"Rozellagama",
    "wof:placetype":"locality"
},
  "geometry": {"coordinates":[80.5515,6.9162],"type":"Point"}
}