{
  "type": "Feature",
  "properties": {
    "gn:admin1_code":"29.0",
    "gn:asciiname":"Perawanguwa",
    "gn:country_code":"LK",
    "gn:dem":788,
    "gn:feature_class":"P",
    "gn:feature_code":"PPL",
    "gn:name":"Perawanguwa",
    "gn:population":0,
    "gn:timezone":"Asia/Colombo",
    "iso:country":"LK",
    "wof:name":"Perawanguwa",
    "wof:placetype":"locality"
},
  "geometry": {"coordinates":[80.7784,7.1905],"type":"Point"}
}