{
  "type": "Feature",
  "properties": {
    "gn:admin1_code":"37.0",
    "gn:asciiname":"Kuddampuli",
    "gn:country_code":"LK",
    "gn:dem":4,
    "gn:feature_class":"P",
    "gn:feature_code":"PPL",
    "gn:name":"Kuddampuli",
    "gn:population":0,
    "gn:timezone":"Asia/Colombo",
    "iso:country":"LK",
    "wof:name":"Kuddampuli",
    "wof:placetype":"locality"
},
  "geometry": {"coordinates":[81.11667,8.48333],"type":"Point"}
}