{
  "type": "Feature",
  "properties": {
    "gn:admin1_code":"38.0",
    "gn:asciiname":"Perunkadu South",
    "gn:country_code":"LK",
    "gn:dem":5,
    "gn:feature_class":"P",
    "gn:feature_code":"PPL",
    "gn:name":"Perunkadu South",
    "gn:population":0,
    "gn:timezone":"Asia/Colombo",
    "iso:country":"LK",
    "wof:name":"Perunkadu South",
    "wof:placetype":"locality"
},
  "geometry": {"coordinates":[79.82380000000001,9.5793],"type":"Point"}
}