{
  "type": "Feature",
  "properties": {
    "gn:admin1_code":"38.0",
    "gn:asciiname":"Kokkuvil",
    "gn:country_code":"LK",
    "gn:dem":12,
    "gn:feature_class":"P",
    "gn:feature_code":"PPL",
    "gn:name":"Kokkuvil",
    "gn:population":0,
    "gn:timezone":"Asia/Colombo",
    "iso:country":"LK",
    "name:ceb_x_preferred":[
        "Kokkuvil"
    ],
    "name:swe_x_preferred":[
        "Kokkuvil"
    ],
    "name:tam_x_preferred":[
        "\u0b95\u0bca\u0b95\u0bcd\u0b95\u0bc1\u0bb5\u0bbf\u0bb2\u0bcd"
    ],
    "wof:name":"Kokkuvil",
    "wof:placetype":"locality"
},
  "geometry": {"coordinates":[80.023,9.6959],"type":"Point"}
}