{
  "type": "Feature",
  "properties": {
    "gn:admin1_code":"37.0",
    "gn:asciiname":"Vayiriuttu",
    "gn:country_code":"LK",
    "gn:dem":29,
    "gn:feature_class":"P",
    "gn:feature_code":"PPL",
    "gn:name":"Vayiriuttu",
    "gn:population":0,
    "gn:timezone":"Asia/Colombo",
    "iso:country":"LK",
    "wof:name":"Vayiriuttu",
    "wof:placetype":"locality"
},
  "geometry": {"coordinates":[81.1614,8.5648],"type":"Point"}
}