{
  "type": "Feature",
  "properties": {
    "gn:admin1_code":"32.0",
    "gn:asciiname":"Koongaswela",
    "gn:country_code":"LK",
    "gn:dem":125,
    "gn:feature_class":"P",
    "gn:feature_code":"PPL",
    "gn:name":"Koongaswela",
    "gn:population":0,
    "gn:timezone":"Asia/Colombo",
    "iso:country":"LK",
    "name:und_x_variant":[
        "Kongaswala"
    ],
    "wof:name":"Koongaswela",
    "wof:placetype":"locality"
},
  "geometry": {"coordinates":[80.4166,7.5063],"type":"Point"}
}