{
  "type": "Feature",
  "properties": {
    "gn:admin1_code":"32.0",
    "gn:asciiname":"Kosgahapitiya",
    "gn:country_code":"LK",
    "gn:dem":132,
    "gn:feature_class":"P",
    "gn:feature_code":"PPL",
    "gn:name":"Kosgahapitiya",
    "gn:population":0,
    "gn:timezone":"Asia/Colombo",
    "iso:country":"LK",
    "wof:name":"Kosgahapitiya",
    "wof:placetype":"locality"
},
  "geometry": {"coordinates":[80.4357,7.546],"type":"Point"}
}