{
  "type": "Feature",
  "properties": {
    "gn:admin1_code":"30.0",
    "gn:asciiname":"Nelikulama",
    "gn:cc2":"LK",
    "gn:country_code":"LK",
    "gn:dem":113,
    "gn:feature_class":"P",
    "gn:feature_code":"PPL",
    "gn:name":"Nelikulama",
    "gn:population":0,
    "gn:timezone":"Asia/Colombo",
    "iso:country":"LK",
    "name:und_x_variant":[
        "Nellikulama",
        "Nelikulama"
    ],
    "wof:name":"Nelikulama",
    "wof:placetype":"locality"
},
  "geometry": {"coordinates":[80.41667,8.21667],"type":"Point"}
}