{
  "type": "Feature",
  "properties": {
    "gn:admin1_code":"34.0",
    "gn:asciiname":"Halpandeniya",
    "gn:country_code":"LK",
    "gn:dem":47,
    "gn:feature_class":"P",
    "gn:feature_code":"PPL",
    "gn:name":"Halpandeniya",
    "gn:population":0,
    "gn:timezone":"Asia/Colombo",
    "iso:country":"LK",
    "wof:name":"Halpandeniya",
    "wof:placetype":"locality"
},
  "geometry": {"coordinates":[80.7379,6.1121],"type":"Point"}
}