{
  "type": "Feature",
  "properties": {
    "gn:admin1_code":"33.0",
    "gn:asciiname":"Millawitiya",
    "gn:country_code":"LK",
    "gn:dem":26,
    "gn:feature_class":"P",
    "gn:feature_code":"PPL",
    "gn:name":"Millawitiya",
    "gn:population":0,
    "gn:timezone":"Asia/Colombo",
    "iso:country":"LK",
    "wof:name":"Millawitiya",
    "wof:placetype":"locality"
},
  "geometry": {"coordinates":[80.3365,6.792],"type":"Point"}
}