{
  "type": "Feature",
  "properties": {
    "gn:admin1_code":"36.0",
    "gn:asciiname":"Wagawathugoda",
    "gn:country_code":"LK",
    "gn:dem":30,
    "gn:feature_class":"P",
    "gn:feature_code":"PPL",
    "gn:name":"Wagawathugoda",
    "gn:population":0,
    "gn:timezone":"Asia/Colombo",
    "iso:country":"LK",
    "wof:name":"Wagawathugoda",
    "wof:placetype":"locality"
},
  "geometry": {"coordinates":[80.07989999999999,6.7607],"type":"Point"}
}