{
  "type": "Feature",
  "properties": {
    "gn:admin1_code":"35.0",
    "gn:asciiname":"Bulupitiya",
    "gn:country_code":"LK",
    "gn:dem":225,
    "gn:feature_class":"P",
    "gn:feature_code":"PPL",
    "gn:name":"Bulupitiya",
    "gn:population":0,
    "gn:timezone":"Asia/Colombo",
    "iso:country":"LK",
    "wof:name":"Bulupitiya",
    "wof:placetype":"locality"
},
  "geometry": {"coordinates":[81.33333,7.25],"type":"Point"}
}