{
  "type": "Feature",
  "properties": {
    "gn:admin1_code":"29.0",
    "gn:asciiname":"Mahara",
    "gn:country_code":"LK",
    "gn:dem":484,
    "gn:feature_class":"P",
    "gn:feature_code":"PPL",
    "gn:name":"Mahara",
    "gn:population":0,
    "gn:timezone":"Asia/Colombo",
    "iso:country":"LK",
    "wof:name":"Mahara",
    "wof:placetype":"locality"
},
  "geometry": {"coordinates":[80.5724,7.1602],"type":"Point"}
}