{
  "type": "Feature",
  "properties": {
    "gn:admin1_code":"35.0",
    "gn:asciiname":"Kebillawela South",
    "gn:country_code":"LK",
    "gn:dem":1368,
    "gn:feature_class":"P",
    "gn:feature_code":"PPL",
    "gn:name":"Kebillawela South",
    "gn:population":0,
    "gn:timezone":"Asia/Colombo",
    "iso:country":"LK",
    "wof:name":"Kebillawela South",
    "wof:placetype":"locality"
},
  "geometry": {"coordinates":[81.0017,6.8106],"type":"Point"}
}