{
  "type": "Feature",
  "properties": {
    "gn:admin1_code":"30.0",
    "gn:asciiname":"Pangurugahagama",
    "gn:cc2":"LK",
    "gn:country_code":"LK",
    "gn:dem":166,
    "gn:feature_class":"P",
    "gn:feature_code":"PPL",
    "gn:name":"Pangurugahagama",
    "gn:population":0,
    "gn:timezone":"Asia/Colombo",
    "iso:country":"LK",
    "name:und_x_variant":[
        "Pangaruwagama",
        "Pangurugahagama"
    ],
    "wof:name":"Pangurugahagama",
    "wof:placetype":"locality"
},
  "geometry": {"coordinates":[80.59999999999999,7.86667],"type":"Point"}
}