{
  "type": "Feature",
  "properties": {
    "gn:admin1_code":"35.0",
    "gn:asciiname":"Ledgerwatta",
    "gn:country_code":"LK",
    "gn:dem":1001,
    "gn:feature_class":"P",
    "gn:feature_code":"PPL",
    "gn:name":"Ledgerwatta",
    "gn:population":0,
    "gn:timezone":"Asia/Colombo",
    "iso:country":"LK",
    "wof:name":"Ledgerwatta",
    "wof:placetype":"locality"
},
  "geometry": {"coordinates":[80.9971,7.0245],"type":"Point"}
}