{
  "type": "Feature",
  "properties": {
    "gn:admin1_code":"32.0",
    "gn:asciiname":"Medawewa",
    "gn:country_code":"LK",
    "gn:dem":66,
    "gn:feature_class":"P",
    "gn:feature_code":"PPL",
    "gn:name":"Medawewa",
    "gn:population":0,
    "gn:timezone":"Asia/Colombo",
    "iso:country":"LK",
    "wof:name":"Medawewa",
    "wof:placetype":"locality"
},
  "geometry": {"coordinates":[80.13209999999999,8.122],"type":"Point"}
}