{
  "type": "Feature",
  "properties": {
    "gn:admin1_code":"32.0",
    "gn:asciiname":"Habarewa",
    "gn:cc2":"LK",
    "gn:country_code":"LK",
    "gn:dem":71,
    "gn:feature_class":"P",
    "gn:feature_code":"PPL",
    "gn:name":"Habarewa",
    "gn:population":0,
    "gn:timezone":"Asia/Colombo",
    "iso:country":"LK",
    "name:und_x_variant":[
        "Haberewa",
        "Habarewa"
    ],
    "wof:name":"Habarewa",
    "wof:placetype":"locality"
},
  "geometry": {"coordinates":[80.09999999999999,7.81667],"type":"Point"}
}