{
  "type": "Feature",
  "properties": {
    "gn:admin1_code":"33.0",
    "gn:asciiname":"Wattehena",
    "gn:country_code":"LK",
    "gn:dem":359,
    "gn:feature_class":"P",
    "gn:feature_code":"PPL",
    "gn:name":"Wattehena",
    "gn:population":0,
    "gn:timezone":"Asia/Colombo",
    "iso:country":"LK",
    "name:ceb_x_preferred":[
        "Wattehena"
    ],
    "name:swe_x_preferred":[
        "Wattehena"
    ],
    "wof:name":"Wattehena",
    "wof:placetype":"locality"
},
  "geometry": {"coordinates":[80.47800000000002,6.5506],"type":"Point"}
}