{
  "type": "Feature",
  "properties": {
    "gn:admin1_code":"32.0",
    "gn:asciiname":"Wilagama",
    "gn:country_code":"LK",
    "gn:dem":32,
    "gn:feature_class":"P",
    "gn:feature_code":"PPL",
    "gn:name":"Wilagama",
    "gn:population":0,
    "gn:timezone":"Asia/Colombo",
    "iso:country":"LK",
    "name:und_x_variant":[
        "Welagama",
        "Wilagama"
    ],
    "wof:name":"Wilagama",
    "wof:placetype":"locality"
},
  "geometry": {"coordinates":[80.0219,7.7116],"type":"Point"}
}