{
  "type": "Feature",
  "properties": {
    "gn:admin1_code":"33.0",
    "gn:asciiname":"Amunuthenna Pahala",
    "gn:country_code":"LK",
    "gn:dem":499,
    "gn:feature_class":"P",
    "gn:feature_code":"PPL",
    "gn:name":"Amunuthenna Pahala",
    "gn:population":0,
    "gn:timezone":"Asia/Colombo",
    "iso:country":"LK",
    "wof:name":"Amunuthenna Pahala",
    "wof:placetype":"locality"
},
  "geometry": {"coordinates":[80.5269,6.7197],"type":"Point"}
}