{
  "type": "Feature",
  "properties": {
    "gn:admin1_code":"30.0",
    "gn:asciiname":"Ihala Hammillawa",
    "gn:country_code":"LK",
    "gn:dem":101,
    "gn:feature_class":"P",
    "gn:feature_code":"PPL",
    "gn:name":"Ihala Hammillawa",
    "gn:population":0,
    "gn:timezone":"Asia/Colombo",
    "iso:country":"LK",
    "wof:name":"Ihala Hammillawa",
    "wof:placetype":"locality"
},
  "geometry": {"coordinates":[80.72790000000001,8.4627],"type":"Point"}
}