{
  "type": "Feature",
  "properties": {
    "gn:admin1_code":"32.0",
    "gn:asciiname":"Kosgahagoda",
    "gn:country_code":"LK",
    "gn:dem":49,
    "gn:feature_class":"P",
    "gn:feature_code":"PPL",
    "gn:name":"Kosgahagoda",
    "gn:population":0,
    "gn:timezone":"Asia/Colombo",
    "iso:country":"LK",
    "wof:name":"Kosgahagoda",
    "wof:placetype":"locality"
},
  "geometry": {"coordinates":[80.0377,7.6785],"type":"Point"}
}