{
  "type": "Feature",
  "properties": {
    "gn:admin1_code":"38.0",
    "gn:asciiname":"Antonimelingikulam",
    "gn:country_code":"LK",
    "gn:dem":8,
    "gn:feature_class":"P",
    "gn:feature_code":"PPL",
    "gn:name":"Antonimelingikulam",
    "gn:population":0,
    "gn:timezone":"Asia/Colombo",
    "iso:country":"LK",
    "name:und_x_variant":[
        "Antonimelingilkulam"
    ],
    "wof:name":"Antonimelingikulam",
    "wof:placetype":"locality"
},
  "geometry": {"coordinates":[79.9457,8.7856],"type":"Point"}
}