{
  "type": "Feature",
  "properties": {
    "gn:admin1_code":"34.0",
    "gn:asciiname":"Urugamuwa West",
    "gn:country_code":"LK",
    "gn:dem":104,
    "gn:feature_class":"P",
    "gn:feature_code":"PPL",
    "gn:name":"Urugamuwa West",
    "gn:population":0,
    "gn:timezone":"Asia/Colombo",
    "iso:country":"LK",
    "wof:name":"Urugamuwa West",
    "wof:placetype":"locality"
},
  "geometry": {"coordinates":[80.65000000000001,6.01667],"type":"Point"}
}