{
  "type": "Feature",
  "properties": {
    "gn:admin1_code":"35.0",
    "gn:asciiname":"Dambagolla",
    "gn:country_code":"LK",
    "gn:dem":132,
    "gn:feature_class":"P",
    "gn:feature_code":"PPL",
    "gn:name":"Dambagolla",
    "gn:population":0,
    "gn:timezone":"Asia/Colombo",
    "iso:country":"LK",
    "wof:name":"Dambagolla",
    "wof:placetype":"locality"
},
  "geometry": {"coordinates":[81.46666999999999,7.31667],"type":"Point"}
}