{
  "type": "Feature",
  "properties": {
    "gn:admin1_code":"35.0",
    "gn:asciiname":"Kandearawa",
    "gn:country_code":"LK",
    "gn:dem":410,
    "gn:feature_class":"P",
    "gn:feature_code":"PPL",
    "gn:name":"Kandearawa",
    "gn:population":0,
    "gn:timezone":"Asia/Colombo",
    "iso:country":"LK",
    "wof:name":"Kandearawa",
    "wof:placetype":"locality"
},
  "geometry": {"coordinates":[80.9927,7.0846],"type":"Point"}
}