{
  "type": "Feature",
  "properties": {
    "gn:admin1_code":"32.0",
    "gn:asciiname":"Thimbiriyagaswela",
    "gn:country_code":"LK",
    "gn:dem":20,
    "gn:feature_class":"P",
    "gn:feature_code":"PPL",
    "gn:name":"Thimbiriyagaswela",
    "gn:population":0,
    "gn:timezone":"Asia/Colombo",
    "iso:country":"LK",
    "name:und_x_variant":[
        "Timbirigaswela",
        "Timbiriyagaswela",
        "Thimbiriyagaswela"
    ],
    "wof:name":"Thimbiriyagaswela",
    "wof:placetype":"locality"
},
  "geometry": {"coordinates":[79.8895,7.4835],"type":"Point"}
}