{
  "type": "Feature",
  "properties": {
    "gn:admin1_code":"32.0",
    "gn:asciiname":"Hengeulla",
    "gn:country_code":"LK",
    "gn:dem":37,
    "gn:feature_class":"P",
    "gn:feature_code":"PPL",
    "gn:name":"Hengeulla",
    "gn:population":0,
    "gn:timezone":"Asia/Colombo",
    "iso:country":"LK",
    "wof:name":"Hengeulla",
    "wof:placetype":"locality"
},
  "geometry": {"coordinates":[80.06667,7.43333],"type":"Point"}
}