{
  "type": "Feature",
  "properties": {
    "gn:admin1_code":"29.0",
    "gn:asciiname":"Warakadeniya",
    "gn:country_code":"LK",
    "gn:dem":513,
    "gn:feature_class":"P",
    "gn:feature_code":"PPL",
    "gn:name":"Warakadeniya",
    "gn:population":0,
    "gn:timezone":"Asia/Colombo",
    "iso:country":"LK",
    "wof:name":"Warakadeniya",
    "wof:placetype":"locality"
},
  "geometry": {"coordinates":[80.5796,7.3704],"type":"Point"}
}