{
  "type": "Feature",
  "properties": {
    "gn:admin1_code":"33.0",
    "gn:asciiname":"Undugodapitiya",
    "gn:country_code":"LK",
    "gn:dem":82,
    "gn:feature_class":"P",
    "gn:feature_code":"PPL",
    "gn:name":"Undugodapitiya",
    "gn:population":0,
    "gn:timezone":"Asia/Colombo",
    "iso:country":"LK",
    "wof:name":"Undugodapitiya",
    "wof:placetype":"locality"
},
  "geometry": {"coordinates":[80.3193,7.2884],"type":"Point"}
}