{
  "type": "Feature",
  "properties": {
    "gn:admin1_code":"33.0",
    "gn:asciiname":"Menerigama",
    "gn:country_code":"LK",
    "gn:dem":260,
    "gn:feature_class":"P",
    "gn:feature_code":"PPL",
    "gn:name":"Menerigama",
    "gn:population":0,
    "gn:timezone":"Asia/Colombo",
    "iso:country":"LK",
    "wof:name":"Menerigama",
    "wof:placetype":"locality"
},
  "geometry": {"coordinates":[80.4603,7.2413],"type":"Point"}
}