{
  "type": "Feature",
  "properties": {
    "gn:admin1_code":"33.0",
    "gn:asciiname":"Palle-Pelpita",
    "gn:country_code":"LK",
    "gn:dem":43,
    "gn:feature_class":"P",
    "gn:feature_code":"PPL",
    "gn:name":"Palle-Pelpita",
    "gn:population":0,
    "gn:timezone":"Asia/Colombo",
    "iso:country":"LK",
    "wof:name":"Palle-Pelpita",
    "wof:placetype":"locality"
},
  "geometry": {"coordinates":[80.2743,7.1089],"type":"Point"}
}