{
  "type": "Feature",
  "properties": {
    "gn:admin1_code":"29.0",
    "gn:asciiname":"Kurupanwela Udagama",
    "gn:country_code":"LK",
    "gn:dem":958,
    "gn:feature_class":"P",
    "gn:feature_code":"PPL",
    "gn:name":"Kurupanwela Udagama",
    "gn:population":0,
    "gn:timezone":"Asia/Colombo",
    "iso:country":"LK",
    "wof:name":"Kurupanwela Udagama",
    "wof:placetype":"locality"
},
  "geometry": {"coordinates":[80.91,7.014],"type":"Point"}
}