{
  "type": "Feature",
  "properties": {
    "gn:admin1_code":"29.0",
    "gn:asciiname":"Kumbukwela",
    "gn:country_code":"LK",
    "gn:dem":1333,
    "gn:feature_class":"P",
    "gn:feature_code":"PPL",
    "gn:name":"Kumbukwela",
    "gn:population":0,
    "gn:timezone":"Asia/Colombo",
    "iso:country":"LK",
    "wof:name":"Kumbukwela",
    "wof:placetype":"locality"
},
  "geometry": {"coordinates":[80.87569999999999,7.0612],"type":"Point"}
}