{
  "type": "Feature",
  "properties": {
    "gn:admin1_code":"29.0",
    "gn:asciiname":"Maluwagoda",
    "gn:country_code":"LK",
    "gn:dem":881,
    "gn:feature_class":"P",
    "gn:feature_code":"PPL",
    "gn:name":"Maluwagoda",
    "gn:population":0,
    "gn:timezone":"Asia/Colombo",
    "iso:country":"LK",
    "wof:name":"Maluwagoda",
    "wof:placetype":"locality"
},
  "geometry": {"coordinates":[80.9149,7.1219],"type":"Point"}
}