{
  "type": "Feature",
  "properties": {
    "gn:admin1_code":"34.0",
    "gn:asciiname":"Waduwadeniya East",
    "gn:country_code":"LK",
    "gn:dem":131,
    "gn:feature_class":"P",
    "gn:feature_code":"PPL",
    "gn:name":"Waduwadeniya East",
    "gn:population":0,
    "gn:timezone":"Asia/Colombo",
    "iso:country":"LK",
    "wof:name":"Waduwadeniya East",
    "wof:placetype":"locality"
},
  "geometry": {"coordinates":[80.6491,6.202],"type":"Point"}
}