{
  "type": "Feature",
  "properties": {
    "gn:admin1_code":"29.0",
    "gn:asciiname":"Pussalakanda",
    "gn:country_code":"LK",
    "gn:dem":389,
    "gn:feature_class":"P",
    "gn:feature_code":"PPL",
    "gn:name":"Pussalakanda",
    "gn:population":0,
    "gn:timezone":"Asia/Colombo",
    "iso:country":"LK",
    "name:und_x_variant":[
        "Pussalakandura"
    ],
    "wof:name":"Pussalakanda",
    "wof:placetype":"locality"
},
  "geometry": {"coordinates":[80.8657,7.1556],"type":"Point"}
}