{
  "type": "Feature",
  "properties": {
    "gn:admin1_code":"32.0",
    "gn:asciiname":"Anderawewa",
    "gn:country_code":"LK",
    "gn:dem":97,
    "gn:feature_class":"P",
    "gn:feature_code":"PPL",
    "gn:name":"Anderawewa",
    "gn:population":0,
    "gn:timezone":"Asia/Colombo",
    "iso:country":"LK",
    "name:und_x_variant":[
        "Andarawewa"
    ],
    "wof:name":"Anderawewa",
    "wof:placetype":"locality"
},
  "geometry": {"coordinates":[80.28699999999998,7.9094],"type":"Point"}
}