{
  "type": "Feature",
  "properties": {
    "gn:admin1_code":"36.0",
    "gn:asciiname":"Nakandapola",
    "gn:country_code":"LK",
    "gn:dem":56,
    "gn:feature_class":"P",
    "gn:feature_code":"PPL",
    "gn:name":"Nakandapola",
    "gn:population":0,
    "gn:timezone":"Asia/Colombo",
    "iso:country":"LK",
    "wof:name":"Nakandapola",
    "wof:placetype":"locality"
},
  "geometry": {"coordinates":[80.0534,7.0113],"type":"Point"}
}