{
  "type": "Feature",
  "properties": {
    "gn:admin1_code":"33.0",
    "gn:asciiname":"Mawella",
    "gn:country_code":"LK",
    "gn:dem":180,
    "gn:feature_class":"P",
    "gn:feature_code":"PPL",
    "gn:name":"Mawella",
    "gn:population":0,
    "gn:timezone":"Asia/Colombo",
    "iso:country":"LK",
    "name:und_x_variant":[
        "Mawella South",
        "Mawella"
    ],
    "wof:name":"Mawella",
    "wof:placetype":"locality"
},
  "geometry": {"coordinates":[80.4704,6.6887],"type":"Point"}
}