{
  "type": "Feature",
  "properties": {
    "gn:admin1_code":"32.0",
    "gn:asciiname":"Narangasyaya",
    "gn:country_code":"LK",
    "gn:dem":47,
    "gn:feature_class":"P",
    "gn:feature_code":"PPL",
    "gn:name":"Narangasyaya",
    "gn:population":0,
    "gn:timezone":"Asia/Colombo",
    "iso:country":"LK",
    "wof:name":"Narangasyaya",
    "wof:placetype":"locality"
},
  "geometry": {"coordinates":[80.0538,7.3589],"type":"Point"}
}