{
  "type": "Feature",
  "properties": {
    "gn:admin1_code":"30.0",
    "gn:asciiname":"Weragala",
    "gn:country_code":"LK",
    "gn:dem":168,
    "gn:feature_class":"P",
    "gn:feature_code":"PPL",
    "gn:name":"Weragala",
    "gn:population":0,
    "gn:timezone":"Asia/Colombo",
    "iso:country":"LK",
    "wof:name":"Weragala",
    "wof:placetype":"locality"
},
  "geometry": {"coordinates":[80.7175,8.0923],"type":"Point"}
}