{
  "type": "Feature",
  "properties": {
    "gn:admin1_code":"33.0",
    "gn:asciiname":"Toragala",
    "gn:country_code":"LK",
    "gn:dem":68,
    "gn:feature_class":"P",
    "gn:feature_code":"PPL",
    "gn:name":"Toragala",
    "gn:population":0,
    "gn:timezone":"Asia/Colombo",
    "iso:country":"LK",
    "wof:name":"Toragala",
    "wof:placetype":"locality"
},
  "geometry": {"coordinates":[80.893,6.2616],"type":"Point"}
}