{
  "type": "Feature",
  "properties": {
    "gn:admin1_code":"36.0",
    "gn:asciiname":"Pepolgahadeniya",
    "gn:country_code":"LK",
    "gn:dem":23,
    "gn:feature_class":"P",
    "gn:feature_code":"PPL",
    "gn:name":"Pepolgahadeniya",
    "gn:population":0,
    "gn:timezone":"Asia/Colombo",
    "iso:country":"LK",
    "wof:name":"Pepolgahadeniya",
    "wof:placetype":"locality"
},
  "geometry": {"coordinates":[80.0309,7.0774],"type":"Point"}
}