{
  "type": "Feature",
  "properties": {
    "gn:admin1_code":"36.0",
    "gn:asciiname":"Gallasse",
    "gn:country_code":"LK",
    "gn:dem":22,
    "gn:feature_class":"P",
    "gn:feature_code":"PPL",
    "gn:name":"Gallasse",
    "gn:population":0,
    "gn:timezone":"Asia/Colombo",
    "iso:country":"LK",
    "wof:name":"Gallasse",
    "wof:placetype":"locality"
},
  "geometry": {"coordinates":[79.9871,6.5573],"type":"Point"}
}