{
  "type": "Feature",
  "properties": {
    "gn:admin1_code":"32.0",
    "gn:asciiname":"Madawa Kanduboda",
    "gn:country_code":"LK",
    "gn:dem":130,
    "gn:feature_class":"P",
    "gn:feature_code":"PPL",
    "gn:name":"Madawa Kanduboda",
    "gn:population":0,
    "gn:timezone":"Asia/Colombo",
    "iso:country":"LK",
    "wof:name":"Madawa Kanduboda",
    "wof:placetype":"locality"
},
  "geometry": {"coordinates":[80.4312,7.4739],"type":"Point"}
}