{
  "type": "Feature",
  "properties": {
    "gn:admin1_code":"32.0",
    "gn:asciiname":"Miyanadeniya",
    "gn:country_code":"LK",
    "gn:dem":213,
    "gn:feature_class":"P",
    "gn:feature_code":"PPL",
    "gn:name":"Miyanadeniya",
    "gn:population":0,
    "gn:timezone":"Asia/Colombo",
    "iso:country":"LK",
    "wof:name":"Miyanadeniya",
    "wof:placetype":"locality"
},
  "geometry": {"coordinates":[80.5108,7.4437],"type":"Point"}
}