{
  "type": "Feature",
  "properties": {
    "gn:admin1_code":"29.0",
    "gn:asciiname":"Gonapitiya",
    "gn:country_code":"LK",
    "gn:dem":1609,
    "gn:feature_class":"P",
    "gn:feature_code":"PPL",
    "gn:name":"Gonapitiya",
    "gn:population":0,
    "gn:timezone":"Asia/Colombo",
    "iso:country":"LK",
    "wof:name":"Gonapitiya",
    "wof:placetype":"locality"
},
  "geometry": {"coordinates":[80.797,7.0519],"type":"Point"}
}