{
  "type": "Feature",
  "properties": {
    "gn:admin1_code":"36.0",
    "gn:asciiname":"Kannimahara",
    "gn:country_code":"LK",
    "gn:dem":41,
    "gn:feature_class":"P",
    "gn:feature_code":"PPL",
    "gn:name":"Kannimahara",
    "gn:population":0,
    "gn:timezone":"Asia/Colombo",
    "iso:country":"LK",
    "wof:name":"Kannimahara",
    "wof:placetype":"locality"
},
  "geometry": {"coordinates":[80.09520000000001,7.0462],"type":"Point"}
}