{
  "type": "Feature",
  "properties": {
    "gn:admin1_code":"29.0",
    "gn:asciiname":"Rattotamale Colony",
    "gn:country_code":"LK",
    "gn:dem":489,
    "gn:feature_class":"P",
    "gn:feature_code":"PPL",
    "gn:name":"Rattotamale Colony",
    "gn:population":0,
    "gn:timezone":"Asia/Colombo",
    "iso:country":"LK",
    "wof:name":"Rattotamale Colony",
    "wof:placetype":"locality"
},
  "geometry": {"coordinates":[80.6748,7.534],"type":"Point"}
}