{
  "type": "Feature",
  "properties": {
    "gn:admin1_code":"35.0",
    "gn:asciiname":"Ranulpatha",
    "gn:country_code":"LK",
    "gn:dem":1251,
    "gn:feature_class":"P",
    "gn:feature_code":"PPL",
    "gn:name":"Ranulpatha",
    "gn:population":0,
    "gn:timezone":"Asia/Colombo",
    "iso:country":"LK",
    "wof:name":"Ranulpatha",
    "wof:placetype":"locality"
},
  "geometry": {"coordinates":[81.014,6.9062],"type":"Point"}
}