{
  "type": "Feature",
  "properties": {
    "gn:admin1_code":"34.0",
    "gn:asciiname":"Padilikokmaduwa",
    "gn:country_code":"LK",
    "gn:dem":9,
    "gn:feature_class":"P",
    "gn:feature_code":"PPL",
    "gn:name":"Padilikokmaduwa",
    "gn:population":0,
    "gn:timezone":"Asia/Colombo",
    "iso:country":"LK",
    "wof:name":"Padilikokmaduwa",
    "wof:placetype":"locality"
},
  "geometry": {"coordinates":[80.43333,6.01667],"type":"Point"}
}