{
  "type": "Feature",
  "properties": {
    "gn:admin1_code":"38.0",
    "gn:asciiname":"Ketpeli",
    "gn:country_code":"LK",
    "gn:dem":11,
    "gn:feature_class":"P",
    "gn:feature_code":"PPL",
    "gn:name":"Ketpeli",
    "gn:population":0,
    "gn:timezone":"Asia/Colombo",
    "iso:country":"LK",
    "name:und_x_variant":[
        "Ketpali",
        "Ketpeli"
    ],
    "wof:name":"Ketpeli",
    "wof:placetype":"locality"
},
  "geometry": {"coordinates":[80.2174,9.643],"type":"Point"}
}