{
  "type": "Feature",
  "properties": {
    "gn:admin1_code":"36.0",
    "gn:asciiname":"Remuna",
    "gn:country_code":"LK",
    "gn:dem":14,
    "gn:feature_class":"P",
    "gn:feature_code":"PPL",
    "gn:name":"Remuna",
    "gn:population":0,
    "gn:timezone":"Asia/Colombo",
    "iso:country":"LK",
    "name:ben_x_preferred":[
        "\u09b0\u09c7\u09ae\u09c1\u09a8\u09be"
    ],
    "name:bpy_x_preferred":[
        "\u09b0\u09c7\u09ae\u09c1\u09a8\u09be"
    ],
    "name:ceb_x_preferred":[
        "Remuna"
    ],
    "name:ita_x_preferred":[
        "Remuna"
    ],
    "name:msa_x_preferred":[
        "Remuna"
    ],
    "name:nld_x_preferred":[
        "Remuna"
    ],
    "name:ori_x_preferred":[
        "\u0b30\u0b47\u0b2e\u0b41\u0b23\u0b3e"
    ],
    "name:por_x_preferred":[
        "Remuna"
    ],
    "name:rus_x_preferred":[
        "\u0420\u0435\u043c\u0443\u043d\u0430"
    ],
    "name:swe_x_preferred":[
        "Remuna"
    ],
    "name:ukr_x_preferred":[
        "\u0420\u0435\u043c\u0443\u043d\u0430"
    ],
    "name:vie_x_preferred":[
        "Remuna"
    ],
    "name:zho_x_preferred":[
        "\u96f7\u7a46\u7eb3"
    ],
    "wof:name":"Remuna",
    "wof:placetype":"locality"
},
  "geometry": {"coordinates":[80.0668,6.6795],"type":"Point"}
}