{
  "type": "Feature",
  "properties": {
    "gn:admin1_code":"33.0",
    "gn:asciiname":"Haligangoda",
    "gn:country_code":"LK",
    "gn:dem":26,
    "gn:feature_class":"P",
    "gn:feature_code":"PPL",
    "gn:name":"Haligangoda",
    "gn:population":0,
    "gn:timezone":"Asia/Colombo",
    "iso:country":"LK",
    "wof:name":"Haligangoda",
    "wof:placetype":"locality"
},
  "geometry": {"coordinates":[80.438,6.6431],"type":"Point"}
}