{
  "type": "Feature",
  "properties": {
    "gn:admin1_code":"34.0",
    "gn:asciiname":"Galpottawala",
    "gn:country_code":"LK",
    "gn:dem":40,
    "gn:feature_class":"P",
    "gn:feature_code":"PPL",
    "gn:name":"Galpottawala",
    "gn:population":0,
    "gn:timezone":"Asia/Colombo",
    "iso:country":"LK",
    "name:und_x_variant":[
        "Galpottawella",
        "Galpottawila",
        "Galpottawala"
    ],
    "wof:name":"Galpottawala",
    "wof:placetype":"locality"
},
  "geometry": {"coordinates":[80.09139999999999,6.3637],"type":"Point"}
}