{
  "type": "Feature",
  "properties": {
    "gn:admin1_code":"38.0",
    "gn:asciiname":"Kuppilan",
    "gn:country_code":"LK",
    "gn:dem":8,
    "gn:feature_class":"P",
    "gn:feature_code":"PPL",
    "gn:name":"Kuppilan",
    "gn:population":0,
    "gn:timezone":"Asia/Colombo",
    "iso:country":"LK",
    "name:tam_x_preferred":[
        "\u0b95\u0bc1\u0baa\u0bcd\u0baa\u0bbf\u0bb3\u0bbe\u0ba9\u0bcd"
    ],
    "wof:name":"Kuppilan",
    "wof:placetype":"locality"
},
  "geometry": {"coordinates":[80.0412,9.7419],"type":"Point"}
}