{
  "type": "Feature",
  "properties": {
    "gn:admin1_code":"32.0",
    "gn:asciiname":"Niraliyadda",
    "gn:country_code":"LK",
    "gn:dem":44,
    "gn:feature_class":"P",
    "gn:feature_code":"PPL",
    "gn:name":"Niraliyadda",
    "gn:population":0,
    "gn:timezone":"Asia/Colombo",
    "iso:country":"LK",
    "wof:name":"Niraliyadda",
    "wof:placetype":"locality"
},
  "geometry": {"coordinates":[80.0322,7.7298],"type":"Point"}
}