{
  "type": "Feature",
  "properties": {
    "gn:admin1_code":"34.0",
    "gn:asciiname":"Gurubebila",
    "gn:country_code":"LK",
    "gn:dem":29,
    "gn:feature_class":"P",
    "gn:feature_code":"PPL",
    "gn:name":"Gurubebila",
    "gn:population":0,
    "gn:timezone":"Asia/Colombo",
    "iso:country":"LK",
    "wof:name":"Gurubebila",
    "wof:placetype":"locality"
},
  "geometry": {"coordinates":[80.2659,6.2417],"type":"Point"}
}