{
  "type": "Feature",
  "properties": {
    "gn:admin1_code":"34.0",
    "gn:asciiname":"Tammitiya",
    "gn:country_code":"LK",
    "gn:dem":82,
    "gn:feature_class":"P",
    "gn:feature_code":"PPL",
    "gn:name":"Tammitiya",
    "gn:population":0,
    "gn:timezone":"Asia/Colombo",
    "iso:country":"LK",
    "wof:name":"Tammitiya",
    "wof:placetype":"locality"
},
  "geometry": {"coordinates":[80.3652,6.1302],"type":"Point"}
}