{
  "type": "Feature",
  "properties": {
    "gn:admin1_code":"29.0",
    "gn:asciiname":"Padupola",
    "gn:country_code":"LK",
    "gn:dem":212,
    "gn:feature_class":"P",
    "gn:feature_code":"PPL",
    "gn:name":"Padupola",
    "gn:population":0,
    "gn:timezone":"Asia/Colombo",
    "iso:country":"LK",
    "wof:name":"Padupola",
    "wof:placetype":"locality"
},
  "geometry": {"coordinates":[80.46666999999999,6.98333],"type":"Point"}
}