{
  "type": "Feature",
  "properties": {
    "gn:admin1_code":"33.0",
    "gn:asciiname":"Walsirigama",
    "gn:country_code":"LK",
    "gn:dem":193,
    "gn:feature_class":"P",
    "gn:feature_code":"PPL",
    "gn:name":"Walsirigama",
    "gn:population":0,
    "gn:timezone":"Asia/Colombo",
    "iso:country":"LK",
    "wof:name":"Walsirigama",
    "wof:placetype":"locality"
},
  "geometry": {"coordinates":[80.5325,6.6399],"type":"Point"}
}