{
  "type": "Feature",
  "properties": {
    "gn:admin1_code":"30.0",
    "gn:asciiname":"Thulaweliya",
    "gn:country_code":"LK",
    "gn:dem":70,
    "gn:feature_class":"P",
    "gn:feature_code":"PPL",
    "gn:name":"Thulaweliya",
    "gn:population":0,
    "gn:timezone":"Asia/Colombo",
    "iso:country":"LK",
    "name:und_x_variant":[
        "Tulaweliya",
        "Thulaweliya",
        "Tulawelliya"
    ],
    "wof:name":"Thulaweliya",
    "wof:placetype":"locality"
},
  "geometry": {"coordinates":[80.4179,8.5219],"type":"Point"}
}