{
  "type": "Feature",
  "properties": {
    "gn:admin1_code":"35.0",
    "gn:asciiname":"Alupota",
    "gn:country_code":"LK",
    "gn:dem":314,
    "gn:feature_class":"P",
    "gn:feature_code":"PPL",
    "gn:name":"Alupota",
    "gn:population":0,
    "gn:timezone":"Asia/Colombo",
    "iso:country":"LK",
    "wof:name":"Alupota",
    "wof:placetype":"locality"
},
  "geometry": {"coordinates":[81.2397,7.0753],"type":"Point"}
}