{
  "type": "Feature",
  "properties": {
    "gn:admin1_code":"32.0",
    "gn:asciiname":"Pahala Dummalasuriya",
    "gn:country_code":"LK",
    "gn:dem":22,
    "gn:feature_class":"P",
    "gn:feature_code":"PPL",
    "gn:name":"Pahala Dummalasuriya",
    "gn:population":0,
    "gn:timezone":"Asia/Colombo",
    "iso:country":"LK",
    "wof:name":"Pahala Dummalasuriya",
    "wof:placetype":"locality"
},
  "geometry": {"coordinates":[79.858,7.4773],"type":"Point"}
}