{
  "type": "Feature",
  "properties": {
    "gn:admin1_code":"34.0",
    "gn:asciiname":"Madapathala",
    "gn:country_code":"LK",
    "gn:dem":44,
    "gn:feature_class":"P",
    "gn:feature_code":"PPL",
    "gn:name":"Madapathala",
    "gn:population":0,
    "gn:timezone":"Asia/Colombo",
    "iso:country":"LK",
    "wof:name":"Madapathala",
    "wof:placetype":"locality"
},
  "geometry": {"coordinates":[80.2115,6.0502],"type":"Point"}
}