{
  "type": "Feature",
  "properties": {
    "gn:admin1_code":"35.0",
    "gn:asciiname":"Randeniyagama",
    "gn:country_code":"LK",
    "gn:dem":234,
    "gn:feature_class":"P",
    "gn:feature_code":"PPL",
    "gn:name":"Randeniyagama",
    "gn:population":0,
    "gn:timezone":"Asia/Colombo",
    "iso:country":"LK",
    "name:und_x_variant":[
        "Randeniya"
    ],
    "wof:name":"Randeniyagama",
    "wof:placetype":"locality"
},
  "geometry": {"coordinates":[81.10899999999999,6.7856],"type":"Point"}
}