{
  "type": "Feature",
  "properties": {
    "gn:admin1_code":"32.0",
    "gn:asciiname":"Williyemulla",
    "gn:country_code":"LK",
    "gn:dem":25,
    "gn:feature_class":"P",
    "gn:feature_code":"PPL",
    "gn:name":"Williyemulla",
    "gn:population":0,
    "gn:timezone":"Asia/Colombo",
    "iso:country":"LK",
    "name:und_x_variant":[
        "Williyamulla"
    ],
    "wof:name":"Williyemulla",
    "wof:placetype":"locality"
},
  "geometry": {"coordinates":[79.9704,7.3932],"type":"Point"}
}