{
  "type": "Feature",
  "properties": {
    "gn:admin1_code":"33.0",
    "gn:asciiname":"Pawanella",
    "gn:country_code":"LK",
    "gn:dem":502,
    "gn:feature_class":"P",
    "gn:feature_code":"PPL",
    "gn:name":"Pawanella",
    "gn:population":0,
    "gn:timezone":"Asia/Colombo",
    "iso:country":"LK",
    "wof:name":"Pawanella",
    "wof:placetype":"locality"
},
  "geometry": {"coordinates":[80.4575,6.793],"type":"Point"}
}