{
  "type": "Feature",
  "properties": {
    "gn:admin1_code":"34.0",
    "gn:asciiname":"Dalawella",
    "gn:country_code":"LK",
    "gn:dem":1,
    "gn:feature_class":"P",
    "gn:feature_code":"PPL",
    "gn:name":"Dalawella",
    "gn:population":0,
    "gn:timezone":"Asia/Colombo",
    "iso:country":"LK",
    "wof:name":"Dalawella",
    "wof:placetype":"locality"
},
  "geometry": {"coordinates":[80.16289999999999,6.071],"type":"Point"}
}