{
  "type": "Feature",
  "properties": {
    "gn:admin1_code":"37.0",
    "gn:asciiname":"Mudduchchenai",
    "gn:country_code":"LK",
    "gn:dem":9,
    "gn:feature_class":"P",
    "gn:feature_code":"PPL",
    "gn:name":"Mudduchchenai",
    "gn:population":0,
    "gn:timezone":"Asia/Colombo",
    "iso:country":"LK",
    "name:und_x_variant":[
        "Muddichchenai",
        "Mudduchchenal",
        "Mudduchchenai"
    ],
    "wof:name":"Mudduchchenai",
    "wof:placetype":"locality"
},
  "geometry": {"coordinates":[81.38333,8.26667],"type":"Point"}
}