{
  "type": "Feature",
  "properties": {
    "gn:admin1_code":"29.0",
    "gn:asciiname":"Nagalawewa",
    "gn:country_code":"LK",
    "gn:dem":199,
    "gn:feature_class":"P",
    "gn:feature_code":"PPL",
    "gn:name":"Nagalawewa",
    "gn:population":0,
    "gn:timezone":"Asia/Colombo",
    "iso:country":"LK",
    "wof:name":"Nagalawewa",
    "wof:placetype":"locality"
},
  "geometry": {"coordinates":[80.73333000000002,7.96667],"type":"Point"}
}