{
  "type": "Feature",
  "properties": {
    "gn:admin1_code":"30.0",
    "gn:asciiname":"Konwewa",
    "gn:country_code":"LK",
    "gn:dem":118,
    "gn:feature_class":"P",
    "gn:feature_code":"PPL",
    "gn:name":"Konwewa",
    "gn:population":0,
    "gn:timezone":"Asia/Colombo",
    "iso:country":"LK",
    "wof:name":"Konwewa",
    "wof:placetype":"locality"
},
  "geometry": {"coordinates":[80.70650000000001,8.4677],"type":"Point"}
}