{
  "type": "Feature",
  "properties": {
    "iso:country":"LK",
    "qs:gn_country":"LK",
    "qs:gn_fcode":"PPL",
    "qs:gn_pop":0,
    "qs:name":"Sinuggala",
    "qs:name_adm0":"Sri Lanka",
    "qs:name_adm1":"Uva",
    "qs:photos":271,
    "qs:photos_1k":55,
    "qs:photos_9k":1,
    "qs:photos_9r":4,
    "qs:photos_all":271,
    "qs:photos_sr":5,
    "qs:placetype":"Town",
    "qs:pop_sr":"0",
    "qs:woe_adm0":23424778,
    "wof:name":"Sinuggala",
    "wof:placetype":"locality"
},
  "geometry": {"coordinates":[80.8734,6.5138],"type":"Point"}
}