{
  "type": "Feature",
  "properties": {
    "gn:admin1_code":"35.0",
    "gn:asciiname":"Rathiriwewa",
    "gn:country_code":"LK",
    "gn:dem":110,
    "gn:feature_class":"P",
    "gn:feature_code":"PPL",
    "gn:name":"Rathiriwewa",
    "gn:population":0,
    "gn:timezone":"Asia/Colombo",
    "iso:country":"LK",
    "wof:name":"Rathiriwewa",
    "wof:placetype":"locality"
},
  "geometry": {"coordinates":[81.3661,6.7145],"type":"Point"}
}