{
  "type": "Feature",
  "properties": {
    "gn:admin1_code":"32.0",
    "gn:asciiname":"Disanayakgamba",
    "gn:country_code":"LK",
    "gn:dem":125,
    "gn:feature_class":"P",
    "gn:feature_code":"PPL",
    "gn:name":"Disanayakgamba",
    "gn:population":0,
    "gn:timezone":"Asia/Colombo",
    "iso:country":"LK",
    "wof:name":"Disanayakgamba",
    "wof:placetype":"locality"
},
  "geometry": {"coordinates":[80.3668,7.9517],"type":"Point"}
}