{
  "type": "Feature",
  "properties": {
    "gn:admin1_code":"34.0",
    "gn:asciiname":"Olagoda",
    "gn:country_code":"LK",
    "gn:dem":23,
    "gn:feature_class":"P",
    "gn:feature_code":"PPL",
    "gn:name":"Olagoda",
    "gn:population":0,
    "gn:timezone":"Asia/Colombo",
    "iso:country":"LK",
    "wof:name":"Olagoda",
    "wof:placetype":"locality"
},
  "geometry": {"coordinates":[80.24939999999999,6.2673],"type":"Point"}
}