{
  "type": "Feature",
  "properties": {
    "gn:admin1_code":"35.0",
    "gn:asciiname":"Purumukulana",
    "gn:country_code":"LK",
    "gn:dem":490,
    "gn:feature_class":"P",
    "gn:feature_code":"PPL",
    "gn:name":"Purumukulana",
    "gn:population":0,
    "gn:timezone":"Asia/Colombo",
    "iso:country":"LK",
    "wof:name":"Purumukulana",
    "wof:placetype":"locality"
},
  "geometry": {"coordinates":[81.0686,7.0498],"type":"Point"}
}