{
  "type": "Feature",
  "properties": {
    "gn:admin1_code":"33.0",
    "gn:asciiname":"Debatgama Pallebage",
    "gn:country_code":"LK",
    "gn:dem":554,
    "gn:feature_class":"P",
    "gn:feature_code":"PPL",
    "gn:name":"Debatgama Pallebage",
    "gn:population":0,
    "gn:timezone":"Asia/Colombo",
    "iso:country":"LK",
    "name:und_x_variant":[
        "Debathgama Pallebage",
        "Debatgama Pallebage"
    ],
    "wof:name":"Debatgama Pallebage",
    "wof:placetype":"locality"
},
  "geometry": {"coordinates":[80.4276,7.1624],"type":"Point"}
}