{
  "type": "Feature",
  "properties": {
    "gn:admin1_code":"29.0",
    "gn:asciiname":"Liyanwala Pahalagama",
    "gn:country_code":"LK",
    "gn:dem":874,
    "gn:feature_class":"P",
    "gn:feature_code":"PPL",
    "gn:name":"Liyanwala Pahalagama",
    "gn:population":0,
    "gn:timezone":"Asia/Colombo",
    "iso:country":"LK",
    "name:und_x_variant":[
        "Liyanwela Pahalagama"
    ],
    "wof:name":"Liyanwala Pahalagama",
    "wof:placetype":"locality"
},
  "geometry": {"coordinates":[80.8308,7.1113],"type":"Point"}
}