{
  "type": "Feature",
  "properties": {
    "gn:admin1_code":"30.0",
    "gn:asciiname":"Kadawatamadu",
    "gn:country_code":"LK",
    "gn:dem":36,
    "gn:feature_class":"P",
    "gn:feature_code":"PPL",
    "gn:name":"Kadawatamadu",
    "gn:population":0,
    "gn:timezone":"Asia/Colombo",
    "iso:country":"LK",
    "wof:name":"Kadawatamadu",
    "wof:placetype":"locality"
},
  "geometry": {"coordinates":[81.31667,7.96667],"type":"Point"}
}