{
  "type": "Feature",
  "properties": {
    "gn:admin1_code":"32.0",
    "gn:asciiname":"Ginipendegam",
    "gn:country_code":"LK",
    "gn:dem":96,
    "gn:feature_class":"P",
    "gn:feature_code":"PPL",
    "gn:name":"Ginipendegam",
    "gn:population":0,
    "gn:timezone":"Asia/Colombo",
    "iso:country":"LK",
    "name:und_x_variant":[
        "Ginipendegama"
    ],
    "wof:name":"Ginipendegam",
    "wof:placetype":"locality"
},
  "geometry": {"coordinates":[80.2303,7.6284],"type":"Point"}
}