{
  "type": "Feature",
  "properties": {
    "gn:admin1_code":"33.0",
    "gn:asciiname":"Waturawa",
    "gn:country_code":"LK",
    "gn:dem":645,
    "gn:feature_class":"P",
    "gn:feature_code":"PPL",
    "gn:name":"Waturawa",
    "gn:population":0,
    "gn:timezone":"Asia/Colombo",
    "iso:country":"LK",
    "wof:name":"Waturawa",
    "wof:placetype":"locality"
},
  "geometry": {"coordinates":[80.4276,6.489],"type":"Point"}
}