{
  "type": "Feature",
  "properties": {
    "gn:admin1_code":"34.0",
    "gn:asciiname":"Mahamadawala",
    "gn:country_code":"LK",
    "gn:dem":64,
    "gn:feature_class":"P",
    "gn:feature_code":"PPL",
    "gn:name":"Mahamadawala",
    "gn:population":0,
    "gn:timezone":"Asia/Colombo",
    "iso:country":"LK",
    "wof:name":"Mahamadawala",
    "wof:placetype":"locality"
},
  "geometry": {"coordinates":[80.6284,6.1552],"type":"Point"}
}