{
  "type": "Feature",
  "properties": {
    "gn:admin1_code":"29.0",
    "gn:asciiname":"Kongahawela",
    "gn:country_code":"LK",
    "gn:dem":208,
    "gn:feature_class":"P",
    "gn:feature_code":"PPL",
    "gn:name":"Kongahawela",
    "gn:population":0,
    "gn:timezone":"Asia/Colombo",
    "iso:country":"LK",
    "wof:name":"Kongahawela",
    "wof:placetype":"locality"
},
  "geometry": {"coordinates":[80.7171,7.6742],"type":"Point"}
}