{
  "type": "Feature",
  "properties": {
    "gn:admin1_code":"37.0",
    "gn:asciiname":"Unapana",
    "gn:country_code":"LK",
    "gn:dem":203,
    "gn:feature_class":"P",
    "gn:feature_code":"PPL",
    "gn:name":"Unapana",
    "gn:population":0,
    "gn:timezone":"Asia/Colombo",
    "iso:country":"LK",
    "wof:name":"Unapana",
    "wof:placetype":"locality"
},
  "geometry": {"coordinates":[81.21666999999999,7.43333],"type":"Point"}
}