{
  "type": "Feature",
  "properties": {
    "gn:admin1_code":"29.0",
    "gn:asciiname":"Totagamuwa",
    "gn:country_code":"LK",
    "gn:dem":430,
    "gn:feature_class":"P",
    "gn:feature_code":"PPL",
    "gn:name":"Totagamuwa",
    "gn:population":0,
    "gn:timezone":"Asia/Colombo",
    "iso:country":"LK",
    "name:und_x_variant":[
        "Thotagamuwa",
        "Totagamuwa"
    ],
    "wof:name":"Totagamuwa",
    "wof:placetype":"locality"
},
  "geometry": {"coordinates":[80.6181,7.5114],"type":"Point"}
}