{
  "type": "Feature",
  "properties": {
    "gn:admin1_code":"34.0",
    "gn:asciiname":"Pillagoda",
    "gn:country_code":"LK",
    "gn:dem":4,
    "gn:feature_class":"P",
    "gn:feature_code":"PPL",
    "gn:name":"Pillagoda",
    "gn:population":0,
    "gn:timezone":"Asia/Colombo",
    "iso:country":"LK",
    "wof:name":"Pillagoda",
    "wof:placetype":"locality"
},
  "geometry": {"coordinates":[80.2042,6.1418],"type":"Point"}
}