{
  "type": "Feature",
  "properties": {
    "gn:admin1_code":"36.0",
    "gn:asciiname":"Etgala",
    "gn:country_code":"LK",
    "gn:dem":21,
    "gn:feature_class":"P",
    "gn:feature_code":"PPL",
    "gn:name":"Etgala",
    "gn:population":0,
    "gn:timezone":"Asia/Colombo",
    "iso:country":"LK",
    "wof:name":"Etgala",
    "wof:placetype":"locality"
},
  "geometry": {"coordinates":[79.88330000000001,7.2579],"type":"Point"}
}