{
  "type": "Feature",
  "properties": {
    "gn:admin1_code":"33.0",
    "gn:asciiname":"Miganawita",
    "gn:country_code":"LK",
    "gn:dem":146,
    "gn:feature_class":"P",
    "gn:feature_code":"PPL",
    "gn:name":"Miganawita",
    "gn:population":0,
    "gn:timezone":"Asia/Colombo",
    "iso:country":"LK",
    "name:und_x_variant":[
        "Miyanawita"
    ],
    "wof:name":"Miganawita",
    "wof:placetype":"locality"
},
  "geometry": {"coordinates":[80.34999999999999,6.9037],"type":"Point"}
}