{
  "type": "Feature",
  "properties": {
    "gn:admin1_code":"36.0",
    "gn:asciiname":"Debehera",
    "gn:country_code":"LK",
    "gn:dem":68,
    "gn:feature_class":"P",
    "gn:feature_code":"PPL",
    "gn:name":"Debehera",
    "gn:population":0,
    "gn:timezone":"Asia/Colombo",
    "iso:country":"LK",
    "name:und_x_variant":[
        "Debahara",
        "Debehera"
    ],
    "wof:name":"Debehera",
    "wof:placetype":"locality"
},
  "geometry": {"coordinates":[80.14399999999998,7.1524],"type":"Point"}
}