{
  "type": "Feature",
  "properties": {
    "gn:admin1_code":"35.0",
    "gn:asciiname":"Pahamburutota",
    "gn:country_code":"LK",
    "gn:dem":868,
    "gn:feature_class":"P",
    "gn:feature_code":"PPL",
    "gn:name":"Pahamburutota",
    "gn:population":0,
    "gn:timezone":"Asia/Colombo",
    "iso:country":"LK",
    "wof:name":"Pahamburutota",
    "wof:placetype":"locality"
},
  "geometry": {"coordinates":[80.9662,6.949],"type":"Point"}
}