{
  "type": "Feature",
  "properties": {
    "gn:admin1_code":"37.0",
    "gn:asciiname":"Kayanadimadu",
    "gn:country_code":"LK",
    "gn:dem":9,
    "gn:feature_class":"P",
    "gn:feature_code":"PPL",
    "gn:name":"Kayanadimadu",
    "gn:population":0,
    "gn:timezone":"Asia/Colombo",
    "iso:country":"LK",
    "wof:name":"Kayanadimadu",
    "wof:placetype":"locality"
},
  "geometry": {"coordinates":[81.68333,7.58333],"type":"Point"}
}