{
  "type": "Feature",
  "properties": {
    "gn:admin1_code":"32.0",
    "gn:asciiname":"Bulana",
    "gn:country_code":"LK",
    "gn:dem":157,
    "gn:feature_class":"P",
    "gn:feature_code":"PPL",
    "gn:name":"Bulana",
    "gn:population":0,
    "gn:timezone":"Asia/Colombo",
    "iso:country":"LK",
    "wof:name":"Bulana",
    "wof:placetype":"locality"
},
  "geometry": {"coordinates":[80.47069999999999,7.6182],"type":"Point"}
}