{
  "type": "Feature",
  "properties": {
    "gn:admin1_code":"35.0",
    "gn:asciiname":"Migahawela",
    "gn:country_code":"LK",
    "gn:dem":172,
    "gn:feature_class":"P",
    "gn:feature_code":"PPL",
    "gn:name":"Migahawela",
    "gn:population":0,
    "gn:timezone":"Asia/Colombo",
    "iso:country":"LK",
    "wof:name":"Migahawela",
    "wof:placetype":"locality"
},
  "geometry": {"coordinates":[81.25,6.75],"type":"Point"}
}