{
  "type": "Feature",
  "properties": {
    "gn:admin1_code":"38.0",
    "gn:asciiname":"Patamoddi Town",
    "gn:country_code":"LK",
    "gn:dem":69,
    "gn:feature_class":"P",
    "gn:feature_code":"PPL",
    "gn:name":"Patamoddi Town",
    "gn:population":0,
    "gn:timezone":"Asia/Colombo",
    "iso:country":"LK",
    "wof:name":"Patamoddi Town",
    "wof:placetype":"locality"
},
  "geometry": {"coordinates":[80.4237,8.9108],"type":"Point"}
}