{
  "type": "Feature",
  "properties": {
    "gn:admin1_code":"33.0",
    "gn:asciiname":"Bithwalgama",
    "gn:country_code":"LK",
    "gn:dem":542,
    "gn:feature_class":"P",
    "gn:feature_code":"PPL",
    "gn:name":"Bithwalgama",
    "gn:population":0,
    "gn:timezone":"Asia/Colombo",
    "iso:country":"LK",
    "wof:name":"Bithwalgama",
    "wof:placetype":"locality"
},
  "geometry": {"coordinates":[80.72190000000001,6.626],"type":"Point"}
}