{
  "type": "Feature",
  "properties": {
    "gn:admin1_code":"32.0",
    "gn:asciiname":"Udattapola",
    "gn:country_code":"LK",
    "gn:dem":107,
    "gn:feature_class":"P",
    "gn:feature_code":"PPL",
    "gn:name":"Udattapola",
    "gn:population":0,
    "gn:timezone":"Asia/Colombo",
    "iso:country":"LK",
    "wof:name":"Udattapola",
    "wof:placetype":"locality"
},
  "geometry": {"coordinates":[80.3387,7.5119],"type":"Point"}
}