{
  "type": "Feature",
  "properties": {
    "gn:admin1_code":"34.0",
    "gn:asciiname":"Mananahena",
    "gn:country_code":"LK",
    "gn:dem":112,
    "gn:feature_class":"P",
    "gn:feature_code":"PPL",
    "gn:name":"Mananahena",
    "gn:population":0,
    "gn:timezone":"Asia/Colombo",
    "iso:country":"LK",
    "wof:name":"Mananahena",
    "wof:placetype":"locality"
},
  "geometry": {"coordinates":[80.2009,6.2975],"type":"Point"}
}