{
  "type": "Feature",
  "properties": {
    "gn:admin1_code":"33.0",
    "gn:asciiname":"Niyadandupola",
    "gn:country_code":"LK",
    "gn:dem":119,
    "gn:feature_class":"P",
    "gn:feature_code":"PPL",
    "gn:name":"Niyadandupola",
    "gn:population":0,
    "gn:timezone":"Asia/Colombo",
    "iso:country":"LK",
    "name:und_x_variant":[
        "Niyadurupola",
        "Niyandurupola",
        "Niyadandupola"
    ],
    "wof:name":"Niyadandupola",
    "wof:placetype":"locality"
},
  "geometry": {"coordinates":[80.2189,7.1665],"type":"Point"}
}