{
  "type": "Feature",
  "properties": {
    "gn:admin1_code":"32.0",
    "gn:asciiname":"Dematapitiya",
    "gn:country_code":"LK",
    "gn:dem":16,
    "gn:feature_class":"P",
    "gn:feature_code":"PPL",
    "gn:name":"Dematapitiya",
    "gn:population":0,
    "gn:timezone":"Asia/Colombo",
    "iso:country":"LK",
    "wof:name":"Dematapitiya",
    "wof:placetype":"locality"
},
  "geometry": {"coordinates":[79.8515,7.5524],"type":"Point"}
}