{
  "type": "Feature",
  "properties": {
    "gn:admin1_code":"33.0",
    "gn:asciiname":"Kalagediara",
    "gn:country_code":"LK",
    "gn:dem":63,
    "gn:feature_class":"P",
    "gn:feature_code":"PPL",
    "gn:name":"Kalagediara",
    "gn:population":0,
    "gn:timezone":"Asia/Colombo",
    "iso:country":"LK",
    "wof:name":"Kalagediara",
    "wof:placetype":"locality"
},
  "geometry": {"coordinates":[80.8745,6.3419],"type":"Point"}
}