{
  "type": "Feature",
  "properties": {
    "gn:admin1_code":"29.0",
    "gn:asciiname":"Alakolawewa",
    "gn:country_code":"LK",
    "gn:dem":1368,
    "gn:feature_class":"P",
    "gn:feature_code":"PPL",
    "gn:name":"Alakolawewa",
    "gn:population":0,
    "gn:timezone":"Asia/Colombo",
    "iso:country":"LK",
    "wof:name":"Alakolawewa",
    "wof:placetype":"locality"
},
  "geometry": {"coordinates":[80.8164,7.0678],"type":"Point"}
}