{
  "type": "Feature",
  "properties": {
    "gn:admin1_code":"34.0",
    "gn:asciiname":"Koggala",
    "gn:country_code":"LK",
    "gn:dem":9,
    "gn:elevation":"3.0",
    "gn:feature_class":"P",
    "gn:feature_code":"PPL",
    "gn:name":"Koggala",
    "gn:population":3000,
    "gn:timezone":"Asia/Colombo",
    "iso:country":"LK",
    "name:ceb_x_preferred":[
        "Koggala"
    ],
    "name:fra_x_preferred":[
        "Koggala"
    ],
    "name:nld_x_preferred":[
        "Koggala"
    ],
    "name:rus_x_preferred":[
        "\u041a\u043e\u0433\u0433\u0430\u043b\u0430"
    ],
    "name:sin_x_preferred":[
        "\u0d9a\u0ddc\u0d9c\u0dca\u0d9c\u0dbd"
    ],
    "name:swe_x_preferred":[
        "Koggala"
    ],
    "name:tam_x_preferred":[
        "\u0b95\u0bca\u0b95\u0bcd\u0b95\u0bb2\u0bc8"
    ],
    "wof:name":"Koggala",
    "wof:placetype":"locality",
    "wof:population":3000
},
  "geometry": {"coordinates":[80.32859999999999,5.9886],"type":"Point"}
}