{
  "type": "Feature",
  "properties": {
    "iso:country":"LK",
    "name:bre_x_preferred":[
        "Dehiwala-Mount Lavinia"
    ],
    "name:cat_x_preferred":[
        "Dehiwala-Mount Lavinia"
    ],
    "name:deu_x_preferred":[
        "Dehiwala-Mount Lavinia"
    ],
    "name:eng_x_preferred":[
        "Dehiwala-Mount Lavinia"
    ],
    "name:epo_x_preferred":[
        "Dehivala-Maunt Lavinia"
    ],
    "name:fas_x_preferred":[
        "\u062f\u0647\u06cc\u0648\u0627\u0644\u0627-\u0645\u0627\u0648\u0646\u062a \u0644\u0627\u0648\u06cc\u0646\u06cc\u0627"
    ],
    "name:fin_x_preferred":[
        "Dehiwala-Mount Lavinia"
    ],
    "name:fra_x_preferred":[
        "Mount Lavinia"
    ],
    "name:ile_x_preferred":[
        "Dehiwala-Mount Lavinia"
    ],
    "name:ita_x_preferred":[
        "Dehiwala-Mount Lavinia"
    ],
    "name:jpn_x_preferred":[
        "\u30c7\u30d2\u30ef\u30e9\u30fb\u30de\u30a6\u30f3\u30c8\u30e9\u30d3\u30cb\u30a2"
    ],
    "name:kat_x_preferred":[
        "\u10db\u10d0\u10e3\u10dc\u10e2-\u10da\u10d0\u10d5\u10d8\u10dc\u10d8\u10d0"
    ],
    "name:lit_x_preferred":[
        "Dehivala-Maunt Lavinija"
    ],
    "name:nld_x_preferred":[
        "Dehiwala-Mount Lavinia"
    ],
    "name:pol_x_preferred":[
        "Dehiwala-Mount Lavinia"
    ],
    "name:por_x_preferred":[
        "Dehiwala-Mount Lavinia"
    ],
    "name:rus_x_preferred":[
        "\u0414\u0435\u0445\u0438\u0432\u0430\u043b\u0430-\u041c\u0430\u0443\u043d\u0442-\u041b\u0430\u0432\u0438\u043d\u0438\u044f"
    ],
    "name:sin_x_preferred":[
        "\u0daf\u0dd9\u0dc4\u0dd2\u0dc0\u0dbd-\u0d9c\u0dbd\u0dca\u0d9a\u0dd2\u0dc3\u0dca\u0dc3"
    ],
    "name:slv_x_preferred":[
        "Dehiwala-Mount Lavinia"
    ],
    "name:spa_x_preferred":[
        "Dehiwala-Mount Lavinia"
    ],
    "name:swe_x_preferred":[
        "Dehiwala-Mount Lavinia"
    ],
    "name:tam_x_preferred":[
        "\u0ba4\u0bc6\u0b95\u0bbf\u0bb5\u0bb3\u0bc8-\u0b95\u0bb2\u0bcd\u0b95\u0bbf\u0b9a\u0bc8"
    ],
    "name:ukr_x_preferred":[
        "\u0414\u0435\u0445\u0456\u0432\u0430\u043b\u0430-\u041c\u0430\u0443\u043d\u0442-\u041b\u0430\u0432\u0456\u043d\u0456\u044f"
    ],
    "name:unk_x_variant":[
        "Mount Laviniya"
    ],
    "name:urd_x_preferred":[
        "\u062f\u06cc\u06c1\u06cc\u0648\u0627\u0644\u0627-\u0645\u0627\u0624\u0646\u0679 \u0644\u0627\u0648\u06cc\u0646\u06cc\u0627"
    ],
    "name:vie_x_preferred":[
        "Dehiwala-Mount Lavinia"
    ],
    "name:war_x_preferred":[
        "Dehiwala-Mount Lavinia"
    ],
    "name:zho_x_preferred":[
        "\u4ee3\u5e0c\u74e6\u52d2-\u8292\u7279\u62c9\u7ef4\u5c3c"
    ],
    "qs:gn_country":"LK",
    "qs:gn_fcode":"PPL",
    "qs:gn_pop":0,
    "qs:name":"Mount Lavinia",
    "qs:name_adm0":"Sri Lanka",
    "qs:name_adm1":"Western",
    "qs:photos":1037,
    "qs:photos_1k":210,
    "qs:photos_9k":5,
    "qs:photos_9r":7,
    "qs:photos_all":1037,
    "qs:photos_sr":11,
    "qs:placetype":"Town",
    "qs:pop_sr":"0",
    "qs:woe_adm0":23424778,
    "wof:name":"Mount Lavinia",
    "wof:placetype":"locality"
},
  "geometry": {"coordinates":[79.86444,6.83389],"type":"Point"}
}