{
  "type": "Feature",
  "properties": {
    "gn:admin1_code":"29.0",
    "gn:asciiname":"Embulpura",
    "gn:country_code":"LK",
    "gn:dem":515,
    "gn:feature_class":"P",
    "gn:feature_code":"PPL",
    "gn:name":"Embulpura",
    "gn:population":0,
    "gn:timezone":"Asia/Colombo",
    "iso:country":"LK",
    "name:und_x_variant":[
        "Embulpure"
    ],
    "wof:name":"Embulpura",
    "wof:placetype":"locality"
},
  "geometry": {"coordinates":[80.59690000000001,7.3372],"type":"Point"}
}