{
  "type": "Feature",
  "properties": {
    "gn:admin1_code":"32.0",
    "gn:asciiname":"Urundayandaluwa",
    "gn:country_code":"LK",
    "gn:dem":14,
    "gn:feature_class":"P",
    "gn:feature_code":"PPL",
    "gn:name":"Urundayandaluwa",
    "gn:population":0,
    "gn:timezone":"Asia/Colombo",
    "iso:country":"LK",
    "wof:name":"Urundayandaluwa",
    "wof:placetype":"locality"
},
  "geometry": {"coordinates":[79.8387,7.5935],"type":"Point"}
}