{
  "type": "Feature",
  "properties": {
    "gn:admin1_code":"35.0",
    "gn:asciiname":"Endurugalayaya",
    "gn:country_code":"LK",
    "gn:dem":209,
    "gn:feature_class":"P",
    "gn:feature_code":"PPL",
    "gn:name":"Endurugalayaya",
    "gn:population":0,
    "gn:timezone":"Asia/Colombo",
    "iso:country":"LK",
    "wof:name":"Endurugalayaya",
    "wof:placetype":"locality"
},
  "geometry": {"coordinates":[81.2556,6.816],"type":"Point"}
}