{
  "type": "Feature",
  "properties": {
    "iso:country":"LK",
    "name:dut_x_preferred":[
        "Minuwangoda"
    ],
    "name:eng_x_preferred":[
        "Minuwangoda"
    ],
    "name:fas_x_preferred":[
        "\u0645\u06cc\u0646\u0648\u0648\u0627\u0646\u06af\u0648\u062f\u0627"
    ],
    "name:jpn_x_preferred":[
        "\u30df\u30cc\u30ef\u30f3\u30b4\u30c0"
    ],
    "name:per_x_preferred":[
        "\u0645\u06cc\u0646\u0648\u0648\u0627\u0646\u06af\u0648\u062f\u0627"
    ],
    "name:sin_x_preferred":[
        "\u0db8\u0dd2\u0db1\u0dd4\u0dc0\u0db1\u0dca\u0d9c\u0ddc\u0da9"
    ],
    "name:swe_x_preferred":[
        "Minuwangoda"
    ],
    "name:urd_x_preferred":[
        "\u0645\u06cc\u0646\u0648\u0648\u0627\u0646\u06af\u0648\u062f\u0627"
    ],
    "qs:gn_country":"LK",
    "qs:gn_fcode":"PPL",
    "qs:gn_pop":7772,
    "qs:name":"Minuwangoda",
    "qs:name_adm0":"Sri Lanka",
    "qs:name_adm1":"Western",
    "qs:photos":30,
    "qs:photos_1k":6,
    "qs:photos_9k":1,
    "qs:photos_9r":2,
    "qs:photos_all":30,
    "qs:photos_sr":2,
    "qs:placetype":"Town",
    "qs:pop_sr":"5",
    "qs:woe_adm0":23424778,
    "wd:wordcount":169,
    "wof:name":"Minuwangoda",
    "wof:placetype":"locality",
    "wof:population":7772
},
  "geometry": {"coordinates":[79.9533,7.1663],"type":"Point"}
}