{
  "type": "Feature",
  "properties": {
    "gn:admin1_code":"33.0",
    "gn:asciiname":"Pannila",
    "gn:country_code":"LK",
    "gn:dem":184,
    "gn:feature_class":"P",
    "gn:feature_code":"PPL",
    "gn:name":"Pannila",
    "gn:population":0,
    "gn:timezone":"Asia/Colombo",
    "iso:country":"LK",
    "wof:name":"Pannila",
    "wof:placetype":"locality"
},
  "geometry": {"coordinates":[80.61799999999999,6.5927],"type":"Point"}
}