{
  "type": "Feature",
  "properties": {
    "gn:admin1_code":"38.0",
    "gn:asciiname":"Kunchukkulam",
    "gn:country_code":"LK",
    "gn:dem":81,
    "gn:feature_class":"P",
    "gn:feature_code":"PPL",
    "gn:name":"Kunchukkulam",
    "gn:population":0,
    "gn:timezone":"Asia/Colombo",
    "iso:country":"LK",
    "wof:name":"Kunchukkulam",
    "wof:placetype":"locality"
},
  "geometry": {"coordinates":[80.34999999999999,8.83333],"type":"Point"}
}