{
  "type": "Feature",
  "properties": {
    "gn:admin1_code":"29.0",
    "gn:asciiname":"Deldeniya",
    "gn:country_code":"LK",
    "gn:dem":511,
    "gn:feature_class":"P",
    "gn:feature_code":"PPL",
    "gn:name":"Deldeniya",
    "gn:population":0,
    "gn:timezone":"Asia/Colombo",
    "iso:country":"LK",
    "wof:name":"Deldeniya",
    "wof:placetype":"locality"
},
  "geometry": {"coordinates":[80.5115,7.2794],"type":"Point"}
}