{
  "type": "Feature",
  "properties": {
    "gn:admin1_code":"36.0",
    "gn:asciiname":"Welihinda",
    "gn:country_code":"LK",
    "gn:dem":44,
    "gn:feature_class":"P",
    "gn:feature_code":"PPL",
    "gn:name":"Welihinda",
    "gn:population":0,
    "gn:timezone":"Asia/Colombo",
    "iso:country":"LK",
    "wof:name":"Welihinda",
    "wof:placetype":"locality"
},
  "geometry": {"coordinates":[80.04170000000001,7.2824],"type":"Point"}
}