{
  "type": "Feature",
  "properties": {
    "gn:admin1_code":"33.0",
    "gn:asciiname":"Dombagaswinna",
    "gn:country_code":"LK",
    "gn:dem":127,
    "gn:feature_class":"P",
    "gn:feature_code":"PPL",
    "gn:name":"Dombagaswinna",
    "gn:population":0,
    "gn:timezone":"Asia/Colombo",
    "iso:country":"LK",
    "wof:name":"Dombagaswinna",
    "wof:placetype":"locality"
},
  "geometry": {"coordinates":[80.5051,6.6476],"type":"Point"}
}