{
  "type": "Feature",
  "properties": {
    "gn:admin1_code":"34.0",
    "gn:asciiname":"Piyadigama",
    "gn:country_code":"LK",
    "gn:dem":10,
    "gn:feature_class":"P",
    "gn:feature_code":"PPL",
    "gn:name":"Piyadigama",
    "gn:population":0,
    "gn:timezone":"Asia/Colombo",
    "iso:country":"LK",
    "wof:name":"Piyadigama",
    "wof:placetype":"locality"
},
  "geometry": {"coordinates":[80.1888,6.052],"type":"Point"}
}