{
  "type": "Feature",
  "properties": {
    "gn:admin1_code":"30.0",
    "gn:asciiname":"Etawiragollewa",
    "gn:country_code":"LK",
    "gn:dem":116,
    "gn:feature_class":"P",
    "gn:feature_code":"PPL",
    "gn:name":"Etawiragollewa",
    "gn:population":0,
    "gn:timezone":"Asia/Colombo",
    "iso:country":"LK",
    "wof:name":"Etawiragollewa",
    "wof:placetype":"locality"
},
  "geometry": {"coordinates":[80.54689999999999,8.6138],"type":"Point"}
}