{
  "type": "Feature",
  "properties": {
    "gn:admin1_code":"34.0",
    "gn:asciiname":"Halgahapala",
    "gn:country_code":"LK",
    "gn:dem":298,
    "gn:feature_class":"P",
    "gn:feature_code":"PPL",
    "gn:name":"Halgahapala",
    "gn:population":0,
    "gn:timezone":"Asia/Colombo",
    "iso:country":"LK",
    "name:und_x_variant":[
        "Halgahapola"
    ],
    "wof:name":"Halgahapala",
    "wof:placetype":"locality"
},
  "geometry": {"coordinates":[80.59310000000001,6.2189],"type":"Point"}
}