{
  "type": "Feature",
  "properties": {
    "gn:admin1_code":"33.0",
    "gn:asciiname":"Mahalassawatta",
    "gn:country_code":"LK",
    "gn:dem":531,
    "gn:feature_class":"P",
    "gn:feature_code":"PPL",
    "gn:name":"Mahalassawatta",
    "gn:population":0,
    "gn:timezone":"Asia/Colombo",
    "iso:country":"LK",
    "wof:name":"Mahalassawatta",
    "wof:placetype":"locality"
},
  "geometry": {"coordinates":[80.57600000000002,6.6922],"type":"Point"}
}