{
  "type": "Feature",
  "properties": {
    "gn:admin1_code":"32.0",
    "gn:asciiname":"Kuda Tammannawa",
    "gn:country_code":"LK",
    "gn:dem":63,
    "gn:feature_class":"P",
    "gn:feature_code":"PPL",
    "gn:name":"Kuda Tammannawa",
    "gn:population":0,
    "gn:timezone":"Asia/Colombo",
    "iso:country":"LK",
    "wof:name":"Kuda Tammannawa",
    "wof:placetype":"locality"
},
  "geometry": {"coordinates":[80.041,7.8857],"type":"Point"}
}