{
  "type": "Feature",
  "properties": {
    "gn:admin1_code":"29.0",
    "gn:asciiname":"Pubbiliya",
    "gn:country_code":"LK",
    "gn:dem":220,
    "gn:feature_class":"P",
    "gn:feature_code":"PPL",
    "gn:name":"Pubbiliya",
    "gn:population":0,
    "gn:timezone":"Asia/Colombo",
    "iso:country":"LK",
    "name:ceb_x_preferred":[
        "Pubbiliya"
    ],
    "name:swe_x_preferred":[
        "Pubbiliya"
    ],
    "wof:name":"Pubbiliya",
    "wof:placetype":"locality"
},
  "geometry": {"coordinates":[80.71666999999999,7.73333],"type":"Point"}
}