{
  "type": "Feature",
  "properties": {
    "gn:admin1_code":"32.0",
    "gn:asciiname":"Elagammillewa",
    "gn:cc2":"LK",
    "gn:country_code":"LK",
    "gn:dem":83,
    "gn:feature_class":"P",
    "gn:feature_code":"PPL",
    "gn:name":"Elagammillewa",
    "gn:population":0,
    "gn:timezone":"Asia/Colombo",
    "iso:country":"LK",
    "name:und_x_variant":[
        "Elagammillawa",
        "Elagammillewa"
    ],
    "wof:name":"Elagammillewa",
    "wof:placetype":"locality"
},
  "geometry": {"coordinates":[80.15000000000001,7.85],"type":"Point"}
}