{
  "type": "Feature",
  "properties": {
    "gn:admin1_code":"32.0",
    "gn:asciiname":"Ratmalagara",
    "gn:country_code":"LK",
    "gn:dem":41,
    "gn:feature_class":"P",
    "gn:feature_code":"PPL",
    "gn:name":"Ratmalagara",
    "gn:population":0,
    "gn:timezone":"Asia/Colombo",
    "iso:country":"LK",
    "name:und_x_variant":[
        "Ratmalagare",
        "Ratmalagara"
    ],
    "wof:name":"Ratmalagara",
    "wof:placetype":"locality"
},
  "geometry": {"coordinates":[79.89100000000001,7.54],"type":"Point"}
}