{
  "type": "Feature",
  "properties": {
    "gn:admin1_code":"33.0",
    "gn:asciiname":"Bambaragastenna",
    "gn:country_code":"LK",
    "gn:dem":245,
    "gn:feature_class":"P",
    "gn:feature_code":"PPL",
    "gn:name":"Bambaragastenna",
    "gn:population":0,
    "gn:timezone":"Asia/Colombo",
    "iso:country":"LK",
    "wof:name":"Bambaragastenna",
    "wof:placetype":"locality"
},
  "geometry": {"coordinates":[80.6957,6.4977],"type":"Point"}
}