{
  "type": "Feature",
  "properties": {
    "gn:admin1_code":"36.0",
    "gn:asciiname":"Warakagoda West",
    "gn:country_code":"LK",
    "gn:dem":53,
    "gn:feature_class":"P",
    "gn:feature_code":"PPL",
    "gn:name":"Warakagoda West",
    "gn:population":0,
    "gn:timezone":"Asia/Colombo",
    "iso:country":"LK",
    "wof:name":"Warakagoda West",
    "wof:placetype":"locality"
},
  "geometry": {"coordinates":[80.1049,6.6144],"type":"Point"}
}