{
  "type": "Feature",
  "properties": {
    "gn:admin1_code":"30.0",
    "gn:asciiname":"Rambakulama",
    "gn:country_code":"LK",
    "gn:dem":153,
    "gn:feature_class":"P",
    "gn:feature_code":"PPL",
    "gn:name":"Rambakulama",
    "gn:population":0,
    "gn:timezone":"Asia/Colombo",
    "iso:country":"LK",
    "wof:name":"Rambakulama",
    "wof:placetype":"locality"
},
  "geometry": {"coordinates":[80.66667,8.25],"type":"Point"}
}