{
  "type": "Feature",
  "properties": {
    "gn:admin1_code":"29.0",
    "gn:asciiname":"Medagahawatura Colony",
    "gn:country_code":"LK",
    "gn:dem":614,
    "gn:feature_class":"P",
    "gn:feature_code":"PPL",
    "gn:name":"Medagahawatura Colony",
    "gn:population":0,
    "gn:timezone":"Asia/Colombo",
    "iso:country":"LK",
    "wof:name":"Medagahawatura Colony",
    "wof:placetype":"locality"
},
  "geometry": {"coordinates":[80.5415,7.0577],"type":"Point"}
}