{
  "type": "Feature",
  "properties": {
    "gn:admin1_code":"35.0",
    "gn:asciiname":"Arawagedara",
    "gn:country_code":"LK",
    "gn:dem":230,
    "gn:feature_class":"P",
    "gn:feature_code":"PPL",
    "gn:name":"Arawagedara",
    "gn:population":0,
    "gn:timezone":"Asia/Colombo",
    "iso:country":"LK",
    "wof:name":"Arawagedara",
    "wof:placetype":"locality"
},
  "geometry": {"coordinates":[80.9897,7.1214],"type":"Point"}
}