{
  "type": "Feature",
  "properties": {
    "gn:admin1_code":"29.0",
    "gn:asciiname":"Monaruwila",
    "gn:country_code":"LK",
    "gn:dem":455,
    "gn:feature_class":"P",
    "gn:feature_code":"PPL",
    "gn:name":"Monaruwila",
    "gn:population":0,
    "gn:timezone":"Asia/Colombo",
    "iso:country":"LK",
    "name:ceb_x_preferred":[
        "Monaruwila"
    ],
    "name:swe_x_preferred":[
        "Monaruwila"
    ],
    "wof:name":"Monaruwila",
    "wof:placetype":"locality"
},
  "geometry": {"coordinates":[80.5943,7.63],"type":"Point"}
}