{
  "type": "Feature",
  "properties": {
    "gn:admin1_code":"35.0",
    "gn:asciiname":"Detagamuwa Colony Stage I",
    "gn:country_code":"LK",
    "gn:dem":52,
    "gn:feature_class":"P",
    "gn:feature_code":"PPL",
    "gn:name":"Detagamuwa Colony Stage I",
    "gn:population":0,
    "gn:timezone":"Asia/Colombo",
    "iso:country":"LK",
    "wof:name":"Detagamuwa Colony Stage I",
    "wof:placetype":"locality"
},
  "geometry": {"coordinates":[81.3219,6.3988],"type":"Point"}
}