{
  "type": "Feature",
  "properties": {
    "gn:admin1_code":"32.0",
    "gn:asciiname":"Kilawamaduchenai",
    "gn:country_code":"LK",
    "gn:dem":13,
    "gn:feature_class":"P",
    "gn:feature_code":"PPL",
    "gn:name":"Kilawamaduchenai",
    "gn:population":0,
    "gn:timezone":"Asia/Colombo",
    "iso:country":"LK",
    "wof:name":"Kilawamaduchenai",
    "wof:placetype":"locality"
},
  "geometry": {"coordinates":[79.78830000000001,7.9087],"type":"Point"}
}