{
  "type": "Feature",
  "properties": {
    "gn:admin1_code":"32.0",
    "gn:asciiname":"Hinduranpitiya",
    "gn:country_code":"LK",
    "gn:dem":108,
    "gn:feature_class":"P",
    "gn:feature_code":"PPL",
    "gn:name":"Hinduranpitiya",
    "gn:population":0,
    "gn:timezone":"Asia/Colombo",
    "iso:country":"LK",
    "wof:name":"Hinduranpitiya",
    "wof:placetype":"locality"
},
  "geometry": {"coordinates":[80.37520000000001,7.5347],"type":"Point"}
}