{
  "type": "Feature",
  "properties": {
    "gn:admin1_code":"30.0",
    "gn:asciiname":"Bisouyona",
    "gn:country_code":"LK",
    "gn:dem":52,
    "gn:feature_class":"P",
    "gn:feature_code":"PPL",
    "gn:name":"Bisouyona",
    "gn:population":0,
    "gn:timezone":"Asia/Colombo",
    "iso:country":"LK",
    "wof:name":"Bisouyona",
    "wof:placetype":"locality"
},
  "geometry": {"coordinates":[81.029,8.1393],"type":"Point"}
}