{
  "type": "Feature",
  "properties": {
    "gn:admin1_code":"30.0",
    "gn:asciiname":"Kalawewa Walauwa",
    "gn:country_code":"LK",
    "gn:dem":129,
    "gn:feature_class":"P",
    "gn:feature_code":"PPL",
    "gn:name":"Kalawewa Walauwa",
    "gn:population":0,
    "gn:timezone":"Asia/Colombo",
    "iso:country":"LK",
    "wof:name":"Kalawewa Walauwa",
    "wof:placetype":"locality"
},
  "geometry": {"coordinates":[80.5273,7.9987],"type":"Point"}
}