{
  "type": "Feature",
  "properties": {
    "gn:admin1_code":"35.0",
    "gn:asciiname":"Naranwatta",
    "gn:country_code":"LK",
    "gn:dem":183,
    "gn:feature_class":"P",
    "gn:feature_code":"PPL",
    "gn:name":"Naranwatta",
    "gn:population":0,
    "gn:timezone":"Asia/Colombo",
    "iso:country":"LK",
    "name:und_x_variant":[
        "Naranwana"
    ],
    "wof:name":"Naranwatta",
    "wof:placetype":"locality"
},
  "geometry": {"coordinates":[81.2963,6.9012],"type":"Point"}
}