{
  "type": "Feature",
  "properties": {
    "gn:admin1_code":"33.0",
    "gn:asciiname":"Madawela",
    "gn:country_code":"LK",
    "gn:dem":146,
    "gn:feature_class":"P",
    "gn:feature_code":"PPL",
    "gn:name":"Madawela",
    "gn:population":0,
    "gn:timezone":"Asia/Colombo",
    "iso:country":"LK",
    "name:und_x_variant":[
        "Madawala"
    ],
    "wof:name":"Madawela",
    "wof:placetype":"locality"
},
  "geometry": {"coordinates":[80.4036,7.3172],"type":"Point"}
}