{
  "type": "Feature",
  "properties": {
    "gn:admin1_code":"34.0",
    "gn:asciiname":"Tennegewatta",
    "gn:country_code":"LK",
    "gn:dem":152,
    "gn:feature_class":"P",
    "gn:feature_code":"PPL",
    "gn:name":"Tennegewatta",
    "gn:population":0,
    "gn:timezone":"Asia/Colombo",
    "iso:country":"LK",
    "wof:name":"Tennegewatta",
    "wof:placetype":"locality"
},
  "geometry": {"coordinates":[80.5826,6.2363],"type":"Point"}
}