{
  "type": "Feature",
  "properties": {
    "gn:admin1_code":"33.0",
    "gn:asciiname":"Hakamuwa Pahala",
    "gn:country_code":"LK",
    "gn:dem":57,
    "gn:feature_class":"P",
    "gn:feature_code":"PPL",
    "gn:name":"Hakamuwa Pahala",
    "gn:population":0,
    "gn:timezone":"Asia/Colombo",
    "iso:country":"LK",
    "wof:name":"Hakamuwa Pahala",
    "wof:placetype":"locality"
},
  "geometry": {"coordinates":[80.4242,6.663],"type":"Point"}
}