{
  "type": "Feature",
  "properties": {
    "gn:admin1_code":"36.0",
    "gn:asciiname":"Kaluayiruppuwa East",
    "gn:cc2":"LK",
    "gn:country_code":"LK",
    "gn:dem":25,
    "gn:feature_class":"P",
    "gn:feature_code":"PPL",
    "gn:name":"Kaluayiruppuwa East",
    "gn:population":0,
    "gn:timezone":"Asia/Colombo",
    "iso:country":"LK",
    "name:und_x_variant":[
        "Kaluayiruppua East",
        "Kaluayiruppuwa East"
    ],
    "wof:name":"Kaluayiruppuwa East",
    "wof:placetype":"locality"
},
  "geometry": {"coordinates":[79.91667,7.25],"type":"Point"}
}