{
  "type": "Feature",
  "properties": {
    "gn:admin1_code":"32.0",
    "gn:asciiname":"Helpandeniya",
    "gn:country_code":"LK",
    "gn:dem":119,
    "gn:feature_class":"P",
    "gn:feature_code":"PPL",
    "gn:name":"Helpandeniya",
    "gn:population":0,
    "gn:timezone":"Asia/Colombo",
    "iso:country":"LK",
    "name:und_x_variant":[
        "Halpandeniya"
    ],
    "wof:name":"Helpandeniya",
    "wof:placetype":"locality"
},
  "geometry": {"coordinates":[80.2679,7.3276],"type":"Point"}
}