{
  "type": "Feature",
  "properties": {
    "gn:admin1_code":"32.0",
    "gn:asciiname":"Ihala Gokarella",
    "gn:country_code":"LK",
    "gn:dem":147,
    "gn:feature_class":"P",
    "gn:feature_code":"PPL",
    "gn:name":"Ihala Gokarella",
    "gn:population":0,
    "gn:timezone":"Asia/Colombo",
    "iso:country":"LK",
    "wof:name":"Ihala Gokarella",
    "wof:placetype":"locality"
},
  "geometry": {"coordinates":[80.464,7.6014],"type":"Point"}
}