{
  "type": "Feature",
  "properties": {
    "gn:admin1_code":"33.0",
    "gn:asciiname":"Owilanda",
    "gn:country_code":"LK",
    "gn:dem":100,
    "gn:feature_class":"P",
    "gn:feature_code":"PPL",
    "gn:name":"Owilanda",
    "gn:population":0,
    "gn:timezone":"Asia/Colombo",
    "iso:country":"LK",
    "wof:name":"Owilanda",
    "wof:placetype":"locality"
},
  "geometry": {"coordinates":[80.483,6.5708],"type":"Point"}
}