{
  "type": "Feature",
  "properties": {
    "gn:admin1_code":"30.0",
    "gn:asciiname":"Senadeerayagama",
    "gn:country_code":"LK",
    "gn:dem":162,
    "gn:feature_class":"P",
    "gn:feature_code":"PPL",
    "gn:name":"Senadeerayagama",
    "gn:population":0,
    "gn:timezone":"Asia/Colombo",
    "iso:country":"LK",
    "name:und_x_variant":[
        "Senadiriyagama"
    ],
    "wof:name":"Senadeerayagama",
    "wof:placetype":"locality"
},
  "geometry": {"coordinates":[80.6795,8.0736],"type":"Point"}
}