{
  "type": "Feature",
  "properties": {
    "gn:admin1_code":"29.0",
    "gn:asciiname":"Bolagandawela",
    "gn:country_code":"LK",
    "gn:dem":426,
    "gn:feature_class":"P",
    "gn:feature_code":"PPL",
    "gn:name":"Bolagandawela",
    "gn:population":0,
    "gn:timezone":"Asia/Colombo",
    "iso:country":"LK",
    "wof:name":"Bolagandawela",
    "wof:placetype":"locality"
},
  "geometry": {"coordinates":[80.9511,7.1144],"type":"Point"}
}