{
  "type": "Feature",
  "properties": {
    "gn:admin1_code":"38.0",
    "gn:asciiname":"Valveddi",
    "gn:country_code":"LK",
    "gn:dem":20,
    "gn:feature_class":"P",
    "gn:feature_code":"PPL",
    "gn:name":"Valveddi",
    "gn:population":0,
    "gn:timezone":"Asia/Colombo",
    "iso:country":"LK",
    "name:und_x_variant":[
        "Valvetty",
        "Valveddi"
    ],
    "wof:name":"Valveddi",
    "wof:placetype":"locality"
},
  "geometry": {"coordinates":[80.18333,9.81667],"type":"Point"}
}