{
  "type": "Feature",
  "properties": {
    "gn:admin1_code":"35.0",
    "gn:asciiname":"Manikpura",
    "gn:country_code":"LK",
    "gn:dem":46,
    "gn:feature_class":"P",
    "gn:feature_code":"PPL",
    "gn:name":"Manikpura",
    "gn:population":0,
    "gn:timezone":"Asia/Colombo",
    "iso:country":"LK",
    "wof:name":"Manikpura",
    "wof:placetype":"locality"
},
  "geometry": {"coordinates":[81.345,6.4064],"type":"Point"}
}