{
  "type": "Feature",
  "properties": {
    "gn:admin1_code":"29.0",
    "gn:asciiname":"Madawala Demalabage",
    "gn:country_code":"LK",
    "gn:dem":281,
    "gn:feature_class":"P",
    "gn:feature_code":"PPL",
    "gn:name":"Madawala Demalabage",
    "gn:population":0,
    "gn:timezone":"Asia/Colombo",
    "iso:country":"LK",
    "name:fas_x_preferred":[
        "\u0645\u0627\u062f\u0627\u0648\u0627 \u062f\u0645\u0627\u0644\u0627\u0628\u0627\u062c"
    ],
    "name:urd_x_preferred":[
        "\u0645\u06cc\u0688\u0627\u0648\u0627\u0644\u0627 \u0688\u06cc\u0645\u0627\u0644\u0627\u0628\u0627\u06af\u06cc"
    ],
    "wof:name":"Madawala Demalabage",
    "wof:placetype":"locality"
},
  "geometry": {"coordinates":[80.649,7.6174],"type":"Point"}
}