{
  "type": "Feature",
  "properties": {
    "gn:admin1_code":"32.0",
    "gn:asciiname":"Talahingoda",
    "gn:country_code":"LK",
    "gn:dem":139,
    "gn:feature_class":"P",
    "gn:feature_code":"PPL",
    "gn:name":"Talahingoda",
    "gn:population":0,
    "gn:timezone":"Asia/Colombo",
    "iso:country":"LK",
    "wof:name":"Talahingoda",
    "wof:placetype":"locality"
},
  "geometry": {"coordinates":[80.4346,7.4871],"type":"Point"}
}