{
  "type": "Feature",
  "properties": {
    "gn:admin1_code":"35.0",
    "gn:asciiname":"Paluwatta",
    "gn:country_code":"LK",
    "gn:dem":397,
    "gn:feature_class":"P",
    "gn:feature_code":"PPL",
    "gn:name":"Paluwatta",
    "gn:population":0,
    "gn:timezone":"Asia/Colombo",
    "iso:country":"LK",
    "name:und_x_variant":[
        "Palawatta",
        "Paluwatta"
    ],
    "wof:name":"Paluwatta",
    "wof:placetype":"locality"
},
  "geometry": {"coordinates":[81.1317,7.0275],"type":"Point"}
}