{
  "type": "Feature",
  "properties": {
    "gn:admin1_code":"32.0",
    "gn:asciiname":"Kadawela",
    "gn:cc2":"LK",
    "gn:country_code":"LK",
    "gn:dem":80,
    "gn:feature_class":"P",
    "gn:feature_code":"PPL",
    "gn:name":"Kadawela",
    "gn:population":0,
    "gn:timezone":"Asia/Colombo",
    "iso:country":"LK",
    "name:und_x_variant":[
        "Kadawala",
        "Kadawela"
    ],
    "wof:name":"Kadawela",
    "wof:placetype":"locality"
},
  "geometry": {"coordinates":[80.25055999999999,7.77917],"type":"Point"}
}