{
  "type": "Feature",
  "properties": {
    "gn:admin1_code":"30.0",
    "gn:asciiname":"Rambewa",
    "gn:country_code":"LK",
    "gn:dem":111,
    "gn:feature_class":"P",
    "gn:feature_code":"PPL",
    "gn:name":"Rambewa",
    "gn:population":0,
    "gn:timezone":"Asia/Colombo",
    "iso:country":"LK",
    "wof:name":"Rambewa",
    "wof:placetype":"locality"
},
  "geometry": {"coordinates":[80.5104,8.6185],"type":"Point"}
}