{
  "type": "Feature",
  "properties": {
    "gn:admin1_code":"36.0",
    "gn:asciiname":"Dedigamuwa",
    "gn:country_code":"LK",
    "gn:dem":20,
    "gn:feature_class":"P",
    "gn:feature_code":"PPL",
    "gn:name":"Dedigamuwa",
    "gn:population":0,
    "gn:timezone":"Asia/Colombo",
    "iso:country":"LK",
    "name:und_x_variant":[
        "Dedigomuwa"
    ],
    "wof:name":"Dedigamuwa",
    "wof:placetype":"locality"
},
  "geometry": {"coordinates":[80.027,6.8905],"type":"Point"}
}