{
  "type": "Feature",
  "properties": {
    "gn:admin1_code":"33.0",
    "gn:asciiname":"Mattamagoda",
    "gn:country_code":"LK",
    "gn:dem":36,
    "gn:feature_class":"P",
    "gn:feature_code":"PPL",
    "gn:name":"Mattamagoda",
    "gn:population":0,
    "gn:timezone":"Asia/Colombo",
    "iso:country":"LK",
    "wof:name":"Mattamagoda",
    "wof:placetype":"locality"
},
  "geometry": {"coordinates":[80.2765,7.0984],"type":"Point"}
}