{
  "type": "Feature",
  "properties": {
    "gn:admin1_code":"29.0",
    "gn:asciiname":"Mahawatta",
    "gn:country_code":"LK",
    "gn:dem":459,
    "gn:feature_class":"P",
    "gn:feature_code":"PPL",
    "gn:name":"Mahawatta",
    "gn:population":0,
    "gn:timezone":"Asia/Colombo",
    "iso:country":"LK",
    "name:ceb_x_preferred":[
        "Mahawatta"
    ],
    "name:swe_x_preferred":[
        "Mahawatta"
    ],
    "wof:name":"Mahawatta",
    "wof:placetype":"locality"
},
  "geometry": {"coordinates":[80.6797,7.2875],"type":"Point"}
}