{
  "type": "Feature",
  "properties": {
    "gn:admin1_code":"32.0",
    "gn:asciiname":"Heenagara",
    "gn:country_code":"LK",
    "gn:dem":34,
    "gn:feature_class":"P",
    "gn:feature_code":"PPL",
    "gn:name":"Heenagara",
    "gn:population":0,
    "gn:timezone":"Asia/Colombo",
    "iso:country":"LK",
    "name:und_x_variant":[
        "Hin-agare",
        "Heenagara"
    ],
    "wof:name":"Heenagara",
    "wof:placetype":"locality"
},
  "geometry": {"coordinates":[79.8792,7.5187],"type":"Point"}
}