{
  "type": "Feature",
  "properties": {
    "gn:admin1_code":"30.0",
    "gn:asciiname":"Dunudambuwewa",
    "gn:country_code":"LK",
    "gn:dem":74,
    "gn:feature_class":"P",
    "gn:feature_code":"PPL",
    "gn:name":"Dunudambuwewa",
    "gn:population":0,
    "gn:timezone":"Asia/Colombo",
    "iso:country":"LK",
    "wof:name":"Dunudambuwewa",
    "wof:placetype":"locality"
},
  "geometry": {"coordinates":[80.18510000000001,8.2529],"type":"Point"}
}