{
  "type": "Feature",
  "properties": {
    "gn:admin1_code":"36.0",
    "gn:asciiname":"Ganemulla",
    "gn:country_code":"LK",
    "gn:dem":30,
    "gn:feature_class":"P",
    "gn:feature_code":"PPL",
    "gn:name":"Ganemulla",
    "gn:population":0,
    "gn:timezone":"Asia/Colombo",
    "iso:country":"LK",
    "name:fra_x_preferred":[
        "Ganemulla"
    ],
    "name:rus_x_preferred":[
        "\u0413\u0430\u043d\u0435\u043c\u0443\u043b\u043b\u0430"
    ],
    "name:sin_x_preferred":[
        "\u0d9c\u0dab\u0dda\u0db8\u0dd4\u0dbd\u0dca\u0dbd"
    ],
    "wof:name":"Ganemulla",
    "wof:placetype":"locality"
},
  "geometry": {"coordinates":[79.96300000000002,7.0652],"type":"Point"}
}