{
  "type": "Feature",
  "properties": {
    "gn:admin1_code":"36.0",
    "gn:asciiname":"Weweldeniya Pahalagama",
    "gn:country_code":"LK",
    "gn:dem":76,
    "gn:feature_class":"P",
    "gn:feature_code":"PPL",
    "gn:name":"Weweldeniya Pahalagama",
    "gn:population":0,
    "gn:timezone":"Asia/Colombo",
    "iso:country":"LK",
    "wof:name":"Weweldeniya Pahalagama",
    "wof:placetype":"locality"
},
  "geometry": {"coordinates":[80.1553,7.2002],"type":"Point"}
}