{
  "type": "Feature",
  "properties": {
    "gn:admin1_code":"35.0",
    "gn:asciiname":"Guruhela",
    "gn:country_code":"LK",
    "gn:dem":106,
    "gn:feature_class":"P",
    "gn:feature_code":"PPL",
    "gn:name":"Guruhela",
    "gn:population":0,
    "gn:timezone":"Asia/Colombo",
    "iso:country":"LK",
    "wof:name":"Guruhela",
    "wof:placetype":"locality"
},
  "geometry": {"coordinates":[81.4922,6.8675],"type":"Point"}
}