{
  "type": "Feature",
  "properties": {
    "gn:admin1_code":"33.0",
    "gn:asciiname":"Bulathgama",
    "gn:country_code":"LK",
    "gn:dem":579,
    "gn:feature_class":"P",
    "gn:feature_code":"PPL",
    "gn:name":"Bulathgama",
    "gn:population":0,
    "gn:timezone":"Asia/Colombo",
    "iso:country":"LK",
    "name:und_x_variant":[
        "Bulatgama"
    ],
    "wof:name":"Bulathgama",
    "wof:placetype":"locality"
},
  "geometry": {"coordinates":[80.6814,6.6714],"type":"Point"}
}