{
  "type": "Feature",
  "properties": {
    "gn:admin1_code":"35.0",
    "gn:asciiname":"Migahawela",
    "gn:country_code":"LK",
    "gn:dem":754,
    "gn:feature_class":"P",
    "gn:feature_code":"PPL",
    "gn:name":"Migahawela",
    "gn:population":0,
    "gn:timezone":"Asia/Colombo",
    "iso:country":"LK",
    "name:und_x_variant":[
        "Meegahawela",
        "Migahawela"
    ],
    "wof:name":"Migahawela",
    "wof:placetype":"locality"
},
  "geometry": {"coordinates":[81.0368,7.0171],"type":"Point"}
}