{
  "type": "Feature",
  "properties": {
    "gn:admin1_code":"35.0",
    "gn:asciiname":"Horadorowwa",
    "gn:country_code":"LK",
    "gn:dem":1192,
    "gn:feature_class":"P",
    "gn:feature_code":"PPL",
    "gn:name":"Horadorowwa",
    "gn:population":0,
    "gn:timezone":"Asia/Colombo",
    "iso:country":"LK",
    "name:und_x_variant":[
        "Horadoruwwa",
        "Horadaruwa",
        "Horadoruwa",
        "Horadorowwa"
    ],
    "wof:name":"Horadorowwa",
    "wof:placetype":"locality"
},
  "geometry": {"coordinates":[80.9204,6.7968],"type":"Point"}
}