{
  "type": "Feature",
  "properties": {
    "gn:admin1_code":"29.0",
    "gn:asciiname":"Samimale",
    "gn:country_code":"LK",
    "gn:dem":1383,
    "gn:feature_class":"P",
    "gn:feature_code":"PPL",
    "gn:name":"Samimale",
    "gn:population":0,
    "gn:timezone":"Asia/Colombo",
    "iso:country":"LK",
    "name:und_x_variant":[
        "Nissankamalla Puraya"
    ],
    "wof:name":"Samimale",
    "wof:placetype":"locality"
},
  "geometry": {"coordinates":[80.6177,6.7889],"type":"Point"}
}