{
  "type": "Feature",
  "properties": {
    "gn:admin1_code":"32.0",
    "gn:asciiname":"Kumbukewatta",
    "gn:country_code":"LK",
    "gn:dem":51,
    "gn:feature_class":"P",
    "gn:feature_code":"PPL",
    "gn:name":"Kumbukewatta",
    "gn:population":0,
    "gn:timezone":"Asia/Colombo",
    "iso:country":"LK",
    "wof:name":"Kumbukewatta",
    "wof:placetype":"locality"
},
  "geometry": {"coordinates":[79.95189999999999,7.8423],"type":"Point"}
}