{
  "type": "Feature",
  "properties": {
    "gn:admin1_code":"32.0",
    "gn:asciiname":"Nikadalupota",
    "gn:country_code":"LK",
    "gn:dem":106,
    "gn:feature_class":"P",
    "gn:feature_code":"PPL",
    "gn:name":"Nikadalupota",
    "gn:population":0,
    "gn:timezone":"Asia/Colombo",
    "iso:country":"LK",
    "wof:name":"Nikadalupota",
    "wof:placetype":"locality"
},
  "geometry": {"coordinates":[80.378,7.6572],"type":"Point"}
}