{
  "type": "Feature",
  "properties": {
    "gn:admin1_code":"30.0",
    "gn:asciiname":"Nambadagaswewa",
    "gn:country_code":"LK",
    "gn:dem":88,
    "gn:feature_class":"P",
    "gn:feature_code":"PPL",
    "gn:name":"Nambadagaswewa",
    "gn:population":0,
    "gn:timezone":"Asia/Colombo",
    "iso:country":"LK",
    "wof:name":"Nambadagaswewa",
    "wof:placetype":"locality"
},
  "geometry": {"coordinates":[80.52160000000001,8.4459],"type":"Point"}
}