{
  "type": "Feature",
  "properties": {
    "gn:admin1_code":"29.0",
    "gn:asciiname":"Yatihalgala Udagama",
    "gn:country_code":"LK",
    "gn:dem":579,
    "gn:feature_class":"P",
    "gn:feature_code":"PPL",
    "gn:name":"Yatihalgala Udagama",
    "gn:population":0,
    "gn:timezone":"Asia/Colombo",
    "iso:country":"LK",
    "wof:name":"Yatihalgala Udagama",
    "wof:placetype":"locality"
},
  "geometry": {"coordinates":[80.5904,7.2962],"type":"Point"}
}