{
  "type": "Feature",
  "properties": {
    "gn:admin1_code":"33.0",
    "gn:asciiname":"Dompitiya",
    "gn:country_code":"LK",
    "gn:dem":266,
    "gn:feature_class":"P",
    "gn:feature_code":"PPL",
    "gn:name":"Dompitiya",
    "gn:population":0,
    "gn:timezone":"Asia/Colombo",
    "iso:country":"LK",
    "wof:name":"Dompitiya",
    "wof:placetype":"locality"
},
  "geometry": {"coordinates":[80.49600000000002,7.1992],"type":"Point"}
}