{
  "type": "Feature",
  "properties": {
    "gn:admin1_code":"36.0",
    "gn:asciiname":"Talagama",
    "gn:country_code":"LK",
    "gn:dem":74,
    "gn:feature_class":"P",
    "gn:feature_code":"PPL",
    "gn:name":"Talagama",
    "gn:population":0,
    "gn:timezone":"Asia/Colombo",
    "iso:country":"LK",
    "wof:name":"Talagama",
    "wof:placetype":"locality"
},
  "geometry": {"coordinates":[80.17699999999998,7.2502],"type":"Point"}
}