{
  "type": "Feature",
  "properties": {
    "gn:admin1_code":"33.0",
    "gn:asciiname":"Nelagama",
    "gn:country_code":"LK",
    "gn:dem":214,
    "gn:feature_class":"P",
    "gn:feature_code":"PPL",
    "gn:name":"Nelagama",
    "gn:population":0,
    "gn:timezone":"Asia/Colombo",
    "iso:country":"LK",
    "name:und_x_variant":[
        "Nilagama"
    ],
    "wof:name":"Nelagama",
    "wof:placetype":"locality"
},
  "geometry": {"coordinates":[80.58669999999999,6.5966],"type":"Point"}
}