{
  "type": "Feature",
  "properties": {
    "gn:admin1_code":"32.0",
    "gn:asciiname":"Mabopitiya",
    "gn:country_code":"LK",
    "gn:dem":76,
    "gn:feature_class":"P",
    "gn:feature_code":"PPL",
    "gn:name":"Mabopitiya",
    "gn:population":0,
    "gn:timezone":"Asia/Colombo",
    "iso:country":"LK",
    "wof:name":"Mabopitiya",
    "wof:placetype":"locality"
},
  "geometry": {"coordinates":[80.20440000000001,7.3059],"type":"Point"}
}