{
  "type": "Feature",
  "properties": {
    "gn:admin1_code":"33.0",
    "gn:asciiname":"Ambagaha Arawa",
    "gn:country_code":"LK",
    "gn:dem":517,
    "gn:feature_class":"P",
    "gn:feature_code":"PPL",
    "gn:name":"Ambagaha Arawa",
    "gn:population":0,
    "gn:timezone":"Asia/Colombo",
    "iso:country":"LK",
    "wof:name":"Ambagaha Arawa",
    "wof:placetype":"locality"
},
  "geometry": {"coordinates":[80.7122,6.7058],"type":"Point"}
}