{
  "type": "Feature",
  "properties": {
    "gn:admin1_code":"30.0",
    "gn:asciiname":"Bogahawila",
    "gn:country_code":"LK",
    "gn:dem":117,
    "gn:feature_class":"P",
    "gn:feature_code":"PPL",
    "gn:name":"Bogahawila",
    "gn:population":0,
    "gn:timezone":"Asia/Colombo",
    "iso:country":"LK",
    "wof:name":"Bogahawila",
    "wof:placetype":"locality"
},
  "geometry": {"coordinates":[80.65730000000001,8.5313],"type":"Point"}
}