{
  "type": "Feature",
  "properties": {
    "gn:admin1_code":"36.0",
    "gn:asciiname":"Pubtidugama",
    "gn:country_code":"LK",
    "gn:dem":4,
    "gn:feature_class":"P",
    "gn:feature_code":"PPL",
    "gn:name":"Pubtidugama",
    "gn:population":0,
    "gn:timezone":"Asia/Colombo",
    "iso:country":"LK",
    "wof:name":"Pubtidugama",
    "wof:placetype":"locality"
},
  "geometry": {"coordinates":[79.87100000000002,7.0478],"type":"Point"}
}