{
  "type": "Feature",
  "properties": {
    "gn:admin1_code":"36.0",
    "gn:asciiname":"Merawaramulla",
    "gn:country_code":"LK",
    "gn:dem":6,
    "gn:feature_class":"P",
    "gn:feature_code":"PPL",
    "gn:name":"Merawaramulla",
    "gn:population":0,
    "gn:timezone":"Asia/Colombo",
    "iso:country":"LK",
    "wof:name":"Merawaramulla",
    "wof:placetype":"locality"
},
  "geometry": {"coordinates":[79.8703,7.0181],"type":"Point"}
}