{
  "type": "Feature",
  "properties": {
    "gn:admin1_code":"30.0",
    "gn:asciiname":"Manikkampattiya",
    "gn:cc2":"LK",
    "gn:country_code":"LK",
    "gn:dem":41,
    "gn:feature_class":"P",
    "gn:feature_code":"PPL",
    "gn:name":"Manikkampattiya",
    "gn:population":0,
    "gn:timezone":"Asia/Colombo",
    "iso:country":"LK",
    "name:und_x_variant":[
        "Manikkanpattiya",
        "Manikkampattiya"
    ],
    "wof:name":"Manikkampattiya",
    "wof:placetype":"locality"
},
  "geometry": {"coordinates":[81.05,7.91667],"type":"Point"}
}