{
  "type": "Feature",
  "properties": {
    "gn:admin1_code":"36.0",
    "gn:asciiname":"Kirikitta",
    "gn:country_code":"LK",
    "gn:dem":39,
    "gn:feature_class":"P",
    "gn:feature_code":"PPL",
    "gn:name":"Kirikitta",
    "gn:population":0,
    "gn:timezone":"Asia/Colombo",
    "iso:country":"LK",
    "wof:name":"Kirikitta",
    "wof:placetype":"locality"
},
  "geometry": {"coordinates":[80.0325,7.004],"type":"Point"}
}