{
  "type": "Feature",
  "properties": {
    "gn:admin1_code":"34.0",
    "gn:asciiname":"Nidahasgama Model Village",
    "gn:country_code":"LK",
    "gn:dem":6,
    "gn:feature_class":"P",
    "gn:feature_code":"PPL",
    "gn:name":"Nidahasgama Model Village",
    "gn:population":0,
    "gn:timezone":"Asia/Colombo",
    "iso:country":"LK",
    "wof:name":"Nidahasgama Model Village",
    "wof:placetype":"locality"
},
  "geometry": {"coordinates":[80.8798,6.0911],"type":"Point"}
}