{
  "type": "Feature",
  "properties": {
    "gn:admin1_code":"29.0",
    "gn:asciiname":"Ashoka Colony",
    "gn:country_code":"LK",
    "gn:dem":599,
    "gn:feature_class":"P",
    "gn:feature_code":"PPL",
    "gn:name":"Ashoka Colony",
    "gn:population":0,
    "gn:timezone":"Asia/Colombo",
    "iso:country":"LK",
    "wof:name":"Ashoka Colony",
    "wof:placetype":"locality"
},
  "geometry": {"coordinates":[80.49509999999999,7.0052],"type":"Point"}
}