{
  "type": "Feature",
  "properties": {
    "gn:admin1_code":"29.0",
    "gn:asciiname":"Illukkumbura",
    "gn:country_code":"LK",
    "gn:dem":632,
    "gn:feature_class":"P",
    "gn:feature_code":"PPL",
    "gn:name":"Illukkumbura",
    "gn:population":0,
    "gn:timezone":"Asia/Colombo",
    "iso:country":"LK",
    "name:und_x_variant":[
        "Ilukkumbura",
        "Illukkumbura"
    ],
    "wof:name":"Illukkumbura",
    "wof:placetype":"locality"
},
  "geometry": {"coordinates":[80.7688,7.5493],"type":"Point"}
}