{
  "type": "Feature",
  "properties": {
    "gn:admin1_code":"37.0",
    "gn:asciiname":"Kathiraveli-Putur",
    "gn:country_code":"LK",
    "gn:dem":-9999,
    "gn:feature_class":"P",
    "gn:feature_code":"PPL",
    "gn:name":"Kathiraveli-Putur",
    "gn:population":0,
    "gn:timezone":"Asia/Colombo",
    "iso:country":"LK",
    "name:und_x_variant":[
        "Katiraveli-Putur",
        "Kathiraveli-Putur"
    ],
    "wof:name":"Kathiraveli-Putur",
    "wof:placetype":"locality"
},
  "geometry": {"coordinates":[81.41667,8.23333],"type":"Point"}
}