{
  "type": "Feature",
  "properties": {
    "gn:admin1_code":"33.0",
    "gn:asciiname":"Godawela",
    "gn:country_code":"LK",
    "gn:dem":419,
    "gn:feature_class":"P",
    "gn:feature_code":"PPL",
    "gn:name":"Godawela",
    "gn:population":0,
    "gn:timezone":"Asia/Colombo",
    "iso:country":"LK",
    "name:ceb_x_preferred":[
        "Godawela"
    ],
    "name:fas_x_preferred":[
        "\u06af\u062f\u0627\u0648\u0644\u0627"
    ],
    "name:swe_x_preferred":[
        "Godawela"
    ],
    "wof:name":"Godawela",
    "wof:placetype":"locality"
},
  "geometry": {"coordinates":[80.6914,6.317],"type":"Point"}
}