{
  "type": "Feature",
  "properties": {
    "gn:admin1_code":"38.0",
    "gn:asciiname":"Achchelu",
    "gn:country_code":"LK",
    "gn:dem":9,
    "gn:feature_class":"P",
    "gn:feature_code":"PPL",
    "gn:name":"Achchelu",
    "gn:population":0,
    "gn:timezone":"Asia/Colombo",
    "iso:country":"LK",
    "name:fas_x_preferred":[
        "\u0627\u0686\u0644\u0648"
    ],
    "name:und_x_variant":[
        "Achelu",
        "Achchelu"
    ],
    "wof:name":"Achchelu",
    "wof:placetype":"locality"
},
  "geometry": {"coordinates":[80.06667,9.73333],"type":"Point"}
}