{
  "type": "Feature",
  "properties": {
    "gn:admin1_code":"30.0",
    "gn:asciiname":"Hinguruwakwela",
    "gn:country_code":"LK",
    "gn:dem":60,
    "gn:feature_class":"P",
    "gn:feature_code":"PPL",
    "gn:name":"Hinguruwakwela",
    "gn:population":0,
    "gn:timezone":"Asia/Colombo",
    "iso:country":"LK",
    "wof:name":"Hinguruwakwela",
    "wof:placetype":"locality"
},
  "geometry": {"coordinates":[80.96666999999999,8.03333],"type":"Point"}
}