{
  "type": "Feature",
  "properties": {
    "gn:admin1_code":"32.0",
    "gn:asciiname":"Mahagama Junction",
    "gn:country_code":"LK",
    "gn:dem":53,
    "gn:feature_class":"P",
    "gn:feature_code":"PPL",
    "gn:name":"Mahagama Junction",
    "gn:population":0,
    "gn:timezone":"Asia/Colombo",
    "iso:country":"LK",
    "wof:name":"Mahagama Junction",
    "wof:placetype":"locality"
},
  "geometry": {"coordinates":[80.03699999999998,8.1635],"type":"Point"}
}