{
  "type": "Feature",
  "properties": {
    "gn:admin1_code":"29.0",
    "gn:asciiname":"Kahatapitiya",
    "gn:country_code":"LK",
    "gn:dem":604,
    "gn:feature_class":"P",
    "gn:feature_code":"PPL",
    "gn:name":"Kahatapitiya",
    "gn:population":0,
    "gn:timezone":"Asia/Colombo",
    "iso:country":"LK",
    "wof:name":"Kahatapitiya",
    "wof:placetype":"locality"
},
  "geometry": {"coordinates":[80.56359999999999,7.1722],"type":"Point"}
}