{
  "type": "Feature",
  "properties": {
    "gn:admin1_code":"32.0",
    "gn:asciiname":"Urulemulla",
    "gn:country_code":"LK",
    "gn:dem":75,
    "gn:feature_class":"P",
    "gn:feature_code":"PPL",
    "gn:name":"Urulemulla",
    "gn:population":0,
    "gn:timezone":"Asia/Colombo",
    "iso:country":"LK",
    "name:und_x_variant":[
        "Urulamulla",
        "Urulemulla"
    ],
    "wof:name":"Urulemulla",
    "wof:placetype":"locality"
},
  "geometry": {"coordinates":[80.21720000000001,7.2966],"type":"Point"}
}