{
  "type": "Feature",
  "properties": {
    "iso:country":"LK",
    "name:bul_x_preferred":[
        "\u0427\u0435\u043d\u043a\u0430\u043b\u0430\u0434\u0439"
    ],
    "name:ceb_x_preferred":[
        "Chenkalady"
    ],
    "name:eng_x_preferred":[
        "Chenkalady"
    ],
    "name:fas_x_preferred":[
        "\u0686\u0646\u06a9\u0627\u0644\u0627\u062f\u06cc"
    ],
    "name:jpn_x_preferred":[
        "\u30c1\u30a7\u30f3\u30ab\u30e9\u30c7\u30a3"
    ],
    "name:nld_x_preferred":[
        "Chenkalady"
    ],
    "name:sin_x_preferred":[
        "\u0da0\u0dd9\u0db1\u0dca\u0d9a\u0dbd\u0da9\u0dd2"
    ],
    "name:swe_x_preferred":[
        "Chenkalady"
    ],
    "name:tam_x_preferred":[
        "\u0b9a\u0bc6\u0b99\u0bcd\u0b95\u0bb2\u0b9f\u0bbf"
    ],
    "name:und_x_variant":[
        "Chenkaladi"
    ],
    "qs:gn_country":"LK",
    "qs:gn_fcode":"PPL",
    "qs:gn_pop":0,
    "qs:name":"Chenkalady",
    "qs:name_adm0":"Sri Lanka",
    "qs:name_adm1":"North Eastern",
    "qs:photos":53,
    "qs:photos_1k":11,
    "qs:photos_9k":1,
    "qs:photos_9r":2,
    "qs:photos_all":53,
    "qs:photos_sr":2,
    "qs:placetype":"Town",
    "qs:pop_sr":"0",
    "qs:woe_adm0":23424778,
    "wd:wordcount":48,
    "wof:name":"Chenkalady",
    "wof:placetype":"locality"
},
  "geometry": {"coordinates":[81.59099999999999,7.786],"type":"Point"}
}