{
  "type": "Feature",
  "properties": {
    "gn:admin1_code":"32.0",
    "gn:asciiname":"Maha Athurumanda",
    "gn:country_code":"LK",
    "gn:dem":36,
    "gn:feature_class":"P",
    "gn:feature_code":"PPL",
    "gn:name":"Maha Athurumanda",
    "gn:population":0,
    "gn:timezone":"Asia/Colombo",
    "iso:country":"LK",
    "name:und_x_variant":[
        "Maha Aturumanda",
        "Maha Athurumanda"
    ],
    "wof:name":"Maha Athurumanda",
    "wof:placetype":"locality"
},
  "geometry": {"coordinates":[80.02,7.6965],"type":"Point"}
}