{
  "type": "Feature",
  "properties": {
    "gn:admin1_code":"35.0",
    "gn:asciiname":"Dombagahawela",
    "gn:country_code":"LK",
    "gn:dem":113,
    "gn:feature_class":"P",
    "gn:feature_code":"PPL",
    "gn:name":"Dombagahawela",
    "gn:population":0,
    "gn:timezone":"Asia/Colombo",
    "iso:country":"LK",
    "wof:name":"Dombagahawela",
    "wof:placetype":"locality"
},
  "geometry": {"coordinates":[81.4425,6.9016],"type":"Point"}
}