{
  "type": "Feature",
  "properties": {
    "gn:admin1_code":"38.0",
    "gn:asciiname":"Arukuveli",
    "gn:country_code":"LK",
    "gn:dem":9,
    "gn:feature_class":"P",
    "gn:feature_code":"PPL",
    "gn:name":"Arukuveli",
    "gn:population":0,
    "gn:timezone":"Asia/Colombo",
    "iso:country":"LK",
    "wof:name":"Arukuveli",
    "wof:placetype":"locality"
},
  "geometry": {"coordinates":[80.16549999999999,9.6152],"type":"Point"}
}