{
  "type": "Feature",
  "properties": {
    "gn:admin1_code":"32.0",
    "gn:asciiname":"Madarawaka Watta",
    "gn:country_code":"LK",
    "gn:dem":59,
    "gn:feature_class":"P",
    "gn:feature_code":"PPL",
    "gn:name":"Madarawaka Watta",
    "gn:population":0,
    "gn:timezone":"Asia/Colombo",
    "iso:country":"LK",
    "name:und_x_variant":[
        "Madarawakka"
    ],
    "wof:name":"Madarawaka Watta",
    "wof:placetype":"locality"
},
  "geometry": {"coordinates":[80.0553,7.4244],"type":"Point"}
}