{
  "type": "Feature",
  "properties": {
    "gn:admin1_code":"29.0",
    "gn:asciiname":"Aponsuwawatta",
    "gn:country_code":"LK",
    "gn:dem":600,
    "gn:feature_class":"P",
    "gn:feature_code":"PPL",
    "gn:name":"Aponsuwawatta",
    "gn:population":0,
    "gn:timezone":"Asia/Colombo",
    "iso:country":"LK",
    "wof:name":"Aponsuwawatta",
    "wof:placetype":"locality"
},
  "geometry": {"coordinates":[80.7538,7.237],"type":"Point"}
}