{
  "type": "Feature",
  "properties": {
    "gn:admin1_code":"33.0",
    "gn:asciiname":"Elaulla",
    "gn:country_code":"LK",
    "gn:dem":277,
    "gn:feature_class":"P",
    "gn:feature_code":"PPL",
    "gn:name":"Elaulla",
    "gn:population":0,
    "gn:timezone":"Asia/Colombo",
    "iso:country":"LK",
    "wof:name":"Elaulla",
    "wof:placetype":"locality"
},
  "geometry": {"coordinates":[80.3443,6.8388],"type":"Point"}
}