{
  "type": "Feature",
  "properties": {
    "gn:admin1_code":"29.0",
    "gn:asciiname":"Karandagolla",
    "gn:country_code":"LK",
    "gn:dem":734,
    "gn:feature_class":"P",
    "gn:feature_code":"PPL",
    "gn:name":"Karandagolla",
    "gn:population":0,
    "gn:timezone":"Asia/Colombo",
    "iso:country":"LK",
    "wof:name":"Karandagolla",
    "wof:placetype":"locality"
},
  "geometry": {"coordinates":[80.798,7.1293],"type":"Point"}
}