{
  "type": "Feature",
  "properties": {
    "gn:admin1_code":"32.0",
    "gn:asciiname":"Polpitigama",
    "gn:cc2":"LK",
    "gn:country_code":"LK",
    "gn:dem":96,
    "gn:feature_class":"P",
    "gn:feature_code":"PPL",
    "gn:name":"Polpitigama",
    "gn:population":0,
    "gn:timezone":"Asia/Colombo",
    "iso:country":"LK",
    "name:und_x_variant":[
        "Polpithigama",
        "Polpitigama"
    ],
    "wof:name":"Polpitigama",
    "wof:placetype":"locality"
},
  "geometry": {"coordinates":[80.21666999999999,7.83333],"type":"Point"}
}