{
  "type": "Feature",
  "properties": {
    "gn:admin1_code":"29.0",
    "gn:asciiname":"Kosagahakandura South",
    "gn:country_code":"LK",
    "gn:dem":123,
    "gn:feature_class":"P",
    "gn:feature_code":"PPL",
    "gn:name":"Kosagahakandura South",
    "gn:population":0,
    "gn:timezone":"Asia/Colombo",
    "iso:country":"LK",
    "wof:name":"Kosagahakandura South",
    "wof:placetype":"locality"
},
  "geometry": {"coordinates":[80.9803,7.2208],"type":"Point"}
}