{
  "type": "Feature",
  "properties": {
    "gn:admin1_code":"33.0",
    "gn:asciiname":"Kalatuwakanda",
    "gn:country_code":"LK",
    "gn:dem":220,
    "gn:feature_class":"P",
    "gn:feature_code":"PPL",
    "gn:name":"Kalatuwakanda",
    "gn:population":0,
    "gn:timezone":"Asia/Colombo",
    "iso:country":"LK",
    "wof:name":"Kalatuwakanda",
    "wof:placetype":"locality"
},
  "geometry": {"coordinates":[80.70229999999999,6.5222],"type":"Point"}
}