{
  "type": "Feature",
  "properties": {
    "gn:admin1_code":"33.0",
    "gn:asciiname":"Welihelatenna",
    "gn:country_code":"LK",
    "gn:dem":188,
    "gn:feature_class":"P",
    "gn:feature_code":"PPL",
    "gn:name":"Welihelatenna",
    "gn:population":0,
    "gn:timezone":"Asia/Colombo",
    "iso:country":"LK",
    "wof:name":"Welihelatenna",
    "wof:placetype":"locality"
},
  "geometry": {"coordinates":[80.3348,7.0281],"type":"Point"}
}