{
  "type": "Feature",
  "properties": {
    "gn:admin1_code":"30.0",
    "gn:asciiname":"Talawa",
    "gn:country_code":"LK",
    "gn:dem":108,
    "gn:feature_class":"P",
    "gn:feature_code":"PPL",
    "gn:name":"Talawa",
    "gn:population":0,
    "gn:timezone":"Asia/Colombo",
    "iso:country":"LK",
    "name:und_x_variant":[
        "Talawa Bazaar",
        "Talawa"
    ],
    "wof:name":"Talawa",
    "wof:placetype":"locality"
},
  "geometry": {"coordinates":[80.3476,8.2364],"type":"Point"}
}