{
  "type": "Feature",
  "properties": {
    "gn:admin1_code":"36.0",
    "gn:asciiname":"Weliweriya East",
    "gn:country_code":"LK",
    "gn:dem":30,
    "gn:feature_class":"P",
    "gn:feature_code":"PPL",
    "gn:name":"Weliweriya East",
    "gn:population":0,
    "gn:timezone":"Asia/Colombo",
    "iso:country":"LK",
    "wof:name":"Weliweriya East",
    "wof:placetype":"locality"
},
  "geometry": {"coordinates":[80.0241,7.0351],"type":"Point"}
}