{
  "type": "Feature",
  "properties": {
    "gn:admin1_code":"35.0",
    "gn:asciiname":"Hinnarangahakumbura",
    "gn:country_code":"LK",
    "gn:dem":590,
    "gn:feature_class":"P",
    "gn:feature_code":"PPL",
    "gn:name":"Hinnarangahakumbura",
    "gn:population":0,
    "gn:timezone":"Asia/Colombo",
    "iso:country":"LK",
    "wof:name":"Hinnarangahakumbura",
    "wof:placetype":"locality"
},
  "geometry": {"coordinates":[81.04179999999999,7.0285],"type":"Point"}
}