{
  "type": "Feature",
  "properties": {
    "gn:admin1_code":"34.0",
    "gn:asciiname":"Giribimbe",
    "gn:country_code":"LK",
    "gn:dem":16,
    "gn:feature_class":"P",
    "gn:feature_code":"PPL",
    "gn:name":"Giribimbe",
    "gn:population":0,
    "gn:timezone":"Asia/Colombo",
    "iso:country":"LK",
    "wof:name":"Giribimbe",
    "wof:placetype":"locality"
},
  "geometry": {"coordinates":[80.2152,6.2251],"type":"Point"}
}