{
  "type": "Feature",
  "properties": {
    "gn:admin1_code":"33.0",
    "gn:asciiname":"Kadawattiya",
    "gn:country_code":"LK",
    "gn:dem":109,
    "gn:feature_class":"P",
    "gn:feature_code":"PPL",
    "gn:name":"Kadawattiya",
    "gn:population":0,
    "gn:timezone":"Asia/Colombo",
    "iso:country":"LK",
    "wof:name":"Kadawattiya",
    "wof:placetype":"locality"
},
  "geometry": {"coordinates":[80.3845,7.3607],"type":"Point"}
}