{
  "type": "Feature",
  "properties": {
    "gn:admin1_code":"30.0",
    "gn:asciiname":"Andaragasmulla",
    "gn:country_code":"LK",
    "gn:dem":104,
    "gn:feature_class":"P",
    "gn:feature_code":"PPL",
    "gn:name":"Andaragasmulla",
    "gn:population":0,
    "gn:timezone":"Asia/Colombo",
    "iso:country":"LK",
    "wof:name":"Andaragasmulla",
    "wof:placetype":"locality"
},
  "geometry": {"coordinates":[80.90000000000001,8.05],"type":"Point"}
}