{
  "type": "Feature",
  "properties": {
    "gn:admin1_code":"32.0",
    "gn:asciiname":"Periya Nagavillu",
    "gn:country_code":"LK",
    "gn:dem":41,
    "gn:feature_class":"P",
    "gn:feature_code":"PPL",
    "gn:name":"Periya Nagavillu",
    "gn:population":0,
    "gn:timezone":"Asia/Colombo",
    "iso:country":"LK",
    "wof:name":"Periya Nagavillu",
    "wof:placetype":"locality"
},
  "geometry": {"coordinates":[79.86360000000001,8.227],"type":"Point"}
}