{
  "type": "Feature",
  "properties": {
    "gn:admin1_code":"38.0",
    "gn:asciiname":"Kodaliparichchan",
    "gn:country_code":"LK",
    "gn:dem":86,
    "gn:feature_class":"P",
    "gn:feature_code":"PPL",
    "gn:name":"Kodaliparichchan",
    "gn:population":0,
    "gn:timezone":"Asia/Colombo",
    "iso:country":"LK",
    "wof:name":"Kodaliparichchan",
    "wof:placetype":"locality"
},
  "geometry": {"coordinates":[80.56010000000001,9.0974],"type":"Point"}
}