{
  "type": "Feature",
  "properties": {
    "gn:admin1_code":"30.0",
    "gn:asciiname":"Pansalawewa",
    "gn:cc2":"LK",
    "gn:country_code":"LK",
    "gn:dem":159,
    "gn:feature_class":"P",
    "gn:feature_code":"PPL",
    "gn:name":"Pansalawewa",
    "gn:population":0,
    "gn:timezone":"Asia/Colombo",
    "iso:country":"LK",
    "name:und_x_variant":[
        "Pansalewewa",
        "Pansalawewa"
    ],
    "wof:name":"Pansalawewa",
    "wof:placetype":"locality"
},
  "geometry": {"coordinates":[80.55,8.11667],"type":"Point"}
}