{
  "type": "Feature",
  "properties": {
    "gn:admin1_code":"32.0",
    "gn:asciiname":"Divullegama",
    "gn:country_code":"LK",
    "gn:dem":85,
    "gn:feature_class":"P",
    "gn:feature_code":"PPL",
    "gn:name":"Divullegama",
    "gn:population":0,
    "gn:timezone":"Asia/Colombo",
    "iso:country":"LK",
    "wof:name":"Divullegama",
    "wof:placetype":"locality"
},
  "geometry": {"coordinates":[80.2077,8.0042],"type":"Point"}
}