{
  "type": "Feature",
  "properties": {
    "gn:admin1_code":"37.0",
    "gn:asciiname":"Ellegoda",
    "gn:country_code":"LK",
    "gn:dem":131,
    "gn:feature_class":"P",
    "gn:feature_code":"PPL",
    "gn:name":"Ellegoda",
    "gn:population":0,
    "gn:timezone":"Asia/Colombo",
    "iso:country":"LK",
    "wof:name":"Ellegoda",
    "wof:placetype":"locality"
},
  "geometry": {"coordinates":[81.3199,7.4571],"type":"Point"}
}