{
  "type": "Feature",
  "properties": {
    "gn:admin1_code":"33.0",
    "gn:asciiname":"Gonawala",
    "gn:country_code":"LK",
    "gn:dem":240,
    "gn:feature_class":"P",
    "gn:feature_code":"PPL",
    "gn:name":"Gonawala",
    "gn:population":0,
    "gn:timezone":"Asia/Colombo",
    "iso:country":"LK",
    "wof:name":"Gonawala",
    "wof:placetype":"locality"
},
  "geometry": {"coordinates":[80.4991,7.1941],"type":"Point"}
}