{
  "type": "Feature",
  "properties": {
    "gn:admin1_code":"33.0",
    "gn:asciiname":"Aturaliya",
    "gn:country_code":"LK",
    "gn:dem":163,
    "gn:feature_class":"P",
    "gn:feature_code":"PPL",
    "gn:name":"Aturaliya",
    "gn:population":0,
    "gn:timezone":"Asia/Colombo",
    "iso:country":"LK",
    "wof:name":"Aturaliya",
    "wof:placetype":"locality"
},
  "geometry": {"coordinates":[80.45,6.75],"type":"Point"}
}