{
  "type": "Feature",
  "properties": {
    "gn:admin1_code":"33.0",
    "gn:asciiname":"Malandeniya",
    "gn:country_code":"LK",
    "gn:dem":148,
    "gn:feature_class":"P",
    "gn:feature_code":"PPL",
    "gn:name":"Malandeniya",
    "gn:population":0,
    "gn:timezone":"Asia/Colombo",
    "iso:country":"LK",
    "wof:name":"Malandeniya",
    "wof:placetype":"locality"
},
  "geometry": {"coordinates":[80.32769999999999,6.9466],"type":"Point"}
}