{
  "type": "Feature",
  "properties": {
    "gn:admin1_code":"32.0",
    "gn:asciiname":"Pothuwatawana",
    "gn:country_code":"LK",
    "gn:dem":20,
    "gn:feature_class":"P",
    "gn:feature_code":"PPL",
    "gn:name":"Pothuwatawana",
    "gn:population":0,
    "gn:timezone":"Asia/Colombo",
    "iso:country":"LK",
    "name:und_x_variant":[
        "Potuwatawana",
        "Pothuwatawana"
    ],
    "wof:name":"Pothuwatawana",
    "wof:placetype":"locality"
},
  "geometry": {"coordinates":[79.9109,7.4921],"type":"Point"}
}