{
  "type": "Feature",
  "properties": {
    "gn:admin1_code":"32.0",
    "gn:asciiname":"Amadarapitiya",
    "gn:country_code":"LK",
    "gn:dem":59,
    "gn:feature_class":"P",
    "gn:feature_code":"PPL",
    "gn:name":"Amadarapitiya",
    "gn:population":0,
    "gn:timezone":"Asia/Colombo",
    "iso:country":"LK",
    "wof:name":"Amadarapitiya",
    "wof:placetype":"locality"
},
  "geometry": {"coordinates":[80.13314,7.76672],"type":"Point"}
}