{
  "type": "Feature",
  "properties": {
    "gn:admin1_code":"29.0",
    "gn:asciiname":"Elamulla",
    "gn:country_code":"LK",
    "gn:dem":1108,
    "gn:feature_class":"P",
    "gn:feature_code":"PPL",
    "gn:name":"Elamulla",
    "gn:population":0,
    "gn:timezone":"Asia/Colombo",
    "iso:country":"LK",
    "wof:name":"Elamulla",
    "wof:placetype":"locality"
},
  "geometry": {"coordinates":[80.7792,7.0542],"type":"Point"}
}