{
  "type": "Feature",
  "properties": {
    "gn:admin1_code":"35.0",
    "gn:asciiname":"Unagollagama",
    "gn:country_code":"LK",
    "gn:dem":800,
    "gn:feature_class":"P",
    "gn:feature_code":"PPL",
    "gn:name":"Unagollagama",
    "gn:population":0,
    "gn:timezone":"Asia/Colombo",
    "iso:country":"LK",
    "name:und_x_variant":[
        "Unagollegama"
    ],
    "wof:name":"Unagollagama",
    "wof:placetype":"locality"
},
  "geometry": {"coordinates":[81.0534,6.9568],"type":"Point"}
}