{
  "type": "Feature",
  "properties": {
    "gn:admin1_code":"38.0",
    "gn:asciiname":"Paranaddakallu",
    "gn:country_code":"LK",
    "gn:dem":82,
    "gn:feature_class":"P",
    "gn:feature_code":"PPL",
    "gn:name":"Paranaddakallu",
    "gn:population":0,
    "gn:timezone":"Asia/Colombo",
    "iso:country":"LK",
    "name:und_x_variant":[
        "Paranaddakal",
        "Paraniddakallu"
    ],
    "wof:name":"Paranaddakallu",
    "wof:placetype":"locality"
},
  "geometry": {"coordinates":[80.476,8.8368],"type":"Point"}
}