{
  "type": "Feature",
  "properties": {
    "gn:admin1_code":"35.0",
    "gn:asciiname":"Mahaulpatha",
    "gn:country_code":"LK",
    "gn:dem":1289,
    "gn:feature_class":"P",
    "gn:feature_code":"PPL",
    "gn:name":"Mahaulpatha",
    "gn:population":0,
    "gn:timezone":"Asia/Colombo",
    "iso:country":"LK",
    "name:und_x_variant":[
        "Manaulpotta",
        "Mahaulpota",
        "Mahaulpatha"
    ],
    "wof:name":"Mahaulpatha",
    "wof:placetype":"locality"
},
  "geometry": {"coordinates":[80.9943,6.8221],"type":"Point"}
}