{
  "type": "Feature",
  "properties": {
    "gn:admin1_code":"35.0",
    "gn:asciiname":"Rajakandiya",
    "gn:country_code":"LK",
    "gn:dem":179,
    "gn:feature_class":"P",
    "gn:feature_code":"PPL",
    "gn:name":"Rajakandiya",
    "gn:population":0,
    "gn:timezone":"Asia/Colombo",
    "iso:country":"LK",
    "wof:name":"Rajakandiya",
    "wof:placetype":"locality"
},
  "geometry": {"coordinates":[81.2437,6.7905],"type":"Point"}
}