{
  "type": "Feature",
  "properties": {
    "gn:admin1_code":"35.0",
    "gn:asciiname":"Akkarapanaha",
    "gn:country_code":"LK",
    "gn:dem":293,
    "gn:feature_class":"P",
    "gn:feature_code":"PPL",
    "gn:name":"Akkarapanaha",
    "gn:population":0,
    "gn:timezone":"Asia/Colombo",
    "iso:country":"LK",
    "wof:name":"Akkarapanaha",
    "wof:placetype":"locality"
},
  "geometry": {"coordinates":[81.26049999999999,6.8856],"type":"Point"}
}