{
  "type": "Feature",
  "properties": {
    "gn:admin1_code":"30.0",
    "gn:asciiname":"Dumbuluwagama",
    "gn:country_code":"LK",
    "gn:dem":50,
    "gn:feature_class":"P",
    "gn:feature_code":"PPL",
    "gn:name":"Dumbuluwagama",
    "gn:population":0,
    "gn:timezone":"Asia/Colombo",
    "iso:country":"LK",
    "wof:name":"Dumbuluwagama",
    "wof:placetype":"locality"
},
  "geometry": {"coordinates":[80.18089999999999,8.183],"type":"Point"}
}