{
  "type": "Feature",
  "properties": {
    "gn:admin1_code":"35.0",
    "gn:asciiname":"Mahawela",
    "gn:country_code":"LK",
    "gn:dem":292,
    "gn:feature_class":"P",
    "gn:feature_code":"PPL",
    "gn:name":"Mahawela",
    "gn:population":0,
    "gn:timezone":"Asia/Colombo",
    "iso:country":"LK",
    "wof:name":"Mahawela",
    "wof:placetype":"locality"
},
  "geometry": {"coordinates":[81.16549999999999,7.1581],"type":"Point"}
}