{
  "type": "Feature",
  "properties": {
    "gn:admin1_code":"33.0",
    "gn:asciiname":"Andoluwa",
    "gn:country_code":"LK",
    "gn:dem":83,
    "gn:feature_class":"P",
    "gn:feature_code":"PPL",
    "gn:name":"Andoluwa",
    "gn:population":0,
    "gn:timezone":"Asia/Colombo",
    "iso:country":"LK",
    "name:und_x_variant":[
        "Andaoluwa"
    ],
    "wof:name":"Andoluwa",
    "wof:placetype":"locality"
},
  "geometry": {"coordinates":[80.3737,7.33],"type":"Point"}
}