{
  "type": "Feature",
  "properties": {
    "gn:admin1_code":"33.0",
    "gn:asciiname":"Walgampata",
    "gn:country_code":"LK",
    "gn:dem":196,
    "gn:feature_class":"P",
    "gn:feature_code":"PPL",
    "gn:name":"Walgampata",
    "gn:population":0,
    "gn:timezone":"Asia/Colombo",
    "iso:country":"LK",
    "wof:name":"Walgampata",
    "wof:placetype":"locality"
},
  "geometry": {"coordinates":[80.21339999999999,7.1244],"type":"Point"}
}