{
  "type": "Feature",
  "properties": {
    "gn:admin1_code":"36.0",
    "gn:asciiname":"Yakgahamulla",
    "gn:country_code":"LK",
    "gn:dem":9,
    "gn:feature_class":"P",
    "gn:feature_code":"PPL",
    "gn:name":"Yakgahamulla",
    "gn:population":0,
    "gn:timezone":"Asia/Colombo",
    "iso:country":"LK",
    "name:und_x_variant":[
        "Egodawatta",
        "Yakgahamulla"
    ],
    "wof:name":"Yakgahamulla",
    "wof:placetype":"locality"
},
  "geometry": {"coordinates":[79.9834,6.4849],"type":"Point"}
}