{
  "type": "Feature",
  "properties": {
    "gn:admin1_code":"29.0",
    "gn:asciiname":"Udawela",
    "gn:country_code":"LK",
    "gn:dem":440,
    "gn:feature_class":"P",
    "gn:feature_code":"PPL",
    "gn:name":"Udawela",
    "gn:population":0,
    "gn:timezone":"Asia/Colombo",
    "iso:country":"LK",
    "name:fas_x_preferred":[
        "\u06cc\u0648\u062f\u0627\u0648\u0644\u0627"
    ],
    "name:urd_x_preferred":[
        "\u0627\u062f\u0627\u0648\u06cc\u0644\u0627"
    ],
    "wof:name":"Udawela",
    "wof:placetype":"locality"
},
  "geometry": {"coordinates":[80.7667,7.3034],"type":"Point"}
}