{
  "type": "Feature",
  "properties": {
    "gn:admin1_code":"35.0",
    "gn:asciiname":"Hela-Alagolla",
    "gn:country_code":"LK",
    "gn:dem":1107,
    "gn:feature_class":"P",
    "gn:feature_code":"PPL",
    "gn:name":"Hela-Alagolla",
    "gn:population":0,
    "gn:timezone":"Asia/Colombo",
    "iso:country":"LK",
    "wof:name":"Hela-Alagolla",
    "wof:placetype":"locality"
},
  "geometry": {"coordinates":[80.9212,6.9693],"type":"Point"}
}