{
  "type": "Feature",
  "properties": {
    "gn:admin1_code":"32.0",
    "gn:asciiname":"Teiyadaluwa",
    "gn:country_code":"LK",
    "gn:dem":27,
    "gn:feature_class":"P",
    "gn:feature_code":"PPL",
    "gn:name":"Teiyadaluwa",
    "gn:population":0,
    "gn:timezone":"Asia/Colombo",
    "iso:country":"LK",
    "name:und_x_variant":[
        "Teyiyadaluwa",
        "Teiyadaluwa"
    ],
    "wof:name":"Teiyadaluwa",
    "wof:placetype":"locality"
},
  "geometry": {"coordinates":[79.98439999999999,7.7008],"type":"Point"}
}