{
  "type": "Feature",
  "properties": {
    "gn:admin1_code":"36.0",
    "gn:asciiname":"Wankepumulla",
    "gn:country_code":"LK",
    "gn:dem":39,
    "gn:feature_class":"P",
    "gn:feature_code":"PPL",
    "gn:name":"Wankepumulla",
    "gn:population":0,
    "gn:timezone":"Asia/Colombo",
    "iso:country":"LK",
    "wof:name":"Wankepumulla",
    "wof:placetype":"locality"
},
  "geometry": {"coordinates":[79.99420000000001,7.1809],"type":"Point"}
}