{
  "type": "Feature",
  "properties": {
    "gn:admin1_code":"36.0",
    "gn:asciiname":"Batuwita North",
    "gn:country_code":"LK",
    "gn:dem":26,
    "gn:feature_class":"P",
    "gn:feature_code":"PPL",
    "gn:name":"Batuwita North",
    "gn:population":0,
    "gn:timezone":"Asia/Colombo",
    "iso:country":"LK",
    "name:und_x_variant":[
        "Batuwita"
    ],
    "wof:name":"Batuwita North",
    "wof:placetype":"locality"
},
  "geometry": {"coordinates":[80.0371,6.7526],"type":"Point"}
}