{
  "type": "Feature",
  "properties": {
    "gn:admin1_code":"38.0",
    "gn:asciiname":"Alampil",
    "gn:country_code":"LK",
    "gn:dem":7,
    "gn:feature_class":"P",
    "gn:feature_code":"PPL",
    "gn:name":"Alampil",
    "gn:population":0,
    "gn:timezone":"Asia/Colombo",
    "iso:country":"LK",
    "name:fas_x_preferred":[
        "\u0627\u0644\u0627\u0645\u067e\u06cc\u0644"
    ],
    "wof:name":"Alampil",
    "wof:placetype":"locality"
},
  "geometry": {"coordinates":[80.84999999999999,9.15],"type":"Point"}
}