{
  "type": "Feature",
  "properties": {
    "gn:admin1_code":"35.0",
    "gn:asciiname":"Darkumbura",
    "gn:country_code":"LK",
    "gn:dem":172,
    "gn:feature_class":"P",
    "gn:feature_code":"PPL",
    "gn:name":"Darkumbura",
    "gn:population":0,
    "gn:timezone":"Asia/Colombo",
    "iso:country":"LK",
    "wof:name":"Darkumbura",
    "wof:placetype":"locality"
},
  "geometry": {"coordinates":[81.23333000000002,7.28333],"type":"Point"}
}