{
  "type": "Feature",
  "properties": {
    "gn:admin1_code":"33.0",
    "gn:asciiname":"Yahalabediwatta",
    "gn:country_code":"LK",
    "gn:dem":228,
    "gn:feature_class":"P",
    "gn:feature_code":"PPL",
    "gn:name":"Yahalabediwatta",
    "gn:population":0,
    "gn:timezone":"Asia/Colombo",
    "iso:country":"LK",
    "wof:name":"Yahalabediwatta",
    "wof:placetype":"locality"
},
  "geometry": {"coordinates":[80.5778,6.5934],"type":"Point"}
}