{
  "type": "Feature",
  "properties": {
    "gn:admin1_code":"30.0",
    "gn:asciiname":"Giranegama",
    "gn:country_code":"LK",
    "gn:dem":143,
    "gn:feature_class":"P",
    "gn:feature_code":"PPL",
    "gn:name":"Giranegama",
    "gn:population":0,
    "gn:timezone":"Asia/Colombo",
    "iso:country":"LK",
    "wof:name":"Giranegama",
    "wof:placetype":"locality"
},
  "geometry": {"coordinates":[80.45,7.96667],"type":"Point"}
}