{
  "type": "Feature",
  "properties": {
    "gn:admin1_code":"34.0",
    "gn:asciiname":"Gongawelana",
    "gn:country_code":"LK",
    "gn:dem":27,
    "gn:feature_class":"P",
    "gn:feature_code":"PPL",
    "gn:name":"Gongawelana",
    "gn:population":0,
    "gn:timezone":"Asia/Colombo",
    "iso:country":"LK",
    "wof:name":"Gongawelana",
    "wof:placetype":"locality"
},
  "geometry": {"coordinates":[81.2612,6.291],"type":"Point"}
}