{
  "type": "Feature",
  "properties": {
    "gn:admin1_code":"32.0",
    "gn:asciiname":"Kimbulwana",
    "gn:country_code":"LK",
    "gn:dem":130,
    "gn:feature_class":"P",
    "gn:feature_code":"PPL",
    "gn:name":"Kimbulwana",
    "gn:population":0,
    "gn:timezone":"Asia/Colombo",
    "iso:country":"LK",
    "wof:name":"Kimbulwana",
    "wof:placetype":"locality"
},
  "geometry": {"coordinates":[80.4525,7.6753],"type":"Point"}
}