{
  "type": "Feature",
  "properties": {
    "gn:admin1_code":"32.0",
    "gn:asciiname":"Bogahawela",
    "gn:country_code":"LK",
    "gn:dem":72,
    "gn:feature_class":"P",
    "gn:feature_code":"PPL",
    "gn:name":"Bogahawela",
    "gn:population":0,
    "gn:timezone":"Asia/Colombo",
    "iso:country":"LK",
    "wof:name":"Bogahawela",
    "wof:placetype":"locality"
},
  "geometry": {"coordinates":[80.1417,7.5179],"type":"Point"}
}