{
  "type": "Feature",
  "properties": {
    "gn:admin1_code":"32.0",
    "gn:asciiname":"Weeragalla",
    "gn:country_code":"LK",
    "gn:dem":285,
    "gn:feature_class":"P",
    "gn:feature_code":"PPL",
    "gn:name":"Weeragalla",
    "gn:population":0,
    "gn:timezone":"Asia/Colombo",
    "iso:country":"LK",
    "name:und_x_variant":[
        "Wiragala"
    ],
    "wof:name":"Weeragalla",
    "wof:placetype":"locality"
},
  "geometry": {"coordinates":[80.28399999999998,7.3428],"type":"Point"}
}