{
  "type": "Feature",
  "properties": {
    "gn:admin1_code":"33.0",
    "gn:asciiname":"Balinduwawa",
    "gn:country_code":"LK",
    "gn:dem":509,
    "gn:feature_class":"P",
    "gn:feature_code":"PPL",
    "gn:name":"Balinduwawa",
    "gn:population":0,
    "gn:timezone":"Asia/Colombo",
    "iso:country":"LK",
    "wof:name":"Balinduwawa",
    "wof:placetype":"locality"
},
  "geometry": {"coordinates":[80.8022,6.6298],"type":"Point"}
}