{
  "type": "Feature",
  "properties": {
    "gn:admin1_code":"29.0",
    "gn:asciiname":"Nagulliyadda",
    "gn:country_code":"LK",
    "gn:dem":544,
    "gn:feature_class":"P",
    "gn:feature_code":"PPL",
    "gn:name":"Nagulliyadda",
    "gn:population":0,
    "gn:timezone":"Asia/Colombo",
    "iso:country":"LK",
    "name:ceb_x_preferred":[
        "Nagulliyadda"
    ],
    "name:swe_x_preferred":[
        "Nagulliyadda"
    ],
    "name:und_x_variant":[
        "Naguliadda"
    ],
    "wof:name":"Nagulliyadda",
    "wof:placetype":"locality"
},
  "geometry": {"coordinates":[80.67749999999999,7.5622],"type":"Point"}
}