{
  "type": "Feature",
  "properties": {
    "gn:admin1_code":"35.0",
    "gn:asciiname":"Korandakumbura",
    "gn:country_code":"LK",
    "gn:dem":1251,
    "gn:feature_class":"P",
    "gn:feature_code":"PPL",
    "gn:name":"Korandakumbura",
    "gn:population":0,
    "gn:timezone":"Asia/Colombo",
    "iso:country":"LK",
    "wof:name":"Korandakumbura",
    "wof:placetype":"locality"
},
  "geometry": {"coordinates":[80.8651,6.9632],"type":"Point"}
}