{
  "type": "Feature",
  "properties": {
    "gn:admin1_code":"33.0",
    "gn:asciiname":"Gallenakanda",
    "gn:country_code":"LK",
    "gn:dem":196,
    "gn:feature_class":"P",
    "gn:feature_code":"PPL",
    "gn:name":"Gallenakanda",
    "gn:population":0,
    "gn:timezone":"Asia/Colombo",
    "iso:country":"LK",
    "wof:name":"Gallenakanda",
    "wof:placetype":"locality"
},
  "geometry": {"coordinates":[80.60300000000002,6.628],"type":"Point"}
}