{
  "type": "Feature",
  "properties": {
    "gn:admin1_code":"32.0",
    "gn:asciiname":"Akaragama",
    "gn:country_code":"LK",
    "gn:dem":125,
    "gn:feature_class":"P",
    "gn:feature_code":"PPL",
    "gn:name":"Akaragama",
    "gn:population":0,
    "gn:timezone":"Asia/Colombo",
    "iso:country":"LK",
    "name:und_x_variant":[
        "Akaragana",
        "Akaragama"
    ],
    "wof:name":"Akaragama",
    "wof:placetype":"locality"
},
  "geometry": {"coordinates":[80.3481,7.4648],"type":"Point"}
}