{
  "type": "Feature",
  "properties": {
    "gn:admin1_code":"32.0",
    "gn:asciiname":"Hettipolegama",
    "gn:country_code":"LK",
    "gn:dem":86,
    "gn:feature_class":"P",
    "gn:feature_code":"PPL",
    "gn:name":"Hettipolegama",
    "gn:population":0,
    "gn:timezone":"Asia/Colombo",
    "iso:country":"LK",
    "wof:name":"Hettipolegama",
    "wof:placetype":"locality"
},
  "geometry": {"coordinates":[80.16667,7.85],"type":"Point"}
}