{
  "type": "Feature",
  "properties": {
    "gn:admin1_code":"38.0",
    "gn:asciiname":"Cheddiyarkandal",
    "gn:country_code":"LK",
    "gn:dem":3,
    "gn:feature_class":"P",
    "gn:feature_code":"PPL",
    "gn:name":"Cheddiyarkandal",
    "gn:population":0,
    "gn:timezone":"Asia/Colombo",
    "iso:country":"LK",
    "name:und_x_variant":[
        "Choddivarkandal",
        "Cheddiyarkandal"
    ],
    "wof:name":"Cheddiyarkandal",
    "wof:placetype":"locality"
},
  "geometry": {"coordinates":[79.95,8.93333],"type":"Point"}
}