{
  "type": "Feature",
  "properties": {
    "gn:admin1_code":"35.0",
    "gn:asciiname":"Koorugama",
    "gn:country_code":"LK",
    "gn:dem":450,
    "gn:feature_class":"P",
    "gn:feature_code":"PPL",
    "gn:name":"Koorugama",
    "gn:population":0,
    "gn:timezone":"Asia/Colombo",
    "iso:country":"LK",
    "wof:name":"Koorugama",
    "wof:placetype":"locality"
},
  "geometry": {"coordinates":[81.0795,6.7942],"type":"Point"}
}