{
  "type": "Feature",
  "properties": {
    "gn:admin1_code":"34.0",
    "gn:asciiname":"Thiranagama",
    "gn:country_code":"LK",
    "gn:dem":20,
    "gn:feature_class":"P",
    "gn:feature_code":"PPL",
    "gn:name":"Thiranagama",
    "gn:population":0,
    "gn:timezone":"Asia/Colombo",
    "iso:country":"LK",
    "name:und_x_variant":[
        "Tiranagama"
    ],
    "wof:name":"Thiranagama",
    "wof:placetype":"locality"
},
  "geometry": {"coordinates":[80.1245,6.1282],"type":"Point"}
}