{
  "type": "Feature",
  "properties": {
    "gn:admin1_code":"35.0",
    "gn:asciiname":"Ambanporuwa",
    "gn:country_code":"LK",
    "gn:dem":254,
    "gn:feature_class":"P",
    "gn:feature_code":"PPL",
    "gn:name":"Ambanporuwa",
    "gn:population":0,
    "gn:timezone":"Asia/Colombo",
    "iso:country":"LK",
    "wof:name":"Ambanporuwa",
    "wof:placetype":"locality"
},
  "geometry": {"coordinates":[81.25879999999999,7.0767],"type":"Point"}
}