{
  "type": "Feature",
  "properties": {
    "gn:admin1_code":"36.0",
    "gn:asciiname":"Pettagamkanda",
    "gn:country_code":"LK",
    "gn:dem":67,
    "gn:feature_class":"P",
    "gn:feature_code":"PPL",
    "gn:name":"Pettagamkanda",
    "gn:population":0,
    "gn:timezone":"Asia/Colombo",
    "iso:country":"LK",
    "wof:name":"Pettagamkanda",
    "wof:placetype":"locality"
},
  "geometry": {"coordinates":[80.15000000000001,6.7716],"type":"Point"}
}