{
  "type": "Feature",
  "properties": {
    "gn:admin1_code":"32.0",
    "gn:asciiname":"Arunodagama",
    "gn:country_code":"LK",
    "gn:dem":199,
    "gn:feature_class":"P",
    "gn:feature_code":"PPL",
    "gn:name":"Arunodagama",
    "gn:population":0,
    "gn:timezone":"Asia/Colombo",
    "iso:country":"LK",
    "wof:name":"Arunodagama",
    "wof:placetype":"locality"
},
  "geometry": {"coordinates":[80.51390000000001,7.4412],"type":"Point"}
}