{
  "type": "Feature",
  "properties": {
    "gn:admin1_code":"30.0",
    "gn:asciiname":"Maha Kalattewa",
    "gn:cc2":"LK",
    "gn:country_code":"LK",
    "gn:dem":93,
    "gn:feature_class":"P",
    "gn:feature_code":"PPL",
    "gn:name":"Maha Kalattewa",
    "gn:population":0,
    "gn:timezone":"Asia/Colombo",
    "iso:country":"LK",
    "name:und_x_variant":[
        "Kalattewa",
        "Maha Kalattewa"
    ],
    "wof:name":"Maha Kalattewa",
    "wof:placetype":"locality"
},
  "geometry": {"coordinates":[80.45,8.31667],"type":"Point"}
}