{
  "type": "Feature",
  "properties": {
    "gn:admin1_code":"34.0",
    "gn:asciiname":"Marakanda",
    "gn:country_code":"LK",
    "gn:dem":43,
    "gn:feature_class":"P",
    "gn:feature_code":"PPL",
    "gn:name":"Marakanda",
    "gn:population":0,
    "gn:timezone":"Asia/Colombo",
    "iso:country":"LK",
    "wof:name":"Marakanda",
    "wof:placetype":"locality"
},
  "geometry": {"coordinates":[80.27209999999999,6.286],"type":"Point"}
}