{
  "type": "Feature",
  "properties": {
    "gn:admin1_code":"32.0",
    "gn:asciiname":"Pahalagama",
    "gn:country_code":"LK",
    "gn:dem":50,
    "gn:feature_class":"P",
    "gn:feature_code":"PPL",
    "gn:name":"Pahalagama",
    "gn:population":0,
    "gn:timezone":"Asia/Colombo",
    "iso:country":"LK",
    "wof:name":"Pahalagama",
    "wof:placetype":"locality"
},
  "geometry": {"coordinates":[80.0111,7.7753],"type":"Point"}
}