{
  "type": "Feature",
  "properties": {
    "gn:admin1_code":"35.0",
    "gn:asciiname":"Madam",
    "gn:country_code":"LK",
    "gn:dem":47,
    "gn:feature_class":"P",
    "gn:feature_code":"PPL",
    "gn:name":"Madam",
    "gn:population":0,
    "gn:timezone":"Asia/Colombo",
    "iso:country":"LK",
    "name:ara_x_preferred":[
        "\u0645\u062f\u0627\u0645"
    ],
    "name:cat_x_preferred":[
        "Madam"
    ],
    "name:ces_x_preferred":[
        "Madam"
    ],
    "name:deu_x_preferred":[
        "Madame"
    ],
    "name:fra_x_preferred":[
        "Madame"
    ],
    "name:hin_x_preferred":[
        "\u092e\u0939\u094b\u0926\u092f\u093e"
    ],
    "name:jpn_x_preferred":[
        "\u30de\u30c0\u30e0"
    ],
    "name:nor_x_preferred":[
        "Madam"
    ],
    "name:rus_x_preferred":[
        "\u041c\u0430\u0434\u0430\u043c"
    ],
    "name:tel_x_preferred":[
        "\u0c2e\u0c47\u0c21\u0c02"
    ],
    "name:ukr_x_preferred":[
        "\u041c\u0430\u0434\u0430\u043c"
    ],
    "wof:name":"Madam",
    "wof:placetype":"locality"
},
  "geometry": {"coordinates":[81.34999999999999,6.41667],"type":"Point"}
}