{
  "type": "Feature",
  "properties": {
    "gn:admin1_code":"29.0",
    "gn:asciiname":"Mihidumpura",
    "gn:country_code":"LK",
    "gn:dem":1928,
    "gn:feature_class":"P",
    "gn:feature_code":"PPL",
    "gn:name":"Mihidumpura",
    "gn:population":0,
    "gn:timezone":"Asia/Colombo",
    "iso:country":"LK",
    "wof:name":"Mihidumpura",
    "wof:placetype":"locality"
},
  "geometry": {"coordinates":[80.8173,6.9906],"type":"Point"}
}