{
  "type": "Feature",
  "properties": {
    "gn:admin1_code":"29.0",
    "gn:asciiname":"Medawala-Madige",
    "gn:country_code":"LK",
    "gn:dem":494,
    "gn:feature_class":"P",
    "gn:feature_code":"PPL",
    "gn:name":"Medawala-Madige",
    "gn:population":0,
    "gn:timezone":"Asia/Colombo",
    "iso:country":"LK",
    "name:und_x_variant":[
        "Madawala Madige"
    ],
    "wof:name":"Medawala-Madige",
    "wof:placetype":"locality"
},
  "geometry": {"coordinates":[80.6675,7.3298],"type":"Point"}
}