{
  "type": "Feature",
  "properties": {
    "gn:admin1_code":"33.0",
    "gn:asciiname":"Thalawitiya Pahala",
    "gn:country_code":"LK",
    "gn:dem":204,
    "gn:feature_class":"P",
    "gn:feature_code":"PPL",
    "gn:name":"Thalawitiya Pahala",
    "gn:population":0,
    "gn:timezone":"Asia/Colombo",
    "iso:country":"LK",
    "wof:name":"Thalawitiya Pahala",
    "wof:placetype":"locality"
},
  "geometry": {"coordinates":[80.2894,6.8396],"type":"Point"}
}