{
  "type": "Feature",
  "properties": {
    "gn:admin1_code":"33.0",
    "gn:asciiname":"Susirigama",
    "gn:country_code":"LK",
    "gn:dem":318,
    "gn:feature_class":"P",
    "gn:feature_code":"PPL",
    "gn:name":"Susirigama",
    "gn:population":0,
    "gn:timezone":"Asia/Colombo",
    "iso:country":"LK",
    "wof:name":"Susirigama",
    "wof:placetype":"locality"
},
  "geometry": {"coordinates":[80.56789999999999,6.5648],"type":"Point"}
}