{
  "type": "Feature",
  "properties": {
    "gn:admin1_code":"36.0",
    "gn:asciiname":"Pallekumbura",
    "gn:country_code":"LK",
    "gn:dem":110,
    "gn:feature_class":"P",
    "gn:feature_code":"PPL",
    "gn:name":"Pallekumbura",
    "gn:population":0,
    "gn:timezone":"Asia/Colombo",
    "iso:country":"LK",
    "wof:name":"Pallekumbura",
    "wof:placetype":"locality"
},
  "geometry": {"coordinates":[80.3116,6.4589],"type":"Point"}
}