{
  "type": "Feature",
  "properties": {
    "gn:admin1_code":"32.0",
    "gn:asciiname":"Walpolamulla",
    "gn:country_code":"LK",
    "gn:dem":79,
    "gn:feature_class":"P",
    "gn:feature_code":"PPL",
    "gn:name":"Walpolamulla",
    "gn:population":0,
    "gn:timezone":"Asia/Colombo",
    "iso:country":"LK",
    "name:und_x_variant":[
        "Walpolemulla"
    ],
    "wof:name":"Walpolamulla",
    "wof:placetype":"locality"
},
  "geometry": {"coordinates":[80.137,7.3945],"type":"Point"}
}