{
  "type": "Feature",
  "properties": {
    "gn:admin1_code":"29.0",
    "gn:asciiname":"Delgasyaya",
    "gn:country_code":"LK",
    "gn:dem":275,
    "gn:feature_class":"P",
    "gn:feature_code":"PPL",
    "gn:name":"Delgasyaya",
    "gn:population":0,
    "gn:timezone":"Asia/Colombo",
    "iso:country":"LK",
    "name:ceb_x_preferred":[
        "Delgasyaya"
    ],
    "name:swe_x_preferred":[
        "Delgasyaya"
    ],
    "wof:name":"Delgasyaya",
    "wof:placetype":"locality"
},
  "geometry": {"coordinates":[80.5305,7.383],"type":"Point"}
}