{
  "type": "Feature",
  "properties": {
    "gn:admin1_code":"35.0",
    "gn:asciiname":"Muppane",
    "gn:country_code":"LK",
    "gn:dem":392,
    "gn:feature_class":"P",
    "gn:feature_code":"PPL",
    "gn:name":"Muppane",
    "gn:population":0,
    "gn:timezone":"Asia/Colombo",
    "iso:country":"LK",
    "wof:name":"Muppane",
    "wof:placetype":"locality"
},
  "geometry": {"coordinates":[81.36667,6.88333],"type":"Point"}
}