{
  "type": "Feature",
  "properties": {
    "gn:admin1_code":"34.0",
    "gn:asciiname":"Kurundugashena",
    "gn:country_code":"LK",
    "gn:dem":68,
    "gn:feature_class":"P",
    "gn:feature_code":"PPL",
    "gn:name":"Kurundugashena",
    "gn:population":0,
    "gn:timezone":"Asia/Colombo",
    "iso:country":"LK",
    "wof:name":"Kurundugashena",
    "wof:placetype":"locality"
},
  "geometry": {"coordinates":[80.32080000000001,6.0807],"type":"Point"}
}