{
  "type": "Feature",
  "properties": {
    "gn:admin1_code":"34.0",
    "gn:asciiname":"Bogamuwa",
    "gn:country_code":"LK",
    "gn:dem":34,
    "gn:feature_class":"P",
    "gn:feature_code":"PPL",
    "gn:name":"Bogamuwa",
    "gn:population":0,
    "gn:timezone":"Asia/Colombo",
    "iso:country":"LK",
    "wof:name":"Bogamuwa",
    "wof:placetype":"locality"
},
  "geometry": {"coordinates":[80.8314,6.1639],"type":"Point"}
}