{
  "type": "Feature",
  "properties": {
    "gn:admin1_code":"30.0",
    "gn:asciiname":"Kongollewa",
    "gn:country_code":"LK",
    "gn:dem":106,
    "gn:feature_class":"P",
    "gn:feature_code":"PPL",
    "gn:name":"Kongollewa",
    "gn:population":0,
    "gn:timezone":"Asia/Colombo",
    "iso:country":"LK",
    "wof:name":"Kongollewa",
    "wof:placetype":"locality"
},
  "geometry": {"coordinates":[80.3291,8.2189],"type":"Point"}
}