{
  "type": "Feature",
  "properties": {
    "gn:admin1_code":"34.0",
    "gn:asciiname":"Weniwalara",
    "gn:country_code":"LK",
    "gn:dem":32,
    "gn:feature_class":"P",
    "gn:feature_code":"PPL",
    "gn:name":"Weniwalara",
    "gn:population":0,
    "gn:timezone":"Asia/Colombo",
    "iso:country":"LK",
    "wof:name":"Weniwalara",
    "wof:placetype":"locality"
},
  "geometry": {"coordinates":[80.9421,6.2709],"type":"Point"}
}