{
  "type": "Feature",
  "properties": {
    "gn:admin1_code":"29.0",
    "gn:asciiname":"Madanwala",
    "gn:country_code":"LK",
    "gn:dem":918,
    "gn:feature_class":"P",
    "gn:feature_code":"PPL",
    "gn:name":"Madanwala",
    "gn:population":0,
    "gn:timezone":"Asia/Colombo",
    "iso:country":"LK",
    "name:und_x_variant":[
        "Madanwela",
        "Madanwala"
    ],
    "name:urd_x_preferred":[
        "\u0645\u0639\u062f\u0646\u0648\u0627\u0644\u0627"
    ],
    "wof:name":"Madanwala",
    "wof:placetype":"locality"
},
  "geometry": {"coordinates":[80.7724,7.1592],"type":"Point"}
}