{
  "type": "Feature",
  "properties": {
    "gn:admin1_code":"32.0",
    "gn:asciiname":"Erunukuliya",
    "gn:country_code":"LK",
    "gn:dem":89,
    "gn:feature_class":"P",
    "gn:feature_code":"PPL",
    "gn:name":"Erunukuliya",
    "gn:population":0,
    "gn:timezone":"Asia/Colombo",
    "iso:country":"LK",
    "wof:name":"Erunukuliya",
    "wof:placetype":"locality"
},
  "geometry": {"coordinates":[80.1431,8.0545],"type":"Point"}
}