{
  "type": "Feature",
  "properties": {
    "gn:admin1_code":"34.0",
    "gn:asciiname":"Kitulwitigala",
    "gn:country_code":"LK",
    "gn:dem":45,
    "gn:feature_class":"P",
    "gn:feature_code":"PPL",
    "gn:name":"Kitulwitigala",
    "gn:population":0,
    "gn:timezone":"Asia/Colombo",
    "iso:country":"LK",
    "wof:name":"Kitulwitigala",
    "wof:placetype":"locality"
},
  "geometry": {"coordinates":[80.1773,6.3265],"type":"Point"}
}