{
  "type": "Feature",
  "properties": {
    "gn:admin1_code":"34.0",
    "gn:asciiname":"Diyakepilla",
    "gn:country_code":"LK",
    "gn:dem":202,
    "gn:feature_class":"P",
    "gn:feature_code":"PPL",
    "gn:name":"Diyakepilla",
    "gn:population":0,
    "gn:timezone":"Asia/Colombo",
    "iso:country":"LK",
    "wof:name":"Diyakepilla",
    "wof:placetype":"locality"
},
  "geometry": {"coordinates":[80.78333000000001,7.95],"type":"Point"}
}