{
  "type": "Feature",
  "properties": {
    "gn:admin1_code":"29.0",
    "gn:asciiname":"Ambaliyadda",
    "gn:country_code":"LK",
    "gn:dem":649,
    "gn:feature_class":"P",
    "gn:feature_code":"PPL",
    "gn:name":"Ambaliyadda",
    "gn:population":0,
    "gn:timezone":"Asia/Colombo",
    "iso:country":"LK",
    "name:ceb_x_preferred":[
        "Ambaliyadda"
    ],
    "name:fas_x_preferred":[
        "\u0627\u0645\u0628\u0627\u0644\u06cc\u0627\u062f\u0627"
    ],
    "name:swe_x_preferred":[
        "Ambaliyadda"
    ],
    "wof:name":"Ambaliyadda",
    "wof:placetype":"locality"
},
  "geometry": {"coordinates":[80.7689,7.1738],"type":"Point"}
}