{
  "type": "Feature",
  "properties": {
    "gn:admin1_code":"29.0",
    "gn:asciiname":"Ambaliyadda",
    "gn:country_code":"LK",
    "gn:dem":649,
    "gn:feature_class":"P",
    "gn:feature_code":"PPL",
    "gn:name":"Ambaliyadda",
    "gn:population":0,
    "gn:timezone":"Asia/Colombo",
    "iso:country":"LK",
    "wof:name":"Ambaliyadda",
    "wof:placetype":"locality"
},
  "geometry": {"coordinates":[80.7689,7.1738],"type":"Point"}
}