{
  "type": "Feature",
  "properties": {
    "gn:admin1_code":"32.0",
    "gn:asciiname":"Kanogama",
    "gn:country_code":"LK",
    "gn:dem":88,
    "gn:feature_class":"P",
    "gn:feature_code":"PPL",
    "gn:name":"Kanogama",
    "gn:population":0,
    "gn:timezone":"Asia/Colombo",
    "iso:country":"LK",
    "wof:name":"Kanogama",
    "wof:placetype":"locality"
},
  "geometry": {"coordinates":[80.26666999999998,7.68333],"type":"Point"}
}