{
  "type": "Feature",
  "properties": {
    "gn:admin1_code":"38.0",
    "gn:asciiname":"Periya Aru",
    "gn:country_code":"LK",
    "gn:dem":-9999,
    "gn:feature_class":"P",
    "gn:feature_code":"PPL",
    "gn:name":"Periya Aru",
    "gn:population":0,
    "gn:timezone":"Asia/Colombo",
    "iso:country":"LK",
    "wof:name":"Periya Aru",
    "wof:placetype":"locality"
},
  "geometry": {"coordinates":[80.08333,9.15],"type":"Point"}
}