{
  "type": "Feature",
  "properties": {
    "gn:admin1_code":"29.0",
    "gn:asciiname":"Hewawisse",
    "gn:country_code":"LK",
    "gn:dem":620,
    "gn:feature_class":"P",
    "gn:feature_code":"PPL",
    "gn:name":"Hewawisse",
    "gn:population":0,
    "gn:timezone":"Asia/Colombo",
    "iso:country":"LK",
    "name:und_x_variant":[
        "Hewawissa",
        "Hewawisse"
    ],
    "wof:name":"Hewawisse",
    "wof:placetype":"locality"
},
  "geometry": {"coordinates":[80.7281,7.2098],"type":"Point"}
}