{
  "type": "Feature",
  "properties": {
    "gn:admin1_code":"37.0",
    "gn:asciiname":"Vakarai",
    "gn:country_code":"LK",
    "gn:dem":9,
    "gn:feature_class":"P",
    "gn:feature_code":"PPL",
    "gn:name":"Vakarai",
    "gn:population":21000,
    "gn:timezone":"Asia/Colombo",
    "iso:country":"LK",
    "name:tam_x_preferred":[
        "\u0bb5\u0bbe\u0b95\u0bb0\u0bc8"
    ],
    "wof:name":"Vakarai",
    "wof:placetype":"locality",
    "wof:population":21000
},
  "geometry": {"coordinates":[81.43333,8.13333],"type":"Point"}
}