{
  "type": "Feature",
  "properties": {
    "gn:admin1_code":"36.0",
    "gn:asciiname":"Sayakkaramulla",
    "gn:country_code":"LK",
    "gn:dem":33,
    "gn:feature_class":"P",
    "gn:feature_code":"PPL",
    "gn:name":"Sayakkaramulla",
    "gn:population":0,
    "gn:timezone":"Asia/Colombo",
    "iso:country":"LK",
    "wof:name":"Sayakkaramulla",
    "wof:placetype":"locality"
},
  "geometry": {"coordinates":[79.98333000000002,7.23333],"type":"Point"}
}