{
  "type": "Feature",
  "properties": {
    "gn:admin1_code":"38.0",
    "gn:asciiname":"Putuvilankulam",
    "gn:country_code":"LK",
    "gn:dem":62,
    "gn:feature_class":"P",
    "gn:feature_code":"PPL",
    "gn:name":"Putuvilankulam",
    "gn:population":0,
    "gn:timezone":"Asia/Colombo",
    "iso:country":"LK",
    "wof:name":"Putuvilankulam",
    "wof:placetype":"locality"
},
  "geometry": {"coordinates":[80.45010000000001,9.0418],"type":"Point"}
}