{
  "type": "Feature",
  "properties": {
    "gn:admin1_code":"33.0",
    "gn:asciiname":"Eggodakanda",
    "gn:country_code":"LK",
    "gn:dem":903,
    "gn:feature_class":"P",
    "gn:feature_code":"PPL",
    "gn:name":"Eggodakanda",
    "gn:population":0,
    "gn:timezone":"Asia/Colombo",
    "iso:country":"LK",
    "name:und_x_variant":[
        "Egodakanda",
        "Eggodakanda"
    ],
    "wof:name":"Eggodakanda",
    "wof:placetype":"locality"
},
  "geometry": {"coordinates":[80.6592,6.3922],"type":"Point"}
}