{
  "type": "Feature",
  "properties": {
    "gn:admin1_code":"29.0",
    "gn:asciiname":"Welapahala",
    "gn:country_code":"LK",
    "gn:dem":656,
    "gn:feature_class":"P",
    "gn:feature_code":"PPL",
    "gn:name":"Welapahala",
    "gn:population":0,
    "gn:timezone":"Asia/Colombo",
    "iso:country":"LK",
    "wof:name":"Welapahala",
    "wof:placetype":"locality"
},
  "geometry": {"coordinates":[80.8027,7.1201],"type":"Point"}
}