{
  "type": "Feature",
  "properties": {
    "gn:admin1_code":"29.0",
    "gn:asciiname":"Ilukwatta",
    "gn:country_code":"LK",
    "gn:dem":514,
    "gn:feature_class":"P",
    "gn:feature_code":"PPL",
    "gn:name":"Ilukwatta",
    "gn:population":0,
    "gn:timezone":"Asia/Colombo",
    "iso:country":"LK",
    "name:und_x_variant":[
        "Illukwatta"
    ],
    "wof:name":"Ilukwatta",
    "wof:placetype":"locality"
},
  "geometry": {"coordinates":[80.54179999999999,7.2624],"type":"Point"}
}