{
  "type": "Feature",
  "properties": {
    "gn:admin1_code":"35.0",
    "gn:asciiname":"Niwasa",
    "gn:country_code":"LK",
    "gn:dem":152,
    "gn:feature_class":"P",
    "gn:feature_code":"PPL",
    "gn:name":"Niwasa",
    "gn:population":0,
    "gn:timezone":"Asia/Colombo",
    "iso:country":"LK",
    "wof:name":"Niwasa",
    "wof:placetype":"locality"
},
  "geometry": {"coordinates":[81.3409,6.8605],"type":"Point"}
}