{
  "type": "Feature",
  "properties": {
    "gn:admin1_code":"38.0",
    "gn:asciiname":"Kulankulam",
    "gn:country_code":"LK",
    "gn:dem":51,
    "gn:feature_class":"P",
    "gn:feature_code":"PPL",
    "gn:name":"Kulankulam",
    "gn:population":0,
    "gn:timezone":"Asia/Colombo",
    "iso:country":"LK",
    "wof:name":"Kulankulam",
    "wof:placetype":"locality"
},
  "geometry": {"coordinates":[80.2317,8.7543],"type":"Point"}
}