{
  "type": "Feature",
  "properties": {
    "gn:admin1_code":"33.0",
    "gn:asciiname":"Godigomuwa",
    "gn:country_code":"LK",
    "gn:dem":266,
    "gn:feature_class":"P",
    "gn:feature_code":"PPL",
    "gn:name":"Godigomuwa",
    "gn:population":0,
    "gn:timezone":"Asia/Colombo",
    "iso:country":"LK",
    "wof:name":"Godigomuwa",
    "wof:placetype":"locality"
},
  "geometry": {"coordinates":[80.4509,7.1997],"type":"Point"}
}