{
  "type": "Feature",
  "properties": {
    "gn:admin1_code":"35.0",
    "gn:asciiname":"Kindagolla",
    "gn:country_code":"LK",
    "gn:dem":226,
    "gn:feature_class":"P",
    "gn:feature_code":"PPL",
    "gn:name":"Kindagolla",
    "gn:population":0,
    "gn:timezone":"Asia/Colombo",
    "iso:country":"LK",
    "name:und_x_variant":[
        "Kindagalla",
        "Kindagolla"
    ],
    "wof:name":"Kindagolla",
    "wof:placetype":"locality"
},
  "geometry": {"coordinates":[81.26049999999999,7.1672],"type":"Point"}
}