{
  "type": "Feature",
  "properties": {
    "gn:admin1_code":"34.0",
    "gn:asciiname":"Howpe",
    "gn:country_code":"LK",
    "gn:dem":20,
    "gn:feature_class":"P",
    "gn:feature_code":"PPL",
    "gn:name":"Howpe",
    "gn:population":0,
    "gn:timezone":"Asia/Colombo",
    "iso:country":"LK",
    "name:und_x_variant":[
        "Hawpe",
        "Howpe"
    ],
    "wof:name":"Howpe",
    "wof:placetype":"locality"
},
  "geometry": {"coordinates":[80.4898,6.1265],"type":"Point"}
}