{
  "type": "Feature",
  "properties": {
    "gn:admin1_code":"34.0",
    "gn:asciiname":"Rallerotawewa",
    "gn:cc2":"LK",
    "gn:country_code":"LK",
    "gn:dem":190,
    "gn:feature_class":"P",
    "gn:feature_code":"PPL",
    "gn:name":"Rallerotawewa",
    "gn:population":0,
    "gn:timezone":"Asia/Colombo",
    "iso:country":"LK",
    "name:und_x_variant":[
        "Rallagerotawewa",
        "Rallerotawewa"
    ],
    "wof:name":"Rallerotawewa",
    "wof:placetype":"locality"
},
  "geometry": {"coordinates":[80.53333000000001,7.81667],"type":"Point"}
}