{
  "type": "Feature",
  "properties": {
    "gn:admin1_code":"29.0",
    "gn:asciiname":"Katugashinna",
    "gn:country_code":"LK",
    "gn:dem":954,
    "gn:feature_class":"P",
    "gn:feature_code":"PPL",
    "gn:name":"Katugashinna",
    "gn:population":0,
    "gn:timezone":"Asia/Colombo",
    "iso:country":"LK",
    "wof:name":"Katugashinna",
    "wof:placetype":"locality"
},
  "geometry": {"coordinates":[80.78619999999999,7.1572],"type":"Point"}
}