{
  "type": "Feature",
  "properties": {
    "gn:admin1_code":"30.0",
    "gn:asciiname":"Udangawa",
    "gn:country_code":"LK",
    "gn:dem":126,
    "gn:feature_class":"P",
    "gn:feature_code":"PPL",
    "gn:name":"Udangawa",
    "gn:population":0,
    "gn:timezone":"Asia/Colombo",
    "iso:country":"LK",
    "wof:name":"Udangawa",
    "wof:placetype":"locality"
},
  "geometry": {"coordinates":[80.6421,8.589],"type":"Point"}
}