{
  "type": "Feature",
  "properties": {
    "gn:admin1_code":"33.0",
    "gn:asciiname":"Waraniyagoda",
    "gn:country_code":"LK",
    "gn:dem":40,
    "gn:feature_class":"P",
    "gn:feature_code":"PPL",
    "gn:name":"Waraniyagoda",
    "gn:population":0,
    "gn:timezone":"Asia/Colombo",
    "iso:country":"LK",
    "name:und_x_variant":[
        "Weraniyagoda"
    ],
    "wof:name":"Waraniyagoda",
    "wof:placetype":"locality"
},
  "geometry": {"coordinates":[80.37269999999999,6.6725],"type":"Point"}
}