{
  "type": "Feature",
  "properties": {
    "gn:admin1_code":"36.0",
    "gn:asciiname":"Kuttiwila",
    "gn:country_code":"LK",
    "gn:dem":51,
    "gn:feature_class":"P",
    "gn:feature_code":"PPL",
    "gn:name":"Kuttiwila",
    "gn:population":0,
    "gn:timezone":"Asia/Colombo",
    "iso:country":"LK",
    "wof:name":"Kuttiwila",
    "wof:placetype":"locality"
},
  "geometry": {"coordinates":[80.15389999999999,7.0399],"type":"Point"}
}