{
  "type": "Feature",
  "properties": {
    "gn:admin1_code":"30.0",
    "gn:asciiname":"Palu Gonumeriyawa",
    "gn:country_code":"LK",
    "gn:dem":125,
    "gn:feature_class":"P",
    "gn:feature_code":"PPL",
    "gn:name":"Palu Gonumeriyawa",
    "gn:population":0,
    "gn:timezone":"Asia/Colombo",
    "iso:country":"LK",
    "wof:name":"Palu Gonumeriyawa",
    "wof:placetype":"locality"
},
  "geometry": {"coordinates":[80.6383,8.4736],"type":"Point"}
}