{
  "type": "Feature",
  "properties": {
    "gn:admin1_code":"34.0",
    "gn:asciiname":"Wadumulla",
    "gn:country_code":"LK",
    "gn:dem":12,
    "gn:feature_class":"P",
    "gn:feature_code":"PPL",
    "gn:name":"Wadumulla",
    "gn:population":0,
    "gn:timezone":"Asia/Colombo",
    "iso:country":"LK",
    "name:und_x_variant":[
        "Kommala Wadumulla"
    ],
    "wof:name":"Wadumulla",
    "wof:placetype":"locality"
},
  "geometry": {"coordinates":[80.0188,6.4274],"type":"Point"}
}