{
  "type": "Feature",
  "properties": {
    "gn:admin1_code":"36.0",
    "gn:asciiname":"Pahala Bope",
    "gn:country_code":"LK",
    "gn:dem":42,
    "gn:feature_class":"P",
    "gn:feature_code":"PPL",
    "gn:name":"Pahala Bope",
    "gn:population":0,
    "gn:timezone":"Asia/Colombo",
    "iso:country":"LK",
    "wof:name":"Pahala Bope",
    "wof:placetype":"locality"
},
  "geometry": {"coordinates":[80.1369,6.8378],"type":"Point"}
}