{
  "type": "Feature",
  "properties": {
    "gn:admin1_code":"29.0",
    "gn:asciiname":"Bembiya",
    "gn:country_code":"LK",
    "gn:dem":580,
    "gn:feature_class":"P",
    "gn:feature_code":"PPL",
    "gn:name":"Bembiya",
    "gn:population":0,
    "gn:timezone":"Asia/Colombo",
    "iso:country":"LK",
    "wof:name":"Bembiya",
    "wof:placetype":"locality"
},
  "geometry": {"coordinates":[80.93333,7.23333],"type":"Point"}
}