{
  "type": "Feature",
  "properties": {
    "gn:admin1_code":"33.0",
    "gn:asciiname":"Gonakumbura",
    "gn:country_code":"LK",
    "gn:dem":134,
    "gn:feature_class":"P",
    "gn:feature_code":"PPL",
    "gn:name":"Gonakumbura",
    "gn:population":0,
    "gn:timezone":"Asia/Colombo",
    "iso:country":"LK",
    "wof:name":"Gonakumbura",
    "wof:placetype":"locality"
},
  "geometry": {"coordinates":[80.45310000000001,6.694],"type":"Point"}
}