{
  "type": "Feature",
  "properties": {
    "gn:admin1_code":"38.0",
    "gn:asciiname":"Tanniyuttu",
    "gn:country_code":"LK",
    "gn:dem":28,
    "gn:feature_class":"P",
    "gn:feature_code":"PPL",
    "gn:name":"Tanniyuttu",
    "gn:population":0,
    "gn:timezone":"Asia/Colombo",
    "iso:country":"LK",
    "name:und_x_variant":[
        "Tannyuttu",
        "Tanniyuttu"
    ],
    "wof:name":"Tanniyuttu",
    "wof:placetype":"locality"
},
  "geometry": {"coordinates":[80.78333000000001,9.21667],"type":"Point"}
}