{
  "type": "Feature",
  "properties": {
    "gn:admin1_code":"34.0",
    "gn:asciiname":"Kudagalage",
    "gn:country_code":"LK",
    "gn:dem":142,
    "gn:feature_class":"P",
    "gn:feature_code":"PPL",
    "gn:name":"Kudagalage",
    "gn:population":0,
    "gn:timezone":"Asia/Colombo",
    "iso:country":"LK",
    "name:und_x_variant":[
        "Kudagalara"
    ],
    "wof:name":"Kudagalage",
    "wof:placetype":"locality"
},
  "geometry": {"coordinates":[80.7677,6.2324],"type":"Point"}
}