{
  "type": "Feature",
  "properties": {
    "gn:admin1_code":"34.0",
    "gn:asciiname":"Andalla",
    "gn:cc2":"LK",
    "gn:country_code":"LK",
    "gn:dem":25,
    "gn:feature_class":"P",
    "gn:feature_code":"PPL",
    "gn:name":"Andalla",
    "gn:population":0,
    "gn:timezone":"Asia/Colombo",
    "iso:country":"LK",
    "name:und_x_variant":[
        "Andalle",
        "Andalla"
    ],
    "wof:name":"Andalla",
    "wof:placetype":"locality"
},
  "geometry": {"coordinates":[81.21666999999999,6.23333],"type":"Point"}
}