{
  "type": "Feature",
  "properties": {
    "gn:admin1_code":"29.0",
    "gn:asciiname":"Naranpanawa Disaneggammedda",
    "gn:cc2":"LK",
    "gn:country_code":"LK",
    "gn:dem":797,
    "gn:feature_class":"P",
    "gn:feature_code":"PPL",
    "gn:name":"Naranpanawa Disaneggammedda",
    "gn:population":0,
    "gn:timezone":"Asia/Colombo",
    "iso:country":"LK",
    "name:und_x_variant":[
        "Naranpanawe Disanekgammedda",
        "Naranpanawa Disaneggammedda"
    ],
    "wof:name":"Naranpanawa Disaneggammedda",
    "wof:placetype":"locality"
},
  "geometry": {"coordinates":[80.71666999999999,7.33333],"type":"Point"}
}