{
  "type": "Feature",
  "properties": {
    "gn:admin1_code":"32.0",
    "gn:asciiname":"Naranmaluwa",
    "gn:country_code":"LK",
    "gn:dem":226,
    "gn:feature_class":"P",
    "gn:feature_code":"PPL",
    "gn:name":"Naranmaluwa",
    "gn:population":0,
    "gn:timezone":"Asia/Colombo",
    "iso:country":"LK",
    "name:und_x_variant":[
        "Naranmoluwa"
    ],
    "wof:name":"Naranmaluwa",
    "wof:placetype":"locality"
},
  "geometry": {"coordinates":[80.4849,7.4661],"type":"Point"}
}