{
  "type": "Feature",
  "properties": {
    "gn:admin1_code":"32.0",
    "gn:asciiname":"Kudatammannewa",
    "gn:country_code":"LK",
    "gn:dem":103,
    "gn:feature_class":"P",
    "gn:feature_code":"PPL",
    "gn:name":"Kudatammannewa",
    "gn:population":0,
    "gn:timezone":"Asia/Colombo",
    "iso:country":"LK",
    "wof:name":"Kudatammannewa",
    "wof:placetype":"locality"
},
  "geometry": {"coordinates":[80.25,8.08333],"type":"Point"}
}