{
  "type": "Feature",
  "properties": {
    "gn:admin1_code":"32.0",
    "gn:asciiname":"Nelunpatgama",
    "gn:country_code":"LK",
    "gn:dem":100,
    "gn:feature_class":"P",
    "gn:feature_code":"PPL",
    "gn:name":"Nelunpatgama",
    "gn:population":0,
    "gn:timezone":"Asia/Colombo",
    "iso:country":"LK",
    "wof:name":"Nelunpatgama",
    "wof:placetype":"locality"
},
  "geometry": {"coordinates":[80.3489,7.6416],"type":"Point"}
}