{
  "type": "Feature",
  "properties": {
    "gn:admin1_code":"35.0",
    "gn:asciiname":"Nanangoda",
    "gn:country_code":"LK",
    "gn:dem":244,
    "gn:feature_class":"P",
    "gn:feature_code":"PPL",
    "gn:name":"Nanangoda",
    "gn:population":0,
    "gn:timezone":"Asia/Colombo",
    "iso:country":"LK",
    "name:und_x_variant":[
        "Nahangoda"
    ],
    "wof:name":"Nanangoda",
    "wof:placetype":"locality"
},
  "geometry": {"coordinates":[81.25020000000001,7.0785],"type":"Point"}
}