{
  "type": "Feature",
  "properties": {
    "gn:admin1_code":"38.0",
    "gn:asciiname":"Padinaddampore",
    "gn:country_code":"LK",
    "gn:dem":58,
    "gn:feature_class":"P",
    "gn:feature_code":"PPL",
    "gn:name":"Padinaddampore",
    "gn:population":0,
    "gn:timezone":"Asia/Colombo",
    "iso:country":"LK",
    "wof:name":"Padinaddampore",
    "wof:placetype":"locality"
},
  "geometry": {"coordinates":[80.4126,9.2319],"type":"Point"}
}