{
  "type": "Feature",
  "properties": {
    "gn:admin1_code":"38.0",
    "gn:asciiname":"Aiyamperumal",
    "gn:country_code":"LK",
    "gn:dem":57,
    "gn:feature_class":"P",
    "gn:feature_code":"PPL",
    "gn:name":"Aiyamperumal",
    "gn:population":0,
    "gn:timezone":"Asia/Colombo",
    "iso:country":"LK",
    "name:fas_x_preferred":[
        "\u0627\u06cc\u0645\u067e\u0631\u0648\u0645\u0627\u0644"
    ],
    "wof:name":"Aiyamperumal",
    "wof:placetype":"locality"
},
  "geometry": {"coordinates":[80.36667,9.05],"type":"Point"}
}