{
  "type": "Feature",
  "properties": {
    "gn:admin1_code":"30.0",
    "gn:asciiname":"Pahala Walawachchiya",
    "gn:country_code":"LK",
    "gn:dem":109,
    "gn:feature_class":"P",
    "gn:feature_code":"PPL",
    "gn:name":"Pahala Walawachchiya",
    "gn:population":0,
    "gn:timezone":"Asia/Colombo",
    "iso:country":"LK",
    "name:und_x_variant":[
        "Pahala Walawichchiya",
        "Pahala Walawachchiya"
    ],
    "wof:name":"Pahala Walawachchiya",
    "wof:placetype":"locality"
},
  "geometry": {"coordinates":[80.53019999999999,8.3595],"type":"Point"}
}