{
  "type": "Feature",
  "properties": {
    "gn:admin1_code":"33.0",
    "gn:asciiname":"Niwatuwa",
    "gn:country_code":"LK",
    "gn:dem":135,
    "gn:feature_class":"P",
    "gn:feature_code":"PPL",
    "gn:name":"Niwatuwa",
    "gn:population":0,
    "gn:timezone":"Asia/Colombo",
    "iso:country":"LK",
    "wof:name":"Niwatuwa",
    "wof:placetype":"locality"
},
  "geometry": {"coordinates":[80.1968,7.1856],"type":"Point"}
}