{
  "type": "Feature",
  "properties": {
    "gn:admin1_code":"32.0",
    "gn:asciiname":"Bendapuwewa",
    "gn:country_code":"LK",
    "gn:dem":115,
    "gn:feature_class":"P",
    "gn:feature_code":"PPL",
    "gn:name":"Bendapuwewa",
    "gn:population":0,
    "gn:timezone":"Asia/Colombo",
    "iso:country":"LK",
    "wof:name":"Bendapuwewa",
    "wof:placetype":"locality"
},
  "geometry": {"coordinates":[80.23333000000002,8.05],"type":"Point"}
}