{
  "type": "Feature",
  "properties": {
    "gn:admin1_code":"34.0",
    "gn:asciiname":"Koragoda",
    "gn:country_code":"LK",
    "gn:dem":42,
    "gn:feature_class":"P",
    "gn:feature_code":"PPL",
    "gn:name":"Koragoda",
    "gn:population":0,
    "gn:timezone":"Asia/Colombo",
    "iso:country":"LK",
    "wof:name":"Koragoda",
    "wof:placetype":"locality"
},
  "geometry": {"coordinates":[80.47199999999999,6.1308],"type":"Point"}
}