{
  "type": "Feature",
  "properties": {
    "gn:admin1_code":"33.0",
    "gn:asciiname":"Palana Kukulegama North",
    "gn:country_code":"LK",
    "gn:dem":225,
    "gn:feature_class":"P",
    "gn:feature_code":"PPL",
    "gn:name":"Palana Kukulegama North",
    "gn:population":0,
    "gn:timezone":"Asia/Colombo",
    "iso:country":"LK",
    "wof:name":"Palana Kukulegama North",
    "wof:placetype":"locality"
},
  "geometry": {"coordinates":[80.3642,6.5358],"type":"Point"}
}