{
  "type": "Feature",
  "properties": {
    "gn:admin1_code":"32.0",
    "gn:asciiname":"Koswatta",
    "gn:country_code":"LK",
    "gn:dem":31,
    "gn:feature_class":"P",
    "gn:feature_code":"PPL",
    "gn:name":"Koswatta",
    "gn:population":0,
    "gn:timezone":"Asia/Colombo",
    "iso:country":"LK",
    "wof:name":"Koswatta",
    "wof:placetype":"locality"
},
  "geometry": {"coordinates":[79.893,7.3692],"type":"Point"}
}