{
  "type": "Feature",
  "properties": {
    "gn:admin1_code":"36.0",
    "gn:asciiname":"Meddegma",
    "gn:country_code":"LK",
    "gn:dem":22,
    "gn:feature_class":"P",
    "gn:feature_code":"PPL",
    "gn:name":"Meddegma",
    "gn:population":0,
    "gn:timezone":"Asia/Colombo",
    "iso:country":"LK",
    "name:und_x_variant":[
        "Meddegama"
    ],
    "wof:name":"Meddegma",
    "wof:placetype":"locality"
},
  "geometry": {"coordinates":[80.1324,7.0269],"type":"Point"}
}