{
  "type": "Feature",
  "properties": {
    "gn:admin1_code":"34.0",
    "gn:asciiname":"Ulianowitimulla",
    "gn:country_code":"LK",
    "gn:dem":13,
    "gn:feature_class":"P",
    "gn:feature_code":"PPL",
    "gn:name":"Ulianowitimulla",
    "gn:population":0,
    "gn:timezone":"Asia/Colombo",
    "iso:country":"LK",
    "wof:name":"Ulianowitimulla",
    "wof:placetype":"locality"
},
  "geometry": {"coordinates":[80.146,6.3596],"type":"Point"}
}