{
  "type": "Feature",
  "properties": {
    "gn:admin1_code":"29.0",
    "gn:asciiname":"Kumbukwela",
    "gn:country_code":"LK",
    "gn:dem":612,
    "gn:feature_class":"P",
    "gn:feature_code":"PPL",
    "gn:name":"Kumbukwela",
    "gn:population":0,
    "gn:timezone":"Asia/Colombo",
    "iso:country":"LK",
    "name:und_x_variant":[
        "Kumbukwala"
    ],
    "wof:name":"Kumbukwela",
    "wof:placetype":"locality"
},
  "geometry": {"coordinates":[80.8116,7.1299],"type":"Point"}
}