{
  "type": "Feature",
  "properties": {
    "gn:admin1_code":"34.0",
    "gn:asciiname":"Marakkalagoda",
    "gn:country_code":"LK",
    "gn:dem":13,
    "gn:feature_class":"P",
    "gn:feature_code":"PPL",
    "gn:name":"Marakkalagoda",
    "gn:population":0,
    "gn:timezone":"Asia/Colombo",
    "iso:country":"LK",
    "wof:name":"Marakkalagoda",
    "wof:placetype":"locality"
},
  "geometry": {"coordinates":[80.77760000000001,6.065],"type":"Point"}
}