{
  "type": "Feature",
  "properties": {
    "gn:admin1_code":"33.0",
    "gn:asciiname":"Elamaldeniya",
    "gn:country_code":"LK",
    "gn:dem":48,
    "gn:feature_class":"P",
    "gn:feature_code":"PPL",
    "gn:name":"Elamaldeniya",
    "gn:population":0,
    "gn:timezone":"Asia/Colombo",
    "iso:country":"LK",
    "name:und_x_variant":[
        "Elamaideniya",
        "Elamaldeniya"
    ],
    "wof:name":"Elamaldeniya",
    "wof:placetype":"locality"
},
  "geometry": {"coordinates":[80.2734,7.1389],"type":"Point"}
}