{
  "type": "Feature",
  "properties": {
    "gn:admin1_code":"33.0",
    "gn:asciiname":"Galamella",
    "gn:country_code":"LK",
    "gn:dem":283,
    "gn:feature_class":"P",
    "gn:feature_code":"PPL",
    "gn:name":"Galamella",
    "gn:population":0,
    "gn:timezone":"Asia/Colombo",
    "iso:country":"LK",
    "wof:name":"Galamella",
    "wof:placetype":"locality"
},
  "geometry": {"coordinates":[80.66379999999999,6.4778],"type":"Point"}
}