{
  "type": "Feature",
  "properties": {
    "gn:admin1_code":"38.0",
    "gn:asciiname":"Kandaikkulam",
    "gn:country_code":"LK",
    "gn:dem":73,
    "gn:feature_class":"P",
    "gn:feature_code":"PPL",
    "gn:name":"Kandaikkulam",
    "gn:population":0,
    "gn:timezone":"Asia/Colombo",
    "iso:country":"LK",
    "wof:name":"Kandaikkulam",
    "wof:placetype":"locality"
},
  "geometry": {"coordinates":[80.3413,8.6468],"type":"Point"}
}