{
  "type": "Feature",
  "properties": {
    "gn:admin1_code":"36.0",
    "gn:asciiname":"Gurudala",
    "gn:country_code":"LK",
    "gn:dem":31,
    "gn:feature_class":"P",
    "gn:feature_code":"PPL",
    "gn:name":"Gurudala",
    "gn:population":0,
    "gn:timezone":"Asia/Colombo",
    "iso:country":"LK",
    "name:und_x_variant":[
        "Gurudola"
    ],
    "wof:name":"Gurudala",
    "wof:placetype":"locality"
},
  "geometry": {"coordinates":[80.1073,6.5409],"type":"Point"}
}