{
  "type": "Feature",
  "properties": {
    "gn:admin1_code":"32.0",
    "gn:asciiname":"Pallekekulawela",
    "gn:country_code":"LK",
    "gn:dem":81,
    "gn:feature_class":"P",
    "gn:feature_code":"PPL",
    "gn:name":"Pallekekulawela",
    "gn:population":0,
    "gn:timezone":"Asia/Colombo",
    "iso:country":"LK",
    "name:und_x_variant":[
        "Pallekekulawala"
    ],
    "wof:name":"Pallekekulawela",
    "wof:placetype":"locality"
},
  "geometry": {"coordinates":[80.1747,7.2829],"type":"Point"}
}