{
  "type": "Feature",
  "properties": {
    "gn:admin1_code":"29.0",
    "gn:asciiname":"Andawala",
    "gn:cc2":"LK",
    "gn:country_code":"LK",
    "gn:dem":441,
    "gn:feature_class":"P",
    "gn:feature_code":"PPL",
    "gn:name":"Andawala",
    "gn:population":0,
    "gn:timezone":"Asia/Colombo",
    "iso:country":"LK",
    "name:und_x_variant":[
        "Andawela"
    ],
    "wof:name":"Andawala",
    "wof:placetype":"locality"
},
  "geometry": {"coordinates":[80.83333,7.13333],"type":"Point"}
}