{
  "type": "Feature",
  "properties": {
    "gn:admin1_code":"33.0",
    "gn:asciiname":"Hewagedara",
    "gn:country_code":"LK",
    "gn:dem":299,
    "gn:feature_class":"P",
    "gn:feature_code":"PPL",
    "gn:name":"Hewagedara",
    "gn:population":0,
    "gn:timezone":"Asia/Colombo",
    "iso:country":"LK",
    "wof:name":"Hewagedara",
    "wof:placetype":"locality"
},
  "geometry": {"coordinates":[80.5682,6.5654],"type":"Point"}
}