{
  "type": "Feature",
  "properties": {
    "gn:admin1_code":"34.0",
    "gn:asciiname":"Elalla",
    "gn:country_code":"LK",
    "gn:dem":57,
    "gn:feature_class":"P",
    "gn:feature_code":"PPL",
    "gn:name":"Elalla",
    "gn:population":0,
    "gn:timezone":"Asia/Colombo",
    "iso:country":"LK",
    "name:und_x_variant":[
        "Ellala",
        "Elalla"
    ],
    "wof:name":"Elalla",
    "wof:placetype":"locality"
},
  "geometry": {"coordinates":[81.06999999999999,6.3111],"type":"Point"}
}