{
  "type": "Feature",
  "properties": {
    "gn:admin1_code":"32.0",
    "gn:asciiname":"Kandegedara",
    "gn:country_code":"LK",
    "gn:dem":183,
    "gn:feature_class":"P",
    "gn:feature_code":"PPL",
    "gn:name":"Kandegedara",
    "gn:population":0,
    "gn:timezone":"Asia/Colombo",
    "iso:country":"LK",
    "wof:name":"Kandegedara",
    "wof:placetype":"locality"
},
  "geometry": {"coordinates":[80.49600000000002,7.6086],"type":"Point"}
}