{
  "type": "Feature",
  "properties": {
    "gn:admin1_code":"30.0",
    "gn:asciiname":"Kanhindewa",
    "gn:country_code":"LK",
    "gn:dem":81,
    "gn:feature_class":"P",
    "gn:feature_code":"PPL",
    "gn:name":"Kanhindewa",
    "gn:population":0,
    "gn:timezone":"Asia/Colombo",
    "iso:country":"LK",
    "wof:name":"Kanhindewa",
    "wof:placetype":"locality"
},
  "geometry": {"coordinates":[80.8073,8.4554],"type":"Point"}
}