{
  "type": "Feature",
  "properties": {
    "gn:admin1_code":"33.0",
    "gn:asciiname":"Nabuluwa",
    "gn:country_code":"LK",
    "gn:dem":340,
    "gn:feature_class":"P",
    "gn:feature_code":"PPL",
    "gn:name":"Nabuluwa",
    "gn:population":0,
    "gn:timezone":"Asia/Colombo",
    "iso:country":"LK",
    "wof:name":"Nabuluwa",
    "wof:placetype":"locality"
},
  "geometry": {"coordinates":[80.5643,6.5446],"type":"Point"}
}