{
  "type": "Feature",
  "properties": {
    "gn:admin1_code":"30.0",
    "gn:asciiname":"Kohombadamana",
    "gn:country_code":"LK",
    "gn:dem":60,
    "gn:feature_class":"P",
    "gn:feature_code":"PPL",
    "gn:name":"Kohombadamana",
    "gn:population":0,
    "gn:timezone":"Asia/Colombo",
    "iso:country":"LK",
    "wof:name":"Kohombadamana",
    "wof:placetype":"locality"
},
  "geometry": {"coordinates":[81.0102,8.1543],"type":"Point"}
}