{
  "type": "Feature",
  "properties": {
    "gn:admin1_code":"32.0",
    "gn:asciiname":"Koshena",
    "gn:country_code":"LK",
    "gn:dem":23,
    "gn:feature_class":"P",
    "gn:feature_code":"PPL",
    "gn:name":"Koshena",
    "gn:population":0,
    "gn:timezone":"Asia/Colombo",
    "iso:country":"LK",
    "wof:name":"Koshena",
    "wof:placetype":"locality"
},
  "geometry": {"coordinates":[79.998,7.5174],"type":"Point"}
}