{
  "type": "Feature",
  "properties": {
    "gn:admin1_code":"32.0",
    "gn:asciiname":"Ihala Labbala",
    "gn:country_code":"LK",
    "gn:dem":67,
    "gn:feature_class":"P",
    "gn:feature_code":"PPL",
    "gn:name":"Ihala Labbala",
    "gn:population":0,
    "gn:timezone":"Asia/Colombo",
    "iso:country":"LK",
    "name:und_x_variant":[
        "Ihala Labbawa"
    ],
    "wof:name":"Ihala Labbala",
    "wof:placetype":"locality"
},
  "geometry": {"coordinates":[80.07859999999999,7.3452],"type":"Point"}
}