{
  "type": "Feature",
  "properties": {
    "gn:admin1_code":"32.0",
    "gn:asciiname":"Thambana",
    "gn:country_code":"LK",
    "gn:dem":31,
    "gn:feature_class":"P",
    "gn:feature_code":"PPL",
    "gn:name":"Thambana",
    "gn:population":0,
    "gn:timezone":"Asia/Colombo",
    "iso:country":"LK",
    "name:und_x_variant":[
        "Tambana"
    ],
    "wof:name":"Thambana",
    "wof:placetype":"locality"
},
  "geometry": {"coordinates":[79.97629999999999,7.3885],"type":"Point"}
}