{
  "type": "Feature",
  "properties": {
    "gn:admin1_code":"30.0",
    "gn:asciiname":"Kuda Ittikattiya",
    "gn:country_code":"LK",
    "gn:dem":151,
    "gn:feature_class":"P",
    "gn:feature_code":"PPL",
    "gn:name":"Kuda Ittikattiya",
    "gn:population":0,
    "gn:timezone":"Asia/Colombo",
    "iso:country":"LK",
    "wof:name":"Kuda Ittikattiya",
    "wof:placetype":"locality"
},
  "geometry": {"coordinates":[80.5402,8.1263],"type":"Point"}
}