{
  "type": "Feature",
  "properties": {
    "gn:admin1_code":"30.0",
    "gn:asciiname":"Hanmillewa",
    "gn:country_code":"LK",
    "gn:dem":152,
    "gn:feature_class":"P",
    "gn:feature_code":"PPL",
    "gn:name":"Hanmillewa",
    "gn:population":0,
    "gn:timezone":"Asia/Colombo",
    "iso:country":"LK",
    "name:und_x_variant":[
        "Hammillewa"
    ],
    "wof:name":"Hanmillewa",
    "wof:placetype":"locality"
},
  "geometry": {"coordinates":[80.51899999999998,7.9505],"type":"Point"}
}