{
  "type": "Feature",
  "properties": {
    "gn:admin1_code":"29.0",
    "gn:asciiname":"Godamunna",
    "gn:cc2":"LK",
    "gn:country_code":"LK",
    "gn:dem":885,
    "gn:feature_class":"P",
    "gn:feature_code":"PPL",
    "gn:name":"Godamunna",
    "gn:population":0,
    "gn:timezone":"Asia/Colombo",
    "iso:country":"LK",
    "name:sin_x_preferred":[
        "\u0d9c\u0ddc\u0da9\u0dcf\u0db8\u0dd4\u0dab"
    ],
    "name:und_x_variant":[
        "Godamuna",
        "Godamunna"
    ],
    "wof:name":"Godamunna",
    "wof:placetype":"locality"
},
  "geometry": {"coordinates":[80.78333000000001,7.33333],"type":"Point"}
}