{
  "type": "Feature",
  "properties": {
    "gn:admin1_code":"38.0",
    "gn:admin2_code":"1236148.0",
    "gn:asciiname":"Manalkulam",
    "gn:country_code":"LK",
    "gn:dem":9,
    "gn:feature_class":"P",
    "gn:feature_code":"PPL",
    "gn:name":"Manalkulam",
    "gn:population":0,
    "gn:timezone":"Asia/Colombo",
    "iso:country":"LK",
    "name:und_x_variant":[
        "Manatkulam",
        "Manalkulam"
    ],
    "wof:name":"Manalkulam",
    "wof:placetype":"locality"
},
  "geometry": {"coordinates":[79.98665,8.87799],"type":"Point"}
}