{
  "type": "Feature",
  "properties": {
    "gn:admin1_code":"29.0",
    "gn:asciiname":"Sirangahawatta",
    "gn:country_code":"LK",
    "gn:dem":757,
    "gn:feature_class":"P",
    "gn:feature_code":"PPL",
    "gn:name":"Sirangahawatta",
    "gn:population":0,
    "gn:timezone":"Asia/Colombo",
    "iso:country":"LK",
    "name:ceb_x_preferred":[
        "Sirangahawatta"
    ],
    "name:swe_x_preferred":[
        "Sirangahawatta"
    ],
    "wof:name":"Sirangahawatta",
    "wof:placetype":"locality"
},
  "geometry": {"coordinates":[80.6964,7.5446],"type":"Point"}
}