{
  "type": "Feature",
  "properties": {
    "gn:admin1_code":"33.0",
    "gn:asciiname":"Alutnuwara",
    "gn:country_code":"LK",
    "gn:dem":239,
    "gn:feature_class":"P",
    "gn:feature_code":"PPL",
    "gn:name":"Alutnuwara",
    "gn:population":0,
    "gn:timezone":"Asia/Colombo",
    "iso:country":"LK",
    "wof:name":"Alutnuwara",
    "wof:placetype":"locality"
},
  "geometry": {"coordinates":[80.46666999999999,7.23333],"type":"Point"}
}