{
  "type": "Feature",
  "properties": {
    "gn:admin1_code":"30.0",
    "gn:asciiname":"Kottalbadda-Karambewa",
    "gn:country_code":"LK",
    "gn:dem":136,
    "gn:feature_class":"P",
    "gn:feature_code":"PPL",
    "gn:name":"Kottalbadda-Karambewa",
    "gn:population":0,
    "gn:timezone":"Asia/Colombo",
    "iso:country":"LK",
    "wof:name":"Kottalbadda-Karambewa",
    "wof:placetype":"locality"
},
  "geometry": {"coordinates":[80.53333000000001,8.06667],"type":"Point"}
}