{
  "type": "Feature",
  "properties": {
    "gn:admin1_code":"32.0",
    "gn:asciiname":"Buluewa",
    "gn:country_code":"LK",
    "gn:dem":132,
    "gn:feature_class":"P",
    "gn:feature_code":"PPL",
    "gn:name":"Buluewa",
    "gn:population":0,
    "gn:timezone":"Asia/Colombo",
    "iso:country":"LK",
    "name:und_x_variant":[
        "Bulnewa"
    ],
    "wof:name":"Buluewa",
    "wof:placetype":"locality"
},
  "geometry": {"coordinates":[80.4059,7.994],"type":"Point"}
}