{
  "type": "Feature",
  "properties": {
    "gn:admin1_code":"30.0",
    "gn:asciiname":"Kivulpitiya",
    "gn:country_code":"LK",
    "gn:dem":101,
    "gn:feature_class":"P",
    "gn:feature_code":"PPL",
    "gn:name":"Kivulpitiya",
    "gn:population":0,
    "gn:timezone":"Asia/Colombo",
    "iso:country":"LK",
    "name:und_x_variant":[
        "Kiwulpitiya"
    ],
    "wof:name":"Kivulpitiya",
    "wof:placetype":"locality"
},
  "geometry": {"coordinates":[80.3963,8.1206],"type":"Point"}
}