{
  "type": "Feature",
  "properties": {
    "gn:admin1_code":"29.0",
    "gn:asciiname":"Kotakedeniya",
    "gn:country_code":"LK",
    "gn:dem":544,
    "gn:feature_class":"P",
    "gn:feature_code":"PPL",
    "gn:name":"Kotakedeniya",
    "gn:population":0,
    "gn:timezone":"Asia/Colombo",
    "iso:country":"LK",
    "wof:name":"Kotakedeniya",
    "wof:placetype":"locality"
},
  "geometry": {"coordinates":[80.5949,7.1949],"type":"Point"}
}