{
  "type": "Feature",
  "properties": {
    "gn:admin1_code":"34.0",
    "gn:asciiname":"Uruperetta",
    "gn:country_code":"LK",
    "gn:dem":37,
    "gn:feature_class":"P",
    "gn:feature_code":"PPL",
    "gn:name":"Uruperetta",
    "gn:population":0,
    "gn:timezone":"Asia/Colombo",
    "iso:country":"LK",
    "wof:name":"Uruperetta",
    "wof:placetype":"locality"
},
  "geometry": {"coordinates":[80.9335,6.2429],"type":"Point"}
}