{
  "type": "Feature",
  "properties": {
    "gn:admin1_code":"29.0",
    "gn:asciiname":"Mawatapola",
    "gn:country_code":"LK",
    "gn:dem":589,
    "gn:feature_class":"P",
    "gn:feature_code":"PPL",
    "gn:name":"Mawatapola",
    "gn:population":0,
    "gn:timezone":"Asia/Colombo",
    "iso:country":"LK",
    "name:ceb_x_preferred":[
        "Mawatapola"
    ],
    "name:swe_x_preferred":[
        "Mawatapola"
    ],
    "name:und_x_variant":[
        "Mawatupola",
        "Mawatapola"
    ],
    "wof:name":"Mawatapola",
    "wof:placetype":"locality"
},
  "geometry": {"coordinates":[80.61799999999999,7.4025],"type":"Point"}
}