{
  "type": "Feature",
  "properties": {
    "gn:admin1_code":"35.0",
    "gn:asciiname":"Udayaya",
    "gn:country_code":"LK",
    "gn:dem":297,
    "gn:feature_class":"P",
    "gn:feature_code":"PPL",
    "gn:name":"Udayaya",
    "gn:population":0,
    "gn:timezone":"Asia/Colombo",
    "iso:country":"LK",
    "wof:name":"Udayaya",
    "wof:placetype":"locality"
},
  "geometry": {"coordinates":[81.0956,7.2014],"type":"Point"}
}