{
  "type": "Feature",
  "properties": {
    "gn:admin1_code":"30.0",
    "gn:asciiname":"Kurapayiyawa",
    "gn:cc2":"LK",
    "gn:country_code":"LK",
    "gn:dem":131,
    "gn:feature_class":"P",
    "gn:feature_code":"PPL",
    "gn:name":"Kurapayiyawa",
    "gn:population":0,
    "gn:timezone":"Asia/Colombo",
    "iso:country":"LK",
    "name:und_x_variant":[
        "Kurupaiyawa",
        "Kurapayiyawa"
    ],
    "wof:name":"Kurapayiyawa",
    "wof:placetype":"locality"
},
  "geometry": {"coordinates":[80.65000000000001,8.28333],"type":"Point"}
}