{
  "type": "Feature",
  "properties": {
    "gn:admin1_code":"35.0",
    "gn:asciiname":"Hambegamuwa",
    "gn:country_code":"LK",
    "gn:dem":127,
    "gn:feature_class":"P",
    "gn:feature_code":"PPL",
    "gn:name":"Hambegamuwa",
    "gn:population":0,
    "gn:timezone":"Asia/Colombo",
    "iso:country":"LK",
    "wof:name":"Hambegamuwa",
    "wof:placetype":"locality"
},
  "geometry": {"coordinates":[80.9568,6.5331],"type":"Point"}
}