{
  "type": "Feature",
  "properties": {
    "gn:admin1_code":"32.0",
    "gn:asciiname":"Henegedara-kala",
    "gn:country_code":"LK",
    "gn:dem":88,
    "gn:feature_class":"P",
    "gn:feature_code":"PPL",
    "gn:name":"Henegedara-kala",
    "gn:population":0,
    "gn:timezone":"Asia/Colombo",
    "iso:country":"LK",
    "wof:name":"Henegedara-kala",
    "wof:placetype":"locality"
},
  "geometry": {"coordinates":[80.27670000000001,7.5107],"type":"Point"}
}