{
  "type": "Feature",
  "properties": {
    "gn:admin1_code":"32.0",
    "gn:asciiname":"Beddegama",
    "gn:country_code":"LK",
    "gn:dem":95,
    "gn:feature_class":"P",
    "gn:feature_code":"PPL",
    "gn:name":"Beddegama",
    "gn:population":0,
    "gn:timezone":"Asia/Colombo",
    "iso:country":"LK",
    "name:sin_x_preferred":[
        "\u0db6\u0dd0\u0daf\u0dca\u0daf\u0dda\u0d9c\u0db8"
    ],
    "wof:name":"Beddegama",
    "wof:placetype":"locality"
},
  "geometry": {"coordinates":[80.3454,7.5927],"type":"Point"}
}