{
  "type": "Feature",
  "properties": {
    "gn:admin1_code":"32.0",
    "gn:asciiname":"Mugunuwatawana",
    "gn:country_code":"LK",
    "gn:dem":19,
    "gn:feature_class":"P",
    "gn:feature_code":"PPL",
    "gn:name":"Mugunuwatawana",
    "gn:population":0,
    "gn:timezone":"Asia/Colombo",
    "iso:country":"LK",
    "wof:name":"Mugunuwatawana",
    "wof:placetype":"locality"
},
  "geometry": {"coordinates":[79.855,7.5861],"type":"Point"}
}