{
  "type": "Feature",
  "properties": {
    "gn:admin1_code":"30.0",
    "gn:asciiname":"Kuda Rambewa",
    "gn:country_code":"LK",
    "gn:dem":177,
    "gn:feature_class":"P",
    "gn:feature_code":"PPL",
    "gn:name":"Kuda Rambewa",
    "gn:population":0,
    "gn:timezone":"Asia/Colombo",
    "iso:country":"LK",
    "wof:name":"Kuda Rambewa",
    "wof:placetype":"locality"
},
  "geometry": {"coordinates":[80.7247,8.0729],"type":"Point"}
}