{
  "type": "Feature",
  "properties": {
    "gn:admin1_code":"36.0",
    "gn:asciiname":"Walpita",
    "gn:country_code":"LK",
    "gn:dem":49,
    "gn:feature_class":"P",
    "gn:feature_code":"PPL",
    "gn:name":"Walpita",
    "gn:population":0,
    "gn:timezone":"Asia/Colombo",
    "iso:country":"LK",
    "wof:name":"Walpita",
    "wof:placetype":"locality"
},
  "geometry": {"coordinates":[80.0493,7.2601],"type":"Point"}
}