{
  "type": "Feature",
  "properties": {
    "gn:admin1_code":"32.0",
    "gn:asciiname":"Kanoyaya",
    "gn:country_code":"LK",
    "gn:dem":62,
    "gn:feature_class":"P",
    "gn:feature_code":"PPL",
    "gn:name":"Kanoyaya",
    "gn:population":0,
    "gn:timezone":"Asia/Colombo",
    "iso:country":"LK",
    "wof:name":"Kanoyaya",
    "wof:placetype":"locality"
},
  "geometry": {"coordinates":[80.1395,7.5139],"type":"Point"}
}