{
  "type": "Feature",
  "properties": {
    "gn:admin1_code":"38.0",
    "gn:asciiname":"Nanthavil",
    "gn:country_code":"LK",
    "gn:dem":10,
    "gn:feature_class":"P",
    "gn:feature_code":"PPL",
    "gn:name":"Nanthavil",
    "gn:population":0,
    "gn:timezone":"Asia/Colombo",
    "iso:country":"LK",
    "wof:name":"Nanthavil",
    "wof:placetype":"locality"
},
  "geometry": {"coordinates":[80.0164,9.7012],"type":"Point"}
}