{
  "type": "Feature",
  "properties": {
    "gn:admin1_code":"38.0",
    "gn:asciiname":"Silavatturai",
    "gn:country_code":"LK",
    "gn:dem":1,
    "gn:feature_class":"P",
    "gn:feature_code":"PPL",
    "gn:name":"Silavatturai",
    "gn:population":0,
    "gn:timezone":"Asia/Colombo",
    "iso:country":"LK",
    "name:und_x_variant":[
        "Silavaturai",
        "Silvatturai",
        "Silavatturai"
    ],
    "wof:name":"Silavatturai",
    "wof:placetype":"locality"
},
  "geometry": {"coordinates":[79.9478,8.7467],"type":"Point"}
}