{
  "type": "Feature",
  "properties": {
    "gn:admin1_code":"32.0",
    "gn:asciiname":"Pallugaturai",
    "gn:cc2":"LK",
    "gn:country_code":"LK",
    "gn:dem":-9999,
    "gn:feature_class":"P",
    "gn:feature_code":"PPL",
    "gn:name":"Pallugaturai",
    "gn:population":0,
    "gn:timezone":"Asia/Colombo",
    "iso:country":"LK",
    "name:und_x_variant":[
        "Palkaturai",
        "Pallugaturai"
    ],
    "wof:name":"Pallugaturai",
    "wof:placetype":"locality"
},
  "geometry": {"coordinates":[79.84999999999999,8.46667],"type":"Point"}
}