{
  "type": "Feature",
  "properties": {
    "gn:admin1_code":"36.0",
    "gn:asciiname":"Gamakkanda",
    "gn:country_code":"LK",
    "gn:dem":227,
    "gn:feature_class":"P",
    "gn:feature_code":"PPL",
    "gn:name":"Gamakkanda",
    "gn:population":0,
    "gn:timezone":"Asia/Colombo",
    "iso:country":"LK",
    "wof:name":"Gamakkanda",
    "wof:placetype":"locality"
},
  "geometry": {"coordinates":[80.26560000000001,6.3878],"type":"Point"}
}