{
  "type": "Feature",
  "properties": {
    "gn:admin1_code":"36.0",
    "gn:asciiname":"Dalugamgoda",
    "gn:country_code":"LK",
    "gn:dem":18,
    "gn:feature_class":"P",
    "gn:feature_code":"PPL",
    "gn:name":"Dalugamgoda",
    "gn:population":0,
    "gn:timezone":"Asia/Colombo",
    "iso:country":"LK",
    "name:und_x_variant":[
        "Dalugangoda"
    ],
    "wof:name":"Dalugamgoda",
    "wof:placetype":"locality"
},
  "geometry": {"coordinates":[79.9139,6.9741],"type":"Point"}
}