{
  "type": "Feature",
  "properties": {
    "gn:admin1_code":"32.0",
    "gn:asciiname":"Kumbukgahawewa",
    "gn:country_code":"LK",
    "gn:dem":109,
    "gn:feature_class":"P",
    "gn:feature_code":"PPL",
    "gn:name":"Kumbukgahawewa",
    "gn:population":0,
    "gn:timezone":"Asia/Colombo",
    "iso:country":"LK",
    "wof:name":"Kumbukgahawewa",
    "wof:placetype":"locality"
},
  "geometry": {"coordinates":[80.3263,7.9625],"type":"Point"}
}