{
  "type": "Feature",
  "properties": {
    "gn:admin1_code":"38.0",
    "gn:admin2_code":"1236148.0",
    "gn:asciiname":"Suriyatevarkaddaikkadu",
    "gn:country_code":"LK",
    "gn:dem":11,
    "gn:feature_class":"P",
    "gn:feature_code":"PPL",
    "gn:name":"Suriyatevarkaddaikkadu",
    "gn:population":0,
    "gn:timezone":"Asia/Colombo",
    "iso:country":"LK",
    "name:eng_x_preferred":[
        "Sooriyakaddaikaadu"
    ],
    "name:tam_x_preferred":[
        "\u0b9a\u0bc2\u0bb0\u0bbf\u0baf\u0b95\u0b9f\u0bcd\u0b9f\u0bc8\u0b95\u0bcd\u0b95\u0bbe\u0b9f\u0bc1"
    ],
    "wof:name":"Suriyatevarkaddaikkadu",
    "wof:placetype":"locality"
},
  "geometry": {"coordinates":[79.97944,8.85319],"type":"Point"}
}