{
  "type": "Feature",
  "properties": {
    "gn:admin1_code":"30.0",
    "gn:asciiname":"Padikaramaduwa",
    "gn:cc2":"LK",
    "gn:country_code":"LK",
    "gn:dem":127,
    "gn:feature_class":"P",
    "gn:feature_code":"PPL",
    "gn:name":"Padikaramaduwa",
    "gn:population":0,
    "gn:timezone":"Asia/Colombo",
    "iso:country":"LK",
    "name:und_x_variant":[
        "Padikkaramaduwa",
        "Padikaramaduwa"
    ],
    "wof:name":"Padikaramaduwa",
    "wof:placetype":"locality"
},
  "geometry": {"coordinates":[80.73333000000002,8.23333],"type":"Point"}
}