{
  "type": "Feature",
  "properties": {
    "gn:admin1_code":"32.0",
    "gn:asciiname":"Tammittigama",
    "gn:country_code":"LK",
    "gn:dem":94,
    "gn:feature_class":"P",
    "gn:feature_code":"PPL",
    "gn:name":"Tammittigama",
    "gn:population":0,
    "gn:timezone":"Asia/Colombo",
    "iso:country":"LK",
    "wof:name":"Tammittigama",
    "wof:placetype":"locality"
},
  "geometry": {"coordinates":[80.366,7.6238],"type":"Point"}
}