{
  "type": "Feature",
  "properties": {
    "gn:admin1_code":"32.0",
    "gn:asciiname":"Talangedara",
    "gn:country_code":"LK",
    "gn:dem":112,
    "gn:feature_class":"P",
    "gn:feature_code":"PPL",
    "gn:name":"Talangedara",
    "gn:population":0,
    "gn:timezone":"Asia/Colombo",
    "iso:country":"LK",
    "wof:name":"Talangedara",
    "wof:placetype":"locality"
},
  "geometry": {"coordinates":[80.30070000000001,7.5325],"type":"Point"}
}