{
  "type": "Feature",
  "properties": {
    "gn:admin1_code":"30.0",
    "gn:asciiname":"Acharigama",
    "gn:country_code":"LK",
    "gn:dem":92,
    "gn:feature_class":"P",
    "gn:feature_code":"PPL",
    "gn:name":"Acharigama",
    "gn:population":0,
    "gn:timezone":"Asia/Colombo",
    "iso:country":"LK",
    "wof:name":"Acharigama",
    "wof:placetype":"locality"
},
  "geometry": {"coordinates":[80.2343,8.2168],"type":"Point"}
}