{
  "type": "Feature",
  "properties": {
    "gn:admin1_code":"34.0",
    "gn:asciiname":"Kapugampota",
    "gn:country_code":"LK",
    "gn:dem":35,
    "gn:feature_class":"P",
    "gn:feature_code":"PPL",
    "gn:name":"Kapugampota",
    "gn:population":0,
    "gn:timezone":"Asia/Colombo",
    "iso:country":"LK",
    "wof:name":"Kapugampota",
    "wof:placetype":"locality"
},
  "geometry": {"coordinates":[80.7805,6.1518],"type":"Point"}
}