{
  "type": "Feature",
  "properties": {
    "gn:admin1_code":"32.0",
    "gn:asciiname":"Ihala Weliyawa",
    "gn:country_code":"LK",
    "gn:dem":93,
    "gn:feature_class":"P",
    "gn:feature_code":"PPL",
    "gn:name":"Ihala Weliyawa",
    "gn:population":0,
    "gn:timezone":"Asia/Colombo",
    "iso:country":"LK",
    "wof:name":"Ihala Weliyawa",
    "wof:placetype":"locality"
},
  "geometry": {"coordinates":[80.2574,8.1012],"type":"Point"}
}