{
  "type": "Feature",
  "properties": {
    "gn:admin1_code":"30.0",
    "gn:asciiname":"Miwamalewa",
    "gn:country_code":"LK",
    "gn:dem":105,
    "gn:feature_class":"P",
    "gn:feature_code":"PPL",
    "gn:name":"Miwamalewa",
    "gn:population":0,
    "gn:timezone":"Asia/Colombo",
    "iso:country":"LK",
    "wof:name":"Miwamalewa",
    "wof:placetype":"locality"
},
  "geometry": {"coordinates":[80.59780000000001,8.438],"type":"Point"}
}