{
  "type": "Feature",
  "properties": {
    "gn:admin1_code":"32.0",
    "gn:asciiname":"Gallallagama",
    "gn:country_code":"LK",
    "gn:dem":115,
    "gn:feature_class":"P",
    "gn:feature_code":"PPL",
    "gn:name":"Gallallagama",
    "gn:population":0,
    "gn:timezone":"Asia/Colombo",
    "iso:country":"LK",
    "wof:name":"Gallallagama",
    "wof:placetype":"locality"
},
  "geometry": {"coordinates":[80.32810000000001,7.9627],"type":"Point"}
}