{
  "type": "Feature",
  "properties": {
    "gn:admin1_code":"29.0",
    "gn:asciiname":"Loolkade",
    "gn:country_code":"LK",
    "gn:dem":198,
    "gn:feature_class":"P",
    "gn:feature_code":"PPL",
    "gn:name":"Loolkade",
    "gn:population":0,
    "gn:timezone":"Asia/Colombo",
    "iso:country":"LK",
    "wof:name":"Loolkade",
    "wof:placetype":"locality"
},
  "geometry": {"coordinates":[80.55670000000001,7.638],"type":"Point"}
}