{
  "type": "Feature",
  "properties": {
    "gn:admin1_code":"33.0",
    "gn:asciiname":"Halpawala",
    "gn:country_code":"LK",
    "gn:dem":232,
    "gn:feature_class":"P",
    "gn:feature_code":"PPL",
    "gn:name":"Halpawala",
    "gn:population":0,
    "gn:timezone":"Asia/Colombo",
    "iso:country":"LK",
    "wof:name":"Halpawala",
    "wof:placetype":"locality"
},
  "geometry": {"coordinates":[80.5314,6.5907],"type":"Point"}
}