{
  "type": "Feature",
  "properties": {
    "gn:admin1_code":"33.0",
    "gn:asciiname":"Paradeniya",
    "gn:country_code":"LK",
    "gn:dem":60,
    "gn:feature_class":"P",
    "gn:feature_code":"PPL",
    "gn:name":"Paradeniya",
    "gn:population":0,
    "gn:timezone":"Asia/Colombo",
    "iso:country":"LK",
    "wof:name":"Paradeniya",
    "wof:placetype":"locality"
},
  "geometry": {"coordinates":[80.27030000000001,7.0987],"type":"Point"}
}