{
  "type": "Feature",
  "properties": {
    "gn:admin1_code":"35.0",
    "gn:asciiname":"Yatigoragalla",
    "gn:country_code":"LK",
    "gn:dem":413,
    "gn:feature_class":"P",
    "gn:feature_code":"PPL",
    "gn:name":"Yatigoragalla",
    "gn:population":0,
    "gn:timezone":"Asia/Colombo",
    "iso:country":"LK",
    "wof:name":"Yatigoragalla",
    "wof:placetype":"locality"
},
  "geometry": {"coordinates":[81.0278,7.0812],"type":"Point"}
}