{
  "type": "Feature",
  "properties": {
    "gn:admin1_code":"36.0",
    "gn:asciiname":"Lihiniyawa",
    "gn:country_code":"LK",
    "gn:dem":61,
    "gn:feature_class":"P",
    "gn:feature_code":"PPL",
    "gn:name":"Lihiniyawa",
    "gn:population":0,
    "gn:timezone":"Asia/Colombo",
    "iso:country":"LK",
    "name:und_x_variant":[
        "Liniyawa"
    ],
    "wof:name":"Lihiniyawa",
    "wof:placetype":"locality"
},
  "geometry": {"coordinates":[80.16930000000001,6.455],"type":"Point"}
}