{
  "type": "Feature",
  "properties": {
    "gn:admin1_code":"32.0",
    "gn:asciiname":"Hangawatta",
    "gn:country_code":"LK",
    "gn:dem":138,
    "gn:feature_class":"P",
    "gn:feature_code":"PPL",
    "gn:name":"Hangawatta",
    "gn:population":0,
    "gn:timezone":"Asia/Colombo",
    "iso:country":"LK",
    "wof:name":"Hangawatta",
    "wof:placetype":"locality"
},
  "geometry": {"coordinates":[80.2612,7.3471],"type":"Point"}
}