{
  "type": "Feature",
  "properties": {
    "gn:admin1_code":"35.0",
    "gn:asciiname":"Pallewella",
    "gn:country_code":"LK",
    "gn:dem":119,
    "gn:feature_class":"P",
    "gn:feature_code":"PPL",
    "gn:name":"Pallewella",
    "gn:population":0,
    "gn:timezone":"Asia/Colombo",
    "iso:country":"LK",
    "name:und_x_variant":[
        "Pallewela"
    ],
    "wof:name":"Pallewella",
    "wof:placetype":"locality"
},
  "geometry": {"coordinates":[81.5354,7.0258],"type":"Point"}
}