{
  "type": "Feature",
  "properties": {
    "gn:admin1_code":"32.0",
    "gn:asciiname":"Medagamagedara",
    "gn:country_code":"LK",
    "gn:dem":114,
    "gn:feature_class":"P",
    "gn:feature_code":"PPL",
    "gn:name":"Medagamagedara",
    "gn:population":0,
    "gn:timezone":"Asia/Colombo",
    "iso:country":"LK",
    "wof:name":"Medagamagedara",
    "wof:placetype":"locality"
},
  "geometry": {"coordinates":[80.2921,7.4266],"type":"Point"}
}