{
  "type": "Feature",
  "properties": {
    "gn:admin1_code":"32.0",
    "gn:asciiname":"Dambaliyadda",
    "gn:country_code":"LK",
    "gn:dem":79,
    "gn:feature_class":"P",
    "gn:feature_code":"PPL",
    "gn:name":"Dambaliyadda",
    "gn:population":0,
    "gn:timezone":"Asia/Colombo",
    "iso:country":"LK",
    "wof:name":"Dambaliyadda",
    "wof:placetype":"locality"
},
  "geometry": {"coordinates":[80.23560000000001,7.5761],"type":"Point"}
}