{
  "type": "Feature",
  "properties": {
    "gn:admin1_code":"34.0",
    "gn:asciiname":"Amunugammulla",
    "gn:country_code":"LK",
    "gn:dem":135,
    "gn:feature_class":"P",
    "gn:feature_code":"PPL",
    "gn:name":"Amunugammulla",
    "gn:population":0,
    "gn:timezone":"Asia/Colombo",
    "iso:country":"LK",
    "wof:name":"Amunugammulla",
    "wof:placetype":"locality"
},
  "geometry": {"coordinates":[80.5587,6.268],"type":"Point"}
}