{
  "type": "Feature",
  "properties": {
    "gn:admin1_code":"34.0",
    "gn:asciiname":"Yaddehigoda",
    "gn:country_code":"LK",
    "gn:dem":117,
    "gn:feature_class":"P",
    "gn:feature_code":"PPL",
    "gn:name":"Yaddehigoda",
    "gn:population":0,
    "gn:timezone":"Asia/Colombo",
    "iso:country":"LK",
    "wof:name":"Yaddehigoda",
    "wof:placetype":"locality"
},
  "geometry": {"coordinates":[80.6477,6.2205],"type":"Point"}
}