{
  "type": "Feature",
  "properties": {
    "gn:admin1_code":"33.0",
    "gn:asciiname":"Paranatala",
    "gn:country_code":"LK",
    "gn:dem":155,
    "gn:feature_class":"P",
    "gn:feature_code":"PPL",
    "gn:name":"Paranatala",
    "gn:population":0,
    "gn:timezone":"Asia/Colombo",
    "iso:country":"LK",
    "wof:name":"Paranatala",
    "wof:placetype":"locality"
},
  "geometry": {"coordinates":[80.1679,7.1477],"type":"Point"}
}