{
  "type": "Feature",
  "properties": {
    "gn:admin1_code":"32.0",
    "gn:asciiname":"Horakele",
    "gn:country_code":"LK",
    "gn:dem":16,
    "gn:feature_class":"P",
    "gn:feature_code":"PPL",
    "gn:name":"Horakele",
    "gn:population":0,
    "gn:timezone":"Asia/Colombo",
    "iso:country":"LK",
    "wof:name":"Horakele",
    "wof:placetype":"locality"
},
  "geometry": {"coordinates":[79.84999999999999,7.45],"type":"Point"}
}