{
  "type": "Feature",
  "properties": {
    "gn:admin1_code":"33.0",
    "gn:asciiname":"Udadadayamkanda",
    "gn:country_code":"LK",
    "gn:dem":383,
    "gn:feature_class":"P",
    "gn:feature_code":"PPL",
    "gn:name":"Udadadayamkanda",
    "gn:population":0,
    "gn:timezone":"Asia/Colombo",
    "iso:country":"LK",
    "name:und_x_variant":[
        "Uda Dadayankanda",
        "Dadayankanda",
        "Udadadayamkanda"
    ],
    "wof:name":"Udadadayamkanda",
    "wof:placetype":"locality"
},
  "geometry": {"coordinates":[80.6773,6.3157],"type":"Point"}
}