{
  "type": "Feature",
  "properties": {
    "gn:admin1_code":"29.0",
    "gn:asciiname":"Hepana",
    "gn:country_code":"LK",
    "gn:dem":568,
    "gn:feature_class":"P",
    "gn:feature_code":"PPL",
    "gn:name":"Hepana",
    "gn:population":0,
    "gn:timezone":"Asia/Colombo",
    "iso:country":"LK",
    "wof:name":"Hepana",
    "wof:placetype":"locality"
},
  "geometry": {"coordinates":[80.5534,7.2393],"type":"Point"}
}