{
  "type": "Feature",
  "properties": {
    "gn:admin1_code":"32.0",
    "gn:asciiname":"Kokkawilagama",
    "gn:country_code":"LK",
    "gn:dem":70,
    "gn:feature_class":"P",
    "gn:feature_code":"PPL",
    "gn:name":"Kokkawilagama",
    "gn:population":0,
    "gn:timezone":"Asia/Colombo",
    "iso:country":"LK",
    "name:und_x_variant":[
        "Kokkavilagama",
        "Kokkawilagama"
    ],
    "wof:name":"Kokkawilagama",
    "wof:placetype":"locality"
},
  "geometry": {"coordinates":[80.1528,7.6704],"type":"Point"}
}