{
  "type": "Feature",
  "properties": {
    "gn:admin1_code":"35.0",
    "gn:asciiname":"Kirigalagama",
    "gn:country_code":"LK",
    "gn:dem":990,
    "gn:feature_class":"P",
    "gn:feature_code":"PPL",
    "gn:name":"Kirigalagama",
    "gn:population":0,
    "gn:timezone":"Asia/Colombo",
    "iso:country":"LK",
    "wof:name":"Kirigalagama",
    "wof:placetype":"locality"
},
  "geometry": {"coordinates":[81.1707,6.9743],"type":"Point"}
}