{
  "type": "Feature",
  "properties": {
    "gn:admin1_code":"37.0",
    "gn:asciiname":"Tirukkalkudah",
    "gn:country_code":"LK",
    "gn:dem":5,
    "gn:feature_class":"P",
    "gn:feature_code":"PPL",
    "gn:name":"Tirukkalkudah",
    "gn:population":0,
    "gn:timezone":"Asia/Colombo",
    "iso:country":"LK",
    "name:und_x_variant":[
        "Tirakkaikuda",
        "Thirukkaikuda",
        "Tirukkaikuda"
    ],
    "wof:name":"Tirukkalkudah",
    "wof:placetype":"locality"
},
  "geometry": {"coordinates":[81.18969,8.54172],"type":"Point"}
}