{
  "type": "Feature",
  "properties": {
    "gn:admin1_code":"33.0",
    "gn:asciiname":"Galapallewatta",
    "gn:country_code":"LK",
    "gn:dem":301,
    "gn:feature_class":"P",
    "gn:feature_code":"PPL",
    "gn:name":"Galapallewatta",
    "gn:population":0,
    "gn:timezone":"Asia/Colombo",
    "iso:country":"LK",
    "wof:name":"Galapallewatta",
    "wof:placetype":"locality"
},
  "geometry": {"coordinates":[80.3917,7.0184],"type":"Point"}
}