{
  "type": "Feature",
  "properties": {
    "gn:admin1_code":"34.0",
    "gn:asciiname":"Manangoda",
    "gn:country_code":"LK",
    "gn:dem":15,
    "gn:feature_class":"P",
    "gn:feature_code":"PPL",
    "gn:name":"Manangoda",
    "gn:population":0,
    "gn:timezone":"Asia/Colombo",
    "iso:country":"LK",
    "wof:name":"Manangoda",
    "wof:placetype":"locality"
},
  "geometry": {"coordinates":[80.1103,6.2191],"type":"Point"}
}