{
  "type": "Feature",
  "properties": {
    "gn:admin1_code":"34.0",
    "gn:asciiname":"Kotagedaragoda",
    "gn:country_code":"LK",
    "gn:dem":37,
    "gn:feature_class":"P",
    "gn:feature_code":"PPL",
    "gn:name":"Kotagedaragoda",
    "gn:population":0,
    "gn:timezone":"Asia/Colombo",
    "iso:country":"LK",
    "name:und_x_variant":[
        "Totagedaragoda"
    ],
    "wof:name":"Kotagedaragoda",
    "wof:placetype":"locality"
},
  "geometry": {"coordinates":[80.40130000000001,6.0167],"type":"Point"}
}