{
  "type": "Feature",
  "properties": {
    "gn:admin1_code":"33.0",
    "gn:asciiname":"Aswedduma",
    "gn:country_code":"LK",
    "gn:dem":555,
    "gn:feature_class":"P",
    "gn:feature_code":"PPL",
    "gn:name":"Aswedduma",
    "gn:population":0,
    "gn:timezone":"Asia/Colombo",
    "iso:country":"LK",
    "wof:name":"Aswedduma",
    "wof:placetype":"locality"
},
  "geometry": {"coordinates":[80.6814,6.6707],"type":"Point"}
}