{
  "type": "Feature",
  "properties": {
    "gn:admin1_code":"34.0",
    "gn:asciiname":"Welihena",
    "gn:country_code":"LK",
    "gn:dem":73,
    "gn:feature_class":"P",
    "gn:feature_code":"PPL",
    "gn:name":"Welihena",
    "gn:population":0,
    "gn:timezone":"Asia/Colombo",
    "iso:country":"LK",
    "wof:name":"Welihena",
    "wof:placetype":"locality"
},
  "geometry": {"coordinates":[80.4948,6.1486],"type":"Point"}
}