{
  "type": "Feature",
  "properties": {
    "gn:admin1_code":"30.0",
    "gn:asciiname":"Kurulupottegala",
    "gn:country_code":"LK",
    "gn:dem":83,
    "gn:feature_class":"P",
    "gn:feature_code":"PPL",
    "gn:name":"Kurulupottegala",
    "gn:population":0,
    "gn:timezone":"Asia/Colombo",
    "iso:country":"LK",
    "wof:name":"Kurulupottegala",
    "wof:placetype":"locality"
},
  "geometry": {"coordinates":[80.2397,8.21],"type":"Point"}
}