{
  "type": "Feature",
  "properties": {
    "gn:admin1_code":"32.0",
    "gn:asciiname":"Henwalagama",
    "gn:country_code":"LK",
    "gn:dem":105,
    "gn:feature_class":"P",
    "gn:feature_code":"PPL",
    "gn:name":"Henwalagama",
    "gn:population":0,
    "gn:timezone":"Asia/Colombo",
    "iso:country":"LK",
    "wof:name":"Henwalagama",
    "wof:placetype":"locality"
},
  "geometry": {"coordinates":[80.31667,8.01667],"type":"Point"}
}