{
  "type": "Feature",
  "properties": {
    "gn:admin1_code":"35.0",
    "gn:asciiname":"Wilaatigoda",
    "gn:country_code":"LK",
    "gn:dem":247,
    "gn:feature_class":"P",
    "gn:feature_code":"PPL",
    "gn:name":"Wilaatigoda",
    "gn:population":0,
    "gn:timezone":"Asia/Colombo",
    "iso:country":"LK",
    "name:und_x_variant":[
        "Wiletigoda",
        "Wilaatigoda"
    ],
    "wof:name":"Wilaatigoda",
    "wof:placetype":"locality"
},
  "geometry": {"coordinates":[81.27379999999999,7.1787],"type":"Point"}
}