{
  "type": "Feature",
  "properties": {
    "gn:admin1_code":"30.0",
    "gn:asciiname":"Kokkichchiya",
    "gn:country_code":"LK",
    "gn:dem":82,
    "gn:feature_class":"P",
    "gn:feature_code":"PPL",
    "gn:name":"Kokkichchiya",
    "gn:population":0,
    "gn:timezone":"Asia/Colombo",
    "iso:country":"LK",
    "wof:name":"Kokkichchiya",
    "wof:placetype":"locality"
},
  "geometry": {"coordinates":[80.3231,8.3778],"type":"Point"}
}