{
  "type": "Feature",
  "properties": {
    "gn:admin1_code":"32.0",
    "gn:asciiname":"Waduwawa",
    "gn:country_code":"LK",
    "gn:dem":95,
    "gn:feature_class":"P",
    "gn:feature_code":"PPL",
    "gn:name":"Waduwawa",
    "gn:population":0,
    "gn:timezone":"Asia/Colombo",
    "iso:country":"LK",
    "wof:name":"Waduwawa",
    "wof:placetype":"locality"
},
  "geometry": {"coordinates":[80.40000000000001,7.68333],"type":"Point"}
}