{
  "type": "Feature",
  "properties": {
    "gn:admin1_code":"29.0",
    "gn:asciiname":"Wiyanamulla",
    "gn:country_code":"LK",
    "gn:dem":498,
    "gn:feature_class":"P",
    "gn:feature_code":"PPL",
    "gn:name":"Wiyanamulla",
    "gn:population":0,
    "gn:timezone":"Asia/Colombo",
    "iso:country":"LK",
    "wof:name":"Wiyanamulla",
    "wof:placetype":"locality"
},
  "geometry": {"coordinates":[80.6558,7.3405],"type":"Point"}
}