{
  "type": "Feature",
  "properties": {
    "gn:admin1_code":"32.0",
    "gn:asciiname":"Kirindawa",
    "gn:country_code":"LK",
    "gn:dem":58,
    "gn:feature_class":"P",
    "gn:feature_code":"PPL",
    "gn:name":"Kirindawa",
    "gn:population":0,
    "gn:timezone":"Asia/Colombo",
    "iso:country":"LK",
    "wof:name":"Kirindawa",
    "wof:placetype":"locality"
},
  "geometry": {"coordinates":[80.0977,7.4982],"type":"Point"}
}