{
  "type": "Feature",
  "properties": {
    "gn:admin1_code":"33.0",
    "gn:asciiname":"Elamalpe",
    "gn:country_code":"LK",
    "gn:dem":355,
    "gn:feature_class":"P",
    "gn:feature_code":"PPL",
    "gn:name":"Elamalpe",
    "gn:population":0,
    "gn:timezone":"Asia/Colombo",
    "iso:country":"LK",
    "wof:name":"Elamalpe",
    "wof:placetype":"locality"
},
  "geometry": {"coordinates":[80.66840000000001,6.5296],"type":"Point"}
}