{
  "type": "Feature",
  "properties": {
    "gn:admin1_code":"35.0",
    "gn:asciiname":"Bulathwatta",
    "gn:country_code":"LK",
    "gn:dem":167,
    "gn:feature_class":"P",
    "gn:feature_code":"PPL",
    "gn:name":"Bulathwatta",
    "gn:population":0,
    "gn:timezone":"Asia/Colombo",
    "iso:country":"LK",
    "wof:name":"Bulathwatta",
    "wof:placetype":"locality"
},
  "geometry": {"coordinates":[81.3436,6.927],"type":"Point"}
}