{
  "type": "Feature",
  "properties": {
    "gn:country":"LK",
    "gn:fcode":"PPLX",
    "gn:population":0,
    "iso:country":"LK",
    "qs_pg:aaroncc":"LK",
    "qs_pg:gn_country":"LK",
    "qs_pg:gn_fcode":"PPLX",
    "qs_pg:gn_pop":0,
    "qs_pg:name":"Wellawatta",
    "qs_pg:name_adm0":"Sri Lanka",
    "qs_pg:name_adm1":"Western",
    "qs_pg:photos":817,
    "qs_pg:photos_1k":166,
    "qs_pg:photos_9k":4,
    "qs_pg:photos_9r":6,
    "qs_pg:photos_all":817,
    "qs_pg:photos_sr":9,
    "qs_pg:pop_sr":0,
    "qs_pg:qs_pg_placetype":"neighbourhood",
    "qs_pg:qs_pg_placetype_gp":"Suburb",
    "qs_pg:woe_adm0":23424778,
    "woe:adm0_id":23424778,
    "woe:name_adm0":"Sri Lanka",
    "woe:name_adm1":"Western",
    "woe:placetype":"Suburb",
    "wof:name":"Wellawatta",
    "wof:placetype":"neighbourhood"
},
  "geometry": {"coordinates":[80.0986,6.1447],"type":"Point"}
}