{
  "type": "Feature",
  "properties": {
    "gn:admin1_code":"32.0",
    "gn:asciiname":"Ennorugama",
    "gn:cc2":"LK",
    "gn:country_code":"LK",
    "gn:dem":45,
    "gn:feature_class":"P",
    "gn:feature_code":"PPL",
    "gn:name":"Ennorugama",
    "gn:population":0,
    "gn:timezone":"Asia/Colombo",
    "iso:country":"LK",
    "name:und_x_variant":[
        "Annarugama",
        "Ennorugama"
    ],
    "wof:name":"Ennorugama",
    "wof:placetype":"locality"
},
  "geometry": {"coordinates":[80.09999999999999,7.76667],"type":"Point"}
}