{
  "type": "Feature",
  "properties": {
    "gn:admin1_code":"33.0",
    "gn:asciiname":"Kottayakanda",
    "gn:country_code":"LK",
    "gn:dem":1037,
    "gn:feature_class":"P",
    "gn:feature_code":"PPL",
    "gn:name":"Kottayakanda",
    "gn:population":0,
    "gn:timezone":"Asia/Colombo",
    "iso:country":"LK",
    "wof:name":"Kottayakanda",
    "wof:placetype":"locality"
},
  "geometry": {"coordinates":[80.718,6.7259],"type":"Point"}
}