{
  "type": "Feature",
  "properties": {
    "gn:admin1_code":"29.0",
    "gn:asciiname":"Karalliyadda Kandegammedda",
    "gn:country_code":"LK",
    "gn:dem":478,
    "gn:feature_class":"P",
    "gn:feature_code":"PPL",
    "gn:name":"Karalliyadda Kandegammedda",
    "gn:population":0,
    "gn:timezone":"Asia/Colombo",
    "iso:country":"LK",
    "name:und_x_variant":[
        "Karalliyada Kandegammedda",
        "Karalliyadda Kandegammedda"
    ],
    "wof:name":"Karalliyadda Kandegammedda",
    "wof:placetype":"locality"
},
  "geometry": {"coordinates":[80.75749999999999,7.3151],"type":"Point"}
}