{
  "type": "Feature",
  "properties": {
    "gn:admin1_code":"37.0",
    "gn:asciiname":"Aiyankerni",
    "gn:country_code":"LK",
    "gn:dem":8,
    "gn:feature_class":"P",
    "gn:feature_code":"PPL",
    "gn:name":"Aiyankerni",
    "gn:population":0,
    "gn:timezone":"Asia/Colombo",
    "iso:country":"LK",
    "name:und_x_variant":[
        "Aiyakerni",
        "Aiyankerni"
    ],
    "wof:name":"Aiyankerni",
    "wof:placetype":"locality"
},
  "geometry": {"coordinates":[81.6125,7.788],"type":"Point"}
}