{
  "type": "Feature",
  "properties": {
    "gn:admin1_code":"32.0",
    "gn:asciiname":"Metiyanpota Sinhalagama",
    "gn:country_code":"LK",
    "gn:dem":150,
    "gn:feature_class":"P",
    "gn:feature_code":"PPL",
    "gn:name":"Metiyanpota Sinhalagama",
    "gn:population":0,
    "gn:timezone":"Asia/Colombo",
    "iso:country":"LK",
    "wof:name":"Metiyanpota Sinhalagama",
    "wof:placetype":"locality"
},
  "geometry": {"coordinates":[80.4748,7.4657],"type":"Point"}
}