{
  "type": "Feature",
  "properties": {
    "gn:admin1_code":"34.0",
    "gn:asciiname":"Pahudale",
    "gn:country_code":"LK",
    "gn:dem":17,
    "gn:feature_class":"P",
    "gn:feature_code":"PPL",
    "gn:name":"Pahudale",
    "gn:population":0,
    "gn:timezone":"Asia/Colombo",
    "iso:country":"LK",
    "wof:name":"Pahudale",
    "wof:placetype":"locality"
},
  "geometry": {"coordinates":[80.2547,6.3259],"type":"Point"}
}