{
  "type": "Feature",
  "properties": {
    "gn:admin1_code":"30.0",
    "gn:asciiname":"Egodagama",
    "gn:country_code":"LK",
    "gn:dem":99,
    "gn:feature_class":"P",
    "gn:feature_code":"PPL",
    "gn:name":"Egodagama",
    "gn:population":0,
    "gn:timezone":"Asia/Colombo",
    "iso:country":"LK",
    "wof:name":"Egodagama",
    "wof:placetype":"locality"
},
  "geometry": {"coordinates":[80.3853,8.2887],"type":"Point"}
}