{
  "type": "Feature",
  "properties": {
    "gn:admin1_code":"29.0",
    "gn:asciiname":"Ambethenna",
    "gn:country_code":"LK",
    "gn:dem":1178,
    "gn:feature_class":"P",
    "gn:feature_code":"PPL",
    "gn:name":"Ambethenna",
    "gn:population":0,
    "gn:timezone":"Asia/Colombo",
    "iso:country":"LK",
    "wof:name":"Ambethenna",
    "wof:placetype":"locality"
},
  "geometry": {"coordinates":[80.7856,7.0641],"type":"Point"}
}