{
  "type": "Feature",
  "properties": {
    "gn:admin1_code":"30.0",
    "gn:asciiname":"Kongaswewa",
    "gn:country_code":"LK",
    "gn:dem":95,
    "gn:feature_class":"P",
    "gn:feature_code":"PPL",
    "gn:name":"Kongaswewa",
    "gn:population":0,
    "gn:timezone":"Asia/Colombo",
    "iso:country":"LK",
    "wof:name":"Kongaswewa",
    "wof:placetype":"locality"
},
  "geometry": {"coordinates":[80.53749999999999,8.4559],"type":"Point"}
}