{
  "type": "Feature",
  "properties": {
    "gn:admin1_code":"33.0",
    "gn:asciiname":"Dodantale",
    "gn:country_code":"LK",
    "gn:dem":268,
    "gn:feature_class":"P",
    "gn:feature_code":"PPL",
    "gn:name":"Dodantale",
    "gn:population":0,
    "gn:timezone":"Asia/Colombo",
    "iso:country":"LK",
    "wof:name":"Dodantale",
    "wof:placetype":"locality"
},
  "geometry": {"coordinates":[80.4335,7.2328],"type":"Point"}
}