{
  "type": "Feature",
  "properties": {
    "gn:admin1_code":"29.0",
    "gn:asciiname":"Buwelikada",
    "gn:country_code":"LK",
    "gn:dem":471,
    "gn:feature_class":"P",
    "gn:feature_code":"PPL",
    "gn:name":"Buwelikada",
    "gn:population":0,
    "gn:timezone":"Asia/Colombo",
    "iso:country":"LK",
    "wof:name":"Buwelikada",
    "wof:placetype":"locality"
},
  "geometry": {"coordinates":[80.6521,7.2956],"type":"Point"}
}