{
  "type": "Feature",
  "properties": {
    "gn:admin1_code":"36.0",
    "gn:asciiname":"Korosduwa",
    "gn:country_code":"LK",
    "gn:dem":3,
    "gn:feature_class":"P",
    "gn:feature_code":"PPL",
    "gn:name":"Korosduwa",
    "gn:population":0,
    "gn:timezone":"Asia/Colombo",
    "iso:country":"LK",
    "name:und_x_variant":[
        "Koboduwa"
    ],
    "wof:name":"Korosduwa",
    "wof:placetype":"locality"
},
  "geometry": {"coordinates":[79.9545,6.6221],"type":"Point"}
}