{
  "type": "Feature",
  "properties": {
    "gn:admin1_code":"36.0",
    "gn:asciiname":"Tempola",
    "gn:country_code":"LK",
    "gn:dem":4,
    "gn:feature_class":"P",
    "gn:feature_code":"PPL",
    "gn:name":"Tempola",
    "gn:population":0,
    "gn:timezone":"Asia/Colombo",
    "iso:country":"LK",
    "wof:name":"Tempola",
    "wof:placetype":"locality"
},
  "geometry": {"coordinates":[79.88679999999999,7.151],"type":"Point"}
}