{
  "type": "Feature",
  "properties": {
    "gn:admin1_code":"32.0",
    "gn:asciiname":"Othegama",
    "gn:country_code":"LK",
    "gn:dem":12,
    "gn:feature_class":"P",
    "gn:feature_code":"PPL",
    "gn:name":"Othegama",
    "gn:population":0,
    "gn:timezone":"Asia/Colombo",
    "iso:country":"LK",
    "wof:name":"Othegama",
    "wof:placetype":"locality"
},
  "geometry": {"coordinates":[79.93859999999999,7.5005],"type":"Point"}
}