{
  "type": "Feature",
  "properties": {
    "gn:admin1_code":"32.0",
    "gn:asciiname":"Hiralugama",
    "gn:country_code":"LK",
    "gn:dem":136,
    "gn:feature_class":"P",
    "gn:feature_code":"PPL",
    "gn:name":"Hiralugama",
    "gn:population":0,
    "gn:timezone":"Asia/Colombo",
    "iso:country":"LK",
    "wof:name":"Hiralugama",
    "wof:placetype":"locality"
},
  "geometry": {"coordinates":[80.41667,8.01667],"type":"Point"}
}