{
  "type": "Feature",
  "properties": {
    "gn:admin1_code":"33.0",
    "gn:asciiname":"Rikillapana",
    "gn:country_code":"LK",
    "gn:dem":166,
    "gn:feature_class":"P",
    "gn:feature_code":"PPL",
    "gn:name":"Rikillapana",
    "gn:population":0,
    "gn:timezone":"Asia/Colombo",
    "iso:country":"LK",
    "wof:name":"Rikillapana",
    "wof:placetype":"locality"
},
  "geometry": {"coordinates":[80.7427,6.2889],"type":"Point"}
}