{
  "type": "Feature",
  "properties": {
    "gn:admin1_code":"32.0",
    "gn:asciiname":"Nithogama",
    "gn:country_code":"LK",
    "gn:dem":117,
    "gn:feature_class":"P",
    "gn:feature_code":"PPL",
    "gn:name":"Nithogama",
    "gn:population":0,
    "gn:timezone":"Asia/Colombo",
    "iso:country":"LK",
    "name:und_x_variant":[
        "Nitogama",
        "Nithogama"
    ],
    "wof:name":"Nithogama",
    "wof:placetype":"locality"
},
  "geometry": {"coordinates":[80.3473,7.9648],"type":"Point"}
}