{
  "type": "Feature",
  "properties": {
    "gn:admin1_code":"30.0",
    "gn:asciiname":"Endaragala",
    "gn:cc2":"LK",
    "gn:country_code":"LK",
    "gn:dem":174,
    "gn:feature_class":"P",
    "gn:feature_code":"PPL",
    "gn:name":"Endaragala",
    "gn:population":0,
    "gn:timezone":"Asia/Colombo",
    "iso:country":"LK",
    "name:und_x_variant":[
        "Enderagala",
        "Endaragala"
    ],
    "wof:name":"Endaragala",
    "wof:placetype":"locality"
},
  "geometry": {"coordinates":[80.51666999999998,7.86667],"type":"Point"}
}