{
  "type": "Feature",
  "properties": {
    "gn:admin1_code":"34.0",
    "gn:asciiname":"Rammalekanda Colony",
    "gn:country_code":"LK",
    "gn:dem":281,
    "gn:feature_class":"P",
    "gn:feature_code":"PPL",
    "gn:name":"Rammalekanda Colony",
    "gn:population":0,
    "gn:timezone":"Asia/Colombo",
    "iso:country":"LK",
    "wof:name":"Rammalekanda Colony",
    "wof:placetype":"locality"
},
  "geometry": {"coordinates":[80.64530000000001,6.2403],"type":"Point"}
}