{
  "type": "Feature",
  "properties": {
    "gn:admin1_code":"29.0",
    "gn:asciiname":"Kumburegama",
    "gn:country_code":"LK",
    "gn:dem":525,
    "gn:feature_class":"P",
    "gn:feature_code":"PPL",
    "gn:name":"Kumburegama",
    "gn:population":0,
    "gn:timezone":"Asia/Colombo",
    "iso:country":"LK",
    "wof:name":"Kumburegama",
    "wof:placetype":"locality"
},
  "geometry": {"coordinates":[80.5493,7.358],"type":"Point"}
}