{
  "type": "Feature",
  "properties": {
    "gn:admin1_code":"35.0",
    "gn:asciiname":"Karawilla",
    "gn:country_code":"LK",
    "gn:dem":58,
    "gn:feature_class":"P",
    "gn:feature_code":"PPL",
    "gn:name":"Karawilla",
    "gn:population":0,
    "gn:timezone":"Asia/Colombo",
    "iso:country":"LK",
    "wof:name":"Karawilla",
    "wof:placetype":"locality"
},
  "geometry": {"coordinates":[81.2873,6.4369],"type":"Point"}
}