{
  "type": "Feature",
  "properties": {
    "gn:admin1_code":"29.0",
    "gn:asciiname":"Kadadekawewa",
    "gn:country_code":"LK",
    "gn:dem":198,
    "gn:feature_class":"P",
    "gn:feature_code":"PPL",
    "gn:name":"Kadadekawewa",
    "gn:population":0,
    "gn:timezone":"Asia/Colombo",
    "iso:country":"LK",
    "wof:name":"Kadadekawewa",
    "wof:placetype":"locality"
},
  "geometry": {"coordinates":[80.58333,7.83333],"type":"Point"}
}