{
  "type": "Feature",
  "properties": {
    "gn:admin1_code":"37.0",
    "gn:asciiname":"Ilakkantai",
    "gn:country_code":"LK",
    "gn:dem":7,
    "gn:feature_class":"P",
    "gn:feature_code":"PPL",
    "gn:name":"Ilakkantai",
    "gn:population":0,
    "gn:timezone":"Asia/Colombo",
    "iso:country":"LK",
    "name:und_x_variant":[
        "Ilakanta",
        "Ilakanthai",
        "Ilakkantai"
    ],
    "wof:name":"Ilakkantai",
    "wof:placetype":"locality"
},
  "geometry": {"coordinates":[81.34999999999999,8.48333],"type":"Point"}
}