{
  "type": "Feature",
  "properties": {
    "gn:admin1_code":"29.0",
    "gn:asciiname":"Inigala",
    "gn:country_code":"LK",
    "gn:dem":479,
    "gn:feature_class":"P",
    "gn:feature_code":"PPL",
    "gn:name":"Inigala",
    "gn:population":0,
    "gn:timezone":"Asia/Colombo",
    "iso:country":"LK",
    "name:ceb_x_preferred":[
        "Inigala"
    ],
    "name:swe_x_preferred":[
        "Inigala"
    ],
    "wof:name":"Inigala",
    "wof:placetype":"locality"
},
  "geometry": {"coordinates":[80.61667,7.31667],"type":"Point"}
}