{
  "type": "Feature",
  "properties": {
    "gn:admin1_code":"34.0",
    "gn:asciiname":"Amuhena",
    "gn:country_code":"LK",
    "gn:dem":134,
    "gn:feature_class":"P",
    "gn:feature_code":"PPL",
    "gn:name":"Amuhena",
    "gn:population":0,
    "gn:timezone":"Asia/Colombo",
    "iso:country":"LK",
    "wof:name":"Amuhena",
    "wof:placetype":"locality"
},
  "geometry": {"coordinates":[80.3385,6.3567],"type":"Point"}
}