{
  "type": "Feature",
  "properties": {
    "gn:admin1_code":"30.0",
    "gn:asciiname":"Amunewewa",
    "gn:country_code":"LK",
    "gn:dem":116,
    "gn:feature_class":"P",
    "gn:feature_code":"PPL",
    "gn:name":"Amunewewa",
    "gn:population":0,
    "gn:timezone":"Asia/Colombo",
    "iso:country":"LK",
    "wof:name":"Amunewewa",
    "wof:placetype":"locality"
},
  "geometry": {"coordinates":[80.7183,8.4128],"type":"Point"}
}