{
  "type": "Feature",
  "properties": {
    "gn:admin1_code":"38.0",
    "gn:asciiname":"Uvari",
    "gn:country_code":"LK",
    "gn:dem":8,
    "gn:feature_class":"P",
    "gn:feature_code":"PPL",
    "gn:name":"Uvari",
    "gn:population":0,
    "gn:timezone":"Asia/Colombo",
    "iso:country":"LK",
    "wof:name":"Uvari",
    "wof:placetype":"locality"
},
  "geometry": {"coordinates":[79.83333,9.05],"type":"Point"}
}