{
  "type": "Feature",
  "properties": {
    "gn:admin1_code":"29.0",
    "gn:asciiname":"Halangoda",
    "gn:country_code":"LK",
    "gn:dem":382,
    "gn:feature_class":"P",
    "gn:feature_code":"PPL",
    "gn:name":"Halangoda",
    "gn:population":0,
    "gn:timezone":"Asia/Colombo",
    "iso:country":"LK",
    "wof:name":"Halangoda",
    "wof:placetype":"locality"
},
  "geometry": {"coordinates":[80.6093,7.4366],"type":"Point"}
}