{
  "type": "Feature",
  "properties": {
    "gn:admin1_code":"32.0",
    "gn:asciiname":"Delikanuwewa",
    "gn:country_code":"LK",
    "gn:dem":105,
    "gn:feature_class":"P",
    "gn:feature_code":"PPL",
    "gn:name":"Delikanuwewa",
    "gn:population":0,
    "gn:timezone":"Asia/Colombo",
    "iso:country":"LK",
    "name:und_x_variant":[
        "Delikanuwawa"
    ],
    "wof:name":"Delikanuwewa",
    "wof:placetype":"locality"
},
  "geometry": {"coordinates":[80.37439999999999,7.5734],"type":"Point"}
}