{
  "type": "Feature",
  "properties": {
    "gn:admin1_code":"35.0",
    "gn:asciiname":"Panwewakanda",
    "gn:country_code":"LK",
    "gn:dem":1009,
    "gn:feature_class":"P",
    "gn:feature_code":"PPL",
    "gn:name":"Panwewakanda",
    "gn:population":0,
    "gn:timezone":"Asia/Colombo",
    "iso:country":"LK",
    "wof:name":"Panwewakanda",
    "wof:placetype":"locality"
},
  "geometry": {"coordinates":[80.9333,7.0379],"type":"Point"}
}