{
  "type": "Feature",
  "properties": {
    "gn:admin1_code":"33.0",
    "gn:asciiname":"Diwulwatta",
    "gn:country_code":"LK",
    "gn:dem":750,
    "gn:feature_class":"P",
    "gn:feature_code":"PPL",
    "gn:name":"Diwulwatta",
    "gn:population":0,
    "gn:timezone":"Asia/Colombo",
    "iso:country":"LK",
    "wof:name":"Diwulwatta",
    "wof:placetype":"locality"
},
  "geometry": {"coordinates":[80.7235,6.7179],"type":"Point"}
}