{
  "type": "Feature",
  "properties": {
    "gn:admin1_code":"35.0",
    "gn:asciiname":"Pitiyegedara",
    "gn:country_code":"LK",
    "gn:dem":560,
    "gn:feature_class":"P",
    "gn:feature_code":"PPL",
    "gn:name":"Pitiyegedara",
    "gn:population":0,
    "gn:timezone":"Asia/Colombo",
    "iso:country":"LK",
    "wof:name":"Pitiyegedara",
    "wof:placetype":"locality"
},
  "geometry": {"coordinates":[81.13500000000001,7.0147],"type":"Point"}
}