{
  "type": "Feature",
  "properties": {
    "gn:admin1_code":"36.0",
    "gn:asciiname":"Pinwala",
    "gn:country_code":"LK",
    "gn:dem":5,
    "gn:feature_class":"P",
    "gn:feature_code":"PPL",
    "gn:name":"Pinwala",
    "gn:population":0,
    "gn:timezone":"Asia/Colombo",
    "iso:country":"LK",
    "wof:name":"Pinwala",
    "wof:placetype":"locality"
},
  "geometry": {"coordinates":[79.9241,6.7155],"type":"Point"}
}