{
  "type": "Feature",
  "properties": {
    "gn:admin1_code":"30.0",
    "gn:asciiname":"Kolongaswewa",
    "gn:country_code":"LK",
    "gn:dem":134,
    "gn:feature_class":"P",
    "gn:feature_code":"PPL",
    "gn:name":"Kolongaswewa",
    "gn:population":0,
    "gn:timezone":"Asia/Colombo",
    "iso:country":"LK",
    "wof:name":"Kolongaswewa",
    "wof:placetype":"locality"
},
  "geometry": {"coordinates":[80.63333,8.26667],"type":"Point"}
}