{
  "type": "Feature",
  "properties": {
    "gn:admin1_code":"35.0",
    "gn:asciiname":"Anda Ulpota",
    "gn:cc2":"LK",
    "gn:country_code":"LK",
    "gn:dem":127,
    "gn:feature_class":"P",
    "gn:feature_code":"PPL",
    "gn:name":"Anda Ulpota",
    "gn:population":0,
    "gn:timezone":"Asia/Colombo",
    "iso:country":"LK",
    "name:und_x_variant":[
        "Andaulpotagama",
        "Anda Ulpota"
    ],
    "wof:name":"Anda Ulpota",
    "wof:placetype":"locality"
},
  "geometry": {"coordinates":[81.06667,7.26667],"type":"Point"}
}