{
  "type": "Feature",
  "properties": {
    "gn:admin1_code":"36.0",
    "gn:asciiname":"Atulugama Sinhalese",
    "gn:country_code":"LK",
    "gn:dem":8,
    "gn:feature_class":"P",
    "gn:feature_code":"PPL",
    "gn:name":"Atulugama Sinhalese",
    "gn:population":0,
    "gn:timezone":"Asia/Colombo",
    "iso:country":"LK",
    "wof:name":"Atulugama Sinhalese",
    "wof:placetype":"locality"
},
  "geometry": {"coordinates":[79.9911,6.6967],"type":"Point"}
}