{
  "type": "Feature",
  "properties": {
    "gn:admin1_code":"36.0",
    "gn:asciiname":"Magura",
    "gn:country_code":"LK",
    "gn:dem":79,
    "gn:feature_class":"P",
    "gn:feature_code":"PPL",
    "gn:name":"Magura",
    "gn:population":0,
    "gn:timezone":"Asia/Colombo",
    "iso:country":"LK",
    "name:ceb_x_preferred":[
        "Magura"
    ],
    "name:ces_x_preferred":[
        "Magura"
    ],
    "name:deu_x_preferred":[
        "Magura"
    ],
    "name:epo_x_preferred":[
        "Magura"
    ],
    "name:nld_x_preferred":[
        "Magura"
    ],
    "name:pol_x_preferred":[
        "Magura"
    ],
    "name:ron_x_preferred":[
        "Magura"
    ],
    "name:rus_x_preferred":[
        "\u041c\u0430\u0433\u0443\u0440\u0430"
    ],
    "name:slk_x_preferred":[
        "Magura"
    ],
    "name:srp_x_preferred":[
        "\u041c\u0430\u0433\u0443\u0440\u0430"
    ],
    "name:swe_x_preferred":[
        "Magura"
    ],
    "name:ukr_x_preferred":[
        "\u041c\u0430\u0491\u0443\u0440\u0430"
    ],
    "wof:name":"Magura",
    "wof:placetype":"locality"
},
  "geometry": {"coordinates":[80.23439999999999,6.4943],"type":"Point"}
}