{
  "type": "Feature",
  "properties": {
    "gn:admin1_code":"36.0",
    "gn:asciiname":"Kudagonaduwa",
    "gn:country_code":"LK",
    "gn:dem":15,
    "gn:feature_class":"P",
    "gn:feature_code":"PPL",
    "gn:name":"Kudagonaduwa",
    "gn:population":0,
    "gn:timezone":"Asia/Colombo",
    "iso:country":"LK",
    "wof:name":"Kudagonaduwa",
    "wof:placetype":"locality"
},
  "geometry": {"coordinates":[79.9721,6.6728],"type":"Point"}
}