{
  "type": "Feature",
  "properties": {
    "gn:admin1_code":"29.0",
    "gn:asciiname":"Rankiriyagolla",
    "gn:country_code":"LK",
    "gn:dem":790,
    "gn:feature_class":"P",
    "gn:feature_code":"PPL",
    "gn:name":"Rankiriyagolla",
    "gn:population":0,
    "gn:timezone":"Asia/Colombo",
    "iso:country":"LK",
    "wof:name":"Rankiriyagolla",
    "wof:placetype":"locality"
},
  "geometry": {"coordinates":[80.93333,7.26667],"type":"Point"}
}