{
  "type": "Feature",
  "properties": {
    "gn:admin1_code":"36.0",
    "gn:asciiname":"Kondurawa",
    "gn:country_code":"LK",
    "gn:dem":15,
    "gn:feature_class":"P",
    "gn:feature_code":"PPL",
    "gn:name":"Kondurawa",
    "gn:population":0,
    "gn:timezone":"Asia/Colombo",
    "iso:country":"LK",
    "name:und_x_variant":[
        "Konduruwawa"
    ],
    "wof:name":"Kondurawa",
    "wof:placetype":"locality"
},
  "geometry": {"coordinates":[79.94710000000001,6.7896],"type":"Point"}
}