{
  "type": "Feature",
  "properties": {
    "gn:admin1_code":"32.0",
    "gn:asciiname":"Bawilgomuwa",
    "gn:country_code":"LK",
    "gn:dem":123,
    "gn:feature_class":"P",
    "gn:feature_code":"PPL",
    "gn:name":"Bawilgomuwa",
    "gn:population":0,
    "gn:timezone":"Asia/Colombo",
    "iso:country":"LK",
    "name:und_x_variant":[
        "Bevilgomuwa",
        "Bewilgamuwa"
    ],
    "wof:name":"Bawilgomuwa",
    "wof:placetype":"locality"
},
  "geometry": {"coordinates":[80.32559999999999,7.3986],"type":"Point"}
}