{
  "type": "Feature",
  "properties": {
    "gn:admin1_code":"35.0",
    "gn:asciiname":"Ganwasangoda",
    "gn:country_code":"LK",
    "gn:dem":760,
    "gn:feature_class":"P",
    "gn:feature_code":"PPL",
    "gn:name":"Ganwasangoda",
    "gn:population":0,
    "gn:timezone":"Asia/Colombo",
    "iso:country":"LK",
    "wof:name":"Ganwasangoda",
    "wof:placetype":"locality"
},
  "geometry": {"coordinates":[80.8511,6.7651],"type":"Point"}
}