{
  "type": "Feature",
  "properties": {
    "gn:admin1_code":"35.0",
    "gn:asciiname":"Sirimalgoda",
    "gn:country_code":"LK",
    "gn:dem":1004,
    "gn:feature_class":"P",
    "gn:feature_code":"PPL",
    "gn:name":"Sirimalgoda",
    "gn:population":0,
    "gn:timezone":"Asia/Colombo",
    "iso:country":"LK",
    "wof:name":"Sirimalgoda",
    "wof:placetype":"locality"
},
  "geometry": {"coordinates":[81.0829,7.0031],"type":"Point"}
}