{
  "type": "Feature",
  "properties": {
    "gn:admin1_code":"32.0",
    "gn:asciiname":"Kahahena",
    "gn:country_code":"LK",
    "gn:dem":287,
    "gn:feature_class":"P",
    "gn:feature_code":"PPL",
    "gn:name":"Kahahena",
    "gn:population":0,
    "gn:timezone":"Asia/Colombo",
    "iso:country":"LK",
    "wof:name":"Kahahena",
    "wof:placetype":"locality"
},
  "geometry": {"coordinates":[80.55710000000001,7.5208],"type":"Point"}
}