{
  "type": "Feature",
  "properties": {
    "gn:admin1_code":"33.0",
    "gn:asciiname":"Ihalakotte",
    "gn:country_code":"LK",
    "gn:dem":226,
    "gn:feature_class":"P",
    "gn:feature_code":"PPL",
    "gn:name":"Ihalakotte",
    "gn:population":0,
    "gn:timezone":"Asia/Colombo",
    "iso:country":"LK",
    "wof:name":"Ihalakotte",
    "wof:placetype":"locality"
},
  "geometry": {"coordinates":[80.4662,7.288],"type":"Point"}
}