{
  "type": "Feature",
  "properties": {
    "gn:admin1_code":"30.0",
    "gn:asciiname":"Nugagahadamana",
    "gn:country_code":"LK",
    "gn:dem":67,
    "gn:feature_class":"P",
    "gn:feature_code":"PPL",
    "gn:name":"Nugagahadamana",
    "gn:population":0,
    "gn:timezone":"Asia/Colombo",
    "iso:country":"LK",
    "wof:name":"Nugagahadamana",
    "wof:placetype":"locality"
},
  "geometry": {"coordinates":[80.95,8.01667],"type":"Point"}
}