{
  "type": "Feature",
  "properties": {
    "gn:admin1_code":"32.0",
    "gn:asciiname":"Kayirakgama",
    "gn:country_code":"LK",
    "gn:dem":89,
    "gn:feature_class":"P",
    "gn:feature_code":"PPL",
    "gn:name":"Kayirakgama",
    "gn:population":0,
    "gn:timezone":"Asia/Colombo",
    "iso:country":"LK",
    "wof:name":"Kayirakgama",
    "wof:placetype":"locality"
},
  "geometry": {"coordinates":[80.2449,7.87068],"type":"Point"}
}