{
  "type": "Feature",
  "properties": {
    "gn:admin1_code":"35.0",
    "gn:asciiname":"Amunumulle",
    "gn:country_code":"LK",
    "gn:dem":1233,
    "gn:feature_class":"P",
    "gn:feature_code":"PPL",
    "gn:name":"Amunumulle",
    "gn:population":0,
    "gn:timezone":"Asia/Colombo",
    "iso:country":"LK",
    "name:und_x_variant":[
        "Amunumulla"
    ],
    "wof:name":"Amunumulle",
    "wof:placetype":"locality"
},
  "geometry": {"coordinates":[80.9084,6.8664],"type":"Point"}
}