{
  "type": "Feature",
  "properties": {
    "gn:admin1_code":"32.0",
    "gn:asciiname":"Arankele",
    "gn:country_code":"LK",
    "gn:dem":118,
    "gn:feature_class":"P",
    "gn:feature_code":"PPL",
    "gn:name":"Arankele",
    "gn:population":0,
    "gn:timezone":"Asia/Colombo",
    "iso:country":"LK",
    "wof:name":"Arankele",
    "wof:placetype":"locality"
},
  "geometry": {"coordinates":[80.4135,7.6464],"type":"Point"}
}