{
  "type": "Feature",
  "properties": {
    "gn:admin1_code":"32.0",
    "gn:asciiname":"Agare",
    "gn:country_code":"LK",
    "gn:dem":49,
    "gn:feature_class":"P",
    "gn:feature_code":"PPL",
    "gn:name":"Agare",
    "gn:population":0,
    "gn:timezone":"Asia/Colombo",
    "iso:country":"LK",
    "wof:name":"Agare",
    "wof:placetype":"locality"
},
  "geometry": {"coordinates":[80.0185,7.6837],"type":"Point"}
}