{
  "type": "Feature",
  "properties": {
    "gn:admin1_code":"36.0",
    "gn:asciiname":"Guruwala",
    "gn:country_code":"LK",
    "gn:dem":25,
    "gn:feature_class":"P",
    "gn:feature_code":"PPL",
    "gn:name":"Guruwala",
    "gn:population":0,
    "gn:timezone":"Asia/Colombo",
    "iso:country":"LK",
    "name:und_x_variant":[
        "Guruwela",
        "Guruwala"
    ],
    "wof:name":"Guruwala",
    "wof:placetype":"locality"
},
  "geometry": {"coordinates":[80.06950000000001,6.9457],"type":"Point"}
}