{
  "type": "Feature",
  "properties": {
    "gn:admin1_code":"30.0",
    "gn:asciiname":"Deketipotana",
    "gn:country_code":"LK",
    "gn:dem":107,
    "gn:feature_class":"P",
    "gn:feature_code":"PPL",
    "gn:name":"Deketipotana",
    "gn:population":0,
    "gn:timezone":"Asia/Colombo",
    "iso:country":"LK",
    "wof:name":"Deketipotana",
    "wof:placetype":"locality"
},
  "geometry": {"coordinates":[80.7998,8.4049],"type":"Point"}
}