{
  "type": "Feature",
  "properties": {
    "gn:admin1_code":"35.0",
    "gn:asciiname":"Inawellagama",
    "gn:country_code":"LK",
    "gn:dem":119,
    "gn:feature_class":"P",
    "gn:feature_code":"PPL",
    "gn:name":"Inawellagama",
    "gn:population":0,
    "gn:timezone":"Asia/Colombo",
    "iso:country":"LK",
    "wof:name":"Inawellagama",
    "wof:placetype":"locality"
},
  "geometry": {"coordinates":[81.434,6.9168],"type":"Point"}
}