{
  "type": "Feature",
  "properties": {
    "gn:admin1_code":"32.0",
    "gn:asciiname":"Pugallegama",
    "gn:cc2":"LK",
    "gn:country_code":"LK",
    "gn:dem":119,
    "gn:feature_class":"P",
    "gn:feature_code":"PPL",
    "gn:name":"Pugallegama",
    "gn:population":0,
    "gn:timezone":"Asia/Colombo",
    "iso:country":"LK",
    "name:und_x_variant":[
        "Pugallagama",
        "Pugallegama"
    ],
    "wof:name":"Pugallegama",
    "wof:placetype":"locality"
},
  "geometry": {"coordinates":[80.40000000000001,7.78333],"type":"Point"}
}