{
  "type": "Feature",
  "properties": {
    "gn:admin1_code":"29.0",
    "gn:asciiname":"Kolenagama",
    "gn:country_code":"LK",
    "gn:dem":290,
    "gn:feature_class":"P",
    "gn:feature_code":"PPL",
    "gn:name":"Kolenagama",
    "gn:population":0,
    "gn:timezone":"Asia/Colombo",
    "iso:country":"LK",
    "wof:name":"Kolenagama",
    "wof:placetype":"locality"
},
  "geometry": {"coordinates":[80.4693,6.9439],"type":"Point"}
}