{
  "type": "Feature",
  "properties": {
    "gn:admin1_code":"34.0",
    "gn:asciiname":"Palamgoda",
    "gn:country_code":"LK",
    "gn:dem":7,
    "gn:feature_class":"P",
    "gn:feature_code":"PPL",
    "gn:name":"Palamgoda",
    "gn:population":0,
    "gn:timezone":"Asia/Colombo",
    "iso:country":"LK",
    "wof:name":"Palamgoda",
    "wof:placetype":"locality"
},
  "geometry": {"coordinates":[80.14100000000001,6.1075],"type":"Point"}
}