{
  "type": "Feature",
  "properties": {
    "gn:admin1_code":"35.0",
    "gn:asciiname":"Ambamulla",
    "gn:country_code":"LK",
    "gn:dem":72,
    "gn:feature_class":"P",
    "gn:feature_code":"PPL",
    "gn:name":"Ambamulla",
    "gn:population":0,
    "gn:timezone":"Asia/Colombo",
    "iso:country":"LK",
    "wof:name":"Ambamulla",
    "wof:placetype":"locality"
},
  "geometry": {"coordinates":[81.5202,6.8195],"type":"Point"}
}