{
  "type": "Feature",
  "properties": {
    "gn:admin1_code":"35.0",
    "gn:asciiname":"Dikwellegama",
    "gn:country_code":"LK",
    "gn:dem":878,
    "gn:feature_class":"P",
    "gn:feature_code":"PPL",
    "gn:name":"Dikwellegama",
    "gn:population":0,
    "gn:timezone":"Asia/Colombo",
    "iso:country":"LK",
    "name:und_x_variant":[
        "Dikwellagama"
    ],
    "wof:name":"Dikwellegama",
    "wof:placetype":"locality"
},
  "geometry": {"coordinates":[81.0279,6.9717],"type":"Point"}
}