{
  "type": "Feature",
  "properties": {
    "gn:admin1_code":"32.0",
    "gn:asciiname":"Kutharappuwa",
    "gn:country_code":"LK",
    "gn:dem":26,
    "gn:feature_class":"P",
    "gn:feature_code":"PPL",
    "gn:name":"Kutharappuwa",
    "gn:population":0,
    "gn:timezone":"Asia/Colombo",
    "iso:country":"LK",
    "name:und_x_variant":[
        "Kutaruppuwa"
    ],
    "wof:name":"Kutharappuwa",
    "wof:placetype":"locality"
},
  "geometry": {"coordinates":[79.9589,7.4372],"type":"Point"}
}