{
  "type": "Feature",
  "properties": {
    "gn:admin1_code":"33.0",
    "gn:asciiname":"Nedungomuwa",
    "gn:country_code":"LK",
    "gn:dem":477,
    "gn:feature_class":"P",
    "gn:feature_code":"PPL",
    "gn:name":"Nedungomuwa",
    "gn:population":0,
    "gn:timezone":"Asia/Colombo",
    "iso:country":"LK",
    "name:und_x_variant":[
        "Nedungamuwa",
        "Nedungomuwa"
    ],
    "wof:name":"Nedungomuwa",
    "wof:placetype":"locality"
},
  "geometry": {"coordinates":[80.7927,6.605],"type":"Point"}
}