{
  "type": "Feature",
  "properties": {
    "gn:admin1_code":"36.0",
    "gn:asciiname":"Akarangaha",
    "gn:country_code":"LK",
    "gn:dem":33,
    "gn:feature_class":"P",
    "gn:feature_code":"PPL",
    "gn:name":"Akarangaha",
    "gn:population":0,
    "gn:timezone":"Asia/Colombo",
    "iso:country":"LK",
    "wof:name":"Akarangaha",
    "wof:placetype":"locality"
},
  "geometry": {"coordinates":[79.9905,7.2781],"type":"Point"}
}