{
  "type": "Feature",
  "properties": {
    "gn:admin1_code":"34.0",
    "gn:asciiname":"Puswelkada",
    "gn:country_code":"LK",
    "gn:dem":76,
    "gn:feature_class":"P",
    "gn:feature_code":"PPL",
    "gn:name":"Puswelkada",
    "gn:population":0,
    "gn:timezone":"Asia/Colombo",
    "iso:country":"LK",
    "wof:name":"Puswelkada",
    "wof:placetype":"locality"
},
  "geometry": {"coordinates":[80.345,6.0441],"type":"Point"}
}