{
  "type": "Feature",
  "properties": {
    "gn:admin1_code":"35.0",
    "gn:asciiname":"Kadegangoda",
    "gn:country_code":"LK",
    "gn:dem":146,
    "gn:feature_class":"P",
    "gn:feature_code":"PPL",
    "gn:name":"Kadegangoda",
    "gn:population":0,
    "gn:timezone":"Asia/Colombo",
    "iso:country":"LK",
    "name:und_x_variant":[
        "Kadigangoda"
    ],
    "wof:name":"Kadegangoda",
    "wof:placetype":"locality"
},
  "geometry": {"coordinates":[81.4509,6.8919],"type":"Point"}
}