{
  "type": "Feature",
  "properties": {
    "gn:admin1_code":"30.0",
    "gn:asciiname":"Ulpothagama",
    "gn:country_code":"LK",
    "gn:dem":156,
    "gn:feature_class":"P",
    "gn:feature_code":"PPL",
    "gn:name":"Ulpothagama",
    "gn:population":0,
    "gn:timezone":"Asia/Colombo",
    "iso:country":"LK",
    "name:und_x_variant":[
        "Ulpotagama"
    ],
    "wof:name":"Ulpothagama",
    "wof:placetype":"locality"
},
  "geometry": {"coordinates":[80.565,7.9234],"type":"Point"}
}