{
  "type": "Feature",
  "properties": {
    "gn:admin1_code":"35.0",
    "gn:asciiname":"Dematagolla",
    "gn:country_code":"LK",
    "gn:dem":133,
    "gn:feature_class":"P",
    "gn:feature_code":"PPL",
    "gn:name":"Dematagolla",
    "gn:population":0,
    "gn:timezone":"Asia/Colombo",
    "iso:country":"LK",
    "name:und_x_variant":[
        "Dawatagolla",
        "Dematagolla",
        "Dewatagolla"
    ],
    "wof:name":"Dematagolla",
    "wof:placetype":"locality"
},
  "geometry": {"coordinates":[81.0625,7.1879],"type":"Point"}
}