{
  "type": "Feature",
  "properties": {
    "gn:admin1_code":"35.0",
    "gn:asciiname":"Deliwa",
    "gn:country_code":"LK",
    "gn:dem":153,
    "gn:feature_class":"P",
    "gn:feature_code":"PPL",
    "gn:name":"Deliwa",
    "gn:population":0,
    "gn:timezone":"Asia/Colombo",
    "iso:country":"LK",
    "wof:name":"Deliwa",
    "wof:placetype":"locality"
},
  "geometry": {"coordinates":[81.3905,7.0369],"type":"Point"}
}