{
  "type": "Feature",
  "properties": {
    "gn:admin1_code":"29.0",
    "gn:asciiname":"Thunmansala",
    "gn:country_code":"LK",
    "gn:dem":391,
    "gn:feature_class":"P",
    "gn:feature_code":"PPL",
    "gn:name":"Thunmansala",
    "gn:population":0,
    "gn:timezone":"Asia/Colombo",
    "iso:country":"LK",
    "wof:name":"Thunmansala",
    "wof:placetype":"locality"
},
  "geometry": {"coordinates":[80.94750000000001,7.1085],"type":"Point"}
}