{
  "type": "Feature",
  "properties": {
    "gn:admin1_code":"29.0",
    "gn:asciiname":"Kobbekaduwa",
    "gn:country_code":"LK",
    "gn:dem":603,
    "gn:feature_class":"P",
    "gn:feature_code":"PPL",
    "gn:name":"Kobbekaduwa",
    "gn:population":0,
    "gn:timezone":"Asia/Colombo",
    "iso:country":"LK",
    "wof:name":"Kobbekaduwa",
    "wof:placetype":"locality"
},
  "geometry": {"coordinates":[80.5624,7.4502],"type":"Point"}
}