{
  "type": "Feature",
  "properties": {
    "gn:admin1_code":"32.0",
    "gn:asciiname":"Kanatolawa Kuppayama",
    "gn:cc2":"LK",
    "gn:country_code":"LK",
    "gn:dem":41,
    "gn:feature_class":"P",
    "gn:feature_code":"PPL",
    "gn:name":"Kanatolawa Kuppayama",
    "gn:population":0,
    "gn:timezone":"Asia/Colombo",
    "iso:country":"LK",
    "name:und_x_variant":[
        "Kanatolawa",
        "Kanatolawa Kuppayama"
    ],
    "wof:name":"Kanatolawa Kuppayama",
    "wof:placetype":"locality"
},
  "geometry": {"coordinates":[80.03333000000001,7.58333],"type":"Point"}
}