{
  "type": "Feature",
  "properties": {
    "iso:country":"LK",
    "name:cat_x_preferred":[
        "Hanwella"
    ],
    "name:eng_x_preferred":[
        "Hanwella"
    ],
    "name:nld_x_preferred":[
        "Hanwella"
    ],
    "name:sin_x_preferred":[
        "\u0dc4\u0d82\u0dc0\u0dd0\u0dbd\u0dca\u0dbd"
    ],
    "name:tam_x_preferred":[
        "\u0bb9\u0ba9\u0bcd\u0bb5\u0bc6\u0bb2\u0bcd\u0bb2\u0bc8"
    ],
    "qs:gn_country":"LK",
    "qs:gn_fcode":"PPL",
    "qs:gn_pop":0,
    "qs:name":"Hanwella",
    "qs:name_adm0":"Sri Lanka",
    "qs:name_adm1":"Western",
    "qs:photos":5,
    "qs:photos_1k":1,
    "qs:photos_9k":1,
    "qs:photos_9r":1,
    "qs:photos_all":5,
    "qs:photos_sr":1,
    "qs:placetype":"Town",
    "qs:pop_sr":"0",
    "qs:woe_adm0":23424778,
    "wd:wordcount":517,
    "wof:name":"Hanwella",
    "wof:placetype":"locality"
},
  "geometry": {"coordinates":[80.0796,6.9086],"type":"Point"}
}