{
  "type": "Feature",
  "properties": {
    "gn:admin1_code":"34.0",
    "gn:asciiname":"Manawila",
    "gn:country_code":"LK",
    "gn:dem":27,
    "gn:feature_class":"P",
    "gn:feature_code":"PPL",
    "gn:name":"Manawila",
    "gn:population":0,
    "gn:timezone":"Asia/Colombo",
    "iso:country":"LK",
    "wof:name":"Manawila",
    "wof:placetype":"locality"
},
  "geometry": {"coordinates":[80.25620000000001,6.0631],"type":"Point"}
}