{
  "type": "Feature",
  "properties": {
    "gn:admin1_code":"34.0",
    "gn:asciiname":"Watukolakanda",
    "gn:cc2":"LK",
    "gn:country_code":"LK",
    "gn:dem":62,
    "gn:feature_class":"P",
    "gn:feature_code":"PPL",
    "gn:name":"Watukolakanda",
    "gn:population":0,
    "gn:timezone":"Asia/Colombo",
    "iso:country":"LK",
    "name:und_x_variant":[
        "Watukolekanda",
        "Watukolakanda"
    ],
    "wof:name":"Watukolakanda",
    "wof:placetype":"locality"
},
  "geometry": {"coordinates":[80.61667,6.03333],"type":"Point"}
}