{
  "type": "Feature",
  "properties": {
    "gn:admin1_code":"33.0",
    "gn:asciiname":"Lenagala Pahala",
    "gn:country_code":"LK",
    "gn:dem":144,
    "gn:feature_class":"P",
    "gn:feature_code":"PPL",
    "gn:name":"Lenagala Pahala",
    "gn:population":0,
    "gn:timezone":"Asia/Colombo",
    "iso:country":"LK",
    "wof:name":"Lenagala Pahala",
    "wof:placetype":"locality"
},
  "geometry": {"coordinates":[80.2654,7.1104],"type":"Point"}
}