{
  "type": "Feature",
  "properties": {
    "iso:country":"LK",
    "name:eng_x_preferred":[
        "Walpola"
    ],
    "name:nld_x_preferred":[
        "Walpola"
    ],
    "qs:gn_country":"LK",
    "qs:gn_fcode":"PPLX",
    "qs:gn_pop":0,
    "qs:name":"Walpola",
    "qs:name_adm0":"Sri Lanka",
    "qs:name_adm1":"Southern",
    "qs:photos":1,
    "qs:photos_1k":1,
    "qs:photos_9k":1,
    "qs:photos_9r":1,
    "qs:photos_all":1,
    "qs:photos_sr":1,
    "qs:placetype":"Suburb",
    "qs:pop_sr":"0",
    "qs:woe_adm0":23424778,
    "wd:wordcount":28,
    "wof:name":"Walpola",
    "wof:placetype":"neighbourhood"
},
  "geometry": {"coordinates":[80.55,5.95],"type":"Point"}
}