{
  "type": "Feature",
  "properties": {
    "gn:admin1_code":"34.0",
    "gn:asciiname":"Dangedara",
    "gn:country_code":"LK",
    "gn:dem":27,
    "gn:feature_class":"P",
    "gn:feature_code":"PPL",
    "gn:name":"Dangedara",
    "gn:population":0,
    "gn:timezone":"Asia/Colombo",
    "iso:country":"LK",
    "wof:name":"Dangedara",
    "wof:placetype":"locality"
},
  "geometry": {"coordinates":[80.2111,6.0586],"type":"Point"}
}