{
  "type": "Feature",
  "properties": {
    "gn:admin1_code":"35.0",
    "gn:asciiname":"Galahitiyawa",
    "gn:country_code":"LK",
    "gn:dem":610,
    "gn:feature_class":"P",
    "gn:feature_code":"PPL",
    "gn:name":"Galahitiyawa",
    "gn:population":0,
    "gn:timezone":"Asia/Colombo",
    "iso:country":"LK",
    "name:ceb_x_preferred":[
        "Galahitiyawa"
    ],
    "name:swe_x_preferred":[
        "Galahitiyawa"
    ],
    "wof:name":"Galahitiyawa",
    "wof:placetype":"locality"
},
  "geometry": {"coordinates":[80.9522,7.0246],"type":"Point"}
}