{
  "type": "Feature",
  "properties": {
    "gn:admin1_code":"38.0",
    "gn:asciiname":"Vaddukkoddai West",
    "gn:country_code":"LK",
    "gn:dem":10,
    "gn:feature_class":"P",
    "gn:feature_code":"PPL",
    "gn:name":"Vaddukkoddai West",
    "gn:population":0,
    "gn:timezone":"Asia/Colombo",
    "iso:country":"LK",
    "name:ceb_x_preferred":[
        "Vaddukkoddai West"
    ],
    "name:swe_x_preferred":[
        "Vaddukkoddai West"
    ],
    "wof:name":"Vaddukkoddai West",
    "wof:placetype":"locality"
},
  "geometry": {"coordinates":[79.93819999999999,9.7281],"type":"Point"}
}