{
  "type": "Feature",
  "properties": {
    "gn:admin1_code":"34.0",
    "gn:asciiname":"Wenivarawela",
    "gn:country_code":"LK",
    "gn:dem":32,
    "gn:feature_class":"P",
    "gn:feature_code":"PPL",
    "gn:name":"Wenivarawela",
    "gn:population":0,
    "gn:timezone":"Asia/Colombo",
    "iso:country":"LK",
    "wof:name":"Wenivarawela",
    "wof:placetype":"locality"
},
  "geometry": {"coordinates":[80.1572,6.188],"type":"Point"}
}