{
  "type": "Feature",
  "properties": {
    "gn:admin1_code":"33.0",
    "gn:asciiname":"Kuttigala",
    "gn:country_code":"LK",
    "gn:dem":69,
    "gn:feature_class":"P",
    "gn:feature_code":"PPL",
    "gn:name":"Kuttigala",
    "gn:population":0,
    "gn:timezone":"Asia/Colombo",
    "iso:country":"LK",
    "wof:name":"Kuttigala",
    "wof:placetype":"locality"
},
  "geometry": {"coordinates":[80.90000000000001,6.25],"type":"Point"}
}