{
  "type": "Feature",
  "properties": {
    "gn:admin1_code":"32.0",
    "gn:asciiname":"Madurugamuwa",
    "gn:country_code":"LK",
    "gn:dem":21,
    "gn:feature_class":"P",
    "gn:feature_code":"PPL",
    "gn:name":"Madurugamuwa",
    "gn:population":0,
    "gn:timezone":"Asia/Colombo",
    "iso:country":"LK",
    "name:und_x_variant":[
        "Madurugomuwa"
    ],
    "wof:name":"Madurugamuwa",
    "wof:placetype":"locality"
},
  "geometry": {"coordinates":[79.96259999999999,7.327],"type":"Point"}
}