{
  "type": "Feature",
  "properties": {
    "gn:admin1_code":"29.0",
    "gn:asciiname":"Kumbiyangaha Ela",
    "gn:country_code":"LK",
    "gn:dem":263,
    "gn:feature_class":"P",
    "gn:feature_code":"PPL",
    "gn:name":"Kumbiyangaha Ela",
    "gn:population":0,
    "gn:timezone":"Asia/Colombo",
    "iso:country":"LK",
    "wof:name":"Kumbiyangaha Ela",
    "wof:placetype":"locality"
},
  "geometry": {"coordinates":[80.68980000000001,7.6746],"type":"Point"}
}