{
  "type": "Feature",
  "properties": {
    "gn:admin1_code":"35.0",
    "gn:asciiname":"Ambalama",
    "gn:country_code":"LK",
    "gn:dem":746,
    "gn:feature_class":"P",
    "gn:feature_code":"PPL",
    "gn:name":"Ambalama",
    "gn:population":0,
    "gn:timezone":"Asia/Colombo",
    "iso:country":"LK",
    "name:sin_x_preferred":[
        "\u0d85\u0db8\u0dca\u0db6\u0dbd\u0db8"
    ],
    "name:tam_x_preferred":[
        "\u0b85\u0bae\u0bcd\u0baa\u0bb2\u0bae"
    ],
    "wof:name":"Ambalama",
    "wof:placetype":"locality"
},
  "geometry": {"coordinates":[81.1476,7.0746],"type":"Point"}
}