{
  "type": "Feature",
  "properties": {
    "gn:admin1_code":"29.0",
    "gn:asciiname":"Thibbotugoda",
    "gn:country_code":"LK",
    "gn:dem":1055,
    "gn:feature_class":"P",
    "gn:feature_code":"PPL",
    "gn:name":"Thibbotugoda",
    "gn:population":0,
    "gn:timezone":"Asia/Colombo",
    "iso:country":"LK",
    "name:und_x_variant":[
        "Tibbotugoda"
    ],
    "wof:name":"Thibbotugoda",
    "wof:placetype":"locality"
},
  "geometry": {"coordinates":[80.8776,7.0817],"type":"Point"}
}