{
  "type": "Feature",
  "properties": {
    "gn:admin1_code":"34.0",
    "gn:asciiname":"Udukawa",
    "gn:country_code":"LK",
    "gn:dem":26,
    "gn:feature_class":"P",
    "gn:feature_code":"PPL",
    "gn:name":"Udukawa",
    "gn:population":0,
    "gn:timezone":"Asia/Colombo",
    "iso:country":"LK",
    "wof:name":"Udukawa",
    "wof:placetype":"locality"
},
  "geometry": {"coordinates":[80.48333000000002,6.01667],"type":"Point"}
}