{
  "type": "Feature",
  "properties": {
    "iso:country":"LK",
    "name:ara_x_preferred":[
        "\u0647\u0627\u062a\u0648\u0646"
    ],
    "name:ben_x_preferred":[
        "\u09b9\u09cd\u09af\u09be\u099f\u09a8"
    ],
    "name:ceb_x_preferred":[
        "Hatton"
    ],
    "name:dan_x_preferred":[
        "Hatton"
    ],
    "name:deu_x_preferred":[
        "Hatton"
    ],
    "name:ell_x_preferred":[
        "\u03a7\u03ac\u03c4\u03c4\u03bf\u03bd"
    ],
    "name:eng_x_preferred":[
        "Hatton"
    ],
    "name:fas_x_preferred":[
        "\u0647\u0627\u062a\u0648\u0646"
    ],
    "name:fin_x_preferred":[
        "Hatton"
    ],
    "name:fra_x_preferred":[
        "Hatton"
    ],
    "name:guj_x_preferred":[
        "\u0ab9\u0ac5\u0a9f\u0aa8"
    ],
    "name:hin_x_preferred":[
        "\u0939\u0948\u091f\u0928"
    ],
    "name:ind_x_preferred":[
        "Hatton"
    ],
    "name:ita_x_preferred":[
        "Hatton"
    ],
    "name:jpn_x_preferred":[
        "\u30cf\u30c3\u30c8\u30f3\u30fb\u30c7\u30a3\u30b3\u30e4"
    ],
    "name:kan_x_preferred":[
        "\u0cb9\u0ccd\u0caf\u0cbe\u0c9f\u0ca8\u0ccd"
    ],
    "name:kor_x_preferred":[
        "\ud574\ud2bc"
    ],
    "name:lav_x_preferred":[
        "Hatona"
    ],
    "name:lit_x_preferred":[
        "Hatonas"
    ],
    "name:mar_x_preferred":[
        "\u0939\u0945\u091f\u0928"
    ],
    "name:msa_x_preferred":[
        "Hatton"
    ],
    "name:nld_x_preferred":[
        "Hatton"
    ],
    "name:nob_x_preferred":[
        "Hatton"
    ],
    "name:pol_x_preferred":[
        "Hatton"
    ],
    "name:por_x_preferred":[
        "Hatton"
    ],
    "name:rus_x_preferred":[
        "\u0425\u0430\u0442\u0442\u043e\u043d"
    ],
    "name:sin_x_preferred":[
        "\u0dc4\u0dd0\u0da7\u0db1\u0dca"
    ],
    "name:spa_x_preferred":[
        "Hatton"
    ],
    "name:swe_x_preferred":[
        "Hatton"
    ],
    "name:tam_x_preferred":[
        "\u0b85\u0b9f\u0bcd\u0b9f\u0ba9\u0bcd"
    ],
    "name:tel_x_preferred":[
        "\u0c39\u0c1f\u0c4d\u0c1f\u0c4b\u0c28\u0c4d"
    ],
    "name:tha_x_preferred":[
        "\u0e41\u0e2e\u0e15\u0e15\u0e31\u0e19 \u0e28\u0e23\u0e35\u0e25\u0e31\u0e07\u0e01\u0e32"
    ],
    "name:tur_x_preferred":[
        "Hatton"
    ],
    "name:ukr_x_preferred":[
        "\u0425\u0430\u0442\u0442\u043e\u043d"
    ],
    "name:urd_x_preferred":[
        "\u06c1\u0627\u0679\u0648\u0646\u060c \u0633\u0631\u06cc \u0644\u0646\u06a9\u0627"
    ],
    "name:urd_x_variant":[
        "\u06c1\u0627\u0679\u0648\u0646"
    ],
    "name:vie_x_preferred":[
        "Hatton"
    ],
    "qs:gn_country":"LK",
    "qs:gn_fcode":"PPL",
    "qs:gn_pop":15073,
    "qs:name":"Hatton",
    "qs:name_adm0":"Sri Lanka",
    "qs:name_adm1":"Central",
    "qs:photos":157,
    "qs:photos_1k":32,
    "qs:photos_9k":1,
    "qs:photos_9r":4,
    "qs:photos_all":157,
    "qs:photos_sr":4,
    "qs:placetype":"Town",
    "qs:pop_sr":"6",
    "qs:woe_adm0":23424778,
    "wd:wordcount":234,
    "wof:name":"Hatton",
    "wof:placetype":"locality",
    "wof:population":15073
},
  "geometry": {"coordinates":[80.5955,6.8916],"type":"Point"}
}