{
  "type": "Feature",
  "properties": {
    "gn:admin1_code":"34.0",
    "gn:asciiname":"Medawadiyagoda",
    "gn:country_code":"LK",
    "gn:dem":380,
    "gn:feature_class":"P",
    "gn:feature_code":"PPL",
    "gn:name":"Medawadiyagoda",
    "gn:population":0,
    "gn:timezone":"Asia/Colombo",
    "iso:country":"LK",
    "wof:name":"Medawadiyagoda",
    "wof:placetype":"locality"
},
  "geometry": {"coordinates":[80.6195,6.2043],"type":"Point"}
}