{
  "type": "Feature",
  "properties": {
    "gn:admin1_code":"32.0",
    "gn:asciiname":"Wetakeyawa",
    "gn:country_code":"LK",
    "gn:dem":37,
    "gn:feature_class":"P",
    "gn:feature_code":"PPL",
    "gn:name":"Wetakeyawa",
    "gn:population":0,
    "gn:timezone":"Asia/Colombo",
    "iso:country":"LK",
    "name:und_x_variant":[
        "Wetakeiyawa"
    ],
    "wof:name":"Wetakeyawa",
    "wof:placetype":"locality"
},
  "geometry": {"coordinates":[79.9559,7.3129],"type":"Point"}
}