{
  "type": "Feature",
  "properties": {
    "gn:admin1_code":"36.0",
    "gn:admin2_code":"1248990.0",
    "gn:admin3_code":"7545424.0",
    "gn:asciiname":"Kudamaduwa",
    "gn:country_code":"LK",
    "gn:dem":18,
    "gn:feature_class":"P",
    "gn:feature_code":"PPL",
    "gn:name":"Kudamaduwa",
    "gn:population":0,
    "gn:timezone":"Asia/Colombo",
    "iso:country":"LK",
    "wof:name":"Kudamaduwa",
    "wof:placetype":"locality"
},
  "geometry": {"coordinates":[79.95869999999999,6.8034],"type":"Point"}
}