{
  "type": "Feature",
  "properties": {
    "gn:admin1_code":"33.0",
    "gn:asciiname":"Talagahawatta",
    "gn:country_code":"LK",
    "gn:dem":652,
    "gn:feature_class":"P",
    "gn:feature_code":"PPL",
    "gn:name":"Talagahawatta",
    "gn:population":0,
    "gn:timezone":"Asia/Colombo",
    "iso:country":"LK",
    "wof:name":"Talagahawatta",
    "wof:placetype":"locality"
},
  "geometry": {"coordinates":[80.6527,6.4467],"type":"Point"}
}