{
  "type": "Feature",
  "properties": {
    "gn:admin1_code":"30.0",
    "gn:asciiname":"Welewa",
    "gn:country_code":"LK",
    "gn:dem":110,
    "gn:feature_class":"P",
    "gn:feature_code":"PPL",
    "gn:name":"Welewa",
    "gn:population":0,
    "gn:timezone":"Asia/Colombo",
    "iso:country":"LK",
    "wof:name":"Welewa",
    "wof:placetype":"locality"
},
  "geometry": {"coordinates":[80.5826,8.4821],"type":"Point"}
}