{
  "type": "Feature",
  "properties": {
    "gn:admin1_code":"32.0",
    "gn:asciiname":"Galagedara",
    "gn:country_code":"LK",
    "gn:dem":294,
    "gn:feature_class":"P",
    "gn:feature_code":"PPL",
    "gn:name":"Galagedara",
    "gn:population":0,
    "gn:timezone":"Asia/Colombo",
    "iso:country":"LK",
    "wof:name":"Galagedara",
    "wof:placetype":"locality"
},
  "geometry": {"coordinates":[80.53248000000001,7.37099],"type":"Point"}
}