{
  "type": "Feature",
  "properties": {
    "gn:admin1_code":"35.0",
    "gn:asciiname":"Moragahamada",
    "gn:country_code":"LK",
    "gn:dem":279,
    "gn:feature_class":"P",
    "gn:feature_code":"PPL",
    "gn:name":"Moragahamada",
    "gn:population":0,
    "gn:timezone":"Asia/Colombo",
    "iso:country":"LK",
    "wof:name":"Moragahamada",
    "wof:placetype":"locality"
},
  "geometry": {"coordinates":[81.2719,6.9032],"type":"Point"}
}