{
  "type": "Feature",
  "properties": {
    "gn:admin1_code":"35.0",
    "gn:asciiname":"Dewalegoda",
    "gn:country_code":"LK",
    "gn:dem":384,
    "gn:feature_class":"P",
    "gn:feature_code":"PPL",
    "gn:name":"Dewalegoda",
    "gn:population":0,
    "gn:timezone":"Asia/Colombo",
    "iso:country":"LK",
    "wof:name":"Dewalegoda",
    "wof:placetype":"locality"
},
  "geometry": {"coordinates":[81.2469,6.9865],"type":"Point"}
}