{
  "type": "Feature",
  "properties": {
    "gn:admin1_code":"36.0",
    "gn:asciiname":"Makilangamuwa",
    "gn:country_code":"LK",
    "gn:dem":26,
    "gn:feature_class":"P",
    "gn:feature_code":"PPL",
    "gn:name":"Makilangamuwa",
    "gn:population":0,
    "gn:timezone":"Asia/Colombo",
    "iso:country":"LK",
    "name:und_x_variant":[
        "Makilangomuwa"
    ],
    "wof:name":"Makilangamuwa",
    "wof:placetype":"locality"
},
  "geometry": {"coordinates":[79.968,7.0772],"type":"Point"}
}