{
  "type": "Feature",
  "properties": {
    "gn:admin1_code":"29.0",
    "gn:asciiname":"Ellepola",
    "gn:country_code":"LK",
    "gn:dem":410,
    "gn:feature_class":"P",
    "gn:feature_code":"PPL",
    "gn:name":"Ellepola",
    "gn:population":0,
    "gn:timezone":"Asia/Colombo",
    "iso:country":"LK",
    "wof:name":"Ellepola",
    "wof:placetype":"locality"
},
  "geometry": {"coordinates":[80.61579999999999,7.5334],"type":"Point"}
}