{
  "type": "Feature",
  "properties": {
    "gn:admin1_code":"32.0",
    "gn:asciiname":"Madawala Pahala",
    "gn:country_code":"LK",
    "gn:dem":100,
    "gn:feature_class":"P",
    "gn:feature_code":"PPL",
    "gn:name":"Madawala Pahala",
    "gn:population":0,
    "gn:timezone":"Asia/Colombo",
    "iso:country":"LK",
    "wof:name":"Madawala Pahala",
    "wof:placetype":"locality"
},
  "geometry": {"coordinates":[80.2801,7.4704],"type":"Point"}
}