{
  "type": "Feature",
  "properties": {
    "gn:admin1_code":"35.0",
    "gn:asciiname":"Ridipana",
    "gn:country_code":"LK",
    "gn:dem":788,
    "gn:feature_class":"P",
    "gn:feature_code":"PPL",
    "gn:name":"Ridipana",
    "gn:population":0,
    "gn:timezone":"Asia/Colombo",
    "iso:country":"LK",
    "name:und_x_variant":[
        "Rideepana",
        "Ridipana"
    ],
    "wof:name":"Ridipana",
    "wof:placetype":"locality"
},
  "geometry": {"coordinates":[81.0535,7.015],"type":"Point"}
}