{
  "type": "Feature",
  "properties": {
    "gn:admin1_code":"32.0",
    "gn:asciiname":"Galkeradiwela",
    "gn:country_code":"LK",
    "gn:dem":114,
    "gn:feature_class":"P",
    "gn:feature_code":"PPL",
    "gn:name":"Galkeradiwela",
    "gn:population":0,
    "gn:timezone":"Asia/Colombo",
    "iso:country":"LK",
    "name:und_x_variant":[
        "Galkerandiwala"
    ],
    "wof:name":"Galkeradiwela",
    "wof:placetype":"locality"
},
  "geometry": {"coordinates":[80.2885,7.3762],"type":"Point"}
}