{
  "type": "Feature",
  "properties": {
    "gn:admin1_code":"32.0",
    "gn:asciiname":"Angomugama",
    "gn:country_code":"LK",
    "gn:dem":112,
    "gn:feature_class":"P",
    "gn:feature_code":"PPL",
    "gn:name":"Angomugama",
    "gn:population":0,
    "gn:timezone":"Asia/Colombo",
    "iso:country":"LK",
    "wof:name":"Angomugama",
    "wof:placetype":"locality"
},
  "geometry": {"coordinates":[80.34999999999999,7.88333],"type":"Point"}
}