{
  "type": "Feature",
  "properties": {
    "gn:admin1_code":"32.0",
    "gn:asciiname":"Konduruwawla",
    "gn:country_code":"LK",
    "gn:dem":99,
    "gn:feature_class":"P",
    "gn:feature_code":"PPL",
    "gn:name":"Konduruwawla",
    "gn:population":0,
    "gn:timezone":"Asia/Colombo",
    "iso:country":"LK",
    "name:und_x_variant":[
        "Konduruwawela"
    ],
    "wof:name":"Konduruwawla",
    "wof:placetype":"locality"
},
  "geometry": {"coordinates":[80.0962,7.3609],"type":"Point"}
}