{
  "type": "Feature",
  "properties": {
    "gn:admin1_code":"33.0",
    "gn:asciiname":"Hallawa",
    "gn:country_code":"LK",
    "gn:dem":191,
    "gn:feature_class":"P",
    "gn:feature_code":"PPL",
    "gn:name":"Hallawa",
    "gn:population":0,
    "gn:timezone":"Asia/Colombo",
    "iso:country":"LK",
    "wof:name":"Hallawa",
    "wof:placetype":"locality"
},
  "geometry": {"coordinates":[80.2269,7.1518],"type":"Point"}
}