{
  "type": "Feature",
  "properties": {
    "gn:admin1_code":"30.0",
    "gn:asciiname":"Pambattiyagama",
    "gn:country_code":"LK",
    "gn:dem":130,
    "gn:feature_class":"P",
    "gn:feature_code":"PPL",
    "gn:name":"Pambattiyagama",
    "gn:population":0,
    "gn:timezone":"Asia/Colombo",
    "iso:country":"LK",
    "wof:name":"Pambattiyagama",
    "wof:placetype":"locality"
},
  "geometry": {"coordinates":[80.6874,8.445],"type":"Point"}
}