{
  "type": "Feature",
  "properties": {
    "gn:admin1_code":"29.0",
    "gn:asciiname":"Serugolla",
    "gn:country_code":"LK",
    "gn:dem":390,
    "gn:feature_class":"P",
    "gn:feature_code":"PPL",
    "gn:name":"Serugolla",
    "gn:population":0,
    "gn:timezone":"Asia/Colombo",
    "iso:country":"LK",
    "wof:name":"Serugolla",
    "wof:placetype":"locality"
},
  "geometry": {"coordinates":[80.65049999999999,7.455],"type":"Point"}
}