{
  "type": "Feature",
  "properties": {
    "gn:admin1_code":"29.0",
    "gn:asciiname":"Koswatta",
    "gn:country_code":"LK",
    "gn:dem":426,
    "gn:feature_class":"P",
    "gn:feature_code":"PPL",
    "gn:name":"Koswatta",
    "gn:population":0,
    "gn:timezone":"Asia/Colombo",
    "iso:country":"LK",
    "wof:name":"Koswatta",
    "wof:placetype":"locality"
},
  "geometry": {"coordinates":[80.5943,7.6406],"type":"Point"}
}