{
  "type": "Feature",
  "properties": {
    "gn:admin1_code":"34.0",
    "gn:asciiname":"Mabotuwana",
    "gn:country_code":"LK",
    "gn:dem":24,
    "gn:feature_class":"P",
    "gn:feature_code":"PPL",
    "gn:name":"Mabotuwana",
    "gn:population":0,
    "gn:timezone":"Asia/Colombo",
    "iso:country":"LK",
    "name:urd_x_preferred":[
        "\u0645\u0627\u0628\u0648\u0679\u0648\u0648\u0627\u0646\u0627"
    ],
    "wof:name":"Mabotuwana",
    "wof:placetype":"locality"
},
  "geometry": {"coordinates":[80.28399999999998,6.1266],"type":"Point"}
}