{
  "type": "Feature",
  "properties": {
    "gn:admin1_code":"29.0",
    "gn:asciiname":"Jayalanka",
    "gn:country_code":"LK",
    "gn:dem":1945,
    "gn:feature_class":"P",
    "gn:feature_code":"PPL",
    "gn:name":"Jayalanka",
    "gn:population":0,
    "gn:timezone":"Asia/Colombo",
    "iso:country":"LK",
    "wof:name":"Jayalanka",
    "wof:placetype":"locality"
},
  "geometry": {"coordinates":[80.803,6.9907],"type":"Point"}
}