{
  "type": "Feature",
  "properties": {
    "gn:admin1_code":"38.0",
    "gn:asciiname":"Sinnakulama",
    "gn:country_code":"LK",
    "gn:dem":98,
    "gn:feature_class":"P",
    "gn:feature_code":"PPL",
    "gn:name":"Sinnakulama",
    "gn:population":0,
    "gn:timezone":"Asia/Colombo",
    "iso:country":"LK",
    "name:und_x_variant":[
        "Sinnakulam",
        "Sinnakulama"
    ],
    "wof:name":"Sinnakulama",
    "wof:placetype":"locality"
},
  "geometry": {"coordinates":[80.5063,8.6721],"type":"Point"}
}