{
  "type": "Feature",
  "properties": {
    "gn:admin1_code":"35.0",
    "gn:asciiname":"Radawa Pelessa",
    "gn:country_code":"LK",
    "gn:dem":140,
    "gn:feature_class":"P",
    "gn:feature_code":"PPL",
    "gn:name":"Radawa Pelessa",
    "gn:population":0,
    "gn:timezone":"Asia/Colombo",
    "iso:country":"LK",
    "wof:name":"Radawa Pelessa",
    "wof:placetype":"locality"
},
  "geometry": {"coordinates":[81.03789999999999,7.2223],"type":"Point"}
}