{
  "type": "Feature",
  "properties": {
    "gn:admin1_code":"36.0",
    "gn:asciiname":"Narangodapaluwa",
    "gn:country_code":"LK",
    "gn:dem":33,
    "gn:feature_class":"P",
    "gn:feature_code":"PPL",
    "gn:name":"Narangodapaluwa",
    "gn:population":0,
    "gn:timezone":"Asia/Colombo",
    "iso:country":"LK",
    "wof:name":"Narangodapaluwa",
    "wof:placetype":"locality"
},
  "geometry": {"coordinates":[79.93899999999999,7.0404],"type":"Point"}
}