{
  "type": "Feature",
  "properties": {
    "gn:admin1_code":"35.0",
    "gn:asciiname":"Mudumpitagama",
    "gn:country_code":"LK",
    "gn:dem":1183,
    "gn:feature_class":"P",
    "gn:feature_code":"PPL",
    "gn:name":"Mudumpitagama",
    "gn:population":0,
    "gn:timezone":"Asia/Colombo",
    "iso:country":"LK",
    "name:und_x_variant":[
        "Mudunpitagama"
    ],
    "wof:name":"Mudumpitagama",
    "wof:placetype":"locality"
},
  "geometry": {"coordinates":[80.8643,6.9033],"type":"Point"}
}