{
  "type": "Feature",
  "properties": {
    "gn:admin1_code":"36.0",
    "gn:asciiname":"Loolbadduwa",
    "gn:country_code":"LK",
    "gn:dem":9,
    "gn:feature_class":"P",
    "gn:feature_code":"PPL",
    "gn:name":"Loolbadduwa",
    "gn:population":0,
    "gn:timezone":"Asia/Colombo",
    "iso:country":"LK",
    "name:und_x_variant":[
        "Lulbadduwa"
    ],
    "wof:name":"Loolbadduwa",
    "wof:placetype":"locality"
},
  "geometry": {"coordinates":[80.0984,6.4027],"type":"Point"}
}