{
  "type": "Feature",
  "properties": {
    "gn:admin1_code":"29.0",
    "gn:asciiname":"Tibbotuwawa",
    "gn:country_code":"LK",
    "gn:dem":416,
    "gn:feature_class":"P",
    "gn:feature_code":"PPL",
    "gn:name":"Tibbotuwawa",
    "gn:population":0,
    "gn:timezone":"Asia/Colombo",
    "iso:country":"LK",
    "name:ceb_x_preferred":[
        "Tibbotuwawa"
    ],
    "name:swe_x_preferred":[
        "Tibbotuwawa"
    ],
    "wof:name":"Tibbotuwawa",
    "wof:placetype":"locality"
},
  "geometry": {"coordinates":[80.5894,7.4411],"type":"Point"}
}