{
  "type": "Feature",
  "properties": {
    "gn:admin1_code":"33.0",
    "gn:asciiname":"Mavudella",
    "gn:country_code":"LK",
    "gn:dem":51,
    "gn:feature_class":"P",
    "gn:feature_code":"PPL",
    "gn:name":"Mavudella",
    "gn:population":0,
    "gn:timezone":"Asia/Colombo",
    "iso:country":"LK",
    "name:und_x_variant":[
        "Maudella"
    ],
    "wof:name":"Mavudella",
    "wof:placetype":"locality"
},
  "geometry": {"coordinates":[80.4448,6.6473],"type":"Point"}
}