{
  "type": "Feature",
  "properties": {
    "gn:admin1_code":"33.0",
    "gn:asciiname":"Galpola",
    "gn:country_code":"LK",
    "gn:dem":136,
    "gn:feature_class":"P",
    "gn:feature_code":"PPL",
    "gn:name":"Galpola",
    "gn:population":0,
    "gn:timezone":"Asia/Colombo",
    "iso:country":"LK",
    "wof:name":"Galpola",
    "wof:placetype":"locality"
},
  "geometry": {"coordinates":[80.3873,7.2699],"type":"Point"}
}