{
  "type": "Feature",
  "properties": {
    "gn:admin1_code":"29.0",
    "gn:asciiname":"Munamale",
    "gn:country_code":"LK",
    "gn:dem":496,
    "gn:feature_class":"P",
    "gn:feature_code":"PPL",
    "gn:name":"Munamale",
    "gn:population":0,
    "gn:timezone":"Asia/Colombo",
    "iso:country":"LK",
    "wof:name":"Munamale",
    "wof:placetype":"locality"
},
  "geometry": {"coordinates":[80.6349,7.3499],"type":"Point"}
}