{
  "type": "Feature",
  "properties": {
    "gn:admin1_code":"33.0",
    "gn:asciiname":"Narangammana",
    "gn:country_code":"LK",
    "gn:dem":264,
    "gn:feature_class":"P",
    "gn:feature_code":"PPL",
    "gn:name":"Narangammana",
    "gn:population":0,
    "gn:timezone":"Asia/Colombo",
    "iso:country":"LK",
    "wof:name":"Narangammana",
    "wof:placetype":"locality"
},
  "geometry": {"coordinates":[80.4534,7.197],"type":"Point"}
}