{
  "type": "Feature",
  "properties": {
    "gn:admin1_code":"33.0",
    "gn:asciiname":"Dandeniya Pahala",
    "gn:country_code":"LK",
    "gn:dem":170,
    "gn:feature_class":"P",
    "gn:feature_code":"PPL",
    "gn:name":"Dandeniya Pahala",
    "gn:population":0,
    "gn:timezone":"Asia/Colombo",
    "iso:country":"LK",
    "wof:name":"Dandeniya Pahala",
    "wof:placetype":"locality"
},
  "geometry": {"coordinates":[80.23333000000002,7.13333],"type":"Point"}
}