{
  "type": "Feature",
  "properties": {
    "gn:admin1_code":"32.0",
    "gn:asciiname":"Pahala Medagama",
    "gn:country_code":"LK",
    "gn:dem":120,
    "gn:feature_class":"P",
    "gn:feature_code":"PPL",
    "gn:name":"Pahala Medagama",
    "gn:population":0,
    "gn:timezone":"Asia/Colombo",
    "iso:country":"LK",
    "wof:name":"Pahala Medagama",
    "wof:placetype":"locality"
},
  "geometry": {"coordinates":[80.4299,7.6738],"type":"Point"}
}