{
  "type": "Feature",
  "properties": {
    "gn:admin1_code":"33.0",
    "gn:asciiname":"Niyangama",
    "gn:country_code":"LK",
    "gn:dem":271,
    "gn:feature_class":"P",
    "gn:feature_code":"PPL",
    "gn:name":"Niyangama",
    "gn:population":0,
    "gn:timezone":"Asia/Colombo",
    "iso:country":"LK",
    "name:ceb_x_preferred":[
        "Niyangama"
    ],
    "name:swe_x_preferred":[
        "Niyangama"
    ],
    "wof:name":"Niyangama",
    "wof:placetype":"locality"
},
  "geometry": {"coordinates":[80.6511,6.5151],"type":"Point"}
}