{
  "type": "Feature",
  "properties": {
    "gn:admin1_code":"34.0",
    "gn:asciiname":"Igala",
    "gn:country_code":"LK",
    "gn:dem":16,
    "gn:feature_class":"P",
    "gn:feature_code":"PPL",
    "gn:name":"Igala",
    "gn:population":0,
    "gn:timezone":"Asia/Colombo",
    "iso:country":"LK",
    "name:fra_x_preferred":[
        "Igala"
    ],
    "wof:name":"Igala",
    "wof:placetype":"locality"
},
  "geometry": {"coordinates":[80.1545,6.2826],"type":"Point"}
}