{
  "type": "Feature",
  "properties": {
    "gn:admin1_code":"32.0",
    "gn:asciiname":"Tennegammedda",
    "gn:country_code":"LK",
    "gn:dem":325,
    "gn:feature_class":"P",
    "gn:feature_code":"PPL",
    "gn:name":"Tennegammedda",
    "gn:population":0,
    "gn:timezone":"Asia/Colombo",
    "iso:country":"LK",
    "wof:name":"Tennegammedda",
    "wof:placetype":"locality"
},
  "geometry": {"coordinates":[80.5479,7.4607],"type":"Point"}
}