{
  "type": "Feature",
  "properties": {
    "gn:admin1_code":"34.0",
    "gn:asciiname":"Ihala Guruwela",
    "gn:country_code":"LK",
    "gn:dem":61,
    "gn:feature_class":"P",
    "gn:feature_code":"PPL",
    "gn:name":"Ihala Guruwela",
    "gn:population":0,
    "gn:timezone":"Asia/Colombo",
    "iso:country":"LK",
    "wof:name":"Ihala Guruwela",
    "wof:placetype":"locality"
},
  "geometry": {"coordinates":[80.84350000000001,6.1937],"type":"Point"}
}