{
  "type": "Feature",
  "properties": {
    "gn:admin1_code":"34.0",
    "gn:asciiname":"Mahabolana",
    "gn:country_code":"LK",
    "gn:dem":21,
    "gn:feature_class":"P",
    "gn:feature_code":"PPL",
    "gn:name":"Mahabolana",
    "gn:population":0,
    "gn:timezone":"Asia/Colombo",
    "iso:country":"LK",
    "wof:name":"Mahabolana",
    "wof:placetype":"locality"
},
  "geometry": {"coordinates":[81.0094,6.1576],"type":"Point"}
}