{
  "type": "Feature",
  "properties": {
    "gn:admin1_code":"35.0",
    "gn:asciiname":"Idamegedaraarawa",
    "gn:country_code":"LK",
    "gn:dem":194,
    "gn:feature_class":"P",
    "gn:feature_code":"PPL",
    "gn:name":"Idamegedaraarawa",
    "gn:population":0,
    "gn:timezone":"Asia/Colombo",
    "iso:country":"LK",
    "wof:name":"Idamegedaraarawa",
    "wof:placetype":"locality"
},
  "geometry": {"coordinates":[81.3472,6.9555],"type":"Point"}
}