{
  "type": "Feature",
  "properties": {
    "gn:admin1_code":"35.0",
    "gn:asciiname":"Ginigatgala",
    "gn:country_code":"LK",
    "gn:dem":1167,
    "gn:feature_class":"P",
    "gn:feature_code":"PPL",
    "gn:name":"Ginigatgala",
    "gn:population":0,
    "gn:timezone":"Asia/Colombo",
    "iso:country":"LK",
    "name:und_x_variant":[
        "Ginigathgala",
        "Ginigatgala"
    ],
    "wof:name":"Ginigatgala",
    "wof:placetype":"locality"
},
  "geometry": {"coordinates":[80.87609999999999,6.7662],"type":"Point"}
}