{
  "type": "Feature",
  "properties": {
    "gn:admin1_code":"36.0",
    "gn:asciiname":"Tarakuliya",
    "gn:country_code":"LK",
    "gn:dem":3,
    "gn:feature_class":"P",
    "gn:feature_code":"PPL",
    "gn:name":"Tarakuliya",
    "gn:population":0,
    "gn:timezone":"Asia/Colombo",
    "iso:country":"LK",
    "name:und_x_variant":[
        "Tarakulliya"
    ],
    "wof:name":"Tarakuliya",
    "wof:placetype":"locality"
},
  "geometry": {"coordinates":[79.8629,7.0818],"type":"Point"}
}