{
  "type": "Feature",
  "properties": {
    "gn:admin1_code":"34.0",
    "gn:asciiname":"Nimalawa",
    "gn:cc2":"LK",
    "gn:country_code":"LK",
    "gn:dem":68,
    "gn:feature_class":"P",
    "gn:feature_code":"PPL",
    "gn:name":"Nimalawa",
    "gn:population":0,
    "gn:timezone":"Asia/Colombo",
    "iso:country":"LK",
    "name:und_x_variant":[
        "Nimalewa",
        "Nimalawa"
    ],
    "wof:name":"Nimalawa",
    "wof:placetype":"locality"
},
  "geometry": {"coordinates":[80.45,6.05],"type":"Point"}
}