{
  "type": "Feature",
  "properties": {
    "gn:admin1_code":"36.0",
    "gn:asciiname":"Muruthagama",
    "gn:country_code":"LK",
    "gn:dem":31,
    "gn:feature_class":"P",
    "gn:feature_code":"PPL",
    "gn:name":"Muruthagama",
    "gn:population":0,
    "gn:timezone":"Asia/Colombo",
    "iso:country":"LK",
    "name:und_x_variant":[
        "Murutagama"
    ],
    "wof:name":"Muruthagama",
    "wof:placetype":"locality"
},
  "geometry": {"coordinates":[80.11960000000001,6.9444],"type":"Point"}
}