{
  "type": "Feature",
  "properties": {
    "gn:admin1_code":"32.0",
    "gn:asciiname":"Pahala Weligepola",
    "gn:country_code":"LK",
    "gn:dem":164,
    "gn:feature_class":"P",
    "gn:feature_code":"PPL",
    "gn:name":"Pahala Weligepola",
    "gn:population":0,
    "gn:timezone":"Asia/Colombo",
    "iso:country":"LK",
    "wof:name":"Pahala Weligepola",
    "wof:placetype":"locality"
},
  "geometry": {"coordinates":[80.4742,7.4241],"type":"Point"}
}