{
  "type": "Feature",
  "properties": {
    "gn:admin1_code":"34.0",
    "gn:asciiname":"Waraketigoda",
    "gn:country_code":"LK",
    "gn:dem":84,
    "gn:feature_class":"P",
    "gn:feature_code":"PPL",
    "gn:name":"Waraketigoda",
    "gn:population":0,
    "gn:timezone":"Asia/Colombo",
    "iso:country":"LK",
    "wof:name":"Waraketigoda",
    "wof:placetype":"locality"
},
  "geometry": {"coordinates":[80.7375,6.1394],"type":"Point"}
}