{
  "type": "Feature",
  "properties": {
    "gn:admin1_code":"33.0",
    "gn:asciiname":"Eluwana",
    "gn:country_code":"LK",
    "gn:dem":138,
    "gn:feature_class":"P",
    "gn:feature_code":"PPL",
    "gn:name":"Eluwana",
    "gn:population":0,
    "gn:timezone":"Asia/Colombo",
    "iso:country":"LK",
    "wof:name":"Eluwana",
    "wof:placetype":"locality"
},
  "geometry": {"coordinates":[80.5754,6.5761],"type":"Point"}
}