{
  "type": "Feature",
  "properties": {
    "gn:admin1_code":"32.0",
    "gn:asciiname":"Gallewa",
    "gn:country_code":"LK",
    "gn:dem":69,
    "gn:feature_class":"P",
    "gn:feature_code":"PPL",
    "gn:name":"Gallewa",
    "gn:population":0,
    "gn:timezone":"Asia/Colombo",
    "iso:country":"LK",
    "wof:name":"Gallewa",
    "wof:placetype":"locality"
},
  "geometry": {"coordinates":[80.12439999999999,7.9815],"type":"Point"}
}