{
  "type": "Feature",
  "properties": {
    "gn:admin1_code":"29.0",
    "gn:asciiname":"Lidesdailwatta",
    "gn:country_code":"LK",
    "gn:dem":1519,
    "gn:feature_class":"P",
    "gn:feature_code":"PPL",
    "gn:name":"Lidesdailwatta",
    "gn:population":0,
    "gn:timezone":"Asia/Colombo",
    "iso:country":"LK",
    "wof:name":"Lidesdailwatta",
    "wof:placetype":"locality"
},
  "geometry": {"coordinates":[80.8661,7.0328],"type":"Point"}
}