{
  "type": "Feature",
  "properties": {
    "gn:admin1_code":"29.0",
    "gn:asciiname":"Mulgama",
    "gn:country_code":"LK",
    "gn:dem":816,
    "gn:feature_class":"P",
    "gn:feature_code":"PPL",
    "gn:name":"Mulgama",
    "gn:population":0,
    "gn:timezone":"Asia/Colombo",
    "iso:country":"LK",
    "wof:name":"Mulgama",
    "wof:placetype":"locality"
},
  "geometry": {"coordinates":[80.6698,7.1527],"type":"Point"}
}