{
  "type": "Feature",
  "properties": {
    "gn:admin1_code":"32.0",
    "gn:asciiname":"Attikulama",
    "gn:country_code":"LK",
    "gn:dem":64,
    "gn:feature_class":"P",
    "gn:feature_code":"PPL",
    "gn:name":"Attikulama",
    "gn:population":0,
    "gn:timezone":"Asia/Colombo",
    "iso:country":"LK",
    "name:und_x_variant":[
        "Aththikulama",
        "Attikulama"
    ],
    "wof:name":"Attikulama",
    "wof:placetype":"locality"
},
  "geometry": {"coordinates":[80.01049999999999,7.8366],"type":"Point"}
}