{
  "type": "Feature",
  "properties": {
    "gn:admin1_code":"36.0",
    "gn:asciiname":"Welimulla Junction",
    "gn:country_code":"LK",
    "gn:dem":31,
    "gn:feature_class":"P",
    "gn:feature_code":"PPL",
    "gn:name":"Welimulla Junction",
    "gn:population":0,
    "gn:timezone":"Asia/Colombo",
    "iso:country":"LK",
    "wof:name":"Welimulla Junction",
    "wof:placetype":"locality"
},
  "geometry": {"coordinates":[79.9717,6.7492],"type":"Point"}
}