{
  "type": "Feature",
  "properties": {
    "gn:admin1_code":"29.0",
    "gn:asciiname":"Ilukhena",
    "gn:country_code":"LK",
    "gn:dem":206,
    "gn:feature_class":"P",
    "gn:feature_code":"PPL",
    "gn:name":"Ilukhena",
    "gn:population":0,
    "gn:timezone":"Asia/Colombo",
    "iso:country":"LK",
    "wof:name":"Ilukhena",
    "wof:placetype":"locality"
},
  "geometry": {"coordinates":[80.86667,7.45],"type":"Point"}
}