{
  "type": "Feature",
  "properties": {
    "gn:admin1_code":"38.0",
    "gn:admin2_code":"1236148.0",
    "gn:asciiname":"Kollarsirukkulam",
    "gn:country_code":"LK",
    "gn:dem":17,
    "gn:feature_class":"P",
    "gn:feature_code":"PPL",
    "gn:name":"Kollarsirukkulam",
    "gn:population":0,
    "gn:timezone":"Asia/Colombo",
    "iso:country":"LK",
    "wof:name":"Kollarsirukkulam",
    "wof:placetype":"locality"
},
  "geometry": {"coordinates":[80.04536,8.84258],"type":"Point"}
}