{
  "type": "Feature",
  "properties": {
    "gn:admin1_code":"29.0",
    "gn:asciiname":"Rogersongama",
    "gn:country_code":"LK",
    "gn:dem":1216,
    "gn:feature_class":"P",
    "gn:feature_code":"PPL",
    "gn:name":"Rogersongama",
    "gn:population":0,
    "gn:timezone":"Asia/Colombo",
    "iso:country":"LK",
    "wof:name":"Rogersongama",
    "wof:placetype":"locality"
},
  "geometry": {"coordinates":[80.62869999999999,7.0418],"type":"Point"}
}