{
  "type": "Feature",
  "properties": {
    "gn:admin1_code":"33.0",
    "gn:asciiname":"Alupota",
    "gn:country_code":"LK",
    "gn:dem":220,
    "gn:feature_class":"P",
    "gn:feature_code":"PPL",
    "gn:name":"Alupota",
    "gn:population":0,
    "gn:timezone":"Asia/Colombo",
    "iso:country":"LK",
    "wof:name":"Alupota",
    "wof:placetype":"locality"
},
  "geometry": {"coordinates":[80.4559,7.2091],"type":"Point"}
}