{
  "type": "Feature",
  "properties": {
    "gn:admin1_code":"30.0",
    "gn:asciiname":"Matongama",
    "gn:country_code":"LK",
    "gn:dem":136,
    "gn:feature_class":"P",
    "gn:feature_code":"PPL",
    "gn:name":"Matongama",
    "gn:population":0,
    "gn:timezone":"Asia/Colombo",
    "iso:country":"LK",
    "wof:name":"Matongama",
    "wof:placetype":"locality"
},
  "geometry": {"coordinates":[80.55,8.08333],"type":"Point"}
}