{
  "type": "Feature",
  "properties": {
    "gn:admin1_code":"30.0",
    "gn:asciiname":"Galenbindunuwewa",
    "gn:country_code":"LK",
    "gn:dem":111,
    "gn:feature_class":"P",
    "gn:feature_code":"PPL",
    "gn:name":"Galenbindunuwewa",
    "gn:population":0,
    "gn:timezone":"Asia/Colombo",
    "iso:country":"LK",
    "wof:name":"Galenbindunuwewa",
    "wof:placetype":"locality"
},
  "geometry": {"coordinates":[80.46169999999999,8.1073],"type":"Point"}
}