{
  "type": "Feature",
  "properties": {
    "gn:asciiname":"Pamankada",
    "gn:country_code":"LK",
    "gn:dem":16,
    "gn:feature_class":"P",
    "gn:feature_code":"PPL",
    "gn:name":"Pamankada",
    "gn:population":0,
    "gn:timezone":"Asia/Colombo",
    "iso:country":"LK",
    "wof:name":"Pamankada",
    "wof:placetype":"locality"
},
  "geometry": {"coordinates":[79.86944,6.87734],"type":"Point"}
}