{
  "type": "Feature",
  "properties": {
    "gn:admin1_code":"38.0",
    "gn:asciiname":"Cholaiyankaddu",
    "gn:country_code":"LK",
    "gn:dem":6,
    "gn:feature_class":"P",
    "gn:feature_code":"PPL",
    "gn:name":"Cholaiyankaddu",
    "gn:population":0,
    "gn:timezone":"Asia/Colombo",
    "iso:country":"LK",
    "wof:name":"Cholaiyankaddu",
    "wof:placetype":"locality"
},
  "geometry": {"coordinates":[79.93333,8.83333],"type":"Point"}
}