{
  "type": "Feature",
  "properties": {
    "gn:admin1_code":"35.0",
    "gn:asciiname":"Tallanda",
    "gn:country_code":"LK",
    "gn:dem":255,
    "gn:feature_class":"P",
    "gn:feature_code":"PPL",
    "gn:name":"Tallanda",
    "gn:population":0,
    "gn:timezone":"Asia/Colombo",
    "iso:country":"LK",
    "wof:name":"Tallanda",
    "wof:placetype":"locality"
},
  "geometry": {"coordinates":[81.29349999999999,7.1771],"type":"Point"}
}