{
  "type": "Feature",
  "properties": {
    "gn:admin1_code":"30.0",
    "gn:asciiname":"Jayasiripura",
    "gn:country_code":"LK",
    "gn:dem":109,
    "gn:feature_class":"P",
    "gn:feature_code":"PPL",
    "gn:name":"Jayasiripura",
    "gn:population":0,
    "gn:timezone":"Asia/Colombo",
    "iso:country":"LK",
    "wof:name":"Jayasiripura",
    "wof:placetype":"locality"
},
  "geometry": {"coordinates":[80.2869,8.2549],"type":"Point"}
}