{
  "type": "Feature",
  "properties": {
    "gn:admin1_code":"35.0",
    "gn:asciiname":"Panditagama",
    "gn:country_code":"LK",
    "gn:dem":672,
    "gn:feature_class":"P",
    "gn:feature_code":"PPL",
    "gn:name":"Panditagama",
    "gn:population":0,
    "gn:timezone":"Asia/Colombo",
    "iso:country":"LK",
    "name:und_x_variant":[
        "Pandithagama",
        "Panditagama"
    ],
    "wof:name":"Panditagama",
    "wof:placetype":"locality"
},
  "geometry": {"coordinates":[80.89699999999998,6.7511],"type":"Point"}
}