{
  "type": "Feature",
  "properties": {
    "gn:admin1_code":"35.0",
    "gn:asciiname":"Radawelyaya",
    "gn:country_code":"LK",
    "gn:dem":178,
    "gn:feature_class":"P",
    "gn:feature_code":"PPL",
    "gn:name":"Radawelyaya",
    "gn:population":0,
    "gn:timezone":"Asia/Colombo",
    "iso:country":"LK",
    "wof:name":"Radawelyaya",
    "wof:placetype":"locality"
},
  "geometry": {"coordinates":[81.34899999999998,6.9476],"type":"Point"}
}