{
  "type": "Feature",
  "properties": {
    "gn:admin1_code":"32.0",
    "gn:asciiname":"Palugahakotuwa",
    "gn:country_code":"LK",
    "gn:dem":122,
    "gn:feature_class":"P",
    "gn:feature_code":"PPL",
    "gn:name":"Palugahakotuwa",
    "gn:population":0,
    "gn:timezone":"Asia/Colombo",
    "iso:country":"LK",
    "wof:name":"Palugahakotuwa",
    "wof:placetype":"locality"
},
  "geometry": {"coordinates":[80.36060000000001,7.9435],"type":"Point"}
}