{
  "type": "Feature",
  "properties": {
    "gn:admin1_code":"33.0",
    "gn:asciiname":"Ihala Nakkawita",
    "gn:country_code":"LK",
    "gn:dem":245,
    "gn:feature_class":"P",
    "gn:feature_code":"PPL",
    "gn:name":"Ihala Nakkawita",
    "gn:population":0,
    "gn:timezone":"Asia/Colombo",
    "iso:country":"LK",
    "wof:name":"Ihala Nakkawita",
    "wof:placetype":"locality"
},
  "geometry": {"coordinates":[80.3665,6.9052],"type":"Point"}
}