{
  "type": "Feature",
  "properties": {
    "gn:admin1_code":"32.0",
    "gn:asciiname":"Karawita-agare",
    "gn:country_code":"LK",
    "gn:dem":28,
    "gn:feature_class":"P",
    "gn:feature_code":"PPL",
    "gn:name":"Karawita-agare",
    "gn:population":0,
    "gn:timezone":"Asia/Colombo",
    "iso:country":"LK",
    "wof:name":"Karawita-agare",
    "wof:placetype":"locality"
},
  "geometry": {"coordinates":[79.8665,7.5585],"type":"Point"}
}