{
  "type": "Feature",
  "properties": {
    "gn:admin1_code":"32.0",
    "gn:asciiname":"Gurumada",
    "gn:country_code":"LK",
    "gn:dem":189,
    "gn:feature_class":"P",
    "gn:feature_code":"PPL",
    "gn:name":"Gurumada",
    "gn:population":0,
    "gn:timezone":"Asia/Colombo",
    "iso:country":"LK",
    "wof:name":"Gurumada",
    "wof:placetype":"locality"
},
  "geometry": {"coordinates":[80.52630000000001,7.4874],"type":"Point"}
}