{
  "type": "Feature",
  "properties": {
    "gn:admin1_code":"29.0",
    "gn:asciiname":"Maussaw",
    "gn:country_code":"LK",
    "gn:dem":1010,
    "gn:feature_class":"P",
    "gn:feature_code":"PPL",
    "gn:name":"Maussaw",
    "gn:population":0,
    "gn:timezone":"Asia/Colombo",
    "iso:country":"LK",
    "wof:name":"Maussaw",
    "wof:placetype":"locality"
},
  "geometry": {"coordinates":[80.72580000000001,7.1858],"type":"Point"}
}