{
  "type": "Feature",
  "properties": {
    "gn:admin1_code":"34.0",
    "gn:asciiname":"Rilamulla",
    "gn:country_code":"LK",
    "gn:dem":3,
    "gn:feature_class":"P",
    "gn:feature_code":"PPL",
    "gn:name":"Rilamulla",
    "gn:population":0,
    "gn:timezone":"Asia/Colombo",
    "iso:country":"LK",
    "wof:name":"Rilamulla",
    "wof:placetype":"locality"
},
  "geometry": {"coordinates":[80.58333,6.01667],"type":"Point"}
}