{
  "type": "Feature",
  "properties": {
    "gn:admin1_code":"33.0",
    "gn:asciiname":"Pallebedda",
    "gn:country_code":"LK",
    "gn:dem":131,
    "gn:feature_class":"P",
    "gn:feature_code":"PPL",
    "gn:name":"Pallebedda",
    "gn:population":0,
    "gn:timezone":"Asia/Colombo",
    "iso:country":"LK",
    "wof:name":"Pallebedda",
    "wof:placetype":"locality"
},
  "geometry": {"coordinates":[80.7388,6.4544],"type":"Point"}
}