{
  "type": "Feature",
  "properties": {
    "gn:admin1_code":"29.0",
    "gn:asciiname":"Yalegoda",
    "gn:country_code":"LK",
    "gn:dem":505,
    "gn:feature_class":"P",
    "gn:feature_code":"PPL",
    "gn:name":"Yalegoda",
    "gn:population":0,
    "gn:timezone":"Asia/Colombo",
    "iso:country":"LK",
    "name:urd_x_preferred":[
        "\u06cc\u0644\u06cc\u06af\u0648\u062f\u06c1"
    ],
    "wof:name":"Yalegoda",
    "wof:placetype":"locality"
},
  "geometry": {"coordinates":[80.58750000000001,7.2422],"type":"Point"}
}