{
  "type": "Feature",
  "properties": {
    "gn:admin1_code":"29.0",
    "gn:asciiname":"Godamunnangamedda",
    "gn:country_code":"LK",
    "gn:dem":418,
    "gn:feature_class":"P",
    "gn:feature_code":"PPL",
    "gn:name":"Godamunnangamedda",
    "gn:population":0,
    "gn:timezone":"Asia/Colombo",
    "iso:country":"LK",
    "wof:name":"Godamunnangamedda",
    "wof:placetype":"locality"
},
  "geometry": {"coordinates":[80.8258,7.2256],"type":"Point"}
}