{
  "type": "Feature",
  "properties": {
    "iso:country":"LK",
    "name:und_x_variant":[
        "Donanduwa"
    ],
    "qs:gn_country":"LK",
    "qs:gn_fcode":"PPL",
    "qs:gn_pop":0,
    "qs:name":"Dodanduwa",
    "qs:name_adm0":"Sri Lanka",
    "qs:name_adm1":"Southern",
    "qs:photos":247,
    "qs:photos_1k":50,
    "qs:photos_9k":1,
    "qs:photos_9r":4,
    "qs:photos_all":247,
    "qs:photos_sr":4,
    "qs:placetype":"Town",
    "qs:pop_sr":"0",
    "qs:woe_adm0":23424778,
    "wof:name":"Dodanduwa",
    "wof:placetype":"locality"
},
  "geometry": {"coordinates":[80.13509999999999,6.0962],"type":"Point"}
}