{
  "type": "Feature",
  "properties": {
    "gn:admin1_code":"34.0",
    "gn:asciiname":"Nawandannagoda",
    "gn:country_code":"LK",
    "gn:dem":87,
    "gn:feature_class":"P",
    "gn:feature_code":"PPL",
    "gn:name":"Nawandannagoda",
    "gn:population":0,
    "gn:timezone":"Asia/Colombo",
    "iso:country":"LK",
    "wof:name":"Nawandannagoda",
    "wof:placetype":"locality"
},
  "geometry": {"coordinates":[80.31570000000001,6.0663],"type":"Point"}
}