{
  "type": "Feature",
  "properties": {
    "gn:admin1_code":"29.0",
    "gn:asciiname":"Haloyawatta",
    "gn:country_code":"LK",
    "gn:dem":841,
    "gn:feature_class":"P",
    "gn:feature_code":"PPL",
    "gn:name":"Haloyawatta",
    "gn:population":0,
    "gn:timezone":"Asia/Colombo",
    "iso:country":"LK",
    "wof:name":"Haloyawatta",
    "wof:placetype":"locality"
},
  "geometry": {"coordinates":[80.62779999999999,7.2236],"type":"Point"}
}