{
  "type": "Feature",
  "properties": {
    "gn:admin1_code":"38.0",
    "gn:asciiname":"Karunkandalvannakulam",
    "gn:country_code":"LK",
    "gn:dem":10,
    "gn:feature_class":"P",
    "gn:feature_code":"PPL",
    "gn:name":"Karunkandalvannakulam",
    "gn:population":0,
    "gn:timezone":"Asia/Colombo",
    "iso:country":"LK",
    "name:und_x_variant":[
        "Vannakulam",
        "Karunkandalvannakulam"
    ],
    "wof:name":"Karunkandalvannakulam",
    "wof:placetype":"locality"
},
  "geometry": {"coordinates":[80.0145,8.90928],"type":"Point"}
}