{
  "type": "Feature",
  "properties": {
    "gn:admin1_code":"32.0",
    "gn:asciiname":"Mipitiya",
    "gn:country_code":"LK",
    "gn:dem":108,
    "gn:feature_class":"P",
    "gn:feature_code":"PPL",
    "gn:name":"Mipitiya",
    "gn:population":0,
    "gn:timezone":"Asia/Colombo",
    "iso:country":"LK",
    "wof:name":"Mipitiya",
    "wof:placetype":"locality"
},
  "geometry": {"coordinates":[80.35300000000002,7.5933],"type":"Point"}
}