{
  "type": "Feature",
  "properties": {
    "gn:admin1_code":"33.0",
    "gn:asciiname":"Wewaldeniya",
    "gn:country_code":"LK",
    "gn:dem":211,
    "gn:feature_class":"P",
    "gn:feature_code":"PPL",
    "gn:name":"Wewaldeniya",
    "gn:population":0,
    "gn:timezone":"Asia/Colombo",
    "iso:country":"LK",
    "name:und_x_variant":[
        "Wewaladeniya"
    ],
    "wof:name":"Wewaldeniya",
    "wof:placetype":"locality"
},
  "geometry": {"coordinates":[80.33839999999999,7.2537],"type":"Point"}
}