{
  "type": "Feature",
  "properties": {
    "gn:admin1_code":"32.0",
    "gn:asciiname":"Maha Mukalanyaya",
    "gn:country_code":"LK",
    "gn:dem":126,
    "gn:feature_class":"P",
    "gn:feature_code":"PPL",
    "gn:name":"Maha Mukalanyaya",
    "gn:population":0,
    "gn:timezone":"Asia/Colombo",
    "iso:country":"LK",
    "name:und_x_variant":[
        "Maha Makalanyaya",
        "Maha Mukalanyaya"
    ],
    "wof:name":"Maha Mukalanyaya",
    "wof:placetype":"locality"
},
  "geometry": {"coordinates":[80.42019999999999,7.5614],"type":"Point"}
}