{
  "type": "Feature",
  "properties": {
    "gn:admin1_code":"33.0",
    "gn:asciiname":"Balawinna",
    "gn:country_code":"LK",
    "gn:dem":200,
    "gn:feature_class":"P",
    "gn:feature_code":"PPL",
    "gn:name":"Balawinna",
    "gn:population":0,
    "gn:timezone":"Asia/Colombo",
    "iso:country":"LK",
    "name:und_x_variant":[
        "Balavinna",
        "Balawinna"
    ],
    "wof:name":"Balawinna",
    "wof:placetype":"locality"
},
  "geometry": {"coordinates":[80.6722,6.4949],"type":"Point"}
}