{
  "type": "Feature",
  "properties": {
    "gn:admin1_code":"36.0",
    "gn:asciiname":"Madiwela",
    "gn:country_code":"LK",
    "gn:dem":11,
    "gn:feature_class":"P",
    "gn:feature_code":"PPL",
    "gn:name":"Madiwela",
    "gn:population":0,
    "gn:timezone":"Asia/Colombo",
    "iso:country":"LK",
    "name:und_x_variant":[
        "Madiwala"
    ],
    "wof:name":"Madiwela",
    "wof:placetype":"locality"
},
  "geometry": {"coordinates":[79.91670000000001,6.8773],"type":"Point"}
}