{
  "type": "Feature",
  "properties": {
    "gn:admin1_code":"32.0",
    "gn:asciiname":"Heramayagama",
    "gn:cc2":"LK",
    "gn:country_code":"LK",
    "gn:dem":81,
    "gn:feature_class":"P",
    "gn:feature_code":"PPL",
    "gn:name":"Heramayagama",
    "gn:population":0,
    "gn:timezone":"Asia/Colombo",
    "iso:country":"LK",
    "name:und_x_variant":[
        "Haramayagama",
        "Heramayagama"
    ],
    "wof:name":"Heramayagama",
    "wof:placetype":"locality"
},
  "geometry": {"coordinates":[80.25,7.78333],"type":"Point"}
}