{
  "type": "Feature",
  "properties": {
    "gn:admin1_code":"32.0",
    "gn:asciiname":"Kuda Sawarana",
    "gn:country_code":"LK",
    "gn:dem":12,
    "gn:feature_class":"P",
    "gn:feature_code":"PPL",
    "gn:name":"Kuda Sawarana",
    "gn:population":0,
    "gn:timezone":"Asia/Colombo",
    "iso:country":"LK",
    "wof:name":"Kuda Sawarana",
    "wof:placetype":"locality"
},
  "geometry": {"coordinates":[79.8219,7.5601],"type":"Point"}
}