{
  "type": "Feature",
  "properties": {
    "gn:admin1_code":"32.0",
    "gn:asciiname":"Padiwela",
    "gn:country_code":"LK",
    "gn:dem":34,
    "gn:feature_class":"P",
    "gn:feature_code":"PPL",
    "gn:name":"Padiwela",
    "gn:population":0,
    "gn:timezone":"Asia/Colombo",
    "iso:country":"LK",
    "wof:name":"Padiwela",
    "wof:placetype":"locality"
},
  "geometry": {"coordinates":[79.97969999999999,7.5477],"type":"Point"}
}