{
  "type": "Feature",
  "properties": {
    "gn:admin1_code":"29.0",
    "gn:asciiname":"Meegolla",
    "gn:country_code":"LK",
    "gn:dem":826,
    "gn:feature_class":"P",
    "gn:feature_code":"PPL",
    "gn:name":"Meegolla",
    "gn:population":0,
    "gn:timezone":"Asia/Colombo",
    "iso:country":"LK",
    "wof:name":"Meegolla",
    "wof:placetype":"locality"
},
  "geometry": {"coordinates":[80.92399999999998,7.0831],"type":"Point"}
}