{
  "type": "Feature",
  "properties": {
    "gn:admin1_code":"32.0",
    "gn:asciiname":"Pirivena",
    "gn:country_code":"LK",
    "gn:dem":118,
    "gn:feature_class":"P",
    "gn:feature_code":"PPL",
    "gn:name":"Pirivena",
    "gn:population":0,
    "gn:timezone":"Asia/Colombo",
    "iso:country":"LK",
    "name:rus_x_preferred":[
        "\u041f\u0438\u0440\u0438\u0432\u044d\u043d\u0430"
    ],
    "name:sin_x_preferred":[
        "\u0db4\u0dd2\u0dbb\u0dd2\u0dc0\u0dd9\u0db1\u0dca"
    ],
    "name:tam_x_preferred":[
        "\u0baa\u0bbf\u0bb0\u0bbf\u0bb5\u0bc7\u0ba9\u0bbe"
    ],
    "wof:name":"Pirivena",
    "wof:placetype":"locality"
},
  "geometry": {"coordinates":[80.35120000000001,7.4898],"type":"Point"}
}