{
  "type": "Feature",
  "properties": {
    "gn:admin1_code":"32.0",
    "gn:asciiname":"Pirivena",
    "gn:country_code":"LK",
    "gn:dem":118,
    "gn:feature_class":"P",
    "gn:feature_code":"PPL",
    "gn:name":"Pirivena",
    "gn:population":0,
    "gn:timezone":"Asia/Colombo",
    "iso:country":"LK",
    "wof:name":"Pirivena",
    "wof:placetype":"locality"
},
  "geometry": {"coordinates":[80.35120000000001,7.4898],"type":"Point"}
}