{
  "type": "Feature",
  "properties": {
    "gn:admin1_code":"32.0",
    "gn:asciiname":"Aluthgama",
    "gn:country_code":"LK",
    "gn:dem":32,
    "gn:feature_class":"P",
    "gn:feature_code":"PPL",
    "gn:name":"Aluthgama",
    "gn:population":0,
    "gn:timezone":"Asia/Colombo",
    "iso:country":"LK",
    "wof:name":"Aluthgama",
    "wof:placetype":"locality"
},
  "geometry": {"coordinates":[79.9675,7.6171],"type":"Point"}
}