{
  "type": "Feature",
  "properties": {
    "gn:admin1_code":"32.0",
    "gn:asciiname":"Budanapitiya",
    "gn:country_code":"LK",
    "gn:dem":128,
    "gn:feature_class":"P",
    "gn:feature_code":"PPL",
    "gn:name":"Budanapitiya",
    "gn:population":0,
    "gn:timezone":"Asia/Colombo",
    "iso:country":"LK",
    "wof:name":"Budanapitiya",
    "wof:placetype":"locality"
},
  "geometry": {"coordinates":[80.3849,7.5421],"type":"Point"}
}