{
  "type": "Feature",
  "properties": {
    "gn:admin1_code":"33.0",
    "gn:asciiname":"Ambulugala",
    "gn:country_code":"LK",
    "gn:dem":318,
    "gn:feature_class":"P",
    "gn:feature_code":"PPL",
    "gn:name":"Ambulugala",
    "gn:population":0,
    "gn:timezone":"Asia/Colombo",
    "iso:country":"LK",
    "wof:name":"Ambulugala",
    "wof:placetype":"locality"
},
  "geometry": {"coordinates":[80.41679999999999,7.2376],"type":"Point"}
}