{
  "type": "Feature",
  "properties": {
    "gn:admin1_code":"36.0",
    "gn:asciiname":"Mahara Nugegoda",
    "gn:country_code":"LK",
    "gn:dem":38,
    "gn:feature_class":"P",
    "gn:feature_code":"PPL",
    "gn:name":"Mahara Nugegoda",
    "gn:population":0,
    "gn:timezone":"Asia/Colombo",
    "iso:country":"LK",
    "wof:name":"Mahara Nugegoda",
    "wof:placetype":"locality"
},
  "geometry": {"coordinates":[79.94459999999999,7.0179],"type":"Point"}
}