{
  "type": "Feature",
  "properties": {
    "gn:admin1_code":"35.0",
    "gn:asciiname":"Pansalwatta",
    "gn:country_code":"LK",
    "gn:dem":190,
    "gn:feature_class":"P",
    "gn:feature_code":"PPL",
    "gn:name":"Pansalwatta",
    "gn:population":0,
    "gn:timezone":"Asia/Colombo",
    "iso:country":"LK",
    "wof:name":"Pansalwatta",
    "wof:placetype":"locality"
},
  "geometry": {"coordinates":[81.4021,6.9889],"type":"Point"}
}