{
  "type": "Feature",
  "properties": {
    "gn:admin1_code":"33.0",
    "gn:asciiname":"Madagammana",
    "gn:country_code":"LK",
    "gn:dem":121,
    "gn:feature_class":"P",
    "gn:feature_code":"PPL",
    "gn:name":"Madagammana",
    "gn:population":0,
    "gn:timezone":"Asia/Colombo",
    "iso:country":"LK",
    "name:und_x_variant":[
        "Modagammena"
    ],
    "wof:name":"Madagammana",
    "wof:placetype":"locality"
},
  "geometry": {"coordinates":[80.2881,6.8775],"type":"Point"}
}