{
  "type": "Feature",
  "properties": {
    "gn:admin1_code":"35.0",
    "gn:asciiname":"Kivuleyaya",
    "gn:country_code":"LK",
    "gn:dem":97,
    "gn:feature_class":"P",
    "gn:feature_code":"PPL",
    "gn:name":"Kivuleyaya",
    "gn:population":0,
    "gn:timezone":"Asia/Colombo",
    "iso:country":"LK",
    "wof:name":"Kivuleyaya",
    "wof:placetype":"locality"
},
  "geometry": {"coordinates":[81.5213,6.9029],"type":"Point"}
}