{
  "type": "Feature",
  "properties": {
    "gn:admin1_code":"35.0",
    "gn:asciiname":"Hapugahawela",
    "gn:country_code":"LK",
    "gn:dem":495,
    "gn:feature_class":"P",
    "gn:feature_code":"PPL",
    "gn:name":"Hapugahawela",
    "gn:population":0,
    "gn:timezone":"Asia/Colombo",
    "iso:country":"LK",
    "wof:name":"Hapugahawela",
    "wof:placetype":"locality"
},
  "geometry": {"coordinates":[81.1718,6.854],"type":"Point"}
}