{
  "type": "Feature",
  "properties": {
    "gn:admin1_code":"36.0",
    "gn:asciiname":"Ekala",
    "gn:country_code":"LK",
    "gn:dem":14,
    "gn:feature_class":"P",
    "gn:feature_code":"PPL",
    "gn:name":"Ekala",
    "gn:population":0,
    "gn:timezone":"Asia/Colombo",
    "iso:country":"LK",
    "name:ceb_x_preferred":[
        "Ekala"
    ],
    "name:hin_x_preferred":[
        "\u090f\u0915\u093e\u0932\u093e"
    ],
    "name:msa_x_preferred":[
        "Ekala"
    ],
    "name:nep_x_preferred":[
        "\u090f\u0915\u093e\u0932\u093e"
    ],
    "name:new_x_preferred":[
        "\u090f\u0915\u093e\u0932\u093e"
    ],
    "name:pol_x_preferred":[
        "Ekala"
    ],
    "name:und_x_variant":[
        "Ekela"
    ],
    "wof:name":"Ekala",
    "wof:placetype":"locality"
},
  "geometry": {"coordinates":[79.913,7.099],"type":"Point"}
}