{
  "type": "Feature",
  "properties": {
    "gn:admin1_code":"30.0",
    "gn:asciiname":"Alutwewa",
    "gn:country_code":"LK",
    "gn:dem":118,
    "gn:feature_class":"P",
    "gn:feature_code":"PPL",
    "gn:name":"Alutwewa",
    "gn:population":0,
    "gn:timezone":"Asia/Colombo",
    "iso:country":"LK",
    "name:ceb_x_preferred":[
        "Alutwewa"
    ],
    "name:fas_x_preferred":[
        "\u0627\u0644\u0648\u062a\u0648\u06cc\u0648\u0627"
    ],
    "name:swe_x_preferred":[
        "Alutwewa"
    ],
    "wof:name":"Alutwewa",
    "wof:placetype":"locality"
},
  "geometry": {"coordinates":[80.45010000000001,8.1199],"type":"Point"}
}