{
  "type": "Feature",
  "properties": {
    "gn:admin1_code":"32.0",
    "gn:asciiname":"Nekattakehelpatanga",
    "gn:country_code":"LK",
    "gn:dem":155,
    "gn:feature_class":"P",
    "gn:feature_code":"PPL",
    "gn:name":"Nekattakehelpatanga",
    "gn:population":0,
    "gn:timezone":"Asia/Colombo",
    "iso:country":"LK",
    "name:und_x_variant":[
        "Nekatta Kehelpatange"
    ],
    "wof:name":"Nekattakehelpatanga",
    "wof:placetype":"locality"
},
  "geometry": {"coordinates":[80.4802,7.6226],"type":"Point"}
}