{
  "type": "Feature",
  "properties": {
    "iso:country":"LK",
    "name:bul_x_preferred":[
        "\u041f\u043e\u0442\u0443\u0432\u0438\u043b"
    ],
    "name:ceb_x_preferred":[
        "Pottuvil"
    ],
    "name:eng_x_preferred":[
        "Pottuvil"
    ],
    "name:hun_x_preferred":[
        "Pottuvil"
    ],
    "name:jpn_x_preferred":[
        "\u30dd\u30c8\u30a5\u30f4\u30a3\u30eb"
    ],
    "name:nld_x_preferred":[
        "Pottuvil"
    ],
    "name:rus_x_preferred":[
        "\u041f\u043e\u0442\u0442\u0443\u0432\u0438\u043b"
    ],
    "name:sin_x_preferred":[
        "\u0db4\u0ddc\u0dad\u0dd4\u0dc0\u0dd2\u0dbd\u0dca"
    ],
    "name:swe_x_preferred":[
        "Pottuvil"
    ],
    "name:tam_x_preferred":[
        "\u0baa\u0bca\u0ba4\u0bcd\u0ba4\u0bc1\u0bb5\u0bbf\u0bb2\u0bcd"
    ],
    "name:ukr_x_preferred":[
        "\u041f\u043e\u0442\u0442\u0443\u0432\u0456\u043b"
    ],
    "name:unk_x_variant":[
        "Pottuville"
    ],
    "name:zho_x_preferred":[
        "\u6ce2\u5716\u7dad\u52d2"
    ],
    "qs:gn_country":"LK",
    "qs:gn_fcode":"PPL",
    "qs:gn_pop":0,
    "qs:name":"Pottuvil",
    "qs:name_adm0":"Sri Lanka",
    "qs:name_adm1":"North Eastern",
    "qs:photos":451,
    "qs:photos_1k":91,
    "qs:photos_9k":2,
    "qs:photos_9r":5,
    "qs:photos_all":451,
    "qs:photos_sr":7,
    "qs:placetype":"Town",
    "qs:pop_sr":"6",
    "qs:woe_adm0":23424778,
    "wd:wordcount":76,
    "wof:name":"Pottuvil",
    "wof:placetype":"locality"
},
  "geometry": {"coordinates":[81.8267,6.8762],"type":"Point"}
}