{
  "type": "Feature",
  "properties": {
    "gn:admin1_code":"34.0",
    "gn:asciiname":"Wellaboda",
    "gn:country_code":"LK",
    "gn:dem":16,
    "gn:feature_class":"P",
    "gn:feature_code":"PPL",
    "gn:name":"Wellaboda",
    "gn:population":0,
    "gn:timezone":"Asia/Colombo",
    "iso:country":"LK",
    "wof:name":"Wellaboda",
    "wof:placetype":"locality"
},
  "geometry": {"coordinates":[80.148,6.0826],"type":"Point"}
}