{
  "type": "Feature",
  "properties": {
    "iso:country":"LK",
    "name:ces_x_preferred":[
        "Hikkaduwa"
    ],
    "name:deu_x_preferred":[
        "Hikkaduwa"
    ],
    "name:eng_x_preferred":[
        "Hikkaduwa"
    ],
    "name:fin_x_preferred":[
        "Hikkaduwa"
    ],
    "name:fra_x_preferred":[
        "Hikkaduwa"
    ],
    "name:ita_x_preferred":[
        "Hikkaduwa"
    ],
    "name:jpn_x_preferred":[
        "\u30d2\u30c3\u30ab\u30c9\u30a5\u30ef"
    ],
    "name:nld_x_preferred":[
        "Hikkaduwa"
    ],
    "name:nob_x_preferred":[
        "Hikkaduwa"
    ],
    "name:nor_x_preferred":[
        "Hikkaduwa"
    ],
    "name:rus_x_preferred":[
        "\u0425\u0438\u043a\u043a\u0430\u0434\u0443\u0432\u0430"
    ],
    "name:sin_x_preferred":[
        "\u0dc4\u0dd2\u0d9a\u0dca\u0d9a\u0da9\u0dd4\u0dc0"
    ],
    "name:spa_x_preferred":[
        "Hikkaduwa"
    ],
    "name:swe_x_preferred":[
        "Hikkaduwa"
    ],
    "name:tam_x_preferred":[
        "\u0b87\u0b95\u0bcd\u0b95\u0b9f\u0bc1\u0bb5\u0bc8"
    ],
    "name:zho_x_preferred":[
        "\u5e0c\u5361\u675c\u74e6"
    ],
    "qs:gn_country":"LK",
    "qs:gn_fcode":"PPL",
    "qs:gn_pop":1300,
    "qs:name":"Hikkaduwa",
    "qs:name_adm0":"Sri Lanka",
    "qs:name_adm1":"Southern",
    "qs:photos":679,
    "qs:photos_1k":138,
    "qs:photos_9k":3,
    "qs:photos_9r":5,
    "qs:photos_all":679,
    "qs:photos_sr":8,
    "qs:placetype":"Town",
    "qs:pop_sr":"3",
    "qs:woe_adm0":23424778,
    "wd:wordcount":307,
    "wof:name":"Hikkaduwa",
    "wof:placetype":"locality",
    "wof:population":1300
},
  "geometry": {"coordinates":[80.10120000000001,6.1407],"type":"Point"}
}