{
  "type": "Feature",
  "properties": {
    "gn:admin1_code":"38.0",
    "gn:asciiname":"Puliyadi Irakkam",
    "gn:country_code":"LK",
    "gn:dem":28,
    "gn:feature_class":"P",
    "gn:feature_code":"PPL",
    "gn:name":"Puliyadi Irakkam",
    "gn:population":0,
    "gn:timezone":"Asia/Colombo",
    "iso:country":"LK",
    "name:und_x_variant":[
        "Puliyadi Irakam",
        "Puliyadi Irakkam"
    ],
    "wof:name":"Puliyadi Irakkam",
    "wof:placetype":"locality"
},
  "geometry": {"coordinates":[80.1554,8.7684],"type":"Point"}
}