{
  "type": "Feature",
  "properties": {
    "gn:admin1_code":"29.0",
    "gn:asciiname":"Weliwita",
    "gn:country_code":"LK",
    "gn:dem":150,
    "gn:feature_class":"P",
    "gn:feature_code":"PPL",
    "gn:name":"Weliwita",
    "gn:population":0,
    "gn:timezone":"Asia/Colombo",
    "iso:country":"LK",
    "wof:name":"Weliwita",
    "wof:placetype":"locality"
},
  "geometry": {"coordinates":[80.8485,7.58947],"type":"Point"}
}