{
  "type": "Feature",
  "properties": {
    "gn:admin1_code":"30.0",
    "gn:asciiname":"Ihala Kitulhitiyawa",
    "gn:country_code":"LK",
    "gn:dem":175,
    "gn:feature_class":"P",
    "gn:feature_code":"PPL",
    "gn:name":"Ihala Kitulhitiyawa",
    "gn:population":0,
    "gn:timezone":"Asia/Colombo",
    "iso:country":"LK",
    "wof:name":"Ihala Kitulhitiyawa",
    "wof:placetype":"locality"
},
  "geometry": {"coordinates":[80.6467,7.9323],"type":"Point"}
}