{
  "type": "Feature",
  "properties": {
    "gn:admin1_code":"32.0",
    "gn:asciiname":"Pimburuwellegama",
    "gn:country_code":"LK",
    "gn:dem":121,
    "gn:feature_class":"P",
    "gn:feature_code":"PPL",
    "gn:name":"Pimburuwellegama",
    "gn:population":0,
    "gn:timezone":"Asia/Colombo",
    "iso:country":"LK",
    "wof:name":"Pimburuwellegama",
    "wof:placetype":"locality"
},
  "geometry": {"coordinates":[80.36667,7.85],"type":"Point"}
}