{
  "type": "Feature",
  "properties": {
    "gn:admin1_code":"36.0",
    "gn:asciiname":"Tharala",
    "gn:country_code":"LK",
    "gn:dem":29,
    "gn:feature_class":"P",
    "gn:feature_code":"PPL",
    "gn:name":"Tharala",
    "gn:population":0,
    "gn:timezone":"Asia/Colombo",
    "iso:country":"LK",
    "name:und_x_variant":[
        "Tarala",
        "Tharala",
        "Tarale"
    ],
    "wof:name":"Tharala",
    "wof:placetype":"locality"
},
  "geometry": {"coordinates":[80.146,6.9768],"type":"Point"}
}