{
  "type": "Feature",
  "properties": {
    "gn:admin1_code":"32.0",
    "gn:asciiname":"Sadaranagama",
    "gn:country_code":"LK",
    "gn:dem":86,
    "gn:feature_class":"P",
    "gn:feature_code":"PPL",
    "gn:name":"Sadaranagama",
    "gn:population":0,
    "gn:timezone":"Asia/Colombo",
    "iso:country":"LK",
    "wof:name":"Sadaranagama",
    "wof:placetype":"locality"
},
  "geometry": {"coordinates":[80.2119,8.0072],"type":"Point"}
}