{
  "type": "Feature",
  "properties": {
    "gn:admin1_code":"29.0",
    "gn:asciiname":"Maraka",
    "gn:country_code":"LK",
    "gn:dem":74,
    "gn:feature_class":"P",
    "gn:feature_code":"PPL",
    "gn:name":"Maraka",
    "gn:population":0,
    "gn:timezone":"Asia/Colombo",
    "iso:country":"LK",
    "wof:name":"Maraka",
    "wof:placetype":"locality"
},
  "geometry": {"coordinates":[80.96666999999999,7.58333],"type":"Point"}
}