{
  "type": "Feature",
  "properties": {
    "gn:admin1_code":"35.0",
    "gn:asciiname":"Gonamutawa",
    "gn:country_code":"LK",
    "gn:dem":1371,
    "gn:feature_class":"P",
    "gn:feature_code":"PPL",
    "gn:name":"Gonamutawa",
    "gn:population":0,
    "gn:timezone":"Asia/Colombo",
    "iso:country":"LK",
    "wof:name":"Gonamutawa",
    "wof:placetype":"locality"
},
  "geometry": {"coordinates":[81.0128,6.8171],"type":"Point"}
}