{
  "type": "Feature",
  "properties": {
    "gn:admin1_code":"29.0",
    "gn:asciiname":"Otagama",
    "gn:country_code":"LK",
    "gn:dem":627,
    "gn:feature_class":"P",
    "gn:feature_code":"PPL",
    "gn:name":"Otagama",
    "gn:population":0,
    "gn:timezone":"Asia/Colombo",
    "iso:country":"LK",
    "wof:name":"Otagama",
    "wof:placetype":"locality"
},
  "geometry": {"coordinates":[80.88333,7.28333],"type":"Point"}
}