{
  "type": "Feature",
  "properties": {
    "gn:admin1_code":"32.0",
    "gn:asciiname":"Gampola Radawewa",
    "gn:country_code":"LK",
    "gn:dem":94,
    "gn:feature_class":"P",
    "gn:feature_code":"PPL",
    "gn:name":"Gampola Radawewa",
    "gn:population":0,
    "gn:timezone":"Asia/Colombo",
    "iso:country":"LK",
    "wof:name":"Gampola Radawewa",
    "wof:placetype":"locality"
},
  "geometry": {"coordinates":[80.191,8.0748],"type":"Point"}
}