{
  "type": "Feature",
  "properties": {
    "gn:admin1_code":"29.0",
    "gn:asciiname":"Ambanpola",
    "gn:country_code":"LK",
    "gn:dem":504,
    "gn:feature_class":"P",
    "gn:feature_code":"PPL",
    "gn:name":"Ambanpola",
    "gn:population":0,
    "gn:timezone":"Asia/Colombo",
    "iso:country":"LK",
    "wof:name":"Ambanpola",
    "wof:placetype":"locality"
},
  "geometry": {"coordinates":[80.57210000000001,7.5496],"type":"Point"}
}