{
  "type": "Feature",
  "properties": {
    "gn:admin1_code":"32.0",
    "gn:asciiname":"Yantampola",
    "gn:country_code":"LK",
    "gn:dem":103,
    "gn:feature_class":"P",
    "gn:feature_code":"PPL",
    "gn:name":"Yantampola",
    "gn:population":0,
    "gn:timezone":"Asia/Colombo",
    "iso:country":"LK",
    "wof:name":"Yantampola",
    "wof:placetype":"locality"
},
  "geometry": {"coordinates":[80.28333000000001,7.46667],"type":"Point"}
}