{
  "type": "Feature",
  "properties": {
    "gn:admin1_code":"32.0",
    "gn:asciiname":"Iranawila",
    "gn:country_code":"LK",
    "gn:dem":11,
    "gn:feature_class":"P",
    "gn:feature_code":"PPL",
    "gn:name":"Iranawila",
    "gn:population":0,
    "gn:timezone":"Asia/Colombo",
    "iso:country":"LK",
    "name:und_x_variant":[
        "Iranavila",
        "Iranawila"
    ],
    "wof:name":"Iranawila",
    "wof:placetype":"locality"
},
  "geometry": {"coordinates":[79.8075,7.4955],"type":"Point"}
}