{
  "type": "Feature",
  "properties": {
    "gn:admin1_code":"32.0",
    "gn:asciiname":"Anawilundawa",
    "gn:country_code":"LK",
    "gn:dem":10,
    "gn:feature_class":"P",
    "gn:feature_code":"PPL",
    "gn:name":"Anawilundawa",
    "gn:population":0,
    "gn:timezone":"Asia/Colombo",
    "iso:country":"LK",
    "name:und_x_variant":[
        "Annaiwilundawa",
        "Anaivilundawa",
        "Anawilundawa"
    ],
    "wof:name":"Anawilundawa",
    "wof:placetype":"locality"
},
  "geometry": {"coordinates":[79.8262,7.7052],"type":"Point"}
}