{
  "type": "Feature",
  "properties": {
    "gn:admin1_code":"32.0",
    "gn:asciiname":"Ihala Kuruketiyawa",
    "gn:country_code":"LK",
    "gn:dem":58,
    "gn:feature_class":"P",
    "gn:feature_code":"PPL",
    "gn:name":"Ihala Kuruketiyawa",
    "gn:population":0,
    "gn:timezone":"Asia/Colombo",
    "iso:country":"LK",
    "name:und_x_variant":[
        "Kuruketiyawa"
    ],
    "wof:name":"Ihala Kuruketiyawa",
    "wof:placetype":"locality"
},
  "geometry": {"coordinates":[80.0513,8.0246],"type":"Point"}
}