{
  "type": "Feature",
  "properties": {
    "gn:admin1_code":"36.0",
    "gn:asciiname":"Ramukkana",
    "gn:country_code":"LK",
    "gn:dem":14,
    "gn:feature_class":"P",
    "gn:feature_code":"PPL",
    "gn:name":"Ramukkana",
    "gn:population":0,
    "gn:timezone":"Asia/Colombo",
    "iso:country":"LK",
    "name:und_x_variant":[
        "Rambukkana",
        "Ramukkana",
        "Rammukkana"
    ],
    "wof:name":"Ramukkana",
    "wof:placetype":"locality"
},
  "geometry": {"coordinates":[79.9823,6.7072],"type":"Point"}
}