{
  "type": "Feature",
  "properties": {
    "gn:admin1_code":"30.0",
    "gn:asciiname":"Kudawewa",
    "gn:country_code":"LK",
    "gn:dem":163,
    "gn:feature_class":"P",
    "gn:feature_code":"PPL",
    "gn:name":"Kudawewa",
    "gn:population":0,
    "gn:timezone":"Asia/Colombo",
    "iso:country":"LK",
    "wof:name":"Kudawewa",
    "wof:placetype":"locality"
},
  "geometry": {"coordinates":[80.65000000000001,8.01667],"type":"Point"}
}