{
  "type": "Feature",
  "properties": {
    "gn:admin1_code":"32.0",
    "gn:asciiname":"Wetiya",
    "gn:country_code":"LK",
    "gn:dem":46,
    "gn:feature_class":"P",
    "gn:feature_code":"PPL",
    "gn:name":"Wetiya",
    "gn:population":0,
    "gn:timezone":"Asia/Colombo",
    "iso:country":"LK",
    "wof:name":"Wetiya",
    "wof:placetype":"locality"
},
  "geometry": {"coordinates":[79.98569999999999,7.7525],"type":"Point"}
}