{
  "type": "Feature",
  "properties": {
    "gn:admin1_code":"32.0",
    "gn:asciiname":"Bujjamuwa",
    "gn:country_code":"LK",
    "gn:dem":30,
    "gn:feature_class":"P",
    "gn:feature_code":"PPL",
    "gn:name":"Bujjamuwa",
    "gn:population":0,
    "gn:timezone":"Asia/Colombo",
    "iso:country":"LK",
    "wof:name":"Bujjamuwa",
    "wof:placetype":"locality"
},
  "geometry": {"coordinates":[80.05,7.55],"type":"Point"}
}