{
  "type": "Feature",
  "properties": {
    "gn:admin1_code":"35.0",
    "gn:asciiname":"Pattiyalanda",
    "gn:country_code":"LK",
    "gn:dem":161,
    "gn:feature_class":"P",
    "gn:feature_code":"PPL",
    "gn:name":"Pattiyalanda",
    "gn:population":0,
    "gn:timezone":"Asia/Colombo",
    "iso:country":"LK",
    "wof:name":"Pattiyalanda",
    "wof:placetype":"locality"
},
  "geometry": {"coordinates":[81.3357,6.8675],"type":"Point"}
}