{
  "type": "Feature",
  "properties": {
    "gn:admin1_code":"29.0",
    "gn:asciiname":"Polwatta Colony",
    "gn:country_code":"LK",
    "gn:dem":569,
    "gn:feature_class":"P",
    "gn:feature_code":"PPL",
    "gn:name":"Polwatta Colony",
    "gn:population":0,
    "gn:timezone":"Asia/Colombo",
    "iso:country":"LK",
    "wof:name":"Polwatta Colony",
    "wof:placetype":"locality"
},
  "geometry": {"coordinates":[80.67270000000001,7.5376],"type":"Point"}
}