{
  "type": "Feature",
  "properties": {
    "gn:admin1_code":"29.0",
    "gn:asciiname":"Matalapitiya",
    "gn:country_code":"LK",
    "gn:dem":561,
    "gn:feature_class":"P",
    "gn:feature_code":"PPL",
    "gn:name":"Matalapitiya",
    "gn:population":0,
    "gn:timezone":"Asia/Colombo",
    "iso:country":"LK",
    "name:ceb_x_preferred":[
        "Matalapitiya"
    ],
    "name:swe_x_preferred":[
        "Matalapitiya"
    ],
    "wof:name":"Matalapitiya",
    "wof:placetype":"locality"
},
  "geometry": {"coordinates":[80.5784,7.5175],"type":"Point"}
}