{
  "type": "Feature",
  "properties": {
    "gn:admin1_code":"32.0",
    "gn:asciiname":"Mahadivullewa",
    "gn:country_code":"LK",
    "gn:dem":77,
    "gn:feature_class":"P",
    "gn:feature_code":"PPL",
    "gn:name":"Mahadivullewa",
    "gn:population":0,
    "gn:timezone":"Asia/Colombo",
    "iso:country":"LK",
    "wof:name":"Mahadivullewa",
    "wof:placetype":"locality"
},
  "geometry": {"coordinates":[80.1893,7.921],"type":"Point"}
}