{
  "type": "Feature",
  "properties": {
    "gn:admin1_code":"33.0",
    "gn:asciiname":"Asselimulla",
    "gn:country_code":"LK",
    "gn:dem":102,
    "gn:feature_class":"P",
    "gn:feature_code":"PPL",
    "gn:name":"Asselimulla",
    "gn:population":0,
    "gn:timezone":"Asia/Colombo",
    "iso:country":"LK",
    "wof:name":"Asselimulla",
    "wof:placetype":"locality"
},
  "geometry": {"coordinates":[80.2585,7.212],"type":"Point"}
}