{
  "type": "Feature",
  "properties": {
    "gn:admin1_code":"29.0",
    "gn:asciiname":"Kosgama",
    "gn:country_code":"LK",
    "gn:dem":686,
    "gn:feature_class":"P",
    "gn:feature_code":"PPL",
    "gn:name":"Kosgama",
    "gn:population":0,
    "gn:timezone":"Asia/Colombo",
    "iso:country":"LK",
    "name:ceb_x_preferred":[
        "Kosgama"
    ],
    "name:sin_x_preferred":[
        "\u0d9a\u0ddc\u0dc3\u0dca\u0d9c\u0db8"
    ],
    "name:swe_x_preferred":[
        "Kosgama"
    ],
    "wof:name":"Kosgama",
    "wof:placetype":"locality"
},
  "geometry": {"coordinates":[80.7448,7.3989],"type":"Point"}
}