{
  "type": "Feature",
  "properties": {
    "gn:admin1_code":"34.0",
    "gn:asciiname":"Diyadawa",
    "gn:country_code":"LK",
    "gn:dem":143,
    "gn:feature_class":"P",
    "gn:feature_code":"PPL",
    "gn:name":"Diyadawa",
    "gn:population":0,
    "gn:timezone":"Asia/Colombo",
    "iso:country":"LK",
    "wof:name":"Diyadawa",
    "wof:placetype":"locality"
},
  "geometry": {"coordinates":[80.5497,6.3159],"type":"Point"}
}