{
  "type": "Feature",
  "properties": {
    "gn:admin1_code":"33.0",
    "gn:asciiname":"Tambadiya",
    "gn:country_code":"LK",
    "gn:dem":94,
    "gn:feature_class":"P",
    "gn:feature_code":"PPL",
    "gn:name":"Tambadiya",
    "gn:population":0,
    "gn:timezone":"Asia/Colombo",
    "iso:country":"LK",
    "wof:name":"Tambadiya",
    "wof:placetype":"locality"
},
  "geometry": {"coordinates":[80.2666,7.1489],"type":"Point"}
}