{
  "type": "Feature",
  "properties": {
    "gn:admin1_code":"34.0",
    "gn:asciiname":"Badungoda Colony",
    "gn:country_code":"LK",
    "gn:dem":15,
    "gn:feature_class":"P",
    "gn:feature_code":"PPL",
    "gn:name":"Badungoda Colony",
    "gn:population":0,
    "gn:timezone":"Asia/Colombo",
    "iso:country":"LK",
    "wof:name":"Badungoda Colony",
    "wof:placetype":"locality"
},
  "geometry": {"coordinates":[80.241,6.0567],"type":"Point"}
}