{
  "type": "Feature",
  "properties": {
    "gn:admin1_code":"32.0",
    "gn:asciiname":"Inigodawela",
    "gn:country_code":"LK",
    "gn:dem":8,
    "gn:feature_class":"P",
    "gn:feature_code":"PPL",
    "gn:name":"Inigodawela",
    "gn:population":0,
    "gn:timezone":"Asia/Colombo",
    "iso:country":"LK",
    "wof:name":"Inigodawela",
    "wof:placetype":"locality"
},
  "geometry": {"coordinates":[79.8083,7.5498],"type":"Point"}
}