{
  "type": "Feature",
  "properties": {
    "gn:admin1_code":"32.0",
    "gn:asciiname":"Morathiha Viharagama",
    "gn:country_code":"LK",
    "gn:dem":157,
    "gn:feature_class":"P",
    "gn:feature_code":"PPL",
    "gn:name":"Morathiha Viharagama",
    "gn:population":0,
    "gn:timezone":"Asia/Colombo",
    "iso:country":"LK",
    "name:und_x_variant":[
        "Moratihe Viharagama"
    ],
    "wof:name":"Morathiha Viharagama",
    "wof:placetype":"locality"
},
  "geometry": {"coordinates":[80.4875,7.5073],"type":"Point"}
}