{
  "type": "Feature",
  "properties": {
    "gn:admin1_code":"35.0",
    "gn:asciiname":"Weragama",
    "gn:country_code":"LK",
    "gn:dem":772,
    "gn:feature_class":"P",
    "gn:feature_code":"PPL",
    "gn:name":"Weragama",
    "gn:population":0,
    "gn:timezone":"Asia/Colombo",
    "iso:country":"LK",
    "name:ceb_x_preferred":[
        "Weragama"
    ],
    "name:swe_x_preferred":[
        "Weragama"
    ],
    "wof:name":"Weragama",
    "wof:placetype":"locality"
},
  "geometry": {"coordinates":[80.9798,6.96],"type":"Point"}
}