{
  "type": "Feature",
  "properties": {
    "gn:admin1_code":"37.0",
    "gn:asciiname":"Akkuranai",
    "gn:country_code":"LK",
    "gn:dem":22,
    "gn:feature_class":"P",
    "gn:feature_code":"PPL",
    "gn:name":"Akkuranai",
    "gn:population":0,
    "gn:timezone":"Asia/Colombo",
    "iso:country":"LK",
    "name:und_x_variant":[
        "Akaranai",
        "Akkuranai"
    ],
    "wof:name":"Akkuranai",
    "wof:placetype":"locality"
},
  "geometry": {"coordinates":[81.38333,7.91667],"type":"Point"}
}