{
  "type": "Feature",
  "properties": {
    "gn:admin1_code":"38.0",
    "gn:asciiname":"Uyilankulam",
    "gn:country_code":"LK",
    "gn:dem":35,
    "gn:feature_class":"P",
    "gn:feature_code":"PPL",
    "gn:name":"Uyilankulam",
    "gn:population":0,
    "gn:timezone":"Asia/Colombo",
    "iso:country":"LK",
    "name:tam_x_preferred":[
        "\u0b89\u0baf\u0bbf\u0bb2\u0b99\u0bcd\u0b95\u0bc1\u0bb3\u0bae\u0bcd"
    ],
    "wof:name":"Uyilankulam",
    "wof:placetype":"locality"
},
  "geometry": {"coordinates":[80.26666999999998,9.18333],"type":"Point"}
}