{
  "type": "Feature",
  "properties": {
    "gn:asciiname":"Dimbulagala Raja Maha Vihara",
    "gn:country_code":"LK",
    "gn:dem":64,
    "gn:feature_class":"P",
    "gn:feature_code":"PPL",
    "gn:name":"Dimbulagala Raja Maha Vihara",
    "gn:population":0,
    "gn:timezone":"Asia/Colombo",
    "iso:country":"LK",
    "name:sin_x_preferred":[
        "\u0daf\u0dd2\u0db9\u0dd4\u0dbd\u0dcf\u0d9c\u0dbd \u0dbb\u0da2 \u0db8\u0dc4\u0dcf \u0dc0\u0dd2\u0dc4\u0dcf\u0dbb\u0dba"
    ],
    "name:tam_x_preferred":[
        "\u0ba4\u0bbf\u0bae\u0bcd\u0baa\u0bc1\u0bb2\u0bbe\u0b95\u0bb2\u0bc8 \u0bb0\u0b9c \u0bae\u0b95\u0bbe \u0bb5\u0bbf\u0b95\u0bbe\u0bb0\u0bc8"
    ],
    "wof:name":"Dimbulagala Raja Maha Vihara",
    "wof:placetype":"locality"
},
  "geometry": {"coordinates":[81.11667,7.86667],"type":"Point"}
}