{
  "type": "Feature",
  "properties": {
    "gn:admin1_code":"37.0",
    "gn:asciiname":"Vellaiyadimadu",
    "gn:country_code":"LK",
    "gn:dem":9,
    "gn:feature_class":"P",
    "gn:feature_code":"PPL",
    "gn:name":"Vellaiyadimadu",
    "gn:population":0,
    "gn:timezone":"Asia/Colombo",
    "iso:country":"LK",
    "wof:name":"Vellaiyadimadu",
    "wof:placetype":"locality"
},
  "geometry": {"coordinates":[81.43333,8.11667],"type":"Point"}
}