{
  "type": "Feature",
  "properties": {
    "gn:admin1_code":"29.0",
    "gn:asciiname":"Etanwela",
    "gn:country_code":"LK",
    "gn:dem":652,
    "gn:feature_class":"P",
    "gn:feature_code":"PPL",
    "gn:name":"Etanwela",
    "gn:population":0,
    "gn:timezone":"Asia/Colombo",
    "iso:country":"LK",
    "name:und_x_variant":[
        "Etanwala",
        "Etanwela"
    ],
    "wof:name":"Etanwela",
    "wof:placetype":"locality"
},
  "geometry": {"coordinates":[80.75660000000001,7.5153],"type":"Point"}
}