{
  "type": "Feature",
  "properties": {
    "gn:admin1_code":"33.0",
    "gn:asciiname":"Udakanda",
    "gn:country_code":"LK",
    "gn:dem":534,
    "gn:feature_class":"P",
    "gn:feature_code":"PPL",
    "gn:name":"Udakanda",
    "gn:population":0,
    "gn:timezone":"Asia/Colombo",
    "iso:country":"LK",
    "wof:name":"Udakanda",
    "wof:placetype":"locality"
},
  "geometry": {"coordinates":[80.69410000000001,6.6481],"type":"Point"}
}