{
  "type": "Feature",
  "properties": {
    "iso:country":"LK",
    "qs:gn_country":"LK",
    "qs:gn_fcode":"PPLX",
    "qs:gn_pop":0,
    "qs:name":"Grandpass",
    "qs:name_adm0":"Sri Lanka",
    "qs:name_adm1":"Western",
    "qs:photos":1,
    "qs:photos_1k":1,
    "qs:photos_9k":1,
    "qs:photos_9r":1,
    "qs:photos_all":1,
    "qs:photos_sr":1,
    "qs:placetype":"Suburb",
    "qs:pop_sr":"0",
    "qs:woe_adm0":23424778,
    "wd:wordcount":85,
    "wof:name":"Grandpass",
    "wof:placetype":"neighbourhood"
},
  "geometry": {"coordinates":[79.87639,6.95722],"type":"Point"}
}