{
  "type": "Feature",
  "properties": {
    "gn:admin1_code":"38.0",
    "gn:asciiname":"Ganeshapuram",
    "gn:country_code":"LK",
    "gn:dem":95,
    "gn:feature_class":"P",
    "gn:feature_code":"PPL",
    "gn:name":"Ganeshapuram",
    "gn:population":0,
    "gn:timezone":"Asia/Colombo",
    "iso:country":"LK",
    "wof:name":"Ganeshapuram",
    "wof:placetype":"locality"
},
  "geometry": {"coordinates":[80.4529,8.7766],"type":"Point"}
}