{
  "type": "Feature",
  "properties": {
    "gn:admin1_code":"29.0",
    "gn:asciiname":"Embilimigama",
    "gn:country_code":"LK",
    "gn:dem":501,
    "gn:feature_class":"P",
    "gn:feature_code":"PPL",
    "gn:name":"Embilimigama",
    "gn:population":0,
    "gn:timezone":"Asia/Colombo",
    "iso:country":"LK",
    "name:und_x_variant":[
        "Embilmeegama",
        "Embilimigama"
    ],
    "wof:name":"Embilimigama",
    "wof:placetype":"locality"
},
  "geometry": {"coordinates":[80.56229999999999,7.2661],"type":"Point"}
}