{
  "type": "Feature",
  "properties": {
    "gn:admin1_code":"32.0",
    "gn:asciiname":"Gonalagama",
    "gn:country_code":"LK",
    "gn:dem":137,
    "gn:feature_class":"P",
    "gn:feature_code":"PPL",
    "gn:name":"Gonalagama",
    "gn:population":0,
    "gn:timezone":"Asia/Colombo",
    "iso:country":"LK",
    "wof:name":"Gonalagama",
    "wof:placetype":"locality"
},
  "geometry": {"coordinates":[80.41667,7.91667],"type":"Point"}
}