{
  "type": "Feature",
  "properties": {
    "gn:admin1_code":"32.0",
    "gn:asciiname":"Galdeniyagama",
    "gn:cc2":"LK",
    "gn:country_code":"LK",
    "gn:dem":46,
    "gn:feature_class":"P",
    "gn:feature_code":"PPL",
    "gn:name":"Galdeniyagama",
    "gn:population":0,
    "gn:timezone":"Asia/Colombo",
    "iso:country":"LK",
    "name:und_x_variant":[
        "Galadenigama",
        "Galdeniyagama"
    ],
    "wof:name":"Galdeniyagama",
    "wof:placetype":"locality"
},
  "geometry": {"coordinates":[80.05,7.68333],"type":"Point"}
}