{
  "type": "Feature",
  "properties": {
    "gn:admin1_code":"32.0",
    "gn:asciiname":"Koswattapitiya",
    "gn:country_code":"LK",
    "gn:dem":93,
    "gn:feature_class":"P",
    "gn:feature_code":"PPL",
    "gn:name":"Koswattapitiya",
    "gn:population":0,
    "gn:timezone":"Asia/Colombo",
    "iso:country":"LK",
    "wof:name":"Koswattapitiya",
    "wof:placetype":"locality"
},
  "geometry": {"coordinates":[80.2576,7.6527],"type":"Point"}
}