{
  "type": "Feature",
  "properties": {
    "gn:admin1_code":"29.0",
    "gn:asciiname":"Sagarapura Colony",
    "gn:country_code":"LK",
    "gn:dem":1569,
    "gn:feature_class":"P",
    "gn:feature_code":"PPL",
    "gn:name":"Sagarapura Colony",
    "gn:population":0,
    "gn:timezone":"Asia/Colombo",
    "iso:country":"LK",
    "wof:name":"Sagarapura Colony",
    "wof:placetype":"locality"
},
  "geometry": {"coordinates":[80.8443,7.061],"type":"Point"}
}