{
  "type": "Feature",
  "properties": {
    "gn:asciiname":"Werellapathana",
    "gn:country_code":"LK",
    "gn:dem":1236,
    "gn:feature_class":"P",
    "gn:feature_code":"PPL",
    "gn:name":"Werellapathana",
    "gn:population":0,
    "gn:timezone":"Asia/Colombo",
    "iso:country":"LK",
    "wof:name":"Werellapathana",
    "wof:placetype":"locality"
},
  "geometry": {"coordinates":[80.94525,6.79438],"type":"Point"}
}