{
  "type": "Feature",
  "properties": {
    "gn:admin1_code":"35.0",
    "gn:asciiname":"Kirioruwa",
    "gn:country_code":"LK",
    "gn:dem":1346,
    "gn:feature_class":"P",
    "gn:feature_code":"PPL",
    "gn:name":"Kirioruwa",
    "gn:population":0,
    "gn:timezone":"Asia/Colombo",
    "iso:country":"LK",
    "wof:name":"Kirioruwa",
    "wof:placetype":"locality"
},
  "geometry": {"coordinates":[81.002,6.8694],"type":"Point"}
}