{
  "type": "Feature",
  "properties": {
    "gn:admin1_code":"37.0",
    "gn:asciiname":"Thimilatheevu",
    "gn:country_code":"LK",
    "gn:dem":6,
    "gn:feature_class":"P",
    "gn:feature_code":"PPL",
    "gn:name":"Thimilatheevu",
    "gn:population":0,
    "gn:timezone":"Asia/Colombo",
    "iso:country":"LK",
    "name:und_x_variant":[
        "Thimilativu",
        "Timilativu",
        "Thimilatheevu"
    ],
    "wof:name":"Thimilatheevu",
    "wof:placetype":"locality"
},
  "geometry": {"coordinates":[81.6782,7.6951],"type":"Point"}
}