{
  "type": "Feature",
  "properties": {
    "gn:admin1_code":"32.0",
    "gn:asciiname":"Badalgama Ihala",
    "gn:country_code":"LK",
    "gn:dem":62,
    "gn:feature_class":"P",
    "gn:feature_code":"PPL",
    "gn:name":"Badalgama Ihala",
    "gn:population":0,
    "gn:timezone":"Asia/Colombo",
    "iso:country":"LK",
    "name:und_x_variant":[
        "Badalgama",
        "Badalgama Ihala",
        "Ihala Badalgama"
    ],
    "wof:name":"Badalgama Ihala",
    "wof:placetype":"locality"
},
  "geometry": {"coordinates":[80.1666,7.5915],"type":"Point"}
}