{
  "type": "Feature",
  "properties": {
    "gn:admin1_code":"38.0",
    "gn:admin2_code":"1236148.0",
    "gn:asciiname":"Karikkamurippu",
    "gn:country_code":"LK",
    "gn:dem":8,
    "gn:feature_class":"P",
    "gn:feature_code":"PPL",
    "gn:name":"Karikkamurippu",
    "gn:population":0,
    "gn:timezone":"Asia/Colombo",
    "iso:country":"LK",
    "wof:name":"Karikkamurippu",
    "wof:placetype":"locality"
},
  "geometry": {"coordinates":[79.95039,8.8375],"type":"Point"}
}