{
  "type": "Feature",
  "properties": {
    "gn:admin1_code":"37.0",
    "gn:asciiname":"Karaichchitidal",
    "gn:country_code":"LK",
    "gn:dem":4,
    "gn:feature_class":"P",
    "gn:feature_code":"PPL",
    "gn:name":"Karaichchitidal",
    "gn:population":0,
    "gn:timezone":"Asia/Colombo",
    "iso:country":"LK",
    "wof:name":"Karaichchitidal",
    "wof:placetype":"locality"
},
  "geometry": {"coordinates":[81.117,8.4831],"type":"Point"}
}