{
  "type": "Feature",
  "properties": {
    "gn:admin1_code":"32.0",
    "gn:asciiname":"Kurundulla",
    "gn:country_code":"LK",
    "gn:dem":83,
    "gn:feature_class":"P",
    "gn:feature_code":"PPL",
    "gn:name":"Kurundulla",
    "gn:population":0,
    "gn:timezone":"Asia/Colombo",
    "iso:country":"LK",
    "wof:name":"Kurundulla",
    "wof:placetype":"locality"
},
  "geometry": {"coordinates":[80.34269999999999,7.6714],"type":"Point"}
}