{
  "type": "Feature",
  "properties": {
    "gn:admin1_code":"31.0",
    "gn:asciiname":"Galmeda",
    "gn:country_code":"LK",
    "gn:dem":81,
    "gn:feature_class":"P",
    "gn:feature_code":"PPL",
    "gn:name":"Galmeda",
    "gn:population":0,
    "gn:timezone":"Asia/Colombo",
    "iso:country":"LK",
    "wof:name":"Galmeda",
    "wof:placetype":"locality"
},
  "geometry": {"coordinates":[81.46666999999999,7.45],"type":"Point"}
}