{
  "type": "Feature",
  "properties": {
    "gn:admin1_code":"38.0",
    "gn:asciiname":"Chavirikkulam",
    "gn:country_code":"LK",
    "gn:dem":6,
    "gn:feature_class":"P",
    "gn:feature_code":"PPL",
    "gn:name":"Chavirikkulam",
    "gn:population":0,
    "gn:timezone":"Asia/Colombo",
    "iso:country":"LK",
    "wof:name":"Chavirikkulam",
    "wof:placetype":"locality"
},
  "geometry": {"coordinates":[80.06667,9.03333],"type":"Point"}
}