{
  "type": "Feature",
  "properties": {
    "gn:admin1_code":"33.0",
    "gn:asciiname":"Pallekumbura",
    "gn:country_code":"LK",
    "gn:dem":491,
    "gn:feature_class":"P",
    "gn:feature_code":"PPL",
    "gn:name":"Pallekumbura",
    "gn:population":0,
    "gn:timezone":"Asia/Colombo",
    "iso:country":"LK",
    "wof:name":"Pallekumbura",
    "wof:placetype":"locality"
},
  "geometry": {"coordinates":[80.70399999999999,6.6418],"type":"Point"}
}