{
  "type": "Feature",
  "properties": {
    "gn:admin1_code":"38.0",
    "gn:asciiname":"Uriyan",
    "gn:country_code":"LK",
    "gn:dem":5,
    "gn:feature_class":"P",
    "gn:feature_code":"PPL",
    "gn:name":"Uriyan",
    "gn:population":0,
    "gn:timezone":"Asia/Colombo",
    "iso:country":"LK",
    "wof:name":"Uriyan",
    "wof:placetype":"locality"
},
  "geometry": {"coordinates":[80.4554,9.4754],"type":"Point"}
}