{
  "type": "Feature",
  "properties": {
    "gn:admin1_code":"36.0",
    "gn:asciiname":"Kelesgamuwa",
    "gn:country_code":"LK",
    "gn:dem":22,
    "gn:feature_class":"P",
    "gn:feature_code":"PPL",
    "gn:name":"Kelesgamuwa",
    "gn:population":0,
    "gn:timezone":"Asia/Colombo",
    "iso:country":"LK",
    "wof:name":"Kelesgamuwa",
    "wof:placetype":"locality"
},
  "geometry": {"coordinates":[80.03579999999999,6.6988],"type":"Point"}
}