{
  "type": "Feature",
  "properties": {
    "gn:admin1_code":"30.0",
    "gn:asciiname":"Maha Migaskada",
    "gn:country_code":"LK",
    "gn:dem":118,
    "gn:feature_class":"P",
    "gn:feature_code":"PPL",
    "gn:name":"Maha Migaskada",
    "gn:population":0,
    "gn:timezone":"Asia/Colombo",
    "iso:country":"LK",
    "wof:name":"Maha Migaskada",
    "wof:placetype":"locality"
},
  "geometry": {"coordinates":[80.5705,8.6719],"type":"Point"}
}