{
  "type": "Feature",
  "properties": {
    "gn:admin1_code":"32.0",
    "gn:asciiname":"Hidawa",
    "gn:country_code":"LK",
    "gn:dem":55,
    "gn:feature_class":"P",
    "gn:feature_code":"PPL",
    "gn:name":"Hidawa",
    "gn:population":0,
    "gn:timezone":"Asia/Colombo",
    "iso:country":"LK",
    "wof:name":"Hidawa",
    "wof:placetype":"locality"
},
  "geometry": {"coordinates":[80.13720000000001,7.5156],"type":"Point"}
}