{
  "type": "Feature",
  "properties": {
    "gn:admin1_code":"38.0",
    "gn:asciiname":"Nakattaivu",
    "gn:country_code":"LK",
    "gn:dem":7,
    "gn:feature_class":"P",
    "gn:feature_code":"PPL",
    "gn:name":"Nakattaivu",
    "gn:population":0,
    "gn:timezone":"Asia/Colombo",
    "iso:country":"LK",
    "name:und_x_variant":[
        "Nakattalvu",
        "Nakattaivu"
    ],
    "wof:name":"Nakattaivu",
    "wof:placetype":"locality"
},
  "geometry": {"coordinates":[80.08333,9.06667],"type":"Point"}
}