{
  "type": "Feature",
  "properties": {
    "gn:admin1_code":"30.0",
    "gn:asciiname":"Kalawellewa",
    "gn:country_code":"LK",
    "gn:dem":112,
    "gn:feature_class":"P",
    "gn:feature_code":"PPL",
    "gn:name":"Kalawellewa",
    "gn:population":0,
    "gn:timezone":"Asia/Colombo",
    "iso:country":"LK",
    "wof:name":"Kalawellewa",
    "wof:placetype":"locality"
},
  "geometry": {"coordinates":[80.3402,8.1676],"type":"Point"}
}