{
  "type": "Feature",
  "properties": {
    "gn:admin1_code":"32.0",
    "gn:asciiname":"Athuruwela",
    "gn:country_code":"LK",
    "gn:dem":63,
    "gn:feature_class":"P",
    "gn:feature_code":"PPL",
    "gn:name":"Athuruwela",
    "gn:population":0,
    "gn:timezone":"Asia/Colombo",
    "iso:country":"LK",
    "name:und_x_variant":[
        "Aturuwala"
    ],
    "wof:name":"Athuruwela",
    "wof:placetype":"locality"
},
  "geometry": {"coordinates":[80.1438,7.3558],"type":"Point"}
}