{
  "type": "Feature",
  "properties": {
    "gn:admin1_code":"38.0",
    "gn:asciiname":"Terumurikandi",
    "gn:country_code":"LK",
    "gn:dem":47,
    "gn:feature_class":"P",
    "gn:feature_code":"PPL",
    "gn:name":"Terumurikandi",
    "gn:population":0,
    "gn:timezone":"Asia/Colombo",
    "iso:country":"LK",
    "name:und_x_variant":[
        "Terumurikandai",
        "Terumurikandi"
    ],
    "wof:name":"Terumurikandi",
    "wof:placetype":"locality"
},
  "geometry": {"coordinates":[80.40940000000001,9.3033],"type":"Point"}
}