{
  "type": "Feature",
  "properties": {
    "gn:admin1_code":"30.0",
    "gn:asciiname":"Mangalagama",
    "gn:country_code":"LK",
    "gn:dem":91,
    "gn:feature_class":"P",
    "gn:feature_code":"PPL",
    "gn:name":"Mangalagama",
    "gn:population":0,
    "gn:timezone":"Asia/Colombo",
    "iso:country":"LK",
    "wof:name":"Mangalagama",
    "wof:placetype":"locality"
},
  "geometry": {"coordinates":[80.43340000000001,8.4052],"type":"Point"}
}