{
  "type": "Feature",
  "properties": {
    "gn:admin1_code":"29.0",
    "gn:asciiname":"Huduhumpola",
    "gn:country_code":"LK",
    "gn:dem":551,
    "gn:feature_class":"P",
    "gn:feature_code":"PPL",
    "gn:name":"Huduhumpola",
    "gn:population":0,
    "gn:timezone":"Asia/Colombo",
    "iso:country":"LK",
    "wof:name":"Huduhumpola",
    "wof:placetype":"locality"
},
  "geometry": {"coordinates":[80.61667,7.28333],"type":"Point"}
}