{
  "type": "Feature",
  "properties": {
    "gn:admin1_code":"34.0",
    "gn:asciiname":"Wellawatta",
    "gn:country_code":"LK",
    "gn:dem":42,
    "gn:feature_class":"P",
    "gn:feature_code":"PPL",
    "gn:name":"Wellawatta",
    "gn:population":0,
    "gn:timezone":"Asia/Colombo",
    "iso:country":"LK",
    "wof:name":"Wellawatta",
    "wof:placetype":"locality"
},
  "geometry": {"coordinates":[80.71666999999999,5.98333],"type":"Point"}
}