{
  "type": "Feature",
  "properties": {
    "gn:admin1_code":"35.0",
    "gn:asciiname":"Talkotayaya",
    "gn:country_code":"LK",
    "gn:dem":430,
    "gn:feature_class":"P",
    "gn:feature_code":"PPL",
    "gn:name":"Talkotayaya",
    "gn:population":0,
    "gn:timezone":"Asia/Colombo",
    "iso:country":"LK",
    "name:und_x_variant":[
        "Talkota"
    ],
    "wof:name":"Talkotayaya",
    "wof:placetype":"locality"
},
  "geometry": {"coordinates":[81.423,7.0323],"type":"Point"}
}