{
  "type": "Feature",
  "properties": {
    "gn:admin1_code":"34.0",
    "gn:asciiname":"Pedimella",
    "gn:country_code":"LK",
    "gn:dem":71,
    "gn:feature_class":"P",
    "gn:feature_code":"PPL",
    "gn:name":"Pedimella",
    "gn:population":0,
    "gn:timezone":"Asia/Colombo",
    "iso:country":"LK",
    "wof:name":"Pedimella",
    "wof:placetype":"locality"
},
  "geometry": {"coordinates":[80.30070000000001,6.0905],"type":"Point"}
}