{
  "type": "Feature",
  "properties": {
    "gn:admin1_code":"33.0",
    "gn:asciiname":"Marapana",
    "gn:country_code":"LK",
    "gn:dem":37,
    "gn:feature_class":"P",
    "gn:feature_code":"PPL",
    "gn:name":"Marapana",
    "gn:population":0,
    "gn:timezone":"Asia/Colombo",
    "iso:country":"LK",
    "name:ceb_x_preferred":[
        "Marapana"
    ],
    "name:por_x_preferred":[
        "Marapana"
    ],
    "name:swe_x_preferred":[
        "Marapana"
    ],
    "name:und_x_variant":[
        "Mapanana"
    ],
    "name:vie_x_preferred":[
        "Marapana"
    ],
    "name:war_x_preferred":[
        "Marapana"
    ],
    "wof:name":"Marapana",
    "wof:placetype":"locality"
},
  "geometry": {"coordinates":[80.44459999999999,6.6444],"type":"Point"}
}