{
  "type": "Feature",
  "properties": {
    "gn:admin1_code":"33.0",
    "gn:asciiname":"Ibiwela",
    "gn:country_code":"LK",
    "gn:dem":408,
    "gn:feature_class":"P",
    "gn:feature_code":"PPL",
    "gn:name":"Ibiwela",
    "gn:population":0,
    "gn:timezone":"Asia/Colombo",
    "iso:country":"LK",
    "wof:name":"Ibiwela",
    "wof:placetype":"locality"
},
  "geometry": {"coordinates":[80.4813,6.4737],"type":"Point"}
}