{
  "type": "Feature",
  "properties": {
    "gn:admin1_code":"34.0",
    "gn:asciiname":"Delgalla",
    "gn:cc2":"LK",
    "gn:country_code":"LK",
    "gn:dem":10,
    "gn:feature_class":"P",
    "gn:feature_code":"PPL",
    "gn:name":"Delgalla",
    "gn:population":0,
    "gn:timezone":"Asia/Colombo",
    "iso:country":"LK",
    "name:fas_x_preferred":[
        "\u0648\u0644\u06af\u0644\u0627"
    ],
    "name:und_x_variant":[
        "Velgalla",
        "Delgalla"
    ],
    "wof:name":"Delgalla",
    "wof:placetype":"locality"
},
  "geometry": {"coordinates":[80.61667,5.95],"type":"Point"}
}