{
  "type": "Feature",
  "properties": {
    "gn:admin1_code":"29.0",
    "gn:asciiname":"Moragaspitiya",
    "gn:country_code":"LK",
    "gn:dem":408,
    "gn:feature_class":"P",
    "gn:feature_code":"PPL",
    "gn:name":"Moragaspitiya",
    "gn:population":0,
    "gn:timezone":"Asia/Colombo",
    "iso:country":"LK",
    "name:ceb_x_preferred":[
        "Moragaspitiya"
    ],
    "name:swe_x_preferred":[
        "Moragaspitiya"
    ],
    "wof:name":"Moragaspitiya",
    "wof:placetype":"locality"
},
  "geometry": {"coordinates":[80.61879999999999,7.631],"type":"Point"}
}