{
  "type": "Feature",
  "properties": {
    "gn:admin1_code":"30.0",
    "gn:asciiname":"Nambadawewa",
    "gn:country_code":"LK",
    "gn:dem":71,
    "gn:feature_class":"P",
    "gn:feature_code":"PPL",
    "gn:name":"Nambadawewa",
    "gn:population":0,
    "gn:timezone":"Asia/Colombo",
    "iso:country":"LK",
    "wof:name":"Nambadawewa",
    "wof:placetype":"locality"
},
  "geometry": {"coordinates":[80.7808,8.701],"type":"Point"}
}