{
  "type": "Feature",
  "properties": {
    "gn:admin1_code":"32.0",
    "gn:asciiname":"Galhinna",
    "gn:country_code":"LK",
    "gn:dem":93,
    "gn:feature_class":"P",
    "gn:feature_code":"PPL",
    "gn:name":"Galhinna",
    "gn:population":0,
    "gn:timezone":"Asia/Colombo",
    "iso:country":"LK",
    "wof:name":"Galhinna",
    "wof:placetype":"locality"
},
  "geometry": {"coordinates":[80.3432,7.6323],"type":"Point"}
}