{
  "type": "Feature",
  "properties": {
    "gn:admin1_code":"32.0",
    "gn:asciiname":"Akkarayankotuwa",
    "gn:country_code":"LK",
    "gn:dem":7,
    "gn:feature_class":"P",
    "gn:feature_code":"PPL",
    "gn:name":"Akkarayankotuwa",
    "gn:population":0,
    "gn:timezone":"Asia/Colombo",
    "iso:country":"LK",
    "wof:name":"Akkarayankotuwa",
    "wof:placetype":"locality"
},
  "geometry": {"coordinates":[79.7971,7.5901],"type":"Point"}
}