{
  "type": "Feature",
  "properties": {
    "gn:admin1_code":"34.0",
    "gn:asciiname":"Karijjawala",
    "gn:country_code":"LK",
    "gn:dem":18,
    "gn:feature_class":"P",
    "gn:feature_code":"PPL",
    "gn:name":"Karijjawala",
    "gn:population":0,
    "gn:timezone":"Asia/Colombo",
    "iso:country":"LK",
    "wof:name":"Karijjawala",
    "wof:placetype":"locality"
},
  "geometry": {"coordinates":[81.33240000000001,6.2207],"type":"Point"}
}