{
  "type": "Feature",
  "properties": {
    "gn:admin1_code":"32.0",
    "gn:asciiname":"Bamunugedara",
    "gn:country_code":"LK",
    "gn:dem":79,
    "gn:feature_class":"P",
    "gn:feature_code":"PPL",
    "gn:name":"Bamunugedara",
    "gn:population":0,
    "gn:timezone":"Asia/Colombo",
    "iso:country":"LK",
    "wof:name":"Bamunugedara",
    "wof:placetype":"locality"
},
  "geometry": {"coordinates":[80.24809999999999,7.4889],"type":"Point"}
}