{
  "type": "Feature",
  "properties": {
    "gn:admin1_code":"35.0",
    "gn:asciiname":"Nagahadoruwa",
    "gn:country_code":"LK",
    "gn:dem":247,
    "gn:feature_class":"P",
    "gn:feature_code":"PPL",
    "gn:name":"Nagahadoruwa",
    "gn:population":0,
    "gn:timezone":"Asia/Colombo",
    "iso:country":"LK",
    "wof:name":"Nagahadoruwa",
    "wof:placetype":"locality"
},
  "geometry": {"coordinates":[81.2255,7.1401],"type":"Point"}
}