{
  "type": "Feature",
  "properties": {
    "gn:admin1_code":"35.0",
    "gn:asciiname":"Medawela",
    "gn:country_code":"LK",
    "gn:dem":1068,
    "gn:feature_class":"P",
    "gn:feature_code":"PPL",
    "gn:name":"Medawela",
    "gn:population":0,
    "gn:timezone":"Asia/Colombo",
    "iso:country":"LK",
    "wof:name":"Medawela",
    "wof:placetype":"locality"
},
  "geometry": {"coordinates":[81.014,6.8851],"type":"Point"}
}