{
  "type": "Feature",
  "properties": {
    "gn:admin1_code":"32.0",
    "gn:asciiname":"Egodapitiya",
    "gn:country_code":"LK",
    "gn:dem":46,
    "gn:feature_class":"P",
    "gn:feature_code":"PPL",
    "gn:name":"Egodapitiya",
    "gn:population":0,
    "gn:timezone":"Asia/Colombo",
    "iso:country":"LK",
    "wof:name":"Egodapitiya",
    "wof:placetype":"locality"
},
  "geometry": {"coordinates":[79.94070000000001,8.0089],"type":"Point"}
}