{
  "type": "Feature",
  "properties": {
    "gn:admin1_code":"35.0",
    "gn:asciiname":"Erabaddagama",
    "gn:country_code":"LK",
    "gn:dem":1147,
    "gn:feature_class":"P",
    "gn:feature_code":"PPL",
    "gn:name":"Erabaddagama",
    "gn:population":0,
    "gn:timezone":"Asia/Colombo",
    "iso:country":"LK",
    "name:und_x_variant":[
        "Erabadda",
        "Erabaddegama",
        "Erabaddagama"
    ],
    "wof:name":"Erabaddagama",
    "wof:placetype":"locality"
},
  "geometry": {"coordinates":[80.8806,6.8832],"type":"Point"}
}