{
  "type": "Feature",
  "properties": {
    "gn:admin1_code":"36.0",
    "gn:asciiname":"Pitigoda",
    "gn:country_code":"LK",
    "gn:dem":650,
    "gn:feature_class":"P",
    "gn:feature_code":"PPL",
    "gn:name":"Pitigoda",
    "gn:population":0,
    "gn:timezone":"Asia/Colombo",
    "iso:country":"LK",
    "wof:name":"Pitigoda",
    "wof:placetype":"locality"
},
  "geometry": {"coordinates":[80.84999999999999,7.23333],"type":"Point"}
}