{
  "type": "Feature",
  "properties": {
    "gn:admin1_code":"30.0",
    "gn:asciiname":"Hammillakulama",
    "gn:cc2":"LK",
    "gn:country_code":"LK",
    "gn:dem":116,
    "gn:feature_class":"P",
    "gn:feature_code":"PPL",
    "gn:name":"Hammillakulama",
    "gn:population":0,
    "gn:timezone":"Asia/Colombo",
    "iso:country":"LK",
    "name:und_x_variant":[
        "Halmillakulama",
        "Hammillakulama"
    ],
    "wof:name":"Hammillakulama",
    "wof:placetype":"locality"
},
  "geometry": {"coordinates":[80.45,8.18333],"type":"Point"}
}