{
  "type": "Feature",
  "properties": {
    "gn:admin1_code":"34.0",
    "gn:asciiname":"Kapuruwediwela",
    "gn:cc2":"LK",
    "gn:country_code":"LK",
    "gn:dem":113,
    "gn:feature_class":"P",
    "gn:feature_code":"PPL",
    "gn:name":"Kapuruwediwela",
    "gn:population":0,
    "gn:timezone":"Asia/Colombo",
    "iso:country":"LK",
    "name:und_x_variant":[
        "Kapuruwadiya",
        "Kapuruwediwela"
    ],
    "wof:name":"Kapuruwediwela",
    "wof:placetype":"locality"
},
  "geometry": {"coordinates":[80.90000000000001,7.51667],"type":"Point"}
}