{
  "type": "Feature",
  "properties": {
    "gn:admin1_code":"33.0",
    "gn:asciiname":"Gondawela",
    "gn:country_code":"LK",
    "gn:dem":170,
    "gn:feature_class":"P",
    "gn:feature_code":"PPL",
    "gn:name":"Gondawela",
    "gn:population":0,
    "gn:timezone":"Asia/Colombo",
    "iso:country":"LK",
    "name:und_x_variant":[
        "Gondewala",
        "Gondawela"
    ],
    "wof:name":"Gondawela",
    "wof:placetype":"locality"
},
  "geometry": {"coordinates":[80.42610000000001,7.3159],"type":"Point"}
}