{
  "type": "Feature",
  "properties": {
    "gn:admin1_code":"33.0",
    "gn:asciiname":"Panwilahena",
    "gn:country_code":"LK",
    "gn:dem":566,
    "gn:feature_class":"P",
    "gn:feature_code":"PPL",
    "gn:name":"Panwilahena",
    "gn:population":0,
    "gn:timezone":"Asia/Colombo",
    "iso:country":"LK",
    "wof:name":"Panwilahena",
    "wof:placetype":"locality"
},
  "geometry": {"coordinates":[80.52589999999999,6.7219],"type":"Point"}
}