{
  "type": "Feature",
  "properties": {
    "gn:admin1_code":"34.0",
    "gn:asciiname":"Lelwala Ihala South",
    "gn:country_code":"LK",
    "gn:dem":14,
    "gn:feature_class":"P",
    "gn:feature_code":"PPL",
    "gn:name":"Lelwala Ihala South",
    "gn:population":0,
    "gn:timezone":"Asia/Colombo",
    "iso:country":"LK",
    "name:und_x_variant":[
        "Lelwala Ihala"
    ],
    "wof:name":"Lelwala Ihala South",
    "wof:placetype":"locality"
},
  "geometry": {"coordinates":[80.2383,6.1395],"type":"Point"}
}