{
  "type": "Feature",
  "properties": {
    "gn:admin1_code":"36.0",
    "gn:asciiname":"Narampitiya",
    "gn:country_code":"LK",
    "gn:dem":60,
    "gn:feature_class":"P",
    "gn:feature_code":"PPL",
    "gn:name":"Narampitiya",
    "gn:population":0,
    "gn:timezone":"Asia/Colombo",
    "iso:country":"LK",
    "wof:name":"Narampitiya",
    "wof:placetype":"locality"
},
  "geometry": {"coordinates":[80.06480000000001,7.2457],"type":"Point"}
}