{
  "type": "Feature",
  "properties": {
    "gn:admin1_code":"37.0",
    "gn:asciiname":"Nilaveli",
    "gn:country_code":"LK",
    "gn:dem":7,
    "gn:feature_class":"P",
    "gn:feature_code":"PPL",
    "gn:name":"Nilaveli",
    "gn:population":0,
    "gn:timezone":"Asia/Colombo",
    "iso:country":"LK",
    "name:ceb_x_preferred":[
        "Nilaveli"
    ],
    "name:sin_x_preferred":[
        "\u0db1\u0dd2\u0dbd\u0dcf\u0dc0\u0dd9\u0dbd\u0dd2"
    ],
    "name:swe_x_preferred":[
        "Nilaveli"
    ],
    "name:tam_x_preferred":[
        "\u0ba8\u0bbf\u0bb2\u0bbe\u0bb5\u0bc6\u0bb3\u0bbf"
    ],
    "wof:name":"Nilaveli",
    "wof:placetype":"locality"
},
  "geometry": {"coordinates":[81.2009,8.6728],"type":"Point"}
}