{
  "type": "Feature",
  "properties": {
    "gn:admin1_code":"33.0",
    "gn:asciiname":"Anhettigama",
    "gn:country_code":"LK",
    "gn:dem":192,
    "gn:feature_class":"P",
    "gn:feature_code":"PPL",
    "gn:name":"Anhettigama",
    "gn:population":0,
    "gn:timezone":"Asia/Colombo",
    "iso:country":"LK",
    "wof:name":"Anhettigama",
    "wof:placetype":"locality"
},
  "geometry": {"coordinates":[80.374,6.9221],"type":"Point"}
}