{
  "type": "Feature",
  "properties": {
    "gn:admin1_code":"29.0",
    "gn:asciiname":"Wanarajah South",
    "gn:country_code":"LK",
    "gn:dem":1119,
    "gn:feature_class":"P",
    "gn:feature_code":"PPL",
    "gn:name":"Wanarajah South",
    "gn:population":0,
    "gn:timezone":"Asia/Colombo",
    "iso:country":"LK",
    "wof:name":"Wanarajah South",
    "wof:placetype":"locality"
},
  "geometry": {"coordinates":[80.5891,6.8632],"type":"Point"}
}