{
  "type": "Feature",
  "properties": {
    "gn:admin1_code":"37.0",
    "gn:asciiname":"Porudutuwala",
    "gn:country_code":"LK",
    "gn:dem":36,
    "gn:feature_class":"P",
    "gn:feature_code":"PPL",
    "gn:name":"Porudutuwala",
    "gn:population":0,
    "gn:timezone":"Asia/Colombo",
    "iso:country":"LK",
    "name:und_x_variant":[
        "Porodutuwala",
        "Porudutuwala"
    ],
    "wof:name":"Porudutuwala",
    "wof:placetype":"locality"
},
  "geometry": {"coordinates":[81.59999999999999,7.45],"type":"Point"}
}