{
  "type": "Feature",
  "properties": {
    "gn:admin1_code":"29.0",
    "gn:asciiname":"Dikkumbura",
    "gn:country_code":"LK",
    "gn:dem":469,
    "gn:feature_class":"P",
    "gn:feature_code":"PPL",
    "gn:name":"Dikkumbura",
    "gn:population":0,
    "gn:timezone":"Asia/Colombo",
    "iso:country":"LK",
    "wof:name":"Dikkumbura",
    "wof:placetype":"locality"
},
  "geometry": {"coordinates":[80.6054,7.5679],"type":"Point"}
}