{
  "type": "Feature",
  "properties": {
    "gn:admin1_code":"32.0",
    "gn:asciiname":"Kalugahatenna",
    "gn:country_code":"LK",
    "gn:dem":573,
    "gn:feature_class":"P",
    "gn:feature_code":"PPL",
    "gn:name":"Kalugahatenna",
    "gn:population":0,
    "gn:timezone":"Asia/Colombo",
    "iso:country":"LK",
    "wof:name":"Kalugahatenna",
    "wof:placetype":"locality"
},
  "geometry": {"coordinates":[80.5574,7.4834],"type":"Point"}
}