{
  "type": "Feature",
  "properties": {
    "gn:admin1_code":"30.0",
    "gn:asciiname":"Kumbukwewa",
    "gn:country_code":"LK",
    "gn:dem":123,
    "gn:feature_class":"P",
    "gn:feature_code":"PPL",
    "gn:name":"Kumbukwewa",
    "gn:population":0,
    "gn:timezone":"Asia/Colombo",
    "iso:country":"LK",
    "wof:name":"Kumbukwewa",
    "wof:placetype":"locality"
},
  "geometry": {"coordinates":[80.4572,8.1221],"type":"Point"}
}