{
  "type": "Feature",
  "properties": {
    "gn:admin1_code":"36.0",
    "gn:asciiname":"Indureagare",
    "gn:country_code":"LK",
    "gn:dem":29,
    "gn:feature_class":"P",
    "gn:feature_code":"PPL",
    "gn:name":"Indureagare",
    "gn:population":0,
    "gn:timezone":"Asia/Colombo",
    "iso:country":"LK",
    "wof:name":"Indureagare",
    "wof:placetype":"locality"
},
  "geometry": {"coordinates":[79.9637,7.2364],"type":"Point"}
}