{
  "type": "Feature",
  "properties": {
    "gn:admin1_code":"35.0",
    "gn:asciiname":"Helahalpe",
    "gn:country_code":"LK",
    "gn:dem":1004,
    "gn:feature_class":"P",
    "gn:feature_code":"PPL",
    "gn:name":"Helahalpe",
    "gn:population":0,
    "gn:timezone":"Asia/Colombo",
    "iso:country":"LK",
    "wof:name":"Helahalpe",
    "wof:placetype":"locality"
},
  "geometry": {"coordinates":[81.03570000000001,6.8885],"type":"Point"}
}