{
  "type": "Feature",
  "properties": {
    "gn:admin1_code":"35.0",
    "gn:asciiname":"Gonkatuwa",
    "gn:country_code":"LK",
    "gn:dem":1055,
    "gn:feature_class":"P",
    "gn:feature_code":"PPL",
    "gn:name":"Gonkatuwa",
    "gn:population":0,
    "gn:timezone":"Asia/Colombo",
    "iso:country":"LK",
    "name:und_x_variant":[
        "Gonkotuwa",
        "Gonkatuwa"
    ],
    "wof:name":"Gonkatuwa",
    "wof:placetype":"locality"
},
  "geometry": {"coordinates":[81.13249999999999,6.9897],"type":"Point"}
}