{
  "type": "Feature",
  "properties": {
    "gn:admin1_code":"29.0",
    "gn:asciiname":"Werawala",
    "gn:country_code":"LK",
    "gn:dem":588,
    "gn:feature_class":"P",
    "gn:feature_code":"PPL",
    "gn:name":"Werawala",
    "gn:population":0,
    "gn:timezone":"Asia/Colombo",
    "iso:country":"LK",
    "wof:name":"Werawala",
    "wof:placetype":"locality"
},
  "geometry": {"coordinates":[80.5476,7.2139],"type":"Point"}
}