{
  "type": "Feature",
  "properties": {
    "gn:admin1_code":"35.0",
    "gn:asciiname":"Ketakelegama",
    "gn:country_code":"LK",
    "gn:dem":492,
    "gn:feature_class":"P",
    "gn:feature_code":"PPL",
    "gn:name":"Ketakelegama",
    "gn:population":0,
    "gn:timezone":"Asia/Colombo",
    "iso:country":"LK",
    "name:und_x_variant":[
        "Ketakellagama"
    ],
    "wof:name":"Ketakelegama",
    "wof:placetype":"locality"
},
  "geometry": {"coordinates":[81.0753,7.0415],"type":"Point"}
}