{
  "type": "Feature",
  "properties": {
    "gn:admin1_code":"33.0",
    "gn:asciiname":"Gonagomuwa",
    "gn:country_code":"LK",
    "gn:dem":180,
    "gn:feature_class":"P",
    "gn:feature_code":"PPL",
    "gn:name":"Gonagomuwa",
    "gn:population":0,
    "gn:timezone":"Asia/Colombo",
    "iso:country":"LK",
    "wof:name":"Gonagomuwa",
    "wof:placetype":"locality"
},
  "geometry": {"coordinates":[80.3793,7.0158],"type":"Point"}
}