{
  "type": "Feature",
  "properties": {
    "gn:admin1_code":"32.0",
    "gn:asciiname":"Udawatta",
    "gn:country_code":"LK",
    "gn:dem":82,
    "gn:feature_class":"P",
    "gn:feature_code":"PPL",
    "gn:name":"Udawatta",
    "gn:population":0,
    "gn:timezone":"Asia/Colombo",
    "iso:country":"LK",
    "name:fas_x_preferred":[
        "\u06cc\u0648\u062f\u0627\u0648\u0627\u062a\u0627"
    ],
    "name:urd_x_preferred":[
        "\u0627\u062f\u0648\u0627\u062a\u0627"
    ],
    "wof:name":"Udawatta",
    "wof:placetype":"locality"
},
  "geometry": {"coordinates":[80.14060000000001,7.4258],"type":"Point"}
}