{
  "type": "Feature",
  "properties": {
    "gn:admin1_code":"30.0",
    "gn:asciiname":"Galapitagala",
    "gn:country_code":"LK",
    "gn:dem":162,
    "gn:feature_class":"P",
    "gn:feature_code":"PPL",
    "gn:name":"Galapitagala",
    "gn:population":0,
    "gn:timezone":"Asia/Colombo",
    "iso:country":"LK",
    "name:und_x_variant":[
        "Galapitigala",
        "Galapitagala"
    ],
    "wof:name":"Galapitagala",
    "wof:placetype":"locality"
},
  "geometry": {"coordinates":[80.6718,8.0856],"type":"Point"}
}