{
  "type": "Feature",
  "properties": {
    "gn:admin1_code":"30.0",
    "gn:asciiname":"Kotawella",
    "gn:cc2":"LK",
    "gn:country_code":"LK",
    "gn:dem":84,
    "gn:feature_class":"P",
    "gn:feature_code":"PPL",
    "gn:name":"Kotawella",
    "gn:population":0,
    "gn:timezone":"Asia/Colombo",
    "iso:country":"LK",
    "name:und_x_variant":[
        "Kotawela",
        "Kotawella"
    ],
    "wof:name":"Kotawella",
    "wof:placetype":"locality"
},
  "geometry": {"coordinates":[80.93333,7.83333],"type":"Point"}
}