{
  "type": "Feature",
  "properties": {
    "gn:admin1_code":"30.0",
    "gn:asciiname":"Track Six",
    "gn:country_code":"LK",
    "gn:dem":52,
    "gn:feature_class":"P",
    "gn:feature_code":"PPL",
    "gn:name":"Track Six",
    "gn:population":0,
    "gn:timezone":"Asia/Colombo",
    "iso:country":"LK",
    "wof:name":"Track Six",
    "wof:placetype":"locality"
},
  "geometry": {"coordinates":[80.1362,8.5071],"type":"Point"}
}