{
  "type": "Feature",
  "properties": {
    "gn:admin1_code":"30.0",
    "gn:asciiname":"Siyambalagaswewa",
    "gn:country_code":"LK",
    "gn:dem":181,
    "gn:feature_class":"P",
    "gn:feature_code":"PPL",
    "gn:name":"Siyambalagaswewa",
    "gn:population":0,
    "gn:timezone":"Asia/Colombo",
    "iso:country":"LK",
    "wof:name":"Siyambalagaswewa",
    "wof:placetype":"locality"
},
  "geometry": {"coordinates":[80.73333000000002,8.05],"type":"Point"}
}