{
  "type": "Feature",
  "properties": {
    "gn:admin1_code":"38.0",
    "gn:asciiname":"Suryanpiddi",
    "gn:country_code":"LK",
    "gn:dem":11,
    "gn:feature_class":"P",
    "gn:feature_code":"PPL",
    "gn:name":"Suryanpiddi",
    "gn:population":0,
    "gn:timezone":"Asia/Colombo",
    "iso:country":"LK",
    "wof:name":"Suryanpiddi",
    "wof:placetype":"locality"
},
  "geometry": {"coordinates":[79.8629,9.7351],"type":"Point"}
}