{
  "type": "Feature",
  "properties": {
    "gn:admin1_code":"38.0",
    "gn:asciiname":"Pandattarippu",
    "gn:country_code":"LK",
    "gn:dem":14,
    "gn:feature_class":"P",
    "gn:feature_code":"PPL",
    "gn:name":"Pandattarippu",
    "gn:population":0,
    "gn:timezone":"Asia/Colombo",
    "iso:country":"LK",
    "name:und_x_variant":[
        "Pandateruppu",
        "Pandattarippu"
    ],
    "wof:name":"Pandattarippu",
    "wof:placetype":"locality"
},
  "geometry": {"coordinates":[79.9717,9.7792],"type":"Point"}
}