{
  "type": "Feature",
  "properties": {
    "gn:gn_country":"LK",
    "gn:gn_fcode":"PPL",
    "gn:gn_pop":0,
    "iso:country":"LK",
    "name:eng_x_preferred":[
        "Pettah"
    ],
    "name:eng_x_variant":[
        "Pettal"
    ],
    "name:jpn_x_preferred":[
        "\u30da\u30bf\u30fc"
    ],
    "name:sin_x_preferred":[
        "\u0db4\u0dd2\u0da7\u0d9a\u0ddc\u0da7\u0dd4\u0dc0"
    ],
    "name:tam_x_preferred":[
        "\u0baa\u0bc1\u0bb1\u0b95\u0bcd\u0b95\u0bcb\u0b9f\u0bcd\u0b9f\u0bc8"
    ],
    "name:unk_x_variant":[
        "Pettal",
        "Pettah"
    ],
    "qs_pg:aaroncc":"LK",
    "qs_pg:gn_country":"LK",
    "qs_pg:gn_fcode":"PPL",
    "qs_pg:gn_pop":0,
    "qs_pg:name":"Pettah",
    "qs_pg:name_adm0":"Sri Lanka",
    "qs_pg:name_adm1":"Western",
    "qs_pg:photos":1202,
    "qs_pg:photos_1k":244,
    "qs_pg:photos_9k":5,
    "qs_pg:photos_9r":7,
    "qs_pg:photos_all":1202,
    "qs_pg:photos_sr":11,
    "qs_pg:pop_sr":0,
    "qs_pg:qs_pg_placetype":"neighbourhood",
    "qs_pg:qs_pg_placetype_gp":"Suburb",
    "qs_pg:woe_adm0":23424778,
    "woe:adm0_id":23424778,
    "woe:name_adm0":"Sri Lanka",
    "woe:name_adm1":"Western",
    "woe:placetype":"Suburb",
    "wof:name":"Pettah",
    "wof:placetype":"neighbourhood"
},
  "geometry": {"coordinates":[79.84910000000001,6.9376],"type":"Point"}
}