{
  "type": "Feature",
  "properties": {
    "gn:admin1_code":"29.0",
    "gn:asciiname":"Hallela",
    "gn:country_code":"LK",
    "gn:dem":889,
    "gn:feature_class":"P",
    "gn:feature_code":"PPL",
    "gn:name":"Hallela",
    "gn:population":0,
    "gn:timezone":"Asia/Colombo",
    "iso:country":"LK",
    "wof:name":"Hallela",
    "wof:placetype":"locality"
},
  "geometry": {"coordinates":[80.7667,7.1463],"type":"Point"}
}