{
  "type": "Feature",
  "properties": {
    "gn:admin1_code":"30.0",
    "gn:asciiname":"Nuwarawewa",
    "gn:cc2":"LK",
    "gn:country_code":"LK",
    "gn:dem":78,
    "gn:feature_class":"P",
    "gn:feature_code":"PPL",
    "gn:name":"Nuwarawewa",
    "gn:population":0,
    "gn:timezone":"Asia/Colombo",
    "iso:country":"LK",
    "name:und_x_variant":[
        "Nuwarawewa East",
        "Nuwarawewa"
    ],
    "wof:name":"Nuwarawewa",
    "wof:placetype":"locality"
},
  "geometry": {"coordinates":[80.41667,8.35],"type":"Point"}
}