{
  "type": "Feature",
  "properties": {
    "gn:admin1_code":"35.0",
    "gn:asciiname":"Gannekkumb",
    "gn:country_code":"LK",
    "gn:dem":1122,
    "gn:feature_class":"P",
    "gn:feature_code":"PPL",
    "gn:name":"Gannekkumb",
    "gn:population":0,
    "gn:timezone":"Asia/Colombo",
    "iso:country":"LK",
    "name:und_x_variant":[
        "Gannekumbura",
        "Gannekkumbura",
        "Gannekkumb"
    ],
    "wof:name":"Gannekkumb",
    "wof:placetype":"locality"
},
  "geometry": {"coordinates":[80.8969,6.8854],"type":"Point"}
}