{
  "type": "Feature",
  "properties": {
    "gn:admin1_code":"29.0",
    "gn:asciiname":"Rambakegama",
    "gn:country_code":"LK",
    "gn:dem":1041,
    "gn:feature_class":"P",
    "gn:feature_code":"PPL",
    "gn:name":"Rambakegama",
    "gn:population":0,
    "gn:timezone":"Asia/Colombo",
    "iso:country":"LK",
    "name:und_x_variant":[
        "Rambuke"
    ],
    "wof:name":"Rambakegama",
    "wof:placetype":"locality"
},
  "geometry": {"coordinates":[80.8736,7.0805],"type":"Point"}
}