{
  "type": "Feature",
  "properties": {
    "gn:admin1_code":"33.0",
    "gn:asciiname":"Udahenkanda",
    "gn:country_code":"LK",
    "gn:dem":238,
    "gn:feature_class":"P",
    "gn:feature_code":"PPL",
    "gn:name":"Udahenkanda",
    "gn:population":0,
    "gn:timezone":"Asia/Colombo",
    "iso:country":"LK",
    "wof:name":"Udahenkanda",
    "wof:placetype":"locality"
},
  "geometry": {"coordinates":[80.3223,6.9284],"type":"Point"}
}