{
  "type": "Feature",
  "properties": {
    "gn:admin1_code":"36.0",
    "gn:asciiname":"Natuduwa",
    "gn:cc2":"LK",
    "gn:country_code":"LK",
    "gn:dem":11,
    "gn:feature_class":"P",
    "gn:feature_code":"PPL",
    "gn:name":"Natuduwa",
    "gn:population":0,
    "gn:timezone":"Asia/Colombo",
    "iso:country":"LK",
    "name:und_x_variant":[
        "Padiliyatuduwa",
        "Natuduwa"
    ],
    "wof:name":"Natuduwa",
    "wof:placetype":"locality"
},
  "geometry": {"coordinates":[79.91667,6.98333],"type":"Point"}
}