{
  "type": "Feature",
  "properties": {
    "gn:admin1_code":"33.0",
    "gn:asciiname":"Hela",
    "gn:country_code":"LK",
    "gn:dem":596,
    "gn:feature_class":"P",
    "gn:feature_code":"PPL",
    "gn:name":"Hela",
    "gn:population":0,
    "gn:timezone":"Asia/Colombo",
    "iso:country":"LK",
    "wof:name":"Hela",
    "wof:placetype":"locality"
},
  "geometry": {"coordinates":[80.76899999999998,6.622],"type":"Point"}
}