{
  "type": "Feature",
  "properties": {
    "gn:admin1_code":"33.0",
    "gn:asciiname":"Halpitiya",
    "gn:country_code":"LK",
    "gn:dem":99,
    "gn:feature_class":"P",
    "gn:feature_code":"PPL",
    "gn:name":"Halpitiya",
    "gn:population":0,
    "gn:timezone":"Asia/Colombo",
    "iso:country":"LK",
    "wof:name":"Halpitiya",
    "wof:placetype":"locality"
},
  "geometry": {"coordinates":[80.37139999999999,7.3148],"type":"Point"}
}