{
  "type": "Feature",
  "properties": {
    "gn:admin1_code":"30.0",
    "gn:asciiname":"Kaduruwewa",
    "gn:country_code":"LK",
    "gn:dem":109,
    "gn:feature_class":"P",
    "gn:feature_code":"PPL",
    "gn:name":"Kaduruwewa",
    "gn:population":0,
    "gn:timezone":"Asia/Colombo",
    "iso:country":"LK",
    "wof:name":"Kaduruwewa",
    "wof:placetype":"locality"
},
  "geometry": {"coordinates":[80.389,8.1687],"type":"Point"}
}