{
  "type": "Feature",
  "properties": {
    "gn:admin1_code":"32.0",
    "gn:asciiname":"Galapitawewa",
    "gn:country_code":"LK",
    "gn:dem":135,
    "gn:feature_class":"P",
    "gn:feature_code":"PPL",
    "gn:name":"Galapitawewa",
    "gn:population":0,
    "gn:timezone":"Asia/Colombo",
    "iso:country":"LK",
    "name:und_x_variant":[
        "Galapitagama",
        "Galapitawewa"
    ],
    "wof:name":"Galapitawewa",
    "wof:placetype":"locality"
},
  "geometry": {"coordinates":[80.3994,7.9363],"type":"Point"}
}