{
  "type": "Feature",
  "properties": {
    "gn:admin1_code":"32.0",
    "gn:asciiname":"Kirivaula",
    "gn:country_code":"LK",
    "gn:dem":119,
    "gn:feature_class":"P",
    "gn:feature_code":"PPL",
    "gn:name":"Kirivaula",
    "gn:population":0,
    "gn:timezone":"Asia/Colombo",
    "iso:country":"LK",
    "name:und_x_variant":[
        "Kiriwaula"
    ],
    "wof:name":"Kirivaula",
    "wof:placetype":"locality"
},
  "geometry": {"coordinates":[80.4139,7.5162],"type":"Point"}
}