{
  "type": "Feature",
  "properties": {
    "gn:admin1_code":"35.0",
    "gn:asciiname":"Godadehigolla",
    "gn:country_code":"LK",
    "gn:dem":329,
    "gn:feature_class":"P",
    "gn:feature_code":"PPL",
    "gn:name":"Godadehigolla",
    "gn:population":0,
    "gn:timezone":"Asia/Colombo",
    "iso:country":"LK",
    "name:und_x_variant":[
        "Gadadehigolla"
    ],
    "wof:name":"Godadehigolla",
    "wof:placetype":"locality"
},
  "geometry": {"coordinates":[81.12260000000001,7.0458],"type":"Point"}
}