{
  "type": "Feature",
  "properties": {
    "gn:admin1_code":"38.0",
    "gn:asciiname":"Tuvaraneri",
    "gn:country_code":"LK",
    "gn:dem":85,
    "gn:feature_class":"P",
    "gn:feature_code":"PPL",
    "gn:name":"Tuvaraneri",
    "gn:population":0,
    "gn:timezone":"Asia/Colombo",
    "iso:country":"LK",
    "name:und_x_variant":[
        "Tuvaraineri",
        "Tuvaraneri"
    ],
    "wof:name":"Tuvaraneri",
    "wof:placetype":"locality"
},
  "geometry": {"coordinates":[80.58029999999999,8.9743],"type":"Point"}
}