{
  "type": "Feature",
  "properties": {
    "gn:admin1_code":"32.0",
    "gn:asciiname":"Siyabalangamuwa",
    "gn:country_code":"LK",
    "gn:dem":114,
    "gn:feature_class":"P",
    "gn:feature_code":"PPL",
    "gn:name":"Siyabalangamuwa",
    "gn:population":0,
    "gn:timezone":"Asia/Colombo",
    "iso:country":"LK",
    "name:und_x_variant":[
        "Siyambalangamuwa"
    ],
    "wof:name":"Siyabalangamuwa",
    "wof:placetype":"locality"
},
  "geometry": {"coordinates":[80.3539,7.5264],"type":"Point"}
}