{
  "type": "Feature",
  "properties": {
    "gn:admin1_code":"32.0",
    "gn:asciiname":"Mokalanegama",
    "gn:country_code":"LK",
    "gn:dem":101,
    "gn:feature_class":"P",
    "gn:feature_code":"PPL",
    "gn:name":"Mokalanegama",
    "gn:population":0,
    "gn:timezone":"Asia/Colombo",
    "iso:country":"LK",
    "name:und_x_variant":[
        "Makalanegama"
    ],
    "wof:name":"Mokalanegama",
    "wof:placetype":"locality"
},
  "geometry": {"coordinates":[80.3057,7.9971],"type":"Point"}
}