{
  "type": "Feature",
  "properties": {
    "gn:admin1_code":"36.0",
    "gn:asciiname":"Bonegala",
    "gn:country_code":"LK",
    "gn:dem":43,
    "gn:feature_class":"P",
    "gn:feature_code":"PPL",
    "gn:name":"Bonegala",
    "gn:population":0,
    "gn:timezone":"Asia/Colombo",
    "iso:country":"LK",
    "name:und_x_variant":[
        "Bonagala",
        "Bonegala"
    ],
    "wof:name":"Bonegala",
    "wof:placetype":"locality"
},
  "geometry": {"coordinates":[80.0864,7.1001],"type":"Point"}
}