{
  "type": "Feature",
  "properties": {
    "gn:admin1_code":"34.0",
    "gn:asciiname":"Waturawa",
    "gn:country_code":"LK",
    "gn:dem":36,
    "gn:feature_class":"P",
    "gn:feature_code":"PPL",
    "gn:name":"Waturawa",
    "gn:population":0,
    "gn:timezone":"Asia/Colombo",
    "iso:country":"LK",
    "wof:name":"Waturawa",
    "wof:placetype":"locality"
},
  "geometry": {"coordinates":[80.22029999999999,6.1416],"type":"Point"}
}