{
  "type": "Feature",
  "properties": {
    "gn:admin1_code":"30.0",
    "gn:asciiname":"Godagomayagama",
    "gn:country_code":"LK",
    "gn:dem":141,
    "gn:feature_class":"P",
    "gn:feature_code":"PPL",
    "gn:name":"Godagomayagama",
    "gn:population":0,
    "gn:timezone":"Asia/Colombo",
    "iso:country":"LK",
    "wof:name":"Godagomayagama",
    "wof:placetype":"locality"
},
  "geometry": {"coordinates":[80.58280000000001,8.0432],"type":"Point"}
}