{
  "type": "Feature",
  "properties": {
    "gn:admin1_code":"33.0",
    "gn:asciiname":"Jeewana",
    "gn:country_code":"LK",
    "gn:dem":129,
    "gn:feature_class":"P",
    "gn:feature_code":"PPL",
    "gn:name":"Jeewana",
    "gn:population":0,
    "gn:timezone":"Asia/Colombo",
    "iso:country":"LK",
    "name:und_x_variant":[
        "Jiwana"
    ],
    "wof:name":"Jeewana",
    "wof:placetype":"locality"
},
  "geometry": {"coordinates":[80.30970000000001,7.2843],"type":"Point"}
}