{
  "type": "Feature",
  "properties": {
    "gn:admin1_code":"32.0",
    "gn:asciiname":"Talangomuwa",
    "gn:cc2":"LK",
    "gn:country_code":"LK",
    "gn:dem":153,
    "gn:feature_class":"P",
    "gn:feature_code":"PPL",
    "gn:name":"Talangomuwa",
    "gn:population":0,
    "gn:timezone":"Asia/Colombo",
    "iso:country":"LK",
    "name:und_x_variant":[
        "Thallangomuwa",
        "Talangomuwa"
    ],
    "wof:name":"Talangomuwa",
    "wof:placetype":"locality"
},
  "geometry": {"coordinates":[80.48333000000002,7.68333],"type":"Point"}
}