{
  "type": "Feature",
  "properties": {
    "gn:admin1_code":"32.0",
    "gn:asciiname":"Kahatagawela",
    "gn:country_code":"LK",
    "gn:dem":106,
    "gn:feature_class":"P",
    "gn:feature_code":"PPL",
    "gn:name":"Kahatagawela",
    "gn:population":0,
    "gn:timezone":"Asia/Colombo",
    "iso:country":"LK",
    "name:und_x_variant":[
        "Kahatagaswala",
        "Kahatagawela",
        "Kahatagaswela"
    ],
    "wof:name":"Kahatagawela",
    "wof:placetype":"locality"
},
  "geometry": {"coordinates":[80.3866,7.5765],"type":"Point"}
}