{
  "type": "Feature",
  "properties": {
    "gn:admin1_code":"36.0",
    "gn:asciiname":"Willegoda",
    "gn:country_code":"LK",
    "gn:dem":48,
    "gn:feature_class":"P",
    "gn:feature_code":"PPL",
    "gn:name":"Willegoda",
    "gn:population":0,
    "gn:timezone":"Asia/Colombo",
    "iso:country":"LK",
    "wof:name":"Willegoda",
    "wof:placetype":"locality"
},
  "geometry": {"coordinates":[80.1084,6.5219],"type":"Point"}
}