{
  "type": "Feature",
  "properties": {
    "gn:admin1_code":"29.0",
    "gn:asciiname":"Pagalawatta",
    "gn:country_code":"LK",
    "gn:dem":1249,
    "gn:feature_class":"P",
    "gn:feature_code":"PPL",
    "gn:name":"Pagalawatta",
    "gn:population":0,
    "gn:timezone":"Asia/Colombo",
    "iso:country":"LK",
    "wof:name":"Pagalawatta",
    "wof:placetype":"locality"
},
  "geometry": {"coordinates":[80.90730000000001,7.0045],"type":"Point"}
}