{
  "type": "Feature",
  "properties": {
    "gn:admin1_code":"35.0",
    "gn:asciiname":"Barawaya",
    "gn:country_code":"LK",
    "gn:dem":94,
    "gn:feature_class":"P",
    "gn:feature_code":"PPL",
    "gn:name":"Barawaya",
    "gn:population":0,
    "gn:timezone":"Asia/Colombo",
    "iso:country":"LK",
    "wof:name":"Barawaya",
    "wof:placetype":"locality"
},
  "geometry": {"coordinates":[81.55199999999998,6.9848],"type":"Point"}
}