{
  "type": "Feature",
  "properties": {
    "gn:admin1_code":"36.0",
    "gn:asciiname":"Basiyawatta",
    "gn:country_code":"LK",
    "gn:dem":-9999,
    "gn:feature_class":"P",
    "gn:feature_code":"PPL",
    "gn:name":"Basiyawatta",
    "gn:population":0,
    "gn:timezone":"Asia/Colombo",
    "iso:country":"LK",
    "name:und_x_variant":[
        "Basiawatta",
        "Basiyawatta"
    ],
    "wof:name":"Basiyawatta",
    "wof:placetype":"locality"
},
  "geometry": {"coordinates":[79.8227,7.1723],"type":"Point"}
}