{
  "type": "Feature",
  "properties": {
    "gn:admin1_code":"33.0",
    "gn:asciiname":"Udumutta",
    "gn:country_code":"LK",
    "gn:dem":37,
    "gn:feature_class":"P",
    "gn:feature_code":"PPL",
    "gn:name":"Udumutta",
    "gn:population":0,
    "gn:timezone":"Asia/Colombo",
    "iso:country":"LK",
    "name:und_x_variant":[
        "Udumatta"
    ],
    "wof:name":"Udumutta",
    "wof:placetype":"locality"
},
  "geometry": {"coordinates":[80.2513,6.8644],"type":"Point"}
}