{
  "type": "Feature",
  "properties": {
    "gn:admin1_code":"30.0",
    "gn:asciiname":"Kumbukwewa",
    "gn:country_code":"LK",
    "gn:dem":77,
    "gn:feature_class":"P",
    "gn:feature_code":"PPL",
    "gn:name":"Kumbukwewa",
    "gn:population":0,
    "gn:timezone":"Asia/Colombo",
    "iso:country":"LK",
    "wof:name":"Kumbukwewa",
    "wof:placetype":"locality"
},
  "geometry": {"coordinates":[80.41667,8.53333],"type":"Point"}
}