{
  "type": "Feature",
  "properties": {
    "gn:admin1_code":"36.0",
    "gn:asciiname":"Maggona",
    "gn:country_code":"LK",
    "gn:dem":12,
    "gn:feature_class":"P",
    "gn:feature_code":"PPL",
    "gn:name":"Maggona",
    "gn:population":0,
    "gn:timezone":"Asia/Colombo",
    "iso:country":"LK",
    "name:und_x_variant":[
        "Maggona West",
        "Maggona"
    ],
    "wof:name":"Maggona",
    "wof:placetype":"locality"
},
  "geometry": {"coordinates":[79.9811,6.5041],"type":"Point"}
}