{
  "type": "Feature",
  "properties": {
    "gn:admin1_code":"29.0",
    "gn:asciiname":"Hapuwala",
    "gn:country_code":"LK",
    "gn:dem":822,
    "gn:feature_class":"P",
    "gn:feature_code":"PPL",
    "gn:name":"Hapuwala",
    "gn:population":0,
    "gn:timezone":"Asia/Colombo",
    "iso:country":"LK",
    "wof:name":"Hapuwala",
    "wof:placetype":"locality"
},
  "geometry": {"coordinates":[80.7608,7.1648],"type":"Point"}
}