{
  "type": "Feature",
  "properties": {
    "gn:admin1_code":"32.0",
    "gn:asciiname":"Delana",
    "gn:country_code":"LK",
    "gn:dem":49,
    "gn:feature_class":"P",
    "gn:feature_code":"PPL",
    "gn:name":"Delana",
    "gn:population":0,
    "gn:timezone":"Asia/Colombo",
    "iso:country":"LK",
    "wof:name":"Delana",
    "wof:placetype":"locality"
},
  "geometry": {"coordinates":[80.06570000000001,7.4774],"type":"Point"}
}