{
  "type": "Feature",
  "properties": {
    "gn:admin1_code":"38.0",
    "gn:asciiname":"Sankattharvayal",
    "gn:country_code":"LK",
    "gn:dem":9,
    "gn:feature_class":"P",
    "gn:feature_code":"PPL",
    "gn:name":"Sankattharvayal",
    "gn:population":0,
    "gn:timezone":"Asia/Colombo",
    "iso:country":"LK",
    "name:und_x_variant":[
        "Chankattarvayal"
    ],
    "wof:name":"Sankattharvayal",
    "wof:placetype":"locality"
},
  "geometry": {"coordinates":[80.41419999999999,9.5509],"type":"Point"}
}