{
  "type": "Feature",
  "properties": {
    "gn:admin1_code":"37.0",
    "gn:asciiname":"Wilpanakulam",
    "gn:country_code":"LK",
    "gn:dem":38,
    "gn:feature_class":"P",
    "gn:feature_code":"PPL",
    "gn:name":"Wilpanakulam",
    "gn:population":0,
    "gn:timezone":"Asia/Colombo",
    "iso:country":"LK",
    "name:und_x_variant":[
        "Wilpanakulama",
        "Wilpanakulam"
    ],
    "wof:name":"Wilpanakulam",
    "wof:placetype":"locality"
},
  "geometry": {"coordinates":[81.0085,8.6669],"type":"Point"}
}