{
  "type": "Feature",
  "properties": {
    "gn:admin1_code":"36.0",
    "gn:asciiname":"Midellawala",
    "gn:country_code":"LK",
    "gn:dem":29,
    "gn:feature_class":"P",
    "gn:feature_code":"PPL",
    "gn:name":"Midellawala",
    "gn:population":0,
    "gn:timezone":"Asia/Colombo",
    "iso:country":"LK",
    "wof:name":"Midellawala",
    "wof:placetype":"locality"
},
  "geometry": {"coordinates":[80.0874,7.1924],"type":"Point"}
}