{
  "type": "Feature",
  "properties": {
    "gn:admin1_code":"32.0",
    "gn:asciiname":"Pothanagama Siyambalewa",
    "gn:country_code":"LK",
    "gn:dem":100,
    "gn:feature_class":"P",
    "gn:feature_code":"PPL",
    "gn:name":"Pothanagama Siyambalewa",
    "gn:population":0,
    "gn:timezone":"Asia/Colombo",
    "iso:country":"LK",
    "name:und_x_variant":[
        "Potane Siyambalewa"
    ],
    "wof:name":"Pothanagama Siyambalewa",
    "wof:placetype":"locality"
},
  "geometry": {"coordinates":[80.3574,8.0501],"type":"Point"}
}