{
  "type": "Feature",
  "properties": {
    "gn:admin1_code":"34.0",
    "gn:asciiname":"Walakadakanda",
    "gn:country_code":"LK",
    "gn:dem":356,
    "gn:feature_class":"P",
    "gn:feature_code":"PPL",
    "gn:name":"Walakadakanda",
    "gn:population":0,
    "gn:timezone":"Asia/Colombo",
    "iso:country":"LK",
    "wof:name":"Walakadakanda",
    "wof:placetype":"locality"
},
  "geometry": {"coordinates":[80.6489,6.2499],"type":"Point"}
}