{
  "type": "Feature",
  "properties": {
    "gn:admin1_code":"32.0",
    "gn:asciiname":"Koragahapokuna",
    "gn:country_code":"LK",
    "gn:dem":42,
    "gn:feature_class":"P",
    "gn:feature_code":"PPL",
    "gn:name":"Koragahapokuna",
    "gn:population":0,
    "gn:timezone":"Asia/Colombo",
    "iso:country":"LK",
    "name:und_x_variant":[
        "Korakahapokuna",
        "Koragahapokuna"
    ],
    "wof:name":"Koragahapokuna",
    "wof:placetype":"locality"
},
  "geometry": {"coordinates":[80.0245,7.6684],"type":"Point"}
}