{
  "type": "Feature",
  "properties": {
    "gn:admin1_code":"34.0",
    "gn:asciiname":"Tanabaddegama",
    "gn:country_code":"LK",
    "gn:dem":25,
    "gn:feature_class":"P",
    "gn:feature_code":"PPL",
    "gn:name":"Tanabaddegama",
    "gn:population":0,
    "gn:timezone":"Asia/Colombo",
    "iso:country":"LK",
    "wof:name":"Tanabaddegama",
    "wof:placetype":"locality"
},
  "geometry": {"coordinates":[80.16160000000001,6.2387],"type":"Point"}
}