{
  "type": "Feature",
  "properties": {
    "gn:admin1_code":"29.0",
    "gn:asciiname":"Galboda",
    "gn:country_code":"LK",
    "gn:dem":271,
    "gn:feature_class":"P",
    "gn:feature_code":"PPL",
    "gn:name":"Galboda",
    "gn:population":0,
    "gn:timezone":"Asia/Colombo",
    "iso:country":"LK",
    "name:ceb_x_preferred":[
        "Galboda"
    ],
    "name:swe_x_preferred":[
        "Galboda"
    ],
    "name:und_x_variant":[
        "Galbode"
    ],
    "wof:name":"Galboda",
    "wof:placetype":"locality"
},
  "geometry": {"coordinates":[80.7201,7.6236],"type":"Point"}
}