{
  "type": "Feature",
  "properties": {
    "gn:admin1_code":"34.0",
    "gn:asciiname":"Gandarawatta",
    "gn:country_code":"LK",
    "gn:dem":17,
    "gn:feature_class":"P",
    "gn:feature_code":"PPL",
    "gn:name":"Gandarawatta",
    "gn:population":0,
    "gn:timezone":"Asia/Colombo",
    "iso:country":"LK",
    "wof:name":"Gandarawatta",
    "wof:placetype":"locality"
},
  "geometry": {"coordinates":[80.59999999999999,5.93333],"type":"Point"}
}