{
  "type": "Feature",
  "properties": {
    "gn:admin1_code":"32.0",
    "gn:asciiname":"Kelegama",
    "gn:country_code":"LK",
    "gn:dem":17,
    "gn:feature_class":"P",
    "gn:feature_code":"PPL",
    "gn:name":"Kelegama",
    "gn:population":0,
    "gn:timezone":"Asia/Colombo",
    "iso:country":"LK",
    "wof:name":"Kelegama",
    "wof:placetype":"locality"
},
  "geometry": {"coordinates":[79.8621,7.6688],"type":"Point"}
}