{
  "type": "Feature",
  "properties": {
    "gn:admin1_code":"33.0",
    "gn:asciiname":"Ruvandeniya",
    "gn:country_code":"LK",
    "gn:dem":351,
    "gn:feature_class":"P",
    "gn:feature_code":"PPL",
    "gn:name":"Ruvandeniya",
    "gn:population":0,
    "gn:timezone":"Asia/Colombo",
    "iso:country":"LK",
    "wof:name":"Ruvandeniya",
    "wof:placetype":"locality"
},
  "geometry": {"coordinates":[80.49160000000001,7.2238],"type":"Point"}
}