{
  "type": "Feature",
  "properties": {
    "gn:admin1_code":"34.0",
    "gn:asciiname":"Landajulana",
    "gn:cc2":"LK",
    "gn:country_code":"LK",
    "gn:dem":23,
    "gn:feature_class":"P",
    "gn:feature_code":"PPL",
    "gn:name":"Landajulana",
    "gn:population":0,
    "gn:timezone":"Asia/Colombo",
    "iso:country":"LK",
    "name:und_x_variant":[
        "Landejulana",
        "Landajulana"
    ],
    "name:urd_x_preferred":[
        "\u0644\u0627\u0646\u0688\u0627\u062c\u0648\u0644\u0627\u0646\u0627"
    ],
    "wof:name":"Landajulana",
    "wof:placetype":"locality"
},
  "geometry": {"coordinates":[81.13333,6.25],"type":"Point"}
}