{
  "type": "Feature",
  "properties": {
    "gn:admin1_code":"32.0",
    "gn:asciiname":"Sinna Ottapanai",
    "gn:country_code":"LK",
    "gn:dem":8,
    "gn:feature_class":"P",
    "gn:feature_code":"PPL",
    "gn:name":"Sinna Ottapanai",
    "gn:population":0,
    "gn:timezone":"Asia/Colombo",
    "iso:country":"LK",
    "name:und_x_variant":[
        "Ottapanai Sinna",
        "Sinna Ottapanai"
    ],
    "wof:name":"Sinna Ottapanai",
    "wof:placetype":"locality"
},
  "geometry": {"coordinates":[79.78530000000001,7.8124],"type":"Point"}
}