{
  "type": "Feature",
  "properties": {
    "gn:admin1_code":"36.0",
    "gn:asciiname":"Hangawatta",
    "gn:country_code":"LK",
    "gn:dem":49,
    "gn:feature_class":"P",
    "gn:feature_code":"PPL",
    "gn:name":"Hangawatta",
    "gn:population":0,
    "gn:timezone":"Asia/Colombo",
    "iso:country":"LK",
    "name:und_x_variant":[
        "Hangawatte",
        "Hangawatta"
    ],
    "wof:name":"Hangawatta",
    "wof:placetype":"locality"
},
  "geometry": {"coordinates":[80.04949999999999,7.2371],"type":"Point"}
}