{
  "type": "Feature",
  "properties": {
    "gn:admin1_code":"29.0",
    "gn:asciiname":"Kottegoda",
    "gn:country_code":"LK",
    "gn:dem":354,
    "gn:feature_class":"P",
    "gn:feature_code":"PPL",
    "gn:name":"Kottegoda",
    "gn:population":0,
    "gn:timezone":"Asia/Colombo",
    "iso:country":"LK",
    "name:und_x_variant":[
        "Kottagoda"
    ],
    "wof:name":"Kottegoda",
    "wof:placetype":"locality"
},
  "geometry": {"coordinates":[80.6371,7.5246],"type":"Point"}
}