{
  "type": "Feature",
  "properties": {
    "gn:admin1_code":"35.0",
    "gn:asciiname":"Kondagolla",
    "gn:country_code":"LK",
    "gn:dem":1379,
    "gn:feature_class":"P",
    "gn:feature_code":"PPL",
    "gn:name":"Kondagolla",
    "gn:population":0,
    "gn:timezone":"Asia/Colombo",
    "iso:country":"LK",
    "wof:name":"Kondagolla",
    "wof:placetype":"locality"
},
  "geometry": {"coordinates":[80.9967,6.8759],"type":"Point"}
}