{
  "type": "Feature",
  "properties": {
    "gn:admin1_code":"34.0",
    "gn:asciiname":"Ampanagala",
    "gn:country_code":"LK",
    "gn:dem":121,
    "gn:feature_class":"P",
    "gn:feature_code":"PPL",
    "gn:name":"Ampanagala",
    "gn:population":0,
    "gn:timezone":"Asia/Colombo",
    "iso:country":"LK",
    "name:und_x_variant":[
        "Ampangala",
        "Ampanagala"
    ],
    "wof:name":"Ampanagala",
    "wof:placetype":"locality"
},
  "geometry": {"coordinates":[80.55929999999999,6.2163],"type":"Point"}
}