{
  "type": "Feature",
  "properties": {
    "gn:admin1_code":"35.0",
    "gn:asciiname":"Kongahapilla",
    "gn:country_code":"LK",
    "gn:dem":162,
    "gn:feature_class":"P",
    "gn:feature_code":"PPL",
    "gn:name":"Kongahapilla",
    "gn:population":0,
    "gn:timezone":"Asia/Colombo",
    "iso:country":"LK",
    "wof:name":"Kongahapilla",
    "wof:placetype":"locality"
},
  "geometry": {"coordinates":[80.9953,7.1862],"type":"Point"}
}