{
  "type": "Feature",
  "properties": {
    "gn:admin1_code":"29.0",
    "gn:asciiname":"Muttettutenna",
    "gn:country_code":"LK",
    "gn:dem":538,
    "gn:feature_class":"P",
    "gn:feature_code":"PPL",
    "gn:name":"Muttettutenna",
    "gn:population":0,
    "gn:timezone":"Asia/Colombo",
    "iso:country":"LK",
    "wof:name":"Muttettutenna",
    "wof:placetype":"locality"
},
  "geometry": {"coordinates":[80.95,7.23333],"type":"Point"}
}