{
  "type": "Feature",
  "properties": {
    "gn:admin1_code":"32.0",
    "gn:asciiname":"Hinguregama",
    "gn:country_code":"LK",
    "gn:dem":49,
    "gn:feature_class":"P",
    "gn:feature_code":"PPL",
    "gn:name":"Hinguregama",
    "gn:population":0,
    "gn:timezone":"Asia/Colombo",
    "iso:country":"LK",
    "wof:name":"Hinguregama",
    "wof:placetype":"locality"
},
  "geometry": {"coordinates":[80.0408,7.5928],"type":"Point"}
}