{
  "type": "Feature",
  "properties": {
    "gn:admin1_code":"36.0",
    "gn:asciiname":"Jambugaswatta",
    "gn:country_code":"LK",
    "gn:dem":24,
    "gn:feature_class":"P",
    "gn:feature_code":"PPL",
    "gn:name":"Jambugaswatta",
    "gn:population":0,
    "gn:timezone":"Asia/Colombo",
    "iso:country":"LK",
    "name:und_x_variant":[
        "Jambugaswadiya"
    ],
    "wof:name":"Jambugaswatta",
    "wof:placetype":"locality"
},
  "geometry": {"coordinates":[79.8982,7.2732],"type":"Point"}
}