{
  "type": "Feature",
  "properties": {
    "gn:admin1_code":"37.0",
    "gn:asciiname":"Kokku Villu",
    "gn:country_code":"LK",
    "gn:dem":9,
    "gn:feature_class":"P",
    "gn:feature_code":"PPL",
    "gn:name":"Kokku Villu",
    "gn:population":0,
    "gn:timezone":"Asia/Colombo",
    "iso:country":"LK",
    "name:und_x_variant":[
        "Kokkaville",
        "Kokku Villu"
    ],
    "wof:name":"Kokku Villu",
    "wof:placetype":"locality"
},
  "geometry": {"coordinates":[81.45,8.03333],"type":"Point"}
}