{
  "type": "Feature",
  "properties": {
    "gn:admin1_code":"30.0",
    "gn:asciiname":"Beddepanwila",
    "gn:country_code":"LK",
    "gn:dem":108,
    "gn:feature_class":"P",
    "gn:feature_code":"PPL",
    "gn:name":"Beddepanwila",
    "gn:population":0,
    "gn:timezone":"Asia/Colombo",
    "iso:country":"LK",
    "wof:name":"Beddepanwila",
    "wof:placetype":"locality"
},
  "geometry": {"coordinates":[80.90000000000001,7.98333],"type":"Point"}
}