{
  "type": "Feature",
  "properties": {
    "gn:admin1_code":"30.0",
    "gn:asciiname":"Puliyankulama",
    "gn:country_code":"LK",
    "gn:dem":128,
    "gn:feature_class":"P",
    "gn:feature_code":"PPL",
    "gn:name":"Puliyankulama",
    "gn:population":0,
    "gn:timezone":"Asia/Colombo",
    "iso:country":"LK",
    "wof:name":"Puliyankulama",
    "wof:placetype":"locality"
},
  "geometry": {"coordinates":[80.6529,8.4692],"type":"Point"}
}