{
  "type": "Feature",
  "properties": {
    "gn:admin1_code":"30.0",
    "gn:asciiname":"Etawiragollewa Kudagama",
    "gn:country_code":"LK",
    "gn:dem":122,
    "gn:feature_class":"P",
    "gn:feature_code":"PPL",
    "gn:name":"Etawiragollewa Kudagama",
    "gn:population":0,
    "gn:timezone":"Asia/Colombo",
    "iso:country":"LK",
    "wof:name":"Etawiragollewa Kudagama",
    "wof:placetype":"locality"
},
  "geometry": {"coordinates":[80.6737,8.5405],"type":"Point"}
}