{
  "type": "Feature",
  "properties": {
    "gn:admin1_code":"29.0",
    "gn:asciiname":"Wewatenna",
    "gn:country_code":"LK",
    "gn:dem":639,
    "gn:feature_class":"P",
    "gn:feature_code":"PPL",
    "gn:name":"Wewatenna",
    "gn:population":0,
    "gn:timezone":"Asia/Colombo",
    "iso:country":"LK",
    "wof:name":"Wewatenna",
    "wof:placetype":"locality"
},
  "geometry": {"coordinates":[80.5993,7.1677],"type":"Point"}
}