{
  "type": "Feature",
  "properties": {
    "gn:admin1_code":"34.0",
    "gn:asciiname":"Katukoliha",
    "gn:country_code":"LK",
    "gn:dem":13,
    "gn:feature_class":"P",
    "gn:feature_code":"PPL",
    "gn:name":"Katukoliha",
    "gn:population":0,
    "gn:timezone":"Asia/Colombo",
    "iso:country":"LK",
    "name:und_x_variant":[
        "Katukohila",
        "Katukoliya"
    ],
    "wof:name":"Katukoliha",
    "wof:placetype":"locality"
},
  "geometry": {"coordinates":[80.0124,6.3902],"type":"Point"}
}