{
  "type": "Feature",
  "properties": {
    "gn:admin1_code":"32.0",
    "gn:asciiname":"Dodampotta",
    "gn:country_code":"LK",
    "gn:dem":49,
    "gn:feature_class":"P",
    "gn:feature_code":"PPL",
    "gn:name":"Dodampotta",
    "gn:population":0,
    "gn:timezone":"Asia/Colombo",
    "iso:country":"LK",
    "name:und_x_variant":[
        "Dodanpotta"
    ],
    "wof:name":"Dodampotta",
    "wof:placetype":"locality"
},
  "geometry": {"coordinates":[80.0795,7.3532],"type":"Point"}
}