{
  "type": "Feature",
  "properties": {
    "gn:admin1_code":"30.0",
    "gn:asciiname":"Kadahattewewa",
    "gn:country_code":"LK",
    "gn:dem":91,
    "gn:feature_class":"P",
    "gn:feature_code":"PPL",
    "gn:name":"Kadahattewewa",
    "gn:population":0,
    "gn:timezone":"Asia/Colombo",
    "iso:country":"LK",
    "wof:name":"Kadahattewewa",
    "wof:placetype":"locality"
},
  "geometry": {"coordinates":[80.5292,8.4853],"type":"Point"}
}