{
  "type": "Feature",
  "properties": {
    "gn:admin1_code":"34.0",
    "gn:asciiname":"Gammeddegoda",
    "gn:country_code":"LK",
    "gn:dem":-9999,
    "gn:feature_class":"P",
    "gn:feature_code":"PPL",
    "gn:name":"Gammeddegoda",
    "gn:population":0,
    "gn:timezone":"Asia/Colombo",
    "iso:country":"LK",
    "name:und_x_variant":[
        "Gammaddegoda",
        "Gammeddegoda"
    ],
    "wof:name":"Gammeddegoda",
    "wof:placetype":"locality"
},
  "geometry": {"coordinates":[80.14019999999999,6.0892],"type":"Point"}
}