{
  "type": "Feature",
  "properties": {
    "gn:admin1_code":"29.0",
    "gn:asciiname":"Urugalawatta",
    "gn:country_code":"LK",
    "gn:dem":1055,
    "gn:feature_class":"P",
    "gn:feature_code":"PPL",
    "gn:name":"Urugalawatta",
    "gn:population":0,
    "gn:timezone":"Asia/Colombo",
    "iso:country":"LK",
    "wof:name":"Urugalawatta",
    "wof:placetype":"locality"
},
  "geometry": {"coordinates":[80.6345,7.2369],"type":"Point"}
}