{
  "type": "Feature",
  "properties": {
    "gn:admin1_code":"38.0",
    "gn:asciiname":"Karaiyankulam",
    "gn:country_code":"LK",
    "gn:dem":99,
    "gn:feature_class":"P",
    "gn:feature_code":"PPL",
    "gn:name":"Karaiyankulam",
    "gn:population":0,
    "gn:timezone":"Asia/Colombo",
    "iso:country":"LK",
    "wof:name":"Karaiyankulam",
    "wof:placetype":"locality"
},
  "geometry": {"coordinates":[80.47110000000001,8.7738],"type":"Point"}
}