{
  "type": "Feature",
  "properties": {
    "gn:admin1_code":"38.0",
    "gn:asciiname":"Ilamaruthankulam",
    "gn:country_code":"LK",
    "gn:dem":77,
    "gn:feature_class":"P",
    "gn:feature_code":"PPL",
    "gn:name":"Ilamaruthankulam",
    "gn:population":0,
    "gn:timezone":"Asia/Colombo",
    "iso:country":"LK",
    "wof:name":"Ilamaruthankulam",
    "wof:placetype":"locality"
},
  "geometry": {"coordinates":[80.3892,8.7396],"type":"Point"}
}