{
  "type": "Feature",
  "properties": {
    "gn:admin1_code":"38.0",
    "gn:asciiname":"Murasumoddai",
    "gn:country_code":"LK",
    "gn:dem":14,
    "gn:feature_class":"P",
    "gn:feature_code":"PPL",
    "gn:name":"Murasumoddai",
    "gn:population":0,
    "gn:timezone":"Asia/Colombo",
    "iso:country":"LK",
    "name:und_x_variant":[
        "Murasamoddai",
        "Murasumoddal",
        "Murasumoddai"
    ],
    "wof:name":"Murasumoddai",
    "wof:placetype":"locality"
},
  "geometry": {"coordinates":[80.45,9.43333],"type":"Point"}
}