{
  "type": "Feature",
  "properties": {
    "gn:admin1_code":"32.0",
    "gn:asciiname":"Doratiyawa",
    "gn:country_code":"LK",
    "gn:dem":151,
    "gn:feature_class":"P",
    "gn:feature_code":"PPL",
    "gn:name":"Doratiyawa",
    "gn:population":0,
    "gn:timezone":"Asia/Colombo",
    "iso:country":"LK",
    "wof:name":"Doratiyawa",
    "wof:placetype":"locality"
},
  "geometry": {"coordinates":[80.383,7.4578],"type":"Point"}
}