{
  "type": "Feature",
  "properties": {
    "gn:admin1_code":"35.0",
    "gn:asciiname":"Palawatta",
    "gn:country_code":"LK",
    "gn:dem":174,
    "gn:feature_class":"P",
    "gn:feature_code":"PPL",
    "gn:name":"Palawatta",
    "gn:population":0,
    "gn:timezone":"Asia/Colombo",
    "iso:country":"LK",
    "wof:name":"Palawatta",
    "wof:placetype":"locality"
},
  "geometry": {"coordinates":[81.068,7.1275],"type":"Point"}
}