{
  "type": "Feature",
  "properties": {
    "gn:admin1_code":"30.0",
    "gn:asciiname":"Pandita Rambewa",
    "gn:country_code":"LK",
    "gn:dem":137,
    "gn:feature_class":"P",
    "gn:feature_code":"PPL",
    "gn:name":"Pandita Rambewa",
    "gn:population":0,
    "gn:timezone":"Asia/Colombo",
    "iso:country":"LK",
    "wof:name":"Pandita Rambewa",
    "wof:placetype":"locality"
},
  "geometry": {"coordinates":[80.61667,8.15],"type":"Point"}
}