{
  "type": "Feature",
  "properties": {
    "gn:admin1_code":"38.0",
    "gn:asciiname":"Kantarodai",
    "gn:country_code":"LK",
    "gn:dem":7,
    "gn:feature_class":"P",
    "gn:feature_code":"PPL",
    "gn:name":"Kantarodai",
    "gn:population":0,
    "gn:timezone":"Asia/Colombo",
    "iso:country":"LK",
    "name:tam_x_preferred":[
        "\u0b95\u0ba8\u0bcd\u0ba4\u0bb0\u0bcb\u0b9f\u0bc8"
    ],
    "name:und_x_variant":[
        "Kandarodai",
        "Kantarodai"
    ],
    "wof:name":"Kantarodai",
    "wof:placetype":"locality"
},
  "geometry": {"coordinates":[80.00749999999999,9.7521],"type":"Point"}
}