{
  "type": "Feature",
  "properties": {
    "gn:admin1_code":"29.0",
    "gn:asciiname":"Amuna",
    "gn:country_code":"LK",
    "gn:dem":679,
    "gn:feature_class":"P",
    "gn:feature_code":"PPL",
    "gn:name":"Amuna",
    "gn:population":0,
    "gn:timezone":"Asia/Colombo",
    "iso:country":"LK",
    "wof:name":"Amuna",
    "wof:placetype":"locality"
},
  "geometry": {"coordinates":[80.93333,7.25],"type":"Point"}
}