{
  "type": "Feature",
  "properties": {
    "gn:admin1_code":"32.0",
    "gn:asciiname":"Wadugama",
    "gn:country_code":"LK",
    "gn:dem":70,
    "gn:feature_class":"P",
    "gn:feature_code":"PPL",
    "gn:name":"Wadugama",
    "gn:population":0,
    "gn:timezone":"Asia/Colombo",
    "iso:country":"LK",
    "wof:name":"Wadugama",
    "wof:placetype":"locality"
},
  "geometry": {"coordinates":[80.1497,7.6302],"type":"Point"}
}