{
  "type": "Feature",
  "properties": {
    "gn:admin1_code":"36.0",
    "gn:asciiname":"Adupe",
    "gn:country_code":"LK",
    "gn:dem":95,
    "gn:feature_class":"P",
    "gn:feature_code":"PPL",
    "gn:name":"Adupe",
    "gn:population":0,
    "gn:timezone":"Asia/Colombo",
    "iso:country":"LK",
    "name:und_x_variant":[
        "Andupe"
    ],
    "wof:name":"Adupe",
    "wof:placetype":"locality"
},
  "geometry": {"coordinates":[80.15219999999999,7.2601],"type":"Point"}
}