{
  "type": "Feature",
  "properties": {
    "gn:admin1_code":"32.0",
    "gn:asciiname":"Maravanchenai",
    "gn:country_code":"LK",
    "gn:dem":8,
    "gn:feature_class":"P",
    "gn:feature_code":"PPL",
    "gn:name":"Maravanchenai",
    "gn:population":0,
    "gn:timezone":"Asia/Colombo",
    "iso:country":"LK",
    "name:und_x_variant":[
        "Maravanchanai",
        "Maravanchenai"
    ],
    "wof:name":"Maravanchenai",
    "wof:placetype":"locality"
},
  "geometry": {"coordinates":[79.7145,8.0506],"type":"Point"}
}