{
  "type": "Feature",
  "properties": {
    "gn:admin1_code":"33.0",
    "gn:asciiname":"Dehenakanda",
    "gn:country_code":"LK",
    "gn:dem":662,
    "gn:feature_class":"P",
    "gn:feature_code":"PPL",
    "gn:name":"Dehenakanda",
    "gn:population":0,
    "gn:timezone":"Asia/Colombo",
    "iso:country":"LK",
    "wof:name":"Dehenakanda",
    "wof:placetype":"locality"
},
  "geometry": {"coordinates":[80.54170000000001,6.7232],"type":"Point"}
}