{
  "type": "Feature",
  "properties": {
    "gn:admin1_code":"29.0",
    "gn:asciiname":"Medakanda",
    "gn:country_code":"LK",
    "gn:dem":1263,
    "gn:feature_class":"P",
    "gn:feature_code":"PPL",
    "gn:name":"Medakanda",
    "gn:population":0,
    "gn:timezone":"Asia/Colombo",
    "iso:country":"LK",
    "wof:name":"Medakanda",
    "wof:placetype":"locality"
},
  "geometry": {"coordinates":[80.6681,7.0264],"type":"Point"}
}