{
  "type": "Feature",
  "properties": {
    "gn:admin1_code":"38.0",
    "gn:asciiname":"Karadikkuli",
    "gn:country_code":"LK",
    "gn:dem":13,
    "gn:feature_class":"P",
    "gn:feature_code":"PPL",
    "gn:name":"Karadikkuli",
    "gn:population":0,
    "gn:timezone":"Asia/Colombo",
    "iso:country":"LK",
    "name:und_x_variant":[
        "Karadikuly",
        "Karadikkuli"
    ],
    "wof:name":"Karadikkuli",
    "wof:placetype":"locality"
},
  "geometry": {"coordinates":[79.9396,8.6073],"type":"Point"}
}