{
  "type": "Feature",
  "properties": {
    "gn:admin1_code":"32.0",
    "gn:asciiname":"Aluthkurumulla",
    "gn:country_code":"LK",
    "gn:dem":28,
    "gn:feature_class":"P",
    "gn:feature_code":"PPL",
    "gn:name":"Aluthkurumulla",
    "gn:population":0,
    "gn:timezone":"Asia/Colombo",
    "iso:country":"LK",
    "wof:name":"Aluthkurumulla",
    "wof:placetype":"locality"
},
  "geometry": {"coordinates":[79.89319999999999,7.6005],"type":"Point"}
}