{
  "type": "Feature",
  "properties": {
    "gn:admin1_code":"32.0",
    "gn:asciiname":"Hawariyawa",
    "gn:country_code":"LK",
    "gn:dem":138,
    "gn:feature_class":"P",
    "gn:feature_code":"PPL",
    "gn:name":"Hawariyawa",
    "gn:population":0,
    "gn:timezone":"Asia/Colombo",
    "iso:country":"LK",
    "wof:name":"Hawariyawa",
    "wof:placetype":"locality"
},
  "geometry": {"coordinates":[80.4498,7.5841],"type":"Point"}
}