{
  "type": "Feature",
  "properties": {
    "gn:admin1_code":"34.0",
    "gn:asciiname":"Gamagoda",
    "gn:country_code":"LK",
    "gn:dem":24,
    "gn:feature_class":"P",
    "gn:feature_code":"PPL",
    "gn:name":"Gamagoda",
    "gn:population":0,
    "gn:timezone":"Asia/Colombo",
    "iso:country":"LK",
    "name:und_x_variant":[
        "Gamegoda"
    ],
    "wof:name":"Gamagoda",
    "wof:placetype":"locality"
},
  "geometry": {"coordinates":[80.2869,6.0189],"type":"Point"}
}