{
  "type": "Feature",
  "properties": {
    "gn:admin1_code":"34.0",
    "gn:asciiname":"Suriyapokuna",
    "gn:country_code":"LK",
    "gn:dem":57,
    "gn:feature_class":"P",
    "gn:feature_code":"PPL",
    "gn:name":"Suriyapokuna",
    "gn:population":0,
    "gn:timezone":"Asia/Colombo",
    "iso:country":"LK",
    "wof:name":"Suriyapokuna",
    "wof:placetype":"locality"
},
  "geometry": {"coordinates":[80.84690000000001,6.2164],"type":"Point"}
}