{
  "type": "Feature",
  "properties": {
    "gn:admin1_code":"35.0",
    "gn:asciiname":"Weragoda",
    "gn:country_code":"LK",
    "gn:dem":248,
    "gn:feature_class":"P",
    "gn:feature_code":"PPL",
    "gn:name":"Weragoda",
    "gn:population":0,
    "gn:timezone":"Asia/Colombo",
    "iso:country":"LK",
    "wof:name":"Weragoda",
    "wof:placetype":"locality"
},
  "geometry": {"coordinates":[81.2517,6.846],"type":"Point"}
}