{
  "type": "Feature",
  "properties": {
    "gn:admin1_code":"35.0",
    "gn:asciiname":"Aluthwela North",
    "gn:country_code":"LK",
    "gn:dem":1222,
    "gn:feature_class":"P",
    "gn:feature_code":"PPL",
    "gn:name":"Aluthwela North",
    "gn:population":0,
    "gn:timezone":"Asia/Colombo",
    "iso:country":"LK",
    "wof:name":"Aluthwela North",
    "wof:placetype":"locality"
},
  "geometry": {"coordinates":[80.9438,6.8185],"type":"Point"}
}