{
  "type": "Feature",
  "properties": {
    "gn:admin1_code":"33.0",
    "gn:asciiname":"Ihala Karawita",
    "gn:country_code":"LK",
    "gn:dem":124,
    "gn:feature_class":"P",
    "gn:feature_code":"PPL",
    "gn:name":"Ihala Karawita",
    "gn:population":0,
    "gn:timezone":"Asia/Colombo",
    "iso:country":"LK",
    "wof:name":"Ihala Karawita",
    "wof:placetype":"locality"
},
  "geometry": {"coordinates":[80.43170000000001,6.5652],"type":"Point"}
}