{
  "type": "Feature",
  "properties": {
    "gn:admin1_code":"33.0",
    "gn:asciiname":"Danduhethakina",
    "gn:country_code":"LK",
    "gn:dem":153,
    "gn:feature_class":"P",
    "gn:feature_code":"PPL",
    "gn:name":"Danduhethakina",
    "gn:population":0,
    "gn:timezone":"Asia/Colombo",
    "iso:country":"LK",
    "wof:name":"Danduhethakina",
    "wof:placetype":"locality"
},
  "geometry": {"coordinates":[80.76819999999999,6.3042],"type":"Point"}
}