{
  "type": "Feature",
  "properties": {
    "gn:admin1_code":"33.0",
    "gn:asciiname":"Kethethenna",
    "gn:country_code":"LK",
    "gn:dem":152,
    "gn:feature_class":"P",
    "gn:feature_code":"PPL",
    "gn:name":"Kethethenna",
    "gn:population":0,
    "gn:timezone":"Asia/Colombo",
    "iso:country":"LK",
    "name:und_x_variant":[
        "Ketetenna"
    ],
    "wof:name":"Kethethenna",
    "wof:placetype":"locality"
},
  "geometry": {"coordinates":[80.5714,6.5873],"type":"Point"}
}