{
  "type": "Feature",
  "properties": {
    "gn:admin1_code":"33.0",
    "gn:asciiname":"Udagama",
    "gn:country_code":"LK",
    "gn:dem":812,
    "gn:feature_class":"P",
    "gn:feature_code":"PPL",
    "gn:name":"Udagama",
    "gn:population":0,
    "gn:timezone":"Asia/Colombo",
    "iso:country":"LK",
    "name:fas_x_preferred":[
        "\u06cc\u0648\u062f\u0627\u06af\u0627\u0645\u0627"
    ],
    "name:urd_x_preferred":[
        "\u0627\u0688\u0627\u06af\u0627\u0645\u0627"
    ],
    "wof:name":"Udagama",
    "wof:placetype":"locality"
},
  "geometry": {"coordinates":[80.67449999999999,6.7284],"type":"Point"}
}