{
  "type": "Feature",
  "properties": {
    "gn:admin1_code":"36.0",
    "gn:asciiname":"Matammana",
    "gn:country_code":"LK",
    "gn:dem":30,
    "gn:feature_class":"P",
    "gn:feature_code":"PPL",
    "gn:name":"Matammana",
    "gn:population":0,
    "gn:timezone":"Asia/Colombo",
    "iso:country":"LK",
    "name:und_x_variant":[
        "Matamana",
        "Matammana"
    ],
    "wof:name":"Matammana",
    "wof:placetype":"locality"
},
  "geometry": {"coordinates":[79.96080000000001,7.1522],"type":"Point"}
}