{
  "type": "Feature",
  "properties": {
    "gn:admin1_code":"33.0",
    "gn:asciiname":"Elangipitiya",
    "gn:country_code":"LK",
    "gn:dem":667,
    "gn:feature_class":"P",
    "gn:feature_code":"PPL",
    "gn:name":"Elangipitiya",
    "gn:population":0,
    "gn:timezone":"Asia/Colombo",
    "iso:country":"LK",
    "wof:name":"Elangipitiya",
    "wof:placetype":"locality"
},
  "geometry": {"coordinates":[80.4288,7.1591],"type":"Point"}
}