{
  "type": "Feature",
  "properties": {
    "gn:admin1_code":"35.0",
    "gn:asciiname":"Udakandegama",
    "gn:country_code":"LK",
    "gn:dem":953,
    "gn:feature_class":"P",
    "gn:feature_code":"PPL",
    "gn:name":"Udakandegama",
    "gn:population":0,
    "gn:timezone":"Asia/Colombo",
    "iso:country":"LK",
    "name:und_x_variant":[
        "Udakanda",
        "Udakandegama"
    ],
    "wof:name":"Udakandegama",
    "wof:placetype":"locality"
},
  "geometry": {"coordinates":[81.09520000000001,7.0459],"type":"Point"}
}