{
  "type": "Feature",
  "properties": {
    "gn:admin1_code":"35.0",
    "gn:asciiname":"Kandiyantalawa",
    "gn:country_code":"LK",
    "gn:dem":458,
    "gn:feature_class":"P",
    "gn:feature_code":"PPL",
    "gn:name":"Kandiyantalawa",
    "gn:population":0,
    "gn:timezone":"Asia/Colombo",
    "iso:country":"LK",
    "wof:name":"Kandiyantalawa",
    "wof:placetype":"locality"
},
  "geometry": {"coordinates":[81.2136,6.8864],"type":"Point"}
}