{
  "type": "Feature",
  "properties": {
    "gn:admin1_code":"34.0",
    "gn:asciiname":"Wiharahena",
    "gn:country_code":"LK",
    "gn:dem":519,
    "gn:feature_class":"P",
    "gn:feature_code":"PPL",
    "gn:name":"Wiharahena",
    "gn:population":0,
    "gn:timezone":"Asia/Colombo",
    "iso:country":"LK",
    "name:und_x_variant":[
        "Viharahena"
    ],
    "wof:name":"Wiharahena",
    "wof:placetype":"locality"
},
  "geometry": {"coordinates":[80.5903,6.3664],"type":"Point"}
}