{
  "type": "Feature",
  "properties": {
    "gn:admin1_code":"34.0",
    "gn:asciiname":"Kumburekanda",
    "gn:country_code":"LK",
    "gn:dem":473,
    "gn:feature_class":"P",
    "gn:feature_code":"PPL",
    "gn:name":"Kumburekanda",
    "gn:population":0,
    "gn:timezone":"Asia/Colombo",
    "iso:country":"LK",
    "wof:name":"Kumburekanda",
    "wof:placetype":"locality"
},
  "geometry": {"coordinates":[80.43333,6.35],"type":"Point"}
}