{
  "type": "Feature",
  "properties": {
    "gn:admin1_code":"34.0",
    "gn:asciiname":"Wemulla",
    "gn:country_code":"LK",
    "gn:dem":15,
    "gn:feature_class":"P",
    "gn:feature_code":"PPL",
    "gn:name":"Wemulla",
    "gn:population":0,
    "gn:timezone":"Asia/Colombo",
    "iso:country":"LK",
    "wof:name":"Wemulla",
    "wof:placetype":"locality"
},
  "geometry": {"coordinates":[80.2701,6.0419],"type":"Point"}
}