{
  "type": "Feature",
  "properties": {
    "gn:admin1_code":"33.0",
    "gn:asciiname":"Aldorathenna",
    "gn:country_code":"LK",
    "gn:dem":517,
    "gn:feature_class":"P",
    "gn:feature_code":"PPL",
    "gn:name":"Aldorathenna",
    "gn:population":0,
    "gn:timezone":"Asia/Colombo",
    "iso:country":"LK",
    "wof:name":"Aldorathenna",
    "wof:placetype":"locality"
},
  "geometry": {"coordinates":[80.7715,6.6151],"type":"Point"}
}