{
  "type": "Feature",
  "properties": {
    "gn:admin1_code":"32.0",
    "gn:asciiname":"Udubodagama",
    "gn:cc2":"LK",
    "gn:country_code":"LK",
    "gn:dem":97,
    "gn:feature_class":"P",
    "gn:feature_code":"PPL",
    "gn:name":"Udubodagama",
    "gn:population":0,
    "gn:timezone":"Asia/Colombo",
    "iso:country":"LK",
    "name:und_x_variant":[
        "Udugodagama",
        "Udubodagama"
    ],
    "wof:name":"Udubodagama",
    "wof:placetype":"locality"
},
  "geometry": {"coordinates":[80.34999999999999,7.68333],"type":"Point"}
}