{
  "type": "Feature",
  "properties": {
    "gn:admin1_code":"37.0",
    "gn:asciiname":"Muhathuvaram",
    "gn:country_code":"LK",
    "gn:dem":9,
    "gn:feature_class":"P",
    "gn:feature_code":"PPL",
    "gn:name":"Muhathuvaram",
    "gn:population":0,
    "gn:timezone":"Asia/Colombo",
    "iso:country":"LK",
    "name:und_x_variant":[
        "Muhattuvaram",
        "Muhathuvaram"
    ],
    "wof:name":"Muhathuvaram",
    "wof:placetype":"locality"
},
  "geometry": {"coordinates":[81.70399999999999,7.7403],"type":"Point"}
}