{
  "type": "Feature",
  "properties": {
    "gn:admin1_code":"29.0",
    "gn:asciiname":"Vilanaudagama",
    "gn:country_code":"LK",
    "gn:dem":652,
    "gn:feature_class":"P",
    "gn:feature_code":"PPL",
    "gn:name":"Vilanaudagama",
    "gn:population":0,
    "gn:timezone":"Asia/Colombo",
    "iso:country":"LK",
    "wof:name":"Vilanaudagama",
    "wof:placetype":"locality"
},
  "geometry": {"coordinates":[80.5908,7.4219],"type":"Point"}
}