{
  "type": "Feature",
  "properties": {
    "gn:admin1_code":"34.0",
    "gn:asciiname":"Akunadiwela",
    "gn:country_code":"LK",
    "gn:dem":107,
    "gn:feature_class":"P",
    "gn:feature_code":"PPL",
    "gn:name":"Akunadiwela",
    "gn:population":0,
    "gn:timezone":"Asia/Colombo",
    "iso:country":"LK",
    "wof:name":"Akunadiwela",
    "wof:placetype":"locality"
},
  "geometry": {"coordinates":[80.65000000000001,6.06667],"type":"Point"}
}