{
  "type": "Feature",
  "properties": {
    "gn:admin1_code":"33.0",
    "gn:asciiname":"Kolandagala",
    "gn:country_code":"LK",
    "gn:dem":78,
    "gn:feature_class":"P",
    "gn:feature_code":"PPL",
    "gn:name":"Kolandagala",
    "gn:population":0,
    "gn:timezone":"Asia/Colombo",
    "iso:country":"LK",
    "wof:name":"Kolandagala",
    "wof:placetype":"locality"
},
  "geometry": {"coordinates":[80.4555,6.663],"type":"Point"}
}