{
  "type": "Feature",
  "properties": {
    "gn:admin1_code":"29.0",
    "gn:asciiname":"Ruwanidalaketiya",
    "gn:country_code":"LK",
    "gn:dem":982,
    "gn:feature_class":"P",
    "gn:feature_code":"PPL",
    "gn:name":"Ruwanidalaketiya",
    "gn:population":0,
    "gn:timezone":"Asia/Colombo",
    "iso:country":"LK",
    "wof:name":"Ruwanidalaketiya",
    "wof:placetype":"locality"
},
  "geometry": {"coordinates":[80.89490000000001,7.0955],"type":"Point"}
}