{
  "type": "Feature",
  "properties": {
    "gn:admin1_code":"37.0",
    "gn:asciiname":"Thalavai",
    "gn:country_code":"LK",
    "gn:dem":11,
    "gn:feature_class":"P",
    "gn:feature_code":"PPL",
    "gn:name":"Thalavai",
    "gn:population":0,
    "gn:timezone":"Asia/Colombo",
    "iso:country":"LK",
    "name:und_x_variant":[
        "Talavai",
        "Thalawai",
        "Thalavai"
    ],
    "wof:name":"Thalavai",
    "wof:placetype":"locality"
},
  "geometry": {"coordinates":[81.61069999999999,7.8026],"type":"Point"}
}