{
  "type": "Feature",
  "properties": {
    "gn:admin1_code":"38.0",
    "gn:asciiname":"Uduthurai",
    "gn:country_code":"LK",
    "gn:dem":9,
    "gn:feature_class":"P",
    "gn:feature_code":"PPL",
    "gn:name":"Uduthurai",
    "gn:population":0,
    "gn:timezone":"Asia/Colombo",
    "iso:country":"LK",
    "name:nor_x_preferred":[
        "Uduthurai"
    ],
    "name:und_x_variant":[
        "Udutuvai",
        "Udutturai"
    ],
    "wof:name":"Uduthurai",
    "wof:placetype":"locality"
},
  "geometry": {"coordinates":[80.42084,9.60111],"type":"Point"}
}