{
  "type": "Feature",
  "properties": {
    "gn:admin1_code":"33.0",
    "gn:asciiname":"Aswedduma",
    "gn:country_code":"LK",
    "gn:dem":503,
    "gn:feature_class":"P",
    "gn:feature_code":"PPL",
    "gn:name":"Aswedduma",
    "gn:population":0,
    "gn:timezone":"Asia/Colombo",
    "iso:country":"LK",
    "name:und_x_variant":[
        "Assedduma"
    ],
    "wof:name":"Aswedduma",
    "wof:placetype":"locality"
},
  "geometry": {"coordinates":[80.5539,6.7097],"type":"Point"}
}