{
  "type": "Feature",
  "properties": {
    "gn:admin1_code":"35.0",
    "gn:asciiname":"Etimole",
    "gn:country_code":"LK",
    "gn:dem":117,
    "gn:feature_class":"P",
    "gn:feature_code":"PPL",
    "gn:name":"Etimole",
    "gn:population":0,
    "gn:timezone":"Asia/Colombo",
    "iso:country":"LK",
    "wof:name":"Etimole",
    "wof:placetype":"locality"
},
  "geometry": {"coordinates":[81.45,6.81667],"type":"Point"}
}