{
  "type": "Feature",
  "properties": {
    "gn:admin1_code":"32.0",
    "gn:asciiname":"Dematewa",
    "gn:country_code":"LK",
    "gn:dem":91,
    "gn:feature_class":"P",
    "gn:feature_code":"PPL",
    "gn:name":"Dematewa",
    "gn:population":0,
    "gn:timezone":"Asia/Colombo",
    "iso:country":"LK",
    "wof:name":"Dematewa",
    "wof:placetype":"locality"
},
  "geometry": {"coordinates":[80.3222,8.0811],"type":"Point"}
}