{
  "type": "Feature",
  "properties": {
    "gn:admin1_code":"33.0",
    "gn:asciiname":"Hinatipone",
    "gn:country_code":"LK",
    "gn:dem":350,
    "gn:feature_class":"P",
    "gn:feature_code":"PPL",
    "gn:name":"Hinatipone",
    "gn:population":0,
    "gn:timezone":"Asia/Colombo",
    "iso:country":"LK",
    "wof:name":"Hinatipone",
    "wof:placetype":"locality"
},
  "geometry": {"coordinates":[80.4927,7.2332],"type":"Point"}
}