{
  "type": "Feature",
  "properties": {
    "gn:admin1_code":"35.0",
    "gn:asciiname":"Ilukmulla",
    "gn:country_code":"LK",
    "gn:dem":368,
    "gn:feature_class":"P",
    "gn:feature_code":"PPL",
    "gn:name":"Ilukmulla",
    "gn:population":0,
    "gn:timezone":"Asia/Colombo",
    "iso:country":"LK",
    "wof:name":"Ilukmulla",
    "wof:placetype":"locality"
},
  "geometry": {"coordinates":[81.2411,6.8946],"type":"Point"}
}