{
  "type": "Feature",
  "properties": {
    "gn:admin1_code":"32.0",
    "gn:asciiname":"Gawaragane",
    "gn:country_code":"LK",
    "gn:dem":67,
    "gn:feature_class":"P",
    "gn:feature_code":"PPL",
    "gn:name":"Gawaragane",
    "gn:population":0,
    "gn:timezone":"Asia/Colombo",
    "iso:country":"LK",
    "wof:name":"Gawaragane",
    "wof:placetype":"locality"
},
  "geometry": {"coordinates":[80.1951,7.9281],"type":"Point"}
}