{
  "type": "Feature",
  "properties": {
    "gn:admin1_code":"36.0",
    "gn:asciiname":"Halgampitiya",
    "gn:country_code":"LK",
    "gn:dem":36,
    "gn:feature_class":"P",
    "gn:feature_code":"PPL",
    "gn:name":"Halgampitiya",
    "gn:population":0,
    "gn:timezone":"Asia/Colombo",
    "iso:country":"LK",
    "wof:name":"Halgampitiya",
    "wof:placetype":"locality"
},
  "geometry": {"coordinates":[80.0376,7.1137],"type":"Point"}
}