{
  "type": "Feature",
  "properties": {
    "gn:admin1_code":"36.0",
    "gn:asciiname":"Peralanda",
    "gn:country_code":"LK",
    "gn:dem":26,
    "gn:feature_class":"P",
    "gn:feature_code":"PPL",
    "gn:name":"Peralanda",
    "gn:population":0,
    "gn:timezone":"Asia/Colombo",
    "iso:country":"LK",
    "wof:name":"Peralanda",
    "wof:placetype":"locality"
},
  "geometry": {"coordinates":[79.91459999999999,7.0379],"type":"Point"}
}