{
  "type": "Feature",
  "properties": {
    "gn:admin1_code":"29.0",
    "gn:asciiname":"Good Wood Colony",
    "gn:country_code":"LK",
    "gn:dem":1337,
    "gn:feature_class":"P",
    "gn:feature_code":"PPL",
    "gn:name":"Good Wood Colony",
    "gn:population":0,
    "gn:timezone":"Asia/Colombo",
    "iso:country":"LK",
    "wof:name":"Good Wood Colony",
    "wof:placetype":"locality"
},
  "geometry": {"coordinates":[80.78870000000001,7.0574],"type":"Point"}
}