{
  "type": "Feature",
  "properties": {
    "gn:admin1_code":"29.0",
    "gn:asciiname":"Hanwella",
    "gn:country_code":"LK",
    "gn:dem":270,
    "gn:feature_class":"P",
    "gn:feature_code":"PPL",
    "gn:name":"Hanwella",
    "gn:population":0,
    "gn:timezone":"Asia/Colombo",
    "iso:country":"LK",
    "name:cat_x_preferred":[
        "Hanwella"
    ],
    "name:sin_x_preferred":[
        "\u0dc4\u0d82\u0dc0\u0dd0\u0dbd\u0dca\u0dbd"
    ],
    "name:tam_x_preferred":[
        "\u0bb9\u0ba9\u0bcd\u0bb5\u0bc6\u0bb2\u0bcd\u0bb2\u0bc8"
    ],
    "wof:name":"Hanwella",
    "wof:placetype":"locality"
},
  "geometry": {"coordinates":[80.84090999999999,7.5212],"type":"Point"}
}