{
  "type": "Feature",
  "properties": {
    "gn:admin1_code":"34.0",
    "gn:asciiname":"Batuwita",
    "gn:cc2":"LK",
    "gn:country_code":"LK",
    "gn:dem":21,
    "gn:feature_class":"P",
    "gn:feature_code":"PPL",
    "gn:name":"Batuwita",
    "gn:population":0,
    "gn:timezone":"Asia/Colombo",
    "iso:country":"LK",
    "name:und_x_variant":[
        "Batuwila",
        "Batuwita"
    ],
    "wof:name":"Batuwita",
    "wof:placetype":"locality"
},
  "geometry": {"coordinates":[80.58333,6.03333],"type":"Point"}
}