{
  "type": "Feature",
  "properties": {
    "gn:admin1_code":"30.0",
    "gn:asciiname":"Puliyankulama",
    "gn:country_code":"LK",
    "gn:dem":89,
    "gn:feature_class":"P",
    "gn:feature_code":"PPL",
    "gn:name":"Puliyankulama",
    "gn:population":0,
    "gn:timezone":"Asia/Colombo",
    "iso:country":"LK",
    "wof:name":"Puliyankulama",
    "wof:placetype":"locality"
},
  "geometry": {"coordinates":[80.4357,8.3667],"type":"Point"}
}