{
  "type": "Feature",
  "properties": {
    "gn:admin1_code":"34.0",
    "gn:asciiname":"Opatha",
    "gn:country_code":"LK",
    "gn:dem":30,
    "gn:feature_class":"P",
    "gn:feature_code":"PPL",
    "gn:name":"Opatha",
    "gn:population":0,
    "gn:timezone":"Asia/Colombo",
    "iso:country":"LK",
    "name:und_x_variant":[
        "Opata"
    ],
    "wof:name":"Opatha",
    "wof:placetype":"locality"
},
  "geometry": {"coordinates":[80.1412,6.3587],"type":"Point"}
}