{
  "type": "Feature",
  "properties": {
    "gn:admin1_code":"35.0",
    "gn:asciiname":"Itanawatte",
    "gn:country_code":"LK",
    "gn:dem":298,
    "gn:feature_class":"P",
    "gn:feature_code":"PPL",
    "gn:name":"Itanawatte",
    "gn:population":0,
    "gn:timezone":"Asia/Colombo",
    "iso:country":"LK",
    "name:und_x_variant":[
        "Itanawatte Megodagama"
    ],
    "wof:name":"Itanawatte",
    "wof:placetype":"locality"
},
  "geometry": {"coordinates":[81.2132,7.1085],"type":"Point"}
}