{
  "type": "Feature",
  "properties": {
    "gn:admin1_code":"32.0",
    "gn:asciiname":"Welpothuwewa",
    "gn:country_code":"LK",
    "gn:dem":39,
    "gn:feature_class":"P",
    "gn:feature_code":"PPL",
    "gn:name":"Welpothuwewa",
    "gn:population":0,
    "gn:timezone":"Asia/Colombo",
    "iso:country":"LK",
    "name:und_x_variant":[
        "Welpotuwewa",
        "Welpothuwewa"
    ],
    "wof:name":"Welpothuwewa",
    "wof:placetype":"locality"
},
  "geometry": {"coordinates":[80.0125,7.6926],"type":"Point"}
}