{
  "type": "Feature",
  "properties": {
    "gn:admin1_code":"35.0",
    "gn:asciiname":"Mahagama",
    "gn:country_code":"LK",
    "gn:dem":86,
    "gn:feature_class":"P",
    "gn:feature_code":"PPL",
    "gn:name":"Mahagama",
    "gn:population":0,
    "gn:timezone":"Asia/Colombo",
    "iso:country":"LK",
    "name:bih_x_preferred":[
        "\u092e\u0939\u0917\u093e\u092e\u093e"
    ],
    "name:hin_x_preferred":[
        "\u092e\u0939\u0917\u093e\u092e\u093e"
    ],
    "wof:name":"Mahagama",
    "wof:placetype":"locality"
},
  "geometry": {"coordinates":[80.9823,6.3597],"type":"Point"}
}