{
  "type": "Feature",
  "properties": {
    "gn:admin1_code":"32.0",
    "gn:asciiname":"Kotadalupota",
    "gn:country_code":"LK",
    "gn:dem":140,
    "gn:feature_class":"P",
    "gn:feature_code":"PPL",
    "gn:name":"Kotadalupota",
    "gn:population":0,
    "gn:timezone":"Asia/Colombo",
    "iso:country":"LK",
    "wof:name":"Kotadalupota",
    "wof:placetype":"locality"
},
  "geometry": {"coordinates":[80.44840000000001,7.4794],"type":"Point"}
}