{
  "type": "Feature",
  "properties": {
    "gn:admin1_code":"36.0",
    "gn:asciiname":"Weboda North",
    "gn:country_code":"LK",
    "gn:dem":41,
    "gn:feature_class":"P",
    "gn:feature_code":"PPL",
    "gn:name":"Weboda North",
    "gn:population":0,
    "gn:timezone":"Asia/Colombo",
    "iso:country":"LK",
    "name:und_x_variant":[
        "Weboda"
    ],
    "wof:name":"Weboda North",
    "wof:placetype":"locality"
},
  "geometry": {"coordinates":[79.99460000000001,7.0176],"type":"Point"}
}