{
  "type": "Feature",
  "properties": {
    "gn:admin1_code":"29.0",
    "gn:asciiname":"Deniyakumbura",
    "gn:country_code":"LK",
    "gn:dem":392,
    "gn:feature_class":"P",
    "gn:feature_code":"PPL",
    "gn:name":"Deniyakumbura",
    "gn:population":0,
    "gn:timezone":"Asia/Colombo",
    "iso:country":"LK",
    "name:und_x_variant":[
        "Deniyekumbura"
    ],
    "wof:name":"Deniyakumbura",
    "wof:placetype":"locality"
},
  "geometry": {"coordinates":[80.6473,7.4644],"type":"Point"}
}