{
  "type": "Feature",
  "properties": {
    "gn:admin1_code":"34.0",
    "gn:asciiname":"Mawadawila",
    "gn:country_code":"LK",
    "gn:dem":27,
    "gn:feature_class":"P",
    "gn:feature_code":"PPL",
    "gn:name":"Mawadawila",
    "gn:population":0,
    "gn:timezone":"Asia/Colombo",
    "iso:country":"LK",
    "name:und_x_variant":[
        "Mawadawella",
        "Mawadawila"
    ],
    "wof:name":"Mawadawila",
    "wof:placetype":"locality"
},
  "geometry": {"coordinates":[80.1534,6.1303],"type":"Point"}
}