{
  "type": "Feature",
  "properties": {
    "gn:admin1_code":"32.0",
    "gn:asciiname":"Ihala Talangedara",
    "gn:cc2":"LK",
    "gn:country_code":"LK",
    "gn:dem":57,
    "gn:feature_class":"P",
    "gn:feature_code":"PPL",
    "gn:name":"Ihala Talangedara",
    "gn:population":0,
    "gn:timezone":"Asia/Colombo",
    "iso:country":"LK",
    "name:und_x_variant":[
        "Ihala Thalangedera",
        "Ihala Talangedara"
    ],
    "wof:name":"Ihala Talangedara",
    "wof:placetype":"locality"
},
  "geometry": {"coordinates":[80.15000000000001,7.75],"type":"Point"}
}