{
  "type": "Feature",
  "properties": {
    "gn:admin1_code":"32.0",
    "gn:asciiname":"Rangama",
    "gn:country_code":"LK",
    "gn:dem":111,
    "gn:feature_class":"P",
    "gn:feature_code":"PPL",
    "gn:name":"Rangama",
    "gn:population":0,
    "gn:timezone":"Asia/Colombo",
    "iso:country":"LK",
    "wof:name":"Rangama",
    "wof:placetype":"locality"
},
  "geometry": {"coordinates":[80.3706,7.5697],"type":"Point"}
}