{
  "type": "Feature",
  "properties": {
    "gn:admin1_code":"34.0",
    "gn:asciiname":"Makarayawala",
    "gn:country_code":"LK",
    "gn:dem":207,
    "gn:feature_class":"P",
    "gn:feature_code":"PPL",
    "gn:name":"Makarayawala",
    "gn:population":0,
    "gn:timezone":"Asia/Colombo",
    "iso:country":"LK",
    "wof:name":"Makarayawala",
    "wof:placetype":"locality"
},
  "geometry": {"coordinates":[80.78333000000001,7.93333],"type":"Point"}
}