{
  "type": "Feature",
  "properties": {
    "gn:admin1_code":"29.0",
    "gn:asciiname":"Hapudandawala",
    "gn:cc2":"LK",
    "gn:country_code":"LK",
    "gn:dem":599,
    "gn:feature_class":"P",
    "gn:feature_code":"PPL",
    "gn:name":"Hapudandawala",
    "gn:population":0,
    "gn:timezone":"Asia/Colombo",
    "iso:country":"LK",
    "name:und_x_variant":[
        "Hapudandawela",
        "Hapudandawala"
    ],
    "wof:name":"Hapudandawala",
    "wof:placetype":"locality"
},
  "geometry": {"coordinates":[80.88333,7.35],"type":"Point"}
}