{
  "type": "Feature",
  "properties": {
    "gn:admin1_code":"29.0",
    "gn:asciiname":"Halmehikandura",
    "gn:country_code":"LK",
    "gn:dem":591,
    "gn:feature_class":"P",
    "gn:feature_code":"PPL",
    "gn:name":"Halmehikandura",
    "gn:population":0,
    "gn:timezone":"Asia/Colombo",
    "iso:country":"LK",
    "wof:name":"Halmehikandura",
    "wof:placetype":"locality"
},
  "geometry": {"coordinates":[80.6073,7.2587],"type":"Point"}
}