{
  "type": "Feature",
  "properties": {
    "gn:admin1_code":"29.0",
    "gn:asciiname":"Ampitigoda",
    "gn:country_code":"LK",
    "gn:dem":892,
    "gn:feature_class":"P",
    "gn:feature_code":"PPL",
    "gn:name":"Ampitigoda",
    "gn:population":0,
    "gn:timezone":"Asia/Colombo",
    "iso:country":"LK",
    "name:fas_x_preferred":[
        "\u0627\u0645\u067e\u06cc\u062a\u06cc\u06af\u0648\u062f\u0627"
    ],
    "wof:name":"Ampitigoda",
    "wof:placetype":"locality"
},
  "geometry": {"coordinates":[80.7871,7.0729],"type":"Point"}
}