{
  "type": "Feature",
  "properties": {
    "gn:admin1_code":"34.0",
    "gn:asciiname":"Alupotdeniya",
    "gn:country_code":"LK",
    "gn:dem":360,
    "gn:feature_class":"P",
    "gn:feature_code":"PPL",
    "gn:name":"Alupotdeniya",
    "gn:population":0,
    "gn:timezone":"Asia/Colombo",
    "iso:country":"LK",
    "wof:name":"Alupotdeniya",
    "wof:placetype":"locality"
},
  "geometry": {"coordinates":[80.70480000000001,6.3022],"type":"Point"}
}