{
  "type": "Feature",
  "properties": {
    "gn:admin1_code":"33.0",
    "gn:asciiname":"Medagaladeniya",
    "gn:country_code":"LK",
    "gn:dem":173,
    "gn:feature_class":"P",
    "gn:feature_code":"PPL",
    "gn:name":"Medagaladeniya",
    "gn:population":0,
    "gn:timezone":"Asia/Colombo",
    "iso:country":"LK",
    "wof:name":"Medagaladeniya",
    "wof:placetype":"locality"
},
  "geometry": {"coordinates":[80.3597,7.3553],"type":"Point"}
}