{
  "type": "Feature",
  "properties": {
    "gn:admin1_code":"38.0",
    "gn:asciiname":"Kalapoomy",
    "gn:country_code":"LK",
    "gn:dem":8,
    "gn:feature_class":"P",
    "gn:feature_code":"PPL",
    "gn:name":"Kalapoomy",
    "gn:population":0,
    "gn:timezone":"Asia/Colombo",
    "iso:country":"LK",
    "name:und_x_variant":[
        "Kalapumi"
    ],
    "wof:name":"Kalapoomy",
    "wof:placetype":"locality"
},
  "geometry": {"coordinates":[79.87179999999999,9.7188],"type":"Point"}
}