{
  "type": "Feature",
  "properties": {
    "gn:admin1_code":"38.0",
    "gn:asciiname":"Kadduvan",
    "gn:country_code":"LK",
    "gn:dem":10,
    "gn:feature_class":"P",
    "gn:feature_code":"PPL",
    "gn:name":"Kadduvan",
    "gn:population":0,
    "gn:timezone":"Asia/Colombo",
    "iso:country":"LK",
    "wof:name":"Kadduvan",
    "wof:placetype":"locality"
},
  "geometry": {"coordinates":[80.03333000000001,9.76667],"type":"Point"}
}