{
  "type": "Feature",
  "properties": {
    "gn:admin1_code":"32.0",
    "gn:asciiname":"Gedarawela",
    "gn:country_code":"LK",
    "gn:dem":83,
    "gn:feature_class":"P",
    "gn:feature_code":"PPL",
    "gn:name":"Gedarawela",
    "gn:population":0,
    "gn:timezone":"Asia/Colombo",
    "iso:country":"LK",
    "wof:name":"Gedarawela",
    "wof:placetype":"locality"
},
  "geometry": {"coordinates":[80.2401,7.488],"type":"Point"}
}