{
  "type": "Feature",
  "properties": {
    "gn:admin1_code":"32.0",
    "gn:asciiname":"Godigamuwa",
    "gn:country_code":"LK",
    "gn:dem":100,
    "gn:feature_class":"P",
    "gn:feature_code":"PPL",
    "gn:name":"Godigamuwa",
    "gn:population":0,
    "gn:timezone":"Asia/Colombo",
    "iso:country":"LK",
    "wof:name":"Godigamuwa",
    "wof:placetype":"locality"
},
  "geometry": {"coordinates":[80.3287,7.3472],"type":"Point"}
}