{
  "type": "Feature",
  "properties": {
    "gn:admin1_code":"36.0",
    "gn:asciiname":"Kinigama",
    "gn:country_code":"LK",
    "gn:dem":13,
    "gn:feature_class":"P",
    "gn:feature_code":"PPL",
    "gn:name":"Kinigama",
    "gn:population":0,
    "gn:timezone":"Asia/Colombo",
    "iso:country":"LK",
    "name:ceb_x_preferred":[
        "Kinigama"
    ],
    "name:swe_x_preferred":[
        "Kinigama"
    ],
    "wof:name":"Kinigama",
    "wof:placetype":"locality"
},
  "geometry": {"coordinates":[80.0337,7.0583],"type":"Point"}
}