{
  "type": "Feature",
  "properties": {
    "gn:admin1_code":"29.0",
    "gn:asciiname":"Welikadawala",
    "gn:country_code":"LK",
    "gn:dem":688,
    "gn:feature_class":"P",
    "gn:feature_code":"PPL",
    "gn:name":"Welikadawala",
    "gn:population":0,
    "gn:timezone":"Asia/Colombo",
    "iso:country":"LK",
    "wof:name":"Welikadawala",
    "wof:placetype":"locality"
},
  "geometry": {"coordinates":[80.8066,7.111],"type":"Point"}
}