{
  "type": "Feature",
  "properties": {
    "gn:admin1_code":"32.0",
    "gn:asciiname":"Balahitiyawa",
    "gn:country_code":"LK",
    "gn:dem":122,
    "gn:feature_class":"P",
    "gn:feature_code":"PPL",
    "gn:name":"Balahitiyawa",
    "gn:population":0,
    "gn:timezone":"Asia/Colombo",
    "iso:country":"LK",
    "wof:name":"Balahitiyawa",
    "wof:placetype":"locality"
},
  "geometry": {"coordinates":[80.3891,7.5579],"type":"Point"}
}