{
  "type": "Feature",
  "properties": {
    "gn:admin1_code":"37.0",
    "gn:asciiname":"Chalampakeni",
    "gn:country_code":"LK",
    "gn:dem":26,
    "gn:feature_class":"P",
    "gn:feature_code":"PPL",
    "gn:name":"Chalampakeni",
    "gn:population":0,
    "gn:timezone":"Asia/Colombo",
    "iso:country":"LK",
    "name:und_x_variant":[
        "Chalampakerni",
        "Chalampakeni"
    ],
    "wof:name":"Chalampakeni",
    "wof:placetype":"locality"
},
  "geometry": {"coordinates":[81.75,7.41667],"type":"Point"}
}