{
  "type": "Feature",
  "properties": {
    "gn:admin1_code":"34.0",
    "gn:asciiname":"Imatuwegoda",
    "gn:country_code":"LK",
    "gn:dem":138,
    "gn:feature_class":"P",
    "gn:feature_code":"PPL",
    "gn:name":"Imatuwegoda",
    "gn:population":0,
    "gn:timezone":"Asia/Colombo",
    "iso:country":"LK",
    "wof:name":"Imatuwegoda",
    "wof:placetype":"locality"
},
  "geometry": {"coordinates":[80.7581,6.2546],"type":"Point"}
}