{
  "type": "Feature",
  "properties": {
    "gn:admin1_code":"30.0",
    "gn:asciiname":"Ulukkulama",
    "gn:country_code":"LK",
    "gn:dem":101,
    "gn:feature_class":"P",
    "gn:feature_code":"PPL",
    "gn:name":"Ulukkulama",
    "gn:population":0,
    "gn:timezone":"Asia/Colombo",
    "iso:country":"LK",
    "wof:name":"Ulukkulama",
    "wof:placetype":"locality"
},
  "geometry": {"coordinates":[80.3236,8.3052],"type":"Point"}
}