{
  "type": "Feature",
  "properties": {
    "gn:admin1_code":"30.0",
    "gn:asciiname":"Iluppukanniya",
    "gn:country_code":"LK",
    "gn:dem":139,
    "gn:feature_class":"P",
    "gn:feature_code":"PPL",
    "gn:name":"Iluppukanniya",
    "gn:population":0,
    "gn:timezone":"Asia/Colombo",
    "iso:country":"LK",
    "wof:name":"Iluppukanniya",
    "wof:placetype":"locality"
},
  "geometry": {"coordinates":[80.66667,8.21667],"type":"Point"}
}