{
  "type": "Feature",
  "properties": {
    "gn:admin1_code":"34.0",
    "gn:asciiname":"Dammala",
    "gn:country_code":"LK",
    "gn:dem":149,
    "gn:feature_class":"P",
    "gn:feature_code":"PPL",
    "gn:name":"Dammala",
    "gn:population":0,
    "gn:timezone":"Asia/Colombo",
    "iso:country":"LK",
    "wof:name":"Dammala",
    "wof:placetype":"locality"
},
  "geometry": {"coordinates":[80.3913,6.2958],"type":"Point"}
}