{
  "type": "Feature",
  "properties": {
    "gn:admin1_code":"38.0",
    "gn:asciiname":"Senthankulam",
    "gn:country_code":"LK",
    "gn:dem":12,
    "gn:feature_class":"P",
    "gn:feature_code":"PPL",
    "gn:name":"Senthankulam",
    "gn:population":0,
    "gn:timezone":"Asia/Colombo",
    "iso:country":"LK",
    "name:und_x_variant":[
        "Senkanthulam"
    ],
    "wof:name":"Senthankulam",
    "wof:placetype":"locality"
},
  "geometry": {"coordinates":[79.9987,9.8099],"type":"Point"}
}