{
  "type": "Feature",
  "properties": {
    "gn:admin1_code":"32.0",
    "gn:asciiname":"Potuwalapitiya",
    "gn:country_code":"LK",
    "gn:dem":166,
    "gn:feature_class":"P",
    "gn:feature_code":"PPL",
    "gn:name":"Potuwalapitiya",
    "gn:population":0,
    "gn:timezone":"Asia/Colombo",
    "iso:country":"LK",
    "wof:name":"Potuwalapitiya",
    "wof:placetype":"locality"
},
  "geometry": {"coordinates":[80.44800000000002,7.4421],"type":"Point"}
}