{
  "type": "Feature",
  "properties": {
    "gn:admin1_code":"32.0",
    "gn:asciiname":"Kosgahawewa",
    "gn:country_code":"LK",
    "gn:dem":58,
    "gn:feature_class":"P",
    "gn:feature_code":"PPL",
    "gn:name":"Kosgahawewa",
    "gn:population":0,
    "gn:timezone":"Asia/Colombo",
    "iso:country":"LK",
    "wof:name":"Kosgahawewa",
    "wof:placetype":"locality"
},
  "geometry": {"coordinates":[80.1074,7.6724],"type":"Point"}
}