{
  "type": "Feature",
  "properties": {
    "gn:admin1_code":"32.0",
    "gn:asciiname":"Yogamuwakanda",
    "gn:country_code":"LK",
    "gn:dem":306,
    "gn:feature_class":"P",
    "gn:feature_code":"PPL",
    "gn:name":"Yogamuwakanda",
    "gn:population":0,
    "gn:timezone":"Asia/Colombo",
    "iso:country":"LK",
    "wof:name":"Yogamuwakanda",
    "wof:placetype":"locality"
},
  "geometry": {"coordinates":[80.2847,7.3376],"type":"Point"}
}