{
  "type": "Feature",
  "properties": {
    "gn:admin1_code":"33.0",
    "gn:asciiname":"Pelamure",
    "gn:country_code":"LK",
    "gn:dem":334,
    "gn:feature_class":"P",
    "gn:feature_code":"PPL",
    "gn:name":"Pelamure",
    "gn:population":0,
    "gn:timezone":"Asia/Colombo",
    "iso:country":"LK",
    "wof:name":"Pelamure",
    "wof:placetype":"locality"
},
  "geometry": {"coordinates":[80.7274,6.5819],"type":"Point"}
}