{
  "type": "Feature",
  "properties": {
    "gn:admin1_code":"33.0",
    "gn:asciiname":"Gangaboda",
    "gn:country_code":"LK",
    "gn:dem":229,
    "gn:feature_class":"P",
    "gn:feature_code":"PPL",
    "gn:name":"Gangaboda",
    "gn:population":0,
    "gn:timezone":"Asia/Colombo",
    "iso:country":"LK",
    "wof:name":"Gangaboda",
    "wof:placetype":"locality"
},
  "geometry": {"coordinates":[80.4058,6.8378],"type":"Point"}
}