{
  "type": "Feature",
  "properties": {
    "gn:admin1_code":"36.0",
    "gn:asciiname":"Settappaduwa",
    "gn:country_code":"LK",
    "gn:dem":1,
    "gn:feature_class":"P",
    "gn:feature_code":"PPL",
    "gn:name":"Settappaduwa",
    "gn:population":0,
    "gn:timezone":"Asia/Colombo",
    "iso:country":"LK",
    "name:und_x_variant":[
        "Sethappaduwa",
        "Settappaduwa"
    ],
    "wof:name":"Settappaduwa",
    "wof:placetype":"locality"
},
  "geometry": {"coordinates":[79.8366,7.1257],"type":"Point"}
}