{
  "type": "Feature",
  "properties": {
    "gn:admin1_code":"38.0",
    "gn:asciiname":"Pullaveli",
    "gn:country_code":"LK",
    "gn:dem":7,
    "gn:feature_class":"P",
    "gn:feature_code":"PPL",
    "gn:name":"Pullaveli",
    "gn:population":0,
    "gn:timezone":"Asia/Colombo",
    "iso:country":"LK",
    "name:und_x_variant":[
        "Puthumadam",
        "Pullaveli"
    ],
    "wof:name":"Pullaveli",
    "wof:placetype":"locality"
},
  "geometry": {"coordinates":[80.4594,9.5516],"type":"Point"}
}