{
  "type": "Feature",
  "properties": {
    "gn:admin1_code":"29.0",
    "gn:asciiname":"Kiriwaula",
    "gn:country_code":"LK",
    "gn:dem":533,
    "gn:feature_class":"P",
    "gn:feature_code":"PPL",
    "gn:name":"Kiriwaula",
    "gn:population":0,
    "gn:timezone":"Asia/Colombo",
    "iso:country":"LK",
    "name:und_x_variant":[
        "Kiriwavula"
    ],
    "wof:name":"Kiriwaula",
    "wof:placetype":"locality"
},
  "geometry": {"coordinates":[80.5484,7.2535],"type":"Point"}
}