{
  "type": "Feature",
  "properties": {
    "gn:admin1_code":"32.0",
    "gn:asciiname":"Doratiyagedara",
    "gn:country_code":"LK",
    "gn:dem":45,
    "gn:feature_class":"P",
    "gn:feature_code":"PPL",
    "gn:name":"Doratiyagedara",
    "gn:population":0,
    "gn:timezone":"Asia/Colombo",
    "iso:country":"LK",
    "wof:name":"Doratiyagedara",
    "wof:placetype":"locality"
},
  "geometry": {"coordinates":[80.0919,7.5527],"type":"Point"}
}