{
  "type": "Feature",
  "properties": {
    "gn:admin1_code":"37.0",
    "gn:asciiname":"Berawa",
    "gn:country_code":"LK",
    "gn:dem":42,
    "gn:feature_class":"P",
    "gn:feature_code":"PPL",
    "gn:name":"Berawa",
    "gn:population":0,
    "gn:timezone":"Asia/Colombo",
    "iso:country":"LK",
    "name:und_x_variant":[
        "Berawa Munmari"
    ],
    "wof:name":"Berawa",
    "wof:placetype":"locality"
},
  "geometry": {"coordinates":[81.6313,7.2171],"type":"Point"}
}