{
  "type": "Feature",
  "properties": {
    "gn:admin1_code":"36.0",
    "gn:asciiname":"Walpola",
    "gn:country_code":"LK",
    "gn:dem":35,
    "gn:feature_class":"P",
    "gn:feature_code":"PPL",
    "gn:name":"Walpola",
    "gn:population":0,
    "gn:timezone":"Asia/Colombo",
    "iso:country":"LK",
    "wof:name":"Walpola",
    "wof:placetype":"locality"
},
  "geometry": {"coordinates":[80.12309999999999,7.0064],"type":"Point"}
}