{
  "type": "Feature",
  "properties": {
    "gn:admin1_code":"33.0",
    "gn:asciiname":"Tebugala",
    "gn:country_code":"LK",
    "gn:dem":400,
    "gn:feature_class":"P",
    "gn:feature_code":"PPL",
    "gn:name":"Tebugala",
    "gn:population":0,
    "gn:timezone":"Asia/Colombo",
    "iso:country":"LK",
    "wof:name":"Tebugala",
    "wof:placetype":"locality"
},
  "geometry": {"coordinates":[80.4986,6.4565],"type":"Point"}
}