{
  "type": "Feature",
  "properties": {
    "gn:admin1_code":"29.0",
    "gn:asciiname":"Ihalawela",
    "gn:country_code":"LK",
    "gn:dem":510,
    "gn:feature_class":"P",
    "gn:feature_code":"PPL",
    "gn:name":"Ihalawela",
    "gn:population":0,
    "gn:timezone":"Asia/Colombo",
    "iso:country":"LK",
    "name:und_x_variant":[
        "Ihalawewa",
        "Ihalawela"
    ],
    "wof:name":"Ihalawela",
    "wof:placetype":"locality"
},
  "geometry": {"coordinates":[80.5869,7.5353],"type":"Point"}
}