{
  "type": "Feature",
  "properties": {
    "gn:admin1_code":"32.0",
    "gn:asciiname":"Muthugalayagama",
    "gn:country_code":"LK",
    "gn:dem":17,
    "gn:feature_class":"P",
    "gn:feature_code":"PPL",
    "gn:name":"Muthugalayagama",
    "gn:population":0,
    "gn:timezone":"Asia/Colombo",
    "iso:country":"LK",
    "name:und_x_variant":[
        "Mutugalayagama"
    ],
    "wof:name":"Muthugalayagama",
    "wof:placetype":"locality"
},
  "geometry": {"coordinates":[79.9614,7.3737],"type":"Point"}
}