{
  "type": "Feature",
  "properties": {
    "gn:country":"LK",
    "gn:fcode":"PPL",
    "gn:population":215941,
    "iso:country":"LK",
    "qs_pg:aaroncc":"LK",
    "qs_pg:gn_country":"LK",
    "qs_pg:gn_fcode":"PPL",
    "qs_pg:gn_pop":215941,
    "qs_pg:name":"Galkissa",
    "qs_pg:photos_9r":0,
    "qs_pg:photos_sr":0,
    "qs_pg:pop_sr":10,
    "qs_pg:qs_pg_placetype":"locality",
    "wof:name":"Galkissa",
    "wof:placetype":"locality",
    "wof:population":215941
},
  "geometry": {"coordinates":[79.863,6.8293],"type":"Point"}
}