{
  "type": "Feature",
  "properties": {
    "gn:admin1_code":"30.0",
    "gn:asciiname":"Thoranagama",
    "gn:country_code":"LK",
    "gn:dem":124,
    "gn:feature_class":"P",
    "gn:feature_code":"PPL",
    "gn:name":"Thoranagama",
    "gn:population":0,
    "gn:timezone":"Asia/Colombo",
    "iso:country":"LK",
    "wof:name":"Thoranagama",
    "wof:placetype":"locality"
},
  "geometry": {"coordinates":[80.43089999999999,8.0462],"type":"Point"}
}