{
  "type": "Feature",
  "properties": {
    "gn:admin1_code":"32.0",
    "gn:asciiname":"Bujjampola",
    "gn:country_code":"LK",
    "gn:dem":40,
    "gn:feature_class":"P",
    "gn:feature_code":"PPL",
    "gn:name":"Bujjampola",
    "gn:population":0,
    "gn:timezone":"Asia/Colombo",
    "iso:country":"LK",
    "wof:name":"Bujjampola",
    "wof:placetype":"locality"
},
  "geometry": {"coordinates":[79.9272,7.3299],"type":"Point"}
}