{
  "type": "Feature",
  "properties": {
    "gn:admin1_code":"32.0",
    "gn:asciiname":"Mawatagama",
    "gn:cc2":"LK",
    "gn:country_code":"LK",
    "gn:dem":38,
    "gn:feature_class":"P",
    "gn:feature_code":"PPL",
    "gn:name":"Mawatagama",
    "gn:population":0,
    "gn:timezone":"Asia/Colombo",
    "iso:country":"LK",
    "name:ceb_x_preferred":[
        "Mawatagama"
    ],
    "name:swe_x_preferred":[
        "Mawatagama"
    ],
    "name:und_x_variant":[
        "Mawathagama"
    ],
    "wof:name":"Mawatagama",
    "wof:placetype":"locality"
},
  "geometry": {"coordinates":[80.09999999999999,7.71667],"type":"Point"}
}