{
  "type": "Feature",
  "properties": {
    "gn:admin1_code":"34.0",
    "gn:asciiname":"Nattanpitiya",
    "gn:country_code":"LK",
    "gn:dem":68,
    "gn:feature_class":"P",
    "gn:feature_code":"PPL",
    "gn:name":"Nattanpitiya",
    "gn:population":0,
    "gn:timezone":"Asia/Colombo",
    "iso:country":"LK",
    "wof:name":"Nattanpitiya",
    "wof:placetype":"locality"
},
  "geometry": {"coordinates":[80.3439,6.3444],"type":"Point"}
}