{
  "type": "Feature",
  "properties": {
    "gn:admin1_code":"34.0",
    "gn:asciiname":"Pitawalgamuwa",
    "gn:country_code":"LK",
    "gn:dem":151,
    "gn:feature_class":"P",
    "gn:feature_code":"PPL",
    "gn:name":"Pitawalgamuwa",
    "gn:population":0,
    "gn:timezone":"Asia/Colombo",
    "iso:country":"LK",
    "wof:name":"Pitawalgamuwa",
    "wof:placetype":"locality"
},
  "geometry": {"coordinates":[80.62260000000001,6.115],"type":"Point"}
}