{
  "type": "Feature",
  "properties": {
    "gn:admin1_code":"29.0",
    "gn:asciiname":"Nikahetiya",
    "gn:country_code":"LK",
    "gn:dem":513,
    "gn:feature_class":"P",
    "gn:feature_code":"PPL",
    "gn:name":"Nikahetiya",
    "gn:population":0,
    "gn:timezone":"Asia/Colombo",
    "iso:country":"LK",
    "name:ceb_x_preferred":[
        "Nikahetiya"
    ],
    "name:swe_x_preferred":[
        "Nikahetiya"
    ],
    "wof:name":"Nikahetiya",
    "wof:placetype":"locality"
},
  "geometry": {"coordinates":[80.5394,7.2194],"type":"Point"}
}