{
  "type": "Feature",
  "properties": {
    "gn:admin1_code":"29.0",
    "gn:asciiname":"Migaskotuwa",
    "gn:country_code":"LK",
    "gn:dem":197,
    "gn:feature_class":"P",
    "gn:feature_code":"PPL",
    "gn:name":"Migaskotuwa",
    "gn:population":0,
    "gn:timezone":"Asia/Colombo",
    "iso:country":"LK",
    "wof:name":"Migaskotuwa",
    "wof:placetype":"locality"
},
  "geometry": {"coordinates":[80.56667,7.76667],"type":"Point"}
}