{
  "type": "Feature",
  "properties": {
    "gn:admin1_code":"35.0",
    "gn:asciiname":"Neelawabedda",
    "gn:country_code":"LK",
    "gn:dem":108,
    "gn:feature_class":"P",
    "gn:feature_code":"PPL",
    "gn:name":"Neelawabedda",
    "gn:population":0,
    "gn:timezone":"Asia/Colombo",
    "iso:country":"LK",
    "name:und_x_variant":[
        "Nilawabedda"
    ],
    "wof:name":"Neelawabedda",
    "wof:placetype":"locality"
},
  "geometry": {"coordinates":[81.443,6.9232],"type":"Point"}
}