{
  "type": "Feature",
  "properties": {
    "gn:admin1_code":"33.0",
    "gn:asciiname":"Radagoda",
    "gn:country_code":"LK",
    "gn:dem":139,
    "gn:feature_class":"P",
    "gn:feature_code":"PPL",
    "gn:name":"Radagoda",
    "gn:population":0,
    "gn:timezone":"Asia/Colombo",
    "iso:country":"LK",
    "wof:name":"Radagoda",
    "wof:placetype":"locality"
},
  "geometry": {"coordinates":[80.605,6.6046],"type":"Point"}
}