{
  "type": "Feature",
  "properties": {
    "gn:admin1_code":"29.0",
    "gn:asciiname":"Mayfield",
    "gn:country_code":"LK",
    "gn:dem":1318,
    "gn:feature_class":"P",
    "gn:feature_code":"PPL",
    "gn:name":"Mayfield",
    "gn:population":0,
    "gn:timezone":"Asia/Colombo",
    "iso:country":"LK",
    "name:cat_x_preferred":[
        "Mayfield"
    ],
    "name:ceb_x_preferred":[
        "Mayfield"
    ],
    "name:deu_x_preferred":[
        "Mayfield"
    ],
    "name:fin_x_preferred":[
        "Mayfield"
    ],
    "name:fra_x_preferred":[
        "Mayfield"
    ],
    "name:ita_x_preferred":[
        "Mayfield"
    ],
    "name:jpn_x_preferred":[
        "\u30e1\u30a4\u30d5\u30a3\u30fc\u30eb\u30c9"
    ],
    "name:mlg_x_preferred":[
        "Mayfield"
    ],
    "name:nld_x_preferred":[
        "Mayfield"
    ],
    "name:pol_x_preferred":[
        "Mayfield"
    ],
    "name:por_x_preferred":[
        "Mayfield"
    ],
    "name:rus_x_preferred":[
        "\u041c\u044d\u0439\u0444\u0438\u043b\u0434"
    ],
    "name:srp_x_preferred":[
        "\u041c\u0435\u0458\u0444\u0438\u043b\u0434"
    ],
    "name:swe_x_preferred":[
        "Mayfield"
    ],
    "name:ukr_x_preferred":[
        "\u041c\u0435\u0439\u0444\u0456\u043b\u0434"
    ],
    "name:vol_x_preferred":[
        "Mayfield"
    ],
    "wof:name":"Mayfield",
    "wof:placetype":"locality"
},
  "geometry": {"coordinates":[80.5928,6.9215],"type":"Point"}
}