{
  "type": "Feature",
  "properties": {
    "gn:admin1_code":"32.0",
    "gn:asciiname":"Setapolai",
    "gn:country_code":"LK",
    "gn:dem":7,
    "gn:feature_class":"P",
    "gn:feature_code":"PPL",
    "gn:name":"Setapolai",
    "gn:population":0,
    "gn:timezone":"Asia/Colombo",
    "iso:country":"LK",
    "name:und_x_variant":[
        "Tetopola",
        "Tetapola",
        "Tetapolai"
    ],
    "wof:name":"Setapolai",
    "wof:placetype":"locality"
},
  "geometry": {"coordinates":[79.7864,7.9588],"type":"Point"}
}