{
  "type": "Feature",
  "properties": {
    "gn:admin1_code":"29.0",
    "gn:asciiname":"Kadawala",
    "gn:country_code":"LK",
    "gn:dem":594,
    "gn:feature_class":"P",
    "gn:feature_code":"PPL",
    "gn:name":"Kadawala",
    "gn:population":0,
    "gn:timezone":"Asia/Colombo",
    "iso:country":"LK",
    "wof:name":"Kadawala",
    "wof:placetype":"locality"
},
  "geometry": {"coordinates":[80.49379999999999,6.9797],"type":"Point"}
}