{
  "type": "Feature",
  "properties": {
    "gn:admin1_code":"37.0",
    "gn:asciiname":"Buhari Nagar",
    "gn:country_code":"LK",
    "gn:dem":66,
    "gn:feature_class":"P",
    "gn:feature_code":"PPL",
    "gn:name":"Buhari Nagar",
    "gn:population":0,
    "gn:timezone":"Asia/Colombo",
    "iso:country":"LK",
    "wof:name":"Buhari Nagar",
    "wof:placetype":"locality"
},
  "geometry": {"coordinates":[81.04689999999999,8.4416],"type":"Point"}
}