{
  "type": "Feature",
  "properties": {
    "gn:admin1_code":"29.0",
    "gn:asciiname":"Galwetiyaya",
    "gn:country_code":"LK",
    "gn:dem":171,
    "gn:feature_class":"P",
    "gn:feature_code":"PPL",
    "gn:name":"Galwetiyaya",
    "gn:population":0,
    "gn:timezone":"Asia/Colombo",
    "iso:country":"LK",
    "wof:name":"Galwetiyaya",
    "wof:placetype":"locality"
},
  "geometry": {"coordinates":[80.63333,7.88333],"type":"Point"}
}