{
  "type": "Feature",
  "properties": {
    "gn:admin1_code":"29.0",
    "gn:asciiname":"Katugastota",
    "gn:country_code":"LK",
    "gn:dem":468,
    "gn:feature_class":"P",
    "gn:feature_code":"PPL",
    "gn:name":"Katugastota",
    "gn:population":0,
    "gn:timezone":"Asia/Colombo",
    "iso:country":"LK",
    "name:ceb_x_preferred":[
        "Katugastota"
    ],
    "name:sin_x_preferred":[
        "\u0d9a\u0da7\u0dd4\u0d9c\u0dc3\u0dca\u0dad\u0ddc\u0da7"
    ],
    "name:swe_x_preferred":[
        "Katugastota"
    ],
    "name:tam_x_preferred":[
        "\u0b95\u0b9f\u0bcd\u0b9f\u0bc1\u0b95\u0bb8\u0bcd\u0ba4\u0bcb\u0b9f\u0bcd\u0b9f\u0bc8"
    ],
    "wof:name":"Katugastota",
    "wof:placetype":"locality"
},
  "geometry": {"coordinates":[80.6212,7.3276],"type":"Point"}
}