{
  "type": "Feature",
  "properties": {
    "gn:admin1_code":"34.0",
    "gn:asciiname":"Hawadagala",
    "gn:country_code":"LK",
    "gn:dem":19,
    "gn:feature_class":"P",
    "gn:feature_code":"PPL",
    "gn:name":"Hawadagala",
    "gn:population":0,
    "gn:timezone":"Asia/Colombo",
    "iso:country":"LK",
    "wof:name":"Hawadagala",
    "wof:placetype":"locality"
},
  "geometry": {"coordinates":[80.14860999999998,6.31306],"type":"Point"}
}