{
  "type": "Feature",
  "properties": {
    "gn:admin1_code":"35.0",
    "gn:asciiname":"Jinanandagama",
    "gn:country_code":"LK",
    "gn:dem":737,
    "gn:feature_class":"P",
    "gn:feature_code":"PPL",
    "gn:name":"Jinanandagama",
    "gn:population":0,
    "gn:timezone":"Asia/Colombo",
    "iso:country":"LK",
    "wof:name":"Jinanandagama",
    "wof:placetype":"locality"
},
  "geometry": {"coordinates":[81.0772,6.985],"type":"Point"}
}