{
  "type": "Feature",
  "properties": {
    "gn:admin1_code":"38.0",
    "gn:asciiname":"Karisal",
    "gn:country_code":"LK",
    "gn:dem":10,
    "gn:feature_class":"P",
    "gn:feature_code":"PPL",
    "gn:name":"Karisal",
    "gn:population":0,
    "gn:timezone":"Asia/Colombo",
    "iso:country":"LK",
    "name:und_x_variant":[
        "Periya Karisal",
        "Karisal"
    ],
    "wof:name":"Karisal",
    "wof:placetype":"locality"
},
  "geometry": {"coordinates":[79.83333,9.06667],"type":"Point"}
}