{
  "type": "Feature",
  "properties": {
    "gn:admin1_code":"35.0",
    "gn:asciiname":"Galgediyaya",
    "gn:country_code":"LK",
    "gn:dem":155,
    "gn:feature_class":"P",
    "gn:feature_code":"PPL",
    "gn:name":"Galgediyaya",
    "gn:population":0,
    "gn:timezone":"Asia/Colombo",
    "iso:country":"LK",
    "name:und_x_variant":[
        "Galgediyawa",
        "Galagediyaya",
        "Galgediyaya"
    ],
    "wof:name":"Galgediyaya",
    "wof:placetype":"locality"
},
  "geometry": {"coordinates":[81.4075,6.8753],"type":"Point"}
}