{
  "type": "Feature",
  "properties": {
    "gn:admin1_code":"34.0",
    "gn:asciiname":"Vikasithagama",
    "gn:country_code":"LK",
    "gn:dem":19,
    "gn:feature_class":"P",
    "gn:feature_code":"PPL",
    "gn:name":"Vikasithagama",
    "gn:population":0,
    "gn:timezone":"Asia/Colombo",
    "iso:country":"LK",
    "name:und_x_variant":[
        "Udagama"
    ],
    "wof:name":"Vikasithagama",
    "wof:placetype":"locality"
},
  "geometry": {"coordinates":[80.46680000000001,6.1782],"type":"Point"}
}