{
  "type": "Feature",
  "properties": {
    "gn:admin1_code":"34.0",
    "gn:asciiname":"Metiwiliya",
    "gn:country_code":"LK",
    "gn:dem":33,
    "gn:feature_class":"P",
    "gn:feature_code":"PPL",
    "gn:name":"Metiwiliya",
    "gn:population":0,
    "gn:timezone":"Asia/Colombo",
    "iso:country":"LK",
    "name:und_x_variant":[
        "Metiwilliya",
        "Metiwiliya"
    ],
    "wof:name":"Metiwiliya",
    "wof:placetype":"locality"
},
  "geometry": {"coordinates":[80.2123,6.344],"type":"Point"}
}