{
  "type": "Feature",
  "properties": {
    "gn:admin1_code":"30.0",
    "gn:asciiname":"Ritigahawewa",
    "gn:country_code":"LK",
    "gn:dem":84,
    "gn:feature_class":"P",
    "gn:feature_code":"PPL",
    "gn:name":"Ritigahawewa",
    "gn:population":0,
    "gn:timezone":"Asia/Colombo",
    "iso:country":"LK",
    "wof:name":"Ritigahawewa",
    "wof:placetype":"locality"
},
  "geometry": {"coordinates":[80.77809999999999,8.526],"type":"Point"}
}