{
  "type": "Feature",
  "properties": {
    "gn:admin1_code":"38.0",
    "gn:asciiname":"Kopay South",
    "gn:country_code":"LK",
    "gn:dem":10,
    "gn:feature_class":"P",
    "gn:feature_code":"PPL",
    "gn:name":"Kopay South",
    "gn:population":0,
    "gn:timezone":"Asia/Colombo",
    "iso:country":"LK",
    "name:ceb_x_preferred":[
        "Kopay"
    ],
    "name:swe_x_preferred":[
        "Kopay"
    ],
    "name:tam_x_preferred":[
        "\u0b95\u0bcb\u0baa\u0bcd\u0baa\u0bbe\u0baf\u0bcd"
    ],
    "name:und_x_variant":[
        "Kopai",
        "Koppay",
        "Kopay",
        "Kopay South",
        "Kopai South"
    ],
    "wof:name":"Kopay South",
    "wof:placetype":"locality"
},
  "geometry": {"coordinates":[80.04649999999999,9.695],"type":"Point"}
}