{
  "type": "Feature",
  "properties": {
    "gn:admin1_code":"33.0",
    "gn:asciiname":"Madurumulla",
    "gn:country_code":"LK",
    "gn:dem":179,
    "gn:feature_class":"P",
    "gn:feature_code":"PPL",
    "gn:name":"Madurumulla",
    "gn:population":0,
    "gn:timezone":"Asia/Colombo",
    "iso:country":"LK",
    "wof:name":"Madurumulla",
    "wof:placetype":"locality"
},
  "geometry": {"coordinates":[80.3742,7.1707],"type":"Point"}
}