{
  "type": "Feature",
  "properties": {
    "gn:admin1_code":"32.0",
    "gn:asciiname":"Nabadawa",
    "gn:country_code":"LK",
    "gn:dem":50,
    "gn:feature_class":"P",
    "gn:feature_code":"PPL",
    "gn:name":"Nabadawa",
    "gn:population":0,
    "gn:timezone":"Asia/Colombo",
    "iso:country":"LK",
    "name:und_x_variant":[
        "Nambadewa"
    ],
    "wof:name":"Nabadawa",
    "wof:placetype":"locality"
},
  "geometry": {"coordinates":[79.98820000000001,7.8318],"type":"Point"}
}