{
  "type": "Feature",
  "properties": {
    "gn:admin1_code":"29.0",
    "gn:asciiname":"Tumpelawaka",
    "gn:country_code":"LK",
    "gn:dem":773,
    "gn:feature_class":"P",
    "gn:feature_code":"PPL",
    "gn:name":"Tumpelawaka",
    "gn:population":0,
    "gn:timezone":"Asia/Colombo",
    "iso:country":"LK",
    "name:und_x_variant":[
        "Tumpelawake",
        "Tumpelawaka"
    ],
    "wof:name":"Tumpelawaka",
    "wof:placetype":"locality"
},
  "geometry": {"coordinates":[80.6652,7.1666],"type":"Point"}
}