{
  "type": "Feature",
  "properties": {
    "gn:admin1_code":"35.0",
    "gn:asciiname":"Usella",
    "gn:country_code":"LK",
    "gn:dem":137,
    "gn:feature_class":"P",
    "gn:feature_code":"PPL",
    "gn:name":"Usella",
    "gn:population":0,
    "gn:timezone":"Asia/Colombo",
    "iso:country":"LK",
    "wof:name":"Usella",
    "wof:placetype":"locality"
},
  "geometry": {"coordinates":[81.4622,6.9073],"type":"Point"}
}