{
  "type": "Feature",
  "properties": {
    "iso:country":"LK",
    "name:ara_x_preferred":[
        "\u0627\u062a\u0627\u0644\u0627"
    ],
    "name:ben_x_preferred":[
        "\u0993\u09af\u09bc\u09be\u099f\u09be\u09b2\u09be"
    ],
    "name:dan_x_preferred":[
        "Wattala"
    ],
    "name:ell_x_preferred":[
        "\u0393\u03bf\u03c5\u03b1\u03c4\u03ac\u03bb\u03b1"
    ],
    "name:eng_x_preferred":[
        "Wattala"
    ],
    "name:fas_x_preferred":[
        "\u0648\u0627\u062a\u0627\u0644\u0627"
    ],
    "name:fin_x_preferred":[
        "Wattala"
    ],
    "name:fra_x_preferred":[
        "Wattala"
    ],
    "name:guj_x_preferred":[
        "\u0ab5\u0a9f\u0acd\u0a9f\u0ab2\u0abe"
    ],
    "name:hin_x_preferred":[
        "\u0935\u091f\u094d\u091f\u093e\u0932\u093e"
    ],
    "name:ind_x_preferred":[
        "Wattala"
    ],
    "name:ita_x_preferred":[
        "Wattla"
    ],
    "name:jpn_x_preferred":[
        "\u30ef\u30c3\u30bf\u30e9"
    ],
    "name:kan_x_preferred":[
        "\u0cb5\u0c9f\u0cb2\u0cbe"
    ],
    "name:kor_x_preferred":[
        "\uc640\ud0c8\ub77c"
    ],
    "name:lav_x_preferred":[
        "Vatala"
    ],
    "name:lit_x_preferred":[
        "Vatala"
    ],
    "name:mar_x_preferred":[
        "\u0935\u091f\u094d\u091f\u093e\u0932\u093e"
    ],
    "name:msa_x_preferred":[
        "Wattala"
    ],
    "name:nld_x_preferred":[
        "Wattala"
    ],
    "name:nob_x_preferred":[
        "Wattala"
    ],
    "name:pol_x_preferred":[
        "Wattala"
    ],
    "name:por_x_preferred":[
        "Wattala"
    ],
    "name:rus_x_preferred":[
        "\u0412\u0430\u0442\u0442\u0430\u043b\u0430"
    ],
    "name:sin_x_preferred":[
        "\u0dc0\u0dad\u0dca\u0dad\u0dbd"
    ],
    "name:spa_x_preferred":[
        "Wattala"
    ],
    "name:swe_x_preferred":[
        "Wattala"
    ],
    "name:tam_x_preferred":[
        "\u0bb5\u0ba4\u0bcd\u0ba4\u0bb3\u0bc8"
    ],
    "name:tel_x_preferred":[
        "\u0c35\u0c1f\u0c4d\u0c1f\u0c3e\u0c32\u0c3e"
    ],
    "name:tha_x_preferred":[
        "\u0e27\u0e31\u0e17\u0e17\u0e32\u0e25\u0e32"
    ],
    "name:tur_x_preferred":[
        "Wattala"
    ],
    "name:ukr_x_preferred":[
        "\u0412\u0430\u0442\u0430\u043b\u0430"
    ],
    "name:urd_x_preferred":[
        "\u0648\u0679\u0627\u0644\u0627"
    ],
    "name:vie_x_preferred":[
        "Wattala"
    ],
    "qs:gn_country":"LK",
    "qs:gn_fcode":"PPL",
    "qs:gn_pop":30725,
    "qs:name":"Wattala",
    "qs:name_adm0":"Sri Lanka",
    "qs:name_adm1":"Western",
    "qs:photos":51,
    "qs:photos_1k":10,
    "qs:photos_9k":1,
    "qs:photos_9r":2,
    "qs:photos_all":51,
    "qs:photos_sr":2,
    "qs:placetype":"Town",
    "qs:pop_sr":"7",
    "qs:woe_adm0":23424778,
    "wd:wordcount":374,
    "wof:name":"Wattala",
    "wof:placetype":"locality",
    "wof:population":30725
},
  "geometry": {"coordinates":[79.88979999999999,6.9779],"type":"Point"}
}