{
  "type": "Feature",
  "properties": {
    "gn:admin1_code":"36.0",
    "gn:asciiname":"Raddolugama",
    "gn:country_code":"LK",
    "gn:dem":22,
    "gn:feature_class":"P",
    "gn:feature_code":"PPL",
    "gn:name":"Raddolugama",
    "gn:population":0,
    "gn:timezone":"Asia/Colombo",
    "iso:country":"LK",
    "name:und_x_variant":[
        "Udagama"
    ],
    "wof:name":"Raddolugama",
    "wof:placetype":"locality"
},
  "geometry": {"coordinates":[79.9034,7.1371],"type":"Point"}
}