{
  "type": "Feature",
  "properties": {
    "gn:admin1_code":"32.0",
    "gn:asciiname":"Delmaga",
    "gn:country_code":"LK",
    "gn:dem":50,
    "gn:feature_class":"P",
    "gn:feature_code":"PPL",
    "gn:name":"Delmaga",
    "gn:population":0,
    "gn:timezone":"Asia/Colombo",
    "iso:country":"LK",
    "wof:name":"Delmaga",
    "wof:placetype":"locality"
},
  "geometry": {"coordinates":[80.07259999999999,7.3642],"type":"Point"}
}