{
  "type": "Feature",
  "properties": {
    "gn:admin1_code":"29.0",
    "gn:asciiname":"Damana",
    "gn:country_code":"LK",
    "gn:dem":186,
    "gn:feature_class":"P",
    "gn:feature_code":"PPL",
    "gn:name":"Damana",
    "gn:population":0,
    "gn:timezone":"Asia/Colombo",
    "iso:country":"LK",
    "name:ceb_x_preferred":[
        "Damana"
    ],
    "name:fra_x_preferred":[
        "Damana"
    ],
    "name:swe_x_preferred":[
        "Damana"
    ],
    "wof:name":"Damana",
    "wof:placetype":"locality"
},
  "geometry": {"coordinates":[80.57971999999999,7.84167],"type":"Point"}
}