{
  "type": "Feature",
  "properties": {
    "gn:admin1_code":"29.0",
    "gn:asciiname":"Dammantenna",
    "gn:country_code":"LK",
    "gn:dem":247,
    "gn:feature_class":"P",
    "gn:feature_code":"PPL",
    "gn:name":"Dammantenna",
    "gn:population":0,
    "gn:timezone":"Asia/Colombo",
    "iso:country":"LK",
    "name:und_x_variant":[
        "Dammanatenna",
        "Dammantenna"
    ],
    "wof:name":"Dammantenna",
    "wof:placetype":"locality"
},
  "geometry": {"coordinates":[80.7398,7.6219],"type":"Point"}
}