{
  "type": "Feature",
  "properties": {
    "gn:admin1_code":"32.0",
    "gn:asciiname":"Palu Kalumetiyawa",
    "gn:country_code":"LK",
    "gn:dem":154,
    "gn:feature_class":"P",
    "gn:feature_code":"PPL",
    "gn:name":"Palu Kalumetiyawa",
    "gn:population":0,
    "gn:timezone":"Asia/Colombo",
    "iso:country":"LK",
    "name:und_x_variant":[
        "Palukatumetiyawa"
    ],
    "wof:name":"Palu Kalumetiyawa",
    "wof:placetype":"locality"
},
  "geometry": {"coordinates":[80.467,7.604],"type":"Point"}
}