{
  "type": "Feature",
  "properties": {
    "iso:country":"LK",
    "name:eng_x_preferred":[
        "Fort"
    ],
    "name:unk_x_variant":[
        "Fort"
    ],
    "qs:gn_adm0_cc":"LK",
    "qs:gn_fcode":"PPLX",
    "qs:gn_local":1248991,
    "qs:gn_nam_loc":"Colombo, Colombo, Western, LK",
    "qs:gn_namadm1":"36",
    "qs:gn_name":"Fort",
    "qs:local_max":2559,
    "qs:local_sum":8835,
    "qs:localhoods":10,
    "qs:name":"Fort",
    "qs:name_adm0":"Sri Lanka",
    "qs:name_adm1":"Western",
    "qs:name_adm2":"Colombo",
    "qs:name_local":"Colombo",
    "qs:photo_max":622,
    "qs:photo_sum":2559,
    "qs:placetype":"Suburb",
    "qs:quad_count":43,
    "qs:woe_adm0":23424778,
    "qs:woe_adm1":2344966,
    "qs:woe_adm2":23706493,
    "qs:woe_lau":0,
    "qs:woe_local":2189783,
    "qs:woe_ver":"7.10.0",
    "wof:lang":[
        "eng"
    ],
    "wof:name":"Fort",
    "wof:placetype":"neighbourhood"
},
  "geometry": {"coordinates":[79.851744,6.931896],"type":"Point"}
}