{
  "type": "Feature",
  "properties": {
    "gn:admin1_code":"35.0",
    "gn:asciiname":"Karandagama",
    "gn:country_code":"LK",
    "gn:dem":341,
    "gn:feature_class":"P",
    "gn:feature_code":"PPL",
    "gn:name":"Karandagama",
    "gn:population":0,
    "gn:timezone":"Asia/Colombo",
    "iso:country":"LK",
    "name:und_x_variant":[
        "Karande"
    ],
    "wof:name":"Karandagama",
    "wof:placetype":"locality"
},
  "geometry": {"coordinates":[81.2509,6.9397],"type":"Point"}
}