{
  "type": "Feature",
  "properties": {
    "gn:admin1_code":"34.0",
    "gn:asciiname":"Dope",
    "gn:country_code":"LK",
    "gn:dem":12,
    "gn:feature_class":"P",
    "gn:feature_code":"PPL",
    "gn:name":"Dope",
    "gn:population":0,
    "gn:timezone":"Asia/Colombo",
    "iso:country":"LK",
    "name:ceb_x_preferred":[
        "Dope"
    ],
    "name:deu_x_preferred":[
        "Dope"
    ],
    "name:fra_x_preferred":[
        "Dope"
    ],
    "name:jpn_x_preferred":[
        "\u30c9\u30fc\u30d7"
    ],
    "name:nld_x_preferred":[
        "Dope"
    ],
    "name:pol_x_preferred":[
        "Dope"
    ],
    "name:por_x_preferred":[
        "Dope"
    ],
    "name:tur_x_preferred":[
        "Dope"
    ],
    "name:zho_x_preferred":[
        "Dope"
    ],
    "wof:name":"Dope",
    "wof:placetype":"locality"
},
  "geometry": {"coordinates":[80.01666999999998,6.41667],"type":"Point"}
}