{
  "type": "Feature",
  "properties": {
    "gn:admin1_code":"38.0",
    "gn:asciiname":"Ilamarudankulam",
    "gn:country_code":"LK",
    "gn:dem":88,
    "gn:feature_class":"P",
    "gn:feature_code":"PPL",
    "gn:name":"Ilamarudankulam",
    "gn:population":0,
    "gn:timezone":"Asia/Colombo",
    "iso:country":"LK",
    "name:und_x_variant":[
        "Ilamarudankulama"
    ],
    "wof:name":"Ilamarudankulam",
    "wof:placetype":"locality"
},
  "geometry": {"coordinates":[80.4888,8.6765],"type":"Point"}
}