{
  "type": "Feature",
  "properties": {
    "gn:admin1_code":"32.0",
    "gn:asciiname":"Thambera",
    "gn:country_code":"LK",
    "gn:dem":107,
    "gn:feature_class":"P",
    "gn:feature_code":"PPL",
    "gn:name":"Thambera",
    "gn:population":0,
    "gn:timezone":"Asia/Colombo",
    "iso:country":"LK",
    "name:und_x_variant":[
        "Tambare",
        "Thambera"
    ],
    "wof:name":"Thambera",
    "wof:placetype":"locality"
},
  "geometry": {"coordinates":[80.26709,7.85327],"type":"Point"}
}