{
  "type": "Feature",
  "properties": {
    "gn:admin1_code":"29.0",
    "gn:asciiname":"Dodandeniya",
    "gn:country_code":"LK",
    "gn:dem":472,
    "gn:feature_class":"P",
    "gn:feature_code":"PPL",
    "gn:name":"Dodandeniya",
    "gn:population":0,
    "gn:timezone":"Asia/Colombo",
    "iso:country":"LK",
    "wof:name":"Dodandeniya",
    "wof:placetype":"locality"
},
  "geometry": {"coordinates":[80.60890000000001,7.4679],"type":"Point"}
}