{
  "type": "Feature",
  "properties": {
    "gn:admin1_code":"36.0",
    "gn:asciiname":"Tebuwana",
    "gn:country_code":"LK",
    "gn:dem":4,
    "gn:feature_class":"P",
    "gn:feature_code":"PPL",
    "gn:name":"Tebuwana",
    "gn:population":0,
    "gn:timezone":"Asia/Colombo",
    "iso:country":"LK",
    "name:und_x_variant":[
        "Tabuwana",
        "Tebuwana"
    ],
    "wof:name":"Tebuwana",
    "wof:placetype":"locality"
},
  "geometry": {"coordinates":[80.0466,6.5829],"type":"Point"}
}