{
  "type": "Feature",
  "properties": {
    "gn:admin1_code":"30.0",
    "gn:asciiname":"Gantiriyagama",
    "gn:country_code":"LK",
    "gn:dem":128,
    "gn:feature_class":"P",
    "gn:feature_code":"PPL",
    "gn:name":"Gantiriyagama",
    "gn:population":0,
    "gn:timezone":"Asia/Colombo",
    "iso:country":"LK",
    "name:und_x_variant":[
        "Alutganthiriyagama",
        "Alut Gantiriyagama",
        "Gantiriyagama"
    ],
    "wof:name":"Gantiriyagama",
    "wof:placetype":"locality"
},
  "geometry": {"coordinates":[80.4975,8.0674],"type":"Point"}
}