{
  "type": "Feature",
  "properties": {
    "gn:admin1_code":"33.0",
    "gn:asciiname":"Liniyagala",
    "gn:country_code":"LK",
    "gn:dem":284,
    "gn:feature_class":"P",
    "gn:feature_code":"PPL",
    "gn:name":"Liniyagala",
    "gn:population":0,
    "gn:timezone":"Asia/Colombo",
    "iso:country":"LK",
    "name:und_x_variant":[
        "Leeniyagala",
        "Liniyagala"
    ],
    "wof:name":"Liniyagala",
    "wof:placetype":"locality"
},
  "geometry": {"coordinates":[80.35250000000001,6.9397],"type":"Point"}
}