{
  "type": "Feature",
  "properties": {
    "gn:admin1_code":"37.0",
    "gn:asciiname":"Kirittona",
    "gn:country_code":"LK",
    "gn:dem":8,
    "gn:feature_class":"P",
    "gn:feature_code":"PPL",
    "gn:name":"Kirittona",
    "gn:population":0,
    "gn:timezone":"Asia/Colombo",
    "iso:country":"LK",
    "wof:name":"Kirittona",
    "wof:placetype":"locality"
},
  "geometry": {"coordinates":[81.75,7.65],"type":"Point"}
}