{
  "type": "Feature",
  "properties": {
    "gn:admin1_code":"32.0",
    "gn:asciiname":"Magallegama",
    "gn:cc2":"LK",
    "gn:country_code":"LK",
    "gn:dem":42,
    "gn:feature_class":"P",
    "gn:feature_code":"PPL",
    "gn:name":"Magallegama",
    "gn:population":0,
    "gn:timezone":"Asia/Colombo",
    "iso:country":"LK",
    "name:und_x_variant":[
        "Magallagama",
        "Magallegama"
    ],
    "wof:name":"Magallegama",
    "wof:placetype":"locality"
},
  "geometry": {"coordinates":[80.11667,7.71667],"type":"Point"}
}