{
  "type": "Feature",
  "properties": {
    "gn:admin1_code":"30.0",
    "gn:asciiname":"Ipalogama",
    "gn:country_code":"LK",
    "gn:dem":91,
    "gn:feature_class":"P",
    "gn:feature_code":"PPL",
    "gn:name":"Ipalogama",
    "gn:population":0,
    "gn:timezone":"Asia/Colombo",
    "iso:country":"LK",
    "wof:name":"Ipalogama",
    "wof:placetype":"locality"
},
  "geometry": {"coordinates":[80.3464,8.1367],"type":"Point"}
}