{
  "type": "Feature",
  "properties": {
    "gn:admin1_code":"29.0",
    "gn:asciiname":"Welpanala",
    "gn:country_code":"LK",
    "gn:dem":434,
    "gn:feature_class":"P",
    "gn:feature_code":"PPL",
    "gn:name":"Welpanala",
    "gn:population":0,
    "gn:timezone":"Asia/Colombo",
    "iso:country":"LK",
    "wof:name":"Welpanala",
    "wof:placetype":"locality"
},
  "geometry": {"coordinates":[80.59520000000001,7.5196],"type":"Point"}
}