{
  "type": "Feature",
  "properties": {
    "gn:admin1_code":"29.0",
    "gn:asciiname":"Puwakpitiya",
    "gn:country_code":"LK",
    "gn:dem":351,
    "gn:feature_class":"P",
    "gn:feature_code":"PPL",
    "gn:name":"Puwakpitiya",
    "gn:population":0,
    "gn:timezone":"Asia/Colombo",
    "iso:country":"LK",
    "name:ceb_x_preferred":[
        "Puwakpitiya"
    ],
    "name:swe_x_preferred":[
        "Puwakpitiya"
    ],
    "wof:name":"Puwakpitiya",
    "wof:placetype":"locality"
},
  "geometry": {"coordinates":[80.6405,7.5812],"type":"Point"}
}