{
  "type": "Feature",
  "properties": {
    "gn:admin1_code":"30.0",
    "gn:asciiname":"Mahadiulgaskada",
    "gn:country_code":"LK",
    "gn:dem":113,
    "gn:feature_class":"P",
    "gn:feature_code":"PPL",
    "gn:name":"Mahadiulgaskada",
    "gn:population":0,
    "gn:timezone":"Asia/Colombo",
    "iso:country":"LK",
    "wof:name":"Mahadiulgaskada",
    "wof:placetype":"locality"
},
  "geometry": {"coordinates":[80.55419999999999,8.6706],"type":"Point"}
}