{
  "type": "Feature",
  "properties": {
    "gn:admin1_code":"36.0",
    "gn:asciiname":"Weragala",
    "gn:country_code":"LK",
    "gn:dem":64,
    "gn:feature_class":"P",
    "gn:feature_code":"PPL",
    "gn:name":"Weragala",
    "gn:population":0,
    "gn:timezone":"Asia/Colombo",
    "iso:country":"LK",
    "wof:name":"Weragala",
    "wof:placetype":"locality"
},
  "geometry": {"coordinates":[79.99694000000002,6.52194],"type":"Point"}
}