{
  "type": "Feature",
  "properties": {
    "gn:admin1_code":"33.0",
    "gn:asciiname":"Halnetikanda",
    "gn:country_code":"LK",
    "gn:dem":441,
    "gn:feature_class":"P",
    "gn:feature_code":"PPL",
    "gn:name":"Halnetikanda",
    "gn:population":0,
    "gn:timezone":"Asia/Colombo",
    "iso:country":"LK",
    "wof:name":"Halnetikanda",
    "wof:placetype":"locality"
},
  "geometry": {"coordinates":[80.4836,6.4226],"type":"Point"}
}