{
  "type": "Feature",
  "properties": {
    "gn:admin1_code":"37.0",
    "gn:asciiname":"Iddapola",
    "gn:country_code":"LK",
    "gn:dem":73,
    "gn:feature_class":"P",
    "gn:feature_code":"PPL",
    "gn:name":"Iddapola",
    "gn:population":0,
    "gn:timezone":"Asia/Colombo",
    "iso:country":"LK",
    "wof:name":"Iddapola",
    "wof:placetype":"locality"
},
  "geometry": {"coordinates":[81.29819999999999,7.4987],"type":"Point"}
}