{
  "type": "Feature",
  "properties": {
    "gn:admin1_code":"33.0",
    "gn:asciiname":"Siripagama",
    "gn:country_code":"LK",
    "gn:dem":444,
    "gn:feature_class":"P",
    "gn:feature_code":"PPL",
    "gn:name":"Siripagama",
    "gn:population":0,
    "gn:timezone":"Asia/Colombo",
    "iso:country":"LK",
    "wof:name":"Siripagama",
    "wof:placetype":"locality"
},
  "geometry": {"coordinates":[80.44970000000001,6.793],"type":"Point"}
}