{
  "type": "Feature",
  "properties": {
    "gn:admin1_code":"32.0",
    "gn:asciiname":"Akkarawelliya",
    "gn:country_code":"LK",
    "gn:dem":14,
    "gn:feature_class":"P",
    "gn:feature_code":"PPL",
    "gn:name":"Akkarawelliya",
    "gn:population":0,
    "gn:timezone":"Asia/Colombo",
    "iso:country":"LK",
    "name:und_x_variant":[
        "Akkaraweli",
        "Akkarawelliya"
    ],
    "wof:name":"Akkarawelliya",
    "wof:placetype":"locality"
},
  "geometry": {"coordinates":[79.8441,7.7585],"type":"Point"}
}