{
  "type": "Feature",
  "properties": {
    "gn:admin1_code":"29.0",
    "gn:asciiname":"Kadwan Town",
    "gn:country_code":"LK",
    "gn:dem":1006,
    "gn:feature_class":"P",
    "gn:feature_code":"PPL",
    "gn:name":"Kadwan Town",
    "gn:population":0,
    "gn:timezone":"Asia/Colombo",
    "iso:country":"LK",
    "wof:name":"Kadwan Town",
    "wof:placetype":"locality"
},
  "geometry": {"coordinates":[80.5822,7.0161],"type":"Point"}
}