{
  "type": "Feature",
  "properties": {
    "gn:admin1_code":"34.0",
    "gn:asciiname":"Panvila",
    "gn:country_code":"LK",
    "gn:dem":7,
    "gn:feature_class":"P",
    "gn:feature_code":"PPL",
    "gn:name":"Panvila",
    "gn:population":0,
    "gn:timezone":"Asia/Colombo",
    "iso:country":"LK",
    "wof:name":"Panvila",
    "wof:placetype":"locality"
},
  "geometry": {"coordinates":[80.1267,6.1311],"type":"Point"}
}