{
  "type": "Feature",
  "properties": {
    "gn:admin1_code":"33.0",
    "gn:asciiname":"Helawatta",
    "gn:country_code":"LK",
    "gn:dem":543,
    "gn:feature_class":"P",
    "gn:feature_code":"PPL",
    "gn:name":"Helawatta",
    "gn:population":0,
    "gn:timezone":"Asia/Colombo",
    "iso:country":"LK",
    "wof:name":"Helawatta",
    "wof:placetype":"locality"
},
  "geometry": {"coordinates":[80.7209,6.6999],"type":"Point"}
}