{
  "type": "Feature",
  "properties": {
    "gn:admin1_code":"35.0",
    "gn:asciiname":"Udagangoda",
    "gn:country_code":"LK",
    "gn:dem":340,
    "gn:feature_class":"P",
    "gn:feature_code":"PPL",
    "gn:name":"Udagangoda",
    "gn:population":0,
    "gn:timezone":"Asia/Colombo",
    "iso:country":"LK",
    "wof:name":"Udagangoda",
    "wof:placetype":"locality"
},
  "geometry": {"coordinates":[81.2788,6.8656],"type":"Point"}
}