{
  "type": "Feature",
  "properties": {
    "gn:admin1_code":"32.0",
    "gn:asciiname":"Peddawa",
    "gn:country_code":"LK",
    "gn:dem":111,
    "gn:feature_class":"P",
    "gn:feature_code":"PPL",
    "gn:name":"Peddawa",
    "gn:population":0,
    "gn:timezone":"Asia/Colombo",
    "iso:country":"LK",
    "wof:name":"Peddawa",
    "wof:placetype":"locality"
},
  "geometry": {"coordinates":[80.4053,7.5684],"type":"Point"}
}