{
  "type": "Feature",
  "properties": {
    "gn:admin1_code":"36.0",
    "gn:asciiname":"Keerantidiya",
    "gn:country_code":"LK",
    "gn:dem":10,
    "gn:feature_class":"P",
    "gn:feature_code":"PPL",
    "gn:name":"Keerantidiya",
    "gn:population":0,
    "gn:timezone":"Asia/Colombo",
    "iso:country":"LK",
    "name:und_x_variant":[
        "Kirantidiya",
        "Keeranthidiya"
    ],
    "wof:name":"Keerantidiya",
    "wof:placetype":"locality"
},
  "geometry": {"coordinates":[80.03789999999999,6.4693],"type":"Point"}
}