{
  "type": "Feature",
  "properties": {
    "gn:admin1_code":"32.0",
    "gn:asciiname":"Koonkadawela Ihala",
    "gn:country_code":"LK",
    "gn:dem":47,
    "gn:feature_class":"P",
    "gn:feature_code":"PPL",
    "gn:name":"Koonkadawela Ihala",
    "gn:population":0,
    "gn:timezone":"Asia/Colombo",
    "iso:country":"LK",
    "name:und_x_variant":[
        "Konkadawala Ihala"
    ],
    "wof:name":"Koonkadawela Ihala",
    "wof:placetype":"locality"
},
  "geometry": {"coordinates":[80.0073,7.6795],"type":"Point"}
}