{
  "type": "Feature",
  "properties": {
    "gn:admin1_code":"32.0",
    "gn:asciiname":"Mawila",
    "gn:country_code":"LK",
    "gn:dem":19,
    "gn:feature_class":"P",
    "gn:feature_code":"PPL",
    "gn:name":"Mawila",
    "gn:population":0,
    "gn:timezone":"Asia/Colombo",
    "iso:country":"LK",
    "wof:name":"Mawila",
    "wof:placetype":"locality"
},
  "geometry": {"coordinates":[79.84690000000001,7.3907],"type":"Point"}
}