{
  "type": "Feature",
  "properties": {
    "gn:admin1_code":"30.0",
    "gn:asciiname":"Palukandewa",
    "gn:country_code":"LK",
    "gn:dem":102,
    "gn:feature_class":"P",
    "gn:feature_code":"PPL",
    "gn:name":"Palukandewa",
    "gn:population":0,
    "gn:timezone":"Asia/Colombo",
    "iso:country":"LK",
    "wof:name":"Palukandewa",
    "wof:placetype":"locality"
},
  "geometry": {"coordinates":[80.5133,8.5879],"type":"Point"}
}