{
  "type": "Feature",
  "properties": {
    "gn:admin1_code":"32.0",
    "gn:asciiname":"Pallepitiya",
    "gn:country_code":"LK",
    "gn:dem":37,
    "gn:feature_class":"P",
    "gn:feature_code":"PPL",
    "gn:name":"Pallepitiya",
    "gn:population":0,
    "gn:timezone":"Asia/Colombo",
    "iso:country":"LK",
    "wof:name":"Pallepitiya",
    "wof:placetype":"locality"
},
  "geometry": {"coordinates":[80.0364,7.4734],"type":"Point"}
}