{
  "type": "Feature",
  "properties": {
    "gn:admin1_code":"29.0",
    "gn:asciiname":"Kurunduwatta",
    "gn:country_code":"LK",
    "gn:dem":497,
    "gn:feature_class":"P",
    "gn:feature_code":"PPL",
    "gn:name":"Kurunduwatta",
    "gn:population":0,
    "gn:timezone":"Asia/Colombo",
    "iso:country":"LK",
    "wof:name":"Kurunduwatta",
    "wof:placetype":"locality"
},
  "geometry": {"coordinates":[80.5945,7.2381],"type":"Point"}
}