{
  "type": "Feature",
  "properties": {
    "gn:admin1_code":"35.0",
    "gn:asciiname":"Mahakumbura",
    "gn:country_code":"LK",
    "gn:dem":810,
    "gn:feature_class":"P",
    "gn:feature_code":"PPL",
    "gn:name":"Mahakumbura",
    "gn:population":0,
    "gn:timezone":"Asia/Colombo",
    "iso:country":"LK",
    "name:ceb_x_preferred":[
        "Mahakumbura"
    ],
    "name:swe_x_preferred":[
        "Mahakumbura"
    ],
    "wof:name":"Mahakumbura",
    "wof:placetype":"locality"
},
  "geometry": {"coordinates":[80.9696,6.9846],"type":"Point"}
}