{
  "type": "Feature",
  "properties": {
    "gn:admin1_code":"34.0",
    "gn:asciiname":"Hatapelana",
    "gn:country_code":"LK",
    "gn:dem":18,
    "gn:feature_class":"P",
    "gn:feature_code":"PPL",
    "gn:name":"Hatapelana",
    "gn:population":0,
    "gn:timezone":"Asia/Colombo",
    "iso:country":"LK",
    "wof:name":"Hatapelana",
    "wof:placetype":"locality"
},
  "geometry": {"coordinates":[80.36667,5.98333],"type":"Point"}
}