{
  "type": "Feature",
  "properties": {
    "gn:admin1_code":"38.0",
    "gn:asciiname":"Periyanochchikulam",
    "gn:country_code":"LK",
    "gn:dem":71,
    "gn:feature_class":"P",
    "gn:feature_code":"PPL",
    "gn:name":"Periyanochchikulam",
    "gn:population":0,
    "gn:timezone":"Asia/Colombo",
    "iso:country":"LK",
    "name:und_x_variant":[
        "Periyanochchikkulam"
    ],
    "wof:name":"Periyanochchikulam",
    "wof:placetype":"locality"
},
  "geometry": {"coordinates":[80.3563,8.6142],"type":"Point"}
}