{
  "type": "Feature",
  "properties": {
    "gn:admin1_code":"34.0",
    "gn:asciiname":"Malittagoda",
    "gn:country_code":"LK",
    "gn:dem":11,
    "gn:feature_class":"P",
    "gn:feature_code":"PPL",
    "gn:name":"Malittagoda",
    "gn:population":0,
    "gn:timezone":"Asia/Colombo",
    "iso:country":"LK",
    "wof:name":"Malittagoda",
    "wof:placetype":"locality"
},
  "geometry": {"coordinates":[80.16930000000001,6.1979],"type":"Point"}
}