{
  "type": "Feature",
  "properties": {
    "gn:admin1_code":"32.0",
    "gn:asciiname":"Pidiwilla",
    "gn:cc2":"LK",
    "gn:country_code":"LK",
    "gn:dem":125,
    "gn:feature_class":"P",
    "gn:feature_code":"PPL",
    "gn:name":"Pidiwilla",
    "gn:population":0,
    "gn:timezone":"Asia/Colombo",
    "iso:country":"LK",
    "name:und_x_variant":[
        "Pidimilla",
        "Pidiwilla"
    ],
    "wof:name":"Pidiwilla",
    "wof:placetype":"locality"
},
  "geometry": {"coordinates":[80.40000000000001,7.85],"type":"Point"}
}