{
  "type": "Feature",
  "properties": {
    "gn:admin1_code":"38.0",
    "gn:asciiname":"Tunukkai",
    "gn:country_code":"LK",
    "gn:dem":38,
    "gn:feature_class":"P",
    "gn:feature_code":"PPL",
    "gn:name":"Tunukkai",
    "gn:population":0,
    "gn:timezone":"Asia/Colombo",
    "iso:country":"LK",
    "name:und_x_variant":[
        "Tunukai",
        "Tunukkai"
    ],
    "wof:name":"Tunukkai",
    "wof:placetype":"locality"
},
  "geometry": {"coordinates":[80.26666999999998,9.15],"type":"Point"}
}