{
  "type": "Feature",
  "properties": {
    "gn:admin1_code":"36.0",
    "gn:asciiname":"Ruwanpura",
    "gn:country_code":"LK",
    "gn:dem":43,
    "gn:feature_class":"P",
    "gn:feature_code":"PPL",
    "gn:name":"Ruwanpura",
    "gn:population":0,
    "gn:timezone":"Asia/Colombo",
    "iso:country":"LK",
    "wof:name":"Ruwanpura",
    "wof:placetype":"locality"
},
  "geometry": {"coordinates":[80.1063,7.0787],"type":"Point"}
}