{
  "type": "Feature",
  "properties": {
    "gn:admin1_code":"35.0",
    "gn:asciiname":"Wattepanguwa",
    "gn:country_code":"LK",
    "gn:dem":994,
    "gn:feature_class":"P",
    "gn:feature_code":"PPL",
    "gn:name":"Wattepanguwa",
    "gn:population":0,
    "gn:timezone":"Asia/Colombo",
    "iso:country":"LK",
    "wof:name":"Wattepanguwa",
    "wof:placetype":"locality"
},
  "geometry": {"coordinates":[81.0467,6.9204],"type":"Point"}
}