{
  "type": "Feature",
  "properties": {
    "gn:admin1_code":"32.0",
    "gn:asciiname":"Elawiligama",
    "gn:country_code":"LK",
    "gn:dem":104,
    "gn:feature_class":"P",
    "gn:feature_code":"PPL",
    "gn:name":"Elawiligama",
    "gn:population":0,
    "gn:timezone":"Asia/Colombo",
    "iso:country":"LK",
    "name:und_x_variant":[
        "Elawitigama"
    ],
    "wof:name":"Elawiligama",
    "wof:placetype":"locality"
},
  "geometry": {"coordinates":[80.2677,7.6283],"type":"Point"}
}