{
  "type": "Feature",
  "properties": {
    "gn:admin1_code":"36.0",
    "gn:asciiname":"Puhambugoda",
    "gn:country_code":"LK",
    "gn:dem":37,
    "gn:feature_class":"P",
    "gn:feature_code":"PPL",
    "gn:name":"Puhambugoda",
    "gn:population":0,
    "gn:timezone":"Asia/Colombo",
    "iso:country":"LK",
    "name:und_x_variant":[
        "Puhabugoda",
        "Puhambugoda",
        "Puhumbugoda"
    ],
    "wof:name":"Puhambugoda",
    "wof:placetype":"locality"
},
  "geometry": {"coordinates":[80.04989999999999,6.5225],"type":"Point"}
}