{
  "type": "Feature",
  "properties": {
    "gn:admin1_code":"29.0",
    "gn:asciiname":"Patingolla",
    "gn:country_code":"LK",
    "gn:dem":667,
    "gn:feature_class":"P",
    "gn:feature_code":"PPL",
    "gn:name":"Patingolla",
    "gn:population":0,
    "gn:timezone":"Asia/Colombo",
    "iso:country":"LK",
    "name:und_x_variant":[
        "Pathingolla",
        "Patingolla"
    ],
    "wof:name":"Patingolla",
    "wof:placetype":"locality"
},
  "geometry": {"coordinates":[80.5667,7.4658],"type":"Point"}
}