{
  "type": "Feature",
  "properties": {
    "gn:admin1_code":"32.0",
    "gn:asciiname":"Kumbukulawa",
    "gn:cc2":"LK",
    "gn:country_code":"LK",
    "gn:dem":134,
    "gn:feature_class":"P",
    "gn:feature_code":"PPL",
    "gn:name":"Kumbukulawa",
    "gn:population":0,
    "gn:timezone":"Asia/Colombo",
    "iso:country":"LK",
    "name:und_x_variant":[
        "Kumbukulewa",
        "Kumbukulawa"
    ],
    "wof:name":"Kumbukulawa",
    "wof:placetype":"locality"
},
  "geometry": {"coordinates":[80.40000000000001,7.83333],"type":"Point"}
}