{
  "type": "Feature",
  "properties": {
    "gn:admin1_code":"34.0",
    "gn:asciiname":"Ihala Bukendayaya",
    "gn:country_code":"LK",
    "gn:dem":121,
    "gn:feature_class":"P",
    "gn:feature_code":"PPL",
    "gn:name":"Ihala Bukendayaya",
    "gn:population":0,
    "gn:timezone":"Asia/Colombo",
    "iso:country":"LK",
    "wof:name":"Ihala Bukendayaya",
    "wof:placetype":"locality"
},
  "geometry": {"coordinates":[80.7109,6.247],"type":"Point"}
}