{
  "type": "Feature",
  "properties": {
    "gn:admin1_code":"29.0",
    "gn:asciiname":"Hawa Eliya East",
    "gn:country_code":"LK",
    "gn:dem":1865,
    "gn:feature_class":"P",
    "gn:feature_code":"PPL",
    "gn:name":"Hawa Eliya East",
    "gn:population":0,
    "gn:timezone":"Asia/Colombo",
    "iso:country":"LK",
    "wof:name":"Hawa Eliya East",
    "wof:placetype":"locality"
},
  "geometry": {"coordinates":[80.7901,6.9664],"type":"Point"}
}