{
  "type": "Feature",
  "properties": {
    "gn:admin1_code":"34.0",
    "gn:asciiname":"Horewela",
    "gn:country_code":"LK",
    "gn:dem":108,
    "gn:feature_class":"P",
    "gn:feature_code":"PPL",
    "gn:name":"Horewela",
    "gn:population":0,
    "gn:timezone":"Asia/Colombo",
    "iso:country":"LK",
    "wof:name":"Horewela",
    "wof:placetype":"locality"
},
  "geometry": {"coordinates":[80.6682,6.1812],"type":"Point"}
}