{
  "type": "Feature",
  "properties": {
    "gn:admin1_code":"35.0",
    "gn:asciiname":"Nugamure",
    "gn:country_code":"LK",
    "gn:dem":269,
    "gn:feature_class":"P",
    "gn:feature_code":"PPL",
    "gn:name":"Nugamure",
    "gn:population":0,
    "gn:timezone":"Asia/Colombo",
    "iso:country":"LK",
    "wof:name":"Nugamure",
    "wof:placetype":"locality"
},
  "geometry": {"coordinates":[81.25369999999999,7.0658],"type":"Point"}
}