{
  "type": "Feature",
  "properties": {
    "gn:admin1_code":"36.0",
    "gn:asciiname":"Kadalawala",
    "gn:country_code":"LK",
    "gn:dem":-9999,
    "gn:feature_class":"P",
    "gn:feature_code":"PPL",
    "gn:name":"Kadalawala",
    "gn:population":0,
    "gn:timezone":"Asia/Colombo",
    "iso:country":"LK",
    "wof:name":"Kadalawala",
    "wof:placetype":"locality"
},
  "geometry": {"coordinates":[79.8514,7.0617],"type":"Point"}
}