{
  "type": "Feature",
  "properties": {
    "gn:admin1_code":"36.0",
    "gn:asciiname":"Welagana",
    "gn:country_code":"LK",
    "gn:dem":31,
    "gn:feature_class":"P",
    "gn:feature_code":"PPL",
    "gn:name":"Welagana",
    "gn:population":0,
    "gn:timezone":"Asia/Colombo",
    "iso:country":"LK",
    "name:und_x_variant":[
        "Welangama",
        "Welagana",
        "Welangana"
    ],
    "wof:name":"Welagana",
    "wof:placetype":"locality"
},
  "geometry": {"coordinates":[80.02249999999999,7.2563],"type":"Point"}
}