{
  "type": "Feature",
  "properties": {
    "gn:admin1_code":"32.0",
    "gn:asciiname":"Moragollagama",
    "gn:country_code":"LK",
    "gn:dem":141,
    "gn:feature_class":"P",
    "gn:feature_code":"PPL",
    "gn:name":"Moragollagama",
    "gn:population":0,
    "gn:timezone":"Asia/Colombo",
    "iso:country":"LK",
    "name:und_x_variant":[
        "Moragollagamuwa",
        "Moragollegama",
        "Moragollagama"
    ],
    "wof:name":"Moragollagama",
    "wof:placetype":"locality"
},
  "geometry": {"coordinates":[80.4208,7.907],"type":"Point"}
}